Workbook

Sheet Summary
A1: May '26 Monthly Summary
B3: Avg Price | C3: Avg Price MoM | D3: Avg Price YoY | E3: Quantity/Mo | F3: Qty by % | G3: Qty MoM | H3: Qty YoY | I3: Revenue/Mo | J3: Revenue by % | K3: Revenue MoM | L3: Revenue YoY
A4: Tablet $800+ | B4: 1513.9489 | C4: -0.014324707 | D4: -0.031861649 | E4: 2297 | F4: 0.0077160805 | G4: -0.007346586 | H4: 0.026821636 | I4: 3477540.7 | J4: 0.10701921 | K4: -0.021566055 | L4: -0.0058945944
A5: Tablet $400-$800 | B5: 545.18097 | C5: 0.001683684 | D5: 0.045315859 | E5: 11903 | F5: 0.039984548 | G5: -0.091651404 | H5: 0.1983288 | I5: 6489289.1 | J5: 0.19970395 | K5: -0.090122032 | L5: 0.2526321
A6: Tablet $400- | B6: 209.91847 | C6: 0.013128357 | D6: 0.029067689 | E6: 26153 | F6: 0.087853136 | G6: -0.035158268 | H6: 0.40668029 | I6: 5489997.8 | J6: 0.16895137 | K6: -0.022491481 | L6: 0.44756924
A7: Total Tablet | B7: 383.04036 | C7: -0.0008675193 | D7: -0.055179676 | E7: 40353 | F7: 0.13555376 | G7: -0.051053523 | H7: 0.31178077 | I7: 15456828 | J7: 0.47567453 | K7: -0.051876752 | L7: 0.23939713
A8: Handheld $75+ | B8: 179.1437 | C8: -0.025501343 | D8: 0.10534129 | E8: 17752 | F8: 0.059632504 | G8: -0.085655421 | H8: 0.19236969 | I8: 3180159 | J8: 0.097867472 | K8: -0.10897244 | L8: 0.31797546
A9: Handheld $75- | B9: 31.387422 | C9: 0.018806128 | D9: 0.0093193017 | E9: 101308 | F9: 0.34031375 | G9: -0.033910589 | H9: 0.0021961498 | I9: 3179796.9 | J9: 0.097856328 | K9: -0.015742188 | L9: 0.011535918
A10: Total Handheld | B10: 53.418074 | C10: -0.023677538 | D10: 0.11494079 | E10: 119060 | F10: 0.39994625 | G10: -0.041994223 | H10: 0.026609412 | I10: 6359955.9 | J10: 0.1957238 | K10: -0.064677441 | L10: 0.14460871
A11: Total Dongle | B11: 87.920125 | C11: 0.03771862 | D11: 0.191942 | E11: 67679 | F11: 0.22734724 | G11: 0.17479908 | H11: -0.0047352245 | I11: 5950346.1 | J11: 0.18311831 | K11: 0.21911088 | L11: 0.18629788
A12: Total Other Tools | B12: 69.21433 | C12: -0.049746839 | D12: 0.045786567 | E12: 66495 | F12: 0.22336995 | G12: 0.08628886 | H12: 0.44322177 | I12: 4602406.9 | J12: 0.14163629 | K12: 0.032249423 | L12: 0.50930194
A13: Total | B13: 110.25535 | C13: -0.029286984 | D13: 0.10205279 | E13: 293587 | F13: 0.98621721 | G13: 0.027875711 | H13: 0.12566955 | I13: 32369537 | J13: 0.99615293 | K13: -0.0022276688 | L13: 0.24054726
A45: May '26 Monthly Summary - Revenue
A46: Brand | B46: # of Listings | C46: Monthly Rev | D46: Estimated 12mo Revenue | E46: Monthly Units | F46: Monthly Rev Market Share % | G46: Price Per Unit | H46: Total Reviews | I46: Avg Rating
A47: autel | B47: 547 | C47: 4990834 | D47: 64472355 | E47: 18656 | F47: 0.1536 | G47: 267.52 | H47: 132487 | I47: 4.6
A48: ancel | B48: 79 | C48: 2748377 | D48: 33286994 | E48: 40920 | F48: 0.0846 | G48: 67.16 | H48: 130538 | I48: 4.2
A49: topdon | B49: 51 | C49: 2698187.6 | D49: 35169754 | E49: 11224 | F49: 0.083 | G49: 240.39 | H49: 26138 | I49: 4.3
A50: launch | B50: 286 | C50: 2569052.5 | D50: 32114238 | E50: 7779 | F50: 0.0791 | G50: 330.25 | H50: 73485 | I50: 4.2
A51: foxwell | B51: 49 | C51: 2004459.1 | D51: 21848414 | E51: 14808 | F51: 0.0617 | G51: 135.36 | H51: 72130 | I51: 4.3
A52: innova | B52: 42 | C52: 1793626.5 | D52: 17823864 | E52: 11876 | F52: 0.0552 | G52: 151.03 | H52: 32448 | I52: 4.3
A53: obdlink | B53: 4 | C53: 1538190.5 | D53: 15013735 | E53: 16012 | F53: 0.0473 | G53: 96.06 | H53: 37252 | I53: 4.6
A54: xtool | B54: 69 | C54: 1537851.7 | D54: 17241589 | E54: 6065 | F54: 0.0473 | G54: 253.56 | H54: 12032 | I54: 4.4
A55: bluedriver | B55: 3 | C55: 1093129.2 | D55: 12240545 | E55: 10265 | F55: 0.0336 | G55: 106.49 | H55: 124836 | I55: 4.5
A56: thinkcar | B56: 25 | C56: 839971.06 | D56: 9681257.5 | E56: 3250 | F56: 0.0258 | G56: 258.45 | H56: 13856 | I56: 4.3
A57: diesel laptops | B57: 21 | C57: 771053.38 | D57: 7722648.9 | E57: 1141 | F57: 0.0237 | G57: 675.77 | H57: 700 | I57: 4.1
A58: generic | B58: 197 | C58: 718749.55 | D58: 4782532.8 | E58: 3130 | F58: 0.0221 | G58: 229.63 | H58: 1392 | I58: 4
... A71: z automotive | B71: 14 | C71: 228306.07 | D71: 2929076.6 | E71: 854 | F71: 0.007 | G71: 267.34 | H71: 1932 | I71: 4.4
A73: Total | B73: =SUM(B46:B71) | C73: =SUM(C47:C71) | D73: =SUM(D47:D71) | E73: =SUM(E47:E71) | F73: =SUM(F47:F71) | G73: =AVERAGE(G47:G71) | H73: =SUM(H47:H71) | I73: =AVERAGE(I47:I71)
A76: May '26 Summary - Units
A77: Brand | B77: # of Listings | C77: Monthly Rev | D77: Estimated 12mo Units | E77: Monthly Units | F77: Monthly Unit Market Share % | G77: Price Per Unit | H77: Reviews | I77: Avg Rating
A78: ancel | B78: 79 | C78: 2748377 | D78: 583145.54 | E78: 40920 | F78: 0.1375 | G78: 67.16 | H78: 130538 | I78: 4.2
A79: autel | B79: 547 | C79: 4990834 | D79: 224601.23 | E79: 18656 | F79: 0.0627 | G79: 267.52 | H79: 132487 | I79: 4.6
A80: obdlink | B80: 4 | C80: 1538190.5 | D80: 155118.46 | E80: 16012 | F80: 0.0538 | G80: 96.06 | H80: 37252 | I80: 4.6
A81: foxwell | B81: 49 | C81: 2004459.1 | D81: 171792 | E81: 14808 | F81: 0.0497 | G81: 135.36 | H81: 72130 | I81: 4.3
A82: motopower | B82: 7 | C82: 307614.7 | D82: 127448.31 | E82: 12057 | F82: 0.0405 | G82: 25.51 | H82: 59491 | I82: 4.5
A83: innova | B83: 42 | C83: 1793626.5 | D83: 96864.923 | E83: 11876 | F83: 0.0399 | G83: 151.03 | H83: 32448 | I83: 4.3
A84: topdon | B84: 51 | C84: 2698187.6 | D84: 148226.77 | E84: 11224 | F84: 0.0377 | G84: 240.39 | H84: 26138 | I84: 4.3
A85: bluedriver | B85: 3 | C85: 1093129.2 | D85: 143465.54 | E85: 10265 | F85: 0.0345 | G85: 106.49 | H85: 124836 | I85: 4.5
A86: veepeak | B86: 4 | C86: 290264.25 | D86: 87092.308 | E86: 9029 | F86: 0.0303 | G86: 32.15 | H86: 53304 | I86: 4.5
A87: launch | B87: 286 | C87: 2569052.5 | D87: 104687.08 | E87: 7779 | F87: 0.0261 | G87: 330.25 | H87: 73485 | I87: 4.2
A88: vgate | B88: 35 | C88: 297379.77 | D88: 73462.154 | E88: 7393 | F88: 0.0248 | G88: 40.22 | H88: 22327 | I88: 4.4
A89: vdiagtool | B89: 10 | C89: 204043.47 | D89: 58968.923 | E89: 7156 | F89: 0.024 | G89: 28.51 | H89: 4382 | I89: 4.5
... A102: parannic | B102: 77 | C102: 52286.71 | D102: 19586.769 | E102: 1803 | F102: 0.0061 | G102: 29 | H102: 1871 | I102: 4.1
A104: Total | B104: =SUM(B78:B102) | C104: =SUM(C78:C102) | D104: =SUM(D78:D102) | E104: =SUM(E78:E102) | F104: =SUM(F78:F102) | G104: =AVERAGE(G78:G102) | H104: =SUM(H78:H102) | I104: =AVERAGE(I78:I102)

Sheet Top 50
A1: Top 50 Products - May '26 ONLY
B3: Avg Price | C3: Avg Price MoM | D3: Avg Price YoY | E3: Quantity/Mo | F3: Qty by % | G3: Qty MoM | H3: Qty YoY | I3: Revenue/Mo | J3: Revenue by % | L3: Revenue MoM | M3: Revenue YoY
A4: Total Tablet | B4: 401.6994 | C4: 0.049128055 | D4: 0.04553251 | E4: 15151 | F4: 0.13626103 | G4: -0.2000528 | H4: 0.13320868 | I4: 6086147.6 | J4: 0.43419987 | L4: -0.16075295 | M4: 0.18480651
A5: Total Handheld | B5: 54.932093 | C5: -0.047394216 | D5: 0.24575025 | E5: 53243 | F5: 0.47884271 | G5: -0.072162972 | H5: -0.075289173 | I5: 2924749.4 | J5: 0.2086584 | L5: -0.11613708 | M5: 0.15195875
A6: Total Dongle | B6: 110.19434 | C6: -0.023288911 | D6: 0.31051401 | E6: 34856 | F6: 0.31347861 | G6: 0.38840868 | H6: -0.083845871 | I6: 3840934 | J6: 0.27402113 | L6: 0.35607416 | M6: 0.20063282
A7: Total Other Tools | B7: 146.71895 | C7: -0.049776608 | D7: -0.038733798 | E7: 7941 | F7: 0.071417651 | G7: 0.1337807 | H7: 0.36045914 | I7: 1165095.2 | J7: 0.08312059 | L7: 0.077344939 | M7: 0.30776339
A8: Total | B8: 126.0617 | C8: -0.055652688 | D8: 0.23033175 | E8: 111191 | F8: 1 | G8: 0.025435061 | H8: -0.031698757 | I8: 14016926 | J8: 1 | L8: -0.031633157 | M8: 0.19133176
A40: Rank By Monthly Revenue - May '26 ONLY
A41: Ranking | B41: ASIN | C41: Product Name | D41: Brand | E41: Type | F41: Price | G41: Est. Monthly Retail Rev | H41: Est. Monthly Units Sold | I41: # of Reviews | J41: Avg. Rating | K41: Column2 | L41: Link
A42: 1 | B42: B07Z481NJM | C42: Innova 5610 OBD2 Bidirectional Scan Tool - Understand Your Vehicle, Pinpoint What's Wrong, and Complete Your Repairs with Less Headache, Updates Included, US-Based Technical Support | D42: innova | E42: Handheld | F42: 313.9311 | G42: 1084945.9 | H42: 3456 | I42: 3548 | J42: 4.4 | K42: https://amazon.com/dp/B07Z481NJM | L42: =IF(K42="","",HYPERLINK(K42,K42))
A43: 2 | B43: B07JFRFJG6 | C43: OBDLink MX+ OBD2 Bluetooth Scanner for iPhone, Android, and Windows | D43: obdlink | E43: Dongle | F43: 139.93305 | G43: 747242.47 | H43: 5340 | I43: 15235 | J43: 4.6 | K43: https://amazon.com/dp/B07JFRFJG6 | L43: =IF(K43="","",HYPERLINK(K43,K43))
A44: 3 | B44: B01G5EA74I | C44: ANCEL AD310 Classic Enhanced Universal OBD II Scanner Car Engine Fault Code Reader CAN Diagnostic Scan Tool, Read and Clear Error Codes for 1996 or Newer OBD2 Protocol Vehicle (Black) | D44: ancel | E44: Handheld | F44: 27.758715 | G44: 668152.27 | H44: 24070 | I44: 64423 | J44: 4.6 | K44: https://amazon.com/dp/B01G5EA74I | L44: =IF(K44="","",HYPERLINK(K44,K44))
A45: 4 | B45: B0GL9RL3XS | C45: BlueDriver Pro Next Gen OBD2 Scanner – No Subscription, Bluetooth Car Code Reader for iPhone & Android – Diagnose 8000+ Issues, ABS SRS TPMS, Repair Reports, Vehicles 1996+ | D45: bluedriver | E45: Dongle | F45: 97.454834 | G45: 634430.97 | H45: 6510 | I45: 62416 | J45: 4.5 | K45: https://amazon.com/dp/B0GL9RL3XS | L45: =IF(K45="","",HYPERLINK(K45,K45))
A46: 5 | B46: B098PYB8XG | C46: Autel Scanner MaxiCOM MK900BT, 2026 MK900-BT V2.0 Bidirectional Diagnostic Tool, 8in Up of MK900 MX900 MK808S MK808BT MX808S MK808Z, 3000+ Active Tests, 40+ Service, CAN-FD&DOIP, All System, FCA 11 OS | D46: autel | E46: Tablet | F46: 658.58882 | G46: 503161.86 | H46: 764 | I46: 723 | J46: 4.6 | K46: https://amazon.com/dp/B098PYB8XG | L46: =IF(K46="","",HYPERLINK(K46,K46))
A47: 6 | B47: B081VQVD3F | C47: OBDLink EX FORScan OBD Adapter | D47: obdlink | E47: Cable/Adapter | F47: 69.944527 | G47: 475692.73 | H47: 6801 | I47: 10006 | J47: 4.8 | K47: https://amazon.com/dp/B081VQVD3F | L47: =IF(K47="","",HYPERLINK(K47,K47))
A48: 7 | B48: B00652G4TS | C48: BlueDriver Bluetooth Pro OBDII Scan Tool for iPhone & Android - No Subscription Fee - OBD2 Car Scanner and Code Reader - Diagnose Check Engine, ABS, SRS, Airbag & 7000+ Issues on Vehicles 1996+ | D48: bluedriver | E48: Dongle | F48: 122.15666 | G48: 458698.26 | H48: 3755 | I48: 62420 | J48: 4.5 | K48: https://amazon.com/dp/B00652G4TS | L48: =IF(K48="","",HYPERLINK(K48,K48))
A49: 8 | B49: B0BPYPNDVP | C49: Diesel Laptops Nexiq USB Link 3 Wired Edition with Repair Information & Diagnostic Software | D49: diesel laptops | E49: VCI | F49: 749.55194 | G49: 454978.03 | H49: 607 | I49: 257 | J49: 4.5 | K49: https://amazon.com/dp/B0BPYPNDVP | L49: =IF(K49="","",HYPERLINK(K49,K49))
A50: 9 | B50: B00UJV3E12 | C50: FOXWELL NT301 OBD2 Scanner Live Data Professional Mechanic OBDII Diagnostic Code Reader Tool for Check Engine Light | D50: foxwell | E50: Handheld | F50: 65.640497 | G50: 390823.52 | H50: 5954 | I50: 29789 | J50: 4.5 | K50: https://amazon.com/dp/B00UJV3E12 | L50: =IF(K50="","",HYPERLINK(K50,K50))
A51: 10 | B51: B0C33Y285Y | C51: TOPDON Bidirectional Scan Tool, 2026 New ArtiDiag900 Lite Automotive Diagnostic Tool for Full System, Scanner for Car with Active Test, 8 Reset, Wireless OBD2 Scanner Diagnostic Tool for All Vehicles | D51: topdon | E51: Tablet | F51: 315.0536 | G51: 384680.45 | H51: 1221 | I51: 1273 | J51: 4.2 | K51: https://amazon.com/dp/B0C33Y285Y | L51: =IF(K51="","",HYPERLINK(K51,K51))
A52: 11 | B52: B0DV2N2FND | C52: BLCKTEC 460T OBD2 Scanner Car Code Reader Engine ABS SRS Transmission Diagnostic Tool, 12 Reset Services, Oil/TPMS/EPB/BMS/SAS/DPF/Throttle Reset, ABS Bleeding, Battery Test, Auto VIN, Free Update | D52: blcktec | E52: Tablet | F52: 196.13548 | G52: 356182.04 | H52: 1816 | I52: 656 | J52: 4.4 | K52: https://amazon.com/dp/B0DV2N2FND | L52: =IF(K52="","",HYPERLINK(K52,K52))
A53: 12 | B53: B08PFJMTY3 | C53: FOXWELL Car Scanner NT604 Elite OBD2 Scanner ABS SRS Transmission, Check Engine Code Reader for Cars and Trucks, Diagnostic Scan Tool with SRS Airbag, Automotive Diagnostic Tool with Live Data | D53: foxwell | E53: Tablet | F53: 153.79738 | G53: 353118.78 | H53: 2296 | I53: 4914 | J53: 4.4 | K53: https://amazon.com/dp/B08PFJMTY3 | L53: =IF(K53="","",HYPERLINK(K53,K53))
... A91: 50 | B91: B0DZC1M7MZ | C91: Autel MaxiSys Ultra S2 Scanner, 2026 Top Intelligen Scan Diagnostic with AI, 6-in-1 VCMI2, Up of MSUltra MS919, Topology 3.0, Multi-Point DVI, Motor Truspeed Repair, EV Test, 48+ Service, ECU Program | D91: autel | E91: Tablet | F91: 5788.9904 | G91: 133146.78 | H91: 23 | I91: 22 | J91: 4.8 | K91: https://amazon.com/dp/B0DZC1M7MZ | L91: =IF(K91="","",HYPERLINK(K91,K91))
A94: Rank By Monthly Units - May '26 ONLY
A95: Ranking | B95: ASIN | C95: Product Name | D95: Brand | E95: Type | F95: Price | G95: Est. Monthly Retail Rev | H95: Est. Monthly Units Sold | I95: # of Reviews | J95: Avg. Rating | K95: Column2 | L95: Link
A96: 1 | B96: B01G5EA74I | C96: ANCEL AD310 Classic Enhanced Universal OBD II Scanner Car Engine Fault Code Reader CAN Diagnostic Scan Tool, Read and Clear Error Codes for 1996 or Newer OBD2 Protocol Vehicle (Black) | D96: ancel | E96: Handheld | F96: 27.758715 | G96: 668152.27 | H96: 24070 | I96: 64423 | J96: 4.6 | K96: https://amazon.com/dp/B01G5EA74I | L96: =IF(K96="","",HYPERLINK(K96,K96))
A97: 2 | B97: B07Z3HB7DR | C97: MOTOPOWER MP69033 Car OBD2 Scanner Code Reader Engine Fault Scanner CAN Diagnostic Scan Tool for All OBD II Protocol Cars Since 1996, Yellow | D97: motopower | E97: Handheld | F97: 24.501724 | G97: 264030.58 | H97: 10776 | I97: 51034 | J97: 4.6 | K97: https://amazon.com/dp/B07Z3HB7DR | L97: =IF(K97="","",HYPERLINK(K97,K97))
A98: 3 | B98: B081VQVD3F | C98: OBDLink EX FORScan OBD Adapter | D98: obdlink | E98: Cable/Adapter | F98: 69.944527 | G98: 475692.73 | H98: 6801 | I98: 10006 | J98: 4.8 | K98: https://amazon.com/dp/B081VQVD3F | L98: =IF(K98="","",HYPERLINK(K98,K98))
A99: 4 | B99: B071FSNL73 | C99: ANCEL AD410 Enhanced OBD2 Scanner, Vehicle Code Reader for Check Engine Light, Automotive OBD II Scanner Fault Diagnosis, OBDII Scan Tool for All OBDII Cars 1996+, Black/Yellow | D99: ancel | E99: Handheld | F99: 45.525505 | G99: 301515.42 | H99: 6623 | I99: 15175 | J99: 4.5 | K99: https://amazon.com/dp/B071FSNL73 | L99: =IF(K99="","",HYPERLINK(K99,K99))
A100: 5 | B100: B0BY1TS725 | C100: VDIAGTOOL VD10 OBD2 Scanner Code Reader Car Diagnostic Tool Engine Fault Code Reader for Turn Off CEL with Freeze Frame/I/M Readiness for All OBDII Protocol Cars, OBD2 Scanner Diagnostic Tool | D100: vdiagtool | E100: Handheld | F100: 19.980454 | G100: 131251.6 | H100: 6569 | I100: 2686 | J100: 4.6 | K100: https://amazon.com/dp/B0BY1TS725 | L100: =IF(K100="","",HYPERLINK(K100,K100))
A101: 6 | B101: B0GL9RL3XS | C101: BlueDriver Pro Next Gen OBD2 Scanner – No Subscription, Bluetooth Car Code Reader for iPhone & Android – Diagnose 8000+ Issues, ABS SRS TPMS, Repair Reports, Vehicles 1996+ | D101: bluedriver | E101: Dongle | F101: 97.454834 | G101: 634430.97 | H101: 6510 | I101: 62416 | J101: 4.5 | K101: https://amazon.com/dp/B0GL9RL3XS | L101: =IF(K101="","",HYPERLINK(K101,K101))
A102: 7 | B102: B00UJV3E12 | C102: FOXWELL NT301 OBD2 Scanner Live Data Professional Mechanic OBDII Diagnostic Code Reader Tool for Check Engine Light | D102: foxwell | E102: Handheld | F102: 65.640497 | G102: 390823.52 | H102: 5954 | I102: 29789 | J102: 4.5 | K102: https://amazon.com/dp/B00UJV3E12 | L102: =IF(K102="","",HYPERLINK(K102,K102))
A103: 8 | B103: B073XKQQQW | C103: Veepeak OBDCheck BLE Bluetooth OBD II Scanner for iOS & Android, Car Wireless Check Engine Light Code Reader Diagnostic Tool | D103: veepeak | E103: Dongle | F103: 31.298403 | G103: 180842.17 | H103: 5778 | I103: 23568 | J103: 4.5 | K103: https://amazon.com/dp/B073XKQQQW | L103: =IF(K103="","",HYPERLINK(K103,K103))
A104: 9 | B104: B07JFRFJG6 | C104: OBDLink MX+ OBD2 Bluetooth Scanner for iPhone, Android, and Windows | D104: obdlink | E104: Dongle | F104: 139.93305 | G104: 747242.47 | H104: 5340 | I104: 15235 | J104: 4.6 | K104: https://amazon.com/dp/B07JFRFJG6 | L104: =IF(K104="","",HYPERLINK(K104,K104))
A105: 10 | B105: B013RIQMEO | C105: FIXD Bluetooth OBD2 Scanner for iPhone & Android - Diagnostic Scan Tool for Repairs and Car Buying - Check Engine Code Reader & Enhanced Codes - (1 Pack w/Free 14-Day FIXD Premium Bundle) | D105: fixd | E105: Dongle | F105: 39.988087 | G105: 150915.04 | H105: 3774 | I105: 35178 | J105: 4.2 | K105: https://amazon.com/dp/B013RIQMEO | L105: =IF(K105="","",HYPERLINK(K105,K105))
A106: 11 | B106: B00652G4TS | C106: BlueDriver Bluetooth Pro OBDII Scan Tool for iPhone & Android - No Subscription Fee - OBD2 Car Scanner and Code Reader - Diagnose Check Engine, ABS, SRS, Airbag & 7000+ Issues on Vehicles 1996+ | D106: bluedriver | E106: Dongle | F106: 122.15666 | G106: 458698.26 | H106: 3755 | I106: 62420 | J106: 4.5 | K106: https://amazon.com/dp/B00652G4TS | L106: =IF(K106="","",HYPERLINK(K106,K106))
A107: 12 | B107: B07Z481NJM | C107: Innova 5610 OBD2 Bidirectional Scan Tool - Understand Your Vehicle, Pinpoint What's Wrong, and Complete Your Repairs with Less Headache, Updates Included, US-Based Technical Support | D107: innova | E107: Handheld | F107: 313.9311 | G107: 1084945.9 | H107: 3456 | I107: 3548 | J107: 4.4 | K107: https://amazon.com/dp/B07Z481NJM | L107: =IF(K107="","",HYPERLINK(K107,K107))
... A125: 30 | B125: B09KZTYD18 | C125: OBD2 Scanner TOPDON AD600S Scan Tool, Code Reader, Diagnostics Scanner for ABS/SRS/AT/Engine, 9 Reset Services, Oil/Brake/BMS/SAS/DPF/TPMS/ETS Reset/ABS Bleeding/Injector Coding, Free Lifetime Upgrade | D125: topdon | E125: Tablet | F125: 201.80111 | G125: 222990.23 | H125: 1105 | I125: 1864 | J125: 4.4 | K125: https://amazon.com/dp/B09KZTYD18 | L125: =IF(K125="","",HYPERLINK(K125,K125))
A126: 31 | B126: B000EVYGV4 | C126: Innova 3568 Digital Timing Light | D126: innova | E126: Other | F126: 77.445181 | G126: 83253.57 | H126: 1075 | K126: https://amazon.com/dp/B000EVYGV4 | L126: =IF(K126="","",HYPERLINK(K126,K126))
A127: 32 | B127: B0DPHCBL89 | C127: 12+8 Pin Connector to OBD2 Adapter, Secutiry Gateway Bypass Cable, 12+8 Cable for Chrysler SGW Equipped FCA Vehicles for Diagnostic, Fit for Scanners MK808 MK808S MX808 MS906 Pro MS908S | D127: ecocstm | E127: Cable/Adapter | F127: 12.980797 | G127: 13850.51 | H127: 1067 | I127: 148 | J127: 4.6 | K127: https://amazon.com/dp/B0DPHCBL89 | L127: =IF(K127="","",HYPERLINK(K127,K127))
A128: 33 | B128: B0DFY6CCSV | C128: pinflaw 2 PCS Automobile Power Upgrade Fuel Saving, OBD2 ECOOBD2 Automotive Plug and Driver Single Plate, Automotive Energy Saver Accessories, Universal for Most Cars (Green) | D128: pinflaw | E128: Other | F128: 13.258625 | G128: 14080.66 | H128: 1062 | I128: 429 | J128: 3.6 | K128: https://amazon.com/dp/B0DFY6CCSV | L128: =IF(K128="","",HYPERLINK(K128,K128))
A129: 34 | B129: B0BX3K8VGJ | C129: ANCEL AD410 PRO OBD2 Scanner and Battery Tester, 2-in-1 Car Diagnostic Tool, Check Engine Light, EVAP Test, Live Data, 12V Battery Analyzer with Cranking & Charging System Test for Car Motorcycle | D129: ancel | E129: Handheld | F129: 63.080853 | G129: 65793.33 | H129: 1043 | I129: 4132 | J129: 4.6 | K129: https://amazon.com/dp/B0BX3K8VGJ | L129: =IF(K129="","",HYPERLINK(K129,K129))
A130: 35 | B130: B0GL2FW97F | C130: 2-in-1 OBD2 Scanner with Battery Tester: 1S Read & Clear Check Engine Codes + Test Battery in 3 Mins - DIY Car Diagnostic Tool with Cold Cranking Amps for Pre-Trip Safety on 1996+ Vehicles | D130: yakry | E130: Handheld | F130: 48.721093 | G130: 50377.61 | H130: 1034 | I130: 58 | J130: 4.6 | K130: https://amazon.com/dp/B0GL2FW97F | L130: =IF(K130="","",HYPERLINK(K130,K130))
A131: 36 | B131: B08JGK8PPM | C131: 2-in-1 FOXWELL NT301 Plus OBD2 Scanner Battery Tester for Cars Trucks, Check Engine Light & Battery Health Test, Code Reader Diagnostic Tool with Live Data, Without a Mechanic, Works on 1996+ Vehicle | D131: foxwell | E131: Handheld | F131: 92.877052 | G131: 93898.7 | H131: 1011 | I131: 2653 | J131: 4.5 | K131: https://amazon.com/dp/B08JGK8PPM | L131: =IF(K131="","",HYPERLINK(K131,K131))
A132: 37 | B132: B011NSX27A | C132: Veepeak Mini Bluetooth OBD2 Scanner for Android ONLY (NOT for iOS) – Car Wireless Check Engine Light Code Reader & Diagnostic Tool | D132: veepeak | E132: Dongle | F132: 14.975142 | G132: 14795.44 | H132: 988 | I132: 18650 | J132: 4.4 | K132: https://amazon.com/dp/B011NSX27A | L132: =IF(K132="","",HYPERLINK(K132,K132))
A133: 38 | B133: B08XK3DJ42 | C133: TOPDON AD500 OBD2 Scanner, Oil SAS Throttle TPMS BMS EPB Reset, Engine ABS SRS Transmission, Diagnostic Scan Tool, AutoVIN, Car Check Engine Code Reader with Battery Test, Lifetime Wi-Fi Free Update | D133: topdon | E133: Tablet | F133: 159.11793 | G133: 150366.44 | H133: 945 | I133: 1766 | J133: 4.4 | K133: https://amazon.com/dp/B08XK3DJ42 | L133: =IF(K133="","",HYPERLINK(K133,K133))
A134: 39 | B134: B0DHQSQYTR | C134: MOTOPOWER MP69033 Pro OBD2 Scanner Code Reader Check Engine Fault Light Diagnostic Scan Tool with Battery Tester | D134: motopower | E134: Handheld | F134: 32.819892 | G134: 30424.04 | H134: 927 | I134: 938 | J134: 4.5 | K134: https://amazon.com/dp/B0DHQSQYTR | L134: =IF(K134="","",HYPERLINK(K134,K134))
A135: 40 | B135: B071L8W7Q7 | C135: bbfly-B6 OBD2 Splitter 16 Pin OBD II Splitter Extension 1x Male and 2X Female Extension Cable Adapter (1FT/30CM) (1Pack) | D135: bbfly | E135: Cable/Adapter | F135: 10.886439 | G135: 10059.07 | H135: 924 | I135: 2121 | J135: 4.6 | K135: https://amazon.com/dp/B071L8W7Q7 | L135: =IF(K135="","",HYPERLINK(K135,K135))
A136: 41 | B136: B07BS7PDC2 | C136: ANCEL VD500 OBD2 Scanner Diagnostic Tool for Volkswagen VW Audi Skoda Seat Diagnosis Check Engine Light EPB ABS SRS Code Reader Oil Throttle Position Adaption Brake Pad Reset | D136: ancel | E136: Handheld | F136: 63.380582 | G136: 56662.24 | H136: 894 | I136: 6359 | J136: 4.5 | K136: https://amazon.com/dp/B07BS7PDC2 | L136: =IF(K136="","",HYPERLINK(K136,K136))
A137: 42 | B137: B0711LGRGQ | C137: bbfly-A9 OBD II OBD2 16 Pin Splitter Extension 1x Male and 2X Female Extension Cable Adapter (2FT/60CM) | D137: bbfly | E137: Cable/Adapter | F137: 9.8914029 | G137: 8813.24 | H137: 891 | I137: 3093 | J137: 4.5 | K137: https://amazon.com/dp/B0711LGRGQ | L137: =IF(K137="","",HYPERLINK(K137,K137))
A138: 43 | B138: B0FZ26RBDC | C138: HPT MPVI4 Diagnostic Code Reader Scanner and Tool | D138: generic | E138: Dongle | F138: 394.73583 | G138: 345393.85 | H138: 875 | I138: 153 | J138: 4.9 | K138: https://amazon.com/dp/B0FZ26RBDC | L138: =IF(K138="","",HYPERLINK(K138,K138))
... A145: 50 | B145: B0G6XWFLT1 | C145: OBD2 Scanner with Battery Tester - Vehicle Code Reader for Check Engine Light, Plug and Play, Car Scanner Diagnostic Tool for All OBDII Vehicles After 1996 | D145: hipepic | E145: Handheld | F145: 17.765565 | G145: 14301.28 | H145: 805 | I145: 48 | J145: 4.7 | K145: https://amazon.com/dp/B0G6XWFLT1 | L145: =IF(K145="","",HYPERLINK(K145,K145))

Sheet Tablet Total
A1: Tablet Monthly Summary
A3: Tablet Overall
B4: Avg Price | C4: Avg Price MoM | D4: Avg Price YoY | E4: Quantity/Mo | F4: Qty by % | G4: Qty MoM | H4: Qty YoY | I4: Revenue/Mo | J4: Revenue by % | L4: Revenue MoM | M4: Revenue YoY
A5: autel | B5: 758.21987 | C5: 0.036543181 | D5: -0.021240031 | E5: 5591 | F5: 0.13855228 | G5: -0.15760133 | H5: 0.049755914 | I5: 4239207.3 | J5: 0.27426115 | L5: -0.1268174 | M5: 0.027459066
A6: launch | B6: 439.35212 | C6: 0.081884841 | D6: 0.14597188 | E6: 5442 | F6: 0.13485986 | G6: -0.096163428 | H6: -0.20554745 | I6: 2390954.2 | J6: 0.15468596 | L6: -0.022152914 | M6: -0.089579713
A7: topdon | B7: 327.91994 | C7: -0.025270915 | D7: 0.031862684 | E7: 6761 | F7: 0.1675464 | G7: -0.18971716 | H7: 0.13211654 | I7: 2217066.7 | J7: 0.14343608 | L7: -0.21019375 | M7: 0.16818882
A8: xtool | B8: 333.66305 | C8: -0.010373718 | D8: -0.12982713 | E8: 3840 | F8: 0.095160211 | G8: 0.016410799 | H8: 0.69014085 | I8: 1281266.1 | J8: 0.082893213 | L8: 0.0058668404 | M8: 0.47071471
A9: ancel | B9: 480.03556 | C9: 0.03865599 | D9: 0.42560697 | E9: 2480 | F9: 0.061457636 | G9: 0.17036338 | H9: 0.34929271 | I9: 1190488.2 | J9: 0.077020215 | L9: 0.21560493 | M9: 0.92356109
A10: blcktec | B10: 196.13548 | C10: 0.034452976 | D10: 0.059213373 | E10: 1816 | F10: 0.04500285 | G10: 0.135 | H10: 2.5193798 | I10: 356182.04 | J10: 0.02304367 | L10: 0.17410413 | M10: 2.7277742
A11: innova | B11: 159.12765 | C11: -0.0077981129 | D11: -0.22299144 | E11: 557 | F11: 0.013803187 | G11: -0.11305732 | H11: 3.2846154 | I11: 88634.1 | J11: 0.0057343009 | L11: -0.1199738 | M11: 2.3291828
A12: Other | B12: 266.33701 | C12: 0.0084489572 | D12: -0.052569202 | E12: 13866 | F12: 0.34361757 | G12: 0.035007838 | H12: 0.76457114 | I12: 3693029 | J12: 0.23892542 | L12: 0.043752574 | M12: 0.67180904
A13: Total Tablet | B13: 383.04036 | C13: -0.0008675193 | D13: -0.055179676 | E13: 40353 | F13: 1 | G13: -0.051053523 | H13: 0.31178077 | I13: 15456828 | J13: 1 | L13: -0.051876752 | M13: 0.23939713
A45: Rank By Monthly Revenue - May '26 ONLY
A46: Ranking | B46: ASIN | C46: Product Name | D46: Brand | E46: Type | F46: Price | G46: Est. Monthly Retail Rev | H46: Est. Monthly Units Sold | I46: # of Reviews | J46: Avg. Rating | K46: Column2 | L46: Link
A47: 1 | B47: B098PYB8XG | C47: Autel Scanner MaxiCOM MK900BT, 2026 MK900-BT V2.0 Bidirectional Diagnostic Tool, 8in Up of MK900 MX900 MK808S MK808BT MX808S MK808Z, 3000+ Active Tests, 40+ Service, CAN-FD&DOIP, All System, FCA 11 OS | D47: autel | E47: Tablet | F47: 658.58882 | G47: 503161.86 | H47: 764 | I47: 723 | J47: 4.6 | K47: https://amazon.com/dp/B098PYB8XG | L47: =IF(K47="","",HYPERLINK(K47,K47))
A48: 2 | B48: B0C33Y285Y | C48: TOPDON Bidirectional Scan Tool, 2026 New ArtiDiag900 Lite Automotive Diagnostic Tool for Full System, Scanner for Car with Active Test, 8 Reset, Wireless OBD2 Scanner Diagnostic Tool for All Vehicles | D48: topdon | E48: Tablet | F48: 315.0536 | G48: 384680.45 | H48: 1221 | I48: 1273 | J48: 4.2 | K48: https://amazon.com/dp/B0C33Y285Y | L48: =IF(K48="","",HYPERLINK(K48,K48))
A49: 3 | B49: B0DV2N2FND | C49: BLCKTEC 460T OBD2 Scanner Car Code Reader Engine ABS SRS Transmission Diagnostic Tool, 12 Reset Services, Oil/TPMS/EPB/BMS/SAS/DPF/Throttle Reset, ABS Bleeding, Battery Test, Auto VIN, Free Update | D49: blcktec | E49: Tablet | F49: 196.13548 | G49: 356182.04 | H49: 1816 | I49: 656 | J49: 4.4 | K49: https://amazon.com/dp/B0DV2N2FND | L49: =IF(K49="","",HYPERLINK(K49,K49))
A50: 4 | B50: B08PFJMTY3 | C50: FOXWELL Car Scanner NT604 Elite OBD2 Scanner ABS SRS Transmission, Check Engine Code Reader for Cars and Trucks, Diagnostic Scan Tool with SRS Airbag, Automotive Diagnostic Tool with Live Data | D50: foxwell | E50: Tablet | F50: 153.79738 | G50: 353118.78 | H50: 2296 | I50: 4914 | J50: 4.4 | K50: https://amazon.com/dp/B08PFJMTY3 | L50: =IF(K50="","",HYPERLINK(K50,K50))
A51: 5 | B51: B0DTK24XKB | C51: MUCAR 892BT AI-Assisted Bidirectional Scan Tool, Full System OBD2 Scanner, Bi-Directional OBD2 Scanner Diagnostic Tool,ECU Coding, 35 Services, FCA Autoauth, CANFD and DOIP, Free Lifetime Upgrade | D51: mucar | E51: Tablet | F51: 639.61776 | G51: 345393.59 | H51: 540 | I51: 421 | J51: 4.3 | K51: https://amazon.com/dp/B0DTK24XKB | L51: =IF(K51="","",HYPERLINK(K51,K51))
A52: 6 | B52: B0BZ82WQ4Q | C52: ANCEL X7HD 10.1'' Heavy Duty Truck Scanner, Semi Trucks Full System Diagnostic Tool, Bidirectional Diesel Scan Tool with DPF, ECU Coding, 40+ Reset for Cummins, Detroit, Caterpillar, Volvo, Paccar etc | D52: ancel | E52: Tablet | F52: 765.33645 | G52: 267102.42 | H52: 349 | I52: 796 | J52: 3.7 | K52: https://amazon.com/dp/B0BZ82WQ4Q | L52: =IF(K52="","",HYPERLINK(K52,K52))
A53: 7 | B53: B0DCFRF2TF | C53: THINKCAR Bidirectional Scan Tool, THINKSCAN 689BT All System Automotive Diagnostic Tool, Bi Directional OBD2 Scanner with ECU Coding, 34 Services, FCA Autoauth, CANFD and DoIP, Wireless Update | D53: thinkcar | E53: Tablet | F53: 555.84548 | G53: 239569.4 | H53: 431 | I53: 603 | J53: 4.4 | K53: https://amazon.com/dp/B0DCFRF2TF | L53: =IF(K53="","",HYPERLINK(K53,K53))
A54: 8 | B54: B091BQNR3S | C54: TOPDON Phoenix Plus 2, OE-Level TOPDON Scanner, Advanced Online ECU Coding & Configuration Flashing, Bidirectional Scan Tool with Topology Map, CANFD, 42+ Services, FCA AutoAuth, 2 Years Free Update | D54: topdon | E54: Tablet | F54: 1017.3352 | G54: 231952.42 | H54: 228 | I54: 502 | J54: 4.5 | K54: https://amazon.com/dp/B091BQNR3S | L54: =IF(K54="","",HYPERLINK(K54,K54))
A55: 9 | B55: B08ML7T7KZ | C55: Autel Scanner MaxiCheck MX808S, 2026 US Ver. of MaxiCOM MK808S MK808Z, Bidirectional 3000+ Active Test 11OS as MK900 MK900BT MX900, 28+ Service, OE All Systems OBD2 Diagnostic Tool, FCA, 10X Faster | D55: autel | E55: Tablet | F55: 427.35611 | G55: 230772.3 | H55: 540 | I55: 722 | J55: 4.7 | K55: https://amazon.com/dp/B08ML7T7KZ | L55: =IF(K55="","",HYPERLINK(K55,K55))
A56: 10 | B56: B09KZTYD18 | C56: OBD2 Scanner TOPDON AD600S Scan Tool, Code Reader, Diagnostics Scanner for ABS/SRS/AT/Engine, 9 Reset Services, Oil/Brake/BMS/SAS/DPF/TPMS/ETS Reset/ABS Bleeding/Injector Coding, Free Lifetime Upgrade | D56: topdon | E56: Tablet | F56: 201.80111 | G56: 222990.23 | H56: 1105 | I56: 1864 | J56: 4.4 | K56: https://amazon.com/dp/B09KZTYD18 | L56: =IF(K56="","",HYPERLINK(K56,K56))
A58: Rank By Monthly Units - May '26 ONLY
A59: Ranking | B59: ASIN | C59: Product Name | D59: Brand | E59: Type | F59: Price | G59: Est. Monthly Retail Rev | H59: Est. Monthly Units Sold | I59: # of Reviews | J59: Avg. Rating | K59: Column2 | L59: Link
A60: 1 | B60: B08PFJMTY3 | C60: FOXWELL Car Scanner NT604 Elite OBD2 Scanner ABS SRS Transmission, Check Engine Code Reader for Cars and Trucks, Diagnostic Scan Tool with SRS Airbag, Automotive Diagnostic Tool with Live Data | D60: foxwell | E60: Tablet | F60: 153.79738 | G60: 353118.78 | H60: 2296 | I60: 4914 | J60: 4.4 | K60: https://amazon.com/dp/B08PFJMTY3 | L60: =IF(K60="","",HYPERLINK(K60,K60))
A61: 2 | B61: B0DV2N2FND | C61: BLCKTEC 460T OBD2 Scanner Car Code Reader Engine ABS SRS Transmission Diagnostic Tool, 12 Reset Services, Oil/TPMS/EPB/BMS/SAS/DPF/Throttle Reset, ABS Bleeding, Battery Test, Auto VIN, Free Update | D61: blcktec | E61: Tablet | F61: 196.13548 | G61: 356182.04 | H61: 1816 | I61: 656 | J61: 4.4 | K61: https://amazon.com/dp/B0DV2N2FND | L61: =IF(K61="","",HYPERLINK(K61,K61))
A62: 3 | B62: B0C33Y285Y | C62: TOPDON Bidirectional Scan Tool, 2026 New ArtiDiag900 Lite Automotive Diagnostic Tool for Full System, Scanner for Car with Active Test, 8 Reset, Wireless OBD2 Scanner Diagnostic Tool for All Vehicles | D62: topdon | E62: Tablet | F62: 315.0536 | G62: 384680.45 | H62: 1221 | I62: 1273 | J62: 4.2 | K62: https://amazon.com/dp/B0C33Y285Y | L62: =IF(K62="","",HYPERLINK(K62,K62))
A63: 4 | B63: B09KZTYD18 | C63: OBD2 Scanner TOPDON AD600S Scan Tool, Code Reader, Diagnostics Scanner for ABS/SRS/AT/Engine, 9 Reset Services, Oil/Brake/BMS/SAS/DPF/TPMS/ETS Reset/ABS Bleeding/Injector Coding, Free Lifetime Upgrade | D63: topdon | E63: Tablet | F63: 201.80111 | G63: 222990.23 | H63: 1105 | I63: 1864 | J63: 4.4 | K63: https://amazon.com/dp/B09KZTYD18 | L63: =IF(K63="","",HYPERLINK(K63,K63))
A64: 5 | B64: B08XK3DJ42 | C64: TOPDON AD500 OBD2 Scanner, Oil SAS Throttle TPMS BMS EPB Reset, Engine ABS SRS Transmission, Diagnostic Scan Tool, AutoVIN, Car Check Engine Code Reader with Battery Test, Lifetime Wi-Fi Free Update | D64: topdon | E64: Tablet | F64: 159.11793 | G64: 150366.44 | H64: 945 | I64: 1766 | J64: 4.4 | K64: https://amazon.com/dp/B08XK3DJ42 | L64: =IF(K64="","",HYPERLINK(K64,K64))
A65: 6 | B65: B098PYB8XG | C65: Autel Scanner MaxiCOM MK900BT, 2026 MK900-BT V2.0 Bidirectional Diagnostic Tool, 8in Up of MK900 MX900 MK808S MK808BT MX808S MK808Z, 3000+ Active Tests, 40+ Service, CAN-FD&DOIP, All System, FCA 11 OS | D65: autel | E65: Tablet | F65: 658.58882 | G65: 503161.86 | H65: 764 | I65: 723 | J65: 4.6 | K65: https://amazon.com/dp/B098PYB8XG | L65: =IF(K65="","",HYPERLINK(K65,K65))
A66: 7 | B66: B08DCNDFVK | C66: FOXWELL NT614 Elite OBD2 Scanner for DIY Mechanics, Upgrade of NT604, 4 System Diagnostic Tool with 5 Resets (ABS Bleeding, EPB, Oil, SAS, Throttle), Read/Clear Engine/ABS/SRS/Transmission Fault Codes | D66: foxwell | E66: Tablet | F66: 177.04205 | G66: 117201.84 | H66: 662 | I66: 745 | J66: 4.3 | K66: https://amazon.com/dp/B08DCNDFVK | L66: =IF(K66="","",HYPERLINK(K66,K66))
A67: 8 | B67: B0DFCMT416 | C67: XTOOL D5S OBD2 Scanner with Touchscreen, Code Reader for Cars & Trucks with 16 Resets, Crank Sensor Relearn, Throttle Relearn, EPB, FCA, CAN FD for GM, Engine ABS SRS Transmission Car Diagnostic Tool | D67: xtool | E67: Tablet | F67: 175.72467 | G67: 105786.25 | H67: 602 | I67: 455 | J67: 4.3 | K67: https://amazon.com/dp/B0DFCMT416 | L67: =IF(K67="","",HYPERLINK(K67,K67))
A68: 9 | B68: B07RLF8FBC | C68: Launch OBD2 Scanner CRP123X V3.0 Elite, 2026 Lifetime Free WiFi Update Scan Tool, FCA SGW, CANFD&DoIP, SAS/Throttle/Brake/BMS/D-P-F/Oil/ABS Service Multi Systems Car Scanner, Battery Test, Auto VIN | D68: launch | E68: Tablet | F68: 209.1466 | G68: 122978.2 | H68: 588 | I68: 3489 | J68: 4.4 | K68: https://amazon.com/dp/B07RLF8FBC | L68: =IF(K68="","",HYPERLINK(K68,K68))
A69: 10 | B69: B073GW5MTS | C69: LAUNCH CRP123 V2.0 OBD2 Scanner-2026 New Model Engine/ABS/SRS/Transmission Diagnostic Scan Tool SRS Airbag Code Reader,3 Reset Oil Service/Throttle Relearn/SAS Reset,Lifetime Free Update | D69: launch | E69: Tablet | F69: 124.90528 | G69: 68323.19 | H69: 547 | I69: 4066 | J69: 4.3 | K69: https://amazon.com/dp/B073GW5MTS | L69: =IF(K69="","",HYPERLINK(K69,K69))
A71: Tablet $800+
B72: Avg Price | C72: Avg Price MoM | D72: Avg Price YoY | E72: Quantity/Mo | F72: Qty by % | G72: Qty MoM | H72: Qty YoY | I72: Revenue/Mo | J72: Revenue by % | L72: Revenue MoM | M72: Revenue YoY
A73: autel | B73: 1904.8305 | C73: 0.033080843 | D73: -0.047155361 | E73: 893 | F73: 0.38876796 | G73: -0.11932939 | H73: -0.018681319 | I73: 1701013.6 | J73: 0.4891427 | L73: -0.090196062 | M73: -0.064955755
A74: launch | B74: 1394.6057 | C74: 0.0093515194 | D74: 0.028908938 | E74: 617 | F74: 0.26861123 | G74: -0.097953216 | H74: -0.15710383 | I74: 860471.73 | J74: 0.24743685 | L74: -0.089517708 | M74: -0.13273659
A75: topdon | B75: 1122.2206 | C75: -0.053103526 | D75: -0.11468976 | E75: 367 | F75: 0.15977362 | G75: -0.016085791 | H75: 0.53556485 | I75: 411854.97 | J75: 0.11843282 | L75: -0.068335104 | M75: 0.35945128
A76: ancel | B76: 952.79519 | C76: -0.033688335 | D76: 0.049564962 | E76: 231 | F76: 0.10056596 | G76: 4.9230769 | H76: 0.34302326 | I76: 220095.69 | J76: 0.063290615 | L76: 4.7235383 | M76: 0.40959015
A77: xtool | B77: 1489.2379 | C77: 0.056823254 | D77: 0.14017342 | E77: 101 | F77: 0.043970396 | G77: -0.1984127 | H77: 0.18823529 | I77: 150413.03 | J77: 0.043252701 | L77: -0.1528639 | M77: 0.3547943
A78: Other | B78: 1519.2234 | C78: 0.45582199 | D78: 0.28889954 | E78: 88 | F78: 0.03831084 | G78: 0.12820513 | H78: -0.11111111 | I78: 133691.66 | J78: 0.038444312 | L78: 0.64246583 | M78: 0.14568848
A79: ='Summary'!A4 | B79: ='Summary'!B4 | C79: ='Summary'!C4 | D79: ='Summary'!D4 | E79: =SUM(E73:E78) | F79: =SUM(F73:F78) | G79: ='Summary'!G4 | H79: ='Summary'!H4 | I79: =SUM(I73:I78) | J79: =SUM(J73:J78) | L79: ='Summary'!K4 | M79: ='Summary'!L4
A81: Tablet $400-$800
B82: Avg Price | C82: Avg Price MoM | D82: Avg Price YoY | E82: Quantity/Mo | F82: Qty by % | G82: Qty MoM | H82: Qty YoY | I82: Revenue/Mo | J82: Revenue by % | L82: Revenue MoM | M82: Revenue YoY
A83: autel | B83: 551.94336 | C83: 0.021962004 | D83: 0.056538215 | E83: 4539 | F83: 0.38133244 | G83: -0.16913784 | H83: 0.02808607 | I83: 2505270.9 | J83: 0.38606246 | L83: -0.15089044 | M83: 0.086212222
A84: launch | B84: 575.09588 | C84: 0.060718993 | D84: 0.048555117 | E84: 1581 | F84: 0.13282366 | G84: 0.061073826 | H84: 0.078444748 | I84: 909226.59 | J84: 0.14011189 | L84: 0.12550116 | M84: 0.13080876
A85: ancel | B85: 557.38959 | C85: -0.055060101 | D85: 0.14208458 | E85: 1318 | F85: 0.11072839 | G85: 0.14409722 | H85: 2.4775726 | I85: 734639.48 | J85: 0.11320801 | L85: 0.081103114 | M85: 2.971682
A86: xtool | B86: 490.90624 | C86: 0.026605701 | D86: -0.10461649 | E86: 1357 | F86: 0.11400487 | G86: -0.007315289 | H86: 0.94134478 | I86: 666159.77 | J86: 0.10265528 | L86: 0.019095783 | M86: 0.7382481
A87: thinkcar | B87: 501.55804 | C87: 0.00020495178 | D87: -0.15348944 | E87: 937 | F87: 0.078719651 | G87: -0.090291262 | H87: 1.2470024 | I87: 469959.88 | J87: 0.072420857 | L87: -0.090104816 | M87: 0.90211126
A88: Other | B88: 554.59809 | C88: -0.053125803 | D88: 0.1301768 | E88: 2171 | F88: 0.18239099 | G88: -0.16564181 | H88: -0.15095815 | I88: 1204032.5 | J88: 0.1855415 | L88: -0.20996776 | M88: -0.040432603
A89: ='Summary'!A5 | B89: ='Summary'!B5 | C89: ='Summary'!C5 | D89: ='Summary'!D5 | E89: =SUM(E83:E88) | F89: =SUM(F83:F88) | G89: ='Summary'!G5 | H89: ='Summary'!H5 | I89: =SUM(I83:I88) | J89: =SUM(J83:J88) | L89: ='Summary'!K5 | M89: ='Summary'!L5
A91: Tablet $400-
B92: Avg Price | C92: Avg Price MoM | D92: Avg Price YoY | E92: Quantity/Mo | F92: Qty by % | G92: Qty MoM | H92: Qty YoY | I92: Revenue/Mo | J92: Revenue by % | L92: Revenue MoM | M92: Revenue YoY
A93: topdon | B93: 246.38195 | C93: 0.025327023 | D93: 0.27502303 | E93: 5654 | F93: 0.21618935 | G93: -0.15232384 | H93: 0.39673913 | I93: 1393043.5 | J93: 0.25374209 | L93: -0.13085472 | M93: 0.78087456
A94: foxwell | B94: 198.57807 | C94: 0.060018384 | D94: 0.026916793 | E94: 4694 | F94: 0.17948228 | G94: -0.079246763 | H94: 0.48497311 | I94: 932125.45 | J94: 0.16978612 | L94: -0.023984642 | M94: 0.52494382
A95: launch | B95: 191.50922 | C95: 0.064329304 | D95: 0.073386682 | E95: 3244 | F95: 0.12403931 | G95: -0.15674552 | H95: -0.30266552 | I95: 621255.92 | J95: 0.11316141 | L95: -0.10249954 | M95: -0.25149046
A96: xtool | B96: 195.08535 | C96: 0.007251184 | D96: -0.22985872 | E96: 2382 | F96: 0.091079417 | G96: 0.042450766 | H96: 0.60080645 | I96: 464693.31 | J96: 0.084643624 | L96: 0.050009768 | M96: 0.23284713
A97: icarsoft | B97: 191.38871 | C97: -0.018905456 | D97: -0.030864141 | E97: 1942 | F97: 0.074255344 | G97: 0.11098398 | H97: 0.3971223 | I97: 371676.87 | J97: 0.067700732 | L97: 0.089980323 | M97: 0.35400132
A98: blcktec | B98: 196.13548 | C98: 0.034452976 | D98: 0.059213373 | E98: 1816 | F98: 0.069437541 | G98: 0.135 | H98: 2.5193798 | I98: 356182.04 | J98: 0.064878357 | L98: 0.17410413 | M98: 2.7277742
A99: innova | B99: 159.12765 | C99: -0.0077981129 | D99: -0.22299144 | E99: 557 | F99: 0.021297748 | G99: -0.11305732 | H99: 3.2846154 | I99: 88634.1 | J99: 0.016144651 | L99: -0.1199738 | M99: 2.3291828
A100: Other | B100: 215.27739 | C100: -0.044767835 | D100: -0.13211923 | E100: 5864 | F100: 0.22421902 | G100: 0.12122371 | H100: 0.82850016 | I100: 1262386.6 | J100: 0.22994301 | L100: 0.071028951 | M100: 0.58692011
A101: ='Summary'!A6 | B101: ='Summary'!B6 | C101: ='Summary'!C6 | D101: ='Summary'!D6 | E101: =SUM(E93:E100) | F101: =SUM(F93:F100) | G101: ='Summary'!G6 | H101: ='Summary'!H6 | I101: =SUM(I93:I100) | J101: =SUM(J93:J100) | L101: ='Summary'!K6 | M101: ='Summary'!L6

Sheet Tablet $800+
A1: Tablet $800+ Monthly Summary
A3: ='Tablet Total'!A71
B4: Avg Price | C4: Avg Price MoM | D4: Avg Price YoY | E4: Quantity/Mo | F4: Qty by % | G4: Qty MoM | H4: Qty YoY | I4: Revenue/Mo | J4: Revenue by % | L4: Revenue MoM | M4: Revenue YoY
A5: ='Tablet Total'!A73 | B5: ='Tablet Total'!B73 | C5: ='Tablet Total'!C73 | D5: ='Tablet Total'!D73 | E5: ='Tablet Total'!E73 | F5: ='Tablet Total'!F73 | G5: ='Tablet Total'!G73 | H5: ='Tablet Total'!H73 | ... M5: ='Tablet Total'!M73
A6: ='Tablet Total'!A74 | B6: ='Tablet Total'!B74 | C6: ='Tablet Total'!C74 | D6: ='Tablet Total'!D74 | E6: ='Tablet Total'!E74 | F6: ='Tablet Total'!F74 | G6: ='Tablet Total'!G74 | H6: ='Tablet Total'!H74 | ... M6: ='Tablet Total'!M74
A7: ='Tablet Total'!A75 | B7: ='Tablet Total'!B75 | C7: ='Tablet Total'!C75 | D7: ='Tablet Total'!D75 | E7: ='Tablet Total'!E75 | F7: ='Tablet Total'!F75 | G7: ='Tablet Total'!G75 | H7: ='Tablet Total'!H75 | ... M7: ='Tablet Total'!M75
A8: ='Tablet Total'!A76 | B8: ='Tablet Total'!B76 | C8: ='Tablet Total'!C76 | D8: ='Tablet Total'!D76 | E8: ='Tablet Total'!E76 | F8: ='Tablet Total'!F76 | G8: ='Tablet Total'!G76 | H8: ='Tablet Total'!H76 | ... M8: ='Tablet Total'!M76
A9: ='Tablet Total'!A77 | B9: ='Tablet Total'!B77 | C9: ='Tablet Total'!C77 | D9: ='Tablet Total'!D77 | E9: ='Tablet Total'!E77 | F9: ='Tablet Total'!F77 | G9: ='Tablet Total'!G77 | H9: ='Tablet Total'!H77 | ... M9: ='Tablet Total'!M77
A10: ='Tablet Total'!A78 | B10: ='Tablet Total'!B78 | C10: ='Tablet Total'!C78 | D10: ='Tablet Total'!D78 | E10: ='Tablet Total'!E78 | F10: ='Tablet Total'!F78 | G10: ='Tablet Total'!G78 | H10: ='Tablet Total'!H78 | ... M10: ='Tablet Total'!M78
A11: ='Tablet Total'!A79 | B11: ='Tablet Total'!B79 | C11: ='Tablet Total'!C79 | D11: ='Tablet Total'!D79 | E11: ='Tablet Total'!E79 | F11: ='Tablet Total'!F79 | G11: ='Tablet Total'!G79 | H11: ='Tablet Total'!H79 | ... M11: ='Tablet Total'!M79
A43: Rank By Monthly Revenue - May '26 ONLY
A44: Ranking | B44: ASIN | C44: Product Name | D44: Brand | E44: Type | F44: Price | G44: Est. Monthly Retail Rev | H44: Est. Monthly Units Sold | I44: # of Reviews | J44: Avg. Rating | K44: Column2 | L44: Link
A45: 1 | B45: B091BQNR3S | C45: TOPDON Phoenix Plus 2, OE-Level TOPDON Scanner, Advanced Online ECU Coding & Configuration Flashing, Bidirectional Scan Tool with Topology Map, CANFD, 42+ Services, FCA AutoAuth, 2 Years Free Update | D45: topdon | E45: Tablet | F45: 1017.3352 | G45: 231952.42 | H45: 228 | I45: 502 | J45: 4.5 | K45: https://amazon.com/dp/B091BQNR3S | L45: =IF(K45="","",HYPERLINK(K45,K45))
A46: 2 | B46: B0DTTTJWYH | C46: Launch X431 PRO3 V+ Elite, 2026 SmartlinkC 2.0 Bidirectional Scan Tool with J2534 Portocol, HD Trucks Scanner, 10.1 inch, Topology Map, 60+Service, Online Code, CANFD/DoIP/D-PDU, FCA, 2 Yrs Update | D46: launch | E46: Tablet | F46: 1352.3306 | G46: 167689 | H46: 124 | I46: 96 | J46: 4.6 | K46: https://amazon.com/dp/B0DTTTJWYH | L46: =IF(K46="","",HYPERLINK(K46,K46))
A47: 3 | B47: B0D7VS8SHS | C47: LAUNCH X431 PRO3S+ Elite, 2026 All-in-One Bidirectional Scan Tool with J2534 Protocols, HD Trucks Scanner, Topology Map, 60+Service, ECU Code Full Function Scanner, CANFD/DoIP/D-PDU/FCA, 2 Yrs Update | D47: launch | E47: Tablet | F47: 1237.3999 | G47: 165811.58 | H47: 134 | I47: 157 | J47: 4.3 | K47: https://amazon.com/dp/B0D7VS8SHS | L47: =IF(K47="","",HYPERLINK(K47,K47))
A48: 4 | B48: B08V59JNYP | C48: LAUNCH X431 PRO3S+ Smartlink HD Heavy Duty Truck Scanner,2026 Diesel&Gasoline Bidirectional Diagnostic Scan Tool with J2534 Protocols,Topology Map,60+Service,ECU Code,CANFD &DOIP,2 Yrs Free Update | D48: launch | E48: Tablet | F48: 1714.2888 | G48: 140571.68 | H48: 82 | I48: 183 | J48: 4.3 | K48: https://amazon.com/dp/B08V59JNYP | L48: =IF(K48="","",HYPERLINK(K48,K48))
A49: 5 | B49: B0DZC1M7MZ | C49: Autel MaxiSys Ultra S2 Scanner, 2026 Top Intelligen Scan Diagnostic with AI, 6-in-1 VCMI2, Up of MSUltra MS919, Topology 3.0, Multi-Point DVI, Motor Truspeed Repair, EV Test, 48+ Service, ECU Program | D49: autel | E49: Tablet | F49: 5788.9904 | G49: 133146.78 | H49: 23 | I49: 22 | J49: 4.8 | K49: https://amazon.com/dp/B0DZC1M7MZ | L49: =IF(K49="","",HYPERLINK(K49,K49))
A50: 6 | B50: B0BMZW65LJ | C50: ANCEL MT700 Motorcycle OBD2 Scanner Full Systems, ABS Engine Meter TPMS Diagnostic Tool with 35+ Reset Functions for Harley Indian Yamaha Polaris Piaggio Ducati Honda BMW, AutoVIN, 7”Touch Screen,16G | D50: ancel | E50: Tablet | F50: 936.38185 | G50: 111429.44 | H50: 119 | I50: 883 | J50: 4.5 | K50: https://amazon.com/dp/B0BMZW65LJ | L50: =IF(K50="","",HYPERLINK(K50,K50))
A51: 7 | B51: B0GLFSPMZ4 | C51: ANCEL X7HD PRO 10.1'' Heavy Duty Truck Scanner, Full-System Diesel Diagnostic Tool with DPF Regen, 42+ Reset, Bi-Directional and Active Test, ECU Coding, HDOBD/OBD2 Scanner for Diesel Trucks - Grey | D51: ancel | E51: Tablet | F51: 940.765 | G51: 88431.91 | H51: 94 | K51: https://amazon.com/dp/B0GLFSPMZ4 | L51: =IF(K51="","",HYPERLINK(K51,K51))
A52: 8 | B52: B0751G1W5C | C52: Autel MaxiPRO MP900-BT KIT Scanner: 2026 Same as MS906 Pro MS906 MAX MK908 w/OE C0ding, 3000+ Test, 40+ Service, 150+ Makes, Up of MP900-BT MP900BT w/ 200 Bucks 11 PCS OBD Cables, CAN FD & FCA SGW | D52: autel | E52: Tablet | F52: 965.19723 | G52: 62737.82 | H52: 65 | I52: 149 | J52: 4.6 | K52: https://amazon.com/dp/B0751G1W5C | L52: =IF(K52="","",HYPERLINK(K52,K52))
A53: 9 | B53: B0DBLQXQ6W | C53: XTOOL IP919 PRO V2.0 ECU Programming Scan Tool, Topology Mapping OBD2 Scanner, 4000+ Bidirectional Test, 51+ Reset, Upgrade of D9S PRO, Automotive ADAS Scanner for Car, FCA/CAN FD/DoIP | D53: xtool | E53: Tablet | F53: 1483.7785 | G53: 60834.92 | H53: 41 | I53: 76 | J53: 4.4 | K53: https://amazon.com/dp/B0DBLQXQ6W | L53: =IF(K53="","",HYPERLINK(K53,K53))
A54: 10 | B54: B0B1HT1J23 | C54: Launch X431 PAD VII Elite, 2026 Top Intelligent Diagnostic Scanner, J2534 Protocol, Topology Map, Remote Diagnosis with Smartlink C, 2-Year Free Update, Bi-Directional Scan,60+ Service | D54: launch | E54: Tablet | F54: 2697.3575 | G54: 53947.15 | H54: 20 | I54: 136 | J54: 4.1 | K54: https://amazon.com/dp/B0B1HT1J23 | L54: =IF(K54="","",HYPERLINK(K54,K54))
A56: Rank By Monthly Units - May '26 ONLY
A57: Ranking | B57: ASIN | C57: Product Name | D57: Brand | E57: Type | F57: Price | G57: Est. Monthly Retail Rev | H57: Est. Monthly Units Sold | I57: # of Reviews | J57: Avg. Rating | K57: Column2 | L57: Link
A58: 1 | B58: B091BQNR3S | C58: TOPDON Phoenix Plus 2, OE-Level TOPDON Scanner, Advanced Online ECU Coding & Configuration Flashing, Bidirectional Scan Tool with Topology Map, CANFD, 42+ Services, FCA AutoAuth, 2 Years Free Update | D58: topdon | E58: Tablet | F58: 1017.3352 | G58: 231952.42 | H58: 228 | I58: 502 | J58: 4.5 | K58: https://amazon.com/dp/B091BQNR3S | L58: =IF(K58="","",HYPERLINK(K58,K58))
A59: 2 | B59: B0D7VS8SHS | C59: LAUNCH X431 PRO3S+ Elite, 2026 All-in-One Bidirectional Scan Tool with J2534 Protocols, HD Trucks Scanner, Topology Map, 60+Service, ECU Code Full Function Scanner, CANFD/DoIP/D-PDU/FCA, 2 Yrs Update | D59: launch | E59: Tablet | F59: 1237.3999 | G59: 165811.58 | H59: 134 | I59: 157 | J59: 4.3 | K59: https://amazon.com/dp/B0D7VS8SHS | L59: =IF(K59="","",HYPERLINK(K59,K59))
A60: 3 | B60: B0DTTTJWYH | C60: Launch X431 PRO3 V+ Elite, 2026 SmartlinkC 2.0 Bidirectional Scan Tool with J2534 Portocol, HD Trucks Scanner, 10.1 inch, Topology Map, 60+Service, Online Code, CANFD/DoIP/D-PDU, FCA, 2 Yrs Update | D60: launch | E60: Tablet | F60: 1352.3306 | G60: 167689 | H60: 124 | I60: 96 | J60: 4.6 | K60: https://amazon.com/dp/B0DTTTJWYH | L60: =IF(K60="","",HYPERLINK(K60,K60))
A61: 4 | B61: B0BMZW65LJ | C61: ANCEL MT700 Motorcycle OBD2 Scanner Full Systems, ABS Engine Meter TPMS Diagnostic Tool with 35+ Reset Functions for Harley Indian Yamaha Polaris Piaggio Ducati Honda BMW, AutoVIN, 7”Touch Screen,16G | D61: ancel | E61: Tablet | F61: 936.38185 | G61: 111429.44 | H61: 119 | I61: 883 | J61: 4.5 | K61: https://amazon.com/dp/B0BMZW65LJ | L61: =IF(K61="","",HYPERLINK(K61,K61))
A62: 5 | B62: B0GLFSPMZ4 | C62: ANCEL X7HD PRO 10.1'' Heavy Duty Truck Scanner, Full-System Diesel Diagnostic Tool with DPF Regen, 42+ Reset, Bi-Directional and Active Test, ECU Coding, HDOBD/OBD2 Scanner for Diesel Trucks - Grey | D62: ancel | E62: Tablet | F62: 940.765 | G62: 88431.91 | H62: 94 | K62: https://amazon.com/dp/B0GLFSPMZ4 | L62: =IF(K62="","",HYPERLINK(K62,K62))
A63: 6 | B63: B08V59JNYP | C63: LAUNCH X431 PRO3S+ Smartlink HD Heavy Duty Truck Scanner,2026 Diesel&Gasoline Bidirectional Diagnostic Scan Tool with J2534 Protocols,Topology Map,60+Service,ECU Code,CANFD &DOIP,2 Yrs Free Update | D63: launch | E63: Tablet | F63: 1714.2888 | G63: 140571.68 | H63: 82 | I63: 183 | J63: 4.3 | K63: https://amazon.com/dp/B08V59JNYP | L63: =IF(K63="","",HYPERLINK(K63,K63))
A64: 7 | B64: B0751G1W5C | C64: Autel MaxiPRO MP900-BT KIT Scanner: 2026 Same as MS906 Pro MS906 MAX MK908 w/OE C0ding, 3000+ Test, 40+ Service, 150+ Makes, Up of MP900-BT MP900BT w/ 200 Bucks 11 PCS OBD Cables, CAN FD & FCA SGW | D64: autel | E64: Tablet | F64: 965.19723 | G64: 62737.82 | H64: 65 | I64: 149 | J64: 4.6 | K64: https://amazon.com/dp/B0751G1W5C | L64: =IF(K64="","",HYPERLINK(K64,K64))
A65: 8 | B65: B08PB6DHBS | C65: 2026 Autel MaxiCOM MK900TS Scanner, MK900-TS Up of MK808S-TS MK900BT MK900 MX900, Bidirectional Scan Tool w/Top TPMS Function, All System, CAN FD & DoIP, 3000+ Active Test, 40+ Service, FCA, OS 11.0 | D65: autel | E65: Tablet | F65: 874.2331 | G65: 50705.52 | H65: 58 | I65: 93 | J65: 4.8 | K65: https://amazon.com/dp/B08PB6DHBS | L65: =IF(K65="","",HYPERLINK(K65,K65))
A66: 9 | B66: B0DFLWDPK2 | C66: TOPDON Phoenix Lite 3 OBD2 Scanner, Upgraded Scanner of Lite 2, Bidirectional Scan Tool with CAN-FD, Car Scanner Diagnostic Tool, 35+ Maintenance Resets, Topology Mapping, ECU Coding, FCA Autoauth | D66: topdon | E66: Tablet | F66: 803.15765 | G66: 40961.04 | H66: 51 | I66: 19 | J66: 4.7 | K66: https://amazon.com/dp/B0DFLWDPK2 | L66: =IF(K66="","",HYPERLINK(K66,K66))
A67: 10 | B67: B092894STV | C67: Launch X431 PRO3S+ V5.0,2026 Upgrade All-in-One Bidirectional Scan Tool,HD Trucks Scan,Topology Map,ECU Code,55+ Service,Full System,CANFD&DOIP,DBSCar VII VCI 2-Year Update | D67: launch | E67: Tablet | F67: 1169.0831 | G67: 49101.49 | H67: 42 | I67: 682 | J67: 4.2 | K67: https://amazon.com/dp/B092894STV | L67: =IF(K67="","",HYPERLINK(K67,K67))

Sheet Tablet $400-$800
A1: Tablet $400-$800 Monthly Summary
A3: ='Tablet Total'!A81
B4: Avg Price | C4: Avg Price MoM | D4: Avg Price YoY | E4: Quantity/Mo | F4: Qty by % | G4: Qty MoM | H4: Qty YoY | I4: Revenue/Mo | J4: Revenue by % | L4: Revenue MoM | M4: Revenue YoY
A5: ='Tablet Total'!A83 | B5: ='Tablet Total'!B83 | C5: ='Tablet Total'!C83 | D5: ='Tablet Total'!D83 | E5: ='Tablet Total'!E83 | F5: ='Tablet Total'!F83 | G5: ='Tablet Total'!G83 | H5: ='Tablet Total'!H83 | ... M5: ='Tablet Total'!M83
A6: ='Tablet Total'!A84 | B6: ='Tablet Total'!B84 | C6: ='Tablet Total'!C84 | D6: ='Tablet Total'!D84 | E6: ='Tablet Total'!E84 | F6: ='Tablet Total'!F84 | G6: ='Tablet Total'!G84 | H6: ='Tablet Total'!H84 | ... M6: ='Tablet Total'!M84
A7: ='Tablet Total'!A85 | B7: ='Tablet Total'!B85 | C7: ='Tablet Total'!C85 | D7: ='Tablet Total'!D85 | E7: ='Tablet Total'!E85 | F7: ='Tablet Total'!F85 | G7: ='Tablet Total'!G85 | H7: ='Tablet Total'!H85 | ... M7: ='Tablet Total'!M85
A8: ='Tablet Total'!A86 | B8: ='Tablet Total'!B86 | C8: ='Tablet Total'!C86 | D8: ='Tablet Total'!D86 | E8: ='Tablet Total'!E86 | F8: ='Tablet Total'!F86 | G8: ='Tablet Total'!G86 | H8: ='Tablet Total'!H86 | ... M8: ='Tablet Total'!M86
A9: ='Tablet Total'!A87 | B9: ='Tablet Total'!B87 | C9: ='Tablet Total'!C87 | D9: ='Tablet Total'!D87 | E9: ='Tablet Total'!E87 | F9: ='Tablet Total'!F87 | G9: ='Tablet Total'!G87 | H9: ='Tablet Total'!H87 | ... M9: ='Tablet Total'!M87
A10: ='Tablet Total'!A88 | B10: ='Tablet Total'!B88 | C10: ='Tablet Total'!C88 | D10: ='Tablet Total'!D88 | E10: ='Tablet Total'!E88 | F10: ='Tablet Total'!F88 | G10: ='Tablet Total'!G88 | H10: ='Tablet Total'!H88 | ... M10: ='Tablet Total'!M88
A11: ='Tablet Total'!A89 | B11: ='Tablet Total'!B89 | C11: ='Tablet Total'!C89 | D11: ='Tablet Total'!D89 | E11: ='Tablet Total'!E89 | F11: ='Tablet Total'!F89 | G11: ='Tablet Total'!G89 | H11: ='Tablet Total'!H89 | ... M11: ='Tablet Total'!M89
A43: Rank By Monthly Revenue - May '26 ONLY
A44: Ranking | B44: ASIN | C44: Product Name | D44: Brand | E44: Type | F44: Price | G44: Est. Monthly Retail Rev | H44: Est. Monthly Units Sold | I44: # of Reviews | J44: Avg. Rating | K44: Column2 | L44: Link
A45: 1 | B45: B098PYB8XG | C45: Autel Scanner MaxiCOM MK900BT, 2026 MK900-BT V2.0 Bidirectional Diagnostic Tool, 8in Up of MK900 MX900 MK808S MK808BT MX808S MK808Z, 3000+ Active Tests, 40+ Service, CAN-FD&DOIP, All System, FCA 11 OS | D45: autel | E45: Tablet | F45: 658.58882 | G45: 503161.86 | H45: 764 | I45: 723 | J45: 4.6 | K45: https://amazon.com/dp/B098PYB8XG | L45: =IF(K45="","",HYPERLINK(K45,K45))
A46: 2 | B46: B0DTK24XKB | C46: MUCAR 892BT AI-Assisted Bidirectional Scan Tool, Full System OBD2 Scanner, Bi-Directional OBD2 Scanner Diagnostic Tool,ECU Coding, 35 Services, FCA Autoauth, CANFD and DOIP, Free Lifetime Upgrade | D46: mucar | E46: Tablet | F46: 639.61776 | G46: 345393.59 | H46: 540 | I46: 421 | J46: 4.3 | K46: https://amazon.com/dp/B0DTK24XKB | L46: =IF(K46="","",HYPERLINK(K46,K46))
A47: 3 | B47: B0BZ82WQ4Q | C47: ANCEL X7HD 10.1'' Heavy Duty Truck Scanner, Semi Trucks Full System Diagnostic Tool, Bidirectional Diesel Scan Tool with DPF, ECU Coding, 40+ Reset for Cummins, Detroit, Caterpillar, Volvo, Paccar etc | D47: ancel | E47: Tablet | F47: 765.33645 | G47: 267102.42 | H47: 349 | I47: 796 | J47: 3.7 | K47: https://amazon.com/dp/B0BZ82WQ4Q | L47: =IF(K47="","",HYPERLINK(K47,K47))
A48: 4 | B48: B0DCFRF2TF | C48: THINKCAR Bidirectional Scan Tool, THINKSCAN 689BT All System Automotive Diagnostic Tool, Bi Directional OBD2 Scanner with ECU Coding, 34 Services, FCA Autoauth, CANFD and DoIP, Wireless Update | D48: thinkcar | E48: Tablet | F48: 555.84548 | G48: 239569.4 | H48: 431 | I48: 603 | J48: 4.4 | K48: https://amazon.com/dp/B0DCFRF2TF | L48: =IF(K48="","",HYPERLINK(K48,K48))
A49: 5 | B49: B08ML7T7KZ | C49: Autel Scanner MaxiCheck MX808S, 2026 US Ver. of MaxiCOM MK808S MK808Z, Bidirectional 3000+ Active Test 11OS as MK900 MK900BT MX900, 28+ Service, OE All Systems OBD2 Diagnostic Tool, FCA, 10X Faster | D49: autel | E49: Tablet | F49: 427.35611 | G49: 230772.3 | H49: 540 | I49: 722 | J49: 4.7 | K49: https://amazon.com/dp/B08ML7T7KZ | L49: =IF(K49="","",HYPERLINK(K49,K49))
A50: 6 | B50: B0GDY7WJB7 | C50: Autel MaxiCOM MK900 Bidirectional Scanner: 2026 Up of MaxiCheck MX808S MK808S, Work as MK900-BT MK900BT MX900 OBD2 Diagnostic Tool w/ 3000+ Active Test, 40+ Service, CAN-FD&DOIP, All System, FCA 11 OS | D50: autel | E50: Tablet | F50: 589.08904 | G50: 196755.74 | H50: 334 | I50: 34 | J50: 4.9 | K50: https://amazon.com/dp/B0GDY7WJB7 | L50: =IF(K50="","",HYPERLINK(K50,K50))
A51: 7 | B51: B09712X5CW | C51: Autel Scanner MaxiCOM MK900BT, 2026 MK900-BT Bidirectional Diagnostic Scan Tool, 2.0 BT Ver. of MK900 MX900, 8in Up of MK808S MK808BT PRO MX808S MK808Z, 40+ Reset, 3K+ Active Tests, CAN FD & DoIP, FCA | D51: autel | E51: Tablet | F51: 659.53915 | G51: 186649.58 | H51: 283 | I51: 224 | J51: 4.5 | K51: https://amazon.com/dp/B09712X5CW | L51: =IF(K51="","",HYPERLINK(K51,K51))
A52: 8 | B52: B0BNKHCXVC | C52: TOPDON ArtiDiag Pro OBD2 Scanner Diagnostic Tool, Bidirectional Scan Tool with ECU Coding, 35+ Services, V.A.G Guided, FCA SGW, Can FD DoIP/All System Diagnosis | D52: topdon | E52: Tablet | F52: 456.01918 | G52: 183775.73 | H52: 403 | I52: 780 | J52: 4.3 | K52: https://amazon.com/dp/B0BNKHCXVC | L52: =IF(K52="","",HYPERLINK(K52,K52))
A53: 9 | B53: B0DCFF7VGF | C53: THINKCAR THINKSCAN 689 OBD2 Scanner, Bidirectional Scan Tool with 34+ Reset, 3000+ Active Test, ECU Coding, PMI, Wired Full System Diagnostic Scanner for Cars, CANFD/DOIP, FCA SGW AutoAuth | D53: thinkcar | E53: Tablet | F53: 458.18879 | G53: 181442.76 | H53: 396 | I53: 301 | J53: 4.4 | K53: https://amazon.com/dp/B0DCFF7VGF | L53: =IF(K53="","",HYPERLINK(K53,K53))
A54: 10 | B54: B073CQMF25 | C54: Autel Scanner MaxiCOM MK900: 2026 Updated as MK900BT MK900-BT MX900 Bidirectional Diagnostic Tool, 8in Up of MK808S MK808BT Pro MX808S 808Z, 3K+ Active Tests, 40+ Service, CAN-FD&DOIP, All System, FCA | D54: autel | E54: Tablet | F54: 570.78419 | G54: 168952.12 | H54: 296 | I54: 598 | J54: 4.4 | K54: https://amazon.com/dp/B073CQMF25 | L54: =IF(K54="","",HYPERLINK(K54,K54))
A56: Rank By Monthly Units - May '26 ONLY
A57: Ranking | B57: ASIN | C57: Product Name | D57: Brand | E57: Type | F57: Price | G57: Est. Monthly Retail Rev | H57: Est. Monthly Units Sold | I57: # of Reviews | J57: Avg. Rating | K57: Column2 | L57: Link
A58: 1 | B58: B098PYB8XG | C58: Autel Scanner MaxiCOM MK900BT, 2026 MK900-BT V2.0 Bidirectional Diagnostic Tool, 8in Up of MK900 MX900 MK808S MK808BT MX808S MK808Z, 3000+ Active Tests, 40+ Service, CAN-FD&DOIP, All System, FCA 11 OS | D58: autel | E58: Tablet | F58: 658.58882 | G58: 503161.86 | H58: 764 | I58: 723 | J58: 4.6 | K58: https://amazon.com/dp/B098PYB8XG | L58: =IF(K58="","",HYPERLINK(K58,K58))
A59: 2 | B59: B0DTK24XKB | C59: MUCAR 892BT AI-Assisted Bidirectional Scan Tool, Full System OBD2 Scanner, Bi-Directional OBD2 Scanner Diagnostic Tool,ECU Coding, 35 Services, FCA Autoauth, CANFD and DOIP, Free Lifetime Upgrade | D59: mucar | E59: Tablet | F59: 639.61776 | G59: 345393.59 | H59: 540 | I59: 421 | J59: 4.3 | K59: https://amazon.com/dp/B0DTK24XKB | L59: =IF(K59="","",HYPERLINK(K59,K59))
A60: 3 | B60: B08ML7T7KZ | C60: Autel Scanner MaxiCheck MX808S, 2026 US Ver. of MaxiCOM MK808S MK808Z, Bidirectional 3000+ Active Test 11OS as MK900 MK900BT MX900, 28+ Service, OE All Systems OBD2 Diagnostic Tool, FCA, 10X Faster | D60: autel | E60: Tablet | F60: 427.35611 | G60: 230772.3 | H60: 540 | I60: 722 | J60: 4.7 | K60: https://amazon.com/dp/B08ML7T7KZ | L60: =IF(K60="","",HYPERLINK(K60,K60))
A61: 4 | B61: B0DCFRF2TF | C61: THINKCAR Bidirectional Scan Tool, THINKSCAN 689BT All System Automotive Diagnostic Tool, Bi Directional OBD2 Scanner with ECU Coding, 34 Services, FCA Autoauth, CANFD and DoIP, Wireless Update | D61: thinkcar | E61: Tablet | F61: 555.84548 | G61: 239569.4 | H61: 431 | I61: 603 | J61: 4.4 | K61: https://amazon.com/dp/B0DCFRF2TF | L61: =IF(K61="","",HYPERLINK(K61,K61))
A62: 5 | B62: B098LF38DS | C62: XTOOL D7 Bidirectional Scan Tool: 2026 Ai-Assisted OBD2 Scanner Diagnostic Tool with 36+ Resets, Full System Car Scanner with EPB, Injector Test, Throttle, Crank Sensor Relearn, FCA, CANFD & DoIP | D62: xtool | E62: Tablet | F62: 401.21926 | G62: 168512.09 | H62: 420 | I62: 1661 | J62: 4.4 | K62: https://amazon.com/dp/B098LF38DS | L62: =IF(K62="","",HYPERLINK(K62,K62))
A63: 6 | B63: B0BNKHCXVC | C63: TOPDON ArtiDiag Pro OBD2 Scanner Diagnostic Tool, Bidirectional Scan Tool with ECU Coding, 35+ Services, V.A.G Guided, FCA SGW, Can FD DoIP/All System Diagnosis | D63: topdon | E63: Tablet | F63: 456.01918 | G63: 183775.73 | H63: 403 | I63: 780 | J63: 4.3 | K63: https://amazon.com/dp/B0BNKHCXVC | L63: =IF(K63="","",HYPERLINK(K63,K63))
A64: 7 | B64: B0DCFF7VGF | C64: THINKCAR THINKSCAN 689 OBD2 Scanner, Bidirectional Scan Tool with 34+ Reset, 3000+ Active Test, ECU Coding, PMI, Wired Full System Diagnostic Scanner for Cars, CANFD/DOIP, FCA SGW AutoAuth | D64: thinkcar | E64: Tablet | F64: 458.18879 | G64: 181442.76 | H64: 396 | I64: 301 | J64: 4.4 | K64: https://amazon.com/dp/B0DCFF7VGF | L64: =IF(K64="","",HYPERLINK(K64,K64))
A65: 8 | B65: B0BZ82WQ4Q | C65: ANCEL X7HD 10.1'' Heavy Duty Truck Scanner, Semi Trucks Full System Diagnostic Tool, Bidirectional Diesel Scan Tool with DPF, ECU Coding, 40+ Reset for Cummins, Detroit, Caterpillar, Volvo, Paccar etc | D65: ancel | E65: Tablet | F65: 765.33645 | G65: 267102.42 | H65: 349 | I65: 796 | J65: 3.7 | K65: https://amazon.com/dp/B0BZ82WQ4Q | L65: =IF(K65="","",HYPERLINK(K65,K65))
A66: 9 | B66: B0FN4JHLY7 | C66: ANCEL DS500BT Bidirectional Scan Tool, Full-System Automotive Diagnostic Scanner with 28+ Services, Injector Coding, DPF/Brake/BMS/Oil/Gear/Throttle Functions, CAN FD Support, Lifetime Free Updates | D66: ancel | E66: Tablet | F66: 493.77205 | G66: 168376.27 | H66: 341 | I66: 1080 | J66: 4.6 | K66: https://amazon.com/dp/B0FN4JHLY7 | L66: =IF(K66="","",HYPERLINK(K66,K66))
A67: 10 | B67: B0GDY7WJB7 | C67: Autel MaxiCOM MK900 Bidirectional Scanner: 2026 Up of MaxiCheck MX808S MK808S, Work as MK900-BT MK900BT MX900 OBD2 Diagnostic Tool w/ 3000+ Active Test, 40+ Service, CAN-FD&DOIP, All System, FCA 11 OS | D67: autel | E67: Tablet | F67: 589.08904 | G67: 196755.74 | H67: 334 | I67: 34 | J67: 4.9 | K67: https://amazon.com/dp/B0GDY7WJB7 | L67: =IF(K67="","",HYPERLINK(K67,K67))

Sheet Tablet $400-
A1: Tablet $400- Monthly Summary
A3: ='Tablet Total'!A91
B4: Avg Price | C4: Avg Price MoM | D4: Avg Price YoY | E4: Quantity/Mo | F4: Qty by % | G4: Qty MoM | H4: Qty YoY | I4: Revenue/Mo | J4: Revenue by % | L4: Revenue MoM | M4: Revenue YoY
A5: ='Tablet Total'!A93 | B5: ='Tablet Total'!B93 | C5: ='Tablet Total'!C93 | D5: ='Tablet Total'!D93 | E5: ='Tablet Total'!E93 | F5: ='Tablet Total'!F93 | G5: ='Tablet Total'!G93 | H5: ='Tablet Total'!H93 | ... M5: ='Tablet Total'!M93
A6: ='Tablet Total'!A94 | B6: ='Tablet Total'!B94 | C6: ='Tablet Total'!C94 | D6: ='Tablet Total'!D94 | E6: ='Tablet Total'!E94 | F6: ='Tablet Total'!F94 | G6: ='Tablet Total'!G94 | H6: ='Tablet Total'!H94 | ... M6: ='Tablet Total'!M94
A7: ='Tablet Total'!A95 | B7: ='Tablet Total'!B95 | C7: ='Tablet Total'!C95 | D7: ='Tablet Total'!D95 | E7: ='Tablet Total'!E95 | F7: ='Tablet Total'!F95 | G7: ='Tablet Total'!G95 | H7: ='Tablet Total'!H95 | ... M7: ='Tablet Total'!M95
A8: ='Tablet Total'!A96 | B8: ='Tablet Total'!B96 | C8: ='Tablet Total'!C96 | D8: ='Tablet Total'!D96 | E8: ='Tablet Total'!E96 | F8: ='Tablet Total'!F96 | G8: ='Tablet Total'!G96 | H8: ='Tablet Total'!H96 | ... M8: ='Tablet Total'!M96
A9: ='Tablet Total'!A97 | B9: ='Tablet Total'!B97 | C9: ='Tablet Total'!C97 | D9: ='Tablet Total'!D97 | E9: ='Tablet Total'!E97 | F9: ='Tablet Total'!F97 | G9: ='Tablet Total'!G97 | H9: ='Tablet Total'!H97 | ... M9: ='Tablet Total'!M97
A10: ='Tablet Total'!A98 | B10: ='Tablet Total'!B98 | C10: ='Tablet Total'!C98 | D10: ='Tablet Total'!D98 | E10: ='Tablet Total'!E98 | F10: ='Tablet Total'!F98 | G10: ='Tablet Total'!G98 | H10: ='Tablet Total'!H98 | ... M10: ='Tablet Total'!M98
A11: ='Tablet Total'!A99 | B11: ='Tablet Total'!B99 | C11: ='Tablet Total'!C99 | D11: ='Tablet Total'!D99 | E11: ='Tablet Total'!E99 | F11: ='Tablet Total'!F99 | G11: ='Tablet Total'!G99 | H11: ='Tablet Total'!H99 | ... M11: ='Tablet Total'!M99
A12: ='Tablet Total'!A100 | B12: ='Tablet Total'!B100 | C12: ='Tablet Total'!C100 | D12: ='Tablet Total'!D100 | E12: ='Tablet Total'!E100 | F12: ='Tablet Total'!F100 | G12: ='Tablet Total'!G100 | H12: ='Tablet Total'!H100 | ... M12: ='Tablet Total'!M100
A13: ='Tablet Total'!A101 | B13: ='Tablet Total'!B101 | C13: ='Tablet Total'!C101 | D13: ='Tablet Total'!D101 | E13: ='Tablet Total'!E101 | F13: ='Tablet Total'!F101 | G13: ='Tablet Total'!G101 | H13: ='Tablet Total'!H101 | ... M13: ='Tablet Total'!M101
A45: Rank By Monthly Revenue - May '26 ONLY
A46: Ranking | B46: ASIN | C46: Product Name | D46: Brand | E46: Type | F46: Price | G46: Est. Monthly Retail Rev | H46: Est. Monthly Units Sold | I46: # of Reviews | J46: Avg. Rating | K46: Column2 | L46: Link
A47: 1 | B47: B0C33Y285Y | C47: TOPDON Bidirectional Scan Tool, 2026 New ArtiDiag900 Lite Automotive Diagnostic Tool for Full System, Scanner for Car with Active Test, 8 Reset, Wireless OBD2 Scanner Diagnostic Tool for All Vehicles | D47: topdon | E47: Tablet | F47: 315.0536 | G47: 384680.45 | H47: 1221 | I47: 1273 | J47: 4.2 | K47: https://amazon.com/dp/B0C33Y285Y | L47: =IF(K47="","",HYPERLINK(K47,K47))
A48: 2 | B48: B0DV2N2FND | C48: BLCKTEC 460T OBD2 Scanner Car Code Reader Engine ABS SRS Transmission Diagnostic Tool, 12 Reset Services, Oil/TPMS/EPB/BMS/SAS/DPF/Throttle Reset, ABS Bleeding, Battery Test, Auto VIN, Free Update | D48: blcktec | E48: Tablet | F48: 196.13548 | G48: 356182.04 | H48: 1816 | I48: 656 | J48: 4.4 | K48: https://amazon.com/dp/B0DV2N2FND | L48: =IF(K48="","",HYPERLINK(K48,K48))
A49: 3 | B49: B08PFJMTY3 | C49: FOXWELL Car Scanner NT604 Elite OBD2 Scanner ABS SRS Transmission, Check Engine Code Reader for Cars and Trucks, Diagnostic Scan Tool with SRS Airbag, Automotive Diagnostic Tool with Live Data | D49: foxwell | E49: Tablet | F49: 153.79738 | G49: 353118.78 | H49: 2296 | I49: 4914 | J49: 4.4 | K49: https://amazon.com/dp/B08PFJMTY3 | L49: =IF(K49="","",HYPERLINK(K49,K49))
A50: 4 | B50: B09KZTYD18 | C50: OBD2 Scanner TOPDON AD600S Scan Tool, Code Reader, Diagnostics Scanner for ABS/SRS/AT/Engine, 9 Reset Services, Oil/Brake/BMS/SAS/DPF/TPMS/ETS Reset/ABS Bleeding/Injector Coding, Free Lifetime Upgrade | D50: topdon | E50: Tablet | F50: 201.80111 | G50: 222990.23 | H50: 1105 | I50: 1864 | J50: 4.4 | K50: https://amazon.com/dp/B09KZTYD18 | L50: =IF(K50="","",HYPERLINK(K50,K50))
A51: 5 | B51: B08TR5PS5V | C51: TOPDON AD800BT 2 OBD2 Scanner, 2026 Bidirectional Scan Tool, Function as AD900 Lite AD Pro, All System Automotive Diagnostic Scanner, Active Test, 28+ Reset Service, FCA Autoauth, 2 Years Free Update | D51: topdon | E51: Tablet | F51: 379.01247 | G51: 206940.81 | H51: 546 | I51: 842 | J51: 4.4 | K51: https://amazon.com/dp/B08TR5PS5V | L51: =IF(K51="","",HYPERLINK(K51,K51))
A52: 6 | B52: B08TBRDH7W | C52: TOPDON Scanner AD800BT V2.0, Bidirectional Scan Tool, Full Systems Diagnostic Tool for All Vehicles, Automotive Diagnostic Scanner for Car, 28+ Services, FCA AutoAuth, CANFD, 2 Years Free Update | D52: topdon | E52: Tablet | F52: 320.66287 | G52: 151994.2 | H52: 474 | I52: 692 | J52: 4.4 | K52: https://amazon.com/dp/B08TBRDH7W | L52: =IF(K52="","",HYPERLINK(K52,K52))
A53: 7 | B53: B08XK3DJ42 | C53: TOPDON AD500 OBD2 Scanner, Oil SAS Throttle TPMS BMS EPB Reset, Engine ABS SRS Transmission, Diagnostic Scan Tool, AutoVIN, Car Check Engine Code Reader with Battery Test, Lifetime Wi-Fi Free Update | D53: topdon | E53: Tablet | F53: 159.11793 | G53: 150366.44 | H53: 945 | I53: 1766 | J53: 4.4 | K53: https://amazon.com/dp/B08XK3DJ42 | L53: =IF(K53="","",HYPERLINK(K53,K53))
A54: 8 | B54: B07RLF8FBC | C54: Launch OBD2 Scanner CRP123X V3.0 Elite, 2026 Lifetime Free WiFi Update Scan Tool, FCA SGW, CANFD&DoIP, SAS/Throttle/Brake/BMS/D-P-F/Oil/ABS Service Multi Systems Car Scanner, Battery Test, Auto VIN | D54: launch | E54: Tablet | F54: 209.1466 | G54: 122978.2 | H54: 588 | I54: 3489 | J54: 4.4 | K54: https://amazon.com/dp/B07RLF8FBC | L54: =IF(K54="","",HYPERLINK(K54,K54))
A55: 9 | B55: B0FGC7K873 | C55: OBD2 Scanner, MUCAR 632 Elite AI-Assisted Bidirectional Scan Tool, 15 Reset Services Oil/TPMS/EPB/BMS/SAS/Brake/Throttle Car Scanner Diagnostic Tool, AutoAuth FCA, CANFD, AutoVIN, Lifetime Free Update | D55: mucar | E55: Tablet | F55: 232.63806 | G55: 122367.62 | H55: 526 | I55: 264 | J55: 4 | K55: https://amazon.com/dp/B0FGC7K873 | L55: =IF(K55="","",HYPERLINK(K55,K55))
A56: 10 | B56: B08DCNDFVK | C56: FOXWELL NT614 Elite OBD2 Scanner for DIY Mechanics, Upgrade of NT604, 4 System Diagnostic Tool with 5 Resets (ABS Bleeding, EPB, Oil, SAS, Throttle), Read/Clear Engine/ABS/SRS/Transmission Fault Codes | D56: foxwell | E56: Tablet | F56: 177.04205 | G56: 117201.84 | H56: 662 | I56: 745 | J56: 4.3 | K56: https://amazon.com/dp/B08DCNDFVK | L56: =IF(K56="","",HYPERLINK(K56,K56))
A58: Rank By Monthly Units - May '26 ONLY
A59: Ranking | B59: ASIN | C59: Product Name | D59: Brand | E59: Type | F59: Price | G59: Est. Monthly Retail Rev | H59: Est. Monthly Units Sold | I59: # of Reviews | J59: Avg. Rating | K59: Column2 | L59: Link
A60: 1 | B60: B08PFJMTY3 | C60: FOXWELL Car Scanner NT604 Elite OBD2 Scanner ABS SRS Transmission, Check Engine Code Reader for Cars and Trucks, Diagnostic Scan Tool with SRS Airbag, Automotive Diagnostic Tool with Live Data | D60: foxwell | E60: Tablet | F60: 153.79738 | G60: 353118.78 | H60: 2296 | I60: 4914 | J60: 4.4 | K60: https://amazon.com/dp/B08PFJMTY3 | L60: =IF(K60="","",HYPERLINK(K60,K60))
A61: 2 | B61: B0DV2N2FND | C61: BLCKTEC 460T OBD2 Scanner Car Code Reader Engine ABS SRS Transmission Diagnostic Tool, 12 Reset Services, Oil/TPMS/EPB/BMS/SAS/DPF/Throttle Reset, ABS Bleeding, Battery Test, Auto VIN, Free Update | D61: blcktec | E61: Tablet | F61: 196.13548 | G61: 356182.04 | H61: 1816 | I61: 656 | J61: 4.4 | K61: https://amazon.com/dp/B0DV2N2FND | L61: =IF(K61="","",HYPERLINK(K61,K61))
A62: 3 | B62: B0C33Y285Y | C62: TOPDON Bidirectional Scan Tool, 2026 New ArtiDiag900 Lite Automotive Diagnostic Tool for Full System, Scanner for Car with Active Test, 8 Reset, Wireless OBD2 Scanner Diagnostic Tool for All Vehicles | D62: topdon | E62: Tablet | F62: 315.0536 | G62: 384680.45 | H62: 1221 | I62: 1273 | J62: 4.2 | K62: https://amazon.com/dp/B0C33Y285Y | L62: =IF(K62="","",HYPERLINK(K62,K62))
A63: 4 | B63: B09KZTYD18 | C63: OBD2 Scanner TOPDON AD600S Scan Tool, Code Reader, Diagnostics Scanner for ABS/SRS/AT/Engine, 9 Reset Services, Oil/Brake/BMS/SAS/DPF/TPMS/ETS Reset/ABS Bleeding/Injector Coding, Free Lifetime Upgrade | D63: topdon | E63: Tablet | F63: 201.80111 | G63: 222990.23 | H63: 1105 | I63: 1864 | J63: 4.4 | K63: https://amazon.com/dp/B09KZTYD18 | L63: =IF(K63="","",HYPERLINK(K63,K63))
A64: 5 | B64: B08XK3DJ42 | C64: TOPDON AD500 OBD2 Scanner, Oil SAS Throttle TPMS BMS EPB Reset, Engine ABS SRS Transmission, Diagnostic Scan Tool, AutoVIN, Car Check Engine Code Reader with Battery Test, Lifetime Wi-Fi Free Update | D64: topdon | E64: Tablet | F64: 159.11793 | G64: 150366.44 | H64: 945 | I64: 1766 | J64: 4.4 | K64: https://amazon.com/dp/B08XK3DJ42 | L64: =IF(K64="","",HYPERLINK(K64,K64))
A65: 6 | B65: B08DCNDFVK | C65: FOXWELL NT614 Elite OBD2 Scanner for DIY Mechanics, Upgrade of NT604, 4 System Diagnostic Tool with 5 Resets (ABS Bleeding, EPB, Oil, SAS, Throttle), Read/Clear Engine/ABS/SRS/Transmission Fault Codes | D65: foxwell | E65: Tablet | F65: 177.04205 | G65: 117201.84 | H65: 662 | I65: 745 | J65: 4.3 | K65: https://amazon.com/dp/B08DCNDFVK | L65: =IF(K65="","",HYPERLINK(K65,K65))
A66: 7 | B66: B0DFCMT416 | C66: XTOOL D5S OBD2 Scanner with Touchscreen, Code Reader for Cars & Trucks with 16 Resets, Crank Sensor Relearn, Throttle Relearn, EPB, FCA, CAN FD for GM, Engine ABS SRS Transmission Car Diagnostic Tool | D66: xtool | E66: Tablet | F66: 175.72467 | G66: 105786.25 | H66: 602 | I66: 455 | J66: 4.3 | K66: https://amazon.com/dp/B0DFCMT416 | L66: =IF(K66="","",HYPERLINK(K66,K66))
A67: 8 | B67: B07RLF8FBC | C67: Launch OBD2 Scanner CRP123X V3.0 Elite, 2026 Lifetime Free WiFi Update Scan Tool, FCA SGW, CANFD&DoIP, SAS/Throttle/Brake/BMS/D-P-F/Oil/ABS Service Multi Systems Car Scanner, Battery Test, Auto VIN | D67: launch | E67: Tablet | F67: 209.1466 | G67: 122978.2 | H67: 588 | I67: 3489 | J67: 4.4 | K67: https://amazon.com/dp/B07RLF8FBC | L67: =IF(K67="","",HYPERLINK(K67,K67))
A68: 9 | B68: B073GW5MTS | C68: LAUNCH CRP123 V2.0 OBD2 Scanner-2026 New Model Engine/ABS/SRS/Transmission Diagnostic Scan Tool SRS Airbag Code Reader,3 Reset Oil Service/Throttle Relearn/SAS Reset,Lifetime Free Update | D68: launch | E68: Tablet | F68: 124.90528 | G68: 68323.19 | H68: 547 | I68: 4066 | J68: 4.3 | K68: https://amazon.com/dp/B073GW5MTS | L68: =IF(K68="","",HYPERLINK(K68,K68))
A69: 10 | B69: B08TR5PS5V | C69: TOPDON AD800BT 2 OBD2 Scanner, 2026 Bidirectional Scan Tool, Function as AD900 Lite AD Pro, All System Automotive Diagnostic Scanner, Active Test, 28+ Reset Service, FCA Autoauth, 2 Years Free Update | D69: topdon | E69: Tablet | F69: 379.01247 | G69: 206940.81 | H69: 546 | I69: 842 | J69: 4.4 | K69: https://amazon.com/dp/B08TR5PS5V | L69: =IF(K69="","",HYPERLINK(K69,K69))

Sheet Handheld Total
A1: Handheld Monthly Summary
A3: Handheld Overall
B4: Avg Price | C4: Avg Price MoM | D4: Avg Price YoY | E4: Quantity/Mo | F4: Qty by % | G4: Qty MoM | H4: Qty YoY | I4: Revenue/Mo | J4: Revenue by % | L4: Revenue MoM | M4: Revenue YoY
A5: innova | B5: 194.09416 | C5: -0.098933341 | D5: -0.026077817 | E5: 7727 | F5: 0.06490005 | G5: -0.092862174 | H5: 1.0980179 | I5: 1499765.6 | J5: 0.23581383 | L5: -0.18260835 | M5: 1.0433062
A6: ancel | B6: 37.802577 | C6: -0.030383248 | D6: 0.021561431 | E6: 35682 | F6: 0.29969763 | G6: -0.060826994 | H6: -0.095857089 | I6: 1348871.5 | J6: 0.21208819 | L6: -0.089362121 | M6: -0.076362474
A7: foxwell | B7: 93.147252 | C7: 0.017198601 | D7: 0.11018679 | E7: 9535 | F7: 0.080085671 | G7: 0.088718886 | H7: 0.023617821 | I7: 888159.05 | J7: 0.13964862 | L7: 0.10744333 | M7: 0.13640699
A8: autel | B8: 56.121729 | C8: -0.055373799 | D8: -0.11049724 | E8: 6291 | F8: 0.052838905 | G8: -0.10550263 | H8: -0.14489602 | I8: 353061.8 | J8: 0.055513246 | L8: -0.15503435 | M8: -0.23938264
A9: motopower | B9: 25.51337 | C9: 0.14859982 | D9: 0.041205665 | E9: 12057 | F9: 0.10126827 | G9: -0.12242521 | H9: 0.15988456 | I9: 307614.7 | J9: 0.048367426 | L9: 0.0079822415 | M9: 0.20767837
A10: blcktec | B10: 60.074995 | C10: 0.032584959 | D10: -0.0099119097 | E10: 1009 | F10: 0.0084747186 | G10: -0.35028976 | H10: -0.55823117 | I10: 60615.67 | J10: 0.0095308317 | L10: -0.32911898 | M10: -0.56260995
A11: Other | B11: 40.67383 | C11: 0.016341739 | D11: 0.026266537 | E11: 46759 | F11: 0.39273476 | G11: 0.0015850916 | H11: 0.075537665 | I11: 1901867.6 | J11: 0.29903786 | L11: 0.017952733 | M11: 0.10378832
A12: Total Handheld | B12: 53.418074 | C12: -0.023677538 | D12: 0.11494079 | E12: 119060 | F12: 1 | G12: -0.041994223 | H12: 0.026609412 | I12: 6359955.9 | J12: 1 | L12: -0.064677441 | M12: 0.14460871
A44: Rank By Monthly Revenue - May '26 ONLY
A45: Ranking | B45: ASIN | C45: Product Name | D45: Brand | E45: Type | F45: Price | G45: Est. Monthly Retail Rev | H45: Est. Monthly Units Sold | I45: # of Reviews | J45: Avg. Rating | K45: Column2 | L45: Link
A46: 1 | B46: B07Z481NJM | C46: Innova 5610 OBD2 Bidirectional Scan Tool - Understand Your Vehicle, Pinpoint What's Wrong, and Complete Your Repairs with Less Headache, Updates Included, US-Based Technical Support | D46: innova | E46: Handheld | F46: 313.9311 | G46: 1084945.9 | H46: 3456 | I46: 3548 | J46: 4.4 | K46: https://amazon.com/dp/B07Z481NJM | L46: =IF(K46="","",HYPERLINK(K46,K46))
A47: 2 | B47: B01G5EA74I | C47: ANCEL AD310 Classic Enhanced Universal OBD II Scanner Car Engine Fault Code Reader CAN Diagnostic Scan Tool, Read and Clear Error Codes for 1996 or Newer OBD2 Protocol Vehicle (Black) | D47: ancel | E47: Handheld | F47: 27.758715 | G47: 668152.27 | H47: 24070 | I47: 64423 | J47: 4.6 | K47: https://amazon.com/dp/B01G5EA74I | L47: =IF(K47="","",HYPERLINK(K47,K47))
A48: 3 | B48: B00UJV3E12 | C48: FOXWELL NT301 OBD2 Scanner Live Data Professional Mechanic OBDII Diagnostic Code Reader Tool for Check Engine Light | D48: foxwell | E48: Handheld | F48: 65.640497 | G48: 390823.52 | H48: 5954 | I48: 29789 | J48: 4.5 | K48: https://amazon.com/dp/B00UJV3E12 | L48: =IF(K48="","",HYPERLINK(K48,K48))
A49: 4 | B49: B071FSNL73 | C49: ANCEL AD410 Enhanced OBD2 Scanner, Vehicle Code Reader for Check Engine Light, Automotive OBD II Scanner Fault Diagnosis, OBDII Scan Tool for All OBDII Cars 1996+, Black/Yellow | D49: ancel | E49: Handheld | F49: 45.525505 | G49: 301515.42 | H49: 6623 | I49: 15175 | J49: 4.5 | K49: https://amazon.com/dp/B071FSNL73 | L49: =IF(K49="","",HYPERLINK(K49,K49))
A50: 5 | B50: B07Z3HB7DR | C50: MOTOPOWER MP69033 Car OBD2 Scanner Code Reader Engine Fault Scanner CAN Diagnostic Scan Tool for All OBD II Protocol Cars Since 1996, Yellow | D50: motopower | E50: Handheld | F50: 24.501724 | G50: 264030.58 | H50: 10776 | I50: 51034 | J50: 4.6 | K50: https://amazon.com/dp/B07Z3HB7DR | L50: =IF(K50="","",HYPERLINK(K50,K50))
A51: 6 | B51: B07Z46L5FG | C51: Innova 5210 OBD2 Scanner & Engine Code Reader, Battery Tester, Live Data, Oil Reset, Car Diagnostic Tool for Most Vehicles, Bluetooth Compatible with America's Top Car Repair App | D51: innova | E51: Handheld | F51: 91.066743 | G51: 215281.78 | H51: 2364 | I51: 4034 | J51: 4.5 | K51: https://amazon.com/dp/B07Z46L5FG | L51: =IF(K51="","",HYPERLINK(K51,K51))
A52: 7 | B52: B0BY1TS725 | C52: VDIAGTOOL VD10 OBD2 Scanner Code Reader Car Diagnostic Tool Engine Fault Code Reader for Turn Off CEL with Freeze Frame/I/M Readiness for All OBDII Protocol Cars, OBD2 Scanner Diagnostic Tool | D52: vdiagtool | E52: Handheld | F52: 19.980454 | G52: 131251.6 | H52: 6569 | I52: 2686 | J52: 4.6 | K52: https://amazon.com/dp/B0BY1TS725 | L52: =IF(K52="","",HYPERLINK(K52,K52))
A53: 8 | B53: B019QCG5RE | C53: FOXWELL NT510 Elite Scan Tool fit for BMW Scanner Full Diagnostic Tool OBD2 Scanner, All System Bi-Directional Control Code Reader with All Reset Services, Battery Registration Tool fit for BMW Mini | D53: foxwell | E53: Handheld | F53: 188.9077 | G53: 119767.48 | H53: 634 | I53: 3146 | J53: 4.3 | K53: https://amazon.com/dp/B019QCG5RE | L53: =IF(K53="","",HYPERLINK(K53,K53))
A54: 9 | B54: B09YRDGY3Z | C54: Thinkdiag2 All System Bidirectional OBD2 Diagnostic Scanner for iOS & Android, THINKCAR Bluetooth Scan Tool with CAN-FD Protocol, 15+ Reset Functions, ECU Code, Active Test, AutoVIN, 1 Year Update | D54: thinkcar | E54: Handheld | F54: 159.8821 | G54: 111277.94 | H54: 696 | I54: 1417 | J54: 4.2 | K54: https://amazon.com/dp/B09YRDGY3Z | L54: =IF(K54="","",HYPERLINK(K54,K54))
A55: 10 | B55: B08JGK8PPM | C55: 2-in-1 FOXWELL NT301 Plus OBD2 Scanner Battery Tester for Cars Trucks, Check Engine Light & Battery Health Test, Code Reader Diagnostic Tool with Live Data, Without a Mechanic, Works on 1996+ Vehicle | D55: foxwell | E55: Handheld | F55: 92.877052 | G55: 93898.7 | H55: 1011 | I55: 2653 | J55: 4.5 | K55: https://amazon.com/dp/B08JGK8PPM | L55: =IF(K55="","",HYPERLINK(K55,K55))
A57: Rank By Monthly Units - May '26 ONLY
A58: Ranking | B58: ASIN | C58: Product Name | D58: Brand | E58: Type | F58: Price | G58: Est. Monthly Retail Rev | H58: Est. Monthly Units Sold | I58: # of Reviews | J58: Avg. Rating | K58: Column2 | L58: Link
A59: 1 | B59: B01G5EA74I | C59: ANCEL AD310 Classic Enhanced Universal OBD II Scanner Car Engine Fault Code Reader CAN Diagnostic Scan Tool, Read and Clear Error Codes for 1996 or Newer OBD2 Protocol Vehicle (Black) | D59: ancel | E59: Handheld | F59: 27.758715 | G59: 668152.27 | H59: 24070 | I59: 64423 | J59: 4.6 | K59: https://amazon.com/dp/B01G5EA74I | L59: =IF(K59="","",HYPERLINK(K59,K59))
A60: 2 | B60: B07Z3HB7DR | C60: MOTOPOWER MP69033 Car OBD2 Scanner Code Reader Engine Fault Scanner CAN Diagnostic Scan Tool for All OBD II Protocol Cars Since 1996, Yellow | D60: motopower | E60: Handheld | F60: 24.501724 | G60: 264030.58 | H60: 10776 | I60: 51034 | J60: 4.6 | K60: https://amazon.com/dp/B07Z3HB7DR | L60: =IF(K60="","",HYPERLINK(K60,K60))
A61: 3 | B61: B071FSNL73 | C61: ANCEL AD410 Enhanced OBD2 Scanner, Vehicle Code Reader for Check Engine Light, Automotive OBD II Scanner Fault Diagnosis, OBDII Scan Tool for All OBDII Cars 1996+, Black/Yellow | D61: ancel | E61: Handheld | F61: 45.525505 | G61: 301515.42 | H61: 6623 | I61: 15175 | J61: 4.5 | K61: https://amazon.com/dp/B071FSNL73 | L61: =IF(K61="","",HYPERLINK(K61,K61))
A62: 4 | B62: B0BY1TS725 | C62: VDIAGTOOL VD10 OBD2 Scanner Code Reader Car Diagnostic Tool Engine Fault Code Reader for Turn Off CEL with Freeze Frame/I/M Readiness for All OBDII Protocol Cars, OBD2 Scanner Diagnostic Tool | D62: vdiagtool | E62: Handheld | F62: 19.980454 | G62: 131251.6 | H62: 6569 | I62: 2686 | J62: 4.6 | K62: https://amazon.com/dp/B0BY1TS725 | L62: =IF(K62="","",HYPERLINK(K62,K62))
A63: 5 | B63: B00UJV3E12 | C63: FOXWELL NT301 OBD2 Scanner Live Data Professional Mechanic OBDII Diagnostic Code Reader Tool for Check Engine Light | D63: foxwell | E63: Handheld | F63: 65.640497 | G63: 390823.52 | H63: 5954 | I63: 29789 | J63: 4.5 | K63: https://amazon.com/dp/B00UJV3E12 | L63: =IF(K63="","",HYPERLINK(K63,K63))
A64: 6 | B64: B07Z481NJM | C64: Innova 5610 OBD2 Bidirectional Scan Tool - Understand Your Vehicle, Pinpoint What's Wrong, and Complete Your Repairs with Less Headache, Updates Included, US-Based Technical Support | D64: innova | E64: Handheld | F64: 313.9311 | G64: 1084945.9 | H64: 3456 | I64: 3548 | J64: 4.4 | K64: https://amazon.com/dp/B07Z481NJM | L64: =IF(K64="","",HYPERLINK(K64,K64))
A65: 7 | B65: B007XE8C74 | C65: Autel Professional OBD2 Scanner AL319 Code Reader, Enhanced Check and Reset Engine Fault Code, Live Data, Freeze Frame, CAN Car Diagnostic Scan Tools for All OBDII Vehicles After 1996, 2026 Upgraded | D65: autel | E65: Handheld | F65: 33.960223 | G65: 91522.8 | H65: 2695 | I65: 25900 | J65: 4.6 | K65: https://amazon.com/dp/B007XE8C74 | L65: =IF(K65="","",HYPERLINK(K65,K65))
A66: 8 | B66: B07Z46L5FG | C66: Innova 5210 OBD2 Scanner & Engine Code Reader, Battery Tester, Live Data, Oil Reset, Car Diagnostic Tool for Most Vehicles, Bluetooth Compatible with America's Top Car Repair App | D66: innova | E66: Handheld | F66: 91.066743 | G66: 215281.78 | H66: 2364 | I66: 4034 | J66: 4.5 | K66: https://amazon.com/dp/B07Z46L5FG | L66: =IF(K66="","",HYPERLINK(K66,K66))
A67: 9 | B67: B0C2V3RYLY | C67: ZMOON ZM201 Professional OBD2 Scanner Diagnostic Tool, Enhanced Check Engine Code Reader with Reset OBDII/EOBD Car Diagnostic Scan Tools for All Vehicles After 1996, 2026 Upgraded | D67: zmoon | E67: Handheld | F67: 39.19704 | G67: 52837.61 | H67: 1348 | I67: 2822 | J67: 4.5 | K67: https://amazon.com/dp/B0C2V3RYLY | L67: =IF(K67="","",HYPERLINK(K67,K67))
A68: 10 | B68: B0BX3K8VGJ | C68: ANCEL AD410 PRO OBD2 Scanner and Battery Tester, 2-in-1 Car Diagnostic Tool, Check Engine Light, EVAP Test, Live Data, 12V Battery Analyzer with Cranking & Charging System Test for Car Motorcycle | D68: ancel | E68: Handheld | F68: 63.080853 | G68: 65793.33 | H68: 1043 | I68: 4132 | J68: 4.6 | K68: https://amazon.com/dp/B0BX3K8VGJ | L68: =IF(K68="","",HYPERLINK(K68,K68))
A70: Handheld $75+
B71: Avg Price | C71: Avg Price MoM | D71: Avg Price YoY | E71: Quantity/Mo | F71: Qty by % | G71: Qty MoM | H71: Qty YoY | I71: Revenue/Mo | J71: Revenue by % | L71: Revenue MoM | M71: Revenue YoY
A72: innova | B72: 212.87107 | C72: -0.027957643 | D72: 0.031427078 | E72: 6875 | F72: 0.38728031 | G72: -0.1734792 | H72: 0.96597083 | I72: 1463488.6 | J72: 0.46019353 | L72: -0.19658678 | M72: 1.0277556
A73: foxwell | B73: 153.12191 | C73: 0.0065628425 | D73: 0.072558376 | E73: 3088 | F73: 0.17395223 | G73: 0.12005803 | H73: 0.24465941 | I73: 472840.47 | J73: 0.14868454 | L73: 0.1274088 | M73: 0.33496988
A74: autel | B74: 171.94188 | C74: -0.11391119 | D74: -0.066340479 | E74: 936 | F74: 0.052726453 | G74: -0.061183551 | H74: -0.33190578 | I74: 160937.6 | J74: 0.050606777 | L74: -0.16812525 | M74: -0.37622747
A75: ancel | B75: 121.74998 | C75: -0.037622011 | D75: -0.091394693 | E75: 1272 | F75: 0.071653898 | G75: -0.28013582 | H75: -0.44186047 | I75: 154865.97 | J75: 0.048697555 | L75: -0.30721856 | M75: -0.49287146
A76: thinkcar | B76: 182.90722 | C76: 0.11058191 | D76: 0.24000686 | E76: 727 | F76: 0.040953132 | G76: 0.23850085 | H76: 0.15213946 | I76: 132973.55 | J76: 0.041813491 | L76: 0.37545664 | M76: 0.42866083
A77: autel | B77: 35.877535 | C77: -0.034856642 | D77: 0.036452876 | E77: 5355 | F77: 0.052858609 | G77: -0.11282306 | H77: -0.10090665 | I77: 192124.2 | J77: 0.060420274 | L77: -0.14374707 | M77: -0.06813211
A78: ='Summary'!A8 | B78: ='Summary'!B8 | C78: ='Summary'!C8 | D78: ='Summary'!D8 | E78: =SUM(E72:E77) | F78: =SUM(F72:F77) | G78: ='Summary'!G8 | H78: ='Summary'!H8 | I78: =SUM(I72:I77) | J78: =SUM(J72:J77) | L78: ='Summary'!K8 | M78: ='Summary'!L8
A80: Handheld $75-
B81: Avg Price | C81: Avg Price MoM | D81: Avg Price YoY | E81: Quantity/Mo | F81: Qty by % | G81: Qty MoM | H81: Qty YoY | I81: Revenue/Mo | J81: Revenue by % | L81: Revenue MoM | M81: Revenue YoY
A82: vdiagtool | B82: 21.275356 | C82: 0.22820047 | D82: -0.28434839 | E82: 6874 | F82: 0.067852489 | G82: 0.01973001 | H82: 2.5233214 | I82: 146246.8 | J82: 0.045992497 | L82: 0.25243288 | M82: 1.5214706
A83: blcktec | B83: 60.074995 | C83: 0.032584959 | D83: 0.52946639 | E83: 1009 | F83: 0.0099597268 | G83: -0.35028976 | H83: -0.23560606 | I83: 60615.67 | J83: 0.019062749 | L83: -0.32911898 | M83: 0.16911484
A84: innova | B84: 42.578556 | C84: -0.35632691 | D84: -0.35409692 | E84: 852 | F84: 0.0084099972 | G84: 3.26 | H84: 3.5806452 | I84: 36276.93 | J84: 0.011408568 | L84: 1.7420474 | M84: 1.9586528
A85: Other | B85: 24.127578 | C85: -0.014671182 | D85: -0.089313251 | E85: 34305 | F85: 0.33862084 | G85: -0.0024426415 | H85: -0.083513665 | I85: 827696.57 | J85: 0.26029856 | L85: -0.017077987 | M85: -0.16536804
A86: innova | B86: 194.09416 | C86: -0.098933341 | D86: -0.026077817 | E86: 7727 | F86: 0.06490005 | G86: -0.092862174 | H86: 1.0980179 | I86: 1499765.6 | J86: 0.23581383 | L86: -0.18260835 | M86: 1.0433062
A87: ancel | B87: 37.802577 | C87: -0.030383248 | D87: 0.021561431 | E87: 35682 | F87: 0.29969763 | G87: -0.060826994 | H87: -0.095857089 | I87: 1348871.5 | J87: 0.21208819 | L87: -0.089362121 | M87: -0.076362474
A88: foxwell | B88: 93.147252 | C88: 0.017198601 | D88: 0.11018679 | E88: 9535 | F88: 0.080085671 | G88: 0.088718886 | H88: 0.023617821 | I88: 888159.05 | J88: 0.13964862 | L88: 0.10744333 | M88: 0.13640699
A89: autel | B89: 56.121729 | C89: -0.055373799 | D89: -0.11049724 | E89: 6291 | F89: 0.052838905 | G89: -0.10550263 | H89: -0.14489602 | I89: 353061.8 | J89: 0.055513246 | L89: -0.15503435 | M89: -0.23938264
A90: ='Summary'!A9 | B90: ='Summary'!B9 | C90: ='Summary'!C9 | D90: ='Summary'!D9 | E90: =SUM(E82:E89) | F90: =SUM(F82:F89) | G90: ='Summary'!G9 | H90: ='Summary'!H9 | I90: =SUM(I82:I89) | J90: =SUM(J82:J89) | L90: ='Summary'!K9 | M90: ='Summary'!L9

Sheet Handheld $75+
A1: Handheld $75+ Monthly Summary
A3: ='Handheld Total'!A70
B4: Avg Price | C4: Avg Price MoM | D4: Avg Price YoY | E4: Quantity/Mo | F4: Qty by % | G4: Qty MoM | H4: Qty YoY | I4: Revenue/Mo | J4: Revenue by % | L4: Revenue MoM | M4: Revenue YoY
A5: ='Handheld Total'!A72 | B5: ='Handheld Total'!B72 | C5: ='Handheld Total'!C72 | D5: ='Handheld Total'!D72 | E5: ='Handheld Total'!E72 | F5: ='Handheld Total'!F72 | G5: ='Handheld Total'!G72 | H5: ='Handheld Total'!H72 | ... M5: ='Handheld Total'!M72
A6: ='Handheld Total'!A73 | B6: ='Handheld Total'!B73 | C6: ='Handheld Total'!C73 | D6: ='Handheld Total'!D73 | E6: ='Handheld Total'!E73 | F6: ='Handheld Total'!F73 | G6: ='Handheld Total'!G73 | H6: ='Handheld Total'!H73 | ... M6: ='Handheld Total'!M73
A7: ='Handheld Total'!A74 | B7: ='Handheld Total'!B74 | C7: ='Handheld Total'!C74 | D7: ='Handheld Total'!D74 | E7: ='Handheld Total'!E74 | F7: ='Handheld Total'!F74 | G7: ='Handheld Total'!G74 | H7: ='Handheld Total'!H74 | ... M7: ='Handheld Total'!M74
A8: ='Handheld Total'!A75 | B8: ='Handheld Total'!B75 | C8: ='Handheld Total'!C75 | D8: ='Handheld Total'!D75 | E8: ='Handheld Total'!E75 | F8: ='Handheld Total'!F75 | G8: ='Handheld Total'!G75 | H8: ='Handheld Total'!H75 | ... M8: ='Handheld Total'!M75
A9: ='Handheld Total'!A76 | B9: ='Handheld Total'!B76 | C9: ='Handheld Total'!C76 | D9: ='Handheld Total'!D76 | E9: ='Handheld Total'!E76 | F9: ='Handheld Total'!F76 | G9: ='Handheld Total'!G76 | H9: ='Handheld Total'!H76 | ... M9: ='Handheld Total'!M76
A10: ='Handheld Total'!A77 | B10: ='Handheld Total'!B77 | C10: ='Handheld Total'!C77 | D10: ='Handheld Total'!D77 | E10: ='Handheld Total'!E77 | F10: ='Handheld Total'!F77 | G10: ='Handheld Total'!G77 | H10: ='Handheld Total'!H77 | ... M10: ='Handheld Total'!M77
A11: ='Handheld Total'!A78 | B11: ='Handheld Total'!B78 | C11: ='Handheld Total'!C78 | D11: ='Handheld Total'!D78 | E11: ='Handheld Total'!E78 | F11: ='Handheld Total'!F78 | G11: ='Handheld Total'!G78 | H11: ='Handheld Total'!H78 | ... M11: ='Handheld Total'!M78
A43: Rank By Monthly Revenue - May '26 ONLY
A44: Ranking | B44: ASIN | C44: Product Name | D44: Brand | E44: Type | F44: Price | G44: Est. Monthly Retail Rev | H44: Est. Monthly Units Sold | I44: # of Reviews | J44: Avg. Rating | K44: Column2 | L44: Link
A45: 1 | B45: B07Z481NJM | C45: Innova 5610 OBD2 Bidirectional Scan Tool - Understand Your Vehicle, Pinpoint What's Wrong, and Complete Your Repairs with Less Headache, Updates Included, US-Based Technical Support | D45: innova | E45: Handheld | F45: 313.9311 | G45: 1084945.9 | H45: 3456 | I45: 3548 | J45: 4.4 | K45: https://amazon.com/dp/B07Z481NJM | L45: =IF(K45="","",HYPERLINK(K45,K45))
A46: 2 | B46: B07Z46L5FG | C46: Innova 5210 OBD2 Scanner & Engine Code Reader, Battery Tester, Live Data, Oil Reset, Car Diagnostic Tool for Most Vehicles, Bluetooth Compatible with America's Top Car Repair App | D46: innova | E46: Handheld | F46: 91.066743 | G46: 215281.78 | H46: 2364 | I46: 4034 | J46: 4.5 | K46: https://amazon.com/dp/B07Z46L5FG | L46: =IF(K46="","",HYPERLINK(K46,K46))
A47: 3 | B47: B019QCG5RE | C47: FOXWELL NT510 Elite Scan Tool fit for BMW Scanner Full Diagnostic Tool OBD2 Scanner, All System Bi-Directional Control Code Reader with All Reset Services, Battery Registration Tool fit for BMW Mini | D47: foxwell | E47: Handheld | F47: 188.9077 | G47: 119767.48 | H47: 634 | I47: 3146 | J47: 4.3 | K47: https://amazon.com/dp/B019QCG5RE | L47: =IF(K47="","",HYPERLINK(K47,K47))
A48: 4 | B48: B09YRDGY3Z | C48: Thinkdiag2 All System Bidirectional OBD2 Diagnostic Scanner for iOS & Android, THINKCAR Bluetooth Scan Tool with CAN-FD Protocol, 15+ Reset Functions, ECU Code, Active Test, AutoVIN, 1 Year Update | D48: thinkcar | E48: Handheld | F48: 159.8821 | G48: 111277.94 | H48: 696 | I48: 1417 | J48: 4.2 | K48: https://amazon.com/dp/B09YRDGY3Z | L48: =IF(K48="","",HYPERLINK(K48,K48))
A49: 5 | B49: B08JGK8PPM | C49: 2-in-1 FOXWELL NT301 Plus OBD2 Scanner Battery Tester for Cars Trucks, Check Engine Light & Battery Health Test, Code Reader Diagnostic Tool with Live Data, Without a Mechanic, Works on 1996+ Vehicle | D49: foxwell | E49: Handheld | F49: 92.877052 | G49: 93898.7 | H49: 1011 | I49: 2653 | J49: 4.5 | K49: https://amazon.com/dp/B08JGK8PPM | L49: =IF(K49="","",HYPERLINK(K49,K49))
A50: 6 | B50: B07ZL7CLYR | C50: Innova 5410 All-System OBD2 Scanner Diagnostic Tool for Cars & Trucks – Automotive Scan Tools for Engine, ABS, SRS & Transmission, Bluetooth Compatible with America's Top Car Repair App | D50: innova | E50: Handheld | F50: 156.81471 | G50: 90952.53 | H50: 580 | I50: 707 | J50: 4.4 | K50: https://amazon.com/dp/B07ZL7CLYR | L50: =IF(K50="","",HYPERLINK(K50,K50))
A51: 7 | B51: B07CSMJJK9 | C51: 2026 FOXWELL NT630 Plus OBD2 Scanner with ABS and SRS, ABS Auto Bleed Scan Tool Brake Code Reader, Car Scanner Diagnostic Tool Bidirectional Live Data with SAS Oil Check Engine Light Reset | D51: foxwell | E51: Handheld | F51: 149.8754 | G51: 74038.45 | H51: 494 | I51: 3951 | J51: 4.2 | K51: https://amazon.com/dp/B07CSMJJK9 | L51: =IF(K51="","",HYPERLINK(K51,K51))
A52: 8 | B52: B0D176ZCXQ | C52: LAUNCH Creader Elite Bi-Directional OBD2 Scanner for Toyota Lexus, 2026 Full System Diagnostic Scan Tool, All Reset Service Code Reader, Battery Registration,AUTO VIN,Lifetime Free Update | D52: launch | E52: Handheld | F52: 156.83556 | G52: 51598.9 | H52: 329 | I52: 371 | J52: 4.3 | K52: https://amazon.com/dp/B0D176ZCXQ | L52: =IF(K52="","",HYPERLINK(K52,K52))
A53: 9 | B53: B08B5RMFBG | C53: FOXWELL NT510 Elite fit for Honda Acura OBD2 Scanner, Bidirectional Full System Engine ABS TCM SRS Diagnostic Scan Tool, All Reset Crankshaft Relearn Oil EPB TPS ABS Bleeding, Code Reader, Free Update | D53: foxwell | E53: Handheld | F53: 189.86864 | G53: 47467.16 | H53: 250 | I53: 474 | J53: 4.2 | K53: https://amazon.com/dp/B08B5RMFBG | L53: =IF(K53="","",HYPERLINK(K53,K53))
A54: 10 | B54: B0FCXMGGPN | C54: OBDMATE OBD2 Scanner with ABS SRS Transmission, Reset Fault Lights | Check Engine Code Reader with Full OBDII Functions | DLC Pin Test | Battery Voltage Check, Car Diagnostic Tool | D54: obdmate | E54: Handheld | F54: 109.48539 | G54: 39414.74 | H54: 360 | I54: 162 | J54: 4.5 | K54: https://amazon.com/dp/B0FCXMGGPN | L54: =IF(K54="","",HYPERLINK(K54,K54))
A56: Rank By Monthly Units - May '26 ONLY
A57: Ranking | B57: ASIN | C57: Product Name | D57: Brand | E57: Type | F57: Price | G57: Est. Monthly Retail Rev | H57: Est. Monthly Units Sold | I57: # of Reviews | J57: Avg. Rating | K57: Column2 | L57: Link
A58: 1 | B58: B07Z481NJM | C58: Innova 5610 OBD2 Bidirectional Scan Tool - Understand Your Vehicle, Pinpoint What's Wrong, and Complete Your Repairs with Less Headache, Updates Included, US-Based Technical Support | D58: innova | E58: Handheld | F58: 313.9311 | G58: 1084945.9 | H58: 3456 | I58: 3548 | J58: 4.4 | K58: https://amazon.com/dp/B07Z481NJM | L58: =IF(K58="","",HYPERLINK(K58,K58))
A59: 2 | B59: B07Z46L5FG | C59: Innova 5210 OBD2 Scanner & Engine Code Reader, Battery Tester, Live Data, Oil Reset, Car Diagnostic Tool for Most Vehicles, Bluetooth Compatible with America's Top Car Repair App | D59: innova | E59: Handheld | F59: 91.066743 | G59: 215281.78 | H59: 2364 | I59: 4034 | J59: 4.5 | K59: https://amazon.com/dp/B07Z46L5FG | L59: =IF(K59="","",HYPERLINK(K59,K59))
A60: 3 | B60: B08JGK8PPM | C60: 2-in-1 FOXWELL NT301 Plus OBD2 Scanner Battery Tester for Cars Trucks, Check Engine Light & Battery Health Test, Code Reader Diagnostic Tool with Live Data, Without a Mechanic, Works on 1996+ Vehicle | D60: foxwell | E60: Handheld | F60: 92.877052 | G60: 93898.7 | H60: 1011 | I60: 2653 | J60: 4.5 | K60: https://amazon.com/dp/B08JGK8PPM | L60: =IF(K60="","",HYPERLINK(K60,K60))
A61: 4 | B61: B09YRDGY3Z | C61: Thinkdiag2 All System Bidirectional OBD2 Diagnostic Scanner for iOS & Android, THINKCAR Bluetooth Scan Tool with CAN-FD Protocol, 15+ Reset Functions, ECU Code, Active Test, AutoVIN, 1 Year Update | D61: thinkcar | E61: Handheld | F61: 159.8821 | G61: 111277.94 | H61: 696 | I61: 1417 | J61: 4.2 | K61: https://amazon.com/dp/B09YRDGY3Z | L61: =IF(K61="","",HYPERLINK(K61,K61))
A62: 5 | B62: B019QCG5RE | C62: FOXWELL NT510 Elite Scan Tool fit for BMW Scanner Full Diagnostic Tool OBD2 Scanner, All System Bi-Directional Control Code Reader with All Reset Services, Battery Registration Tool fit for BMW Mini | D62: foxwell | E62: Handheld | F62: 188.9077 | G62: 119767.48 | H62: 634 | I62: 3146 | J62: 4.3 | K62: https://amazon.com/dp/B019QCG5RE | L62: =IF(K62="","",HYPERLINK(K62,K62))
A63: 6 | B63: B07ZL7CLYR | C63: Innova 5410 All-System OBD2 Scanner Diagnostic Tool for Cars & Trucks – Automotive Scan Tools for Engine, ABS, SRS & Transmission, Bluetooth Compatible with America's Top Car Repair App | D63: innova | E63: Handheld | F63: 156.81471 | G63: 90952.53 | H63: 580 | I63: 707 | J63: 4.4 | K63: https://amazon.com/dp/B07ZL7CLYR | L63: =IF(K63="","",HYPERLINK(K63,K63))
A64: 7 | B64: B07CSMJJK9 | C64: 2026 FOXWELL NT630 Plus OBD2 Scanner with ABS and SRS, ABS Auto Bleed Scan Tool Brake Code Reader, Car Scanner Diagnostic Tool Bidirectional Live Data with SAS Oil Check Engine Light Reset | D64: foxwell | E64: Handheld | F64: 149.8754 | G64: 74038.45 | H64: 494 | I64: 3951 | J64: 4.2 | K64: https://amazon.com/dp/B07CSMJJK9 | L64: =IF(K64="","",HYPERLINK(K64,K64))
A65: 8 | B65: B0FCXMGGPN | C65: OBDMATE OBD2 Scanner with ABS SRS Transmission, Reset Fault Lights | Check Engine Code Reader with Full OBDII Functions | DLC Pin Test | Battery Voltage Check, Car Diagnostic Tool | D65: obdmate | E65: Handheld | F65: 109.48539 | G65: 39414.74 | H65: 360 | I65: 162 | J65: 4.5 | K65: https://amazon.com/dp/B0FCXMGGPN | L65: =IF(K65="","",HYPERLINK(K65,K65))
A66: 9 | B66: B08925H3H1 | C66: ANCEL BM500 OBD2 Scanner for BMW & MINI, Simplified Battery Registration, EPB, Oil, Throttle, PCM Resets, I/M Readiness, Full System Diagnostics for Engine, Transmission, ABS, SRS, DSC & More | D66: ancel | E66: Handheld | F66: 104.30181 | G66: 36401.33 | H66: 349 | I66: 886 | J66: 4.5 | K66: https://amazon.com/dp/B08925H3H1 | L66: =IF(K66="","",HYPERLINK(K66,K66))
A67: 10 | B67: B0D176ZCXQ | C67: LAUNCH Creader Elite Bi-Directional OBD2 Scanner for Toyota Lexus, 2026 Full System Diagnostic Scan Tool, All Reset Service Code Reader, Battery Registration,AUTO VIN,Lifetime Free Update | D67: launch | E67: Handheld | F67: 156.83556 | G67: 51598.9 | H67: 329 | I67: 371 | J67: 4.3 | K67: https://amazon.com/dp/B0D176ZCXQ | L67: =IF(K67="","",HYPERLINK(K67,K67))

Sheet Handheld $75-
A1: Handheld $75- Monthly Summary
A3: ='Handheld Total'!A80
B4: Avg Price | C4: Avg Price MoM | D4: Avg Price YoY | E4: Quantity/Mo | F4: Qty by % | G4: Qty MoM | H4: Qty YoY | I4: Revenue/Mo | J4: Revenue by % | L4: Revenue MoM | M4: Revenue YoY
A5: ='Handheld Total'!A82 | B5: ='Handheld Total'!B82 | C5: ='Handheld Total'!C82 | D5: ='Handheld Total'!D82 | E5: ='Handheld Total'!E82 | F5: ='Handheld Total'!F82 | G5: ='Handheld Total'!G82 | H5: ='Handheld Total'!H82 | ... M5: ='Handheld Total'!M82
A6: ='Handheld Total'!A83 | B6: ='Handheld Total'!B83 | C6: ='Handheld Total'!C83 | D6: ='Handheld Total'!D83 | E6: ='Handheld Total'!E83 | F6: ='Handheld Total'!F83 | G6: ='Handheld Total'!G83 | H6: ='Handheld Total'!H83 | ... M6: ='Handheld Total'!M83
A7: ='Handheld Total'!A84 | B7: ='Handheld Total'!B84 | C7: ='Handheld Total'!C84 | D7: ='Handheld Total'!D84 | E7: ='Handheld Total'!E84 | F7: ='Handheld Total'!F84 | G7: ='Handheld Total'!G84 | H7: ='Handheld Total'!H84 | ... M7: ='Handheld Total'!M84
A8: ='Handheld Total'!A85 | B8: ='Handheld Total'!B85 | C8: ='Handheld Total'!C85 | D8: ='Handheld Total'!D85 | E8: ='Handheld Total'!E85 | F8: ='Handheld Total'!F85 | G8: ='Handheld Total'!G85 | H8: ='Handheld Total'!H85 | ... M8: ='Handheld Total'!M85
A9: ='Handheld Total'!A86 | B9: ='Handheld Total'!B86 | C9: ='Handheld Total'!C86 | D9: ='Handheld Total'!D86 | E9: ='Handheld Total'!E86 | F9: ='Handheld Total'!F86 | G9: ='Handheld Total'!G86 | H9: ='Handheld Total'!H86 | ... M9: ='Handheld Total'!M86
A10: ='Handheld Total'!A87 | B10: ='Handheld Total'!B87 | C10: ='Handheld Total'!C87 | D10: ='Handheld Total'!D87 | E10: ='Handheld Total'!E87 | F10: ='Handheld Total'!F87 | G10: ='Handheld Total'!G87 | H10: ='Handheld Total'!H87 | ... M10: ='Handheld Total'!M87
A11: ='Handheld Total'!A88 | B11: ='Handheld Total'!B88 | C11: ='Handheld Total'!C88 | D11: ='Handheld Total'!D88 | E11: ='Handheld Total'!E88 | F11: ='Handheld Total'!F88 | G11: ='Handheld Total'!G88 | H11: ='Handheld Total'!H88 | ... M11: ='Handheld Total'!M88
A12: ='Handheld Total'!A89 | B12: ='Handheld Total'!B89 | C12: ='Handheld Total'!C89 | D12: ='Handheld Total'!D89 | E12: ='Handheld Total'!E89 | F12: ='Handheld Total'!F89 | G12: ='Handheld Total'!G89 | H12: ='Handheld Total'!H89 | ... M12: ='Handheld Total'!M89
A13: ='Handheld Total'!A90 | B13: ='Handheld Total'!B90 | C13: ='Handheld Total'!C90 | D13: ='Handheld Total'!D90 | E13: ='Handheld Total'!E90 | F13: ='Handheld Total'!F90 | G13: ='Handheld Total'!G90 | H13: ='Handheld Total'!H90 | ... M13: ='Handheld Total'!M90
A45: Rank By Monthly Revenue - May '26 ONLY
A46: Ranking | B46: ASIN | C46: Product Name | D46: Brand | E46: Type | F46: Price | G46: Est. Monthly Retail Rev | H46: Est. Monthly Units Sold | I46: # of Reviews | J46: Avg. Rating | K46: Column2 | L46: Link
A47: 1 | B47: B01G5EA74I | C47: ANCEL AD310 Classic Enhanced Universal OBD II Scanner Car Engine Fault Code Reader CAN Diagnostic Scan Tool, Read and Clear Error Codes for 1996 or Newer OBD2 Protocol Vehicle (Black) | D47: ancel | E47: Handheld | F47: 27.758715 | G47: 668152.27 | H47: 24070 | I47: 64423 | J47: 4.6 | K47: https://amazon.com/dp/B01G5EA74I | L47: =IF(K47="","",HYPERLINK(K47,K47))
A48: 2 | B48: B00UJV3E12 | C48: FOXWELL NT301 OBD2 Scanner Live Data Professional Mechanic OBDII Diagnostic Code Reader Tool for Check Engine Light | D48: foxwell | E48: Handheld | F48: 65.640497 | G48: 390823.52 | H48: 5954 | I48: 29789 | J48: 4.5 | K48: https://amazon.com/dp/B00UJV3E12 | L48: =IF(K48="","",HYPERLINK(K48,K48))
A49: 3 | B49: B071FSNL73 | C49: ANCEL AD410 Enhanced OBD2 Scanner, Vehicle Code Reader for Check Engine Light, Automotive OBD II Scanner Fault Diagnosis, OBDII Scan Tool for All OBDII Cars 1996+, Black/Yellow | D49: ancel | E49: Handheld | F49: 45.525505 | G49: 301515.42 | H49: 6623 | I49: 15175 | J49: 4.5 | K49: https://amazon.com/dp/B071FSNL73 | L49: =IF(K49="","",HYPERLINK(K49,K49))
A50: 4 | B50: B07Z3HB7DR | C50: MOTOPOWER MP69033 Car OBD2 Scanner Code Reader Engine Fault Scanner CAN Diagnostic Scan Tool for All OBD II Protocol Cars Since 1996, Yellow | D50: motopower | E50: Handheld | F50: 24.501724 | G50: 264030.58 | H50: 10776 | I50: 51034 | J50: 4.6 | K50: https://amazon.com/dp/B07Z3HB7DR | L50: =IF(K50="","",HYPERLINK(K50,K50))
A51: 5 | B51: B0BY1TS725 | C51: VDIAGTOOL VD10 OBD2 Scanner Code Reader Car Diagnostic Tool Engine Fault Code Reader for Turn Off CEL with Freeze Frame/I/M Readiness for All OBDII Protocol Cars, OBD2 Scanner Diagnostic Tool | D51: vdiagtool | E51: Handheld | F51: 19.980454 | G51: 131251.6 | H51: 6569 | I51: 2686 | J51: 4.6 | K51: https://amazon.com/dp/B0BY1TS725 | L51: =IF(K51="","",HYPERLINK(K51,K51))
A52: 6 | B52: B007XE8C74 | C52: Autel Professional OBD2 Scanner AL319 Code Reader, Enhanced Check and Reset Engine Fault Code, Live Data, Freeze Frame, CAN Car Diagnostic Scan Tools for All OBDII Vehicles After 1996, 2026 Upgraded | D52: autel | E52: Handheld | F52: 33.960223 | G52: 91522.8 | H52: 2695 | I52: 25900 | J52: 4.6 | K52: https://amazon.com/dp/B007XE8C74 | L52: =IF(K52="","",HYPERLINK(K52,K52))
A53: 7 | B53: B0BX3K8VGJ | C53: ANCEL AD410 PRO OBD2 Scanner and Battery Tester, 2-in-1 Car Diagnostic Tool, Check Engine Light, EVAP Test, Live Data, 12V Battery Analyzer with Cranking & Charging System Test for Car Motorcycle | D53: ancel | E53: Handheld | F53: 63.080853 | G53: 65793.33 | H53: 1043 | I53: 4132 | J53: 4.6 | K53: https://amazon.com/dp/B0BX3K8VGJ | L53: =IF(K53="","",HYPERLINK(K53,K53))
A54: 8 | B54: B07BS7PDC2 | C54: ANCEL VD500 OBD2 Scanner Diagnostic Tool for Volkswagen VW Audi Skoda Seat Diagnosis Check Engine Light EPB ABS SRS Code Reader Oil Throttle Position Adaption Brake Pad Reset | D54: ancel | E54: Handheld | F54: 63.380582 | G54: 56662.24 | H54: 894 | I54: 6359 | J54: 4.5 | K54: https://amazon.com/dp/B07BS7PDC2 | L54: =IF(K54="","",HYPERLINK(K54,K54))
A55: 9 | B55: B0C2V3RYLY | C55: ZMOON ZM201 Professional OBD2 Scanner Diagnostic Tool, Enhanced Check Engine Code Reader with Reset OBDII/EOBD Car Diagnostic Scan Tools for All Vehicles After 1996, 2026 Upgraded | D55: zmoon | E55: Handheld | F55: 39.19704 | G55: 52837.61 | H55: 1348 | I55: 2822 | J55: 4.5 | K55: https://amazon.com/dp/B0C2V3RYLY | L55: =IF(K55="","",HYPERLINK(K55,K55))
A56: 10 | B56: B0GL2FW97F | C56: 2-in-1 OBD2 Scanner with Battery Tester: 1S Read & Clear Check Engine Codes + Test Battery in 3 Mins - DIY Car Diagnostic Tool with Cold Cranking Amps for Pre-Trip Safety on 1996+ Vehicles | D56: yakry | E56: Handheld | F56: 48.721093 | G56: 50377.61 | H56: 1034 | I56: 58 | J56: 4.6 | K56: https://amazon.com/dp/B0GL2FW97F | L56: =IF(K56="","",HYPERLINK(K56,K56))
A58: Rank By Monthly Units - May '26 ONLY
A59: Ranking | B59: ASIN | C59: Product Name | D59: Brand | E59: Type | F59: Price | G59: Est. Monthly Retail Rev | H59: Est. Monthly Units Sold | I59: # of Reviews | J59: Avg. Rating | K59: Column2 | L59: Link
A60: 1 | B60: B01G5EA74I | C60: ANCEL AD310 Classic Enhanced Universal OBD II Scanner Car Engine Fault Code Reader CAN Diagnostic Scan Tool, Read and Clear Error Codes for 1996 or Newer OBD2 Protocol Vehicle (Black) | D60: ancel | E60: Handheld | F60: 27.758715 | G60: 668152.27 | H60: 24070 | I60: 64423 | J60: 4.6 | K60: https://amazon.com/dp/B01G5EA74I | L60: =IF(K60="","",HYPERLINK(K60,K60))
A61: 2 | B61: B07Z3HB7DR | C61: MOTOPOWER MP69033 Car OBD2 Scanner Code Reader Engine Fault Scanner CAN Diagnostic Scan Tool for All OBD II Protocol Cars Since 1996, Yellow | D61: motopower | E61: Handheld | F61: 24.501724 | G61: 264030.58 | H61: 10776 | I61: 51034 | J61: 4.6 | K61: https://amazon.com/dp/B07Z3HB7DR | L61: =IF(K61="","",HYPERLINK(K61,K61))
A62: 3 | B62: B071FSNL73 | C62: ANCEL AD410 Enhanced OBD2 Scanner, Vehicle Code Reader for Check Engine Light, Automotive OBD II Scanner Fault Diagnosis, OBDII Scan Tool for All OBDII Cars 1996+, Black/Yellow | D62: ancel | E62: Handheld | F62: 45.525505 | G62: 301515.42 | H62: 6623 | I62: 15175 | J62: 4.5 | K62: https://amazon.com/dp/B071FSNL73 | L62: =IF(K62="","",HYPERLINK(K62,K62))
A63: 4 | B63: B0BY1TS725 | C63: VDIAGTOOL VD10 OBD2 Scanner Code Reader Car Diagnostic Tool Engine Fault Code Reader for Turn Off CEL with Freeze Frame/I/M Readiness for All OBDII Protocol Cars, OBD2 Scanner Diagnostic Tool | D63: vdiagtool | E63: Handheld | F63: 19.980454 | G63: 131251.6 | H63: 6569 | I63: 2686 | J63: 4.6 | K63: https://amazon.com/dp/B0BY1TS725 | L63: =IF(K63="","",HYPERLINK(K63,K63))
A64: 5 | B64: B00UJV3E12 | C64: FOXWELL NT301 OBD2 Scanner Live Data Professional Mechanic OBDII Diagnostic Code Reader Tool for Check Engine Light | D64: foxwell | E64: Handheld | F64: 65.640497 | G64: 390823.52 | H64: 5954 | I64: 29789 | J64: 4.5 | K64: https://amazon.com/dp/B00UJV3E12 | L64: =IF(K64="","",HYPERLINK(K64,K64))
A65: 6 | B65: B007XE8C74 | C65: Autel Professional OBD2 Scanner AL319 Code Reader, Enhanced Check and Reset Engine Fault Code, Live Data, Freeze Frame, CAN Car Diagnostic Scan Tools for All OBDII Vehicles After 1996, 2026 Upgraded | D65: autel | E65: Handheld | F65: 33.960223 | G65: 91522.8 | H65: 2695 | I65: 25900 | J65: 4.6 | K65: https://amazon.com/dp/B007XE8C74 | L65: =IF(K65="","",HYPERLINK(K65,K65))
A66: 7 | B66: B0C2V3RYLY | C66: ZMOON ZM201 Professional OBD2 Scanner Diagnostic Tool, Enhanced Check Engine Code Reader with Reset OBDII/EOBD Car Diagnostic Scan Tools for All Vehicles After 1996, 2026 Upgraded | D66: zmoon | E66: Handheld | F66: 39.19704 | G66: 52837.61 | H66: 1348 | I66: 2822 | J66: 4.5 | K66: https://amazon.com/dp/B0C2V3RYLY | L66: =IF(K66="","",HYPERLINK(K66,K66))
A67: 8 | B67: B0BX3K8VGJ | C67: ANCEL AD410 PRO OBD2 Scanner and Battery Tester, 2-in-1 Car Diagnostic Tool, Check Engine Light, EVAP Test, Live Data, 12V Battery Analyzer with Cranking & Charging System Test for Car Motorcycle | D67: ancel | E67: Handheld | F67: 63.080853 | G67: 65793.33 | H67: 1043 | I67: 4132 | J67: 4.6 | K67: https://amazon.com/dp/B0BX3K8VGJ | L67: =IF(K67="","",HYPERLINK(K67,K67))
A68: 9 | B68: B0GL2FW97F | C68: 2-in-1 OBD2 Scanner with Battery Tester: 1S Read & Clear Check Engine Codes + Test Battery in 3 Mins - DIY Car Diagnostic Tool with Cold Cranking Amps for Pre-Trip Safety on 1996+ Vehicles | D68: yakry | E68: Handheld | F68: 48.721093 | G68: 50377.61 | H68: 1034 | I68: 58 | J68: 4.6 | K68: https://amazon.com/dp/B0GL2FW97F | L68: =IF(K68="","",HYPERLINK(K68,K68))
A69: 10 | B69: B0DHQSQYTR | C69: MOTOPOWER MP69033 Pro OBD2 Scanner Code Reader Check Engine Fault Light Diagnostic Scan Tool with Battery Tester | D69: motopower | E69: Handheld | F69: 32.819892 | G69: 30424.04 | H69: 927 | I69: 938 | J69: 4.5 | K69: https://amazon.com/dp/B0DHQSQYTR | L69: =IF(K69="","",HYPERLINK(K69,K69))

Sheet Dongle
A1: Dongle Monthly Summary
A3: Dongle Overall
B4: Avg Price | C4: Avg Price MoM | D4: Avg Price YoY | E4: Quantity/Mo | F4: Qty by % | G4: Qty MoM | H4: Qty YoY | I4: Revenue/Mo | J4: Revenue by % | L4: Revenue MoM | M4: Revenue YoY
A5: bluedriver | B5: 106.49091 | C5: 0.14889329 | D5: 0.15055846 | E5: 10265 | F5: 0.15167186 | G5: 3.5866845 | H5: -0.095992955 | I5: 1093129.2 | J5: 0.18370851 | L5: 4.2696111 | M5: 0.040112956
A6: obdlink | B6: 115.35097 | C6: -0.0067773839 | D6: -0.014047597 | E6: 9211 | F6: 0.13609835 | G6: -0.010208468 | H6: 0.3347341 | I6: 1062497.8 | J6: 0.17856067 | L6: -0.016916665 | M6: 0.31598429
A7: generic | B7: 395.77622 | C7: -0.012334124 | D7: 1.3611623 | E7: 1289 | F7: 0.01904579 | G7: 0.14679715 | H7: 7.2101911 | I7: 510155.55 | J7: 0.085735441 | L7: 0.13265241 | M7: 18.385594
A8: fixd | B8: 64.787239 | C8: -0.11720457 | D8: 0.32677236 | E8: 6088 | F8: 0.089954048 | G8: -0.11421504 | H8: -0.48336728 | I8: 394424.71 | J8: 0.066286011 | L8: -0.21803309 | M8: -0.31454599
A9: obdeleven | B9: 157.85119 | C9: -0.0078454732 | D9: 0.18655002 | E9: 2175 | F9: 0.032137 | G9: 0.60872781 | H9: 4.815508 | I9: 343326.34 | J9: 0.05769855 | L9: 0.59610658 | M9: 5.9003912
A10: blcktec | B10: 63.799256 | C10: 0.020506121 | D10: 0.078176646 | E10: 551 | F10: 0.0081413732 | G10: -0.29358974 | H10: -0.40816327 | I10: 35153.39 | J10: 0.0059077891 | L10: -0.27910401 | M10: -0.36189545
A11: innova | B11: 89.033862 | C11: -0.010186555 | D11: -0.052650497 | E11: 246 | F11: 0.0036348055 | G11: -0.11510791 | H11: -0.43577982 | I11: 21902.33 | J11: 0.0036808498 | L11: -0.12412192 | M11: -0.46548629
A12: Other | B12: 65.77262 | C12: -0.0015615593 | D12: -0.015779554 | E12: 37854 | F12: 0.55931677 | G12: 0.061585058 | H12: 0.04966309 | I12: 2489756.8 | J12: 0.41842218 | L12: 0.05992733 | M12: 0.033099874
A13: Total Dongle | B13: 87.920125 | C13: 0.03771862 | D13: 0.191942 | E13: 67679 | F13: 1 | G13: 0.17479908 | H13: -0.0047352245 | I13: 5950346.1 | J13: 1 | L13: 0.21911088 | M13: 0.18629788
A45: Rank By Monthly Revenue - May '26 ONLY
A46: Ranking | B46: ASIN | C46: Product Name | D46: Brand | E46: Type | F46: Price | G46: Est. Monthly Retail Rev | H46: Est. Monthly Units Sold | I46: # of Reviews | J46: Avg. Rating | K46: Column2 | L46: Link
A47: 1 | B47: B07JFRFJG6 | C47: OBDLink MX+ OBD2 Bluetooth Scanner for iPhone, Android, and Windows | D47: obdlink | E47: Dongle | F47: 139.93305 | G47: 747242.47 | H47: 5340 | I47: 15235 | J47: 4.6 | K47: https://amazon.com/dp/B07JFRFJG6 | L47: =IF(K47="","",HYPERLINK(K47,K47))
A48: 2 | B48: B0GL9RL3XS | C48: BlueDriver Pro Next Gen OBD2 Scanner – No Subscription, Bluetooth Car Code Reader for iPhone & Android – Diagnose 8000+ Issues, ABS SRS TPMS, Repair Reports, Vehicles 1996+ | D48: bluedriver | E48: Dongle | F48: 97.454834 | G48: 634430.97 | H48: 6510 | I48: 62416 | J48: 4.5 | K48: https://amazon.com/dp/B0GL9RL3XS | L48: =IF(K48="","",HYPERLINK(K48,K48))
A49: 3 | B49: B00652G4TS | C49: BlueDriver Bluetooth Pro OBDII Scan Tool for iPhone & Android - No Subscription Fee - OBD2 Car Scanner and Code Reader - Diagnose Check Engine, ABS, SRS, Airbag & 7000+ Issues on Vehicles 1996+ | D49: bluedriver | E49: Dongle | F49: 122.15666 | G49: 458698.26 | H49: 3755 | I49: 62420 | J49: 4.5 | K49: https://amazon.com/dp/B00652G4TS | L49: =IF(K49="","",HYPERLINK(K49,K49))
A50: 4 | B50: B0FZ26RBDC | C50: HPT MPVI4 Diagnostic Code Reader Scanner and Tool | D50: generic | E50: Dongle | F50: 394.73583 | G50: 345393.85 | H50: 875 | I50: 153 | J50: 4.9 | K50: https://amazon.com/dp/B0FZ26RBDC | L50: =IF(K50="","",HYPERLINK(K50,K50))
A51: 5 | B51: B0BSFTHFC1 | C51: Diesel Laptops Nexiq USB Link 3 Wireless Edition with Repair Information & Diagnostic Software Bluetooth WiFi | D51: diesel laptops | E51: Dongle | F51: 799.30595 | G51: 274161.94 | H51: 343 | I51: 137 | J51: 4.6 | K51: https://amazon.com/dp/B0BSFTHFC1 | L51: =IF(K51="","",HYPERLINK(K51,K51))
A52: 6 | B52: B08NFLL3NT | C52: OBDLink CX Bimmercode Bluetooth 5.1 OBD2 Adapter for BMW/Mini, Works with iPhone/iOS & Android, Car Coding, OBD II Diagnostic Scanner | D52: obdlink | E52: Dongle | F52: 79.944199 | G52: 262936.47 | H52: 3289 | I52: 4426 | J52: 4.6 | K52: https://amazon.com/dp/B08NFLL3NT | L52: =IF(K52="","",HYPERLINK(K52,K52))
A53: 7 | B53: B09KT9XNML | C53: OBD2 Scanner Diagnostic Tool XTOOL A30M V2.0, 2026 Wireless Bidirectional Code Reader, 26 Reset, All System, Crank Sensor Relearn, EPB, Throttle Relearn, Lifetime Free Updates, Android & iOS | D53: xtool | E53: Dongle | F53: 155.67614 | G53: 191170.3 | H53: 1228 | I53: 1456 | J53: 4.3 | K53: https://amazon.com/dp/B09KT9XNML | L53: =IF(K53="","",HYPERLINK(K53,K53))
A54: 8 | B54: B073XKQQQW | C54: Veepeak OBDCheck BLE Bluetooth OBD II Scanner for iOS & Android, Car Wireless Check Engine Light Code Reader Diagnostic Tool | D54: veepeak | E54: Dongle | F54: 31.298403 | G54: 180842.17 | H54: 5778 | I54: 23568 | J54: 4.5 | K54: https://amazon.com/dp/B073XKQQQW | L54: =IF(K54="","",HYPERLINK(K54,K54))
A55: 9 | B55: B09N9RMVFP | C55: Z Automotive Tazer Mini Programmer | Fits 2018-2026 Jeep Wrangler JL and Gladiator JT | Customize Over 70 Settings | Activates Anti-Theft Pin Lock, Rock Crawl, Winch Mode and More! | D55: z automotive | E55: Dongle | F55: 327.67973 | G55: 156303.23 | H55: 477 | I55: 1002 | J55: 4.6 | K55: https://amazon.com/dp/B09N9RMVFP | L55: =IF(K55="","",HYPERLINK(K55,K55))
A56: 10 | B56: B013RIQMEO | C56: FIXD Bluetooth OBD2 Scanner for iPhone & Android - Diagnostic Scan Tool for Repairs and Car Buying - Check Engine Code Reader & Enhanced Codes - (1 Pack w/Free 14-Day FIXD Premium Bundle) | D56: fixd | E56: Dongle | F56: 39.988087 | G56: 150915.04 | H56: 3774 | I56: 35178 | J56: 4.2 | K56: https://amazon.com/dp/B013RIQMEO | L56: =IF(K56="","",HYPERLINK(K56,K56))
A58: Rank By Monthly Units - May '26 ONLY
A59: Ranking | B59: ASIN | C59: Product Name | D59: Brand | E59: Type | F59: Price | G59: Est. Monthly Retail Rev | H59: Est. Monthly Units Sold | I59: # of Reviews | J59: Avg. Rating | K59: Column2 | L59: Link
A60: 1 | B60: B0GL9RL3XS | C60: BlueDriver Pro Next Gen OBD2 Scanner – No Subscription, Bluetooth Car Code Reader for iPhone & Android – Diagnose 8000+ Issues, ABS SRS TPMS, Repair Reports, Vehicles 1996+ | D60: bluedriver | E60: Dongle | F60: 97.454834 | G60: 634430.97 | H60: 6510 | I60: 62416 | J60: 4.5 | K60: https://amazon.com/dp/B0GL9RL3XS | L60: =IF(K60="","",HYPERLINK(K60,K60))
A61: 2 | B61: B073XKQQQW | C61: Veepeak OBDCheck BLE Bluetooth OBD II Scanner for iOS & Android, Car Wireless Check Engine Light Code Reader Diagnostic Tool | D61: veepeak | E61: Dongle | F61: 31.298403 | G61: 180842.17 | H61: 5778 | I61: 23568 | J61: 4.5 | K61: https://amazon.com/dp/B073XKQQQW | L61: =IF(K61="","",HYPERLINK(K61,K61))
A62: 3 | B62: B07JFRFJG6 | C62: OBDLink MX+ OBD2 Bluetooth Scanner for iPhone, Android, and Windows | D62: obdlink | E62: Dongle | F62: 139.93305 | G62: 747242.47 | H62: 5340 | I62: 15235 | J62: 4.6 | K62: https://amazon.com/dp/B07JFRFJG6 | L62: =IF(K62="","",HYPERLINK(K62,K62))
A63: 4 | B63: B013RIQMEO | C63: FIXD Bluetooth OBD2 Scanner for iPhone & Android - Diagnostic Scan Tool for Repairs and Car Buying - Check Engine Code Reader & Enhanced Codes - (1 Pack w/Free 14-Day FIXD Premium Bundle) | D63: fixd | E63: Dongle | F63: 39.988087 | G63: 150915.04 | H63: 3774 | I63: 35178 | J63: 4.2 | K63: https://amazon.com/dp/B013RIQMEO | L63: =IF(K63="","",HYPERLINK(K63,K63))
A64: 5 | B64: B00652G4TS | C64: BlueDriver Bluetooth Pro OBDII Scan Tool for iPhone & Android - No Subscription Fee - OBD2 Car Scanner and Code Reader - Diagnose Check Engine, ABS, SRS, Airbag & 7000+ Issues on Vehicles 1996+ | D64: bluedriver | E64: Dongle | F64: 122.15666 | G64: 458698.26 | H64: 3755 | I64: 62420 | J64: 4.5 | K64: https://amazon.com/dp/B00652G4TS | L64: =IF(K64="","",HYPERLINK(K64,K64))
A65: 6 | B65: B08NFLL3NT | C65: OBDLink CX Bimmercode Bluetooth 5.1 OBD2 Adapter for BMW/Mini, Works with iPhone/iOS & Android, Car Coding, OBD II Diagnostic Scanner | D65: obdlink | E65: Dongle | F65: 79.944199 | G65: 262936.47 | H65: 3289 | I65: 4426 | J65: 4.6 | K65: https://amazon.com/dp/B08NFLL3NT | L65: =IF(K65="","",HYPERLINK(K65,K65))
A66: 7 | B66: B076XVQMVS | C66: Veepeak OBDCheck BLE+ Bluetooth OBD II Scanner for iOS & Android, Car Check Engine Code Reader Wireless OBD Diagnostic Scan Tool | D66: veepeak | E66: Dongle | F66: 41.965154 | G66: 94043.91 | H66: 2241 | I66: 10941 | J66: 4.6 | K66: https://amazon.com/dp/B076XVQMVS | L66: =IF(K66="","",HYPERLINK(K66,K66))
A67: 8 | B67: B0C3QQYQ1B | C67: TOPDON TopScan Lite OBD2 Scanner Bluetooth, Bi-Directional Scanner Wireless All System Diagnostic Tool for iOS & Android, 8+ Hot Reset, Repair Guides, Check Engine Car Code Reader, Performance Test | D67: topdon | E67: Dongle | F67: 54.020125 | G67: 82380.69 | H67: 1525 | I67: 5736 | J67: 4 | K67: https://amazon.com/dp/B0C3QQYQ1B | L67: =IF(K67="","",HYPERLINK(K67,K67))
A68: 9 | B68: B06XGB4873 | C68: Vgate iCar Pro Bluetooth 4.0 (BLE) OBD2 Fault Code Reader OBDII Code Scanner Car Check Engine Light for iOS/Android | D68: vgate | E68: Dongle | F68: 31.974764 | G68: 48729.54 | H68: 1524 | I68: 7232 | J68: 4.6 | K68: https://amazon.com/dp/B06XGB4873 | L68: =IF(K68="","",HYPERLINK(K68,K68))
A69: 10 | B69: B07CFVD2P3 | C69: FIXD Bluetooth OBD2 Scanner for iPhone & Android - Diagnostic Scan Tool for Repairs and Car Buying - Check Engine Code Reader & Enhanced Codes - (2 Pack w/Free 14-Day FIXD Premium Bundle) | D69: fixd | E69: Dongle | F69: 98.001609 | G69: 144944.38 | H69: 1479 | I69: 1248 | J69: 4.1 | K69: https://amazon.com/dp/B07CFVD2P3 | L69: =IF(K69="","",HYPERLINK(K69,K69))

Sheet Other Tools
A1: Other Tools Monthly Summary
A3: Other Tools Overall
B4: Avg Price | C4: Avg Price MoM | D4: Avg Price YoY | E4: Quantity/Mo | F4: Qty by % | G4: Qty MoM | H4: Qty YoY | I4: Revenue/Mo | J4: Revenue by % | L4: Revenue MoM | M4: Revenue YoY
A5: opus | ivs | B5: 780.06179 | C5: 0.074284224 | D5: -0.0466279 | E5: 641 | F5: 0.0096398225 | G5: 0.17184644 | H5: 0.51895735 | I5: 500019.61 | J5: 0.10864307 | L5: 0.25889614 | M5: 0.44813155
A6: diesel laptops | B6: 632.09501 | C6: 0.017648586 | D6: -0.13215917 | E6: 770 | F6: 0.011579818 | G6: -0.063260341 | H6: 0.37254902 | I6: 486713.16 | J6: 0.10575188 | L6: -0.04672821 | M6: 0.19115407
A7: obdlink | B7: 69.944527 | C7: 0.00012588831 | D7: 0.1815381 | E7: 6801 | F7: 0.10227837 | G7: 0.14514228 | H7: 0.31572838 | I7: 475692.73 | J7: 0.10335738 | L7: 0.14528644 | M7: 0.55458321
A8: topdon | B8: 221.14013 | C8: 0.089044736 | D8: -0.20119552 | E8: 1224 | F8: 0.018407399 | G8: 0.016611296 | H8: 2.007371 | I8: 270675.52 | J8: 0.058811732 | L8: 0.10713518 | M8: 1.4023014
A9: autel | B9: 51.231676 | C9: -0.052698676 | D9: -0.2288476 | E9: 5102 | F9: 0.076727574 | G9: -0.017334361 | H9: 0.29591059 | I9: 261384.01 | J9: 0.056792895 | L9: -0.069119538 | M9: -0.00065543903
A10: innova | B10: 62.782473 | C10: -0.36650549 | E10: 2786 | F10: 0.041897887 | G10: 98.5 | I10: 174911.97 | J10: 0.038004456 | L10: 62.032703
A11: Other | B11: 49.480586 | C11: -0.098974796 | D11: 0.089877346 | E11: 49171 | F11: 0.73946913 | G11: 0.035593185 | H11: 0.38206195 | I11: 2433009.9 | J11: 0.52863859 | L11: -0.06690444 | M11: 0.50627801
A12: Total Other Tools | B12: 69.21433 | C12: -0.049746839 | D12: 0.045786567 | E12: 66495 | F12: 1 | G12: 0.08628886 | H12: 0.44322177 | I12: 4602406.9 | J12: 1 | L12: 0.032249423 | M12: 0.50930194
A44: Rank By Monthly Revenue - May '26 ONLY
A45: Ranking | B45: ASIN | C45: Product Name | D45: Brand | E45: Type | F45: Price | G45: Est. Monthly Retail Rev | H45: Est. Monthly Units Sold | I45: # of Reviews | J45: Avg. Rating | K45: Column2 | L45: Link
A46: 1 | B46: B081VQVD3F | C46: OBDLink EX FORScan OBD Adapter | D46: obdlink | E46: Cable/Adapter | F46: 69.944527 | G46: 475692.73 | H46: 6801 | I46: 10006 | J46: 4.8 | K46: https://amazon.com/dp/B081VQVD3F | L46: =IF(K46="","",HYPERLINK(K46,K46))
A47: 2 | B47: B0BPYPNDVP | C47: Diesel Laptops Nexiq USB Link 3 Wired Edition with Repair Information & Diagnostic Software | D47: diesel laptops | E47: VCI | F47: 749.55194 | G47: 454978.03 | H47: 607 | I47: 257 | J47: 4.5 | K47: https://amazon.com/dp/B0BPYPNDVP | L47: =IF(K47="","",HYPERLINK(K47,K47))
A48: 3 | B48: B087WMGLF1 | C48: Edge Insight CTS3 Digital Gauge, Compatible with 1996 & Up OBD-II Vehicles, 84130-3 | D48: krazy on highways | E48: Other | F48: 439.82068 | G48: 234424.42 | H48: 533 | I48: 1068 | J48: 4.3 | K48: https://amazon.com/dp/B087WMGLF1 | L48: =IF(K48="","",HYPERLINK(K48,K48))
A49: 4 | B49: B0DFM25BZB | C49: TOPDON RLink J2534 Pass-Thru Programmer, OEM Reprogramming and Diagnostic Tool, Enhanced J2534 VCI, Supports J2534/D-PDU/CAN-FD/DoIP, Compatible with 18+ Vehicle Brands, No OE Software Provided | D49: topdon | E49: VCI | F49: 298.89048 | G49: 124637.33 | H49: 417 | I49: 278 | J49: 4.5 | K49: https://amazon.com/dp/B0DFM25BZB | L49: =IF(K49="","",HYPERLINK(K49,K49))
A50: 5 | B50: B07HX5QHKV | C50: BOSCH EL-52100-AM GM Global Multiple Diagnostic Interface (MDI 2) Kit - Compatible with All 1996 and Newer General Motors Vehicles | D50: bosch | E50: VCI | F50: 1062.3966 | G50: 104114.87 | H50: 98 | I50: 141 | J50: 4.5 | K50: https://amazon.com/dp/B07HX5QHKV | L50: =IF(K50="","",HYPERLINK(K50,K50))
A51: 6 | B51: B09SNVC9JR | C51: Opus IVS CarDAQ-Plus 3 All Makes J2534 Reprogramming Tool - Bluetooth | D51: opus | ivs | E51: Other | F51: 2217.243 | G51: 95341.45 | H51: 43 | I51: 83 | J51: 4.4 | K51: https://amazon.com/dp/B09SNVC9JR | L51: =IF(K51="","",HYPERLINK(K51,K51))
A52: 7 | B52: B0120XZ234 | C52: Innovative Products of America Light Ranger MUTT®: USA Made Universal Portable and Water-Resistant Trailer Light Tester with 7-Way Spade Pin Style with Adapter | D52: innovative products of america | E52: Other | F52: 194.54836 | G52: 84239.44 | H52: 433 | I52: 311 | J52: 4.6 | K52: https://amazon.com/dp/B0120XZ234 | L52: =IF(K52="","",HYPERLINK(K52,K52))
A53: 8 | B53: B000EVYGV4 | C53: Innova 3568 Digital Timing Light | D53: innova | E53: Other | F53: 77.445181 | G53: 83253.57 | H53: 1075 | K53: https://amazon.com/dp/B000EVYGV4 | L53: =IF(K53="","",HYPERLINK(K53,K53))
A54: 9 | B54: B09SP8F2X6 | C54: Opus IVS CarDAQ-Plus 3 All Makes J2534 Reprogramming Tool | D54: opus | ivs | E54: Other | F54: 1895.2073 | G54: 77703.5 | H54: 41 | I54: 83 | J54: 4.4 | K54: https://amazon.com/dp/B09SP8F2X6 | L54: =IF(K54="","",HYPERLINK(K54,K54))
A55: 10 | B55: B00H9UT1OU | C55: Innovative Products of America Heavy Ranger® MUTT® Portable Trailer Light Tester with 7-Way Round Pin (SAE J560) for Commercial Tractor Trailers | D55: innovative products of america | E55: Other | F55: 185.37829 | G55: 71370.64 | H55: 385 | I55: 449 | J55: 4.6 | K55: https://amazon.com/dp/B00H9UT1OU | L55: =IF(K55="","",HYPERLINK(K55,K55))
A57: Rank By Monthly Units - May '26 ONLY
A58: Ranking | B58: ASIN | C58: Product Name | D58: Brand | E58: Type | F58: Price | G58: Est. Monthly Retail Rev | H58: Est. Monthly Units Sold | I58: # of Reviews | J58: Avg. Rating | K58: Column2 | L58: Link
A59: 1 | B59: B081VQVD3F | C59: OBDLink EX FORScan OBD Adapter | D59: obdlink | E59: Cable/Adapter | F59: 69.944527 | G59: 475692.73 | H59: 6801 | I59: 10006 | J59: 4.8 | K59: https://amazon.com/dp/B081VQVD3F | L59: =IF(K59="","",HYPERLINK(K59,K59))
A60: 2 | B60: B094Z7PBLS | C60: Vgate vLinker FS OBD2 USB Adapter for FORScan HS/MS-CAN Auto Switch | D60: vgate | E60: Cable/Adapter | F60: 34.987456 | G60: 66021.33 | H60: 1887 | I60: 2757 | J60: 4.7 | K60: https://amazon.com/dp/B094Z7PBLS | L60: =IF(K60="","",HYPERLINK(K60,K60))
A61: 3 | B61: B01F0GVBWY | C61: OHP FORScan ELM327-based OBD2 to USB Diagnostic Scan Tool with MS-Can/HS-Can Switch for Ford Lincoln Mazda Mercury Vehicles | D61: ohp | E61: Cable/Adapter | F61: 35.985413 | G61: 64953.67 | H61: 1805 | I61: 4938 | J61: 4.4 | K61: https://amazon.com/dp/B01F0GVBWY | L61: =IF(K61="","",HYPERLINK(K61,K61))
A62: 4 | B62: B000EVYGV4 | C62: Innova 3568 Digital Timing Light | D62: innova | E62: Other | F62: 77.445181 | G62: 83253.57 | H62: 1075 | K62: https://amazon.com/dp/B000EVYGV4 | L62: =IF(K62="","",HYPERLINK(K62,K62))
A63: 5 | B63: B0DPHCBL89 | C63: 12+8 Pin Connector to OBD2 Adapter, Secutiry Gateway Bypass Cable, 12+8 Cable for Chrysler SGW Equipped FCA Vehicles for Diagnostic, Fit for Scanners MK808 MK808S MX808 MS906 Pro MS908S | D63: ecocstm | E63: Cable/Adapter | F63: 12.980797 | G63: 13850.51 | H63: 1067 | I63: 148 | J63: 4.6 | K63: https://amazon.com/dp/B0DPHCBL89 | L63: =IF(K63="","",HYPERLINK(K63,K63))
A64: 6 | B64: B0DFY6CCSV | C64: pinflaw 2 PCS Automobile Power Upgrade Fuel Saving, OBD2 ECOOBD2 Automotive Plug and Driver Single Plate, Automotive Energy Saver Accessories, Universal for Most Cars (Green) | D64: pinflaw | E64: Other | F64: 13.258625 | G64: 14080.66 | H64: 1062 | I64: 429 | J64: 3.6 | K64: https://amazon.com/dp/B0DFY6CCSV | L64: =IF(K64="","",HYPERLINK(K64,K64))
A65: 7 | B65: B071L8W7Q7 | C65: bbfly-B6 OBD2 Splitter 16 Pin OBD II Splitter Extension 1x Male and 2X Female Extension Cable Adapter (1FT/30CM) (1Pack) | D65: bbfly | E65: Cable/Adapter | F65: 10.886439 | G65: 10059.07 | H65: 924 | I65: 2121 | J65: 4.6 | K65: https://amazon.com/dp/B071L8W7Q7 | L65: =IF(K65="","",HYPERLINK(K65,K65))
A66: 8 | B66: B0711LGRGQ | C66: bbfly-A9 OBD II OBD2 16 Pin Splitter Extension 1x Male and 2X Female Extension Cable Adapter (2FT/60CM) | D66: bbfly | E66: Cable/Adapter | F66: 9.8914029 | G66: 8813.24 | H66: 891 | I66: 3093 | J66: 4.5 | K66: https://amazon.com/dp/B0711LGRGQ | L66: =IF(K66="","",HYPERLINK(K66,K66))
A67: 9 | B67: B07MQ8GHG3 | C67: ELM327 USB Adapter OBD2 Scanner for Windows, ELMconfig FoCCCus Diagnostic Scan Tool with MS-Can/HS-Can Switch for Ford Lincoln Mazda Mercury Series Vehicles | D67: obdresource | E67: Cable/Adapter | F67: 18.674798 | G67: 15686.83 | H67: 840 | I67: 6826 | J67: 4.4 | K67: https://amazon.com/dp/B07MQ8GHG3 | L67: =IF(K67="","",HYPERLINK(K67,K67))
A68: 10 | B68: B0CZ92SLDY | C68: VGATE vLinker FS USB FORScan OBD2 Adapter for HS/MS-CAN Auto Switch, Wire OBD2 USB FORScan Adapter Code Readers & Scanner Diagnostic Tools | D68: vlinker | E68: Cable/Adapter | F68: 33.98953 | G68: 27497.53 | H68: 809 | I68: 381 | J68: 4.6 | K68: https://amazon.com/dp/B0CZ92SLDY | L68: =IF(K68="","",HYPERLINK(K68,K68))

Sheet Ancel
B7: Avg Price | C7: Avg Price MoM | D7: Avg Price YoY | E7: Quantity/Mo | F7: Qty by % | G7: Qty MoM | H7: Qty YoY | I7: Revenue/Mo | J7: Revenue by % | L7: Revenue MoM | M7: Revenue YoY
A8: Tablet $800+ | B8: 952.79519 | C8: -0.033688335 | D8: 0.049564962 | E8: 231 | F8: 0.0056451613 | G8: 4.9230769 | H8: 0.34302326 | I8: 220095.69 | J8: 0.080082059 | L8: 4.7235383 | M8: 0.40959015
A9: Tablet $400-$800 | B9: 557.38959 | C9: -0.055060101 | D9: 0.14208458 | E9: 1318 | F9: 0.032209189 | G9: 0.14409722 | H9: 2.4775726 | I9: 734639.48 | J9: 0.26729938 | L9: 0.081103114 | M9: 2.971682
A10: Tablet $400- | B10: 253.22559 | C10: -0.10086849 | D10: 0.17320558 | E10: 931 | F10: 0.022751711 | G10: 0.0032327586 | H10: -0.27661228 | I10: 235753.02 | J10: 0.085778995 | L10: -0.097961814 | M10: -0.15131749
A11: Total Tablet | B11: 480.03556 | C11: 0.03865599 | D11: 0.42560697 | E11: 2480 | F11: 0.060606061 | G11: 0.17036338 | H11: 0.34929271 | I11: 1190488.2 | J11: 0.43316044 | L11: 0.21560493 | M11: 0.92356109
A12: Handheld $75+ | B12: 121.74998 | C12: -0.037622011 | D12: -0.091394693 | E12: 1272 | F12: 0.031085044 | G12: -0.28013582 | H12: -0.44186047 | I12: 154865.97 | J12: 0.056348153 | L12: -0.30721856 | M12: -0.49287146
A13: Handheld $75- | B13: 34.699377 | C13: -0.00053761885 | D13: 0.1171577 | E13: 34410 | F13: 0.84090909 | G13: -0.050129741 | H13: -0.074651751 | I13: 1194005.6 | J13: 0.43444024 | L13: -0.050640409 | M13: 0.033759922
A14: Total Handheld | B14: 37.802577 | C14: -0.030383248 | D14: 0.021561431 | E14: 35682 | F14: 0.87199413 | G14: -0.060826994 | H14: -0.095857089 | I14: 1348871.5 | J14: 0.49078839 | L14: -0.089362121 | M14: -0.076362474
A15: Total Dongle | B15: 89.644874 | C15: -0.037936481 | D15: -0.1951985 | E15: 1385 | F15: 0.03384653 | G15: 0.18073316 | H15: 1.6634615 | I15: 124158.15 | J15: 0.045175079 | L15: 0.1359403 | M15: 1.1435578
A16: Total Other Tools | B16: 61.805637 | C16: -0.15591154 | D16: -0.45074051 | E16: 1373 | F16: 0.033553275 | G16: 0.19808028 | H16: 1.8020408 | I16: 84859.14 | J16: 0.030876091 | L16: 0.011285734 | M16: 0.53904751
A17: Total | B17: 67.164639 | C17: 0.073884788 | D17: 0.29629872 | E17: 40920 | F17: 1 | G17: -0.035610756 | H17: -0.032921324 | I17: 2748377 | J17: 1 | L17: 0.035642939 | M17: 0.25362285
A51: Rank by Revenue
A52: Product Name | B52: ASIN | C52: Type | D52: Avg Price | E52: Estimated 12mo Revenue | F52: Monthly Rev | G52: Estimated 12mo Units | H52: Monthly Units | I52: # of Reviews | J52: Tool Rating | K52: Column1 | L52: Link
A53: ANCEL AD310 Classic Enhanced Universal OBD II Scanner Car Engine Fault Code Reader CAN Diagnostic Scan Tool, Read and Clear Error Codes for 1996 or Newer OBD2 Protocol Vehicle (Black) | B53: B01G5EA74I | C53: Handheld | D53: 27.758715 | E53: 11452892 | F53: 668152.27 | G53: 409062 | H53: 24070 | I53: 64423 | J53: 4.6 | K53: https://amazon.com/dp/B01G5EA74I | L53: =IF(K53="","",HYPERLINK(K53,K53))
A54: ANCEL AD410 Enhanced OBD2 Scanner, Vehicle Code Reader for Check Engine Light, Automotive OBD II Scanner Fault Diagnosis, OBDII Scan Tool for All OBDII Cars 1996+, Black/Yellow | B54: B071FSNL73 | C54: Handheld | D54: 45.525505 | E54: 4099600.3 | F54: 301515.42 | G54: 88159 | H54: 6623 | I54: 15175 | J54: 4.5 | K54: https://amazon.com/dp/B071FSNL73 | L54: =IF(K54="","",HYPERLINK(K54,K54))
A55: ANCEL X7HD 10.1'' Heavy Duty Truck Scanner, Semi Trucks Full System Diagnostic Tool, Bidirectional Diesel Scan Tool with DPF, ECU Coding, 40+ Reset for Cummins, Detroit, Caterpillar, Volvo, Paccar etc | B55: B0BZ82WQ4Q | C55: Tablet | D55: 765.33645 | E55: 2614467.8 | F55: 267102.42 | G55: 3257 | H55: 349 | I55: 796 | J55: 3.7 | K55: https://amazon.com/dp/B0BZ82WQ4Q | L55: =IF(K55="","",HYPERLINK(K55,K55))
A56: ANCEL DS500BT Bidirectional Scan Tool, Full-System Automotive Diagnostic Scanner with 28+ Services, Injector Coding, DPF/Brake/BMS/Oil/Gear/Throttle Functions, CAN FD Support, Lifetime Free Updates | B56: B0FN4JHLY7 | C56: Tablet | D56: 493.77205 | E56: 1535661.4 | F56: 168376.27 | G56: 1499 | H56: 341 | I56: 1080 | J56: 4.6 | K56: https://amazon.com/dp/B0FN4JHLY7 | L56: =IF(K56="","",HYPERLINK(K56,K56))
A57: ANCEL MT700 Motorcycle OBD2 Scanner Full Systems, ABS Engine Meter TPMS Diagnostic Tool with 35+ Reset Functions for Harley Indian Yamaha Polaris Piaggio Ducati Honda BMW, AutoVIN, 7”Touch Screen,16G | B57: B0BMZW65LJ | C57: Tablet | D57: 936.38185 | E57: 241926.74 | F57: 111429.44 | G57: 250 | H57: 119 | I57: 883 | J57: 4.5 | K57: https://amazon.com/dp/B0BMZW65LJ | L57: =IF(K57="","",HYPERLINK(K57,K57))
A58: ANCEL HD3400 Pro Heavy Duty Truck Scanner with DPF Regen for Cummins, Paccar, Caterpillar, Detroit, Volvo, Mack and International, Full-System Diesel Scan Tool for 6/9-Pin HDOBD & OBD2 Vehicles | B58: B09R3L5BP2 | C58: Tablet | D58: 442.7028 | E58: 1035701 | F58: 94738.4 | G58: 2219 | H58: 214 | I58: 565 | J58: 4.1 | K58: https://amazon.com/dp/B09R3L5BP2 | L58: =IF(K58="","",HYPERLINK(K58,K58))
A59: ANCEL X7HD PRO 10.1'' Heavy Duty Truck Scanner, Full-System Diesel Diagnostic Tool with DPF Regen, 42+ Reset, Bi-Directional and Active Test, ECU Coding, HDOBD/OBD2 Scanner for Diesel Trucks - Grey | B59: B0GLFSPMZ4 | C59: Tablet | D59: 940.765 | E59: 1067985.4 | F59: 88431.91 | G59: 94 | H59: 94 | K59: https://amazon.com/dp/B0GLFSPMZ4 | L59: =IF(K59="","",HYPERLINK(K59,K59))
A60: ANCEL AD410 PRO OBD2 Scanner and Battery Tester, 2-in-1 Car Diagnostic Tool, Check Engine Light, EVAP Test, Live Data, 12V Battery Analyzer with Cranking & Charging System Test for Car Motorcycle | B60: B0BX3K8VGJ | C60: Handheld | D60: 63.080853 | E60: 959925.27 | F60: 65793.33 | G60: 12726 | H60: 1043 | I60: 4132 | J60: 4.6 | K60: https://amazon.com/dp/B0BX3K8VGJ | L60: =IF(K60="","",HYPERLINK(K60,K60))
A61: ANCEL DS200 Full System OBD2 Scanner with 15+ Reset Services - Oil/BMS/Brake Reset, DPF Regen, Injector Coding, ABS Bleeding, Free Lifetime Updates, Online Customer Service | B61: B0DHX29NMC | C61: Tablet | D61: 354.38169 | E61: 751745.65 | F61: 63079.94 | G61: 2644 | H61: 178 | I61: 206 | J61: 4.4 | K61: https://amazon.com/dp/B0DHX29NMC | L61: =IF(K61="","",HYPERLINK(K61,K61))
A62: ANCEL VD500 OBD2 Scanner Diagnostic Tool for Volkswagen VW Audi Skoda Seat Diagnosis Check Engine Light EPB ABS SRS Code Reader Oil Throttle Position Adaption Brake Pad Reset | B62: B07BS7PDC2 | C62: Handheld | D62: 63.380582 | E62: 764414.5 | F62: 56662.24 | G62: 11552 | H62: 894 | I62: 6359 | J62: 4.5 | K62: https://amazon.com/dp/B07BS7PDC2 | L62: =IF(K62="","",HYPERLINK(K62,K62))
A63: ANCEL BD500 Bluetooth Diagnostic Scan Tool for VW Audi Seat Skoda Diagnosis, Full Systems Volkswagen OBD2 Scanner Vag Car Code Reader with Battery Check EPB Reset for iPhone, iPad & Android | B63: B0B1MHSMBW | C63: Dongle | D63: 81.931726 | E63: 165394.75 | F63: 53173.69 | G63: 2032 | H63: 649 | I63: 1729 | J63: 4.4 | K63: https://amazon.com/dp/B0B1MHSMBW | L63: =IF(K63="","",HYPERLINK(K63,K63))
A64: ANCEL HD7000 Elite 7" Heavy Duty Truck Scanner with DPF Regen, Speed/Idle Adjustment, Service Reset, Diagnostic Tool for Cummins Detroit CAT Volvo Paccar Mack International, Lifetime Free Updates | B64: B0FP9BMYKG | C64: Tablet | D64: 520.85541 | E64: 555921.83 | F64: 51043.83 | G64: 516 | H64: 98 | I64: 77 | J64: 3.5 | K64: https://amazon.com/dp/B0FP9BMYKG | L64: =IF(K64="","",HYPERLINK(K64,K64))
A65: ANCEL HD110 Heavy Duty Truck Scanner with DPF Regen and Reset for Detroit Paccar Engine, Full System HDOBD & OBD2 Scanner for Diesel Trucks Lifetime Free Updates | B65: B0D3F2953F | C65: Cable/Adapter | D65: 172.55352 | E65: 621396.12 | F65: 50040.52 | G65: 3530 | H65: 290 | I65: 198 | J65: 4.1 | K65: https://amazon.com/dp/B0D3F2953F | L65: =IF(K65="","",HYPERLINK(K65,K65))
A66: ANCEL HD3600 Heavy Equipment Diagnostic Tool with D-P-F Regen, Full System Heavy Duty Truck Scanner Machinery Scanner Diesel Code Reader Fit for Cummins, Caterpillar, John Deere, Komatsu, Yanmar&Case | B66: B0B1LD8663 | C66: Tablet | D66: 473.98533 | E66: 467626.93 | F66: 49768.46 | G66: 978 | H66: 105 | I66: 351 | J66: 3.8 | K66: https://amazon.com/dp/B0B1LD8663 | L66: =IF(K66="","",HYPERLINK(K66,K66))
A67: ANCEL AD530 OBD2 Scanner-Upgraded AD310, Car Code Reader for Check Engine Light, Full OBDII Scan Tool for Read & Clear Fault Codes, Battery Test & Live Data, OBD II Diagnostic Scanner for 1996+ Cars | B67: B07N66TTQG | C67: Handheld | D67: 68.794464 | E67: 670860.37 | F67: 46229.88 | G67: 10237 | H67: 672 | I67: 4152 | J67: 4.5 | K67: https://amazon.com/dp/B07N66TTQG | L67: =IF(K67="","",HYPERLINK(K67,K67))
A68: ANCEL DS500 Elite Bidirectional Scan Tool, Full System Car Diagnostic Scanner with 28+ Services, Injector Coding, Active Test, ABS Bleeding Throttle BMS TPMS Reset, CAN-FD, FCA, Lifetime Free Update | B68: B0FVFQCJ41 | C68: Tablet | D68: 410.61578 | E68: 528382.71 | F68: 44757.12 | G68: 633 | H68: 109 | I68: 92 | J68: 4.6 | K68: https://amazon.com/dp/B0FVFQCJ41 | L68: =IF(K68="","",HYPERLINK(K68,K68))
A69: ANCEL BD310 Bluetooth OBD2 Scanner, 2-in-1 Car Diagnostic Scan Tool & Code Reader with App, Battery Test, Trip Analysis, Performance Test, for iPhone & Android, All 1996+ Vehicles | B69: B07J51W9NS | C69: Handheld | D69: 58.212055 | E69: 750531.42 | F69: 44182.95 | G69: 11897 | H69: 759 | I69: 1520 | J69: 4.4 | K69: https://amazon.com/dp/B07J51W9NS | L69: =IF(K69="","",HYPERLINK(K69,K69))
A70: ANCEL DS100 OBD2 Scanner, 5” Full Touchscreen 4-System Diagnostic Tool for Engine ABS SRS Transmission, 7 Reset Services, AutoVIN Code Reader with ABS Bleeding, BMS, Oil Reset, PDF Report | B70: B0DHX8FFVR | C70: Tablet | D70: 229.16803 | E70: 802237.89 | F70: 40791.91 | G70: 4313 | H70: 178 | I70: 380 | J70: 4.3 | K70: https://amazon.com/dp/B0DHX8FFVR | L70: =IF(K70="","",HYPERLINK(K70,K70))
A71: ANCEL BD300 Bluetooth OBD2 Scanner, Full System Code Reader and Diagnostic Tool for BMW with Battery Registration Service Reset EPB CBS ETC ABS Airbag & Powerful OBD2 Functions | B71: B09ZPB3JV9 | C71: Dongle | D71: 77.490212 | E71: 217183.79 | F71: 40217.42 | G71: 2646 | H71: 519 | I71: 2247 | J71: 4.5 | K71: https://amazon.com/dp/B09ZPB3JV9 | L71: =IF(K71="","",HYPERLINK(K71,K71))
... A112: ANCEL Waterproof Storage Case Bag for HD100 Heavy Duty Truck Scanner and Other Testers - Durable Zipper Carry Box (8.66’’ x 6.22’’ x 3.15’’) | B112: B0DPH4VF4Y | C112: Other | D112: 20.063065 | E112: 9140.86 | F112: 1243.91 | G112: 466 | H112: 62 | I112: 196 | J112: 4.3 | K112: https://amazon.com/dp/B0DPH4VF4Y | L112: =IF(K112="","",HYPERLINK(K112,K112))
A113: ANCEL Protective Case Storage Bag for HD100, HD110, HD120, HD200, HD210 Heavy Duty Truck Scanners(Only The Case) | B113: B0FX24WF6Q | C113: Other | D113: 20.024333 | E113: 13400.9 | F113: 1201.46 | G113: 60 | H113: 60 | K113: https://amazon.com/dp/B0FX24WF6Q | L113: =IF(K113="","",HYPERLINK(K113,K113))
A114: ANCEL EVA Hard Protective Case for V5 HD PRO Heavy Truck Scanner, Waterproof Shockproof Storage Bag with Large Capacity, Smooth Zippers and Easy Carry Handle, Travel Ready | B114: B0828TC9T9 | C114: Other | D114: 34.632353 | E114: 12742.131 | F114: 1177.5 | G114: 56 | H114: 34 | I114: 172 | J114: 4.2 | K114: https://amazon.com/dp/B0828TC9T9 | L114: =IF(K114="","",HYPERLINK(K114,K114))
A115: ANCEL OBD2 Scanner Extension Cable 3.3ft/1m, 16 Pin OBDII OBD2 Male to Female Extender Cord, OBD2 Diagnostic Extender Connector for All OBD2 Vehicles | B115: B0DS453BBG | C115: Cable/Adapter | D115: 16.570806 | E115: 14319.87 | F115: 1027.39 | G115: 1051 | H115: 62 | I115: 38 | J115: 4.6 | K115: https://amazon.com/dp/B0DS453BBG | L115: =IF(K115="","",HYPERLINK(K115,K115))
A116: ANCEL Obd2 Female to 20 Pin Extension Convert Adapter OBD1 to OBD II Cable for 20 Pin E31 E32 E34 E36 E39 E38 E53 X 5 Z3 | B116: B0B2LKYW3T | C116: Cable/Adapter | D116: 15.884107 | E116: 10368.44 | F116: 889.51 | G116: 650 | H116: 56 | I116: 211 | J116: 4.4 | K116: https://amazon.com/dp/B0B2LKYW3T | L116: =IF(K116="","",HYPERLINK(K116,K116))
A117: ANCEL CAN 3 - CAN 1 Crossover Cable for 2016 & Newer Paccar Peterbilts/Kenworths/Cummins Engines, 9 Pin Heavy Duty Truck Scanner Diagnostic Adapter Tool | B117: B0C4FGGVZ4 | C117: Cable/Adapter | D117: 46.573333 | E117: 15955.16 | F117: 838.32 | G117: 316 | H117: 18 | I117: 17 | J117: 4.5 | K117: https://amazon.com/dp/B0C4FGGVZ4 | L117: =IF(K117="","",HYPERLINK(K117,K117))
A118: ANCEL DS600 Elite OBD2 Scanner, 2025 New Bidirectional Full System Scan Tool with 34+Resets, ECU Online Coding, FCA SGW AutoAuth, VAG Guide, Wireless Car Scanner Diagnostic Tool with 2-Year Update | B118: B0CWNP8JDD | C118: Tablet | D118: 593.38 | E118: 13785.78 | F118: 593.38 | G118: 19 | H118: 1 | I118: 15 | J118: 3.4 | K118: https://amazon.com/dp/B0CWNP8JDD | L118: =IF(K118="","",HYPERLINK(K118,K118))
A119: ANCEL HD Series-Compatible Printer for HD3100, HD3100 PRO, HD3200, HD3300, HD3400, HD3500, HD3600: Exclusive Heavy Duty Truck Scanner Diagnostic Tool Accessory for Diesel Vehicle Reports | B119: B097D8JHJG | C119: Other | D119: 148.0225 | E119: 9239.49 | F119: 592.09 | G119: 61 | H119: 4 | I119: 25 | J119: 3.8 | K119: https://amazon.com/dp/B097D8JHJG | L119: =IF(K119="","",HYPERLINK(K119,K119))
A120: ANCEL Large Hard Protective Case for Heavy Duty Truck Scanner HD3300 Plus+ HD3600 HD430, OBD2 Scanner Diagnostic Tool FX6000 Elite FX6100, Automotive Smoke Machine Leak Detector S3000 S3000 PRO | B120: B0FJFJRX71 | C120: Other | D120: 29.936429 | E120: 7294.8846 | F120: 419.11 | G120: 156 | H120: 14 | I120: 108 | J120: 3.4 | K120: https://amazon.com/dp/B0FJFJRX71 | L120: =IF(K120="","",HYPERLINK(K120,K120))
A121: ANCEL FX2000 Plus OBD2 Scanner Diagnostic Tool with Protective Bag, ABS SRS Transmission Airbag Scan Tool, Check Engine Code Reader, Scanner for Car Lifetime Free Upgrade | B121: B0DQPJ8QVK | C121: Tablet | D121: 205.12 | E121: 22418.183 | F121: 410.24 | G121: 149 | H121: 2 | I121: 52 | J121: 4 | K121: https://amazon.com/dp/B0DQPJ8QVK | L121: =IF(K121="","",HYPERLINK(K121,K121))
A122: ANCEL BD200 Pro OBD2 Scanner Bluetooth, Enhanced Wireless Code Readers ABS SRS Transmission Airbag Car Scanner Diagnostic Tool with Battery Test, Check Engine Light Exclusive App for iPhone & Android | B122: B0CWN69XH4 | C122: Dongle | D122: 68.2275 | E122: 7538.01 | F122: 272.91 | G122: 99 | H122: 4 | I122: 75 | J122: 3.5 | K122: https://amazon.com/dp/B0CWN69XH4 | L122: =IF(K122="","",HYPERLINK(K122,K122))
A123: ANCEL Large Eva Bag for DS500 Elite FX6100 FX6000 Elite OBD2 Scanner, S3000 S3000 PRO Automotive Smoke Machine Leak Detector... | B123: B0FZ9FKQH4 | C123: Other | D123: 29.913333 | E123: 1083.7831 | F123: 89.74 | G123: 3 | H123: 3 | K123: https://amazon.com/dp/B0FZ9FKQH4 | L123: =IF(K123="","",HYPERLINK(K123,K123))
A124: ANCEL Protective Case Storage Bag for Bluetooth Heavy Duty Truck Scanner – Compatible with HD110 Diesel Diagnostic Tool and Other Small Code Readers & Battery Testers | B124: B0G8DGNVR7 | C124: Other | D124: 20.386667 | E124: 702.14923 | F124: 61.16 | G124: 4 | H124: 3 | K124: https://amazon.com/dp/B0G8DGNVR7 | L124: =IF(K124="","",HYPERLINK(K124,K124))
A125: ANCEL OBD2 Diagnostic Scan Tools Protective Hard – Custom-fit for MT700, MT500Pro, MT500Plus, MR500, HD7000 Elite & HD8000 (Case Only) | B125: B0FLXQ35LZ | C125: Other | D125: 27.625 | E125: 645.54 | F125: 55.25 | G125: 3 | H125: 2 | K125: https://amazon.com/dp/B0FLXQ35LZ | L125: =IF(K125="","",HYPERLINK(K125,K125))
A126: ANCEL Heavy Duty Truck Scanner HD601 All System Diesel Diagnostic Scan Tool fits for Cummins, Detroit, Freightliner, International, Paccar, Check Engine for Truck & Car 2 in 1 Code Reader | B126: B0B452YDWT | C126: Handheld | D126: 147.88792 | E126: 1115728.6 | F126: 0 | G126: 7139 | H126: 0 | I126: 637 | J126: 4 | K126: https://amazon.com/dp/B0B452YDWT | L126: =IF(K126="","",HYPERLINK(K126,K126))
A127: ANCEL DS600 Plus Top Bi-Directional Scan Tool OEM All System Automotive OBD2 Scanner for All Cars, 34+ Reset Services Car Diagnostic Tablet, Online Coding, Active Test | B127: B0B1JD8D4H | C127: Tablet | D127: 599.99 | E127: 14518.16 | F127: 0 | G127: 22 | H127: 0 | I127: 12 | J127: 4.7 | K127: https://amazon.com/dp/B0B1JD8D4H | L127: =IF(K127="","",HYPERLINK(K127,K127))
A128: ANCEL HD210 Heavy Duty Truck Scanner, Speed Limit and Idle Adjust for Volvo & International Maxxforce Engines, Diesel Truck Scanner, All-System HDOBD/OBD2 Scan Tool, Bluetooth Lifetime Updates | B128: B0G6D482MK | C128: Tablet | D128: 239.99 | E128: 0 | F128: 0 | G128: 0 | H128: 0 | K128: https://amazon.com/dp/B0G6D482MK | L128: =IF(K128="","",HYPERLINK(K128,K128))
A129: ANCEL HD200 Heavy Duty Truck Scanner,Speed Limit and Idle Reset for Cummins & Caterpillar Engines, Full System Diesel HDOBD & OBD2 Scanner Diagnostic Tool,Lifetime Free Updates | B129: B0GK8C7GM6 | C129: Tablet | D129: 239.99 | E129: 0 | F129: 0 | G129: 0 | H129: 0 | K129: https://amazon.com/dp/B0GK8C7GM6 | L129: =IF(K129="","",HYPERLINK(K129,K129))
A130: ANCEL OBD2 Scanner AD410Pro Car Battery Tester 2 in 1,12V 100-2000 CCA Battery Charging Cranking Test Car Scanner Diagnostic Tool, Check Engine Code Reader Scan Tool for All OBDII Vehicles | B130: B0B96LTZNG | C130: Handheld | D130: 49.99 | E130: 4911.81 | F130: 0 | G130: 64 | H130: 0 | I130: 150 | J130: 4.5 | K130: https://amazon.com/dp/B0B96LTZNG | L130: =IF(K130="","",HYPERLINK(K130,K130))
A131: ANCEL Echo OBD2 Scanner Bluetooth - All Systems Code Reader, Car Diagnostic Tool for iOS Android, Vehicle Scanner for Oil Light & Brake Reset, Battery Registration - Bidirectional Scan Tool, Live Data | B131: B0D8HQG673 | C131: Dongle | D131: 98.628667 | E131: 65785.44 | F131: 0 | G131: 682 | H131: 0 | I131: 263 | J131: 4.1 | K131: https://amazon.com/dp/B0D8HQG673 | L131: =IF(K131="","",HYPERLINK(K131,K131))
A132: Total | E132: =SUM(E53:E131) | F132: =SUM(F53:F131)
A133: Rank by Units
A134: Product Name | B134: ASIN | C134: Type | D134: Avg Price | E134: Estimated 12mo Revenue | F134: Monthly Rev | G134: Estimated 12mo Units | H134: Monthly Units | I134: # of Reviews | J134: Tool Rating | K134: Column1 | L134: Link
A135: ANCEL AD310 Classic Enhanced Universal OBD II Scanner Car Engine Fault Code Reader CAN Diagnostic Scan Tool, Read and Clear Error Codes for 1996 or Newer OBD2 Protocol Vehicle (Black) | B135: B01G5EA74I | C135: Handheld | D135: 27.758715 | E135: 11452892 | F135: 668152.27 | G135: 409062 | H135: 24070 | I135: 64423 | J135: 4.6 | K135: https://amazon.com/dp/B01G5EA74I | L135: =IF(K135="","",HYPERLINK(K135,K135))
A136: ANCEL AD410 Enhanced OBD2 Scanner, Vehicle Code Reader for Check Engine Light, Automotive OBD II Scanner Fault Diagnosis, OBDII Scan Tool for All OBDII Cars 1996+, Black/Yellow | B136: B071FSNL73 | C136: Handheld | D136: 45.525505 | E136: 4099600.3 | F136: 301515.42 | G136: 88159 | H136: 6623 | I136: 15175 | J136: 4.5 | K136: https://amazon.com/dp/B071FSNL73 | L136: =IF(K136="","",HYPERLINK(K136,K136))
A137: ANCEL AD410 PRO OBD2 Scanner and Battery Tester, 2-in-1 Car Diagnostic Tool, Check Engine Light, EVAP Test, Live Data, 12V Battery Analyzer with Cranking & Charging System Test for Car Motorcycle | B137: B0BX3K8VGJ | C137: Handheld | D137: 63.080853 | E137: 959925.27 | F137: 65793.33 | G137: 12726 | H137: 1043 | I137: 4132 | J137: 4.6 | K137: https://amazon.com/dp/B0BX3K8VGJ | L137: =IF(K137="","",HYPERLINK(K137,K137))
A138: ANCEL VD500 OBD2 Scanner Diagnostic Tool for Volkswagen VW Audi Skoda Seat Diagnosis Check Engine Light EPB ABS SRS Code Reader Oil Throttle Position Adaption Brake Pad Reset | B138: B07BS7PDC2 | C138: Handheld | D138: 63.380582 | E138: 764414.5 | F138: 56662.24 | G138: 11552 | H138: 894 | I138: 6359 | J138: 4.5 | K138: https://amazon.com/dp/B07BS7PDC2 | L138: =IF(K138="","",HYPERLINK(K138,K138))
A139: ANCEL BD310 Bluetooth OBD2 Scanner, 2-in-1 Car Diagnostic Scan Tool & Code Reader with App, Battery Test, Trip Analysis, Performance Test, for iPhone & Android, All 1996+ Vehicles | B139: B07J51W9NS | C139: Handheld | D139: 58.212055 | E139: 750531.42 | F139: 44182.95 | G139: 11897 | H139: 759 | I139: 1520 | J139: 4.4 | K139: https://amazon.com/dp/B07J51W9NS | L139: =IF(K139="","",HYPERLINK(K139,K139))
A140: ANCEL AD530 OBD2 Scanner-Upgraded AD310, Car Code Reader for Check Engine Light, Full OBDII Scan Tool for Read & Clear Fault Codes, Battery Test & Live Data, OBD II Diagnostic Scanner for 1996+ Cars | B140: B07N66TTQG | C140: Handheld | D140: 68.794464 | E140: 670860.37 | F140: 46229.88 | G140: 10237 | H140: 672 | I140: 4152 | J140: 4.5 | K140: https://amazon.com/dp/B07N66TTQG | L140: =IF(K140="","",HYPERLINK(K140,K140))
A141: ANCEL BD500 Bluetooth Diagnostic Scan Tool for VW Audi Seat Skoda Diagnosis, Full Systems Volkswagen OBD2 Scanner Vag Car Code Reader with Battery Check EPB Reset for iPhone, iPad & Android | B141: B0B1MHSMBW | C141: Dongle | D141: 81.931726 | E141: 165394.75 | F141: 53173.69 | G141: 2032 | H141: 649 | I141: 1729 | J141: 4.4 | K141: https://amazon.com/dp/B0B1MHSMBW | L141: =IF(K141="","",HYPERLINK(K141,K141))
A142: ANCEL BD300 Bluetooth OBD2 Scanner, Full System Code Reader and Diagnostic Tool for BMW with Battery Registration Service Reset EPB CBS ETC ABS Airbag & Powerful OBD2 Functions | B142: B09ZPB3JV9 | C142: Dongle | D142: 77.490212 | E142: 217183.79 | F142: 40217.42 | G142: 2646 | H142: 519 | I142: 2247 | J142: 4.5 | K142: https://amazon.com/dp/B09ZPB3JV9 | L142: =IF(K142="","",HYPERLINK(K142,K142))
A143: ANCEL Protective Case Storage Bag for OBD2 Scanner Code Reader Diagnostic Scan Tool Battery Tester | B143: B07B49PHXD | C143: Other | D143: 20.922359 | E143: 115079.44 | F143: 7804.04 | G143: 4661 | H143: 373 | I143: 4127 | J143: 4.6 | K143: https://amazon.com/dp/B07B49PHXD | L143: =IF(K143="","",HYPERLINK(K143,K143))
A144: ANCEL BM500 OBD2 Scanner for BMW & MINI, Simplified Battery Registration, EPB, Oil, Throttle, PCM Resets, I/M Readiness, Full System Diagnostics for Engine, Transmission, ABS, SRS, DSC & More | B144: B08925H3H1 | C144: Handheld | D144: 104.30181 | E144: 482419.17 | F144: 36401.33 | G144: 4886 | H144: 349 | I144: 886 | J144: 4.5 | K144: https://amazon.com/dp/B08925H3H1 | L144: =IF(K144="","",HYPERLINK(K144,K144))
A145: ANCEL X7HD 10.1'' Heavy Duty Truck Scanner, Semi Trucks Full System Diagnostic Tool, Bidirectional Diesel Scan Tool with DPF, ECU Coding, 40+ Reset for Cummins, Detroit, Caterpillar, Volvo, Paccar etc | B145: B0BZ82WQ4Q | C145: Tablet | D145: 765.33645 | E145: 2614467.8 | F145: 267102.42 | G145: 3257 | H145: 349 | I145: 796 | J145: 3.7 | K145: https://amazon.com/dp/B0BZ82WQ4Q | L145: =IF(K145="","",HYPERLINK(K145,K145))
A146: ANCEL DS500BT Bidirectional Scan Tool, Full-System Automotive Diagnostic Scanner with 28+ Services, Injector Coding, DPF/Brake/BMS/Oil/Gear/Throttle Functions, CAN FD Support, Lifetime Free Updates | B146: B0FN4JHLY7 | C146: Tablet | D146: 493.77205 | E146: 1535661.4 | F146: 168376.27 | G146: 1499 | H146: 341 | I146: 1080 | J146: 4.6 | K146: https://amazon.com/dp/B0FN4JHLY7 | L146: =IF(K146="","",HYPERLINK(K146,K146))
... A162: ANCEL HD7000 Elite 7" Heavy Duty Truck Scanner with DPF Regen, Speed/Idle Adjustment, Service Reset, Diagnostic Tool for Cummins Detroit CAT Volvo Paccar Mack International, Lifetime Free Updates | B162: B0FP9BMYKG | C162: Tablet | D162: 520.85541 | E162: 555921.83 | F162: 51043.83 | G162: 516 | H162: 98 | I162: 77 | J162: 3.5 | K162: https://amazon.com/dp/B0FP9BMYKG | L162: =IF(K162="","",HYPERLINK(K162,K162))
A163: ANCEL X7HD PRO 10.1'' Heavy Duty Truck Scanner, Full-System Diesel Diagnostic Tool with DPF Regen, 42+ Reset, Bi-Directional and Active Test, ECU Coding, HDOBD/OBD2 Scanner for Diesel Trucks - Grey | B163: B0GLFSPMZ4 | C163: Tablet | D163: 940.765 | E163: 1067985.4 | F163: 88431.91 | G163: 94 | H163: 94 | K163: https://amazon.com/dp/B0GLFSPMZ4 | L163: =IF(K163="","",HYPERLINK(K163,K163))
A164: ANCEL VD700 OBD2 Diagnostic Code Reader Scan Tool Fit for Volkswagen Audi VW Skoda Seat, All Functions OBD11 Scanner for VAG Vehicles with Battery Registration EPB Reset (Upgraded VD500) | B164: B07WD9B7GR | C164: Handheld | D164: 147.13935 | E164: 763000.01 | F164: 13683.96 | G164: 5526 | H164: 93 | I164: 1729 | J164: 4.4 | K164: https://amazon.com/dp/B07WD9B7GR | L164: =IF(K164="","",HYPERLINK(K164,K164))
A165: Ancel AD310BT Bluetooth OBD2 Scanner & Engine Code Reader for Most 1996 OBD2 Vehicles 2-in-1 Car Diagnostic Tool with App for Android & iPhone, Battery Test, Trip Analysis, Performance Test - OBD | B165: B0CR42ZB1T | C165: Handheld | D165: 49.940989 | E165: 110122.71 | F165: 4544.63 | G165: 2340 | H165: 91 | I165: 148 | J165: 4.5 | K165: https://amazon.com/dp/B0CR42ZB1T | L165: =IF(K165="","",HYPERLINK(K165,K165))
A166: ANCEL AD530 PRO OBD2 Scanner with Battery Tester for Mechanics Technicians and Drivers Check Engine Light, Battery Health Test, Cranking & Charging Test, OBD2 Check Engine Diagnostics | B166: B0D6R66XZ5 | C166: Handheld | D166: 96.646092 | E166: 126547.41 | F166: 8408.21 | G166: 1230 | H166: 87 | I166: 162 | J166: 4.6 | K166: https://amazon.com/dp/B0D6R66XZ5 | L166: =IF(K166="","",HYPERLINK(K166,K166))
A167: ANCEL HD431 Heavy Duty Truck Scanner, DPF Regen & Forced Reset for Paccar & Detroit Engines, Full System Diagnostics Diesel Code Reader, Professional OBD2/HDOBD Mechanic Tool for Commercial Vehicles | B167: B0DB86T5F5 | C167: Tablet | D167: 290.21488 | E167: 197118.3 | F167: 24958.48 | G167: 680 | H167: 86 | I167: 199 | J167: 4.2 | K167: https://amazon.com/dp/B0DB86T5F5 | L167: =IF(K167="","",HYPERLINK(K167,K167))
A168: ANCEL JP700 JOBD OBD2 Japanese Car Scanner, JDM Automotive Code Reader Check Engine Light OBDII Diagnostic Scan Tool Fits for Toyota Nissan Honda Mazda Subaru Vehicle Diagnosis | B168: B07B8FV26L | C168: Handheld | D168: 49.74378 | E168: 35182.56 | F168: 4078.99 | G168: 705 | H168: 82 | I168: 614 | J168: 4 | K168: https://amazon.com/dp/B07B8FV26L | L168: =IF(K168="","",HYPERLINK(K168,K168))
A169: ANCEL BZ700 Mercedes Benz Sprinter/Vaneo/Vito/Viano/V/Metris/Citan/X Smart OBD2 Scanner, Full System Automotive Car Code Reader with All Reset Services, Battery Reset ABS Bleed Airbag EPB Oil SAS TPS | B169: B0B2NR31DQ | C169: Handheld | D169: 129.88648 | E169: 75150.76 | F169: 9221.94 | G169: 580 | H169: 71 | I169: 234 | J169: 3.6 | K169: https://amazon.com/dp/B0B2NR31DQ | L169: =IF(K169="","",HYPERLINK(K169,K169))
A170: ANCEL HD200 Bluetooth Heavy Duty Truck Scanner, Speed Limit and Idle Reset for Cummins & Caterpillar Engines, J1939/J1708 Diesel Code Reader & All-System Diagnostic Tool, Lifetime Free Updates | B170: B0D9JYL5Y5 | C170: Cable/Adapter | D170: 169.55435 | E170: 182229.9 | F170: 11699.25 | G170: 989 | H170: 69 | I170: 111 | J170: 3.6 | K170: https://amazon.com/dp/B0D9JYL5Y5 | L170: =IF(K170="","",HYPERLINK(K170,K170))
A171: ANCEL BD330 BMW OBD2 Scanner for BMW, MINI, and Rolls-Royce Vehicles, ABS Full-System Diagnostic Scan Tool, Battery Registration/BAT Check, EPB/Oil/Throttle Reset, 3-in-1 Bluetooth/Wired/HUD- Black | B171: B0CT39TV55 | C171: Handheld | D171: 81.645846 | E171: 59209.55 | F171: 5306.98 | G171: 637 | H171: 65 | I171: 58 | J171: 4.7 | K171: https://amazon.com/dp/B0CT39TV55 | L171: =IF(K171="","",HYPERLINK(K171,K171))
A172: ANCEL VOD700 All System OBD2 Scanner Fits for Volvo Car Code Reader Full Function Diagnostic Scan Tool ABS Bleeding Injector Oil ETC SRL BMS EPB TPMS Reset Tool | B172: B0B45WGSDX | C172: Handheld | D172: 130.48714 | E172: 79840.21 | F172: 8220.69 | G172: 614 | H172: 63 | I172: 142 | J172: 3.9 | K172: https://amazon.com/dp/B0B45WGSDX | L172: =IF(K172="","",HYPERLINK(K172,K172))
A173: ANCEL Waterproof Storage Case Bag for HD100 Heavy Duty Truck Scanner and Other Testers - Durable Zipper Carry Box (8.66’’ x 6.22’’ x 3.15’’) | B173: B0DPH4VF4Y | C173: Other | D173: 20.063065 | E173: 9140.86 | F173: 1243.91 | G173: 466 | H173: 62 | I173: 196 | J173: 4.3 | K173: https://amazon.com/dp/B0DPH4VF4Y | L173: =IF(K173="","",HYPERLINK(K173,K173))
A174: ANCEL OBD2 Scanner Extension Cable 3.3ft/1m, 16 Pin OBDII OBD2 Male to Female Extender Cord, OBD2 Diagnostic Extender Connector for All OBD2 Vehicles | B174: B0DS453BBG | C174: Cable/Adapter | D174: 16.570806 | E174: 14319.87 | F174: 1027.39 | G174: 1051 | H174: 62 | I174: 38 | J174: 4.6 | K174: https://amazon.com/dp/B0DS453BBG | L174: =IF(K174="","",HYPERLINK(K174,K174))
A175: ANCEL TD700 Fits for Toyota OBD2 Scanner, Engine Car Diagnostic Scan Tool Fit for Toyota Lexus Scion, All System Code Reader Reading/Erasing Code,1996-2021 | B175: B0BLYXVR4K | C175: Handheld | D175: 140.67115 | E175: 64599.42 | F175: 8580.94 | G175: 463 | H175: 61 | I175: 180 | J175: 4.1 | K175: https://amazon.com/dp/B0BLYXVR4K | L175: =IF(K175="","",HYPERLINK(K175,K175))
A176: ANCEL Protective Case Storage Bag for HD100, HD110, HD120, HD200, HD210 Heavy Duty Truck Scanners(Only The Case) | B176: B0FX24WF6Q | C176: Other | D176: 20.024333 | E176: 13400.9 | F176: 1201.46 | G176: 60 | H176: 60 | K176: https://amazon.com/dp/B0FX24WF6Q | L176: =IF(K176="","",HYPERLINK(K176,K176))
A177: ANCEL FX6100 Bidirectional Scan Tool, Full System OBD2 Scanner Diagnostic Tool with Lifetime Free Updates, 15+ Service Reset, AutoVIN, Automotive Diagnostic Scanner for Car, CAN FD & FCA AutoAuth | B177: B0F38JZ2PR | C177: Tablet | D177: 380.24881 | E177: 886612.38 | F177: 22434.68 | G177: 2781 | H177: 59 | I177: 280 | J177: 4.3 | K177: https://amazon.com/dp/B0F38JZ2PR | L177: =IF(K177="","",HYPERLINK(K177,K177))
A178: ANCEL BM700 PRO Fit for BMW Scanner - Battery Registration Tool, Code Reader for BMW/Mini/RR, Advanced OBD2 Scanner Auto V-I-N, Full System Diagnostic for BMW Scan Tool with All Reset Services (Blue) | B178: B0F7R3JGYM | C178: Handheld | D178: 158.70948 | E178: 512156.61 | F178: 9205.15 | G178: 3371 | H178: 58 | I178: 2245 | J178: 4.5 | K178: https://amazon.com/dp/B0F7R3JGYM | L178: =IF(K178="","",HYPERLINK(K178,K178))
A179: ANCEL Obd2 Female to 20 Pin Extension Convert Adapter OBD1 to OBD II Cable for 20 Pin E31 E32 E34 E36 E39 E38 E53 X 5 Z3 | B179: B0B2LKYW3T | C179: Cable/Adapter | D179: 15.884107 | E179: 10368.44 | F179: 889.51 | G179: 650 | H179: 56 | I179: 211 | J179: 4.4 | K179: https://amazon.com/dp/B0B2LKYW3T | L179: =IF(K179="","",HYPERLINK(K179,K179))
A180: ANCEL FX6000 Bidirectional Scan Tool, OBD2 Scanner & Engine Code Reader, Live Data, Oil/EPB/BMS/SAS/Throttle Reset, ABS Bleed, Car Diagnostic Scanner for Most Vehicles, Auto VIN, Lifetime Free Update | B180: B0F38MDM2H | C180: Tablet | D180: 277.18655 | E180: 348151.58 | F180: 15245.26 | G180: 1523 | H180: 55 | I180: 177 | J180: 4.5 | K180: https://amazon.com/dp/B0F38MDM2H | L180: =IF(K180="","",HYPERLINK(K180,K180))
A181: ANCEL Heavy Duty Truck Scanner HD601 All System Diesel Diagnostic Scan Tool fits for Cummins, Detroit, Freightliner, International, Paccar, Check Engine for Truck & Car 2 in 1 Code Reader (Gray) | B181: B0G2XHXW61 | C181: Handheld | D181: 168.25673 | E181: 95349.855 | F181: 8244.58 | G181: 114 | H181: 49 | I181: 658 | J181: 4 | K181: https://amazon.com/dp/B0G2XHXW61 | L181: =IF(K181="","",HYPERLINK(K181,K181))
A182: ANCEL BD200 OBD2 Scanner Bluetooth - Code Reader & Check Engine Diagnostic Scan Tools with Car Battery Test, Exclusive App on iOS & Android, Wireless OBDII Adapter Works for 1996 & Newer Vehicles | B182: B08DFYMTS6 | C182: Dongle | D182: 40.29587 | E182: 33790.61 | F182: 1853.61 | G182: 856 | H182: 46 | I182: 1914 | J182: 4.2 | K182: https://amazon.com/dp/B08DFYMTS6 | L182: =IF(K182="","",HYPERLINK(K182,K182))
A183: ANCEL Large Hard Protective Case Storage Box for ANCEL HD8000 Heavy Duty Truck Scanner (Only the Case) | B183: B0DPH4CDJ3 | C183: Other | D183: 30.171364 | E183: 8115.18 | F183: 1327.54 | G183: 280 | H183: 44 | I183: 72 | J183: 3.7 | K183: https://amazon.com/dp/B0DPH4CDJ3 | L183: =IF(K183="","",HYPERLINK(K183,K183))
A184: ANCEL BM700 PRO Fit for BMW Scanner - Battery Registration Tool, Code Reader for BMW/Mini/RR, Advanced OBD2 Scanner Auto V-I-N, Full System Diagnostic for BMW Scan Tool with All Reset Services (Red) | B184: B0F7R5J5Y6 | C184: Handheld | D184: 160.21884 | E184: 176945.24 | F184: 6889.41 | G184: 1113 | H184: 43 | I184: 2245 | J184: 4.5 | K184: https://amazon.com/dp/B0F7R5J5Y6 | L184: =IF(K184="","",HYPERLINK(K184,K184))
A185: ANCEL FX2000-US OBD2 Scanner Diagnostic Tool, ABS SRS Transmission Airbag Car Scanner, Check Engine Car Code Reader, Automotive Diagnostic Tool Lifetime Free Upgrade | B185: B07N69PC3D | C185: Tablet | D185: 173.16946 | E185: 357628.81 | F185: 6407.27 | G185: 2464 | H185: 37 | I185: 4064 | J185: 4.3 | K185: https://amazon.com/dp/B07N69PC3D | L185: =IF(K185="","",HYPERLINK(K185,K185))
A186: ANCEL EVA Hard Protective Case for V5 HD PRO Heavy Truck Scanner, Waterproof Shockproof Storage Bag with Large Capacity, Smooth Zippers and Easy Carry Handle, Travel Ready | B186: B0828TC9T9 | C186: Other | D186: 34.632353 | E186: 12742.131 | F186: 1177.5 | G186: 56 | H186: 34 | I186: 172 | J186: 4.2 | K186: https://amazon.com/dp/B0828TC9T9 | L186: =IF(K186="","",HYPERLINK(K186,K186))
A187: ANCEL MT500 PRO Motorcycle Scanner, Full-System OBD2 Diagnostic Tool with Quick Service Resets & Advanced Programming, Fits for Harley, Honda, Yamaha, Indian, Kawasaki, Suzuki, Polaris, BRP, Victory | B187: B0BN1YCCD8 | C187: Tablet | D187: 559.03353 | E187: 174572.87 | F187: 19007.14 | G187: 315 | H187: 34 | I187: 132 | J187: 4.1 | K187: https://amazon.com/dp/B0BN1YCCD8 | L187: =IF(K187="","",HYPERLINK(K187,K187))
A188: ANCEL AD610 Pro ABS SRS OBD2 Scanner, ABS Bleeding, SAS Calibration, ABS, Airbag, EPB, Oil Reset, Full OBD2 Functions, AutoVIN, Free Lifetime WiFi Updates | B188: B0DBZC9PRC | C188: Handheld | D188: 131.1525 | E188: 121233.2 | F188: 3672.27 | G188: 838 | H188: 28 | I188: 197 | J188: 4.3 | K188: https://amazon.com/dp/B0DBZC9PRC | L188: =IF(K188="","",HYPERLINK(K188,K188))
... A201: ANCEL HD Series-Compatible Printer for HD3100, HD3100 PRO, HD3200, HD3300, HD3400, HD3500, HD3600: Exclusive Heavy Duty Truck Scanner Diagnostic Tool Accessory for Diesel Vehicle Reports | B201: B097D8JHJG | C201: Other | D201: 148.0225 | E201: 9239.49 | F201: 592.09 | G201: 61 | H201: 4 | I201: 25 | J201: 3.8 | K201: https://amazon.com/dp/B097D8JHJG | L201: =IF(K201="","",HYPERLINK(K201,K201))
A202: ANCEL Large Eva Bag for DS500 Elite FX6100 FX6000 Elite OBD2 Scanner, S3000 S3000 PRO Automotive Smoke Machine Leak Detector... | B202: B0FZ9FKQH4 | C202: Other | D202: 29.913333 | E202: 1083.7831 | F202: 89.74 | G202: 3 | H202: 3 | K202: https://amazon.com/dp/B0FZ9FKQH4 | L202: =IF(K202="","",HYPERLINK(K202,K202))
A203: ANCEL Protective Case Storage Bag for Bluetooth Heavy Duty Truck Scanner – Compatible with HD110 Diesel Diagnostic Tool and Other Small Code Readers & Battery Testers | B203: B0G8DGNVR7 | C203: Other | D203: 20.386667 | E203: 702.14923 | F203: 61.16 | G203: 4 | H203: 3 | K203: https://amazon.com/dp/B0G8DGNVR7 | L203: =IF(K203="","",HYPERLINK(K203,K203))
A204: ANCEL FX2000 Plus OBD2 Scanner Diagnostic Tool with Protective Bag, ABS SRS Transmission Airbag Scan Tool, Check Engine Code Reader, Scanner for Car Lifetime Free Upgrade | B204: B0DQPJ8QVK | C204: Tablet | D204: 205.12 | E204: 22418.183 | F204: 410.24 | G204: 149 | H204: 2 | I204: 52 | J204: 4 | K204: https://amazon.com/dp/B0DQPJ8QVK | L204: =IF(K204="","",HYPERLINK(K204,K204))
A205: ANCEL OBD2 Diagnostic Scan Tools Protective Hard – Custom-fit for MT700, MT500Pro, MT500Plus, MR500, HD7000 Elite & HD8000 (Case Only) | B205: B0FLXQ35LZ | C205: Other | D205: 27.625 | E205: 645.54 | F205: 55.25 | G205: 3 | H205: 2 | K205: https://amazon.com/dp/B0FLXQ35LZ | L205: =IF(K205="","",HYPERLINK(K205,K205))
A206: ANCEL MT700 Motorcycle Diagnostic Tool for Harley BMW Kawasaki Suzuki Piaggio Ducati Obd2 Scanner, ABS Bleeding Check Engine Code Reader with Oil Light Reset, 31+ Function, 16 Brand-Specific Adapters | B206: B0CGXFXRJY | C206: Tablet | D206: 1059.54 | E206: 35597.91 | F206: 2119.08 | G206: 39 | H206: 2 | I206: 34 | J206: 4.3 | K206: https://amazon.com/dp/B0CGXFXRJY | L206: =IF(K206="","",HYPERLINK(K206,K206))
...

Sheet AUTEL
B7: Avg Price | C7: Avg Price MoM | D7: Avg Price YoY | E7: Quantity/Mo | F7: Qty by % | G7: Qty MoM | H7: Qty YoY | I7: Revenue/Mo | J7: Revenue by % | L7: Revenue MoM | M7: Revenue YoY
A8: Tablet $800+ | B8: 1904.8305 | C8: 0.033080843 | D8: -0.047155361 | E8: 893 | F8: 0.047866638 | G8: -0.11932939 | H8: -0.018681319 | I8: 1701013.6 | J8: 0.34082754 | L8: -0.090196062 | M8: -0.064955755
A9: Tablet $400-$800 | B9: 551.94336 | C9: 0.021962004 | D9: 0.056538215 | E9: 4539 | F9: 0.24329974 | G9: -0.16913784 | H9: 0.02808607 | I9: 2505270.9 | J9: 0.50197441 | L9: -0.15089044 | M9: 0.086212222
A10: Tablet $400- | B10: 207.06101 | C10: -0.047312888 | D10: -0.32133397 | E10: 159 | F10: 0.0085227273 | G10: -0.00625 | H10: 158 | I10: 32922.7 | J10: 0.006596633 | L10: -0.053267182 | M10: 106.9079
A11: Total Tablet | B11: 758.21987 | C11: 0.036543181 | D11: -0.021240031 | E11: 5591 | F11: 0.29968911 | G11: -0.15760133 | H11: 0.049755914 | I11: 4239207.3 | J11: 0.84939858 | L11: -0.1268174 | M11: 0.027459066
A12: Handheld $75+ | B12: 171.94188 | C12: -0.11391119 | D12: -0.066340479 | E12: 936 | F12: 0.050171527 | G12: -0.061183551 | H12: -0.33190578 | I12: 160937.6 | J12: 0.032246635 | L12: -0.16812525 | M12: -0.37622747
A13: Handheld $75- | B13: 35.877535 | C13: -0.034856642 | D13: 0.036452876 | E13: 5355 | F13: 0.28703902 | G13: -0.11282306 | H13: -0.10090665 | I13: 192124.2 | J13: 0.03849541 | L13: -0.14374707 | M13: -0.06813211
A14: Total Handheld | B14: 56.121729 | C14: -0.055373799 | D14: -0.11049724 | E14: 6291 | F14: 0.33721055 | G14: -0.10550263 | H14: -0.14489602 | I14: 353061.8 | J14: 0.070742045 | L14: -0.15503435 | M14: -0.23938264
A15: Total Dongle | B15: 95.283019 | C15: 0.023273165 | D15: 0.0011699984 | E15: 1388 | F15: 0.074399657 | G15: 0.092053501 | H15: 0.14050945 | I15: 132252.83 | J15: 0.026499144 | L15: 0.11746904 | M15: 0.14184384
A16: Total Other Tools | B16: 51.231676 | C16: -0.052698676 | D16: -0.2288476 | E16: 5102 | F16: 0.2734777 | G16: -0.017334361 | H16: 0.29591059 | I16: 261384.01 | J16: 0.052372812 | L16: -0.069119538 | M16: -0.00065543903
A17: Total | B17: 271.38613 | C17: -0.036682631 | D17: -0.025517314 | E17: 18372 | F17: 0.98477702 | G17: -0.087468336 | H17: 0.029993833 | I17: 4985905.9 | J17: 0.99901258 | L17: -0.1209424 | M17: 0.0037111573
A51: Rank by Revenue
A52: Product Name | B52: ASIN | C52: Type | D52: Avg Price | E52: Estimated 12mo Revenue | F52: Monthly Rev | G52: Estimated 12mo Units | H52: Monthly Units | I52: # of Reviews | J52: Tool Rating | K52: Column1 | L52: Link
A53: Autel Scanner MaxiCOM MK900BT, 2026 MK900-BT V2.0 Bidirectional Diagnostic Tool, 8in Up of MK900 MX900 MK808S MK808BT MX808S MK808Z, 3000+ Active Tests, 40+ Service, CAN-FD&DOIP, All System, FCA 11 OS | B53: B098PYB8XG | C53: Tablet | D53: 658.58882 | E53: 6161168.1 | F53: 503161.86 | G53: 9349 | H53: 764 | I53: 723 | J53: 4.6 | K53: https://amazon.com/dp/B098PYB8XG | L53: =IF(K53="","",HYPERLINK(K53,K53))
A54: Autel Scanner MaxiCheck MX808S, 2026 US Ver. of MaxiCOM MK808S MK808Z, Bidirectional 3000+ Active Test 11OS as MK900 MK900BT MX900, 28+ Service, OE All Systems OBD2 Diagnostic Tool, FCA, 10X Faster | B54: B08ML7T7KZ | C54: Tablet | D54: 427.35611 | E54: 3579921.3 | F54: 230772.3 | G54: 8319 | H54: 540 | I54: 722 | J54: 4.7 | K54: https://amazon.com/dp/B08ML7T7KZ | L54: =IF(K54="","",HYPERLINK(K54,K54))
A55: Autel MaxiCOM MK900 Bidirectional Scanner: 2026 Up of MaxiCheck MX808S MK808S, Work as MK900-BT MK900BT MX900 OBD2 Diagnostic Tool w/ 3000+ Active Test, 40+ Service, CAN-FD&DOIP, All System, FCA 11 OS | B55: B0GDY7WJB7 | C55: Tablet | D55: 589.08904 | E55: 1906578.9 | F55: 196755.74 | G55: 769 | H55: 334 | I55: 34 | J55: 4.9 | K55: https://amazon.com/dp/B0GDY7WJB7 | L55: =IF(K55="","",HYPERLINK(K55,K55))
A56: Autel Scanner MaxiCOM MK900BT, 2026 MK900-BT Bidirectional Diagnostic Scan Tool, 2.0 BT Ver. of MK900 MX900, 8in Up of MK808S MK808BT PRO MX808S MK808Z, 40+ Reset, 3K+ Active Tests, CAN FD & DoIP, FCA | B56: B09712X5CW | C56: Tablet | D56: 659.53915 | E56: 1662035.7 | F56: 186649.58 | G56: 2522 | H56: 283 | I56: 224 | J56: 4.5 | K56: https://amazon.com/dp/B09712X5CW | L56: =IF(K56="","",HYPERLINK(K56,K56))
A57: Autel Scanner MaxiCOM MK900: 2026 Updated as MK900BT MK900-BT MX900 Bidirectional Diagnostic Tool, 8in Up of MK808S MK808BT Pro MX808S 808Z, 3K+ Active Tests, 40+ Service, CAN-FD&DOIP, All System, FCA | B57: B073CQMF25 | C57: Tablet | D57: 570.78419 | E57: 2105668.9 | F57: 168952.12 | G57: 3714 | H57: 296 | I57: 598 | J57: 4.4 | K57: https://amazon.com/dp/B073CQMF25 | L57: =IF(K57="","",HYPERLINK(K57,K57))
A58: Autel Scanner MaxiIM KM100(X), 2026 New Car Diagnostic Scan Tool, Lifetime Fre.e Updates, OBD-Learn on 95% Car, Wireless Auto Tool, Auto VIN & Scan VIN/License, Android 9.0, 2+64GB, 5.5in 1280x720 | B58: B0G6DZWVJ5 | C58: Tablet | D58: 490.93022 | E58: 1430148.6 | F58: 154152.09 | G58: 862 | H58: 314 | I58: 81 | J58: 4.3 | K58: https://amazon.com/dp/B0G6DZWVJ5 | L58: =IF(K58="","",HYPERLINK(K58,K58))
A59: Autel MaxiSys Ultra S2 Scanner, 2026 Top Intelligen Scan Diagnostic with AI, 6-in-1 VCMI2, Up of MSUltra MS919, Topology 3.0, Multi-Point DVI, Motor Truspeed Repair, EV Test, 48+ Service, ECU Program | B59: B0DZC1M7MZ | C59: Tablet | D59: 5788.9904 | E59: 1594361.6 | F59: 133146.78 | G59: 280 | H59: 23 | I59: 22 | J59: 4.8 | K59: https://amazon.com/dp/B0DZC1M7MZ | L59: =IF(K59="","",HYPERLINK(K59,K59))
A60: Autel MaxiCheck MX900 Scanner, 2026 Bidirectional Scan Tool with 3000+ Active Test, DoIP&CAN FD, 40+ Service, US Ver. of MaxiCOM MK900 MK900BT, Up of MK808BT MK808S MX808S, All-Sys Diagnose, FCA 11OS | B60: B09JFXPYKL | C60: Tablet | D60: 558.045 | E60: 795686.26 | F60: 98215.92 | G60: 1423 | H60: 176 | I60: 117 | J60: 4.7 | K60: https://amazon.com/dp/B09JFXPYKL | L60: =IF(K60="","",HYPERLINK(K60,K60))
A61: Autel Professional OBD2 Scanner AL319 Code Reader, Enhanced Check and Reset Engine Fault Code, Live Data, Freeze Frame, CAN Car Diagnostic Scan Tools for All OBDII Vehicles After 1996, 2026 Upgraded | B61: B007XE8C74 | C61: Handheld | D61: 33.960223 | E61: 1137051.4 | F61: 91522.8 | G61: 33791 | H61: 2695 | I61: 25900 | J61: 4.6 | K61: https://amazon.com/dp/B007XE8C74 | L61: =IF(K61="","",HYPERLINK(K61,K61))
A62: Autel Scanner MaxiCOM MK808BT PRO, 2026 Bidirectional Diagnostic Scan Tool as MK900BT, 2.0 BT Ver. of MK808S MX808S MX900 MK900, 3000+ Active Tests, 28+ Reset, Injector Coding, All Systems, FCA, OS 11 | B62: B07FFT8SCC | C62: Tablet | D62: 548.40134 | E62: 698019.13 | F62: 89937.82 | G62: 1270 | H62: 164 | I62: 668 | J62: 4.5 | K62: https://amazon.com/dp/B07FFT8SCC | L62: =IF(K62="","",HYPERLINK(K62,K62))
A63: Autel Scanner MaxiCOM MK900BT: 2026 8in MK900-BT V2.0 Bidirectional Scan Tool, 33ft BT Ver. of MK900 MX900 MK808S MK808BT PRO MX808S MK808Z, 40+ Service, 3K+ Active Tests, DOIP CANFD, All System, FCA | B63: B07PGYY8SS | C63: Tablet | D63: 659.10015 | E63: 1124847.6 | F63: 85683.02 | G63: 1708 | H63: 130 | I63: 179 | J63: 4.6 | K63: https://amazon.com/dp/B07PGYY8SS | L63: =IF(K63="","",HYPERLINK(K63,K63))
A64: Autel MaxiCOM MK808Z OBD2 Scanner, 2026 Bidirectional Scan Tool Same As MK808S MX808S, Work as MaxiCheck MX900 MK900BT, Active Test, 28+ Service, All System Diagnose, Injector Coding, FCA Autoauth | B64: B094VZN94S | C64: Tablet | D64: 411.30111 | E64: 431895.76 | F64: 66630.78 | G64: 587 | H64: 162 | I64: 69 | J64: 4.2 | K64: https://amazon.com/dp/B094VZN94S | L64: =IF(K64="","",HYPERLINK(K64,K64))
... A106: Autel MaxiSYS MS906 MAX Scanner 2026, MS906MAX 10.1" V2.0 of MS906 PRO MP900BT MS908 MK908 with ECU C0ding, Top Bidirectional Scan Tool, 3000+ Tests, 40+ Service, All System, CAN FD & DoIP, OS 10, FCA | B106: B09TR9KTMB | C106: Tablet | D106: 1569.0017 | E106: 264142.72 | F106: 18828.02 | G106: 170 | H106: 12 | I106: 19 | J106: 4.7 | K106: https://amazon.com/dp/B09TR9KTMB | L106: =IF(K106="","",HYPERLINK(K106,K106))
A107: 2026 Autel MaxiCOM Ultra Lite Intelligent Scanner, 2 Years Free Update, Up of MS919 Elite II Pro Same as MaxiSys Ultra, Motor TruSpeed, Topology 2.0, 40+ Service, 3000+ Active Test, FCA SGW | B107: B0GVXCG3S3 | C107: Tablet | D107: 3127.9767 | E107: 218240.82 | F107: 18767.86 | G107: 9 | H107: 6 | K107: https://amazon.com/dp/B0GVXCG3S3 | L107: =IF(K107="","",HYPERLINK(K107,K107))
A108: Autel OBD2 Scanner MS309 Universal Car Engine Fault Code Reader, Check Engine Light and Emission Monitor Status, OBDII CAN Diagnostic Scan Tool | B108: B07Q5H7M5S | C108: Handheld | D108: 22.980344 | E108: 352413.8 | F108: 18016.59 | G108: 15683 | H108: 784 | I108: 17097 | J108: 4.6 | K108: https://amazon.com/dp/B07Q5H7M5S | L108: =IF(K108="","",HYPERLINK(K108,K108))
A109: Autel OBD2 Scanner AL329, Upgraded AutoLink AL319, Auto VIN, Check-Engine-Light Code Reader, MIL Reset, One-Click I/M Readiness, CAN Car Diagnostic Scan Tool, for All OBD II Vehicles After 1996 | B109: B0BHNRPZXR | C109: Handheld | D109: 34.989118 | E109: 143912.44 | F109: 17844.45 | G109: 4150 | H109: 510 | I109: 151 | J109: 4.6 | K109: https://amazon.com/dp/B0BHNRPZXR | L109: =IF(K109="","",HYPERLINK(K109,K109))
A110: Autel Code Reader Diagnostic Tool, 2026 OBDII Scan Tool with Lifetime Free Updates, Wireless BT Scan Tool, 2GB & 64GB Android 9.0, for Home Mechanics & DIYers | B110: B0F6VCB25L | C110: Cable/Adapter | D110: 536.79909 | E110: 142174.22 | F110: 17714.37 | G110: 266 | H110: 33 | I110: 28 | J110: 4.6 | K110: https://amazon.com/dp/B0F6VCB25L | L110: =IF(K110="","",HYPERLINK(K110,K110))
A111: Autel MaxiCheck MX900 OBD2 Scanner, Same as MaxiCOM MK900 MK900BT, Bidirectional Scan Tool, All System Diagnose for Cars, Up of MK808 MX808, 40+ Services, 3000+ Active Tests, CAN FD/DoIP, FCA | B111: B0C65KF99Q | C111: Tablet | D111: 552.00937 | E111: 180648.09 | F111: 17664.3 | G111: 327 | H111: 32 | I111: 143 | J111: 4.5 | K111: https://amazon.com/dp/B0C65KF99Q | L111: =IF(K111="","",HYPERLINK(K111,K111))
A112: Autel MaxiSys MS919 S2 AI Scanner, 2026 MS919S2 Same as Ultra S2 Up of MSUltra MS909 S2, Top Intelligent Scan Tool, Topology 3.0, 6-in-1 VCMI2 [$2000 Value], Multi-Point DVI, EV Test, 12+256GB, 13 OS | B112: B0FXMP177Q | C112: Tablet | D112: 4397.0725 | E112: 180516.89 | F112: 17588.29 | G112: 8 | H112: 4 | K112: https://amazon.com/dp/B0FXMP177Q | L112: =IF(K112="","",HYPERLINK(K112,K112))
A113: Autel MaxiTPMS TS408S PRO TPMS Programming Tool: 2026 Ver. Same as TS501 Pro 508WF MX808TS MK808TS MP900TS Relearn Tool, Activate Relearn 99% Sensors, Program Autel MX-Sensors, TPMS Reset/Diagnosis | B113: B07VZFHJ6H | C113: Handheld | D113: 188.86538 | E113: 131133.43 | F113: 17186.75 | G113: 694 | H113: 91 | I113: 994 | J113: 4.3 | K113: https://amazon.com/dp/B07VZFHJ6H | L113: =IF(K113="","",HYPERLINK(K113,K113))
A114: Autel MaxiSys MS909 Intelligent Scanner: 2026 MS909 Same as Ultra MS919, Up of MS908S PRO II Elite II PRO, Motor TruSpeed Repair as Ultra S2, Topology 2.0, ECU Programming, 40+ Resets, 3K+ Test | B114: B09FX53KGZ | C114: Tablet | D114: 3264.484 | E114: 124776 | F114: 16322.42 | G114: 41 | H114: 5 | I114: 5 | J114: 5 | K114: https://amazon.com/dp/B09FX53KGZ | L114: =IF(K114="","",HYPERLINK(K114,K114))
A115: Autel MaxiVCI V200 VCI200 Wireless Diagnostic Dongle, 2026 VCI 200 OBD2 Connector Adapter, Work with Scanner MK900BT MP900-BT MaxiSys MS906 PRO MS906MAX MS906 PRO-TS MK906 PRO-TS KM100 BT608 BT609 | B115: B0BBFY2848 | C115: Dongle | D115: 217.79274 | E115: 174695.21 | F115: 15898.87 | G115: 817 | H115: 73 | I115: 69 | J115: 4.6 | K115: https://amazon.com/dp/B0BBFY2848 | L115: =IF(K115="","",HYPERLINK(K115,K115))
A116: Autel AutoLink AL519 OBD2 Scanner Enhanced Mode 6 Car Diagnostic Tool Check Engine Code Reader CAN Scan Tool, Advanced Ver. of AL319 | B116: B07PQH6HSQ | C116: Handheld | D116: 59.997816 | E116: 198189.65 | F116: 15659.43 | G116: 3367 | H116: 261 | I116: 2617 | J116: 4.5 | K116: https://amazon.com/dp/B07PQH6HSQ | L116: =IF(K116="","",HYPERLINK(K116,K116))
A117: Autel MaxiPRO MP900 Scanner, 2026 Newer of MP808BT PRO MP808S MK900 MX900, ECU C0ding, Same as MS906 MAX MS906 PRO MP900BT, Bidirectional Diagnostic Scan Tool 3000+ Test, 40+ Service, CAN FD&DOIP, FCA | B117: B09YM7YPDJ | C117: Tablet | D117: 782.0555 | E117: 195658.22 | F117: 15641.11 | G117: 244 | H117: 20 | I117: 40 | J117: 4.5 | K117: https://amazon.com/dp/B09YM7YPDJ | L117: =IF(K117="","",HYPERLINK(K117,K117))
A118: Autel MK900 Scanner, 2026 OBD2 Diagnostic Tool Up of MK808S MX808S MK808BT, Works as MaxiCOM MX900 MK900BT MK900-BT w/ 3000+ Bidirectional Active Tests, All System, 40+ Resets, DOIP CANFD, FCA | B118: B07BQQFDKQ | C118: Tablet | D118: 552.84536 | E118: 335098.18 | F118: 15479.67 | G118: 598 | H118: 28 | I118: 147 | J118: 4.6 | K118: https://amazon.com/dp/B07BQQFDKQ | L118: =IF(K118="","",HYPERLINK(K118,K118))
A119: Autel MaxiPRO MP900TS Scanner: 2026 8in MP900-TS up of MaxiSYS MS906 PRO MS906TS MP900BT MK900-TS, Full TPMS as MS906 Pro-TS, Car Bidirectional Scan Tool, 40+ Service, All System, CAN FD&DOIP, OS 11.0 | B119: B073CS2RLP | C119: Tablet | D119: 1100.2371 | E119: 180615.59 | F119: 15403.32 | G119: 164 | H119: 14 | I119: 75 | J119: 4.6 | K119: https://amazon.com/dp/B073CS2RLP | L119: =IF(K119="","",HYPERLINK(K119,K119))
A120: 2026 Autel MaxiPRO MP808BT PRO, ECU Coding with 2 Year Update, Function as MS906 PRO MS906 MAX MP900 MP900BT, Bidirectional Scan Tool, 30+ Service, 3000+ Test, Up of MK900BT MK900 MX900 MK808S, OS 11 | B120: B09F3MZZ3F | C120: Tablet | D120: 693.41545 | E120: 164734.44 | F120: 15255.14 | G120: 230 | H120: 22 | I120: 85 | J120: 4.6 | K120: https://amazon.com/dp/B09F3MZZ3F | L120: =IF(K120="","",HYPERLINK(K120,K120))
A121: Autel Scanner IM608 PRO 2, 2026 IM608 II Automotive Diagnostic Tool with XP400 PRO GBOX3 Up of IM508S PRO/IM608 Advanced Function as Elite II Pro, 3000+ Tests, 40 Reset, OS10 4/128GB CAN FD DoIP | B121: B0FMKDJD8S | C121: Tablet | D121: 3047.282 | E121: 171633.58 | F121: 15236.41 | G121: 28 | H121: 5 | I121: 4 | J121: 5 | K121: https://amazon.com/dp/B0FMKDJD8S | L121: =IF(K121="","",HYPERLINK(K121,K121))
A122: Autel AutoLink AL619 Scanner, 2026 ABS SRS Airbag Warning Light Diagnostic Scan Tool, Up of AL519 ML519 ML619, 10 OBDII Test Modes, DTCs Lookup, Live Data, Turn Off Check Engine Light OBD2 Code Reader | B122: B0925G7QY1 | C122: Handheld | D122: 100.18558 | E122: 204498.18 | F122: 14727.28 | G122: 2083 | H122: 147 | I122: 568 | J122: 4.4 | K122: https://amazon.com/dp/B0925G7QY1 | L122: =IF(K122="","",HYPERLINK(K122,K122))
A123: Autel MaxiSys Ultra S2 AI Scanner, 2026 UltraS2 Top Intelligent Scan Tool, Up of MS919 S2 MSUltra EV, 6IN1 VCMI2, Multi-Point DVI, Topology 3.0, Motor Truspeed, 48+ Service, EV Tests, 3K+ Active Tests | B123: B0936PQ6Y8 | C123: Tablet | D123: 7024.125 | E123: 120907.04 | F123: 14048.25 | G123: 22 | H123: 2 | I123: 8 | J123: 5 | K123: https://amazon.com/dp/B0936PQ6Y8 | L123: =IF(K123="","",HYPERLINK(K123,K123))
A124: Autel MaxiSYS Ultra S2 OBD2 Scanner, New Diagnostic with AI, Upgraded MS Ultra, 6-in-1 VCMI2, Topology 3.0, EV Tests, WiFi 6, 48+ Services, Motor Truspeed Repair, Multi-Point DVI, ECU Programming | B124: B0F2M4JM9H | C124: Tablet | D124: 7000.395 | E124: 231332.12 | F124: 14000.79 | G124: 38 | H124: 2 | I124: 4 | J124: 5 | K124: https://amazon.com/dp/B0F2M4JM9H | L124: =IF(K124="","",HYPERLINK(K124,K124))
... A144: Autel Scanner MaxiSys Elite 2 PRO, 2026 Elite II PRO 2-Year Update $2590, ECU Functions as Ultra MS919 MS909, Up of MK908P, Bidirectional Diagnostic Scan Tool, Intelligent Motor, 40+ Reset, CANFD DoIP | B144: B09YGZRW51 | C144: Tablet | D144: 2163.412 | E144: 158404.19 | F144: 10817.06 | G144: 67 | H144: 5 | I144: 12 | J144: 4.6 | K144: https://amazon.com/dp/B09YGZRW51 | L144: =IF(K144="","",HYPERLINK(K144,K144))
A145: Autel IM508S PRO OBD2 Diagnostic Scanner, 2026 Full Bundle as 608 pro 2, Upgrade of IM508S IM508, 40+ Service, 3000+ Active Tests, All System Diagnostic, FCA, OS 11.0 | B145: B0GQ8F5F23 | C145: Tablet | D145: 1746.2067 | E145: 118560.5 | F145: 10477.24 | G145: 7 | H145: 6 | K145: https://amazon.com/dp/B0GQ8F5F23 | L145: =IF(K145="","",HYPERLINK(K145,K145))
A146: Autel MaxiSys MS906MAX OBD2 Scanner, Way Better Than MS906 Pro, 2026 MS906 MAX Up of MS906S MS906BT MS908, ECU Coding, 3000+ Active Test, 40+ Service, All System Diagnostic, CAN FD/DoIP, AutoScan 2.0 | B146: B0DRG4YXXJ | C146: Tablet | D146: 1470.29 | E146: 151807.58 | F146: 10292.03 | G146: 99 | H146: 7 | I146: 9 | J146: 4.7 | K146: https://amazon.com/dp/B0DRG4YXXJ | L146: =IF(K146="","",HYPERLINK(K146,K146))
A147: Autel MaxiIM IM608 PRO 2 Scanner with Full Kit ($1316), 2026 IM608 PRO II Diagnostic Tool Upgrade of IM608 Pro IM608S II IM508S, ECU as Elite II Pro, 40+Reset, 3000+ Active Tests, Full System | B147: B07NYR2STX | C147: Tablet | D147: 3340.15 | E147: 97390.836 | F147: 10020.45 | G147: 26 | H147: 3 | I147: 8 | J147: 4.5 | K147: https://amazon.com/dp/B07NYR2STX | L147: =IF(K147="","",HYPERLINK(K147,K147))
A148: Autel Scanner MaxiCOM MK908 Pro MS908S PRO II: 2026 J2534 Reprogramming Tool as MaxiSYS MS909 MS919 Elite II PRO Ultra Lite S2, OE Coding, 38+ Resets, All System Scan, 3K+ Active Tests, CANFD & DoIP | B148: B00RFUY6XU | C148: Tablet | D148: 1989.674 | E148: 154840.46 | F148: 9948.37 | G148: 78 | H148: 5 | I148: 177 | J148: 4.5 | K148: https://amazon.com/dp/B00RFUY6XU | L148: =IF(K148="","",HYPERLINK(K148,K148))
A149: Autel MaxiSYS MS906pro TS Autel Scanner Upgrade of MS906 Pro/ MS906TS/ MK908 Top Car Scanner CAN FD/Do IP 36+ Services All System Diagnostic ECU Coding 3000+ Test FCA OS 10 | B149: B0BG2M2ZFD | C149: Tablet | D149: 1652.3067 | E149: 133179.57 | F149: 9913.84 | G149: 87 | H149: 6 | I149: 20 | J149: 4.9 | K149: https://amazon.com/dp/B0BG2M2ZFD | L149: =IF(K149="","",HYPERLINK(K149,K149))
A150: Autel MaxiSys MS909CV 2026 Top Heavy Duty Truck Scanner for Semi Commercial Cars, Upgrade of MS908CV with Intelligent Scan, 60+ Services, J2534 Programmer Coding, 3000+ Test,Topology 2.0 | B150: B094XRTNPK | C150: Tablet | D150: 4843.98 | E150: 174614.44 | F150: 9687.96 | G150: 39 | H150: 2 | I150: 8 | J150: 4.6 | K150: https://amazon.com/dp/B094XRTNPK | L150: =IF(K150="","",HYPERLINK(K150,K150))
A151: Autel Scanner MaxiPRO MP900TS, 2026 8in MP900-TS Top TPMS as MS906 Pro-TS, Up of MaxiSYS MS906 PRO MS906TS MK900TS, Advanced Function 40+ Service, Bidirectional Scan Tool, Aut0 Scan 2.0 CAN FD&DOIP | B151: B08P1RBNHY | C151: Tablet | D151: 1074.9889 | E151: 112542.37 | F151: 9674.9 | G151: 102 | H151: 9 | I151: 115 | J151: 4.5 | K151: https://amazon.com/dp/B08P1RBNHY | L151: =IF(K151="","",HYPERLINK(K151,K151))
A152: Autel Scanner MaxiCheck MX808S-TS, 2026 TPMS & Bidirectional Diagnostic Scan Tool, Same as MK900TS MK808S-TS TS900 Up of MK808S MX808S, Top TPMS Programming Tool, 3000+ Test, 28+ Service, FCA, OS 11 | B152: B09QX781WY | C152: Tablet | D152: 635.49133 | E152: 80037.85 | F152: 9532.37 | G152: 124 | H152: 15 | I152: 77 | J152: 4.5 | K152: https://amazon.com/dp/B09QX781WY | L152: =IF(K152="","",HYPERLINK(K152,K152))
A153: Autel MaxiSys Ultra EV Scanner, 2026 Top EV Intelligent Scan Diagnostic Tool, with 5-in-1 VCMI & EVDiag KIT, High-Voltage System & Battery Pack Analysis, Up of Ultra/ MS919/ MS909 EV, E-C*U Program | B153: B0BM3D2K2J | C153: Tablet | D153: 4745.155 | E153: 111327.05 | F153: 9490.31 | G153: 21 | H153: 2 | I153: 9 | J153: 3.4 | K153: https://amazon.com/dp/B0BM3D2K2J | L153: =IF(K153="","",HYPERLINK(K153,K153))
A154: 2026 Autel Scanner MaxiIM IM508S PRO, Plus Upgraded $569 PRO Bundle, Same as IM608 PRO 2, Bidirectional Scan Tool, 40+ Service, 3000+ Tests, OE All System Diagnostics, Auto Scan 2.0, FCA, OS 11.0 | B154: B08DLGGXP6 | C154: Tablet | D154: 1569.7567 | E154: 111871.68 | F154: 9418.54 | G154: 69 | H154: 6 | I154: 36 | J154: 4.6 | K154: https://amazon.com/dp/B08DLGGXP6 | L154: =IF(K154="","",HYPERLINK(K154,K154))
A155: Autel MaxiSYS VCI100 Wireless Diagnostic Interface, 2026 MaxiVCI VCI V100 Car Communication Interface, OBD2 Connector Adapter Dongle, Compatible for Autel Scanner MS906BT MK906BT MS906TS | B155: B0BL79T62P | C155: Dongle | D155: 197.69319 | E155: 77984.32 | F155: 9291.58 | G155: 398 | H155: 47 | I155: 31 | J155: 4.6 | K155: https://amazon.com/dp/B0BL79T62P | L155: =IF(K155="","",HYPERLINK(K155,K155))
A156: Autel MaxiSys MS908CV II Truck Scanner: 2026 Heavy Duty Tool for Commercial Semi Trucks, OE C0ding, J-2534 Pr0grammer, 64 Service as MS909CV MS908S Pro II Elite II Pro Ultra Lite | B156: B0749MHKXT | C156: Tablet | D156: 3053.6733 | E156: 208369.92 | F156: 9161.02 | G156: 72 | H156: 3 | I156: 26 | J156: 4.4 | K156: https://amazon.com/dp/B0749MHKXT | L156: =IF(K156="","",HYPERLINK(K156,K156))
A157: Autel MaxiCOM MK808S Bidirectional Scanner: 2026 Same as MaxiCheck MX808S MX900 MK900BT MK808BT Pro, 3000+ Active Test, 28+ Service for 200+ Brands, OBD2 All System Diagnose, FCA Autoauth & SGW, OS 11 | B157: B0GX1WPD31 | C157: Tablet | D157: 477.02316 | E157: 101092.22 | F157: 9063.44 | G157: 19 | H157: 19 | K157: https://amazon.com/dp/B0GX1WPD31 | L157: =IF(K157="","",HYPERLINK(K157,K157))
A158: Autel MaxiSys MS909CV Truck Scanner: 2026 Top MS909CV Up of MS908CV II, Topology 2.0, Intelligent Scanner for Commercial/Heavy Duty Truck, ECU Programmer Coding, 3K+ Test, 64 Service, Auto Scan 2.0 | B158: B075ZLBR63 | C158: Tablet | D158: 4510.465 | E158: 96240.11 | F158: 9020.93 | G158: 21 | H158: 2 | I158: 6 | J158: 5 | K158: https://amazon.com/dp/B075ZLBR63 | L158: =IF(K158="","",HYPERLINK(K158,K158))
A159: Autel Scanner MaxiCOM MK906S PRO 2-TS: 2026 Up of MaxiSYS MS906 PRO2-TS/ MS906 MAX/ MS906PRO TS, Coding Same as Elite II PRO, Top TPMS Programming Tool, 40+ Services 3000+ Active Tests CAN FD DOIP | B159: B09YM9KJ1F | C159: Tablet | D159: 1490.2533 | E159: 76098.603 | F159: 8941.52 | G159: 28 | H159: 6 | I159: 9 | J159: 4.5 | K159: https://amazon.com/dp/B09YM9KJ1F | L159: =IF(K159="","",HYPERLINK(K159,K159))
A160: Autel MaxiSys Ultra Lite 2026 Top Autel Scanner 2 Year Free Update MaxiFlash VCI ECU C*ding/Pr*gr*mming Cloud Service Topology Mapping 40+ Services Advanced MS906 PRO MS908S PRO MS909 MS919 | B160: B0GQ3VXNV4 | C160: Tablet | D160: 2973.06 | E160: 106562.34 | F160: 8919.18 | G160: 5 | H160: 3 | K160: https://amazon.com/dp/B0GQ3VXNV4 | L160: =IF(K160="","",HYPERLINK(K160,K160))
A161: Autel MaxiSys Ultra 1-Year Update Service, Total Care Program (TCP) Card, One Year Software Subscription & Warranty | B161: B0G7FM9844 | C161: Other | D161: 1272.58 | E161: 85465.817 | F161: 8908.06 | G161: 16 | H161: 7 | K161: https://amazon.com/dp/B0G7FM9844 | L161: =IF(K161="","",HYPERLINK(K161,K161))
A162: Autel Scanner MaxiIM IM508S: 2026 Full Bidirectional Automotive Diagnostic Scan Tool, 3000+ Active Tests, 40+ Services, OE Full Sys, OS11, 4-Core, 4/64G, FCA AutoAuth, Upgraded of MK808S MK808 MK900 | B162: B0DFH2ZX33 | C162: Tablet | D162: 1270.45 | E162: 158246.54 | F162: 8893.15 | G162: 130 | H162: 7 | I162: 126 | J162: 4.6 | K162: https://amazon.com/dp/B0DFH2ZX33 | L162: =IF(K162="","",HYPERLINK(K162,K162))
A163: Autel Scanner KM100E OBD2 Tool: 2026 Lite Version of IM508 Pro, IM608 Pro 2 IM608S II, V200 Wireless BT Connect, Auto Scan 2.0, Android 9.0, 10X Faster Hardware, Full Functions, Support 150-200 Brands | B163: B07Q2LMS7J | C163: Tablet | D163: 522.76471 | E163: 27109.08 | F163: 8887 | G163: 51 | H163: 17 | I163: 187 | J163: 4.5 | K163: https://amazon.com/dp/B07Q2LMS7J | L163: =IF(K163="","",HYPERLINK(K163,K163))
A164: Autel MaxiTPMS TS508WF TPMS Programming Tool, WiFi Relearn & Reset for Tire Pressure Sensors, Diagnose, Activate & Program MX-Sensors (315/433MHz), OBD2 Scanner, Free Lifetime Updates | B164: B0DGQ5N9K2 | C164: Handheld | D164: 261.17118 | E164: 73002.59 | F164: 8879.82 | G164: 276 | H164: 34 | I164: 11 | J164: 4.8 | K164: https://amazon.com/dp/B0DGQ5N9K2 | L164: =IF(K164="","",HYPERLINK(K164,K164))
A165: Autel MaxiLink ML519 Enhanced Mode 6 OBD2 Scanner Auto Diagnostic Scan Tool Check Engine Fault Code Reader CAN Scan Tool, Upgraded Ver. of AL319 | B165: B07NQFM2P2 | C165: Handheld | D165: 59.993147 | E165: 78102.86 | F165: 8579.02 | G165: 1326 | H165: 143 | I165: 2617 | J165: 4.5 | K165: https://amazon.com/dp/B07NQFM2P2 | L165: =IF(K165="","",HYPERLINK(K165,K165))
A166: Autel Scanner MaxiSys Elite 2 Pro : 2026 Elite II Pro with 2-Years Update, J2534 Tool as MS Ultra Lite MS909 S2 MS919 Up of MS908S PRO II, 40+ Service, 3K+ Active Test, DOIP CANFD, Intelligent Motor | B166: B00RD6B6MU | C166: Tablet | D166: 2090.51 | E166: 402704.74 | F166: 8362.04 | G166: 164 | H166: 4 | I166: 79 | J166: 4.4 | K166: https://amazon.com/dp/B00RD6B6MU | L166: =IF(K166="","",HYPERLINK(K166,K166))
A167: Autel MaxiSYS Ultra EV Intelligent Scanner, 2026 EV Ver.of Ultra S2 MS909S2, Up of Ultra MS909 MS909EV MS919, with EVDiag Kit, High-Voltage System & Battery Pack Analysis, 5-in-1 VCMI, Motor Truspeed | B167: B0BGSJYCTY | C167: Tablet | D167: 4150.275 | E167: 52253.47 | F167: 8300.55 | G167: 11 | H167: 2 | I167: 2 | J167: 5 | K167: https://amazon.com/dp/B0BGSJYCTY | L167: =IF(K167="","",HYPERLINK(K167,K167))
A168: Autel AutoLink AL519 OBD2 Scanner, Professional Mechanic OBDII & CAN Car Diagnostic Scan Tool, Code Reader for Check Engine Light, One-Click Smog Check, DTCs Lookup, Upgraded Ver. of AL319/ MS309 | B168: B07CJHWHNX | C168: Handheld | D168: 60.041812 | E168: 160812.08 | F168: 8285.77 | G168: 2717 | H168: 138 | I168: 1117 | J168: 4.5 | K168: https://amazon.com/dp/B07CJHWHNX | L168: =IF(K168="","",HYPERLINK(K168,K168))
A169: Autel Scanner MaxiCheck MX900, 2026 Bidirectional OBD2 Diagnostic Scan Tool with CAN FD DOIP, 8In US Ver. of MaxiCOM MK900 MK900BT V2.0 of MK808S MK808 MK808BT MX808S, 3000+ Active Test, 40+ Service | B169: B07PYSM27R | C169: Tablet | D169: 550.77267 | E169: 44446.42 | F169: 8261.59 | G169: 84 | H169: 15 | I169: 172 | J169: 4.4 | K169: https://amazon.com/dp/B07PYSM27R | L169: =IF(K169="","",HYPERLINK(K169,K169))
A170: Autel MaxiTPMS TS508WF TPMS Programming Tool Kit, 2026 WiFi Tire Sensor Relearn Activation Tool, Up of TS508 TS601 TS501 PRO, Clear TPMS DTCs, 4PCS 315+433MHz MX Sensors ($120), Lifetime Free Updates | B170: B0788GG1PZ | C170: Handheld | D170: 305.40222 | E170: 126993.28 | F170: 8245.86 | G170: 409 | H170: 27 | I170: 223 | J170: 4.5 | K170: https://amazon.com/dp/B0788GG1PZ | L170: =IF(K170="","",HYPERLINK(K170,K170))
A171: Autel MaxiSYS MS906MAX Scanner, 2026 10.1" MS906 MAX 2.0 Upgrade of MS906 PRO MP900BT MS906BT MS908S, OE ECU C0ding Bidirectional Scan Tool, 3000+ Active Test, 40+ Reset, All-System, CAN FD DoIP | B171: B0DXFPD42C | C171: Tablet | D171: 1645.336 | E171: 159389.9 | F171: 8226.68 | G171: 101 | H171: 5 | I171: 14 | J171: 4.5 | K171: https://amazon.com/dp/B0DXFPD42C | L171: =IF(K171="","",HYPERLINK(K171,K171))
A172: Autel MaxiSys Elite II Pro 2026 Diagnostic Scanner, J2534 ECU Programming Tool (As Ultra/MS908S PRO II), CAN FD & DoIP, Bidirectional Control, 150+ Car Brands, 40+ Services, 2-Year Free Updates | B172: B0FJLSKLBP | C172: Tablet | D172: 2736.58 | E172: 148654.02 | F172: 8209.74 | G172: 48 | H172: 3 | I172: 6 | J172: 5 | K172: https://amazon.com/dp/B0FJLSKLBP | L172: =IF(K172="","",HYPERLINK(K172,K172))
A173: Autel MaxiSYS Ultra S2 Diagnostic Scanner, 6-in-1 VCMI2, Topology 3.0, AI-Powered Inspection, EV/HV System Tests, WiFi 6, 48+ Services, Motor Truspeed Repair, Multi-Point DVI, ECU Programming, FCA SGW | B173: B0F3X8ZWBN | C173: Tablet | D173: 7865.08 | E173: 278360.85 | F173: 7865.08 | G173: 47 | H173: 1 | I173: 5 | J173: 4.4 | K173: https://amazon.com/dp/B0F3X8ZWBN | L173: =IF(K173="","",HYPERLINK(K173,K173))
... A207: Autel MaxiIM IM508S Pro OBD2 Diagnostic Scanner, 2026 All System Scan Tool w/Pro Accessory up of IM508S, Professional Automotive Tablet Work as IM608 Pro II w/ 40+ Reset Services, 3000+ Active Tests | B207: B0FSZDZ264 | C207: Tablet | D207: 1438.2 | E207: 67441.246 | F207: 5752.8 | G207: 6 | H207: 4 | I207: 1 | J207: 5 | K207: https://amazon.com/dp/B0FSZDZ264 | L207: =IF(K207="","",HYPERLINK(K207,K207))
A208: Autel - Maxisys Ultra Diagnostic Tablet with Advanced Vcmi (MSULTRA) | B208: B09WW69LMX | C208: Tablet | D208: 5612.21 | E208: 71392.96 | F208: 5612.21 | G208: 17 | H208: 1 | K208: https://amazon.com/dp/B09WW69LMX | L208: =IF(K208="","",HYPERLINK(K208,K208))
A209: Autel Original OBD2 16 Pin OBDII Y Splitter Extension Adapter Cable, 16Pin 1x Male to 2X Female Extension Y Connector, Fits for All Standard OBD II Scanners (1FT/30CM) | B209: B0DF2WK54W | C209: Cable/Adapter | D209: 19.981475 | E209: 55224.42 | F209: 5554.85 | G209: 2766 | H209: 278 | I209: 80 | J209: 4.6 | K209: https://amazon.com/dp/B0DF2WK54W | L209: =IF(K209="","",HYPERLINK(K209,K209))
A210: Autel Scanner MaxiPro MP900Z-BT: 2026 ECU Coding OBD2 Bidirectional Scan Tool with 40+ Services, Upgraded of MP900 MS906BT MP900BT All System OBDII Car Code Reader CAN FD, Alternative to MS906 Pro | B210: B0CCJMF7PY | C210: Tablet | D210: 914.57167 | E210: 33495.33 | F210: 5487.43 | G210: 36 | H210: 6 | I210: 136 | J210: 4.4 | K210: https://amazon.com/dp/B0CCJMF7PY | L210: =IF(K210="","",HYPERLINK(K210,K210))
A211: Autel MaxiDiag MD806 OBD2 Scanner, ABS SRS Engine Transmission 4 Systems Diagnostic Scan Tool, 7 Hot Service as MD808 Pro, Oil Reset D-P.F, EPB SAS BMS Throttle A/F, Up of MD805 MD802, Free Update | B211: B07PXQVKBY | C211: Handheld | D211: 169.72313 | E211: 54616.65 | F211: 5431.14 | G211: 284 | H211: 32 | I211: 1155 | J211: 4.3 | K211: https://amazon.com/dp/B07PXQVKBY | L211: =IF(K211="","",HYPERLINK(K211,K211))
A212: Autel Scanner MaxiPRO MP808BT PRO, 2 Years Update ($700), 2026 Up of MaxiSys MS906BT MaxiCOM MK900BT MK900, Advanced as MS906MAX MS906 PRO MP900-BT, 3000+ Active Test, 30+ Service, FCA, 11OS 4/ 64GB | B212: B09F2VJHW1 | C212: Tablet | D212: 675.16875 | E212: 102710.65 | F212: 5401.35 | G212: 138 | H212: 8 | I212: 108 | J212: 4.6 | K212: https://amazon.com/dp/B09F2VJHW1 | L212: =IF(K212="","",HYPERLINK(K212,K212))
A213: Autel Scanner MaxiIM IM508S, 2026 Full Bidirectional OBD2 Diagnostic Tool, 3000+ Active Tests, 40+ Services, OE All Systems OBDII Scan for All Cars, Up of IM508 MaxiCOM MK900BT MK900 MK808S, FCA | B213: B0FR4T4L8L | C213: Tablet | D213: 1337.8475 | E213: 59391.103 | F213: 5351.39 | G213: 29 | H213: 4 | I213: 84 | J213: 4.3 | K213: https://amazon.com/dp/B0FR4T4L8L | L213: =IF(K213="","",HYPERLINK(K213,K213))
A214: Autel Scanner KM100(E), OBD2 Diagnostic Scan Tool with Lifetime Free Updates, Professional Code Reader with 10X Fast Hardware, Versatile Auto Diagnostics Toolkit for Pros & DIYers | B214: B0GWDV6WJ7 | C214: Tablet | D214: 531.931 | E214: 64240.898 | F214: 5319.31 | G214: 10 | H214: 10 | K214: https://amazon.com/dp/B0GWDV6WJ7 | L214: =IF(K214="","",HYPERLINK(K214,K214))
A215: Autel MaxiSys MaxiVCI VCI Mini OBD2 Adapter Connector, 2026 Vehicle Wireless Diagnostic Interface, Work w/Autel Scanner MaxiCOM MK808BT PRO MK808Z-BT MK808K-BT MP808BT Pro MK808S-TS MP808S-TS MK808TS | B215: B0F26J3QSC | C215: Tablet | D215: 118.54545 | E215: 40237.239 | F215: 5216 | G215: 300 | H215: 44 | I215: 17 | J215: 4.6 | K215: https://amazon.com/dp/B0F26J3QSC | L215: =IF(K215="","",HYPERLINK(K215,K215))
A216: Autel MaxiSYS EV Box Upgrade Kit, 2026 Fit Ultra S2 MS919S2 UltraADAS MSUltra MS919 MS909, Same EV Adapters in UltraEV, Full Electric Vehicle Diagnostics, High-Voltage System & Battery Pack Analysis | B216: B0FG7JR9DW | C216: Tablet | D216: 867.38333 | E216: 38427.615 | F216: 5204.3 | G216: 11 | H216: 6 | K216: https://amazon.com/dp/B0FG7JR9DW | L216: =IF(K216="","",HYPERLINK(K216,K216))
A217: Autel MaxiSys Ultra ADAS, 2026 Top Intelligent Scan Diagnostic Tool with ADAS System Calibration Software, Up of MSUltra Lite MS919 MS909 MS908 Pro, Topology 2.0, 40+ Services, J2534 Programming | B217: B0D8VMZL46 | C217: Tablet | D217: 5202.06 | E217: 58264.89 | F217: 5202.06 | G217: 11 | H217: 1 | I217: 1 | J217: 5 | K217: https://amazon.com/dp/B0D8VMZL46 | L217: =IF(K217="","",HYPERLINK(K217,K217))
A218: Autel MS300 OBD2 Scanner Code Reader, Turn Off Check Engine Light, Read & Erase Fault Codes, Check Emission Monitor Status CAN Diagnostic Scan Tool | B218: B001LHVOVK | C218: Handheld | D218: 19.990233 | E218: 83621.548 | F218: 5137.49 | G218: 4001 | H218: 257 | I218: 20195 | J218: 4.4 | K218: https://amazon.com/dp/B001LHVOVK | L218: =IF(K218="","",HYPERLINK(K218,K218))
A219: 2026 Autel MaxiSys MS909CV Truck Scanner: Top Heavy Duty Truck Tool for Semi Commercial Cars, Updated of MS908CV with Intelligent Diagnosis, Topology, J2534 ECU C0ding, 64+ Services, Active Test | B219: B08F7TQZ41 | C219: Tablet | D219: 5078.48 | E219: 66517.05 | F219: 5078.48 | G219: 15 | H219: 1 | I219: 3 | J219: 5 | K219: https://amazon.com/dp/B08F7TQZ41 | L219: =IF(K219="","",HYPERLINK(K219,K219))
A220: Autel MaxiCheck MX900 Scanner, 2026 Bidirectional Scan Tool with 3000+ Active Tests, All System Diagnosis, CAN FD/Do IP, OE No-IP Limited, Upgrade MK808S MK808BT MX808S MK808Z Same as MK900 | B220: B0C1RPXXQ8 | C220: Tablet | D220: 553.16778 | E220: 68782.048 | F220: 4978.51 | G220: 117 | H220: 9 | I220: 56 | J220: 4.5 | K220: https://amazon.com/dp/B0C1RPXXQ8 | L220: =IF(K220="","",HYPERLINK(K220,K220))
A221: Autel MaxiFlash VCI Kit, J2534 Pass-Thru Programming Device, Compatible with MS909/MS909EV/MS909CV/Ultra Lite/Elite II Pro, Supports CAN FD, DoIP, RP1210, ECU Coding & BMW Benz Programming | B221: B0BS2LXT6X | C221: VCI | D221: 979.47 | E221: 28237.603 | F221: 4897.35 | G221: 11 | H221: 5 | I221: 5 | J221: 4.7 | K221: https://amazon.com/dp/B0BS2LXT6X | L221: =IF(K221="","",HYPERLINK(K221,K221))
A222: 2026 Autel MaxiSYS Ultra Scanner: Top Auto Tool with 40+ Service, 5-in-1 VCMI, Intelligent Scan, Topology Map, OE Programming & Coding, Upgraded of MaxiCOM Ultra Lite Elite II Pro MS919 Ultra EV | B222: B08SVXHWK9 | C222: Tablet | D222: 4811.05 | E222: 175019.35 | F222: 4811.05 | G222: 44 | H222: 1 | I222: 30 | J222: 4.4 | K222: https://amazon.com/dp/B08SVXHWK9 | L222: =IF(K222="","",HYPERLINK(K222,K222))
A223: Autel MaxiPRO MP900 Scanner, 2026 MP900 Same as MP900BT MS906 PRO MS906MAX, Up of MS906 MP808BT PRO MP808S MK900 MX900, Bidirectional Scan Tool, 3K+ Test, 40+ Resets, CAN FD & DOIP, 11.0 OS | B223: B0F5H3MBQW | C223: Tablet | D223: 795.88667 | E223: 30263.518 | F223: 4775.32 | G223: 32 | H223: 6 | I223: 6 | J223: 4.4 | K223: https://amazon.com/dp/B0F5H3MBQW | L223: =IF(K223="","",HYPERLINK(K223,K223))
A224: Autel AutoLink AL619 OBD2 Scanner | 2026 ABS/SRS/CAN Diagnostic Tool | Read/Erase Codes, Check Engine Light, OBDII Live Data & DTC Library | Upgrade for AL519, ML519, ML619 (Vehicle-Specific) | B224: B07PQJTQN2 | C224: Handheld | D224: 98.944894 | E224: 53003.97 | F224: 4650.41 | G224: 529 | H224: 47 | I224: 545 | J224: 4.4 | K224: https://amazon.com/dp/B07PQJTQN2 | L224: =IF(K224="","",HYPERLINK(K224,K224))
A225: Autel APB112 Accessory Tool, Working with Autel MaxiIM IM608Pro II/ IM608S II/ IM608 II/ IM508S II/ XP400 PRO | B225: B0DFXSX4Y1 | C225: Key | D225: 256.32056 | E225: 53293.57 | F225: 4613.77 | G225: 208 | H225: 18 | I225: 10 | J225: 5 | K225: https://amazon.com/dp/B0DFXSX4Y1 | L225: =IF(K225="","",HYPERLINK(K225,K225))
A226: Autel MaxiPRO MP900-BT Kit Scanner w/ 200 Bucks OBD1 Kit: 2026 MP900BT Kit New Model of MK900BT MP900-BT(No Cables), Pro C0ding as MS906 Pro MS906 MAX, 40+ Service, 3000+ Tests, OS 11, CAN FD FCA SGW | B226: B01CQNNBA4 | C226: Tablet | D226: 918.318 | E226: 111525.97 | F226: 4591.59 | G226: 116 | H226: 5 | I226: 248 | J226: 4.6 | K226: https://amazon.com/dp/B01CQNNBA4 | L226: =IF(K226="","",HYPERLINK(K226,K226))
A227: 2026 Autel MaxiIM XP400 PRO Bi-Directional K** Progra-mer I-O Tool, 3000+ Chip Re-d/Wr-te/Learn/F-OB, EEPROM-Data, Work with Autel Scanner IM508 IM608 IM508S IM608 Pro 2 IM608S II | B227: B0DFWNZPQG | C227: Other | D227: 506.84778 | E227: 34105.95 | F227: 4561.63 | G227: 68 | H227: 9 | I227: 34 | J227: 4.3 | K227: https://amazon.com/dp/B0DFWNZPQG | L227: =IF(K227="","",HYPERLINK(K227,K227))
A228: Autel MaxiSys MS906 Pro-TS Scanner, 2026 Same as MS906 PRO2-TS Up of MP900TS MS-906MAX MS906PRO, Top TPMS Scan Tool W/OE C0d-ing, 3000+ Active Test, 36+ Service, CAN FD&DoIP Auto Scan 2.0 | B228: B071RLXN2W | C228: Tablet | D228: 1519.7333 | E228: 96759.39 | F228: 4559.2 | G228: 61 | H228: 3 | I228: 26 | J228: 4.7 | K228: https://amazon.com/dp/B071RLXN2W | L228: =IF(K228="","",HYPERLINK(K228,K228))
... A260: 2026 Autel Scanner MaxiPRO MP900 KIT, Up of MP900 MP900BT MK900 MK900BT w/ 200 Bucks 11PCS OBD Adapter, Same OE C0ding as MS906 PRO MS906MAX MK908, CAN FD DoIP, 3K+ Bidirectional Diagnostic, 40+ Reset | B260: B08PDJ21WS | C260: Tablet | D260: 821.495 | E260: 85582.53 | F260: 3285.98 | G260: 99 | H260: 4 | I260: 58 | J260: 4.4 | K260: https://amazon.com/dp/B08PDJ21WS | L260: =IF(K260="","",HYPERLINK(K260,K260))
A261: Autel IM508S Pro Scanner OE Level Automotive Diagnostic Scan Tool 5X Faster Android 11.0 View Freeze Frame and Live Data FCA SGW 40+ Service Auto Scan 2.0 4-Core 4/64G | B261: B0G2RJ5HFL | C261: Tablet | D261: 1614.995 | E261: 53850.425 | F261: 3229.99 | G261: 20 | H261: 2 | K261: https://amazon.com/dp/B0G2RJ5HFL | L261: =IF(K261="","",HYPERLINK(K261,K261))
A262: 2026 Autel Scanner MaxilM IM508S PRO OBD II Diagnostic Scan Tool, Same as IM608 PRO 2/ IM608S II, Enhanced of IM508S IM508 | B262: B07PQ878S5 | C262: Tablet | D262: 1603.71 | E262: 54936.99 | F262: 3207.42 | G262: 34 | H262: 2 | I262: 13 | J262: 4.3 | K262: https://amazon.com/dp/B07PQ878S5 | L262: =IF(K262="","",HYPERLINK(K262,K262))
A263: Autel MaxiDiag MD909 PRO OBD2 Scanner, 2026 MD909PRO Car Code Reader All System Diagnostic Tool, 11 Reset Services, AutoVIN, No Subscription Fee, Lite of MaxiCOM MK808S MX808S MK808BT, CAN FD& FCA SGW | B263: B0FMRPF7W1 | C263: Tablet | D263: 320.28 | E263: 39537.185 | F263: 3202.8 | G263: 65 | H263: 10 | I263: 2 | J263: 4.5 | K263: https://amazon.com/dp/B0FMRPF7W1 | L263: =IF(K263="","",HYPERLINK(K263,K263))
...

Sheet Foxwell
B7: Avg Price | C7: Avg Price MoM | D7: Avg Price YoY | E7: Quantity/Mo | F7: Qty by % | G7: Qty MoM | H7: Qty YoY | I7: Revenue/Mo | J7: Revenue by % | L7: Revenue MoM | M7: Revenue YoY
A8: Tablet $400-$800 | B8: 490.57775 | C8: -0.075866803 | D8: 0.03678774 | E8: 369 | F8: 0.024918963 | G8: 0.17142857 | H8: 0.43579767 | I8: 181023.19 | J8: 0.090310242 | L8: 0.082556031 | M8: 0.48861742
A9: Tablet $400- | B9: 198.57807 | C9: 0.060018384 | D9: 0.026916793 | E9: 4694 | F9: 0.31699082 | G9: -0.079246763 | H9: 0.48497311 | I9: 932125.45 | J9: 0.46502592 | L9: -0.023984642 | M9: 0.52494382
A10: Total Tablet | B10: 219.8595 | C10: 0.05287803 | D10: 0.014979331 | E10: 5063 | F10: 0.34190978 | G10: -0.066728111 | H10: 0.47652377 | I10: 1113148.6 | J10: 0.55533616 | L10: -0.017378531 | M10: 0.49864111
A11: Handheld $75+ | B11: 153.12191 | C11: 0.0065628425 | D11: 0.072558376 | E11: 3088 | F11: 0.20853593 | G11: 0.12005803 | H11: 0.24465941 | I11: 472840.47 | J11: 0.23589429 | L11: 0.1274088 | M11: 0.33496988
