Workbook

Sheet Summary
A1: July '26 Monthly Summary
B3: Avg Price | C3: Avg Price MoM | D3: Avg Price YoY | E3: Quantity/Mo | F3: Qty by % | G3: Qty MoM | H3: Qty YoY | I3: Revenue/Mo | J3: Revenue by % | K3: Revenue MoM | L3: Revenue YoY
A4: Tablet $800+ | B4: 1406.8611 | C4: -0.022631585 | D4: -0.052279211 | E4: 2768 | F4: 0.0094059759 | G4: -0.14329929 | H4: -0.042214533 | I4: 3894191.6 | J4: 0.12036917 | K4: -0.16268778 | L4: -0.092286802
A5: Tablet $400-$800 | B5: 539.83251 | C5: -0.037189415 | D5: 0.035243678 | E5: 12352 | F5: 0.041973488 | G5: -0.18950131 | H5: 0.029762401 | I5: 6668011.1 | J5: 0.20610772 | K5: -0.21964328 | L5: 0.066055015
A6: Tablet $400- | B6: 209.72935 | C6: -0.018292626 | D6: 0.036285409 | E6: 24480 | F6: 0.083185799 | G6: -0.1179332 | H6: 0.27089606 | I6: 5134174.6 | J6: 0.15869695 | K6: -0.13406851 | L6: 0.31701105
A7: Total Tablet | B7: 396.37317 | C7: -0.041975622 | D7: -0.062891283 | E7: 39600 | F7: 0.13456526 | G7: -0.14330218 | H7: 0.15969192 | I7: 15696377 | J7: 0.48517384 | K7: -0.1792626 | L7: 0.086757408
A8: Handheld $75+ | B8: 180.22417 | C8: -0.0016173916 | D8: 0.051403239 | E8: 19050 | F8: 0.064734047 | G8: -0.02870545 | H8: 0.026566794 | I8: 3433270.4 | J8: 0.10612213 | K8: -0.030276414 | L8: 0.079335653
A9: Handheld $75- | B9: 30.780802 | C9: -0.018278528 | D9: -0.030450769 | E9: 99909 | F9: 0.33950204 | G9: -0.0014292568 | H9: -0.037513367 | I9: 3075279.1 | J9: 0.095056645 | K9: -0.01968166 | L9: -0.066821825
A10: Total Handheld | B10: 54.712543 | C10: -0.019514423 | D10: 0.033695623 | E10: 118959 | F10: 0.40423609 | G10: -0.0058998036 | H10: -0.027795031 | I10: 6508549.5 | J10: 0.20117877 | K10: -0.025299096 | L10: 0.0049640211
A11: Total Dongle | B11: 79.634064 | C11: -0.081148913 | D11: 0.01093587 | E11: 70393 | F11: 0.23920335 | G11: -0.042975229 | H11: 0.024613548 | I11: 5605680.7 | J11: 0.17327117 | K11: -0.12063675 | L11: 0.035818589
A12: Total Other Tools | B12: 70.644106 | C12: -0.11515887 | D12: -0.08130698 | E12: 63693 | F12: 0.21643599 | G12: -0.0099790161 | H12: 0.38698227 | I12: 4499535 | J12: 0.13908029 | K12: -0.12398871 | L12: 0.27421093
A13: Total | B13: 110.40729 | C13: -0.10114344 | D13: 0.0024129621 | E13: 292645 | F13: 0.99444069 | G13: -0.036648474 | H13: 0.079349097 | I13: 32310143 | J13: 0.99870406 | K13: -0.13408516 | L13: 0.081953525
A45: July '26 Monthly Summary - Revenue
A46: Brand | B46: # of Listings | C46: Monthly Rev | D46: Estimated 12mo Revenue | E46: Monthly Units | F46: Monthly Rev Market Share % | G46: Price Per Unit | H46: Total Reviews | I46: Avg Rating
A47: autel | B47: 549 | C47: 5379094.3 | D47: 65893996 | E47: 19094 | F47: 0.1663 | G47: 281.72 | H47: 133280 | I47: 4.2
A48: ancel | B48: 98 | C48: 2928004.5 | D48: 35077611 | E48: 45181 | F48: 0.0905 | G48: 64.81 | H48: 132284 | I48: 3.9
A49: topdon | B49: 62 | C49: 2709586.9 | D49: 36642541 | E49: 11551 | F49: 0.0838 | G49: 234.58 | H49: 31472 | I49: 4.1
A50: launch | B50: 282 | C50: 2115401.8 | D50: 31923133 | E50: 5646 | F50: 0.0654 | G50: 374.67 | H50: 76897 | I50: 3.8
A51: foxwell | B51: 55 | C51: 2070737.2 | D51: 23299903 | E51: 14797 | F51: 0.064 | G51: 139.94 | H51: 71849 | I51: 4
A52: innova | B52: 28 | C52: 1704290.9 | D52: 19448456 | E52: 8901 | F52: 0.0527 | G52: 191.47 | H52: 18620 | I52: 3.9
A53: xtool | B53: 71 | C53: 1688939.4 | D53: 18764664 | E53: 7046 | F53: 0.0522 | G53: 239.7 | H53: 12839 | I53: 4.2
A54: obdlink | B54: 4 | C54: 1234069.9 | D54: 15618816 | E54: 14008 | F54: 0.0381 | G54: 88.1 | H54: 37983 | I54: 4.6
A55: bluedriver | B55: 3 | C55: 1102294.6 | D55: 12527462 | E55: 11010 | F55: 0.0341 | G55: 100.12 | H55: 125779 | I55: 3
A56: mucar | B56: 19 | C56: 819251.95 | D56: 6048042 | E56: 2131 | F56: 0.0253 | G56: 384.44 | H56: 3734 | I56: 4.4
A57: generic | B57: 203 | C57: 816277.77 | D57: 5956257.6 | E57: 3466 | F57: 0.0252 | G57: 235.51 | H57: 1623 | I57: 1.8
A58: thinkcar | B58: 28 | C58: 746388.21 | D58: 10402801 | E58: 2980 | F58: 0.0231 | G58: 250.47 | H58: 10953 | I58: 3.8
... A71: bosch | B71: 15 | C71: 222987.61 | D71: 1711230.6 | E71: 206 | F71: 0.0069 | G71: 1082.46 | H71: 285 | I71: 3.2
A73: Total | B73: =SUM(B46:B71) -> 1750 | C73: =SUM(C47:C71) -> 28079752 | D73: =SUM(D47:D71) -> 3.3307135e+08 | E73: =SUM(E47:E71) -> 195083 | F73: =SUM(F47:F71) -> 0.8682 | G73: =AVERAGE(G47:G71) -> 263.3616 | H73: =SUM(H47:H71) -> 877051 | I73: =AVERAGE(I47:I71) -> 3.876
A76: July '26 Summary - Units
A77: Brand | B77: # of Listings | C77: Monthly Rev | D77: Estimated 12mo Units | E77: Monthly Units | F77: Monthly Unit Market Share % | G77: Price Per Unit | H77: Reviews | I77: Avg Rating
A78: ancel | B78: 98 | C78: 2928004.5 | D78: 589947.69 | E78: 45181 | F78: 0.1535 | G78: 64.81 | H78: 132284 | I78: 3.9
A79: autel | B79: 549 | C79: 5379094.3 | D79: 228949.85 | E79: 19094 | F79: 0.0649 | G79: 281.72 | H79: 133280 | I79: 4.2
A80: foxwell | B80: 55 | C80: 2070737.2 | D80: 177126.46 | E80: 14797 | F80: 0.0503 | G80: 139.94 | H80: 71849 | I80: 4
A81: obdlink | B81: 4 | C81: 1234069.9 | D81: 161243.08 | E81: 14008 | F81: 0.0476 | G81: 88.1 | H81: 37983 | I81: 4.6
A82: motopower | B82: 9 | C82: 289964.62 | D82: 133705.85 | E82: 12161 | F82: 0.0413 | G82: 23.84 | H82: 62031 | I82: 4.3
A83: topdon | B83: 62 | C83: 2709586.9 | D83: 150843.69 | E83: 11551 | F83: 0.0393 | G83: 234.58 | H83: 31472 | I83: 4.1
A84: bluedriver | B84: 3 | C84: 1102294.6 | D84: 144433.85 | E84: 11010 | F84: 0.0374 | G84: 100.12 | H84: 125779 | I84: 3
A85: veepeak | B85: 5 | C85: 323973.18 | D85: 91291.385 | E85: 9819 | F85: 0.0334 | G85: 32.99 | H85: 54026 | I85: 4.6
A86: innova | B86: 28 | C86: 1704290.9 | D86: 101092.62 | E86: 8901 | F86: 0.0302 | G86: 191.47 | H86: 18620 | I86: 3.9
A87: vgate | B87: 39 | C87: 364403.93 | D87: 79697.538 | E87: 8637 | F87: 0.0293 | G87: 42.19 | H87: 21714 | I87: 4.2
A88: xtool | B88: 71 | C88: 1688939.4 | D88: 72470.769 | E88: 7046 | F88: 0.0239 | G88: 239.7 | H88: 12839 | I88: 4.2
A89: vdiagtool | B89: 11 | C89: 167749.77 | D89: 67373.538 | E89: 6154 | F89: 0.0209 | G89: 27.26 | H89: 4889 | I89: 4.5
... A102: amhtdol | B102: 52 | C102: 36444.38 | D102: 18497.538 | E102: 2066 | F102: 0.007 | G102: 17.64 | H102: 1337 | I102: 4
A104: Total | B104: =SUM(B78:B102) -> 1816 | C104: =SUM(C78:C102) -> 26368641 | D104: =SUM(D78:D102) -> 2529033.2 | E104: =SUM(E78:E102) -> 211527 | F104: =SUM(F78:F102) -> 0.7187 | G104: =AVERAGE(G78:G102) -> 134.5036 | H104: =SUM(H78:H102) -> 919555 | I104: =AVERAGE(I78:I102) -> 4.012

Sheet Top 50
A1: Top 50 Products - July '26 ONLY
B3: Avg Price | C3: Avg Price MoM | D3: Avg Price YoY | E3: Quantity/Mo | F3: Qty by % | G3: Qty MoM | H3: Qty YoY | I3: Revenue/Mo | J3: Revenue by % | L3: Revenue MoM | M3: Revenue YoY
A4: Total Tablet | B4: 404.67979 | C4: -0.15055658 | D4: -0.030231171 | E4: 15463 | F4: 0.13399248 | G4: 0.06296831 | H4: 0.08733563 | I4: 6257563.6 | J4: 0.44341701 | L4: -0.09706856 | M4: 0.054464201
A5: Total Handheld | B5: 52.857726 | C5: -0.10467711 | D5: -0.029039156 | E5: 58474 | F5: 0.50669832 | G5: 0.34163913 | H5: 0.10338711 | I5: 3090802.7 | J5: 0.21901727 | L5: 0.20120022 | M5: 0.071345682
A6: Total Dongle | B6: 98.066479 | C6: -0.14106376 | D6: 0.14905742 | E6: 32467 | F6: 0.28133828 | G6: -0.014239738 | H6: -0.20637986 | I6: 3183924.4 | J6: 0.22561596 | L6: -0.15329479 | M6: -0.088084889
A7: Total Other Tools | B7: 175.578 | C7: -0.23709824 | D7: -0.042269602 | E7: 8998 | F7: 0.077970919 | G7: 0.036635945 | H7: 0.35818868 | I7: 1579850.9 | J7: 0.11194976 | L7: -0.20914861 | M7: 0.30077858
A8: Total | B8: 122.2868 | C8: -0.20074549 | D8: 0.037499546 | E8: 115402 | F8: 1 | G8: 0.15694708 | H8: 0.0056731532 | I8: 14112142 | J8: 1 | L8: -0.075304829 | M8: 0.04338544
A40: Rank By Monthly Revenue - Jul '26 ONLY
A41: Ranking | B41: ASIN | C41: Product Name | D41: Brand | E41: Type | F41: Price | G41: Est. Monthly Retail Rev | H41: Est. Monthly Units Sold | I41: # of Reviews | J41: Avg. Rating | K41: Column2 | L41: Link
A42: 1 | B42: B07Z481NJM | C42: Innova 5610 OBD2 Bidirectional Scan Tool - Understand Your Vehicle, Pinpoint What's Wrong, and Complete Your Repairs with Less Headache, Updates Included, US-Based Technical Support | D42: innova | E42: Handheld | F42: 304.05607 | G42: 1174264.6 | H42: 3862 | I42: 3791 | J42: 4.4 | K42: https://amazon.com/dp/B07Z481NJM | L42: =IF(K42="","",HYPERLINK(K42,K42)) -> https://amazon.com/dp/B07Z481NJM
A43: 2 | B43: B0GL9RL3XS | C43: BlueDriver OBD2 Scanner Bluetooth, No Subscription, ABS SRS TPMS | D43: bluedriver | E43: Dongle | F43: 95.184528 | G43: 926145.46 | H43: 9730 | I43: 63029 | J43: 4.5 | K43: https://amazon.com/dp/B0GL9RL3XS | L43: =IF(K43="","",HYPERLINK(K43,K43)) -> https://amazon.com/dp/B0GL9RL3XS
A44: 3 | B44: B01G5EA74I | C44: ANCEL AD310 Classic Enhanced Universal OBD II Scanner Car Engine Fault Code Reader CAN Diagnostic Scan Tool, Read and Clear Error Codes for 1996 or Newer OBD2 Protocol Vehicle (Black) | D44: ancel | E44: Handheld | F44: 27.817391 | G44: 815550.26 | H44: 29318 | I44: 65760 | J44: 4.6 | K44: https://amazon.com/dp/B01G5EA74I | L44: =IF(K44="","",HYPERLINK(K44,K44)) -> https://amazon.com/dp/B01G5EA74I
A45: 4 | B45: B081VQVD3F | C45: OBDLink EX FORScan OBD Adapter | D45: obdlink | E45: Cable/Adapter | F45: 69.947921 | G45: 494182.06 | H45: 7065 | I45: 10265 | J45: 4.8 | K45: https://amazon.com/dp/B081VQVD3F | L45: =IF(K45="","",HYPERLINK(K45,K45)) -> https://amazon.com/dp/B081VQVD3F
A46: 5 | B46: B0BPYPNDVP | C46: Diesel Laptops Nexiq USB Link 3 Wired Edition with Repair Information & Diagnostic Software | D46: diesel laptops | E46: VCI | F46: 759.48003 | G46: 463282.82 | H46: 610 | I46: 290 | J46: 4.5 | K46: https://amazon.com/dp/B0BPYPNDVP | L46: =IF(K46="","",HYPERLINK(K46,K46)) -> https://amazon.com/dp/B0BPYPNDVP
A47: 6 | B47: B098PYB8XG | C47: Autel Scanner MaxiCOM MK900BT Bidirectional Tool, 40+ Service, CAN-FD& DOIP | D47: autel | E47: Tablet | F47: 658.71861 | G47: 425532.22 | H47: 646 | I47: 778 | J47: 4.6 | K47: https://amazon.com/dp/B098PYB8XG | L47: =IF(K47="","",HYPERLINK(K47,K47)) -> https://amazon.com/dp/B098PYB8XG
A48: 7 | B48: B07JFRFJG6 | C48: OBDLink MX+ OBD2 Bluetooth Scanner for iPhone, Android, and Windows | D48: obdlink | E48: Dongle | F48: 139.92839 | G48: 419085.53 | H48: 2995 | I48: 15453 | J48: 4.6 | K48: https://amazon.com/dp/B07JFRFJG6 | L48: =IF(K48="","",HYPERLINK(K48,K48)) -> https://amazon.com/dp/B07JFRFJG6
A49: 8 | B49: B0GK9G6YDL | C49: TOPDON ONE Bidirectional Scan Tool, 10.1" Professional Diagnostic Tool | D49: topdon | E49: Tablet | F49: 734.64028 | G49: 418010.32 | H49: 569 | I49: 206 | J49: 4.5 | K49: https://amazon.com/dp/B0GK9G6YDL | L49: =IF(K49="","",HYPERLINK(K49,K49)) -> https://amazon.com/dp/B0GK9G6YDL
A50: 9 | B50: B00UJV3E12 | C50: FOXWELL NT301 OBD2 Scanner Live Data Professional Mechanic OBDII Diagnostic Code Reader Tool for Check Engine Light | D50: foxwell | E50: Handheld | F50: 64.043987 | G50: 358198.02 | H50: 5593 | I50: 30049 | J50: 4.5 | K50: https://amazon.com/dp/B00UJV3E12 | L50: =IF(K50="","",HYPERLINK(K50,K50)) -> https://amazon.com/dp/B00UJV3E12
A51: 10 | B51: B0DV2N2FND | C51: BLCKTEC 460T OBD2 Scanner Car Code Reader Engine ABS SRS Transmission Diagnostic Tool, 12 Reset Services, Oil/TPMS/EPB/BMS/SAS/DPF/Throttle Reset, ABS Bleeding, Battery Test, Auto VIN, Free Update | D51: blcktec | E51: Tablet | F51: 189.09779 | G51: 347561.74 | H51: 1838 | I51: 773 | J51: 4.4 | K51: https://amazon.com/dp/B0DV2N2FND | L51: =IF(K51="","",HYPERLINK(K51,K51)) -> https://amazon.com/dp/B0DV2N2FND
A52: 11 | B52: B0DTK24XKB | C52: MUCAR 892BT AI-Assisted Bidirectional Scan Tool, Full System OBD2 Scanner, Bi-Directional OBD2 Scanner Diagnostic Tool,ECU Coding, 35 Services, FCA Autoauth, CANFD and DOIP, Free Lifetime Updates | D52: mucar | E52: Tablet | F52: 586.13082 | G52: 341128.14 | H52: 582 | I52: 477 | J52: 4.2 | K52: https://amazon.com/dp/B0DTK24XKB | L52: =IF(K52="","",HYPERLINK(K52,K52)) -> https://amazon.com/dp/B0DTK24XKB
A53: 12 | B53: B0C33Y285Y | C53: TOPDON AD900 Lite OBD2 Scanner, Bidirectional Scan Tool, 8" Large Screen | D53: topdon | E53: Tablet | F53: 313.50156 | G53: 323847.11 | H53: 1033 | I53: 3990 | J53: 4.3 | K53: https://amazon.com/dp/B0C33Y285Y | L53: =IF(K53="","",HYPERLINK(K53,K53)) -> https://amazon.com/dp/B0C33Y285Y
... A91: 50 | B91: B08XK3DJ42 | C91: TOPDON AD500 OBD2 Scanner Car Diagnostic Tool, Engine ABS SRS Transmission | D91: topdon | E91: Tablet | F91: 155.79363 | G91: 131801.41 | H91: 846 | I91: 1841 | J91: 4.4 | K91: https://amazon.com/dp/B08XK3DJ42 | L91: =IF(K91="","",HYPERLINK(K91,K91)) -> https://amazon.com/dp/B08XK3DJ42
A94: Rank By Monthly Units - Jul '26 ONLY
A95: Ranking | B95: ASIN | C95: Product Name | D95: Brand | E95: Type | F95: Price | G95: Est. Monthly Retail Rev | H95: Est. Monthly Units Sold | I95: # of Reviews | J95: Avg. Rating | K95: Column2 | L95: Link
A96: 1 | B96: B01G5EA74I | C96: ANCEL AD310 Classic Enhanced Universal OBD II Scanner Car Engine Fault Code Reader CAN Diagnostic Scan Tool, Read and Clear Error Codes for 1996 or Newer OBD2 Protocol Vehicle (Black) | D96: ancel | E96: Handheld | F96: 27.817391 | G96: 815550.26 | H96: 29318 | I96: 65760 | J96: 4.6 | K96: https://amazon.com/dp/B01G5EA74I | L96: =IF(K96="","",HYPERLINK(K96,K96)) -> https://amazon.com/dp/B01G5EA74I
A97: 2 | B97: B07Z3HB7DR | C97: MOTOPOWER MP69033 Car OBD2 Scanner Code Reader Engine Fault Scanner CAN Diagnostic Scan Tool for All OBD II Protocol Cars Since 1996, Yellow | D97: motopower | E97: Handheld | F97: 23.211108 | G97: 259500.19 | H97: 11180 | I97: 51762 | J97: 4.6 | K97: https://amazon.com/dp/B07Z3HB7DR | L97: =IF(K97="","",HYPERLINK(K97,K97)) -> https://amazon.com/dp/B07Z3HB7DR
A98: 3 | B98: B0GL9RL3XS | C98: BlueDriver OBD2 Scanner Bluetooth, No Subscription, ABS SRS TPMS | D98: bluedriver | E98: Dongle | F98: 95.184528 | G98: 926145.46 | H98: 9730 | I98: 63029 | J98: 4.5 | K98: https://amazon.com/dp/B0GL9RL3XS | L98: =IF(K98="","",HYPERLINK(K98,K98)) -> https://amazon.com/dp/B0GL9RL3XS
A99: 4 | B99: B081VQVD3F | C99: OBDLink EX FORScan OBD Adapter | D99: obdlink | E99: Cable/Adapter | F99: 69.947921 | G99: 494182.06 | H99: 7065 | I99: 10265 | J99: 4.8 | K99: https://amazon.com/dp/B081VQVD3F | L99: =IF(K99="","",HYPERLINK(K99,K99)) -> https://amazon.com/dp/B081VQVD3F
A100: 5 | B100: B073XKQQQW | C100: Veepeak OBDCheck BLE Bluetooth OBD II Scanner for iOS & Android, Car Wireless Check Engine Light Code Reader Diagnostic Tool | D100: veepeak | E100: Dongle | F100: 31.98093 | G100: 205317.57 | H100: 6420 | I100: 23908 | J100: 4.5 | K100: https://amazon.com/dp/B073XKQQQW | L100: =IF(K100="","",HYPERLINK(K100,K100)) -> https://amazon.com/dp/B073XKQQQW
A101: 6 | B101: B071FSNL73 | C101: ANCEL AD410 Enhanced OBD2 Scanner, Vehicle Code Reader for Check Engine Light, Automotive OBD II Scanner Fault Diagnosis, OBDII Scan Tool for All OBDII Cars 1996+, Black/Yellow | D101: ancel | E101: Handheld | F101: 41.468081 | G101: 234211.72 | H101: 5648 | I101: 15482 | J101: 4.5 | K101: https://amazon.com/dp/B071FSNL73 | L101: =IF(K101="","",HYPERLINK(K101,K101)) -> https://amazon.com/dp/B071FSNL73
A102: 7 | B102: B00UJV3E12 | C102: FOXWELL NT301 OBD2 Scanner Live Data Professional Mechanic OBDII Diagnostic Code Reader Tool for Check Engine Light | D102: foxwell | E102: Handheld | F102: 64.043987 | G102: 358198.02 | H102: 5593 | I102: 30049 | J102: 4.5 | K102: https://amazon.com/dp/B00UJV3E12 | L102: =IF(K102="","",HYPERLINK(K102,K102)) -> https://amazon.com/dp/B00UJV3E12
A103: 8 | B103: B0BY1TS725 | C103: VDIAGTOOL VD10 OBD2 Scanner Code Reader Car Diagnostic Tool Engine Fault Code Reader for Turn Off CEL with Freeze Frame/I/M Readiness for All OBDII Protocol Cars, OBD2 Scanner Diagnostic Tool | D103: vdiagtool | E103: Handheld | F103: 18.105488 | G103: 98186.06 | H103: 5423 | I103: 3034 | J103: 4.6 | K103: https://amazon.com/dp/B0BY1TS725 | L103: =IF(K103="","",HYPERLINK(K103,K103)) -> https://amazon.com/dp/B0BY1TS725
A104: 9 | B104: B013RIQMEO | C104: FIXD Bluetooth OBD2 Scanner - Car Diagnostic Check Engine Code Reader | D104: fixd | E104: Dongle | F104: 39.987912 | G104: 192821.71 | H104: 4822 | I104: 35597 | J104: 4.2 | K104: https://amazon.com/dp/B013RIQMEO | L104: =IF(K104="","",HYPERLINK(K104,K104)) -> https://amazon.com/dp/B013RIQMEO
A105: 10 | B105: B07Z481NJM | C105: Innova 5610 OBD2 Bidirectional Scan Tool - Understand Your Vehicle, Pinpoint What's Wrong, and Complete Your Repairs with Less Headache, Updates Included, US-Based Technical Support | D105: innova | E105: Handheld | F105: 304.05607 | G105: 1174264.6 | H105: 3862 | I105: 3791 | J105: 4.4 | K105: https://amazon.com/dp/B07Z481NJM | L105: =IF(K105="","",HYPERLINK(K105,K105)) -> https://amazon.com/dp/B07Z481NJM
A106: 11 | B106: B08NFLL3NT | C106: OBDLink CX Bimmercode Bluetooth 5.1 OBD2 Adapter for BMW/Mini, Works with iPhone/iOS & Android, Car Coding, OBD II Diagnostic Scanner | D106: obdlink | E106: Dongle | F106: 79.945739 | G106: 274133.94 | H106: 3429 | I106: 4614 | J106: 4.6 | K106: https://amazon.com/dp/B08NFLL3NT | L106: =IF(K106="","",HYPERLINK(K106,K106)) -> https://amazon.com/dp/B08NFLL3NT
A107: 12 | B107: B07JFRFJG6 | C107: OBDLink MX+ OBD2 Bluetooth Scanner for iPhone, Android, and Windows | D107: obdlink | E107: Dongle | F107: 139.92839 | G107: 419085.53 | H107: 2995 | I107: 15453 | J107: 4.6 | K107: https://amazon.com/dp/B07JFRFJG6 | L107: =IF(K107="","",HYPERLINK(K107,K107)) -> https://amazon.com/dp/B07JFRFJG6
... A145: 50 | B145: B019QCG5RE | C145: FOXWELL NT510 Elite Scan Tool fit for BMW Scanner Full Diagnostic Tool OBD2 Scanner, All System Bi-Directional Control Code Reader with All Reset Services, Battery Registration Tool fit for BMW Mini | D145: foxwell | E145: Handheld | F145: 177.72473 | G145: 125118.21 | H145: 704 | I145: 3174 | J145: 4.3 | K145: https://amazon.com/dp/B019QCG5RE | L145: =IF(K145="","",HYPERLINK(K145,K145)) -> https://amazon.com/dp/B019QCG5RE

Sheet Tablet Total
A1: Tablet Monthly Summary
A3: Tablet Overall
B4: Avg Price | C4: Avg Price MoM | D4: Avg Price YoY | E4: Quantity/Mo | F4: Qty by % | G4: Qty MoM | H4: Qty YoY | I4: Revenue/Mo | J4: Revenue by % | L4: Revenue MoM | M4: Revenue YoY
A5: autel | B5: 714.95074 | C5: -0.044762822 | D5: -0.10853758 | E5: 6439 | F5: 0.16260101 | G5: -0.064778504 | H5: 0.15997118 | I5: 4603567.8 | J5: 0.29328855 | L5: -0.10664166 | M5: 0.034070713
A6: topdon | B6: 348.71624 | C6: -0.087407675 | D6: -0.0017426969 | E6: 6338 | F6: 0.16005051 | G6: -0.11947763 | H6: -0.011540861 | I6: 2210163.5 | J6: 0.14080724 | L6: -0.19644205 | M6: -0.013263446
A7: launch | B7: 478.3969 | C7: -0.092444713 | D7: 0.1934296 | E7: 4300 | F7: 0.10858586 | G7: -0.21974233 | H7: -0.36334024 | I7: 2057106.7 | J7: 0.13105614 | L7: -0.29187303 | M7: -0.2401914
A8: xtool | B8: 317.4671 | C8: -0.078522711 | D8: -0.26726577 | E8: 4369 | F8: 0.11032828 | G8: -0.0079473206 | H8: 0.40844616 | I8: 1387013.8 | J8: 0.088365216 | L8: -0.085845986 | M8: 0.032016709
A9: ancel | B9: 496.93086 | C9: 0.045223408 | D9: 0.55125435 | E9: 2541 | F9: 0.064166667 | G9: -0.27791986 | H9: 0.091026191 | I9: 1262701.3 | J9: 0.080445398 | L9: -0.24526494 | M9: 0.69245912
A10: blcktec | B10: 189.09779 | C10: -0.054412014 | D10: -0.054359836 | E10: 1838 | F10: 0.046414141 | G10: 0.047293447 | H10: 1.2889166 | I10: 347561.74 | J10: 0.0221428 | L10: -0.0096918982 | M10: 1.1644914
A11: innova | B11: 141.40307 | C11: -0.098281875 | D11: -0.24429351 | E11: 672 | F11: 0.016969697 | G11: -0.14503817 | H11: 2.5368421 | I11: 95022.86 | J11: 0.0060538083 | L11: -0.22906542 | M11: 1.6728145
A12: Other | B12: 284.91488 | C12: -0.0098235417 | D12: -0.069624852 | E12: 13103 | F12: 0.33088384 | G12: -0.18947173 | H12: 0.45491894 | I12: 3733239.7 | J12: 0.23784085 | L12: -0.19743399 | M12: 0.35362043
A13: Total Tablet | B13: 396.37317 | C13: -0.041975622 | D13: -0.062891283 | E13: 39600 | F13: 1 | G13: -0.14330218 | H13: 0.15969192 | I13: 15696377 | J13: 1 | L13: -0.1792626 | M13: 0.086757408
A45: Rank By Monthly Revenue - Jul '26 ONLY
A46: Ranking | B46: ASIN | C46: Product Name | D46: Brand | E46: Type | F46: Price | G46: Est. Monthly Retail Rev | H46: Est. Monthly Units Sold | I46: # of Reviews | J46: Avg. Rating | K46: Column2 | L46: Link
A47: 1 | B47: B098PYB8XG | C47: Autel Scanner MaxiCOM MK900BT Bidirectional Tool, 40+ Service, CAN-FD& DOIP | D47: autel | E47: Tablet | F47: 658.71861 | G47: 425532.22 | H47: 646 | I47: 778 | J47: 4.6 | K47: https://amazon.com/dp/B098PYB8XG | L47: =IF(K47="","",HYPERLINK(K47,K47)) -> https://amazon.com/dp/B098PYB8XG
A48: 2 | B48: B0GK9G6YDL | C48: TOPDON ONE Bidirectional Scan Tool, 10.1" Professional Diagnostic Tool | D48: topdon | E48: Tablet | F48: 734.64028 | G48: 418010.32 | H48: 569 | I48: 206 | J48: 4.5 | K48: https://amazon.com/dp/B0GK9G6YDL | L48: =IF(K48="","",HYPERLINK(K48,K48)) -> https://amazon.com/dp/B0GK9G6YDL
A49: 3 | B49: B0DV2N2FND | C49: BLCKTEC 460T OBD2 Scanner Car Code Reader Engine ABS SRS Transmission Diagnostic Tool, 12 Reset Services, Oil/TPMS/EPB/BMS/SAS/DPF/Throttle Reset, ABS Bleeding, Battery Test, Auto VIN, Free Update | D49: blcktec | E49: Tablet | F49: 189.09779 | G49: 347561.74 | H49: 1838 | I49: 773 | J49: 4.4 | K49: https://amazon.com/dp/B0DV2N2FND | L49: =IF(K49="","",HYPERLINK(K49,K49)) -> https://amazon.com/dp/B0DV2N2FND
A50: 4 | B50: B0DTK24XKB | C50: MUCAR 892BT AI-Assisted Bidirectional Scan Tool, Full System OBD2 Scanner, Bi-Directional OBD2 Scanner Diagnostic Tool,ECU Coding, 35 Services, FCA Autoauth, CANFD and DOIP, Free Lifetime Updates | D50: mucar | E50: Tablet | F50: 586.13082 | G50: 341128.14 | H50: 582 | I50: 477 | J50: 4.2 | K50: https://amazon.com/dp/B0DTK24XKB | L50: =IF(K50="","",HYPERLINK(K50,K50)) -> https://amazon.com/dp/B0DTK24XKB
A51: 5 | B51: B0C33Y285Y | C51: TOPDON AD900 Lite OBD2 Scanner, Bidirectional Scan Tool, 8" Large Screen | D51: topdon | E51: Tablet | F51: 313.50156 | G51: 323847.11 | H51: 1033 | I51: 3990 | J51: 4.3 | K51: https://amazon.com/dp/B0C33Y285Y | L51: =IF(K51="","",HYPERLINK(K51,K51)) -> https://amazon.com/dp/B0C33Y285Y
A52: 6 | B52: B0BMZW65LJ | C52: ANCEL MT700 Motorcycle OBD2 Scanner Full Systems, ABS Engine Meter TPMS Diagnostic Tool with 35+ Reset Functions for Harley Indian Yamaha Polaris Piaggio Ducati Honda BMW, AutoVIN, 7”Touch Screen,16G | D52: ancel | E52: Tablet | F52: 954.64527 | G52: 322670.1 | H52: 338 | I52: 914 | J52: 4.5 | K52: https://amazon.com/dp/B0BMZW65LJ | L52: =IF(K52="","",HYPERLINK(K52,K52)) -> https://amazon.com/dp/B0BMZW65LJ
A53: 7 | B53: B08PFJMTY3 | C53: FOXWELL Car Scanner NT604 Elite OBD2 Scanner ABS SRS Transmission | D53: foxwell | E53: Tablet | F53: 149.44571 | G53: 290373.01 | H53: 1943 | I53: 5051 | J53: 4.4 | K53: https://amazon.com/dp/B08PFJMTY3 | L53: =IF(K53="","",HYPERLINK(K53,K53)) -> https://amazon.com/dp/B08PFJMTY3
A54: 8 | B54: B0GX1WPD31 | C54: Autel Scanner MaxiCOM MK808S: 3000+ Active Tests 28+ Service as MK900-BT | D54: autel | E54: Tablet | F54: 468.70797 | G54: 284505.74 | H54: 607 | I54: 381 | J54: 4.4 | K54: https://amazon.com/dp/B0GX1WPD31 | L54: =IF(K54="","",HYPERLINK(K54,K54)) -> https://amazon.com/dp/B0GX1WPD31
A55: 9 | B55: B0744B55QV | C55: Autel Scanner MaxiCOM MK808S Bidirectional Tool, 28+ Hot Service All System | D55: autel | E55: Tablet | F55: 457.87741 | G55: 263737.39 | H55: 576 | I55: 3903 | J55: 4.4 | K55: https://amazon.com/dp/B0744B55QV | L55: =IF(K55="","",HYPERLINK(K55,K55)) -> https://amazon.com/dp/B0744B55QV
A56: 10 | B56: B08ML7T7KZ | C56: Autel Scanner MaxiCheck MX808S, Bidirectional OBD2 Scan Tool 28+ Service | D56: autel | E56: Tablet | F56: 430.55856 | G56: 248432.29 | H56: 577 | I56: 756 | J56: 4.6 | K56: https://amazon.com/dp/B08ML7T7KZ | L56: =IF(K56="","",HYPERLINK(K56,K56)) -> https://amazon.com/dp/B08ML7T7KZ
A58: Rank By Monthly Units - Jul '26 ONLY
A59: Ranking | B59: ASIN | C59: Product Name | D59: Brand | E59: Type | F59: Price | G59: Est. Monthly Retail Rev | H59: Est. Monthly Units Sold | I59: # of Reviews | J59: Avg. Rating | K59: Column2 | L59: Link
A60: 1 | B60: B08PFJMTY3 | C60: FOXWELL Car Scanner NT604 Elite OBD2 Scanner ABS SRS Transmission | D60: foxwell | E60: Tablet | F60: 149.44571 | G60: 290373.01 | H60: 1943 | I60: 5051 | J60: 4.4 | K60: https://amazon.com/dp/B08PFJMTY3 | L60: =IF(K60="","",HYPERLINK(K60,K60)) -> https://amazon.com/dp/B08PFJMTY3
A61: 2 | B61: B0DV2N2FND | C61: BLCKTEC 460T OBD2 Scanner Car Code Reader Engine ABS SRS Transmission Diagnostic Tool, 12 Reset Services, Oil/TPMS/EPB/BMS/SAS/DPF/Throttle Reset, ABS Bleeding, Battery Test, Auto VIN, Free Update | D61: blcktec | E61: Tablet | F61: 189.09779 | G61: 347561.74 | H61: 1838 | I61: 773 | J61: 4.4 | K61: https://amazon.com/dp/B0DV2N2FND | L61: =IF(K61="","",HYPERLINK(K61,K61)) -> https://amazon.com/dp/B0DV2N2FND
A62: 3 | B62: B0C33Y285Y | C62: TOPDON AD900 Lite OBD2 Scanner, Bidirectional Scan Tool, 8" Large Screen | D62: topdon | E62: Tablet | F62: 313.50156 | G62: 323847.11 | H62: 1033 | I62: 3990 | J62: 4.3 | K62: https://amazon.com/dp/B0C33Y285Y | L62: =IF(K62="","",HYPERLINK(K62,K62)) -> https://amazon.com/dp/B0C33Y285Y
A63: 4 | B63: B09KZTYD18 | C63: TOPDON AD600S OBD2 Scanner, Engine ABS SRS Transmission Diagnostic Tool | D63: topdon | E63: Tablet | F63: 191.15372 | G63: 187139.49 | H63: 979 | I63: 1944 | J63: 4.4 | K63: https://amazon.com/dp/B09KZTYD18 | L63: =IF(K63="","",HYPERLINK(K63,K63)) -> https://amazon.com/dp/B09KZTYD18
A64: 5 | B64: B08XK3DJ42 | C64: TOPDON AD500 OBD2 Scanner Car Diagnostic Tool, Engine ABS SRS Transmission | D64: topdon | E64: Tablet | F64: 155.79363 | G64: 131801.41 | H64: 846 | I64: 1841 | J64: 4.4 | K64: https://amazon.com/dp/B08XK3DJ42 | L64: =IF(K64="","",HYPERLINK(K64,K64)) -> https://amazon.com/dp/B08XK3DJ42
A65: 6 | B65: B08DCNDFVK | C65: 2026 FOXWELL NT614 Elite OBD2 Scanner, 4 Systems, 5 Resets Code Reader | D65: foxwell | E65: Tablet | F65: 168.11133 | G65: 125074.83 | H65: 744 | I65: 796 | J65: 4.3 | K65: https://amazon.com/dp/B08DCNDFVK | L65: =IF(K65="","",HYPERLINK(K65,K65)) -> https://amazon.com/dp/B08DCNDFVK
A66: 7 | B66: B098PYB8XG | C66: Autel Scanner MaxiCOM MK900BT Bidirectional Tool, 40+ Service, CAN-FD& DOIP | D66: autel | E66: Tablet | F66: 658.71861 | G66: 425532.22 | H66: 646 | I66: 778 | J66: 4.6 | K66: https://amazon.com/dp/B098PYB8XG | L66: =IF(K66="","",HYPERLINK(K66,K66)) -> https://amazon.com/dp/B098PYB8XG
A67: 8 | B67: B0F254MVB5 | C67: Innova SD35 OBD2 Scanner – ABS, SRS, TPMS & Check Engine Code Reader, Live Data, All System Diagnostics, Compatible with Most Vehicles | D67: innova | E67: Tablet | F67: 131.7605 | G67: 84063.2 | H67: 638 | I67: 430 | J67: 4.4 | K67: https://amazon.com/dp/B0F254MVB5 | L67: =IF(K67="","",HYPERLINK(K67,K67)) -> https://amazon.com/dp/B0F254MVB5
A68: 9 | B68: B0GX1WPD31 | C68: Autel Scanner MaxiCOM MK808S: 3000+ Active Tests 28+ Service as MK900-BT | D68: autel | E68: Tablet | F68: 468.70797 | G68: 284505.74 | H68: 607 | I68: 381 | J68: 4.4 | K68: https://amazon.com/dp/B0GX1WPD31 | L68: =IF(K68="","",HYPERLINK(K68,K68)) -> https://amazon.com/dp/B0GX1WPD31
A69: 10 | B69: B0DFCMT416 | C69: XTOOL D5S OBD2 Scanner, 16 Resets, Engine ABS SRS Transmission Scan Tool | D69: xtool | E69: Tablet | F69: 170.41203 | G69: 102417.63 | H69: 601 | I69: 518 | J69: 4.3 | K69: https://amazon.com/dp/B0DFCMT416 | L69: =IF(K69="","",HYPERLINK(K69,K69)) -> https://amazon.com/dp/B0DFCMT416
A71: Tablet $800+
B72: Avg Price | C72: Avg Price MoM | D72: Avg Price YoY | E72: Quantity/Mo | F72: Qty by % | G72: Qty MoM | H72: Qty YoY | I72: Revenue/Mo | J72: Revenue by % | L72: Revenue MoM | M72: Revenue YoY
A73: autel | B73: 2023.8071 | C73: 0.012531454 | D73: 0.037540182 | E73: 810 | F73: 0.29263006 | G73: -0.16062176 | H73: -0.24581006 | I73: 1639283.8 | J73: 0.42095612 | L73: -0.15010313 | M73: -0.21749763
A74: launch | B74: 1289.4599 | C74: 0.033920138 | D74: -0.013875621 | E74: 703 | F74: 0.25397399 | G74: -0.30943026 | H74: -0.14580802 | I74: 906490.33 | J74: 0.2327801 | L74: -0.28600603 | M74: -0.15766046
A75: ancel | B75: 939.33984 | C75: -0.013969347 | D75: 0.082263364 | E75: 551 | F75: 0.19906069 | G75: 0.091089109 | H75: 1.9308511 | I75: 517576.25 | J75: 0.13290981 | L75: 0.075847307 | M75: 2.1719527
A76: topdon | B76: 1200.1367 | C76: -0.033244164 | D76: -0.014638563 | E76: 324 | F76: 0.11705202 | G76: -0.21927711 | H76: -0.3106383 | I76: 388844.3 | J76: 0.09985238 | L76: -0.24523159 | M76: -0.32072956
A77: xtool | B77: 1307.0251 | C77: 0.046914868 | D77: 0.06847153 | E77: 146 | F77: 0.052745665 | G77: -0.039473684 | H77: -0.15116279 | I77: 190825.66 | J77: 0.049002637 | L77: 0.0055892812 | M77: -0.093041608
A78: Other | B78: 1073.3816 | C78: -0.29080559 | D78: 0.011272512 | E78: 234 | F78: 0.084537572 | G78: 0.32954545 | H78: 0.43558282 | I78: 251171.29 | J78: 0.064498955 | L78: -0.057093791 | M78: 0.45176545
A79: =Summary!A4 -> Tablet $800+ | B79: =Summary!B4 -> 1406.8611 | C79: =Summary!C4 -> -0.022631585 | D79: =Summary!D4 -> -0.052279211 | E79: =SUM(E73:E78) -> 2768 | F79: =SUM(F73:F78) -> 1 | G79: =Summary!G4 -> -0.14329929 | H79: =Summary!H4 -> -0.042214533 | I79: =SUM(I73:I78) -> 3894191.6 | J79: =SUM(J73:J78) -> 1 | L79: =Summary!K4 -> -0.16268778 | M79: =Summary!L4 -> -0.092286802
A81: Tablet $400-$800
B82: Avg Price | C82: Avg Price MoM | D82: Avg Price YoY | E82: Quantity/Mo | F82: Qty by % | G82: Qty MoM | H82: Qty YoY | I82: Revenue/Mo | J82: Revenue by % | L82: Revenue MoM | M82: Revenue YoY
A83: autel | B83: 536.14049 | C83: -0.031530742 | D83: 0.018309988 | E83: 5461 | F83: 0.44211464 | G83: -0.052238806 | H83: 0.22006256 | I83: 2927863.2 | J83: 0.43909093 | L83: -0.082122419 | M83: 0.24240189
A84: launch | B84: 554.10393 | C84: -0.038343847 | D84: 0.0027720742 | E84: 1307 | F84: 0.10581282 | G84: -0.34747878 | H84: -0.16164208 | I84: 724213.84 | J84: 0.10861017 | L84: -0.37249896 | M84: -0.15931809
A85: topdon | B85: 615.18187 | C85: -0.020308442 | D85: 0.29935597 | E85: 1053 | F85: 0.085249352 | G85: -0.28269755 | H85: -0.3965616 | I85: 647786.51 | J85: 0.097148385 | L85: -0.29726484 | M85: -0.21591872
A86: xtool | B86: 496.94875 | C86: -0.016668468 | D86: -0.028920039 | E86: 997 | F86: 0.080715674 | G86: -0.35594315 | H86: -0.4420817 | I86: 495457.9 | J86: 0.0743037 | L86: -0.36667859 | M86: -0.45821672
A87: ancel | B87: 540.73332 | C87: -0.023584292 | D87: 0.11696695 | E87: 906 | F87: 0.073348446 | G87: -0.36995828 | H87: 1.0590909 | I87: 489904.39 | J87: 0.073470842 | L87: -0.38481736 | M87: 1.2999365
A88: innova | B88: 514.99 | E88: 4 | F88: 0.0003238342 | I88: 2059.96 | J88: 0.0003089317
A89: Other | B89: 526.19106 | C89: -0.065148451 | D89: -0.034188075 | E89: 2624 | F89: 0.21243523 | G89: -0.13141344 | H89: 0.31991952 | I89: 1380725.3 | J89: 0.20706704 | L89: -0.18800051 | M89: 0.27479401
A90: =Summary!A5 -> Tablet $400-$800 | B90: =Summary!B5 -> 539.83251 | C90: =Summary!C5 -> -0.037189415 | D90: =Summary!D5 -> 0.035243678 | E90: =SUM(E83:E89) -> 12352 | F90: =SUM(F83:F89) -> 1 | G90: =Summary!G5 -> -0.18950131 | H90: =Summary!H5 -> 0.029762401 | I90: =SUM(I83:I89) -> 6668011.1 | J90: =SUM(J83:J89) -> 1 | L90: =Summary!K5 -> -0.21964328 | M90: =Summary!L5 -> 0.066055015
A92: Tablet $400-
B93: Avg Price | C93: Avg Price MoM | D93: Avg Price YoY | E93: Quantity/Mo | F93: Qty by % | G93: Qty MoM | H93: Qty YoY | I93: Revenue/Mo | J93: Revenue by % | L93: Revenue MoM | M93: Revenue YoY
A94: topdon | B94: 236.55165 | C94: -0.04279377 | D94: 0.18014981 | E94: 4961 | F94: 0.20265523 | G94: -0.066603951 | H94: 0.18203479 | I94: 1173532.7 | J94: 0.22857281 | L94: -0.10654749 | M94: 0.39497812
A95: foxwell | B95: 197.28926 | C95: -0.026523972 | D95: 0.017417114 | E95: 4481 | F95: 0.18304739 | G95: -0.13959293 | H95: 0.38046827 | I95: 884053.18 | J95: 0.17218993 | L95: -0.16241435 | M95: 0.40451204
A96: xtool | B96: 217.21334 | C96: 0.077334866 | D96: 0.13322267 | E96: 3226 | F96: 0.13178105 | G96: 0.19304734 | H96: 1.8223972 | I96: 700730.22 | J96: 0.13648352 | L96: 0.28531149 | M96: 2.1984045
A97: launch | B97: 186.20196 | C97: -0.036622572 | D97: 0.057537918 | E97: 2290 | F97: 0.093545752 | G97: -0.080321285 | H97: -0.47621226 | I97: 426402.49 | J97: 0.083051809 | L97: -0.11400229 | M97: -0.4460746
A98: icarsoft | B98: 204.08907 | C98: 0.006354074 | D98: 0.0044221043 | E98: 1882 | F98: 0.076879085 | G98: -0.16578014 | H98: 0.093550261 | I98: 384095.63 | J98: 0.074811564 | L98: -0.16047945 | M98: 0.098386055
A99: blcktec | B99: 189.09779 | C99: -0.054412014 | D99: -0.054359836 | E99: 1838 | F99: 0.075081699 | G99: 0.047293447 | H99: 1.2889166 | I99: 347561.74 | J99: 0.067695738 | L99: -0.0096918982 | M99: 1.1644914
A100: innova | B100: 139.16602 | C100: -0.11254738 | D100: -0.25624906 | E100: 668 | F100: 0.027287582 | G100: -0.15012723 | H100: 2.5157895 | I100: 92962.9 | J100: 0.018106688 | L100: -0.24577818 | M100: 1.6148717
A101: Other | B101: 219.09539 | C101: -0.0099241479 | D101: -0.11917528 | E101: 5134 | F101: 0.20972222 | G101: -0.29078602 | H101: 0.43008357 | I101: 1124835.7 | J101: 0.21908793 | L101: -0.29782436 | M101: 0.25965295
A102: =Summary!A6 -> Tablet $400- | B102: =Summary!B6 -> 209.72935 | C102: =Summary!C6 -> -0.018292626 | D102: =Summary!D6 -> 0.036285409 | E102: =SUM(E94:E101) -> 24480 | F102: =SUM(F94:F101) -> 1 | G102: =Summary!G6 -> -0.1179332 | H102: =Summary!H6 -> 0.27089606 | I102: =SUM(I94:I101) -> 5134174.6 | J102: =SUM(J94:J101) -> 1 | L102: =Summary!K6 -> -0.13406851 | M102: =Summary!L6 -> 0.31701105

Sheet Tablet $800+
A1: Tablet $800+ Monthly Summary
A3: ='Tablet Total'!A71 -> Tablet $800+
B4: Avg Price | C4: Avg Price MoM | D4: Avg Price YoY | E4: Quantity/Mo | F4: Qty by % | G4: Qty MoM | H4: Qty YoY | I4: Revenue/Mo | J4: Revenue by % | L4: Revenue MoM | M4: Revenue YoY
A5: ='Tablet Total'!A73 -> autel | B5: ='Tablet Total'!B73 -> 2023.8071 | C5: ='Tablet Total'!C73 -> 0.012531454 | D5: ='Tablet Total'!D73 -> 0.037540182 | E5: ='Tablet Total'!E73 -> 810 | F5: ='Tablet Total'!F73 -> 0.29263006 | G5: ='Tablet Total'!G73 -> -0.16062176 | H5: ='Tablet Total'!H73 -> -0.24581006 | ... M5: ='Tablet Total'!M73 -> -0.21749763
A6: ='Tablet Total'!A74 -> launch | B6: ='Tablet Total'!B74 -> 1289.4599 | C6: ='Tablet Total'!C74 -> 0.033920138 | D6: ='Tablet Total'!D74 -> -0.013875621 | E6: ='Tablet Total'!E74 -> 703 | F6: ='Tablet Total'!F74 -> 0.25397399 | G6: ='Tablet Total'!G74 -> -0.30943026 | H6: ='Tablet Total'!H74 -> -0.14580802 | ... M6: ='Tablet Total'!M74 -> -0.15766046
A7: ='Tablet Total'!A75 -> ancel | B7: ='Tablet Total'!B75 -> 939.33984 | C7: ='Tablet Total'!C75 -> -0.013969347 | D7: ='Tablet Total'!D75 -> 0.082263364 | E7: ='Tablet Total'!E75 -> 551 | F7: ='Tablet Total'!F75 -> 0.19906069 | G7: ='Tablet Total'!G75 -> 0.091089109 | H7: ='Tablet Total'!H75 -> 1.9308511 | ... M7: ='Tablet Total'!M75 -> 2.1719527
A8: ='Tablet Total'!A76 -> topdon | B8: ='Tablet Total'!B76 -> 1200.1367 | C8: ='Tablet Total'!C76 -> -0.033244164 | D8: ='Tablet Total'!D76 -> -0.014638563 | E8: ='Tablet Total'!E76 -> 324 | F8: ='Tablet Total'!F76 -> 0.11705202 | G8: ='Tablet Total'!G76 -> -0.21927711 | H8: ='Tablet Total'!H76 -> -0.3106383 | ... M8: ='Tablet Total'!M76 -> -0.32072956
A9: ='Tablet Total'!A77 -> xtool | B9: ='Tablet Total'!B77 -> 1307.0251 | C9: ='Tablet Total'!C77 -> 0.046914868 | D9: ='Tablet Total'!D77 -> 0.06847153 | E9: ='Tablet Total'!E77 -> 146 | F9: ='Tablet Total'!F77 -> 0.052745665 | G9: ='Tablet Total'!G77 -> -0.039473684 | H9: ='Tablet Total'!H77 -> -0.15116279 | ... M9: ='Tablet Total'!M77 -> -0.093041608
A10: ='Tablet Total'!A78 -> Other | B10: ='Tablet Total'!B78 -> 1073.3816 | C10: ='Tablet Total'!C78 -> -0.29080559 | D10: ='Tablet Total'!D78 -> 0.011272512 | E10: ='Tablet Total'!E78 -> 234 | F10: ='Tablet Total'!F78 -> 0.084537572 | G10: ='Tablet Total'!G78 -> 0.32954545 | H10: ='Tablet Total'!H78 -> 0.43558282 | ... M10: ='Tablet Total'!M78 -> 0.45176545
A11: ='Tablet Total'!A79 -> Tablet $800+ | B11: ='Tablet Total'!B79 -> 1406.8611 | C11: ='Tablet Total'!C79 -> -0.022631585 | D11: ='Tablet Total'!D79 -> -0.052279211 | E11: ='Tablet Total'!E79 -> 2768 | F11: ='Tablet Total'!F79 -> 1 | G11: ='Tablet Total'!G79 -> -0.14329929 | H11: ='Tablet Total'!H79 -> -0.042214533 | ... M11: ='Tablet Total'!M79 -> -0.092286802
A43: Rank By Monthly Revenue - Jul '26 ONLY
A44: Ranking | B44: ASIN | C44: Product Name | D44: Brand | E44: Type | F44: Price | G44: Est. Monthly Retail Rev | H44: Est. Monthly Units Sold | I44: # of Reviews | J44: Avg. Rating | K44: Column2 | L44: Link
A45: 1 | B45: B0BMZW65LJ | C45: ANCEL MT700 Motorcycle OBD2 Scanner Full Systems, ABS Engine Meter TPMS Diagnostic Tool with 35+ Reset Functions for Harley Indian Yamaha Polaris Piaggio Ducati Honda BMW, AutoVIN, 7”Touch Screen,16G | D45: ancel | E45: Tablet | F45: 954.64527 | G45: 322670.1 | H45: 338 | I45: 914 | J45: 4.5 | K45: https://amazon.com/dp/B0BMZW65LJ | L45: =IF(K45="","",HYPERLINK(K45,K45)) -> https://amazon.com/dp/B0BMZW65LJ
A46: 2 | B46: B0DTTTJWYH | C46: Launch X431 PRO3 V+ Elite SmartlinkC Bidirectional Scan Tool J2534 Protocol | D46: launch | E46: Tablet | F46: 1327.7482 | G46: 217750.71 | H46: 164 | I46: 113 | J46: 4.4 | K46: https://amazon.com/dp/B0DTTTJWYH | L46: =IF(K46="","",HYPERLINK(K46,K46)) -> https://amazon.com/dp/B0DTTTJWYH
A47: 3 | B47: B091BQNR3S | C47: TOPDON Phoenix Plus 2 Scanner with ECU Coding & Configuration, FCA SGW | D47: topdon | E47: Tablet | F47: 1004.0686 | G47: 211858.47 | H47: 211 | I47: 526 | J47: 4.5 | K47: https://amazon.com/dp/B091BQNR3S | L47: =IF(K47="","",HYPERLINK(K47,K47)) -> https://amazon.com/dp/B091BQNR3S
A48: 4 | B48: B0GLFSPMZ4 | C48: ANCEL X7HD PRO 10.1'' Heavy Duty Truck Scanner, Full-System Diesel Diagnostic Tool with DPF Regen, 42+ Reset, Bi-Directional and Active Test, ECU Coding, HDOBD/OBD2 Scanner for Diesel Trucks - Grey | D48: ancel | E48: Tablet | F48: 898.63143 | G48: 157260.5 | H48: 175 | I48: 48 | J48: 4.7 | K48: https://amazon.com/dp/B0GLFSPMZ4 | L48: =IF(K48="","",HYPERLINK(K48,K48)) -> https://amazon.com/dp/B0GLFSPMZ4
A49: 5 | B49: B0DZC1M7MZ | C49: Autel MaxiSys Ultra S2 Scanner, 2026 Top Intelligen Scan Diagnostic with AI, 6-in-1 VCMI2, Up of MSUltra MS919, Topology 3.0, Multi-Point DVI, Motor Truspeed Repair, EV Test, 48+ Service, ECU Program | D49: autel | E49: Tablet | F49: 5726.4109 | G49: 131707.45 | H49: 23 | I49: 24 | J49: 4.9 | K49: https://amazon.com/dp/B0DZC1M7MZ | L49: =IF(K49="","",HYPERLINK(K49,K49)) -> https://amazon.com/dp/B0DZC1M7MZ
A50: 6 | B50: B08V59JNYP | C50: LAUNCH X431 PRO3S+ Smartlink HD Heavy Duty Truck Scanner,J2534 Protocols | D50: launch | E50: Tablet | F50: 1881.0209 | G50: 129790.44 | H50: 69 | I50: 186 | J50: 4.3 | K50: https://amazon.com/dp/B08V59JNYP | L50: =IF(K50="","",HYPERLINK(K50,K50)) -> https://amazon.com/dp/B08V59JNYP
A51: 7 | B51: B0D7VS8SHS | C51: LAUNCH X431 PRO3S+ Elite, 2026 Bidirectional Scan Tool with J2534 Protocols | D51: launch | E51: Tablet | F51: 1218.3985 | G51: 102345.47 | H51: 84 | I51: 172 | J51: 4.2 | K51: https://amazon.com/dp/B0D7VS8SHS | L51: =IF(K51="","",HYPERLINK(K51,K51)) -> https://amazon.com/dp/B0D7VS8SHS
A52: 8 | B52: B0G7P96Y1B | C52: GEARWRENCH 10" Pro Command Wireless Bi-Directional Diagnostic Tablet with Rapid-Charge Dock, Includes 4 Years of Software Updates | GWSMART10 | D52: gearwrench | E52: Tablet | F52: 1556.5595 | G52: 99619.81 | H52: 64 | I52: 24 | J52: 4.8 | K52: https://amazon.com/dp/B0G7P96Y1B | L52: =IF(K52="","",HYPERLINK(K52,K52)) -> https://amazon.com/dp/B0G7P96Y1B
A53: 9 | B53: B0GL6G61LW | C53: MUCAR 892BT PRO OBD2 Scanner with Topology Map, AI-Assisted Diagnostic Tool | D53: mucar | E53: Tablet | F53: 801.61017 | G53: 96193.22 | H53: 120 | I53: 164 | J53: 4.6 | K53: https://amazon.com/dp/B0GL6G61LW | L53: =IF(K53="","",HYPERLINK(K53,K53)) -> https://amazon.com/dp/B0GL6G61LW
A54: 10 | B54: B08PNTTMQ8 | C54: Autel MaxiIM IM608 PRO 2 Scanner, ECU Coding 40+ Service $1316 Bundle | D54: autel | E54: Tablet | F54: 3264.3671 | G54: 55494.24 | H54: 17 | I54: 81 | J54: 4.8 | K54: https://amazon.com/dp/B08PNTTMQ8 | L54: =IF(K54="","",HYPERLINK(K54,K54)) -> https://amazon.com/dp/B08PNTTMQ8
A56: Rank By Monthly Units - Jul '26 ONLY
A57: Ranking | B57: ASIN | C57: Product Name | D57: Brand | E57: Type | F57: Price | G57: Est. Monthly Retail Rev | H57: Est. Monthly Units Sold | I57: # of Reviews | J57: Avg. Rating | K57: Column2 | L57: Link
A58: 1 | B58: B0BMZW65LJ | C58: ANCEL MT700 Motorcycle OBD2 Scanner Full Systems, ABS Engine Meter TPMS Diagnostic Tool with 35+ Reset Functions for Harley Indian Yamaha Polaris Piaggio Ducati Honda BMW, AutoVIN, 7”Touch Screen,16G | D58: ancel | E58: Tablet | F58: 954.64527 | G58: 322670.1 | H58: 338 | I58: 914 | J58: 4.5 | K58: https://amazon.com/dp/B0BMZW65LJ | L58: =IF(K58="","",HYPERLINK(K58,K58)) -> https://amazon.com/dp/B0BMZW65LJ
A59: 2 | B59: B091BQNR3S | C59: TOPDON Phoenix Plus 2 Scanner with ECU Coding & Configuration, FCA SGW | D59: topdon | E59: Tablet | F59: 1004.0686 | G59: 211858.47 | H59: 211 | I59: 526 | J59: 4.5 | K59: https://amazon.com/dp/B091BQNR3S | L59: =IF(K59="","",HYPERLINK(K59,K59)) -> https://amazon.com/dp/B091BQNR3S
A60: 3 | B60: B0GLFSPMZ4 | C60: ANCEL X7HD PRO 10.1'' Heavy Duty Truck Scanner, Full-System Diesel Diagnostic Tool with DPF Regen, 42+ Reset, Bi-Directional and Active Test, ECU Coding, HDOBD/OBD2 Scanner for Diesel Trucks - Grey | D60: ancel | E60: Tablet | F60: 898.63143 | G60: 157260.5 | H60: 175 | I60: 48 | J60: 4.7 | K60: https://amazon.com/dp/B0GLFSPMZ4 | L60: =IF(K60="","",HYPERLINK(K60,K60)) -> https://amazon.com/dp/B0GLFSPMZ4
A61: 4 | B61: B0DTTTJWYH | C61: Launch X431 PRO3 V+ Elite SmartlinkC Bidirectional Scan Tool J2534 Protocol | D61: launch | E61: Tablet | F61: 1327.7482 | G61: 217750.71 | H61: 164 | I61: 113 | J61: 4.4 | K61: https://amazon.com/dp/B0DTTTJWYH | L61: =IF(K61="","",HYPERLINK(K61,K61)) -> https://amazon.com/dp/B0DTTTJWYH
A62: 5 | B62: B0GL6G61LW | C62: MUCAR 892BT PRO OBD2 Scanner with Topology Map, AI-Assisted Diagnostic Tool | D62: mucar | E62: Tablet | F62: 801.61017 | G62: 96193.22 | H62: 120 | I62: 164 | J62: 4.6 | K62: https://amazon.com/dp/B0GL6G61LW | L62: =IF(K62="","",HYPERLINK(K62,K62)) -> https://amazon.com/dp/B0GL6G61LW
A63: 6 | B63: B0D7VS8SHS | C63: LAUNCH X431 PRO3S+ Elite, 2026 Bidirectional Scan Tool with J2534 Protocols | D63: launch | E63: Tablet | F63: 1218.3985 | G63: 102345.47 | H63: 84 | I63: 172 | J63: 4.2 | K63: https://amazon.com/dp/B0D7VS8SHS | L63: =IF(K63="","",HYPERLINK(K63,K63)) -> https://amazon.com/dp/B0D7VS8SHS
A64: 7 | B64: B08V59JNYP | C64: LAUNCH X431 PRO3S+ Smartlink HD Heavy Duty Truck Scanner,J2534 Protocols | D64: launch | E64: Tablet | F64: 1881.0209 | G64: 129790.44 | H64: 69 | I64: 186 | J64: 4.3 | K64: https://amazon.com/dp/B08V59JNYP | L64: =IF(K64="","",HYPERLINK(K64,K64)) -> https://amazon.com/dp/B08V59JNYP
A65: 8 | B65: B0G7P96Y1B | C65: GEARWRENCH 10" Pro Command Wireless Bi-Directional Diagnostic Tablet with Rapid-Charge Dock, Includes 4 Years of Software Updates | GWSMART10 | D65: gearwrench | E65: Tablet | F65: 1556.5595 | G65: 99619.81 | H65: 64 | I65: 24 | J65: 4.8 | K65: https://amazon.com/dp/B0G7P96Y1B | L65: =IF(K65="","",HYPERLINK(K65,K65)) -> https://amazon.com/dp/B0G7P96Y1B
A66: 9 | B66: B092894STV | C66: Launch X431 PRO3S+ V5.0,2026 Upgrade All-in-One Bidirectional Scan Tool,HD Trucks Scan,Topology Map,ECU Code,55+ Service,Full System,CANFD&DOIP,DBSCar VII VCI 2-Year Update | D66: launch | E66: Tablet | F66: 1046.2453 | G66: 55451 | H66: 53 | I66: 699 | J66: 4.2 | K66: https://amazon.com/dp/B092894STV | L66: =IF(K66="","",HYPERLINK(K66,K66)) -> https://amazon.com/dp/B092894STV
A67: 10 | B67: B08PB6DHBS | C67: Autel MaxiCOM MK900TS Scanner, Bidirectional Scan Tool w/Top TPMS Function | D67: autel | E67: Tablet | F67: 886.63267 | G67: 39898.47 | H67: 45 | I67: 96 | J67: 4.8 | K67: https://amazon.com/dp/B08PB6DHBS | L67: =IF(K67="","",HYPERLINK(K67,K67)) -> https://amazon.com/dp/B08PB6DHBS

Sheet Tablet $400-$800
A1: Tablet $400-$800 Monthly Summary
A3: ='Tablet Total'!A81 -> Tablet $400-$800
B4: Avg Price | C4: Avg Price MoM | D4: Avg Price YoY | E4: Quantity/Mo | F4: Qty by % | G4: Qty MoM | H4: Qty YoY | I4: Revenue/Mo | J4: Revenue by % | L4: Revenue MoM | M4: Revenue YoY
A5: ='Tablet Total'!A83 -> autel | B5: ='Tablet Total'!B83 -> 536.14049 | C5: ='Tablet Total'!C83 -> -0.031530742 | D5: ='Tablet Total'!D83 -> 0.018309988 | E5: ='Tablet Total'!E83 -> 5461 | F5: ='Tablet Total'!F83 -> 0.44211464 | G5: ='Tablet Total'!G83 -> -0.052238806 | H5: ='Tablet Total'!H83 -> 0.22006256 | ... M5: ='Tablet Total'!M83 -> 0.24240189
A6: ='Tablet Total'!A84 -> launch | B6: ='Tablet Total'!B84 -> 554.10393 | C6: ='Tablet Total'!C84 -> -0.038343847 | D6: ='Tablet Total'!D84 -> 0.0027720742 | E6: ='Tablet Total'!E84 -> 1307 | F6: ='Tablet Total'!F84 -> 0.10581282 | G6: ='Tablet Total'!G84 -> -0.34747878 | H6: ='Tablet Total'!H84 -> -0.16164208 | ... M6: ='Tablet Total'!M84 -> -0.15931809
A7: ='Tablet Total'!A85 -> topdon | B7: ='Tablet Total'!B85 -> 615.18187 | C7: ='Tablet Total'!C85 -> -0.020308442 | D7: ='Tablet Total'!D85 -> 0.29935597 | E7: ='Tablet Total'!E85 -> 1053 | F7: ='Tablet Total'!F85 -> 0.085249352 | G7: ='Tablet Total'!G85 -> -0.28269755 | H7: ='Tablet Total'!H85 -> -0.3965616 | ... M7: ='Tablet Total'!M85 -> -0.21591872
A8: ='Tablet Total'!A86 -> xtool | B8: ='Tablet Total'!B86 -> 496.94875 | C8: ='Tablet Total'!C86 -> -0.016668468 | D8: ='Tablet Total'!D86 -> -0.028920039 | E8: ='Tablet Total'!E86 -> 997 | F8: ='Tablet Total'!F86 -> 0.080715674 | G8: ='Tablet Total'!G86 -> -0.35594315 | H8: ='Tablet Total'!H86 -> -0.4420817 | ... M8: ='Tablet Total'!M86 -> -0.45821672
A9: ='Tablet Total'!A87 -> ancel | B9: ='Tablet Total'!B87 -> 540.73332 | C9: ='Tablet Total'!C87 -> -0.023584292 | D9: ='Tablet Total'!D87 -> 0.11696695 | E9: ='Tablet Total'!E87 -> 906 | F9: ='Tablet Total'!F87 -> 0.073348446 | G9: ='Tablet Total'!G87 -> -0.36995828 | H9: ='Tablet Total'!H87 -> 1.0590909 | ... M9: ='Tablet Total'!M87 -> 1.2999365
A10: ='Tablet Total'!A88 -> innova | B10: ='Tablet Total'!B88 -> 514.99 | C10: ='Tablet Total'!C88 -> 0 | D10: ='Tablet Total'!D88 -> 0 | E10: ='Tablet Total'!E88 -> 4 | F10: ='Tablet Total'!F88 -> 0.0003238342 | G10: ='Tablet Total'!G88 -> 0 | H10: ='Tablet Total'!H88 -> 0 | ... M10: ='Tablet Total'!M88 -> 0
A11: ='Tablet Total'!A89 -> Other | B11: ='Tablet Total'!B89 -> 526.19106 | C11: ='Tablet Total'!C89 -> -0.065148451 | D11: ='Tablet Total'!D89 -> -0.034188075 | E11: ='Tablet Total'!E89 -> 2624 | F11: ='Tablet Total'!F89 -> 0.21243523 | G11: ='Tablet Total'!G89 -> -0.13141344 | H11: ='Tablet Total'!H89 -> 0.31991952 | ... M11: ='Tablet Total'!M89 -> 0.27479401
A12: ='Tablet Total'!A90 -> Tablet $400-$800 | B12: ='Tablet Total'!B90 -> 539.83251 | C12: ='Tablet Total'!C90 -> -0.037189415 | D12: ='Tablet Total'!D90 -> 0.035243678 | E12: ='Tablet Total'!E90 -> 12352 | F12: ='Tablet Total'!F90 -> 1 | G12: ='Tablet Total'!G90 -> -0.18950131 | H12: ='Tablet Total'!H90 -> 0.029762401 | ... M12: ='Tablet Total'!M90 -> 0.066055015
A44: Rank By Monthly Revenue - Jul '26 ONLY
A45: Ranking | B45: ASIN | C45: Product Name | D45: Brand | E45: Type | F45: Price | G45: Est. Monthly Retail Rev | H45: Est. Monthly Units Sold | I45: # of Reviews | J45: Avg. Rating | K45: Column2 | L45: Link
A46: 1 | B46: B098PYB8XG | C46: Autel Scanner MaxiCOM MK900BT Bidirectional Tool, 40+ Service, CAN-FD& DOIP | D46: autel | E46: Tablet | F46: 658.71861 | G46: 425532.22 | H46: 646 | I46: 778 | J46: 4.6 | K46: https://amazon.com/dp/B098PYB8XG | L46: =IF(K46="","",HYPERLINK(K46,K46)) -> https://amazon.com/dp/B098PYB8XG
A47: 2 | B47: B0GK9G6YDL | C47: TOPDON ONE Bidirectional Scan Tool, 10.1" Professional Diagnostic Tool | D47: topdon | E47: Tablet | F47: 734.64028 | G47: 418010.32 | H47: 569 | I47: 206 | J47: 4.5 | K47: https://amazon.com/dp/B0GK9G6YDL | L47: =IF(K47="","",HYPERLINK(K47,K47)) -> https://amazon.com/dp/B0GK9G6YDL
A48: 3 | B48: B0DTK24XKB | C48: MUCAR 892BT AI-Assisted Bidirectional Scan Tool, Full System OBD2 Scanner, Bi-Directional OBD2 Scanner Diagnostic Tool,ECU Coding, 35 Services, FCA Autoauth, CANFD and DOIP, Free Lifetime Updates | D48: mucar | E48: Tablet | F48: 586.13082 | G48: 341128.14 | H48: 582 | I48: 477 | J48: 4.2 | K48: https://amazon.com/dp/B0DTK24XKB | L48: =IF(K48="","",HYPERLINK(K48,K48)) -> https://amazon.com/dp/B0DTK24XKB
A49: 4 | B49: B0GX1WPD31 | C49: Autel Scanner MaxiCOM MK808S: 3000+ Active Tests 28+ Service as MK900-BT | D49: autel | E49: Tablet | F49: 468.70797 | G49: 284505.74 | H49: 607 | I49: 381 | J49: 4.4 | K49: https://amazon.com/dp/B0GX1WPD31 | L49: =IF(K49="","",HYPERLINK(K49,K49)) -> https://amazon.com/dp/B0GX1WPD31
A50: 5 | B50: B0744B55QV | C50: Autel Scanner MaxiCOM MK808S Bidirectional Tool, 28+ Hot Service All System | D50: autel | E50: Tablet | F50: 457.87741 | G50: 263737.39 | H50: 576 | I50: 3903 | J50: 4.4 | K50: https://amazon.com/dp/B0744B55QV | L50: =IF(K50="","",HYPERLINK(K50,K50)) -> https://amazon.com/dp/B0744B55QV
A51: 6 | B51: B08ML7T7KZ | C51: Autel Scanner MaxiCheck MX808S, Bidirectional OBD2 Scan Tool 28+ Service | D51: autel | E51: Tablet | F51: 430.55856 | G51: 248432.29 | H51: 577 | I51: 756 | J51: 4.6 | K51: https://amazon.com/dp/B08ML7T7KZ | L51: =IF(K51="","",HYPERLINK(K51,K51)) -> https://amazon.com/dp/B08ML7T7KZ
A52: 7 | B52: B09712X5CW | C52: Autel Scanner MaxiCOM MK900BT, 2026 MK900-BT 8in V2.0 Bidirectional Tool | D52: autel | E52: Tablet | F52: 659.4073 | G52: 222220.26 | H52: 337 | I52: 248 | J52: 4.6 | K52: https://amazon.com/dp/B09712X5CW | L52: =IF(K52="","",HYPERLINK(K52,K52)) -> https://amazon.com/dp/B09712X5CW
A53: 8 | B53: B0DCFRF2TF | C53: THINKCAR Bidirectional Scan Tool, THINKSCAN 689BT All System Automotive Diagnostic Tool, Bi Directional OBD2 Scanner with ECU Coding, 34 Services, FCA Autoauth, CANFD and DoIP, Wireless Update | D53: thinkcar | E53: Tablet | F53: 495.72564 | G53: 190854.37 | H53: 385 | I53: 642 | J53: 4.3 | K53: https://amazon.com/dp/B0DCFRF2TF | L53: =IF(K53="","",HYPERLINK(K53,K53)) -> https://amazon.com/dp/B0DCFRF2TF
A54: 9 | B54: B073CQMF25 | C54: Autel Scanner MaxiCOM MK900: 3000+ Active Tests 40+ Service as MK900-BT | D54: autel | E54: Tablet | F54: 588.2876 | G54: 186487.17 | H54: 317 | I54: 606 | J54: 4.4 | K54: https://amazon.com/dp/B073CQMF25 | L54: =IF(K54="","",HYPERLINK(K54,K54)) -> https://amazon.com/dp/B073CQMF25
A55: 10 | B55: B07PGYY8SS | C55: Autel Scanner MaxiCOM MK900BT: MK900-BT 8in V2.0 Bidirectional Scan Tool | D55: autel | E55: Tablet | F55: 660.23368 | G55: 159776.55 | H55: 242 | I55: 199 | J55: 4.5 | K55: https://amazon.com/dp/B07PGYY8SS | L55: =IF(K55="","",HYPERLINK(K55,K55)) -> https://amazon.com/dp/B07PGYY8SS
A57: Rank By Monthly Units - Jul '26 ONLY
A58: Ranking | B58: ASIN | C58: Product Name | D58: Brand | E58: Type | F58: Price | G58: Est. Monthly Retail Rev | H58: Est. Monthly Units Sold | I58: # of Reviews | J58: Avg. Rating | K58: Column2 | L58: Link
A59: 1 | B59: B098PYB8XG | C59: Autel Scanner MaxiCOM MK900BT Bidirectional Tool, 40+ Service, CAN-FD& DOIP | D59: autel | E59: Tablet | F59: 658.71861 | G59: 425532.22 | H59: 646 | I59: 778 | J59: 4.6 | K59: https://amazon.com/dp/B098PYB8XG | L59: =IF(K59="","",HYPERLINK(K59,K59)) -> https://amazon.com/dp/B098PYB8XG
A60: 2 | B60: B0GX1WPD31 | C60: Autel Scanner MaxiCOM MK808S: 3000+ Active Tests 28+ Service as MK900-BT | D60: autel | E60: Tablet | F60: 468.70797 | G60: 284505.74 | H60: 607 | I60: 381 | J60: 4.4 | K60: https://amazon.com/dp/B0GX1WPD31 | L60: =IF(K60="","",HYPERLINK(K60,K60)) -> https://amazon.com/dp/B0GX1WPD31
A61: 3 | B61: B0DTK24XKB | C61: MUCAR 892BT AI-Assisted Bidirectional Scan Tool, Full System OBD2 Scanner, Bi-Directional OBD2 Scanner Diagnostic Tool,ECU Coding, 35 Services, FCA Autoauth, CANFD and DOIP, Free Lifetime Updates | D61: mucar | E61: Tablet | F61: 586.13082 | G61: 341128.14 | H61: 582 | I61: 477 | J61: 4.2 | K61: https://amazon.com/dp/B0DTK24XKB | L61: =IF(K61="","",HYPERLINK(K61,K61)) -> https://amazon.com/dp/B0DTK24XKB
A62: 4 | B62: B08ML7T7KZ | C62: Autel Scanner MaxiCheck MX808S, Bidirectional OBD2 Scan Tool 28+ Service | D62: autel | E62: Tablet | F62: 430.55856 | G62: 248432.29 | H62: 577 | I62: 756 | J62: 4.6 | K62: https://amazon.com/dp/B08ML7T7KZ | L62: =IF(K62="","",HYPERLINK(K62,K62)) -> https://amazon.com/dp/B08ML7T7KZ
A63: 5 | B63: B0744B55QV | C63: Autel Scanner MaxiCOM MK808S Bidirectional Tool, 28+ Hot Service All System | D63: autel | E63: Tablet | F63: 457.87741 | G63: 263737.39 | H63: 576 | I63: 3903 | J63: 4.4 | K63: https://amazon.com/dp/B0744B55QV | L63: =IF(K63="","",HYPERLINK(K63,K63)) -> https://amazon.com/dp/B0744B55QV
A64: 6 | B64: B0GK9G6YDL | C64: TOPDON ONE Bidirectional Scan Tool, 10.1" Professional Diagnostic Tool | D64: topdon | E64: Tablet | F64: 734.64028 | G64: 418010.32 | H64: 569 | I64: 206 | J64: 4.5 | K64: https://amazon.com/dp/B0GK9G6YDL | L64: =IF(K64="","",HYPERLINK(K64,K64)) -> https://amazon.com/dp/B0GK9G6YDL
A65: 7 | B65: B0DCFRF2TF | C65: THINKCAR Bidirectional Scan Tool, THINKSCAN 689BT All System Automotive Diagnostic Tool, Bi Directional OBD2 Scanner with ECU Coding, 34 Services, FCA Autoauth, CANFD and DoIP, Wireless Update | D65: thinkcar | E65: Tablet | F65: 495.72564 | G65: 190854.37 | H65: 385 | I65: 642 | J65: 4.3 | K65: https://amazon.com/dp/B0DCFRF2TF | L65: =IF(K65="","",HYPERLINK(K65,K65)) -> https://amazon.com/dp/B0DCFRF2TF
A66: 8 | B66: B0BNKHCXVC | C66: TOPDON ArtiDiag Pro Bidirectional Scan Tool with ECU Coding, 35+ Services | D66: topdon | E66: Tablet | F66: 417.12327 | G66: 142656.16 | H66: 342 | I66: 801 | J66: 4.3 | K66: https://amazon.com/dp/B0BNKHCXVC | L66: =IF(K66="","",HYPERLINK(K66,K66)) -> https://amazon.com/dp/B0BNKHCXVC
A67: 9 | B67: B09712X5CW | C67: Autel Scanner MaxiCOM MK900BT, 2026 MK900-BT 8in V2.0 Bidirectional Tool | D67: autel | E67: Tablet | F67: 659.4073 | G67: 222220.26 | H67: 337 | I67: 248 | J67: 4.6 | K67: https://amazon.com/dp/B09712X5CW | L67: =IF(K67="","",HYPERLINK(K67,K67)) -> https://amazon.com/dp/B09712X5CW
A68: 10 | B68: B073CQMF25 | C68: Autel Scanner MaxiCOM MK900: 3000+ Active Tests 40+ Service as MK900-BT | D68: autel | E68: Tablet | F68: 588.2876 | G68: 186487.17 | H68: 317 | I68: 606 | J68: 4.4 | K68: https://amazon.com/dp/B073CQMF25 | L68: =IF(K68="","",HYPERLINK(K68,K68)) -> https://amazon.com/dp/B073CQMF25

Sheet Tablet $400-
A1: Tablet $400- Monthly Summary
A3: ='Tablet Total'!A91 -> 0
B4: Avg Price | C4: Avg Price MoM | D4: Avg Price YoY | E4: Quantity/Mo | F4: Qty by % | G4: Qty MoM | H4: Qty YoY | I4: Revenue/Mo | J4: Revenue by % | L4: Revenue MoM | M4: Revenue YoY
A5: ='Tablet Total'!A94 -> topdon | B5: ='Tablet Total'!B94 -> 236.55165 | C5: ='Tablet Total'!C94 -> -0.04279377 | D5: ='Tablet Total'!D94 -> 0.18014981 | E5: ='Tablet Total'!E94 -> 4961 | F5: ='Tablet Total'!F94 -> 0.20265523 | G5: ='Tablet Total'!G94 -> -0.066603951 | H5: ='Tablet Total'!H94 -> 0.18203479 | ... M5: ='Tablet Total'!M94 -> 0.39497812
A6: ='Tablet Total'!A95 -> foxwell | B6: ='Tablet Total'!B95 -> 197.28926 | C6: ='Tablet Total'!C95 -> -0.026523972 | D6: ='Tablet Total'!D95 -> 0.017417114 | E6: ='Tablet Total'!E95 -> 4481 | F6: ='Tablet Total'!F95 -> 0.18304739 | G6: ='Tablet Total'!G95 -> -0.13959293 | H6: ='Tablet Total'!H95 -> 0.38046827 | ... M6: ='Tablet Total'!M95 -> 0.40451204
A7: ='Tablet Total'!A96 -> xtool | B7: ='Tablet Total'!B96 -> 217.21334 | C7: ='Tablet Total'!C96 -> 0.077334866 | D7: ='Tablet Total'!D96 -> 0.13322267 | E7: ='Tablet Total'!E96 -> 3226 | F7: ='Tablet Total'!F96 -> 0.13178105 | G7: ='Tablet Total'!G96 -> 0.19304734 | H7: ='Tablet Total'!H96 -> 1.8223972 | ... M7: ='Tablet Total'!M96 -> 2.1984045
A8: ='Tablet Total'!A97 -> launch | B8: ='Tablet Total'!B97 -> 186.20196 | C8: ='Tablet Total'!C97 -> -0.036622572 | D8: ='Tablet Total'!D97 -> 0.057537918 | E8: ='Tablet Total'!E97 -> 2290 | F8: ='Tablet Total'!F97 -> 0.093545752 | G8: ='Tablet Total'!G97 -> -0.080321285 | H8: ='Tablet Total'!H97 -> -0.47621226 | ... M8: ='Tablet Total'!M97 -> -0.4460746
A9: ='Tablet Total'!A98 -> icarsoft | B9: ='Tablet Total'!B98 -> 204.08907 | C9: ='Tablet Total'!C98 -> 0.006354074 | D9: ='Tablet Total'!D98 -> 0.0044221043 | E9: ='Tablet Total'!E98 -> 1882 | F9: ='Tablet Total'!F98 -> 0.076879085 | G9: ='Tablet Total'!G98 -> -0.16578014 | H9: ='Tablet Total'!H98 -> 0.093550261 | ... M9: ='Tablet Total'!M98 -> 0.098386055
A10: ='Tablet Total'!A99 -> blcktec | B10: ='Tablet Total'!B99 -> 189.09779 | C10: ='Tablet Total'!C99 -> -0.054412014 | D10: ='Tablet Total'!D99 -> -0.054359836 | E10: ='Tablet Total'!E99 -> 1838 | F10: ='Tablet Total'!F99 -> 0.075081699 | G10: ='Tablet Total'!G99 -> 0.047293447 | H10: ='Tablet Total'!H99 -> 1.2889166 | ... M10: ='Tablet Total'!M99 -> 1.1644914
A11: ='Tablet Total'!A100 -> innova | B11: ='Tablet Total'!B100 -> 139.16602 | C11: ='Tablet Total'!C100 -> -0.11254738 | D11: ='Tablet Total'!D100 -> -0.25624906 | E11: ='Tablet Total'!E100 -> 668 | F11: ='Tablet Total'!F100 -> 0.027287582 | G11: ='Tablet Total'!G100 -> -0.15012723 | H11: ='Tablet Total'!H100 -> 2.5157895 | ... M11: ='Tablet Total'!M100 -> 1.6148717
A12: ='Tablet Total'!A101 -> Other | B12: ='Tablet Total'!B101 -> 219.09539 | C12: ='Tablet Total'!C101 -> -0.0099241479 | D12: ='Tablet Total'!D101 -> -0.11917528 | E12: ='Tablet Total'!E101 -> 5134 | F12: ='Tablet Total'!F101 -> 0.20972222 | G12: ='Tablet Total'!G101 -> -0.29078602 | H12: ='Tablet Total'!H101 -> 0.43008357 | ... M12: ='Tablet Total'!M101 -> 0.25965295
A13: ='Tablet Total'!A102 -> Tablet $400- | B13: ='Tablet Total'!B102 -> 209.72935 | C13: ='Tablet Total'!C102 -> -0.018292626 | D13: ='Tablet Total'!D102 -> 0.036285409 | E13: ='Tablet Total'!E102 -> 24480 | F13: ='Tablet Total'!F102 -> 1 | G13: ='Tablet Total'!G102 -> -0.1179332 | H13: ='Tablet Total'!H102 -> 0.27089606 | ... M13: ='Tablet Total'!M102 -> 0.31701105
A45: Rank By Monthly Revenue - Jul '26 ONLY
A46: Ranking | B46: ASIN | C46: Product Name | D46: Brand | E46: Type | F46: Price | G46: Est. Monthly Retail Rev | H46: Est. Monthly Units Sold | I46: # of Reviews | J46: Avg. Rating | K46: Column2 | L46: Link
A47: 1 | B47: B0DV2N2FND | C47: BLCKTEC 460T OBD2 Scanner Car Code Reader Engine ABS SRS Transmission Diagnostic Tool, 12 Reset Services, Oil/TPMS/EPB/BMS/SAS/DPF/Throttle Reset, ABS Bleeding, Battery Test, Auto VIN, Free Update | D47: blcktec | E47: Tablet | F47: 189.09779 | G47: 347561.74 | H47: 1838 | I47: 773 | J47: 4.4 | K47: https://amazon.com/dp/B0DV2N2FND | L47: =IF(K47="","",HYPERLINK(K47,K47)) -> https://amazon.com/dp/B0DV2N2FND
A48: 2 | B48: B0C33Y285Y | C48: TOPDON AD900 Lite OBD2 Scanner, Bidirectional Scan Tool, 8" Large Screen | D48: topdon | E48: Tablet | F48: 313.50156 | G48: 323847.11 | H48: 1033 | I48: 3990 | J48: 4.3 | K48: https://amazon.com/dp/B0C33Y285Y | L48: =IF(K48="","",HYPERLINK(K48,K48)) -> https://amazon.com/dp/B0C33Y285Y
A49: 3 | B49: B08PFJMTY3 | C49: FOXWELL Car Scanner NT604 Elite OBD2 Scanner ABS SRS Transmission | D49: foxwell | E49: Tablet | F49: 149.44571 | G49: 290373.01 | H49: 1943 | I49: 5051 | J49: 4.4 | K49: https://amazon.com/dp/B08PFJMTY3 | L49: =IF(K49="","",HYPERLINK(K49,K49)) -> https://amazon.com/dp/B08PFJMTY3
A50: 4 | B50: B098LF38DS | C50: XTOOL D7 Bidirectional Scan Tool, 39+ Resets, ECU Coding OBD2 Scanner | D50: xtool | E50: Tablet | F50: 356.70991 | G50: 199757.55 | H50: 560 | I50: 1679 | J50: 4.4 | K50: https://amazon.com/dp/B098LF38DS | L50: =IF(K50="","",HYPERLINK(K50,K50)) -> https://amazon.com/dp/B098LF38DS
A51: 5 | B51: B09KZTYD18 | C51: TOPDON AD600S OBD2 Scanner, Engine ABS SRS Transmission Diagnostic Tool | D51: topdon | E51: Tablet | F51: 191.15372 | G51: 187139.49 | H51: 979 | I51: 1944 | J51: 4.4 | K51: https://amazon.com/dp/B09KZTYD18 | L51: =IF(K51="","",HYPERLINK(K51,K51)) -> https://amazon.com/dp/B09KZTYD18
A52: 6 | B52: B08TR5PS5V | C52: TOPDON AD800BT 2 OBD2 Scanner, Bidirectional Scan Tool, 28+ Reset Service | D52: topdon | E52: Tablet | F52: 312.08133 | G52: 151983.61 | H52: 487 | I52: 870 | J52: 4.4 | K52: https://amazon.com/dp/B08TR5PS5V | L52: =IF(K52="","",HYPERLINK(K52,K52)) -> https://amazon.com/dp/B08TR5PS5V
A53: 7 | B53: B0BFBQZZMC | C53: ScanGauge 3 Touch Screen OBD2 Scanner, Digital Gauges & Trip Computer SG3 | D53: scangauge | E53: Tablet | F53: 269.97451 | G53: 143626.44 | H53: 532 | I53: 451 | J53: 4.5 | K53: https://amazon.com/dp/B0BFBQZZMC | L53: =IF(K53="","",HYPERLINK(K53,K53)) -> https://amazon.com/dp/B0BFBQZZMC
A54: 8 | B54: B08XK3DJ42 | C54: TOPDON AD500 OBD2 Scanner Car Diagnostic Tool, Engine ABS SRS Transmission | D54: topdon | E54: Tablet | F54: 155.79363 | G54: 131801.41 | H54: 846 | I54: 1841 | J54: 4.4 | K54: https://amazon.com/dp/B08XK3DJ42 | L54: =IF(K54="","",HYPERLINK(K54,K54)) -> https://amazon.com/dp/B08XK3DJ42
A55: 9 | B55: B08DCNDFVK | C55: 2026 FOXWELL NT614 Elite OBD2 Scanner, 4 Systems, 5 Resets Code Reader | D55: foxwell | E55: Tablet | F55: 168.11133 | G55: 125074.83 | H55: 744 | I55: 796 | J55: 4.3 | K55: https://amazon.com/dp/B08DCNDFVK | L55: =IF(K55="","",HYPERLINK(K55,K55)) -> https://amazon.com/dp/B08DCNDFVK
A56: 10 | B56: B0F3XRK4P9 | C56: 2026 FOXWELL NT726 OBD2 Scanner, 12Resets, All System Bidirectional Scanner | D56: foxwell | E56: Tablet | F56: 342.43927 | G56: 121565.94 | H56: 355 | I56: 135 | J56: 4.4 | K56: https://amazon.com/dp/B0F3XRK4P9 | L56: =IF(K56="","",HYPERLINK(K56,K56)) -> https://amazon.com/dp/B0F3XRK4P9
A58: Rank By Monthly Units - Jul '26 ONLY
A59: Ranking | B59: ASIN | C59: Product Name | D59: Brand | E59: Type | F59: Price | G59: Est. Monthly Retail Rev | H59: Est. Monthly Units Sold | I59: # of Reviews | J59: Avg. Rating | K59: Column2 | L59: Link
A60: 1 | B60: B08PFJMTY3 | C60: FOXWELL Car Scanner NT604 Elite OBD2 Scanner ABS SRS Transmission | D60: foxwell | E60: Tablet | F60: 149.44571 | G60: 290373.01 | H60: 1943 | I60: 5051 | J60: 4.4 | K60: https://amazon.com/dp/B08PFJMTY3 | L60: =IF(K60="","",HYPERLINK(K60,K60)) -> https://amazon.com/dp/B08PFJMTY3
A61: 2 | B61: B0DV2N2FND | C61: BLCKTEC 460T OBD2 Scanner Car Code Reader Engine ABS SRS Transmission Diagnostic Tool, 12 Reset Services, Oil/TPMS/EPB/BMS/SAS/DPF/Throttle Reset, ABS Bleeding, Battery Test, Auto VIN, Free Update | D61: blcktec | E61: Tablet | F61: 189.09779 | G61: 347561.74 | H61: 1838 | I61: 773 | J61: 4.4 | K61: https://amazon.com/dp/B0DV2N2FND | L61: =IF(K61="","",HYPERLINK(K61,K61)) -> https://amazon.com/dp/B0DV2N2FND
A62: 3 | B62: B0C33Y285Y | C62: TOPDON AD900 Lite OBD2 Scanner, Bidirectional Scan Tool, 8" Large Screen | D62: topdon | E62: Tablet | F62: 313.50156 | G62: 323847.11 | H62: 1033 | I62: 3990 | J62: 4.3 | K62: https://amazon.com/dp/B0C33Y285Y | L62: =IF(K62="","",HYPERLINK(K62,K62)) -> https://amazon.com/dp/B0C33Y285Y
A63: 4 | B63: B09KZTYD18 | C63: TOPDON AD600S OBD2 Scanner, Engine ABS SRS Transmission Diagnostic Tool | D63: topdon | E63: Tablet | F63: 191.15372 | G63: 187139.49 | H63: 979 | I63: 1944 | J63: 4.4 | K63: https://amazon.com/dp/B09KZTYD18 | L63: =IF(K63="","",HYPERLINK(K63,K63)) -> https://amazon.com/dp/B09KZTYD18
A64: 5 | B64: B08XK3DJ42 | C64: TOPDON AD500 OBD2 Scanner Car Diagnostic Tool, Engine ABS SRS Transmission | D64: topdon | E64: Tablet | F64: 155.79363 | G64: 131801.41 | H64: 846 | I64: 1841 | J64: 4.4 | K64: https://amazon.com/dp/B08XK3DJ42 | L64: =IF(K64="","",HYPERLINK(K64,K64)) -> https://amazon.com/dp/B08XK3DJ42
A65: 6 | B65: B08DCNDFVK | C65: 2026 FOXWELL NT614 Elite OBD2 Scanner, 4 Systems, 5 Resets Code Reader | D65: foxwell | E65: Tablet | F65: 168.11133 | G65: 125074.83 | H65: 744 | I65: 796 | J65: 4.3 | K65: https://amazon.com/dp/B08DCNDFVK | L65: =IF(K65="","",HYPERLINK(K65,K65)) -> https://amazon.com/dp/B08DCNDFVK
A66: 7 | B66: B0F254MVB5 | C66: Innova SD35 OBD2 Scanner – ABS, SRS, TPMS & Check Engine Code Reader, Live Data, All System Diagnostics, Compatible with Most Vehicles | D66: innova | E66: Tablet | F66: 131.7605 | G66: 84063.2 | H66: 638 | I66: 430 | J66: 4.4 | K66: https://amazon.com/dp/B0F254MVB5 | L66: =IF(K66="","",HYPERLINK(K66,K66)) -> https://amazon.com/dp/B0F254MVB5
A67: 8 | B67: B0DFCMT416 | C67: XTOOL D5S OBD2 Scanner, 16 Resets, Engine ABS SRS Transmission Scan Tool | D67: xtool | E67: Tablet | F67: 170.41203 | G67: 102417.63 | H67: 601 | I67: 518 | J67: 4.3 | K67: https://amazon.com/dp/B0DFCMT416 | L67: =IF(K67="","",HYPERLINK(K67,K67)) -> https://amazon.com/dp/B0DFCMT416
A68: 9 | B68: B098LF38DS | C68: XTOOL D7 Bidirectional Scan Tool, 39+ Resets, ECU Coding OBD2 Scanner | D68: xtool | E68: Tablet | F68: 356.70991 | G68: 199757.55 | H68: 560 | I68: 1679 | J68: 4.4 | K68: https://amazon.com/dp/B098LF38DS | L68: =IF(K68="","",HYPERLINK(K68,K68)) -> https://amazon.com/dp/B098LF38DS
A69: 10 | B69: B0BFBQZZMC | C69: ScanGauge 3 Touch Screen OBD2 Scanner, Digital Gauges & Trip Computer SG3 | D69: scangauge | E69: Tablet | F69: 269.97451 | G69: 143626.44 | H69: 532 | I69: 451 | J69: 4.5 | K69: https://amazon.com/dp/B0BFBQZZMC | L69: =IF(K69="","",HYPERLINK(K69,K69)) -> https://amazon.com/dp/B0BFBQZZMC

Sheet Handheld Total
A1: Handheld Monthly Summary
A3: Handheld Overall
B4: Avg Price | C4: Avg Price MoM | D4: Avg Price YoY | E4: Quantity/Mo | F4: Qty by % | G4: Qty MoM | H4: Qty YoY | I4: Revenue/Mo | J4: Revenue by % | L4: Revenue MoM | M4: Revenue YoY
A5: innova | B5: 202.87034 | C5: -0.061848381 | D5: -0.021625905 | E5: 7792 | F5: 0.065501559 | G5: 0.19987681 | H5: 0.32314485 | I5: 1580765.7 | J5: 0.24287527 | L5: 0.12566637 | M5: 0.29453064
A6: ancel | B6: 36.162241 | C6: -0.010861046 | D6: -0.14298288 | E6: 40165 | F6: 0.33763734 | G6: 0.048968399 | H6: 0.015036644 | I6: 1452456.4 | J6: 0.22316131 | L6: 0.037575505 | M6: -0.13009622
A7: foxwell | B7: 96.752896 | C7: -0.025143489 | D7: 0.094259908 | E7: 9668 | F7: 0.081271699 | G7: -0.0072902762 | H7: -0.035803331 | I7: 935407 | J7: 0.14371973 | L7: -0.032250462 | M7: 0.055081759
A8: autel | B8: 58.052552 | C8: -0.086485016 | D8: -0.28212029 | E8: 6259 | F8: 0.052614766 | G8: -0.14552901 | H8: -0.11194665 | I8: 363350.92 | J8: 0.055826713 | L8: -0.21942795 | M8: -0.36248452
A9: motopower | B9: 23.843814 | C9: -0.14830861 | D9: -0.0052300627 | E9: 12161 | F9: 0.1022285 | G9: 0.89305729 | H9: 0.24728205 | I9: 289964.62 | J9: 0.044551343 | L9: 0.6123006 | M9: 0.24075869
A10: blcktec | B10: 60.834929 | C10: 0.053489786 | D10: 0.15075622 | E10: 911 | F10: 0.0076581007 | G10: -0.12319538 | H10: -0.51047824 | I10: 55420.62 | J10: 0.0085150494 | L10: -0.076295289 | M10: -0.43667979
A11: Other | B11: 43.596509 | C11: -0.002797984 | D11: 0.16972289 | E11: 42003 | F11: 0.35308804 | G11: -0.16584581 | H11: -0.12883957 | I11: 1831184.2 | J11: 0.28135058 | L11: -0.16817976 | M11: 0.019016293
A12: Total Handheld | B12: 54.712543 | C12: -0.019514423 | D12: 0.033695623 | E12: 118959 | F12: 1 | G12: -0.0058998036 | H12: -0.027795031 | I12: 6508549.5 | J12: 1 | L12: -0.025299096 | M12: 0.0049640211
A44: Rank By Monthly Revenue - Jul '26 ONLY
A45: Ranking | B45: ASIN | C45: Product Name | D45: Brand | E45: Type | F45: Price | G45: Est. Monthly Retail Rev | H45: Est. Monthly Units Sold | I45: # of Reviews | J45: Avg. Rating | K45: Column2 | L45: Link
A46: 1 | B46: B07Z481NJM | C46: Innova 5610 OBD2 Bidirectional Scan Tool - Understand Your Vehicle, Pinpoint What's Wrong, and Complete Your Repairs with Less Headache, Updates Included, US-Based Technical Support | D46: innova | E46: Handheld | F46: 304.05607 | G46: 1174264.6 | H46: 3862 | I46: 3791 | J46: 4.4 | K46: https://amazon.com/dp/B07Z481NJM | L46: =IF(K46="","",HYPERLINK(K46,K46)) -> https://amazon.com/dp/B07Z481NJM
A47: 2 | B47: B01G5EA74I | C47: ANCEL AD310 Classic Enhanced Universal OBD II Scanner Car Engine Fault Code Reader CAN Diagnostic Scan Tool, Read and Clear Error Codes for 1996 or Newer OBD2 Protocol Vehicle (Black) | D47: ancel | E47: Handheld | F47: 27.817391 | G47: 815550.26 | H47: 29318 | I47: 65760 | J47: 4.6 | K47: https://amazon.com/dp/B01G5EA74I | L47: =IF(K47="","",HYPERLINK(K47,K47)) -> https://amazon.com/dp/B01G5EA74I
A48: 3 | B48: B00UJV3E12 | C48: FOXWELL NT301 OBD2 Scanner Live Data Professional Mechanic OBDII Diagnostic Code Reader Tool for Check Engine Light | D48: foxwell | E48: Handheld | F48: 64.043987 | G48: 358198.02 | H48: 5593 | I48: 30049 | J48: 4.5 | K48: https://amazon.com/dp/B00UJV3E12 | L48: =IF(K48="","",HYPERLINK(K48,K48)) -> https://amazon.com/dp/B00UJV3E12
A49: 4 | B49: B07Z3HB7DR | C49: MOTOPOWER MP69033 Car OBD2 Scanner Code Reader Engine Fault Scanner CAN Diagnostic Scan Tool for All OBD II Protocol Cars Since 1996, Yellow | D49: motopower | E49: Handheld | F49: 23.211108 | G49: 259500.19 | H49: 11180 | I49: 51762 | J49: 4.6 | K49: https://amazon.com/dp/B07Z3HB7DR | L49: =IF(K49="","",HYPERLINK(K49,K49)) -> https://amazon.com/dp/B07Z3HB7DR
A50: 5 | B50: B07Z46L5FG | C50: Innova 5210 OBD2 Scanner & Engine Code Reader, Battery Tester, Live Data, Oil Reset, Car Diagnostic Tool for Most Vehicles, Bluetooth Compatible with America's Top Car Repair App | D50: innova | E50: Handheld | F50: 86.696119 | G50: 249077.95 | H50: 2873 | I50: 4155 | J50: 4.5 | K50: https://amazon.com/dp/B07Z46L5FG | L50: =IF(K50="","",HYPERLINK(K50,K50)) -> https://amazon.com/dp/B07Z46L5FG
A51: 6 | B51: B071FSNL73 | C51: ANCEL AD410 Enhanced OBD2 Scanner, Vehicle Code Reader for Check Engine Light, Automotive OBD II Scanner Fault Diagnosis, OBDII Scan Tool for All OBDII Cars 1996+, Black/Yellow | D51: ancel | E51: Handheld | F51: 41.468081 | G51: 234211.72 | H51: 5648 | I51: 15482 | J51: 4.5 | K51: https://amazon.com/dp/B071FSNL73 | L51: =IF(K51="","",HYPERLINK(K51,K51)) -> https://amazon.com/dp/B071FSNL73
A52: 7 | B52: B019QCG5RE | C52: FOXWELL NT510 Elite Scan Tool fit for BMW Scanner Full Diagnostic Tool OBD2 Scanner, All System Bi-Directional Control Code Reader with All Reset Services, Battery Registration Tool fit for BMW Mini | D52: foxwell | E52: Handheld | F52: 177.72473 | G52: 125118.21 | H52: 704 | I52: 3174 | J52: 4.3 | K52: https://amazon.com/dp/B019QCG5RE | L52: =IF(K52="","",HYPERLINK(K52,K52)) -> https://amazon.com/dp/B019QCG5RE
A53: 8 | B53: B0BY1TS725 | C53: VDIAGTOOL VD10 OBD2 Scanner Code Reader Car Diagnostic Tool Engine Fault Code Reader for Turn Off CEL with Freeze Frame/I/M Readiness for All OBDII Protocol Cars, OBD2 Scanner Diagnostic Tool | D53: vdiagtool | E53: Handheld | F53: 18.105488 | G53: 98186.06 | H53: 5423 | I53: 3034 | J53: 4.6 | K53: https://amazon.com/dp/B0BY1TS725 | L53: =IF(K53="","",HYPERLINK(K53,K53)) -> https://amazon.com/dp/B0BY1TS725
A54: 9 | B54: B09YRDGY3Z | C54: Thinkdiag2 All System Bidirectional OBD2 Diagnostic Scanner for iOS & Android, THINKCAR Bluetooth Scan Tool with CAN-FD Protocol, 15+ Reset Functions, ECU Code, Active Test, AutoVIN, 1 Year Update | D54: thinkcar | E54: Handheld | F54: 159.9019 | G54: 90664.38 | H54: 567 | I54: 1468 | J54: 4.2 | K54: https://amazon.com/dp/B09YRDGY3Z | L54: =IF(K54="","",HYPERLINK(K54,K54)) -> https://amazon.com/dp/B09YRDGY3Z
A55: 10 | B55: B07ZL7CLYR | C55: Innova 5410 All-System OBD2 Scanner Diagnostic Tool for Cars & Trucks – Automotive Scan Tools for Engine, ABS, SRS & Transmission, Bluetooth Compatible with America's Top Car Repair App | D55: innova | E55: Handheld | F55: 154.21691 | G55: 87286.77 | H55: 566 | I55: 730 | J55: 4.4 | K55: https://amazon.com/dp/B07ZL7CLYR | L55: =IF(K55="","",HYPERLINK(K55,K55)) -> https://amazon.com/dp/B07ZL7CLYR
A57: Rank By Monthly Units - Jul '26 ONLY
A58: Ranking | B58: ASIN | C58: Product Name | D58: Brand | E58: Type | F58: Price | G58: Est. Monthly Retail Rev | H58: Est. Monthly Units Sold | I58: # of Reviews | J58: Avg. Rating | K58: Column2 | L58: Link
A59: 1 | B59: B01G5EA74I | C59: ANCEL AD310 Classic Enhanced Universal OBD II Scanner Car Engine Fault Code Reader CAN Diagnostic Scan Tool, Read and Clear Error Codes for 1996 or Newer OBD2 Protocol Vehicle (Black) | D59: ancel | E59: Handheld | F59: 27.817391 | G59: 815550.26 | H59: 29318 | I59: 65760 | J59: 4.6 | K59: https://amazon.com/dp/B01G5EA74I | L59: =IF(K59="","",HYPERLINK(K59,K59)) -> https://amazon.com/dp/B01G5EA74I
A60: 2 | B60: B07Z3HB7DR | C60: MOTOPOWER MP69033 Car OBD2 Scanner Code Reader Engine Fault Scanner CAN Diagnostic Scan Tool for All OBD II Protocol Cars Since 1996, Yellow | D60: motopower | E60: Handheld | F60: 23.211108 | G60: 259500.19 | H60: 11180 | I60: 51762 | J60: 4.6 | K60: https://amazon.com/dp/B07Z3HB7DR | L60: =IF(K60="","",HYPERLINK(K60,K60)) -> https://amazon.com/dp/B07Z3HB7DR
A61: 3 | B61: B071FSNL73 | C61: ANCEL AD410 Enhanced OBD2 Scanner, Vehicle Code Reader for Check Engine Light, Automotive OBD II Scanner Fault Diagnosis, OBDII Scan Tool for All OBDII Cars 1996+, Black/Yellow | D61: ancel | E61: Handheld | F61: 41.468081 | G61: 234211.72 | H61: 5648 | I61: 15482 | J61: 4.5 | K61: https://amazon.com/dp/B071FSNL73 | L61: =IF(K61="","",HYPERLINK(K61,K61)) -> https://amazon.com/dp/B071FSNL73
A62: 4 | B62: B00UJV3E12 | C62: FOXWELL NT301 OBD2 Scanner Live Data Professional Mechanic OBDII Diagnostic Code Reader Tool for Check Engine Light | D62: foxwell | E62: Handheld | F62: 64.043987 | G62: 358198.02 | H62: 5593 | I62: 30049 | J62: 4.5 | K62: https://amazon.com/dp/B00UJV3E12 | L62: =IF(K62="","",HYPERLINK(K62,K62)) -> https://amazon.com/dp/B00UJV3E12
A63: 5 | B63: B0BY1TS725 | C63: VDIAGTOOL VD10 OBD2 Scanner Code Reader Car Diagnostic Tool Engine Fault Code Reader for Turn Off CEL with Freeze Frame/I/M Readiness for All OBDII Protocol Cars, OBD2 Scanner Diagnostic Tool | D63: vdiagtool | E63: Handheld | F63: 18.105488 | G63: 98186.06 | H63: 5423 | I63: 3034 | J63: 4.6 | K63: https://amazon.com/dp/B0BY1TS725 | L63: =IF(K63="","",HYPERLINK(K63,K63)) -> https://amazon.com/dp/B0BY1TS725
A64: 6 | B64: B07Z481NJM | C64: Innova 5610 OBD2 Bidirectional Scan Tool - Understand Your Vehicle, Pinpoint What's Wrong, and Complete Your Repairs with Less Headache, Updates Included, US-Based Technical Support | D64: innova | E64: Handheld | F64: 304.05607 | G64: 1174264.6 | H64: 3862 | I64: 3791 | J64: 4.4 | K64: https://amazon.com/dp/B07Z481NJM | L64: =IF(K64="","",HYPERLINK(K64,K64)) -> https://amazon.com/dp/B07Z481NJM
A65: 7 | B65: B07Z46L5FG | C65: Innova 5210 OBD2 Scanner & Engine Code Reader, Battery Tester, Live Data, Oil Reset, Car Diagnostic Tool for Most Vehicles, Bluetooth Compatible with America's Top Car Repair App | D65: innova | E65: Handheld | F65: 86.696119 | G65: 249077.95 | H65: 2873 | I65: 4155 | J65: 4.5 | K65: https://amazon.com/dp/B07Z46L5FG | L65: =IF(K65="","",HYPERLINK(K65,K65)) -> https://amazon.com/dp/B07Z46L5FG
A66: 8 | B66: B007XE8C74 | C66: Autel AL319 Professional OBD2 Scanner, Enhanced Check Engine Code Reader | D66: autel | E66: Handheld | F66: 33.609584 | G66: 77503.7 | H66: 2306 | I66: 26046 | J66: 4.6 | K66: https://amazon.com/dp/B007XE8C74 | L66: =IF(K66="","",HYPERLINK(K66,K66)) -> https://amazon.com/dp/B007XE8C74
A67: 9 | B67: B0C2V3RYLY | C67: ZMOON ZM201 Professional OBD2 Scanner Diagnostic Tool, Enhanced Check Engine Code Reader with Reset OBDII/EOBD Car Diagnostic Scan Tools for All Vehicles After 1996, 2026 Upgraded | D67: zmoon | E67: Handheld | F67: 33.202878 | G67: 44193.03 | H67: 1331 | I67: 2922 | J67: 4.5 | K67: https://amazon.com/dp/B0C2V3RYLY | L67: =IF(K67="","",HYPERLINK(K67,K67)) -> https://amazon.com/dp/B0C2V3RYLY
A68: 10 | B68: B0G6XWFLT1 | C68: OBD2 Scanner with Battery Tester - Vehicle Code Reader for Check Engine Light, Plug and Play, Car Scanner Diagnostic Tool for All OBDII Vehicles After 1996 | D68: hipepic | E68: Handheld | F68: 16.304977 | G68: 17690.9 | H68: 1085 | I68: 117 | J68: 4.6 | K68: https://amazon.com/dp/B0G6XWFLT1 | L68: =IF(K68="","",HYPERLINK(K68,K68)) -> https://amazon.com/dp/B0G6XWFLT1
A70: Handheld $75+
B71: Avg Price | C71: Avg Price MoM | D71: Avg Price YoY | E71: Quantity/Mo | F71: Qty by % | G71: Qty MoM | H71: Qty YoY | I71: Revenue/Mo | J71: Revenue by % | L71: Revenue MoM | M71: Revenue YoY
A72: innova | B72: 203.773 | C72: -0.079758146 | D72: -0.034810136 | E72: 7741 | F72: 0.40635171 | G72: 0.23283962 | H72: 0.34954672 | I72: 1577406.8 | J72: 0.4594473 | L72: 0.13451062 | M72: 0.30256882
A73: foxwell | B73: 157.31527 | C73: -0.01919401 | D73: 0.050930011 | E73: 3512 | F73: 0.18435696 | G73: -0.019542155 | H73: 0.19293478 | I73: 552491.24 | J73: 0.16092273 | L73: -0.038361073 | M73: 0.25369096
A74: ancel | B74: 124.97187 | C74: 0.060038602 | D74: 0.11636424 | E74: 1559 | F74: 0.08183727 | G74: -0.030472637 | H74: -0.57497274 | I74: 194831.14 | J74: 0.056747975 | L74: 0.02773643 | M74: -0.52551476
A75: generic | B75: 236.74507 | C75: 0.36250217 | D75: 0.31133714 | E75: 724 | F75: 0.038005249 | G75: -0.12560386 | H75: 0.74879227 | I75: 171403.43 | J75: 0.049924245 | L75: 0.19136663 | M75: 1.2932562
A76: autel | B76: 172.765 | C76: -0.17946582 | D76: -0.3041263 | E76: 940 | F76: 0.049343832 | G76: -0.088263822 | H76: -0.39354839 | I76: 162399.1 | J76: 0.047301576 | L76: -0.2518893 | M76: -0.57798627
A77: Other | B77: 169.3788 | C77: 0.038557438 | D77: 0.090993238 | E77: 4574 | F77: 0.24010499 | G77: -0.27223548 | H77: 0.077502945 | I77: 774738.64 | J77: 0.22565617 | L77: -0.24417475 | M77: 0.17554843
A78: =Summary!A8 -> Handheld $75+ | B78: =Summary!B8 -> 180.22417 | C78: =Summary!C8 -> -0.0016173916 | D78: =Summary!D8 -> 0.051403239 | E78: =SUM(E72:E77) -> 19050 | F78: =SUM(F72:F77) -> 1 | G78: =Summary!G8 -> -0.02870545 | H78: =Summary!H8 -> 0.026566794 | I78: =SUM(I72:I77) -> 3433270.4 | J78: =SUM(J72:J77) -> 1 | L78: =Summary!K8 -> -0.030276414 | M78: =Summary!L8 -> 0.079335653
A80: Handheld $75-
B81: Avg Price | C81: Avg Price MoM | D81: Avg Price YoY | E81: Quantity/Mo | F81: Qty by % | G81: Qty MoM | H81: Qty YoY | I81: Revenue/Mo | J81: Revenue by % | L81: Revenue MoM | M81: Revenue YoY
A82: ancel | B82: 32.575902 | C82: -0.012669611 | D82: -0.071099885 | E82: 38606 | F82: 0.38641163 | G82: 0.052450793 | H82: 0.075316138 | I82: 1257625.3 | J82: 0.40894671 | L82: 0.039116651 | M82: -0.0011387155
A83: foxwell | B83: 62.20204 | C83: -0.023136963 | D83: -0.011896034 | E83: 6156 | F83: 0.061616071 | G83: -0.00016241676 | H83: -0.13087675 | I83: 382915.76 | J83: 0.12451415 | L83: -0.023295622 | M83: -0.14121587
A84: motopower | B84: 23.829042 | C84: -0.13176968 | D84: 0.036477495 | E84: 12159 | F84: 0.12170075 | G84: 0.9120931 | H84: 0.26960426 | I84: 289737.32 | J84: 0.094214967 | L84: 0.6601372 | M84: 0.31591624
A85: autel | B85: 37.78 | C85: -0.042778682 | D85: 0.12199894 | E85: 5319 | F85: 0.053238447 | G85: -0.15490944 | H85: -0.032557294 | I85: 200951.82 | J85: 0.065344254 | L85: -0.1910613 | M85: 0.085469687
A86: vdiagtool | B86: 19.383197 | C86: -0.10269869 | D86: -0.14989768 | E86: 5893 | F86: 0.058983675 | G86: -0.11516517 | H86: 0.73629935 | I86: 114225.18 | J86: 0.037143029 | L86: -0.20603655 | M86: 0.47603211
A87: blcktec | B87: 60.834929 | C87: 0.053489786 | D87: 0.15075622 | E87: 911 | F87: 0.0091182977 | G87: -0.12319538 | H87: -0.51047824 | I87: 55420.62 | J87: 0.01802133 | L87: -0.076295289 | M87: -0.43667979
A88: innova | B88: 65.86098 | C88: 0.018123373 | D88: -0.0037027223 | E88: 51 | F88: 0.00051046452 | G88: -0.7627907 | H88: -0.66666667 | I88: 3358.91 | J88: 0.0010922293 | L88: -0.75849166 | M88: -0.66790091
A89: Other | B89: 25.022529 | C89: 0.025727933 | D89: 0.0099315831 | E89: 30814 | F89: 0.30842066 | G89: -0.15914424 | H89: -0.2360481 | I89: 771044.22 | J89: 0.25072333 | L89: -0.13751076 | M89: -0.22846085
A90: =Summary!A9 -> Handheld $75- | B90: =Summary!B9 -> 30.780802 | C90: =Summary!C9 -> -0.018278528 | D90: =Summary!D9 -> -0.030450769 | E90: =SUM(E82:E89) -> 99909 | F90: =SUM(F82:F89) -> 1 | G90: =Summary!G9 -> -0.0014292568 | H90: =Summary!H9 -> -0.037513367 | I90: =SUM(I82:I89) -> 3075279.1 | J90: =SUM(J82:J89) -> 1 | L90: =Summary!K9 -> -0.01968166 | M90: =Summary!L9 -> -0.066821825

Sheet Handheld $75+
A1: Handheld $75+ Monthly Summary
A3: ='Handheld Total'!A70 -> Handheld $75+
B4: Avg Price | C4: Avg Price MoM | D4: Avg Price YoY | E4: Quantity/Mo | F4: Qty by % | G4: Qty MoM | H4: Qty YoY | I4: Revenue/Mo | J4: Revenue by % | L4: Revenue MoM | M4: Revenue YoY
A5: ='Handheld Total'!A72 -> innova | B5: ='Handheld Total'!B72 -> 203.773 | C5: ='Handheld Total'!C72 -> -0.079758146 | D5: ='Handheld Total'!D72 -> -0.034810136 | E5: ='Handheld Total'!E72 -> 7741 | F5: ='Handheld Total'!F72 -> 0.40635171 | G5: ='Handheld Total'!G72 -> 0.23283962 | H5: ='Handheld Total'!H72 -> 0.34954672 | ... M5: ='Handheld Total'!M72 -> 0.30256882
A6: ='Handheld Total'!A73 -> foxwell | B6: ='Handheld Total'!B73 -> 157.31527 | C6: ='Handheld Total'!C73 -> -0.01919401 | D6: ='Handheld Total'!D73 -> 0.050930011 | E6: ='Handheld Total'!E73 -> 3512 | F6: ='Handheld Total'!F73 -> 0.18435696 | G6: ='Handheld Total'!G73 -> -0.019542155 | H6: ='Handheld Total'!H73 -> 0.19293478 | ... M6: ='Handheld Total'!M73 -> 0.25369096
A7: ='Handheld Total'!A74 -> ancel | B7: ='Handheld Total'!B74 -> 124.97187 | C7: ='Handheld Total'!C74 -> 0.060038602 | D7: ='Handheld Total'!D74 -> 0.11636424 | E7: ='Handheld Total'!E74 -> 1559 | F7: ='Handheld Total'!F74 -> 0.08183727 | G7: ='Handheld Total'!G74 -> -0.030472637 | H7: ='Handheld Total'!H74 -> -0.57497274 | ... M7: ='Handheld Total'!M74 -> -0.52551476
A8: ='Handheld Total'!A75 -> generic | B8: ='Handheld Total'!B75 -> 236.74507 | C8: ='Handheld Total'!C75 -> 0.36250217 | D8: ='Handheld Total'!D75 -> 0.31133714 | E8: ='Handheld Total'!E75 -> 724 | F8: ='Handheld Total'!F75 -> 0.038005249 | G8: ='Handheld Total'!G75 -> -0.12560386 | H8: ='Handheld Total'!H75 -> 0.74879227 | ... M8: ='Handheld Total'!M75 -> 1.2932562
A9: ='Handheld Total'!A76 -> autel | B9: ='Handheld Total'!B76 -> 172.765 | C9: ='Handheld Total'!C76 -> -0.17946582 | D9: ='Handheld Total'!D76 -> -0.3041263 | E9: ='Handheld Total'!E76 -> 940 | F9: ='Handheld Total'!F76 -> 0.049343832 | G9: ='Handheld Total'!G76 -> -0.088263822 | H9: ='Handheld Total'!H76 -> -0.39354839 | ... M9: ='Handheld Total'!M76 -> -0.57798627
A10: ='Handheld Total'!A77 -> Other | B10: ='Handheld Total'!B77 -> 169.3788 | C10: ='Handheld Total'!C77 -> 0.038557438 | D10: ='Handheld Total'!D77 -> 0.090993238 | E10: ='Handheld Total'!E77 -> 4574 | F10: ='Handheld Total'!F77 -> 0.24010499 | G10: ='Handheld Total'!G77 -> -0.27223548 | H10: ='Handheld Total'!H77 -> 0.077502945 | ... M10: ='Handheld Total'!M77 -> 0.17554843
A11: ='Handheld Total'!A78 -> Handheld $75+ | B11: ='Handheld Total'!B78 -> 180.22417 | C11: ='Handheld Total'!C78 -> -0.0016173916 | D11: ='Handheld Total'!D78 -> 0.051403239 | E11: ='Handheld Total'!E78 -> 19050 | F11: ='Handheld Total'!F78 -> 1 | G11: ='Handheld Total'!G78 -> -0.02870545 | H11: ='Handheld Total'!H78 -> 0.026566794 | ... M11: ='Handheld Total'!M78 -> 0.079335653
A43: Rank By Monthly Revenue - Jul '26 ONLY
A44: Ranking | B44: ASIN | C44: Product Name | D44: Brand | E44: Type | F44: Price | G44: Est. Monthly Retail Rev | H44: Est. Monthly Units Sold | I44: # of Reviews | J44: Avg. Rating | K44: Column2 | L44: Link
A45: 1 | B45: B07Z481NJM | C45: Innova 5610 OBD2 Bidirectional Scan Tool - Understand Your Vehicle, Pinpoint What's Wrong, and Complete Your Repairs with Less Headache, Updates Included, US-Based Technical Support | D45: innova | E45: Handheld | F45: 304.05607 | G45: 1174264.6 | H45: 3862 | I45: 3791 | J45: 4.4 | K45: https://amazon.com/dp/B07Z481NJM | L45: =IF(K45="","",HYPERLINK(K45,K45)) -> https://amazon.com/dp/B07Z481NJM
A46: 2 | B46: B07Z46L5FG | C46: Innova 5210 OBD2 Scanner & Engine Code Reader, Battery Tester, Live Data, Oil Reset, Car Diagnostic Tool for Most Vehicles, Bluetooth Compatible with America's Top Car Repair App | D46: innova | E46: Handheld | F46: 86.696119 | G46: 249077.95 | H46: 2873 | I46: 4155 | J46: 4.5 | K46: https://amazon.com/dp/B07Z46L5FG | L46: =IF(K46="","",HYPERLINK(K46,K46)) -> https://amazon.com/dp/B07Z46L5FG
A47: 3 | B47: B019QCG5RE | C47: FOXWELL NT510 Elite Scan Tool fit for BMW Scanner Full Diagnostic Tool OBD2 Scanner, All System Bi-Directional Control Code Reader with All Reset Services, Battery Registration Tool fit for BMW Mini | D47: foxwell | E47: Handheld | F47: 177.72473 | G47: 125118.21 | H47: 704 | I47: 3174 | J47: 4.3 | K47: https://amazon.com/dp/B019QCG5RE | L47: =IF(K47="","",HYPERLINK(K47,K47)) -> https://amazon.com/dp/B019QCG5RE
A48: 4 | B48: B09YRDGY3Z | C48: Thinkdiag2 All System Bidirectional OBD2 Diagnostic Scanner for iOS & Android, THINKCAR Bluetooth Scan Tool with CAN-FD Protocol, 15+ Reset Functions, ECU Code, Active Test, AutoVIN, 1 Year Update | D48: thinkcar | E48: Handheld | F48: 159.9019 | G48: 90664.38 | H48: 567 | I48: 1468 | J48: 4.2 | K48: https://amazon.com/dp/B09YRDGY3Z | L48: =IF(K48="","",HYPERLINK(K48,K48)) -> https://amazon.com/dp/B09YRDGY3Z
A49: 5 | B49: B07ZL7CLYR | C49: Innova 5410 All-System OBD2 Scanner Diagnostic Tool for Cars & Trucks – Automotive Scan Tools for Engine, ABS, SRS & Transmission, Bluetooth Compatible with America's Top Car Repair App | D49: innova | E49: Handheld | F49: 154.21691 | G49: 87286.77 | H49: 566 | I49: 730 | J49: 4.4 | K49: https://amazon.com/dp/B07ZL7CLYR | L49: =IF(K49="","",HYPERLINK(K49,K49)) -> https://amazon.com/dp/B07ZL7CLYR
A50: 6 | B50: B08JGK8PPM | C50: FOXWELL NT301 Plus 2-in-1 OBD2 Scanner & 12V Car Battery Tester | D50: foxwell | E50: Handheld | F50: 90.973941 | G50: 79875.12 | H50: 878 | I50: 2715 | J50: 4.5 | K50: https://amazon.com/dp/B08JGK8PPM | L50: =IF(K50="","",HYPERLINK(K50,K50)) -> https://amazon.com/dp/B08JGK8PPM
A51: 7 | B51: B08B5RMFBG | C51: FOXWELL NT510 Elite fit for Honda Acura OBD2 Scanner, Bidirectional Full System Engine ABS TCM SRS Diagnostic Scan Tool, All Reset Crankshaft Relearn Oil EPB TPS ABS Bleeding, Code Reader, Free Update | D51: foxwell | E51: Handheld | F51: 189.7644 | G51: 72490 | H51: 382 | I51: 463 | J51: 4.2 | K51: https://amazon.com/dp/B08B5RMFBG | L51: =IF(K51="","",HYPERLINK(K51,K51)) -> https://amazon.com/dp/B08B5RMFBG
A52: 8 | B52: B07CSMJJK9 | C52: FOXWELL NT630 Plus OBD2 Scanner with ABS and SRS, ABS Auto Bleed, 4 Resets | D52: foxwell | E52: Handheld | F52: 149.97574 | G52: 66889.18 | H52: 446 | I52: 3962 | J52: 4.2 | K52: https://amazon.com/dp/B07CSMJJK9 | L52: =IF(K52="","",HYPERLINK(K52,K52)) -> https://amazon.com/dp/B07CSMJJK9
A53: 9 | B53: B0BPYTTTMQ | C53: NEXIQ Tech 121054 USB-Link 3 - Wired Vehicle Diagnostic Scanner, Vehicle Powered, Blue, Compatible with Windows 10, Windows 11, iOS, Android | D53: generic | E53: Handheld | F53: 747.59512 | G53: 61302.8 | H53: 82 | I53: 16 | J53: 4.8 | K53: https://amazon.com/dp/B0BPYTTTMQ | L53: =IF(K53="","",HYPERLINK(K53,K53)) -> https://amazon.com/dp/B0BPYTTTMQ
A54: 10 | B54: B0DDQ6MX9M | C54: FOXWELL NT630 Pro 2-in-1 OBD2 Scanner, ABS/SRS & Battery Tester, 5 Resets | D54: foxwell | E54: Handheld | F54: 193.3157 | G54: 52581.87 | H54: 272 | I54: 150 | J54: 4.4 | K54: https://amazon.com/dp/B0DDQ6MX9M | L54: =IF(K54="","",HYPERLINK(K54,K54)) -> https://amazon.com/dp/B0DDQ6MX9M
A56: Rank By Monthly Units - Jul '26 ONLY
A57: Ranking | B57: ASIN | C57: Product Name | D57: Brand | E57: Type | F57: Price | G57: Est. Monthly Retail Rev | H57: Est. Monthly Units Sold | I57: # of Reviews | J57: Avg. Rating | K57: Column2 | L57: Link
A58: 1 | B58: B07Z481NJM | C58: Innova 5610 OBD2 Bidirectional Scan Tool - Understand Your Vehicle, Pinpoint What's Wrong, and Complete Your Repairs with Less Headache, Updates Included, US-Based Technical Support | D58: innova | E58: Handheld | F58: 304.05607 | G58: 1174264.6 | H58: 3862 | I58: 3791 | J58: 4.4 | K58: https://amazon.com/dp/B07Z481NJM | L58: =IF(K58="","",HYPERLINK(K58,K58)) -> https://amazon.com/dp/B07Z481NJM
A59: 2 | B59: B07Z46L5FG | C59: Innova 5210 OBD2 Scanner & Engine Code Reader, Battery Tester, Live Data, Oil Reset, Car Diagnostic Tool for Most Vehicles, Bluetooth Compatible with America's Top Car Repair App | D59: innova | E59: Handheld | F59: 86.696119 | G59: 249077.95 | H59: 2873 | I59: 4155 | J59: 4.5 | K59: https://amazon.com/dp/B07Z46L5FG | L59: =IF(K59="","",HYPERLINK(K59,K59)) -> https://amazon.com/dp/B07Z46L5FG
A60: 3 | B60: B08JGK8PPM | C60: FOXWELL NT301 Plus 2-in-1 OBD2 Scanner & 12V Car Battery Tester | D60: foxwell | E60: Handheld | F60: 90.973941 | G60: 79875.12 | H60: 878 | I60: 2715 | J60: 4.5 | K60: https://amazon.com/dp/B08JGK8PPM | L60: =IF(K60="","",HYPERLINK(K60,K60)) -> https://amazon.com/dp/B08JGK8PPM
A61: 4 | B61: B019QCG5RE | C61: FOXWELL NT510 Elite Scan Tool fit for BMW Scanner Full Diagnostic Tool OBD2 Scanner, All System Bi-Directional Control Code Reader with All Reset Services, Battery Registration Tool fit for BMW Mini | D61: foxwell | E61: Handheld | F61: 177.72473 | G61: 125118.21 | H61: 704 | I61: 3174 | J61: 4.3 | K61: https://amazon.com/dp/B019QCG5RE | L61: =IF(K61="","",HYPERLINK(K61,K61)) -> https://amazon.com/dp/B019QCG5RE
A62: 5 | B62: B09YRDGY3Z | C62: Thinkdiag2 All System Bidirectional OBD2 Diagnostic Scanner for iOS & Android, THINKCAR Bluetooth Scan Tool with CAN-FD Protocol, 15+ Reset Functions, ECU Code, Active Test, AutoVIN, 1 Year Update | D62: thinkcar | E62: Handheld | F62: 159.9019 | G62: 90664.38 | H62: 567 | I62: 1468 | J62: 4.2 | K62: https://amazon.com/dp/B09YRDGY3Z | L62: =IF(K62="","",HYPERLINK(K62,K62)) -> https://amazon.com/dp/B09YRDGY3Z
A63: 6 | B63: B07ZL7CLYR | C63: Innova 5410 All-System OBD2 Scanner Diagnostic Tool for Cars & Trucks – Automotive Scan Tools for Engine, ABS, SRS & Transmission, Bluetooth Compatible with America's Top Car Repair App | D63: innova | E63: Handheld | F63: 154.21691 | G63: 87286.77 | H63: 566 | I63: 730 | J63: 4.4 | K63: https://amazon.com/dp/B07ZL7CLYR | L63: =IF(K63="","",HYPERLINK(K63,K63)) -> https://amazon.com/dp/B07ZL7CLYR
A64: 7 | B64: B0FCXMGGPN | C64: OBDMATE OBD2 Scanner with ABS SRS Transmission, Reset Fault Lights | Check Engine Code Reader with Full OBDII Functions | DLC Pin Test | Battery Voltage Check, Car Diagnostic Tool | D64: obdmate | E64: Handheld | F64: 108.69069 | G64: 52280.22 | H64: 481 | I64: 209 | J64: 4.3 | K64: https://amazon.com/dp/B0FCXMGGPN | L64: =IF(K64="","",HYPERLINK(K64,K64)) -> https://amazon.com/dp/B0FCXMGGPN
A65: 8 | B65: B07CSMJJK9 | C65: FOXWELL NT630 Plus OBD2 Scanner with ABS and SRS, ABS Auto Bleed, 4 Resets | D65: foxwell | E65: Handheld | F65: 149.97574 | G65: 66889.18 | H65: 446 | I65: 3962 | J65: 4.2 | K65: https://amazon.com/dp/B07CSMJJK9 | L65: =IF(K65="","",HYPERLINK(K65,K65)) -> https://amazon.com/dp/B07CSMJJK9
A66: 9 | B66: B08B5RMFBG | C66: FOXWELL NT510 Elite fit for Honda Acura OBD2 Scanner, Bidirectional Full System Engine ABS TCM SRS Diagnostic Scan Tool, All Reset Crankshaft Relearn Oil EPB TPS ABS Bleeding, Code Reader, Free Update | D66: foxwell | E66: Handheld | F66: 189.7644 | G66: 72490 | H66: 382 | I66: 463 | J66: 4.2 | K66: https://amazon.com/dp/B08B5RMFBG | L66: =IF(K66="","",HYPERLINK(K66,K66)) -> https://amazon.com/dp/B08B5RMFBG
A67: 10 | B67: B014CT4M3K | C67: FOXWELL NT510 Elite fit for GM OBD2 Scanner, Bi-Directional All System Engine ABS SRS Diagnostic Scan Tool Code Reader for Chevrolet Cadillac GMC, All Reset Oil EPB TPS ABS Bleeding Crankshaft Relearn | D67: foxwell | E67: Handheld | F67: 181.63035 | G67: 51946.28 | H67: 286 | I67: 584 | J67: 4.1 | K67: https://amazon.com/dp/B014CT4M3K | L67: =IF(K67="","",HYPERLINK(K67,K67)) -> https://amazon.com/dp/B014CT4M3K

Sheet Handheld $75-
A1: Handheld $75- Monthly Summary
A3: ='Handheld Total'!A80 -> Handheld $75-
B4: Avg Price | C4: Avg Price MoM | D4: Avg Price YoY | E4: Quantity/Mo | F4: Qty by % | G4: Qty MoM | H4: Qty YoY | I4: Revenue/Mo | J4: Revenue by % | L4: Revenue MoM | M4: Revenue YoY
A5: ='Handheld Total'!A82 -> ancel | B5: ='Handheld Total'!B82 -> 32.575902 | C5: ='Handheld Total'!C82 -> -0.012669611 | D5: ='Handheld Total'!D82 -> -0.071099885 | E5: ='Handheld Total'!E82 -> 38606 | F5: ='Handheld Total'!F82 -> 0.38641163 | G5: ='Handheld Total'!G82 -> 0.052450793 | H5: ='Handheld Total'!H82 -> 0.075316138 | ... M5: ='Handheld Total'!M82 -> -0.0011387155
A6: ='Handheld Total'!A83 -> foxwell | B6: ='Handheld Total'!B83 -> 62.20204 | C6: ='Handheld Total'!C83 -> -0.023136963 | D6: ='Handheld Total'!D83 -> -0.011896034 | E6: ='Handheld Total'!E83 -> 6156 | F6: ='Handheld Total'!F83 -> 0.061616071 | G6: ='Handheld Total'!G83 -> -0.00016241676 | H6: ='Handheld Total'!H83 -> -0.13087675 | ... M6: ='Handheld Total'!M83 -> -0.14121587
A7: ='Handheld Total'!A84 -> motopower | B7: ='Handheld Total'!B84 -> 23.829042 | C7: ='Handheld Total'!C84 -> -0.13176968 | D7: ='Handheld Total'!D84 -> 0.036477495 | E7: ='Handheld Total'!E84 -> 12159 | F7: ='Handheld Total'!F84 -> 0.12170075 | G7: ='Handheld Total'!G84 -> 0.9120931 | H7: ='Handheld Total'!H84 -> 0.26960426 | ... M7: ='Handheld Total'!M84 -> 0.31591624
A8: ='Handheld Total'!A85 -> autel | B8: ='Handheld Total'!B85 -> 37.78 | C8: ='Handheld Total'!C85 -> -0.042778682 | D8: ='Handheld Total'!D85 -> 0.12199894 | E8: ='Handheld Total'!E85 -> 5319 | F8: ='Handheld Total'!F85 -> 0.053238447 | G8: ='Handheld Total'!G85 -> -0.15490944 | H8: ='Handheld Total'!H85 -> -0.032557294 | ... M8: ='Handheld Total'!M85 -> 0.085469687
A9: ='Handheld Total'!A86 -> vdiagtool | B9: ='Handheld Total'!B86 -> 19.383197 | C9: ='Handheld Total'!C86 -> -0.10269869 | D9: ='Handheld Total'!D86 -> -0.14989768 | E9: ='Handheld Total'!E86 -> 5893 | F9: ='Handheld Total'!F86 -> 0.058983675 | G9: ='Handheld Total'!G86 -> -0.11516517 | H9: ='Handheld Total'!H86 -> 0.73629935 | ... M9: ='Handheld Total'!M86 -> 0.47603211
A10: ='Handheld Total'!A87 -> blcktec | B10: ='Handheld Total'!B87 -> 60.834929 | C10: ='Handheld Total'!C87 -> 0.053489786 | D10: ='Handheld Total'!D87 -> 0.15075622 | E10: ='Handheld Total'!E87 -> 911 | F10: ='Handheld Total'!F87 -> 0.0091182977 | G10: ='Handheld Total'!G87 -> -0.12319538 | H10: ='Handheld Total'!H87 -> -0.51047824 | ... M10: ='Handheld Total'!M87 -> -0.43667979
A11: ='Handheld Total'!A88 -> innova | B11: ='Handheld Total'!B88 -> 65.86098 | C11: ='Handheld Total'!C88 -> 0.018123373 | D11: ='Handheld Total'!D88 -> -0.0037027223 | E11: ='Handheld Total'!E88 -> 51 | F11: ='Handheld Total'!F88 -> 0.00051046452 | G11: ='Handheld Total'!G88 -> -0.7627907 | H11: ='Handheld Total'!H88 -> -0.66666667 | ... M11: ='Handheld Total'!M88 -> -0.66790091
A12: ='Handheld Total'!A89 -> Other | B12: ='Handheld Total'!B89 -> 25.022529 | C12: ='Handheld Total'!C89 -> 0.025727933 | D12: ='Handheld Total'!D89 -> 0.0099315831 | E12: ='Handheld Total'!E89 -> 30814 | F12: ='Handheld Total'!F89 -> 0.30842066 | G12: ='Handheld Total'!G89 -> -0.15914424 | H12: ='Handheld Total'!H89 -> -0.2360481 | ... M12: ='Handheld Total'!M89 -> -0.22846085
A13: ='Handheld Total'!A90 -> Handheld $75- | B13: ='Handheld Total'!B90 -> 30.780802 | C13: ='Handheld Total'!C90 -> -0.018278528 | D13: ='Handheld Total'!D90 -> -0.030450769 | E13: ='Handheld Total'!E90 -> 99909 | F13: ='Handheld Total'!F90 -> 1 | G13: ='Handheld Total'!G90 -> -0.0014292568 | H13: ='Handheld Total'!H90 -> -0.037513367 | ... M13: ='Handheld Total'!M90 -> -0.066821825
A45: Rank By Monthly Revenue - Jul '26 ONLY
A46: Ranking | B46: ASIN | C46: Product Name | D46: Brand | E46: Type | F46: Price | G46: Est. Monthly Retail Rev | H46: Est. Monthly Units Sold | I46: # of Reviews | J46: Avg. Rating | K46: Column2 | L46: Link
A47: 1 | B47: B01G5EA74I | C47: ANCEL AD310 Classic Enhanced Universal OBD II Scanner Car Engine Fault Code Reader CAN Diagnostic Scan Tool, Read and Clear Error Codes for 1996 or Newer OBD2 Protocol Vehicle (Black) | D47: ancel | E47: Handheld | F47: 27.817391 | G47: 815550.26 | H47: 29318 | I47: 65760 | J47: 4.6 | K47: https://amazon.com/dp/B01G5EA74I | L47: =IF(K47="","",HYPERLINK(K47,K47)) -> https://amazon.com/dp/B01G5EA74I
A48: 2 | B48: B00UJV3E12 | C48: FOXWELL NT301 OBD2 Scanner Live Data Professional Mechanic OBDII Diagnostic Code Reader Tool for Check Engine Light | D48: foxwell | E48: Handheld | F48: 64.043987 | G48: 358198.02 | H48: 5593 | I48: 30049 | J48: 4.5 | K48: https://amazon.com/dp/B00UJV3E12 | L48: =IF(K48="","",HYPERLINK(K48,K48)) -> https://amazon.com/dp/B00UJV3E12
A49: 3 | B49: B07Z3HB7DR | C49: MOTOPOWER MP69033 Car OBD2 Scanner Code Reader Engine Fault Scanner CAN Diagnostic Scan Tool for All OBD II Protocol Cars Since 1996, Yellow | D49: motopower | E49: Handheld | F49: 23.211108 | G49: 259500.19 | H49: 11180 | I49: 51762 | J49: 4.6 | K49: https://amazon.com/dp/B07Z3HB7DR | L49: =IF(K49="","",HYPERLINK(K49,K49)) -> https://amazon.com/dp/B07Z3HB7DR
A50: 4 | B50: B071FSNL73 | C50: ANCEL AD410 Enhanced OBD2 Scanner, Vehicle Code Reader for Check Engine Light, Automotive OBD II Scanner Fault Diagnosis, OBDII Scan Tool for All OBDII Cars 1996+, Black/Yellow | D50: ancel | E50: Handheld | F50: 41.468081 | G50: 234211.72 | H50: 5648 | I50: 15482 | J50: 4.5 | K50: https://amazon.com/dp/B071FSNL73 | L50: =IF(K50="","",HYPERLINK(K50,K50)) -> https://amazon.com/dp/B071FSNL73
A51: 5 | B51: B0BY1TS725 | C51: VDIAGTOOL VD10 OBD2 Scanner Code Reader Car Diagnostic Tool Engine Fault Code Reader for Turn Off CEL with Freeze Frame/I/M Readiness for All OBDII Protocol Cars, OBD2 Scanner Diagnostic Tool | D51: vdiagtool | E51: Handheld | F51: 18.105488 | G51: 98186.06 | H51: 5423 | I51: 3034 | J51: 4.6 | K51: https://amazon.com/dp/B0BY1TS725 | L51: =IF(K51="","",HYPERLINK(K51,K51)) -> https://amazon.com/dp/B0BY1TS725
A52: 6 | B52: B007XE8C74 | C52: Autel AL319 Professional OBD2 Scanner, Enhanced Check Engine Code Reader | D52: autel | E52: Handheld | F52: 33.609584 | G52: 77503.7 | H52: 2306 | I52: 26046 | J52: 4.6 | K52: https://amazon.com/dp/B007XE8C74 | L52: =IF(K52="","",HYPERLINK(K52,K52)) -> https://amazon.com/dp/B007XE8C74
A53: 7 | B53: B0BX3K8VGJ | C53: ANCEL AD410 PRO OBD2 Scanner and Battery Tester, 2-in-1 Car Diagnostic Tool, Check Engine Light, EVAP Test, Live Data, 12V Battery Analyzer with Cranking & Charging System Test for Car Motorcycle | D53: ancel | E53: Handheld | F53: 62.168795 | G53: 66023.26 | H53: 1062 | I53: 4204 | J53: 4.6 | K53: https://amazon.com/dp/B0BX3K8VGJ | L53: =IF(K53="","",HYPERLINK(K53,K53)) -> https://amazon.com/dp/B0BX3K8VGJ
A54: 8 | B54: B07BS7PDC2 | C54: ANCEL VD500 OBD2 Scanner Diagnostic Tool for Volkswagen VW Audi Skoda Seat Full Systems Check Engine Light EPB ABS SRS Code Reader Oil Throttle Position Adaption Brake Pad Reset | D54: ancel | E54: Handheld | F54: 62.905059 | G54: 58942.04 | H54: 937 | I54: 6433 | J54: 4.5 | K54: https://amazon.com/dp/B07BS7PDC2 | L54: =IF(K54="","",HYPERLINK(K54,K54)) -> https://amazon.com/dp/B07BS7PDC2
A55: 9 | B55: B0C2V3RYLY | C55: ZMOON ZM201 Professional OBD2 Scanner Diagnostic Tool, Enhanced Check Engine Code Reader with Reset OBDII/EOBD Car Diagnostic Scan Tools for All Vehicles After 1996, 2026 Upgraded | D55: zmoon | E55: Handheld | F55: 33.202878 | G55: 44193.03 | H55: 1331 | I55: 2922 | J55: 4.5 | K55: https://amazon.com/dp/B0C2V3RYLY | L55: =IF(K55="","",HYPERLINK(K55,K55)) -> https://amazon.com/dp/B0C2V3RYLY
A56: 10 | B56: B0C8XSKFX8 | C56: BLCKTEC 440 Bluetooth OBD2 Scanner Diagnostic Tool - Car Code Reader and Scanner for Car - Comes with Live Data - Battery/Charging System Test - Works for All OBD Compliant Cars 1996 & Newer | D56: blcktec | E56: Handheld | F56: 71.96301 | G56: 43033.88 | H56: 598 | I56: 1152 | J56: 4.5 | K56: https://amazon.com/dp/B0C8XSKFX8 | L56: =IF(K56="","",HYPERLINK(K56,K56)) -> https://amazon.com/dp/B0C8XSKFX8
A58: Rank By Monthly Units - Jul '26 ONLY
A59: Ranking | B59: ASIN | C59: Product Name | D59: Brand | E59: Type | F59: Price | G59: Est. Monthly Retail Rev | H59: Est. Monthly Units Sold | I59: # of Reviews | J59: Avg. Rating | K59: Column2 | L59: Link
A60: 1 | B60: B01G5EA74I | C60: ANCEL AD310 Classic Enhanced Universal OBD II Scanner Car Engine Fault Code Reader CAN Diagnostic Scan Tool, Read and Clear Error Codes for 1996 or Newer OBD2 Protocol Vehicle (Black) | D60: ancel | E60: Handheld | F60: 27.817391 | G60: 815550.26 | H60: 29318 | I60: 65760 | J60: 4.6 | K60: https://amazon.com/dp/B01G5EA74I | L60: =IF(K60="","",HYPERLINK(K60,K60)) -> https://amazon.com/dp/B01G5EA74I
A61: 2 | B61: B07Z3HB7DR | C61: MOTOPOWER MP69033 Car OBD2 Scanner Code Reader Engine Fault Scanner CAN Diagnostic Scan Tool for All OBD II Protocol Cars Since 1996, Yellow | D61: motopower | E61: Handheld | F61: 23.211108 | G61: 259500.19 | H61: 11180 | I61: 51762 | J61: 4.6 | K61: https://amazon.com/dp/B07Z3HB7DR | L61: =IF(K61="","",HYPERLINK(K61,K61)) -> https://amazon.com/dp/B07Z3HB7DR
A62: 3 | B62: B071FSNL73 | C62: ANCEL AD410 Enhanced OBD2 Scanner, Vehicle Code Reader for Check Engine Light, Automotive OBD II Scanner Fault Diagnosis, OBDII Scan Tool for All OBDII Cars 1996+, Black/Yellow | D62: ancel | E62: Handheld | F62: 41.468081 | G62: 234211.72 | H62: 5648 | I62: 15482 | J62: 4.5 | K62: https://amazon.com/dp/B071FSNL73 | L62: =IF(K62="","",HYPERLINK(K62,K62)) -> https://amazon.com/dp/B071FSNL73
A63: 4 | B63: B00UJV3E12 | C63: FOXWELL NT301 OBD2 Scanner Live Data Professional Mechanic OBDII Diagnostic Code Reader Tool for Check Engine Light | D63: foxwell | E63: Handheld | F63: 64.043987 | G63: 358198.02 | H63: 5593 | I63: 30049 | J63: 4.5 | K63: https://amazon.com/dp/B00UJV3E12 | L63: =IF(K63="","",HYPERLINK(K63,K63)) -> https://amazon.com/dp/B00UJV3E12
A64: 5 | B64: B0BY1TS725 | C64: VDIAGTOOL VD10 OBD2 Scanner Code Reader Car Diagnostic Tool Engine Fault Code Reader for Turn Off CEL with Freeze Frame/I/M Readiness for All OBDII Protocol Cars, OBD2 Scanner Diagnostic Tool | D64: vdiagtool | E64: Handheld | F64: 18.105488 | G64: 98186.06 | H64: 5423 | I64: 3034 | J64: 4.6 | K64: https://amazon.com/dp/B0BY1TS725 | L64: =IF(K64="","",HYPERLINK(K64,K64)) -> https://amazon.com/dp/B0BY1TS725
A65: 6 | B65: B007XE8C74 | C65: Autel AL319 Professional OBD2 Scanner, Enhanced Check Engine Code Reader | D65: autel | E65: Handheld | F65: 33.609584 | G65: 77503.7 | H65: 2306 | I65: 26046 | J65: 4.6 | K65: https://amazon.com/dp/B007XE8C74 | L65: =IF(K65="","",HYPERLINK(K65,K65)) -> https://amazon.com/dp/B007XE8C74
A66: 7 | B66: B0C2V3RYLY | C66: ZMOON ZM201 Professional OBD2 Scanner Diagnostic Tool, Enhanced Check Engine Code Reader with Reset OBDII/EOBD Car Diagnostic Scan Tools for All Vehicles After 1996, 2026 Upgraded | D66: zmoon | E66: Handheld | F66: 33.202878 | G66: 44193.03 | H66: 1331 | I66: 2922 | J66: 4.5 | K66: https://amazon.com/dp/B0C2V3RYLY | L66: =IF(K66="","",HYPERLINK(K66,K66)) -> https://amazon.com/dp/B0C2V3RYLY
A67: 8 | B67: B0G6XWFLT1 | C67: OBD2 Scanner with Battery Tester - Vehicle Code Reader for Check Engine Light, Plug and Play, Car Scanner Diagnostic Tool for All OBDII Vehicles After 1996 | D67: hipepic | E67: Handheld | F67: 16.304977 | G67: 17690.9 | H67: 1085 | I67: 117 | J67: 4.6 | K67: https://amazon.com/dp/B0G6XWFLT1 | L67: =IF(K67="","",HYPERLINK(K67,K67)) -> https://amazon.com/dp/B0G6XWFLT1
A68: 9 | B68: B0BX3K8VGJ | C68: ANCEL AD410 PRO OBD2 Scanner and Battery Tester, 2-in-1 Car Diagnostic Tool, Check Engine Light, EVAP Test, Live Data, 12V Battery Analyzer with Cranking & Charging System Test for Car Motorcycle | D68: ancel | E68: Handheld | F68: 62.168795 | G68: 66023.26 | H68: 1062 | I68: 4204 | J68: 4.6 | K68: https://amazon.com/dp/B0BX3K8VGJ | L68: =IF(K68="","",HYPERLINK(K68,K68)) -> https://amazon.com/dp/B0BX3K8VGJ
A69: 10 | B69: B07BS7PDC2 | C69: ANCEL VD500 OBD2 Scanner Diagnostic Tool for Volkswagen VW Audi Skoda Seat Full Systems Check Engine Light EPB ABS SRS Code Reader Oil Throttle Position Adaption Brake Pad Reset | D69: ancel | E69: Handheld | F69: 62.905059 | G69: 58942.04 | H69: 937 | I69: 6433 | J69: 4.5 | K69: https://amazon.com/dp/B07BS7PDC2 | L69: =IF(K69="","",HYPERLINK(K69,K69)) -> https://amazon.com/dp/B07BS7PDC2

Sheet Dongle
A1: Dongle Monthly Summary
A3: Dongle Overall
B4: Avg Price | C4: Avg Price MoM | D4: Avg Price YoY | E4: Quantity/Mo | F4: Qty by % | G4: Qty MoM | H4: Qty YoY | I4: Revenue/Mo | J4: Revenue by % | L4: Revenue MoM | M4: Revenue YoY
A5: bluedriver | B5: 100.11758 | C5: 0.0015016092 | D5: 0.079219996 | E5: 11010 | F5: 0.1564076 | G5: -0.18335559 | H5: -0.09075894 | I5: 1102294.6 | J5: 0.19663884 | L5: -0.1821293 | M5: -0.018728867
A6: obdlink | B6: 106.56601 | C6: -0.092693368 | D6: -0.085759579 | E6: 6943 | F6: 0.098631966 | G6: -0.29833249 | H6: -0.21494799 | I6: 739887.84 | J6: 0.13198894 | L6: -0.36337242 | M6: -0.28227372
A7: generic | B7: 316.64251 | C7: -0.20331498 | D7: 0.30797625 | E7: 1437 | F7: 0.020413962 | G7: 0.13417522 | H7: 10.314961 | I7: 455015.29 | J7: 0.081170391 | L7: -0.096419593 | M7: 13.7997
A8: obdeleven | B8: 149.39941 | C8: -0.070796792 | D8: 0.19953891 | E8: 2184 | F8: 0.031025812 | G8: 0.19934102 | H8: -0.0072727273 | I8: 326288.31 | J8: 0.058206724 | L8: 0.11443152 | M8: 0.19081499
A9: veepeak | B9: 33.005477 | C9: 0.02510007 | D9: 0.052713046 | E9: 9806 | F9: 0.13930362 | G9: 0.18601838 | H9: 0.30537806 | I9: 323651.71 | J9: 0.05773638 | L9: 0.21578753 | M9: 0.37418852
A10: blcktec | B10: 61.470882 | C10: -0.014995264 | D10: 0.011295797 | E10: 578 | F10: 0.0082110437 | G10: -0.11349693 | H10: -0.31353919 | I10: 35530.17 | J10: 0.0063382437 | L10: -0.12679028 | M10: -0.30578507
A11: innova | B11: 88.915444 | C11: 0.0043215414 | D11: -0.008060368 | E11: 248 | F11: 0.0035230776 | G11: 0.037656904 | H11: -0.57093426 | I11: 22051.03 | J11: 0.0039336936 | L11: 0.042141181 | M11: -0.57439268
A12: Other | B12: 68.111183 | C12: -0.057247433 | D12: -0.049337526 | E12: 38187 | F12: 0.54248292 | G12: 0.0067756393 | H12: 0.046505892 | I12: 2600961.8 | J12: 0.46398679 | L12: -0.050859682 | M12: -0.00512612
A13: Total Dongle | B13: 79.634064 | C13: -0.081148913 | D13: 0.01093587 | E13: 70393 | F13: 1 | G13: -0.042975229 | H13: 0.024613548 | I13: 5605680.7 | J13: 1 | L13: -0.12063675 | M13: 0.035818589
A45: Rank By Monthly Revenue - Jul '26 ONLY
A46: Ranking | B46: ASIN | C46: Product Name | D46: Brand | E46: Type | F46: Price | G46: Est. Monthly Retail Rev | H46: Est. Monthly Units Sold | I46: # of Reviews | J46: Avg. Rating | K46: Column2 | L46: Link
A47: 1 | B47: B0GL9RL3XS | C47: BlueDriver OBD2 Scanner Bluetooth, No Subscription, ABS SRS TPMS | D47: bluedriver | E47: Dongle | F47: 95.184528 | G47: 926145.46 | H47: 9730 | I47: 63029 | J47: 4.5 | K47: https://amazon.com/dp/B0GL9RL3XS | L47: =IF(K47="","",HYPERLINK(K47,K47)) -> https://amazon.com/dp/B0GL9RL3XS
A48: 2 | B48: B07JFRFJG6 | C48: OBDLink MX+ OBD2 Bluetooth Scanner for iPhone, Android, and Windows | D48: obdlink | E48: Dongle | F48: 139.92839 | G48: 419085.53 | H48: 2995 | I48: 15453 | J48: 4.6 | K48: https://amazon.com/dp/B07JFRFJG6 | L48: =IF(K48="","",HYPERLINK(K48,K48)) -> https://amazon.com/dp/B07JFRFJG6
A49: 3 | B49: B08NFLL3NT | C49: OBDLink CX Bimmercode Bluetooth 5.1 OBD2 Adapter for BMW/Mini, Works with iPhone/iOS & Android, Car Coding, OBD II Diagnostic Scanner | D49: obdlink | E49: Dongle | F49: 79.945739 | G49: 274133.94 | H49: 3429 | I49: 4614 | J49: 4.6 | K49: https://amazon.com/dp/B08NFLL3NT | L49: =IF(K49="","",HYPERLINK(K49,K49)) -> https://amazon.com/dp/B08NFLL3NT
A50: 4 | B50: B0FZ26RBDC | C50: Hinson HPT Bundle of MPVI4 Diagnostic Code Reader and Hinson Credit Notice | D50: generic | E50: Dongle | F50: 399.81909 | G50: 233894.17 | H50: 585 | I50: 203 | J50: 4.8 | K50: https://amazon.com/dp/B0FZ26RBDC | L50: =IF(K50="","",HYPERLINK(K50,K50)) -> https://amazon.com/dp/B0FZ26RBDC
A51: 5 | B51: B09KT9XNML | C51: XTOOL A30M V2.0 OBD2 Scanner Diagnostic Tool, 26 Resets, All System | D51: xtool | E51: Dongle | F51: 149.36395 | G51: 232858.4 | H51: 1559 | I51: 1535 | J51: 4.4 | K51: https://amazon.com/dp/B09KT9XNML | L51: =IF(K51="","",HYPERLINK(K51,K51)) -> https://amazon.com/dp/B09KT9XNML
A52: 6 | B52: B073XKQQQW | C52: Veepeak OBDCheck BLE Bluetooth OBD II Scanner for iOS & Android, Car Wireless Check Engine Light Code Reader Diagnostic Tool | D52: veepeak | E52: Dongle | F52: 31.98093 | G52: 205317.57 | H52: 6420 | I52: 23908 | J52: 4.5 | K52: https://amazon.com/dp/B073XKQQQW | L52: =IF(K52="","",HYPERLINK(K52,K52)) -> https://amazon.com/dp/B073XKQQQW
A53: 7 | B53: B0BSFTHFC1 | C53: Diesel Laptops Nexiq USB Link 3 Wireless Edition with Repair Information & Diagnostic Software Bluetooth WiFi | D53: diesel laptops | E53: Dongle | F53: 804.07673 | G53: 199411.03 | H53: 248 | I53: 153 | J53: 4.6 | K53: https://amazon.com/dp/B0BSFTHFC1 | L53: =IF(K53="","",HYPERLINK(K53,K53)) -> https://amazon.com/dp/B0BSFTHFC1
A54: 8 | B54: B013RIQMEO | C54: FIXD Bluetooth OBD2 Scanner - Car Diagnostic Check Engine Code Reader | D54: fixd | E54: Dongle | F54: 39.987912 | G54: 192821.71 | H54: 4822 | I54: 35597 | J54: 4.2 | K54: https://amazon.com/dp/B013RIQMEO | L54: =IF(K54="","",HYPERLINK(K54,K54)) -> https://amazon.com/dp/B013RIQMEO
A55: 9 | B55: B00652G4TS | C55: BlueDriver OBD2 Scanner Bluetooth, No Subscription, ABS SRS TPMS | D55: bluedriver | E55: Dongle | F55: 137.61649 | G55: 176149.11 | H55: 1280 | I55: 62750 | J55: 4.5 | K55: https://amazon.com/dp/B00652G4TS | L55: =IF(K55="","",HYPERLINK(K55,K55)) -> https://amazon.com/dp/B00652G4TS
A56: 10 | B56: B0FY7MYBX7 | C56: HPT MPVI4 Diagnostic Code Reader Scanner and Tool | D56: generic | E56: Dongle | F56: 400.45847 | G56: 166991.18 | H56: 417 | I56: 58 | J56: 4.8 | K56: https://amazon.com/dp/B0FY7MYBX7 | L56: =IF(K56="","",HYPERLINK(K56,K56)) -> https://amazon.com/dp/B0FY7MYBX7
A58: Rank By Monthly Units - Jul '26 ONLY
A59: Ranking | B59: ASIN | C59: Product Name | D59: Brand | E59: Type | F59: Price | G59: Est. Monthly Retail Rev | H59: Est. Monthly Units Sold | I59: # of Reviews | J59: Avg. Rating | K59: Column2 | L59: Link
A60: 1 | B60: B0GL9RL3XS | C60: BlueDriver OBD2 Scanner Bluetooth, No Subscription, ABS SRS TPMS | D60: bluedriver | E60: Dongle | F60: 95.184528 | G60: 926145.46 | H60: 9730 | I60: 63029 | J60: 4.5 | K60: https://amazon.com/dp/B0GL9RL3XS | L60: =IF(K60="","",HYPERLINK(K60,K60)) -> https://amazon.com/dp/B0GL9RL3XS
A61: 2 | B61: B073XKQQQW | C61: Veepeak OBDCheck BLE Bluetooth OBD II Scanner for iOS & Android, Car Wireless Check Engine Light Code Reader Diagnostic Tool | D61: veepeak | E61: Dongle | F61: 31.98093 | G61: 205317.57 | H61: 6420 | I61: 23908 | J61: 4.5 | K61: https://amazon.com/dp/B073XKQQQW | L61: =IF(K61="","",HYPERLINK(K61,K61)) -> https://amazon.com/dp/B073XKQQQW
A62: 3 | B62: B013RIQMEO | C62: FIXD Bluetooth OBD2 Scanner - Car Diagnostic Check Engine Code Reader | D62: fixd | E62: Dongle | F62: 39.987912 | G62: 192821.71 | H62: 4822 | I62: 35597 | J62: 4.2 | K62: https://amazon.com/dp/B013RIQMEO | L62: =IF(K62="","",HYPERLINK(K62,K62)) -> https://amazon.com/dp/B013RIQMEO
A63: 4 | B63: B08NFLL3NT | C63: OBDLink CX Bimmercode Bluetooth 5.1 OBD2 Adapter for BMW/Mini, Works with iPhone/iOS & Android, Car Coding, OBD II Diagnostic Scanner | D63: obdlink | E63: Dongle | F63: 79.945739 | G63: 274133.94 | H63: 3429 | I63: 4614 | J63: 4.6 | K63: https://amazon.com/dp/B08NFLL3NT | L63: =IF(K63="","",HYPERLINK(K63,K63)) -> https://amazon.com/dp/B08NFLL3NT
A64: 5 | B64: B07JFRFJG6 | C64: OBDLink MX+ OBD2 Bluetooth Scanner for iPhone, Android, and Windows | D64: obdlink | E64: Dongle | F64: 139.92839 | G64: 419085.53 | H64: 2995 | I64: 15453 | J64: 4.6 | K64: https://amazon.com/dp/B07JFRFJG6 | L64: =IF(K64="","",HYPERLINK(K64,K64)) -> https://amazon.com/dp/B07JFRFJG6
A65: 6 | B65: B076XVQMVS | C65: Veepeak OBDCheck BLE+ Bluetooth OBD II Scanner for iOS & Android, Car Check Engine Code Reader Wireless OBD Diagnostic Scan Tool | D65: veepeak | E65: Dongle | F65: 41.98355 | G65: 105126.81 | H65: 2504 | I65: 11195 | J65: 4.5 | K65: https://amazon.com/dp/B076XVQMVS | L65: =IF(K65="","",HYPERLINK(K65,K65)) -> https://amazon.com/dp/B076XVQMVS
A66: 7 | B66: B0D44C1F7Y | C66: OBD2 Scanner Diagnostic Tool, Car Scanner for iOS & Android, Bluetooth 5.4 | D66: umeija | E66: Dongle | F66: 21.787326 | G66: 53771.12 | H66: 2468 | I66: 2252 | J66: 4.3 | K66: https://amazon.com/dp/B0D44C1F7Y | L66: =IF(K66="","",HYPERLINK(K66,K66)) -> https://amazon.com/dp/B0D44C1F7Y
A67: 8 | B67: B0C3QQYQ1B | C67: TOPDON TopScan Lite OBD2 Scanner, Bidirectional Scan Tool, 8 Resets & AI | D67: topdon | E67: Dongle | F67: 51.997386 | G67: 95883.18 | H67: 1844 | I67: 5999 | J67: 4 | K67: https://amazon.com/dp/B0C3QQYQ1B | L67: =IF(K67="","",HYPERLINK(K67,K67)) -> https://amazon.com/dp/B0C3QQYQ1B
A68: 9 | B68: B09KT9XNML | C68: XTOOL A30M V2.0 OBD2 Scanner Diagnostic Tool, 26 Resets, All System | D68: xtool | E68: Dongle | F68: 149.36395 | G68: 232858.4 | H68: 1559 | I68: 1535 | J68: 4.4 | K68: https://amazon.com/dp/B09KT9XNML | L68: =IF(K68="","",HYPERLINK(K68,K68)) -> https://amazon.com/dp/B09KT9XNML
A69: 10 | B69: B06XGB4873 | C69: Vgate iCar Pro Bluetooth 4.0 (BLE) OBD2 Fault Code Reader OBDII Code Scanner Car Check Engine Light for iOS/Android | D69: vgate | E69: Dongle | F69: 34.53262 | G69: 50348.56 | H69: 1458 | I69: 7417 | J69: 4.6 | K69: https://amazon.com/dp/B06XGB4873 | L69: =IF(K69="","",HYPERLINK(K69,K69)) -> https://amazon.com/dp/B06XGB4873

Sheet Other Tools
A1: Other Tools Monthly Summary
A3: Other Tools Overall
B4: Avg Price | C4: Avg Price MoM | D4: Avg Price YoY | E4: Quantity/Mo | F4: Qty by % | G4: Qty MoM | H4: Qty YoY | I4: Revenue/Mo | J4: Revenue by % | L4: Revenue MoM | M4: Revenue YoY
A5: diesel laptops | B5: 623.88233 | C5: 0.063277713 | D5: -0.08036599 | E5: 800 | F5: 0.01256025 | G5: -0.067599068 | H5: 0.26984127 | I5: 499105.86 | J5: 0.11092387 | L5: -0.0085988687 | M5: 0.16778922
A6: obdlink | B6: 69.947921 | C6: -8.1010113e-05 | D6: 0.021884544 | E6: 7065 | F6: 0.11092271 | G6: 0.050870147 | H6: 0.35241194 | I6: 494182.06 | J6: 0.10982958 | L6: 0.050785016 | M6: 0.38200886
A7: opus | ivs | B7: 727.96075 | C7: -0.33750108 | D7: 0.12689979 | E7: 585 | F7: 0.0091846828 | G7: -0.45173383 | H7: 0.26623377 | I7: 425857.04 | J7: 0.094644677 | L7: -0.63677425 | M7: 0.42691857
A8: krazy on highways | B8: 480.79019 | C8: 0.11077334 | D8: 0.17184119 | E8: 616 | F8: 0.0096713925 | G8: 0.28601253 | H8: -0.27014218 | I8: 296166.76 | J8: 0.065821636 | L8: 0.42846843 | M8: -0.14472255
A9: autel | B9: 56.627564 | C9: 0.010879262 | D9: -0.36681106 | E9: 4712 | F9: 0.073979872 | G9: -0.041107041 | H9: 0.26056715 | I9: 266829.08 | J9: 0.059301478 | L9: -0.030674994 | M9: -0.20182282
A10: innova | B10: 34.133968 | C10: -0.64920113 | E10: 189 | F10: 0.0029673591 | G10: 10.117647 | I10: 6451.32 | J10: 0.0014337748 | L10: 2.900058
A11: Other | B11: 50.495574 | C11: 0.01308841 | D11: 0.00075003922 | E11: 49726 | F11: 0.78071374 | G11: -0.010959286 | H11: 0.4197693 | I11: 2510942.9 | J11: 0.55804498 | L11: 0.0019856847 | M11: 0.42083418
A12: Total Other Tools | B12: 70.644106 | C12: -0.11515887 | D12: -0.08130698 | E12: 63693 | F12: 1 | G12: -0.0099790161 | H12: 0.38698227 | I12: 4499535 | J12: 1 | L12: -0.12398871 | M12: 0.27421093
A44: Rank By Monthly Revenue - Jul '26 ONLY
A45: Ranking | B45: ASIN | C45: Product Name | D45: Brand | E45: Type | F45: Price | G45: Est. Monthly Retail Rev | H45: Est. Monthly Units Sold | I45: # of Reviews | J45: Avg. Rating | K45: Column2 | L45: Link
A46: 1 | B46: B081VQVD3F | C46: OBDLink EX FORScan OBD Adapter | D46: obdlink | E46: Cable/Adapter | F46: 69.947921 | G46: 494182.06 | H46: 7065 | I46: 10265 | J46: 4.8 | K46: https://amazon.com/dp/B081VQVD3F | L46: =IF(K46="","",HYPERLINK(K46,K46)) -> https://amazon.com/dp/B081VQVD3F
A47: 2 | B47: B0BPYPNDVP | C47: Diesel Laptops Nexiq USB Link 3 Wired Edition with Repair Information & Diagnostic Software | D47: diesel laptops | E47: VCI | F47: 759.48003 | G47: 463282.82 | H47: 610 | I47: 290 | J47: 4.5 | K47: https://amazon.com/dp/B0BPYPNDVP | L47: =IF(K47="","",HYPERLINK(K47,K47)) -> https://amazon.com/dp/B0BPYPNDVP
A48: 3 | B48: B087WMGLF1 | C48: Edge 84130-3 Insight CTS3 | D48: krazy on highways | E48: Other | F48: 480.79019 | G48: 296166.76 | H48: 616 | I48: 1085 | J48: 4.4 | K48: https://amazon.com/dp/B087WMGLF1 | L48: =IF(K48="","",HYPERLINK(K48,K48)) -> https://amazon.com/dp/B087WMGLF1
A49: 4 | B49: B07HX5QHKV | C49: BOSCH EL-52100-AM GM Global Multiple Diagnostic Interface (MDI 2) Kit | D49: bosch | E49: VCI | F49: 1107.3609 | G49: 192680.8 | H49: 174 | I49: 149 | J49: 4.5 | K49: https://amazon.com/dp/B07HX5QHKV | L49: =IF(K49="","",HYPERLINK(K49,K49)) -> https://amazon.com/dp/B07HX5QHKV
A50: 5 | B50: B0DFM25BZB | C50: TOPDON RLink J2534 Pass-Thru Programmer, Supports J2534/D-PDU/CAN-FD/DoIP | D50: topdon | E50: VCI | F50: 250.54113 | G50: 133538.42 | H50: 533 | I50: 307 | J50: 4.4 | K50: https://amazon.com/dp/B0DFM25BZB | L50: =IF(K50="","",HYPERLINK(K50,K50)) -> https://amazon.com/dp/B0DFM25BZB
A51: 6 | B51: B094Z7PBLS | C51: Vgate vLinker FS OBD2 USB Adapter for FORScan | D51: vgate | E51: Cable/Adapter | F51: 36.5453 | G51: 99147.4 | H51: 2713 | I51: 2865 | J51: 4.7 | K51: https://amazon.com/dp/B094Z7PBLS | L51: =IF(K51="","",HYPERLINK(K51,K51)) -> https://amazon.com/dp/B094Z7PBLS
A52: 7 | B52: B01F0GVBWY | C52: OHP FORScan ELM327 OBD2 to USB Diagnostic Scan Tool MS-CAN/HS-CAN | D52: ohp | E52: Cable/Adapter | F52: 35.983574 | G52: 77724.52 | H52: 2160 | I52: 4999 | J52: 4.4 | K52: https://amazon.com/dp/B01F0GVBWY | L52: =IF(K52="","",HYPERLINK(K52,K52)) -> https://amazon.com/dp/B01F0GVBWY
A53: 8 | B53: B000AAMY86 | C53: ScanGauge SG2 Ultra Compact 3-in-1 Automotive Computer with Customizable Real-Time Fuel Economy Digital Gauges for OBD2 Vehicles | D53: scangauge | E53: Other | F53: 157.58566 | G53: 63191.85 | H53: 401 | I53: 2275 | J53: 4.6 | K53: https://amazon.com/dp/B000AAMY86 | L53: =IF(K53="","",HYPERLINK(K53,K53)) -> https://amazon.com/dp/B000AAMY86
A54: 9 | B54: B0D3F2953F | C54: ANCEL HD110 Heavy Duty Truck Scanner with DPF Regen and Reset for Detroit Paccar Engine, Full System HDOBD & OBD2 Scanner for Diesel Trucks Lifetime Free Updates | D54: ancel | E54: Cable/Adapter | F54: 186.19516 | G54: 59582.45 | H54: 320 | I54: 216 | J54: 4.1 | K54: https://amazon.com/dp/B0D3F2953F | L54: =IF(K54="","",HYPERLINK(K54,K54)) -> https://amazon.com/dp/B0D3F2953F
A55: 10 | B55: B097NHQ7ZW | C55: Opus IVS Mongoose-Plus J2534 OEM Vehicle Interface Cable - Ford/Lincoln/Mercury OEM Reprogramming and Diagnostics. | D55: opus | ivs | E55: Cable/Adapter | F55: 585.68388 | G55: 57397.02 | H55: 98 | I55: 114 | J55: 4.6 | K55: https://amazon.com/dp/B097NHQ7ZW | L55: =IF(K55="","",HYPERLINK(K55,K55)) -> https://amazon.com/dp/B097NHQ7ZW
A57: Rank By Monthly Units - Jul '26 ONLY
A58: Ranking | B58: ASIN | C58: Product Name | D58: Brand | E58: Type | F58: Price | G58: Est. Monthly Retail Rev | H58: Est. Monthly Units Sold | I58: # of Reviews | J58: Avg. Rating | K58: Column2 | L58: Link
A59: 1 | B59: B081VQVD3F | C59: OBDLink EX FORScan OBD Adapter | D59: obdlink | E59: Cable/Adapter | F59: 69.947921 | G59: 494182.06 | H59: 7065 | I59: 10265 | J59: 4.8 | K59: https://amazon.com/dp/B081VQVD3F | L59: =IF(K59="","",HYPERLINK(K59,K59)) -> https://amazon.com/dp/B081VQVD3F
A60: 2 | B60: B094Z7PBLS | C60: Vgate vLinker FS OBD2 USB Adapter for FORScan | D60: vgate | E60: Cable/Adapter | F60: 36.5453 | G60: 99147.4 | H60: 2713 | I60: 2865 | J60: 4.7 | K60: https://amazon.com/dp/B094Z7PBLS | L60: =IF(K60="","",HYPERLINK(K60,K60)) -> https://amazon.com/dp/B094Z7PBLS
A61: 3 | B61: B01F0GVBWY | C61: OHP FORScan ELM327 OBD2 to USB Diagnostic Scan Tool MS-CAN/HS-CAN | D61: ohp | E61: Cable/Adapter | F61: 35.983574 | G61: 77724.52 | H61: 2160 | I61: 4999 | J61: 4.4 | K61: https://amazon.com/dp/B01F0GVBWY | L61: =IF(K61="","",HYPERLINK(K61,K61)) -> https://amazon.com/dp/B01F0GVBWY
A62: 4 | B62: B07MQ8GHG3 | C62: ELM327 USB Adapter OBD2 Scanner for Windows, ELMconfig FoCCCus Diagnostic Scan Tool with MS-Can/HS-Can Switch for Ford Lincoln Mazda Mercury Series Vehicles | D62: obdresource | E62: Cable/Adapter | F62: 18.568282 | G62: 17509.89 | H62: 943 | I62: 6918 | J62: 4.4 | K62: https://amazon.com/dp/B07MQ8GHG3 | L62: =IF(K62="","",HYPERLINK(K62,K62)) -> https://amazon.com/dp/B07MQ8GHG3
A63: 5 | B63: B0711LGRGQ | C63: bbfly-A9 OBD II OBD2 16Pin Splitter Extension Cable Adapter (2FT/60CM) | D63: bbfly | E63: Cable/Adapter | F63: 9.9054648 | G63: 7884.75 | H63: 796 | I63: 3153 | J63: 4.5 | K63: https://amazon.com/dp/B0711LGRGQ | L63: =IF(K63="","",HYPERLINK(K63,K63)) -> https://amazon.com/dp/B0711LGRGQ
A64: 6 | B64: B0DPHCBL89 | C64: ecocstm 12+8 Pin Connector to OBD2 Adapter, Secutiry Gateway Bypass Cable | D64: ecocstm | E64: Cable/Adapter | F64: 12.991741 | G64: 9925.69 | H64: 764 | I64: 216 | J64: 4.7 | K64: https://amazon.com/dp/B0DPHCBL89 | L64: =IF(K64="","",HYPERLINK(K64,K64)) -> https://amazon.com/dp/B0DPHCBL89
A65: 7 | B65: B0CZ92SLDY | C65: VGATE vLinker FS USB FORScan OBD2 Adapter for HS/MS-CAN Auto Switch, Wire OBD2 USB FORScan Adapter Code Readers & Scanner Diagnostic Tools | D65: vlinker | E65: Cable/Adapter | F65: 35.856671 | G65: 26713.22 | H65: 745 | I65: 439 | J65: 4.6 | K65: https://amazon.com/dp/B0CZ92SLDY | L65: =IF(K65="","",HYPERLINK(K65,K65)) -> https://amazon.com/dp/B0CZ92SLDY
A66: 8 | B66: B071L8W7Q7 | C66: bbfly-B6 OBD2 Splitter OBDII Extension Cable Adapter (1FT/30CM) (1Pack) | D66: bbfly | E66: Cable/Adapter | F66: 10.901696 | G66: 8099.96 | H66: 743 | I66: 2157 | J66: 4.6 | K66: https://amazon.com/dp/B071L8W7Q7 | L66: =IF(K66="","",HYPERLINK(K66,K66)) -> https://amazon.com/dp/B071L8W7Q7
A67: 9 | B67: B0BJQKK2TJ | C67: OBD2 12+8 Adapter for Chrysler, 12 8 OBD II Security Gateway Bypass Cable | D67: autel | E67: Cable/Adapter | F67: 25.98708 | G67: 18242.93 | H67: 702 | I67: 593 | J67: 4.7 | K67: https://amazon.com/dp/B0BJQKK2TJ | L67: =IF(K67="","",HYPERLINK(K67,K67)) -> https://amazon.com/dp/B0BJQKK2TJ
A68: 10 | B68: B09KZWP19M | C68: Mellbree 2Pcs Fiber Optic Loop, Female and Male Fiber Optic Bypass Loop Adapter Connector Diagnostic Device Tool Compatible for Benz Audi Mercedes BMW VW Porsche Most Optical System | D68: mellbree | E68: Cable/Adapter | F68: 7.9895886 | G68: 5049.42 | H68: 632 | I68: 636 | J68: 4.3 | K68: https://amazon.com/dp/B09KZWP19M | L68: =IF(K68="","",HYPERLINK(K68,K68)) -> https://amazon.com/dp/B09KZWP19M

Sheet Ancel
B7: Avg Price | C7: Avg Price MoM | D7: Avg Price YoY | E7: Quantity/Mo | F7: Qty by % | G7: Qty MoM | H7: Qty YoY | I7: Revenue/Mo | J7: Revenue by % | L7: Revenue MoM | M7: Revenue YoY
A8: Tablet $800+ | B8: 939.33984 | C8: -0.013969347 | D8: 0.082263364 | E8: 551 | F8: 0.012195392 | G8: 0.091089109 | H8: 1.9308511 | I8: 517576.25 | J8: 0.17676757 | L8: 0.075847307 | M8: 2.1719527
A9: Tablet $400-$800 | B9: 540.73332 | C9: -0.023584292 | D9: 0.11696695 | E9: 906 | F9: 0.020052677 | G9: -0.36995828 | H9: 1.0590909 | I9: 489904.39 | J9: 0.16731681 | L9: -0.38481736 | M9: 1.2999365
A10: Tablet $400- | B10: 235.44343 | C10: -0.062025949 | D10: 0.082712494 | E10: 1084 | F10: 0.023992386 | G10: -0.31218274 | H10: -0.36272781 | I10: 255220.68 | J10: 0.087165398 | L10: -0.35484526 | M10: -0.31001743
A11: Total Tablet | B11: 496.93086 | C11: 0.045223408 | D11: 0.55125435 | E11: 2541 | F11: 0.056240455 | G11: -0.27791986 | H11: 0.091026191 | I11: 1262701.3 | J11: 0.43124978 | L11: -0.24526494 | M11: 0.69245912
A12: Handheld $75+ | B12: 124.97187 | C12: 0.060038602 | D12: 0.11636424 | E12: 1559 | F12: 0.034505655 | G12: -0.030472637 | H12: -0.57497274 | I12: 194831.14 | J12: 0.066540587 | L12: 0.02773643 | M12: -0.52551476
A13: Handheld $75- | B13: 32.575902 | C13: -0.012669611 | D13: -0.071099885 | E13: 38606 | F13: 0.85447423 | G13: 0.052450793 | H13: 0.075316138 | I13: 1257625.3 | J13: 0.42951616 | L13: 0.039116651 | M13: -0.0011387155
A14: Total Handheld | B14: 36.162241 | C14: -0.010861046 | D14: -0.14298288 | E14: 40165 | F14: 0.88897988 | G14: 0.048968399 | H14: 0.015036644 | I14: 1452456.4 | J14: 0.49605675 | L14: 0.037575505 | M14: -0.13009622
A15: Total Dongle | B15: 101.5245 | C15: 0.057694896 | D15: -0.063159116 | E15: 1327 | F15: 0.029370753 | G15: -0.071378586 | H15: 1.5817121 | I15: 134723.01 | J15: 0.046011886 | L15: -0.01780187 | M15: 1.4186534
A16: Total Other Tools | B16: 68.052082 | C16: 0.12210663 | D16: -0.32106849 | E16: 1148 | F16: 0.025408911 | G16: -0.11076685 | H16: 0.54925776 | I16: 78123.79 | J16: 0.026681581 | L16: -0.0021855827 | M16: 0.051839917
A17: Total | B17: 64.806103 | C17: -0.12243327 | D17: 0.098564352 | E17: 45181 | F17: 1 | G17: 0.014642143 | H17: 0.046971312 | I17: 2928004.5 | J17: 1 | L17: -0.10958381 | M17: 0.15016536
A51: Rank by Revenue
A52: Product Name | B52: ASIN | C52: Type | D52: Avg Price | E52: Estimated 12mo Revenue | F52: Monthly Rev | G52: Estimated 12mo Units | H52: Monthly Units | I52: # of Reviews | J52: Tool Rating | K52: Column1 | L52: Link
A53: ANCEL AD310 Classic Enhanced Universal OBD II Scanner Car Engine Fault Code Reader CAN Diagnostic Scan Tool, Read and Clear Error Codes for 1996 or Newer OBD2 Protocol Vehicle (Black) | B53: B01G5EA74I | C53: Handheld | D53: 27.817391 | E53: 11583023 | F53: 815550.26 | G53: 410944 | H53: 29318 | I53: 65760 | J53: 4.6 | K53: https://amazon.com/dp/B01G5EA74I | L53: =IF(K53="","",HYPERLINK(K53,K53)) -> https://amazon.com/dp/B01G5EA74I
A54: ANCEL MT700 Motorcycle OBD2 Scanner Full Systems, ABS Engine Meter TPMS Diagnostic Tool with 35+ Reset Functions for Harley Indian Yamaha Polaris Piaggio Ducati Honda BMW, AutoVIN, 7”Touch Screen,16G | B54: B0BMZW65LJ | C54: Tablet | D54: 954.64527 | E54: 766997.36 | F54: 322670.1 | G54: 796 | H54: 338 | I54: 914 | J54: 4.5 | K54: https://amazon.com/dp/B0BMZW65LJ | L54: =IF(K54="","",HYPERLINK(K54,K54)) -> https://amazon.com/dp/B0BMZW65LJ
A55: ANCEL AD410 Enhanced OBD2 Scanner, Vehicle Code Reader for Check Engine Light, Automotive OBD II Scanner Fault Diagnosis, OBDII Scan Tool for All OBDII Cars 1996+, Black/Yellow | B55: B071FSNL73 | C55: Handheld | D55: 41.468081 | E55: 4091221.8 | F55: 234211.72 | G55: 87822 | H55: 5648 | I55: 15482 | J55: 4.5 | K55: https://amazon.com/dp/B071FSNL73 | L55: =IF(K55="","",HYPERLINK(K55,K55)) -> https://amazon.com/dp/B071FSNL73
A56: ANCEL X7HD PRO 10.1'' Heavy Duty Truck Scanner, Full-System Diesel Diagnostic Tool with DPF Regen, 42+ Reset, Bi-Directional and Active Test, ECU Coding, HDOBD/OBD2 Scanner for Diesel Trucks - Grey | B56: B0GLFSPMZ4 | C56: Tablet | D56: 898.63143 | E56: 1920478.7 | F56: 157260.5 | G56: 511 | H56: 175 | I56: 48 | J56: 4.7 | K56: https://amazon.com/dp/B0GLFSPMZ4 | L56: =IF(K56="","",HYPERLINK(K56,K56)) -> https://amazon.com/dp/B0GLFSPMZ4
A57: ANCEL X7HD 10.1'' Heavy Duty Truck Scanner, Semi Trucks Full System Diagnostic Tool, Bidirectional Diesel Scan Tool with DPF, ECU Coding, 40+ Reset for Cummins, Detroit, Caterpillar, Volvo, Paccar etc | B57: B0BZ82WQ4Q | C57: Tablet | D57: 766.31939 | E57: 2731748.1 | F57: 137937.49 | G57: 3458 | H57: 180 | I57: 812 | J57: 3.7 | K57: https://amazon.com/dp/B0BZ82WQ4Q | L57: =IF(K57="","",HYPERLINK(K57,K57)) -> https://amazon.com/dp/B0BZ82WQ4Q
A58: ANCEL DS500BT Bidirectional Scan Tool, Wireless Full-System OBD2 Diagnostic Scanner with 3000+ Active Tests, 28+ Service Functions, Lifetime Free Updates & CAN FD Support | B58: B0FN4JHLY7 | C58: Tablet | D58: 479.45766 | E58: 1363254.5 | F58: 116987.67 | G58: 2081 | H58: 244 | I58: 1116 | J58: 4.5 | K58: https://amazon.com/dp/B0FN4JHLY7 | L58: =IF(K58="","",HYPERLINK(K58,K58)) -> https://amazon.com/dp/B0FN4JHLY7
A59: ANCEL HD3400 Pro Heavy Duty Truck Scanner with DPF Regen for Cummins, Paccar, Caterpillar, Detroit, Volvo, Mack and International, Full-System Diesel Scan Tool for 6/9-Pin HDOBD & OBD2 Vehicles | B59: B09R3L5BP2 | C59: Tablet | D59: 460.31478 | E59: 1116538.7 | F59: 93443.9 | G59: 2395 | H59: 203 | I59: 578 | J59: 4.2 | K59: https://amazon.com/dp/B09R3L5BP2 | L59: =IF(K59="","",HYPERLINK(K59,K59)) -> https://amazon.com/dp/B09R3L5BP2
A60: ANCEL AD410 PRO OBD2 Scanner and Battery Tester, 2-in-1 Car Diagnostic Tool, Check Engine Light, EVAP Test, Live Data, 12V Battery Analyzer with Cranking & Charging System Test for Car Motorcycle | B60: B0BX3K8VGJ | C60: Handheld | D60: 62.168795 | E60: 1002613 | F60: 66023.26 | G60: 14419 | H60: 1062 | I60: 4204 | J60: 4.6 | K60: https://amazon.com/dp/B0BX3K8VGJ | L60: =IF(K60="","",HYPERLINK(K60,K60)) -> https://amazon.com/dp/B0BX3K8VGJ
A61: ANCEL HD110 Heavy Duty Truck Scanner with DPF Regen and Reset for Detroit Paccar Engine, Full System HDOBD & OBD2 Scanner for Diesel Trucks Lifetime Free Updates | B61: B0D3F2953F | C61: Cable/Adapter | D61: 186.19516 | E61: 677255.53 | F61: 59582.45 | G61: 3805 | H61: 320 | I61: 216 | J61: 4.1 | K61: https://amazon.com/dp/B0D3F2953F | L61: =IF(K61="","",HYPERLINK(K61,K61)) -> https://amazon.com/dp/B0D3F2953F
A62: ANCEL VD500 OBD2 Scanner Diagnostic Tool for Volkswagen VW Audi Skoda Seat Full Systems Check Engine Light EPB ABS SRS Code Reader Oil Throttle Position Adaption Brake Pad Reset | B62: B07BS7PDC2 | C62: Handheld | D62: 62.905059 | E62: 769959.85 | F62: 58942.04 | G62: 11759 | H62: 937 | I62: 6433 | J62: 4.5 | K62: https://amazon.com/dp/B07BS7PDC2 | L62: =IF(K62="","",HYPERLINK(K62,K62)) -> https://amazon.com/dp/B07BS7PDC2
A63: ANCEL HD100 Heavy Duty Truck Scanner with DPF Regen for Cummins & CAT Engines, Bluetooth Diesel Diagnostic Tool with All-System Scan, HDOBD & OBD2 Code Reader for Semi Trucks, Lifetime Free Updates | B63: B0CQ4V8X9L | C63: Dongle | D63: 168.48529 | E63: 392347.7 | F63: 57958.94 | G63: 2163 | H63: 344 | I63: 169 | J63: 4.1 | K63: https://amazon.com/dp/B0CQ4V8X9L | L63: =IF(K63="","",HYPERLINK(K63,K63)) -> https://amazon.com/dp/B0CQ4V8X9L
A64: ANCEL DS200 Full System OBD2 Scanner with 15 Service Functions, Automotive Scan Tool ABS Bleeding, EPB, Oil, BMS, SAS, Throttle, Injector, FCA AutoAuth, AutoVIN, Lifetime Free Update | B64: B0DHX29NMC | C64: Tablet | D64: 316.58 | E64: 808694.59 | F64: 56034.66 | G64: 2801 | H64: 177 | I64: 223 | J64: 4.4 | K64: https://amazon.com/dp/B0DHX29NMC | L64: =IF(K64="","",HYPERLINK(K64,K64)) -> https://amazon.com/dp/B0DHX29NMC
... A150: ANCEL BM300 12V Battery Monitor, Bluetooth 4.0 Automotive Voltmeter with ANCEL DS200 OBD2 Scanner for ABS, SRS, Transmission, All Systems Diagnostics, 15+ Reset Services | B150: B0DVSY4W1R | C150: Handheld | D150: 332.9 | E150: 0 | F150: 0 | G150: 0 | H150: 0 | I150: 0 | J150: 0 | K150: https://amazon.com/dp/B0DVSY4W1R | L150: =IF(K150="","",HYPERLINK(K150,K150)) -> https://amazon.com/dp/B0DVSY4W1R
A151: Total | E151: =SUM(E53:E150) -> 40235845 | F151: =SUM(F53:F150) -> 2928004.5
A153: Rank by Units
A154: Product Name | B154: ASIN | C154: Type | D154: Avg Price | E154: Estimated 12mo Revenue | F154: Monthly Rev | G154: Estimated 12mo Units | H154: Monthly Units | I154: # of Reviews | J154: Tool Rating | K154: Column1 | L154: Link
A155: ANCEL AD310 Classic Enhanced Universal OBD II Scanner Car Engine Fault Code Reader CAN Diagnostic Scan Tool, Read and Clear Error Codes for 1996 or Newer OBD2 Protocol Vehicle (Black) | B155: B01G5EA74I | C155: Handheld | D155: 27.817391 | E155: 11583023 | F155: 815550.26 | G155: 410944 | H155: 29318 | I155: 65760 | J155: 4.6 | K155: https://amazon.com/dp/B01G5EA74I | L155: =IF(K155="","",HYPERLINK(K155,K155)) -> https://amazon.com/dp/B01G5EA74I
A156: ANCEL AD410 Enhanced OBD2 Scanner, Vehicle Code Reader for Check Engine Light, Automotive OBD II Scanner Fault Diagnosis, OBDII Scan Tool for All OBDII Cars 1996+, Black/Yellow | B156: B071FSNL73 | C156: Handheld | D156: 41.468081 | E156: 4091221.8 | F156: 234211.72 | G156: 87822 | H156: 5648 | I156: 15482 | J156: 4.5 | K156: https://amazon.com/dp/B071FSNL73 | L156: =IF(K156="","",HYPERLINK(K156,K156)) -> https://amazon.com/dp/B071FSNL73
A157: ANCEL AD410 PRO OBD2 Scanner and Battery Tester, 2-in-1 Car Diagnostic Tool, Check Engine Light, EVAP Test, Live Data, 12V Battery Analyzer with Cranking & Charging System Test for Car Motorcycle | B157: B0BX3K8VGJ | C157: Handheld | D157: 62.168795 | E157: 1002613 | F157: 66023.26 | G157: 14419 | H157: 1062 | I157: 4204 | J157: 4.6 | K157: https://amazon.com/dp/B0BX3K8VGJ | L157: =IF(K157="","",HYPERLINK(K157,K157)) -> https://amazon.com/dp/B0BX3K8VGJ
A158: ANCEL VD500 OBD2 Scanner Diagnostic Tool for Volkswagen VW Audi Skoda Seat Full Systems Check Engine Light EPB ABS SRS Code Reader Oil Throttle Position Adaption Brake Pad Reset | B158: B07BS7PDC2 | C158: Handheld | D158: 62.905059 | E158: 769959.85 | F158: 58942.04 | G158: 11759 | H158: 937 | I158: 6433 | J158: 4.5 | K158: https://amazon.com/dp/B07BS7PDC2 | L158: =IF(K158="","",HYPERLINK(K158,K158)) -> https://amazon.com/dp/B07BS7PDC2
A159: ANCEL BD310 Bluetooth OBD2 Scanner, 2-in-1 Car Diagnostic Scan Tool & Code Reader with App, Battery Test, Trip Analysis, Performance Test, for iPhone & Android, All 1996+ Vehicles | B159: B07J51W9NS | C159: Handheld | D159: 59.399179 | E159: 714273.63 | F159: 40510.24 | G159: 11379 | H159: 682 | I159: 1549 | J159: 4.4 | K159: https://amazon.com/dp/B07J51W9NS | L159: =IF(K159="","",HYPERLINK(K159,K159)) -> https://amazon.com/dp/B07J51W9NS
A160: ANCEL BD500 Bluetooth Diagnostic Scan Tool for VW Audi Seat Skoda Diagnosis, Full Systems Volkswagen OBD2 Scanner Vag Car Code Reader with Battery Check EPB Reset for iPhone, iPad & Android | B160: B0B1MHSMBW | C160: Dongle | D160: 80.885821 | E160: 247625.51 | F160: 55164.13 | G160: 3061 | H160: 682 | I160: 1782 | J160: 4.4 | K160: https://amazon.com/dp/B0B1MHSMBW | L160: =IF(K160="","",HYPERLINK(K160,K160)) -> https://amazon.com/dp/B0B1MHSMBW
A161: ANCEL AD530 OBD2 Scanner-Upgraded AD310, Car Code Reader for Check Engine Light, Full OBDII Scan Tool for Read & Clear Fault Codes, Battery Test & Live Data, OBD II Diagnostic Scanner for 1996+ Cars | B161: B07N66TTQG | C161: Handheld | D161: 58.656119 | E161: 650283.27 | F161: 28565.53 | G161: 9917 | H161: 487 | I161: 4215 | J161: 4.5 | K161: https://amazon.com/dp/B07N66TTQG | L161: =IF(K161="","",HYPERLINK(K161,K161)) -> https://amazon.com/dp/B07N66TTQG
A162: ANCEL HD100 Heavy Duty Truck Scanner with DPF Regen for Cummins & CAT Engines, Bluetooth Diesel Diagnostic Tool with All-System Scan, HDOBD & OBD2 Code Reader for Semi Trucks, Lifetime Free Updates | B162: B0CQ4V8X9L | C162: Dongle | D162: 168.48529 | E162: 392347.7 | F162: 57958.94 | G162: 2163 | H162: 344 | I162: 169 | J162: 4.1 | K162: https://amazon.com/dp/B0CQ4V8X9L | L162: =IF(K162="","",HYPERLINK(K162,K162)) -> https://amazon.com/dp/B0CQ4V8X9L
A163: ANCEL MT700 Motorcycle OBD2 Scanner Full Systems, ABS Engine Meter TPMS Diagnostic Tool with 35+ Reset Functions for Harley Indian Yamaha Polaris Piaggio Ducati Honda BMW, AutoVIN, 7”Touch Screen,16G | B163: B0BMZW65LJ | C163: Tablet | D163: 954.64527 | E163: 766997.36 | F163: 322670.1 | G163: 796 | H163: 338 | I163: 914 | J163: 4.5 | K163: https://amazon.com/dp/B0BMZW65LJ | L163: =IF(K163="","",HYPERLINK(K163,K163)) -> https://amazon.com/dp/B0BMZW65LJ
A164: ANCEL HD110 Heavy Duty Truck Scanner with DPF Regen and Reset for Detroit Paccar Engine, Full System HDOBD & OBD2 Scanner for Diesel Trucks Lifetime Free Updates | B164: B0D3F2953F | C164: Cable/Adapter | D164: 186.19516 | E164: 677255.53 | F164: 59582.45 | G164: 3805 | H164: 320 | I164: 216 | J164: 4.1 | K164: https://amazon.com/dp/B0D3F2953F | L164: =IF(K164="","",HYPERLINK(K164,K164)) -> https://amazon.com/dp/B0D3F2953F
A165: ANCEL Protective Case Storage Bag for OBD2 Scanner Code Reader Diagnostic Scan Tool Battery Tester | B165: B07B49PHXD | C165: Other | D165: 20.728067 | E165: 110122.26 | F165: 6218.42 | G165: 4880 | H165: 300 | I165: 4202 | J165: 4.6 | K165: https://amazon.com/dp/B07B49PHXD | L165: =IF(K165="","",HYPERLINK(K165,K165)) -> https://amazon.com/dp/B07B49PHXD
A166: ANCEL 2 ft OBD2 Extension Cable, 16-Pin Male to Female OBD2 Adapter | B166: B0DS56LD3K | C166: Handheld | D166: 16.303286 | E166: 20437.62 | F166: 4564.92 | G166: 1334 | H166: 280 | I166: 54 | J166: 4.7 | K166: https://amazon.com/dp/B0DS56LD3K | L166: =IF(K166="","",HYPERLINK(K166,K166)) -> https://amazon.com/dp/B0DS56LD3K
... A252: ANCEL BM300 12V Battery Monitor, Bluetooth 4.0 Automotive Voltmeter with ANCEL DS200 OBD2 Scanner for ABS, SRS, Transmission, All Systems Diagnostics, 15+ Reset Services | B252: B0DVSY4W1R | C252: Handheld | D252: 332.9 | E252: 0 | F252: 0 | G252: 0 | H252: 0 | I252: 0 | J252: 0 | K252: https://amazon.com/dp/B0DVSY4W1R | L252: =IF(K252="","",HYPERLINK(K252,K252)) -> https://amazon.com/dp/B0DVSY4W1R
A253: Total | G253: =SUM(G155:G252) -> 635407 | H253: =SUM(H155:H252) -> 45181

Sheet AUTEL
B7: Avg Price | C7: Avg Price MoM | D7: Avg Price YoY | E7: Quantity/Mo | F7: Qty by % | G7: Qty MoM | H7: Qty YoY | I7: Revenue/Mo | J7: Revenue by % | L7: Revenue MoM | M7: Revenue YoY
A8: Tablet $800+ | B8: 2023.8071 | C8: 0.012531454 | D8: 0.037540182 | E8: 810 | F8: 0.042421703 | G8: -0.16062176 | H8: -0.24581006 | I8: 1639283.8 | J8: 0.30475089 | L8: -0.15010313 | M8: -0.21749763
A9: Tablet $400-$800 | B9: 536.14049 | C9: -0.031530742 | D9: 0.018309988 | E9: 5461 | F9: 0.28600608 | G9: -0.052238806 | H9: 0.22006256 | I9: 2927863.2 | J9: 0.54430412 | L9: -0.082122419 | M9: 0.24240189
A10: Tablet $400- | B10: 216.79054 | C10: -0.006622017 | D10: -0.37800386 | E10: 168 | F10: 0.0087985755 | G10: 0.063291139 | H10: 167 | I10: 36420.81 | J10: 0.0067708071 | L10: 0.056250007 | M10: 103.49535
A11: Total Tablet | B11: 714.95074 | C11: -0.044762822 | D11: -0.10853758 | E11: 6439 | F11: 0.33722635 | G11: -0.064778504 | H11: 0.15997118 | I11: 4603567.8 | J11: 0.85582581 | L11: -0.10664166 | M11: 0.034070713
A12: Handheld $75+ | B12: 172.765 | C12: -0.17946582 | D12: -0.3041263 | E12: 940 | F12: 0.049230125 | G12: -0.088263822 | H12: -0.39354839 | I12: 162399.1 | J12: 0.030190789 | L12: -0.2518893 | M12: -0.57798627
A13: Handheld $75- | B13: 37.78 | C13: -0.042778682 | D13: 0.12199894 | E13: 5319 | F13: 0.27856918 | G13: -0.15490944 | H13: -0.032557294 | I13: 200951.82 | J13: 0.037357928 | L13: -0.1910613 | M13: 0.085469687
A14: Total Handheld | B14: 58.052552 | C14: -0.086485016 | D14: -0.28212029 | E14: 6259 | F14: 0.32779931 | G14: -0.14552901 | H14: -0.11194665 | I14: 363350.92 | J14: 0.067548717 | L14: -0.21942795 | M14: -0.36248452
A15: Total Dongle | B15: 92.742797 | C15: -0.090472126 | D15: 0.083573457 | E15: 1541 | F15: 0.080705981 | G15: 0.057652711 | H15: -0.044637322 | I15: 142916.65 | J15: 0.026568906 | L15: -0.038035379 | M15: 0.03520564
A16: Total Other Tools | B16: 56.627564 | C16: 0.010879262 | D16: -0.36681106 | E16: 4712 | F16: 0.24677909 | G16: -0.041107041 | H16: 0.26056715 | I16: 266829.08 | J16: 0.049604834 | L16: -0.030674994 | M16: -0.20182282
A17: Total | B17: 283.71402 | C17: -0.033648449 | D17: -0.073081689 | E17: 18951 | F17: 0.99251074 | G17: -0.079199261 | H17: 0.055766017 | I17: 5376664.4 | J17: 0.99954827 | L17: -0.11018278 | M17: -0.021391147
A51: Rank by Revenue
A52: Product Name | B52: ASIN | C52: Type | D52: Avg Price | E52: Estimated 12mo Revenue | F52: Monthly Rev | G52: Estimated 12mo Units | H52: Monthly Units | I52: # of Reviews | J52: Tool Rating | K52: Column1 | L52: Link
A53: Autel Scanner MaxiCOM MK900BT Bidirectional Tool, 40+ Service, CAN-FD& DOIP | B53: B098PYB8XG | C53: Tablet | D53: 658.71861 | E53: 6217858.7 | F53: 425532.22 | G53: 9435 | H53: 646 | I53: 778 | J53: 4.6 | K53: https://amazon.com/dp/B098PYB8XG | L53: =IF(K53="","",HYPERLINK(K53,K53)) -> https://amazon.com/dp/B098PYB8XG
A54: Autel Scanner MaxiCOM MK808S: 3000+ Active Tests 28+ Service as MK900-BT | B54: B0GX1WPD31 | C54: Tablet | D54: 468.70797 | E54: 2839883.1 | F54: 284505.74 | G54: 1016 | H54: 607 | I54: 381 | J54: 4.4 | K54: https://amazon.com/dp/B0GX1WPD31 | L54: =IF(K54="","",HYPERLINK(K54,K54)) -> https://amazon.com/dp/B0GX1WPD31
A55: Autel Scanner MaxiCOM MK808S Bidirectional Tool, 28+ Hot Service All System | B55: B0744B55QV | C55: Tablet | D55: 457.87741 | E55: 6541456.9 | F55: 263737.39 | G55: 13852 | H55: 576 | I55: 3903 | J55: 4.4 | K55: https://amazon.com/dp/B0744B55QV | L55: =IF(K55="","",HYPERLINK(K55,K55)) -> https://amazon.com/dp/B0744B55QV
A56: Autel Scanner MaxiCheck MX808S, Bidirectional OBD2 Scan Tool 28+ Service | B56: B08ML7T7KZ | C56: Tablet | D56: 430.55856 | E56: 3403035.4 | F56: 248432.29 | G56: 7875 | H56: 577 | I56: 756 | J56: 4.6 | K56: https://amazon.com/dp/B08ML7T7KZ | L56: =IF(K56="","",HYPERLINK(K56,K56)) -> https://amazon.com/dp/B08ML7T7KZ
A57: Autel Scanner MaxiCOM MK900BT, 2026 MK900-BT 8in V2.0 Bidirectional Tool | B57: B09712X5CW | C57: Tablet | D57: 659.4073 | E57: 2016560.4 | F57: 222220.26 | G57: 3060 | H57: 337 | I57: 248 | J57: 4.6 | K57: https://amazon.com/dp/B09712X5CW | L57: =IF(K57="","",HYPERLINK(K57,K57)) -> https://amazon.com/dp/B09712X5CW
A58: Autel Scanner MaxiCOM MK900: 3000+ Active Tests 40+ Service as MK900-BT | B58: B073CQMF25 | C58: Tablet | D58: 588.2876 | E58: 2097346.7 | F58: 186487.17 | G58: 3700 | H58: 317 | I58: 606 | J58: 4.4 | K58: https://amazon.com/dp/B073CQMF25 | L58: =IF(K58="","",HYPERLINK(K58,K58)) -> https://amazon.com/dp/B073CQMF25
A59: Autel Scanner MaxiCOM MK900BT: MK900-BT 8in V2.0 Bidirectional Scan Tool | B59: B07PGYY8SS | C59: Tablet | D59: 660.23368 | E59: 1347325.8 | F59: 159776.55 | G59: 2045 | H59: 242 | I59: 199 | J59: 4.5 | K59: https://amazon.com/dp/B07PGYY8SS | L59: =IF(K59="","",HYPERLINK(K59,K59)) -> https://amazon.com/dp/B07PGYY8SS
A60: Autel Scanner MaxiIM KM100 (X), 700+ Models, for Home Mechanics & DIYers | B60: B0FZBK7KJD | C60: Tablet | D60: 483.26557 | E60: 998453.8 | F60: 131931.5 | G60: 536 | H60: 273 | I60: 33 | J60: 4.9 | K60: https://amazon.com/dp/B0FZBK7KJD | L60: =IF(K60="","",HYPERLINK(K60,K60)) -> https://amazon.com/dp/B0FZBK7KJD
A61: Autel MaxiSys Ultra S2 Scanner, 2026 Top Intelligen Scan Diagnostic with AI, 6-in-1 VCMI2, Up of MSUltra MS919, Topology 3.0, Multi-Point DVI, Motor Truspeed Repair, EV Test, 48+ Service, ECU Program | B61: B0DZC1M7MZ | C61: Tablet | D61: 5726.4109 | E61: 1667016.7 | F61: 131707.45 | G61: 294 | H61: 23 | I61: 24 | J61: 4.9 | K61: https://amazon.com/dp/B0DZC1M7MZ | L61: =IF(K61="","",HYPERLINK(K61,K61)) -> https://amazon.com/dp/B0DZC1M7MZ
A62: Autel MaxiCheck MX900 Scanner, 3000+ Active Test, 40+ Service, DoIP&CAN FD | B62: B09JFXPYKL | C62: Tablet | D62: 559.71837 | E62: 965531.77 | F62: 96271.56 | G62: 1727 | H62: 172 | I62: 128 | J62: 4.7 | K62: https://amazon.com/dp/B09JFXPYKL | L62: =IF(K62="","",HYPERLINK(K62,K62)) -> https://amazon.com/dp/B09JFXPYKL
A63: Autel Scanner MaxiCOM MK808BT PRO, 2026 Newer Bidirectional Tool as MK900BT | B63: B07MBSZH48 | C63: Tablet | D63: 548.85976 | E63: 1606549.9 | F63: 91659.58 | G63: 2980 | H63: 167 | I63: 1791 | J63: 4.6 | K63: https://amazon.com/dp/B07MBSZH48 | L63: =IF(K63="","",HYPERLINK(K63,K63)) -> https://amazon.com/dp/B07MBSZH48
A64: Autel Obd2 Scanner Diagnostic Tool MaxiCOM MK808Z: 2026 Bidirectional Scan Tool, 28+ Service, Active Tests Scanner for Car, All System OBD2 Diagnostics Car Scanner for DIY, Mechanic and Small Shops | B64: B0GMQD4M5N | C64: Tablet | D64: 423.39417 | E64: 936046.34 | F64: 86372.41 | G64: 502 | H64: 204 | I64: 35 | J64: 4.8 | K64: https://amazon.com/dp/B0GMQD4M5N | L64: =IF(K64="","",HYPERLINK(K64,K64)) -> https://amazon.com/dp/B0GMQD4M5N
... A601: Autel MaxiTPMS TS900 Kit(4PCS MX Sensors Valued $120) TPMS Programming Tool Scanner All System Diagnosis Full TPMS 40+Services CAN FD/DoIP Compatible 315/433/434MHz Autel Sensors | B601: B0CP25139M | C601: Tablet | D601: 920 | E601: 0 | F601: 0 | G601: 0 | H601: 0 | I601: 3 | J601: 5 | K601: https://amazon.com/dp/B0CP25139M | L601: =IF(K601="","",HYPERLINK(K601,K601)) -> https://amazon.com/dp/B0CP25139M
A602: Total | E602: =SUM(E53:E601) -> 74667063 | F602: =SUM(F53:F601) -> 5379094.3
A604: Rank by Units
A605: Product Name | B605: ASIN | C605: Type | D605: Avg Price | E605: Estimated 12mo Revenue | F605: Monthly Rev | G605: Estimated 12mo Units | H605: Monthly Units | I605: # of Reviews | J605: Tool Rating | K605: Column1 | L605: Link
A606: Autel AL319 Professional OBD2 Scanner, Enhanced Check Engine Code Reader | B606: B007XE8C74 | C606: Handheld | D606: 33.609584 | E606: 1124462.2 | F606: 77503.7 | G606: 33473 | H606: 2306 | I606: 26046 | J606: 4.6 | K606: https://amazon.com/dp/B007XE8C74 | L606: =IF(K606="","",HYPERLINK(K606,K606)) -> https://amazon.com/dp/B007XE8C74
A607: Autel MaxiAP AP200 OBD2 Scanner Bluetooth, Wireless OBD II Diagnostic Tool | B607: B07QD4GZW4 | C607: Dongle | D607: 68.968703 | E607: 601179.53 | F607: 69106.64 | G607: 9258 | H607: 1002 | I607: 3238 | J607: 4.1 | K607: https://amazon.com/dp/B07QD4GZW4 | L607: =IF(K607="","",HYPERLINK(K607,K607)) -> https://amazon.com/dp/B07QD4GZW4
A608: Autel OBD2 Scanner MS309 Universal Car Engine Fault Code Reader, Check Engine Light and Emission Monitor Status, OBDII CAN Diagnostic Scan Tool | B608: B07Q5H7M5S | C608: Handheld | D608: 22.307551 | E608: 335476.05 | F608: 18760.65 | G608: 14798 | H608: 841 | I608: 17172 | J608: 4.6 | K608: https://amazon.com/dp/B07Q5H7M5S | L608: =IF(K608="","",HYPERLINK(K608,K608)) -> https://amazon.com/dp/B07Q5H7M5S
A609: OBD2 12+8 Adapter for Chrysler, 12 8 OBD II Security Gateway Bypass Cable | B609: B0BJQKK2TJ | C609: Cable/Adapter | D609: 25.98708 | E609: 236893.46 | F609: 18242.93 | G609: 9187 | H609: 702 | I609: 593 | J609: 4.7 | K609: https://amazon.com/dp/B0BJQKK2TJ | L609: =IF(K609="","",HYPERLINK(K609,K609)) -> https://amazon.com/dp/B0BJQKK2TJ
A610: Autel Scanner MaxiCOM MK900BT Bidirectional Tool, 40+ Service, CAN-FD& DOIP | B610: B098PYB8XG | C610: Tablet | D610: 658.71861 | E610: 6217858.7 | F610: 425532.22 | G610: 9435 | H610: 646 | I610: 778 | J610: 4.6 | K610: https://amazon.com/dp/B098PYB8XG | L610: =IF(K610="","",HYPERLINK(K610,K610)) -> https://amazon.com/dp/B098PYB8XG
A611: Autel Scanner MaxiCOM MK808S: 3000+ Active Tests 28+ Service as MK900-BT | B611: B0GX1WPD31 | C611: Tablet | D611: 468.70797 | E611: 2839883.1 | F611: 284505.74 | G611: 1016 | H611: 607 | I611: 381 | J611: 4.4 | K611: https://amazon.com/dp/B0GX1WPD31 | L611: =IF(K611="","",HYPERLINK(K611,K611)) -> https://amazon.com/dp/B0GX1WPD31
A612: Autel Scanner MaxiCheck MX808S, Bidirectional OBD2 Scan Tool 28+ Service | B612: B08ML7T7KZ | C612: Tablet | D612: 430.55856 | E612: 3403035.4 | F612: 248432.29 | G612: 7875 | H612: 577 | I612: 756 | J612: 4.6 | K612: https://amazon.com/dp/B08ML7T7KZ | L612: =IF(K612="","",HYPERLINK(K612,K612)) -> https://amazon.com/dp/B08ML7T7KZ
A613: Autel Scanner MaxiCOM MK808S Bidirectional Tool, 28+ Hot Service All System | B613: B0744B55QV | C613: Tablet | D613: 457.87741 | E613: 6541456.9 | F613: 263737.39 | G613: 13852 | H613: 576 | I613: 3903 | J613: 4.4 | K613: https://amazon.com/dp/B0744B55QV | L613: =IF(K613="","",HYPERLINK(K613,K613)) -> https://amazon.com/dp/B0744B55QV
A614: Autel OBD2 Scanner AL329, Vehicle Check Engine Code Reader | B614: B0BHNRPZXR | C614: Handheld | D614: 34.78834 | E614: 170635.85 | F614: 17394.17 | G614: 4934 | H614: 500 | I614: 174 | J614: 4.6 | K614: https://amazon.com/dp/B0BHNRPZXR | L614: =IF(K614="","",HYPERLINK(K614,K614)) -> https://amazon.com/dp/B0BHNRPZXR
A615: Autel PowerScan PS100 Circuit Tester 2.0, 12-24V Power Circuit Probe Tool | B615: B0BW48DKFG | C615: Probe | D615: 89.929838 | E615: 491216.2 | F615: 44425.34 | G615: 5004 | H615: 494 | I615: 406 | J615: 4.7 | K615: https://amazon.com/dp/B0BW48DKFG | L615: =IF(K615="","",HYPERLINK(K615,K615)) -> https://amazon.com/dp/B0BW48DKFG
A616: Autel Scanner MaxiCOM MK900BT, 2026 MK900-BT 8in V2.0 Bidirectional Tool | B616: B09712X5CW | C616: Tablet | D616: 659.4073 | E616: 2016560.4 | F616: 222220.26 | G616: 3060 | H616: 337 | I616: 248 | J616: 4.6 | K616: https://amazon.com/dp/B09712X5CW | L616: =IF(K616="","",HYPERLINK(K616,K616)) -> https://amazon.com/dp/B09712X5CW
A617: Autel Scanner MaxiCOM MK900: 3000+ Active Tests 40+ Service as MK900-BT | B617: B073CQMF25 | C617: Tablet | D617: 588.2876 | E617: 2097346.7 | F617: 186487.17 | G617: 3700 | H617: 317 | I617: 606 | J617: 4.4 | K617: https://amazon.com/dp/B073CQMF25 | L617: =IF(K617="","",HYPERLINK(K617,K617)) -> https://amazon.com/dp/B073CQMF25
... A1154: Autel MaxiTPMS TS900 Kit(4PCS MX Sensors Valued $120) TPMS Programming Tool Scanner All System Diagnosis Full TPMS 40+Services CAN FD/DoIP Compatible 315/433/434MHz Autel Sensors | B1154: B0CP25139M | C1154: Tablet | D1154: 920 | E1154: 0 | F1154: 0 | G1154: 0 | H1154: 0 | I1154: 3 | J1154: 5 | K1154: https://amazon.com/dp/B0CP25139M | L1154: =IF(K1154="","",HYPERLINK(K1154,K1154)) -> https://amazon.com/dp/B0CP25139M
A1155: Total | G1155: =SUM(G606:G1154) -> 235999 | H1155: =SUM(H606:H1154) -> 19094

Sheet Foxwell
B7: Avg Price | C7: Avg Price MoM | D7: Avg Price YoY | E7: Quantity/Mo | F7: Qty by % | G7: Qty MoM | H7: Qty YoY | I7: Revenue/Mo | J7: Revenue by % | L7: Revenue MoM | M7: Revenue YoY
A8: Tablet $400-$800 | B8: 558.70964 | C8: -0.024197187 | D8: 0.085374621 | E8: 444 | F8: 0.030006082 | G8: -0.39010989 | H8: 0.49494949 | I8: 248067.08 | J8: 0.1197965 | L8: -0.40486752 | M8: 0.62258024
A9: Tablet $400- | B9: 197.28926 | C9: -0.026523972 | D9: 0.017417114 | E9: 4481 | F9: 0.30283166 | G9: -0.13959293 | H9: 0.38046827 | I9: 884053.18 | J9: 0.42692679 | L9: -0.16241435 | M9: 0.40451204
A10: Total Tablet | B10: 229.87213 | C10: -0.073207408 | D10: 0.0083007446 | E10: 4925 | F10: 0.33283774 | G10: -0.17031671 | H10: 0.37531416 | I10: 1132120.3 | J10: 0.54672329 | L10: -0.23105567 | M10: 0.38673029
A11: Handheld $75+ | B11: 157.31527 | C11: -0.01919401 | D11: 0.050930011 | E11: 3512 | F11: 0.23734541 | G11: -0.019542155 | H11: 0.19293478 | I11: 552491.24 | J11: 0.26680896 | L11: -0.038361073 | M11: 0.25369096
A12: Handheld $75- | B12: 62.20204 | C12: -0.023136963 | D12: -0.011896034 | E12: 6156 | F12: 0.41603028 | G12: -0.00016241676 | H12: -0.13087675 | I12: 382915.76 | J12: 0.1849176 | L12: -0.023295622 | M12: -0.14121587
A13: Total Handheld | B13: 96.752896 | C13: -0.025143489 | D13: 0.094259908 | E13: 9668 | F13: 0.65337568 | G13: -0.0072902762 | H13: -0.035803331 | I13: 935407 | J13: 0.45172656 | L13: -0.032250462 | M13: 0.055081759
A14: Total Other Tools | B14: 15.735049 | C14: -0.076147518 | D14: 0.030583691 | E14: 204 | F14: 0.013786578 | G14: -0.28671329 | H14: -0.45013477 | I14: 3209.95 | J14: 0.0015501484 | L14: -0.3410283 | M14: -0.43331786
A15: Total | B15: 139.94304 | C15: -0.085984248 | D15: 0.14492927 | E15: 14797 | F15: 1 | G15: -0.072927761 | H15: 0.058516346 | I15: 2070737.2 | J15: 1 | L15: -0.15264137 | M15: 0.21192635
A47: Rank by Revenue
A48: Product Name | B48: ASIN | C48: Type | D48: Avg Price | E48: Estimated 12mo Revenue | F48: Monthly Rev | G48: Estimated 12mo Units | H48: Monthly Units | I48: # of Reviews | J48: Tool Rating | K48: Column1 | L48: Link
A49: FOXWELL NT301 OBD2 Scanner Live Data Professional Mechanic OBDII Diagnostic Code Reader Tool for Check Engine Light | B49: B00UJV3E12 | C49: Handheld | D49: 64.043987 | E49: 5118816.4 | F49: 358198.02 | G49: 78367 | H49: 5593 | I49: 30049 | J49: 4.5 | K49: https://amazon.com/dp/B00UJV3E12 | L49: =IF(K49="","",HYPERLINK(K49,K49)) -> https://amazon.com/dp/B00UJV3E12
A50: FOXWELL Car Scanner NT604 Elite OBD2 Scanner ABS SRS Transmission | B50: B08PFJMTY3 | C50: Tablet | D50: 149.44571 | E50: 3742749.3 | F50: 290373.01 | G50: 23813 | H50: 1943 | I50: 5051 | J50: 4.4 | K50: https://amazon.com/dp/B08PFJMTY3 | L50: =IF(K50="","",HYPERLINK(K50,K50)) -> https://amazon.com/dp/B08PFJMTY3
A51: FOXWELL NT510 Elite Scan Tool fit for BMW Scanner Full Diagnostic Tool OBD2 Scanner, All System Bi-Directional Control Code Reader with All Reset Services, Battery Registration Tool fit for BMW Mini | B51: B019QCG5RE | C51: Handheld | D51: 177.72473 | E51: 1462286.8 | F51: 125118.21 | G51: 7910 | H51: 704 | I51: 3174 | J51: 4.3 | K51: https://amazon.com/dp/B019QCG5RE | L51: =IF(K51="","",HYPERLINK(K51,K51)) -> https://amazon.com/dp/B019QCG5RE
A52: 2026 FOXWELL NT614 Elite OBD2 Scanner, 4 Systems, 5 Resets Code Reader | B52: B08DCNDFVK | C52: Tablet | D52: 168.11133 | E52: 1484539.7 | F52: 125074.83 | G52: 8351 | H52: 744 | I52: 796 | J52: 4.3 | K52: https://amazon.com/dp/B08DCNDFVK | L52: =IF(K52="","",HYPERLINK(K52,K52)) -> https://amazon.com/dp/B08DCNDFVK
A53: 2026 FOXWELL NT726 OBD2 Scanner, 12Resets, All System Bidirectional Scanner | B53: B0F3XRK4P9 | C53: Tablet | D53: 342.43927 | E53: 892289.28 | F53: 121565.94 | G53: 2527 | H53: 355 | I53: 135 | J53: 4.4 | K53: https://amazon.com/dp/B0F3XRK4P9 | L53: =IF(K53="","",HYPERLINK(K53,K53)) -> https://amazon.com/dp/B0F3XRK4P9
A54: 2026 FOXWELL NT624 Elite OBD2 Scanner, All-System 8 Resets Code Reader | B54: B07X9JQSGZ | C54: Tablet | D54: 245.07175 | E54: 1037340.8 | F54: 91166.69 | G54: 4045 | H54: 372 | I54: 2372 | J54: 4.2 | K54: https://amazon.com/dp/B07X9JQSGZ | L54: =IF(K54="","",HYPERLINK(K54,K54)) -> https://amazon.com/dp/B07X9JQSGZ
A55: FOXWELL NT301 Plus 2-in-1 OBD2 Scanner & 12V Car Battery Tester | B55: B08JGK8PPM | C55: Handheld | D55: 90.973941 | E55: 1268357.6 | F55: 79875.12 | G55: 13520 | H55: 878 | I55: 2715 | J55: 4.5 | K55: https://amazon.com/dp/B08JGK8PPM | L55: =IF(K55="","",HYPERLINK(K55,K55)) -> https://amazon.com/dp/B08JGK8PPM
A56: FOXWELL HD500 Heavy Duty Truck Scanner - Diesel Scanner with DPF Regen/Injector Cutoff/Limit Setting, Full System Diesel Diagnostic Scan Tool for Cummins, Detroit, Caterpillar, Paccar & Pickup Trucks | B56: B0D7M4Q46L | C56: Tablet | D56: 561.12087 | E56: 901616.09 | F56: 77434.68 | G56: 1583 | H56: 138 | I56: 401 | J56: 4 | K56: https://amazon.com/dp/B0D7M4Q46L | L56: =IF(K56="","",HYPERLINK(K56,K56)) -> https://amazon.com/dp/B0D7M4Q46L
A57: FOXWELL NT510 Elite fit for Honda Acura OBD2 Scanner, Bidirectional Full System Engine ABS TCM SRS Diagnostic Scan Tool, All Reset Crankshaft Relearn Oil EPB TPS ABS Bleeding, Code Reader, Free Update | B57: B08B5RMFBG | C57: Handheld | D57: 189.7644 | E57: 549852.76 | F57: 72490 | G57: 2896 | H57: 382 | I57: 463 | J57: 4.2 | K57: https://amazon.com/dp/B08B5RMFBG | L57: =IF(K57="","",HYPERLINK(K57,K57)) -> https://amazon.com/dp/B08B5RMFBG
A58: FOXWELL NT630 Plus OBD2 Scanner with ABS and SRS, ABS Auto Bleed, 4 Resets | B58: B07CSMJJK9 | C58: Handheld | D58: 149.97574 | E58: 775769.77 | F58: 66889.18 | G58: 5276 | H58: 446 | I58: 3962 | J58: 4.2 | K58: https://amazon.com/dp/B07CSMJJK9 | L58: =IF(K58="","",HYPERLINK(K58,K58)) -> https://amazon.com/dp/B07CSMJJK9
A59: FOXWELL NT919BT All System Diagnostic Tool - Automotive Bidirectional Scan Tool, 3000+ Active Tests, 34 Maintenances, ECU Coding, CAN FD & DoIP, Lifetime Free Update, Car OBD2 Scanner for 140+ Brands | B59: B0GX22P774 | C59: Tablet | D59: 696.66775 | E59: 735083.55 | F59: 62003.43 | G59: 225 | H59: 89 | I59: 48 | J59: 4.8 | K59: https://amazon.com/dp/B0GX22P774 | L59: =IF(K59="","",HYPERLINK(K59,K59)) -> https://amazon.com/dp/B0GX22P774
A60: FOXWELL NT630 Pro 2-in-1 OBD2 Scanner, ABS/SRS & Battery Tester, 5 Resets | B60: B0DDQ6MX9M | C60: Handheld | D60: 193.3157 | E60: 377370.31 | F60: 52581.87 | G60: 1949 | H60: 272 | I60: 150 | J60: 4.4 | K60: https://amazon.com/dp/B0DDQ6MX9M | L60: =IF(K60="","",HYPERLINK(K60,K60)) -> https://amazon.com/dp/B0DDQ6MX9M
... A103: FOXWELL NT630 Plus ABS SRS Airbag Bleed Scanner with FOXWELL BT100 Pro 12V Car Battery Tester | B103: B08HV27Q3M | C103: Handheld | D103: 159.99 | E103: 0 | F103: 0 | G103: 0 | H103: 0 | I103: 2 | J103: 3 | K103: https://amazon.com/dp/B08HV27Q3M | L103: =IF(K103="","",HYPERLINK(K103,K103)) -> https://amazon.com/dp/B08HV27Q3M
A104: Total | E104: =SUM(E49:E103) -> 25496113 | F104: =SUM(F49:F103) -> 2070737.2
A106: Rank by Units
A107: Product Name | B107: ASIN | C107: Type | D107: Avg Price | E107: Estimated 12mo Revenue | F107: Monthly Rev | G107: Estimated 12mo Units | H107: Monthly Units | I107: # of Reviews | J107: Tool Rating | K107: Column1 | L107: Link
A108: FOXWELL NT301 OBD2 Scanner Live Data Professional Mechanic OBDII Diagnostic Code Reader Tool for Check Engine Light | B108: B00UJV3E12 | C108: Handheld | D108: 64.043987 | E108: 5118816.4 | F108: 358198.02 | G108: 78367 | H108: 5593 | I108: 30049 | J108: 4.5 | K108: https://amazon.com/dp/B00UJV3E12 | L108: =IF(K108="","",HYPERLINK(K108,K108)) -> https://amazon.com/dp/B00UJV3E12
A109: FOXWELL Car Scanner NT604 Elite OBD2 Scanner ABS SRS Transmission | B109: B08PFJMTY3 | C109: Tablet | D109: 149.44571 | E109: 3742749.3 | F109: 290373.01 | G109: 23813 | H109: 1943 | I109: 5051 | J109: 4.4 | K109: https://amazon.com/dp/B08PFJMTY3 | L109: =IF(K109="","",HYPERLINK(K109,K109)) -> https://amazon.com/dp/B08PFJMTY3
A110: FOXWELL NT301 Plus 2-in-1 OBD2 Scanner & 12V Car Battery Tester | B110: B08JGK8PPM | C110: Handheld | D110: 90.973941 | E110: 1268357.6 | F110: 79875.12 | G110: 13520 | H110: 878 | I110: 2715 | J110: 4.5 | K110: https://amazon.com/dp/B08JGK8PPM | L110: =IF(K110="","",HYPERLINK(K110,K110)) -> https://amazon.com/dp/B08JGK8PPM
A111: 2026 FOXWELL NT614 Elite OBD2 Scanner, 4 Systems, 5 Resets Code Reader | B111: B08DCNDFVK | C111: Tablet | D111: 168.11133 | E111: 1484539.7 | F111: 125074.83 | G111: 8351 | H111: 744 | I111: 796 | J111: 4.3 | K111: https://amazon.com/dp/B08DCNDFVK | L111: =IF(K111="","",HYPERLINK(K111,K111)) -> https://amazon.com/dp/B08DCNDFVK
A112: FOXWELL NT510 Elite Scan Tool fit for BMW Scanner Full Diagnostic Tool OBD2 Scanner, All System Bi-Directional Control Code Reader with All Reset Services, Battery Registration Tool fit for BMW Mini | B112: B019QCG5RE | C112: Handheld | D112: 177.72473 | E112: 1462286.8 | F112: 125118.21 | G112: 7910 | H112: 704 | I112: 3174 | J112: 4.3 | K112: https://amazon.com/dp/B019QCG5RE | L112: =IF(K112="","",HYPERLINK(K112,K112)) -> https://amazon.com/dp/B019QCG5RE
A113: FOXWELL NT201 OBD2 Scanner Code Reader for Cars and Trucks - Reset Check Engine Light, Read and Clear Fault Codes, Live Data Diagnostic Tool for All Cars Since 1996 | B113: B01N6RKE29 | C113: Handheld | D113: 43.903623 | E113: 556163.11 | F113: 24717.74 | G113: 12166 | H113: 563 | I113: 10024 | J113: 4.5 | K113: https://amazon.com/dp/B01N6RKE29 | L113: =IF(K113="","",HYPERLINK(K113,K113)) -> https://amazon.com/dp/B01N6RKE29
A114: FOXWELL NT630 Plus OBD2 Scanner with ABS and SRS, ABS Auto Bleed, 4 Resets | B114: B07CSMJJK9 | C114: Handheld | D114: 149.97574 | E114: 775769.77 | F114: 66889.18 | G114: 5276 | H114: 446 | I114: 3962 | J114: 4.2 | K114: https://amazon.com/dp/B07CSMJJK9 | L114: =IF(K114="","",HYPERLINK(K114,K114)) -> https://amazon.com/dp/B07CSMJJK9
A115: FOXWELL NT510 Elite fit for Honda Acura OBD2 Scanner, Bidirectional Full System Engine ABS TCM SRS Diagnostic Scan Tool, All Reset Crankshaft Relearn Oil EPB TPS ABS Bleeding, Code Reader, Free Update | B115: B08B5RMFBG | C115: Handheld | D115: 189.7644 | E115: 549852.76 | F115: 72490 | G115: 2896 | H115: 382 | I115: 463 | J115: 4.2 | K115: https://amazon.com/dp/B08B5RMFBG | L115: =IF(K115="","",HYPERLINK(K115,K115)) -> https://amazon.com/dp/B08B5RMFBG
A116: 2026 FOXWELL NT624 Elite OBD2 Scanner, All-System 8 Resets Code Reader | B116: B07X9JQSGZ | C116: Tablet | D116: 245.07175 | E116: 1037340.8 | F116: 91166.69 | G116: 4045 | H116: 372 | I116: 2372 | J116: 4.2 | K116: https://amazon.com/dp/B07X9JQSGZ | L116: =IF(K116="","",HYPERLINK(K116,K116)) -> https://amazon.com/dp/B07X9JQSGZ
A117: 2026 FOXWELL NT726 OBD2 Scanner, 12Resets, All System Bidirectional Scanner | B117: B0F3XRK4P9 | C117: Tablet | D117: 342.43927 | E117: 892289.28 | F117: 121565.94 | G117: 2527 | H117: 355 | I117: 135 | J117: 4.4 | K117: https://amazon.com/dp/B0F3XRK4P9 | L117: =IF(K117="","",HYPERLINK(K117,K117)) -> https://amazon.com/dp/B0F3XRK4P9
A118: FOXWELL NT510 Elite fit for GM OBD2 Scanner, Bi-Directional All System Engine ABS SRS Diagnostic Scan Tool Code Reader for Chevrolet Cadillac GMC, All Reset Oil EPB TPS ABS Bleeding Crankshaft Relearn | B118: B014CT4M3K | C118: Handheld | D118: 181.63035 | E118: 381907.82 | F118: 51946.28 | G118: 2038 | H118: 286 | I118: 584 | J118: 4.1 | K118: https://amazon.com/dp/B014CT4M3K | L118: =IF(K118="","",HYPERLINK(K118,K118)) -> https://amazon.com/dp/B014CT4M3K
A119: FOXWELL NT630 Pro 2-in-1 OBD2 Scanner, ABS/SRS & Battery Tester, 5 Resets | B119: B0DDQ6MX9M | C119: Handheld | D119: 193.3157 | E119: 377370.31 | F119: 52581.87 | G119: 1949 | H119: 272 | I119: 150 | J119: 4.4 | K119: https://amazon.com/dp/B0DDQ6MX9M | L119: =IF(K119="","",HYPERLINK(K119,K119)) -> https://amazon.com/dp/B0DDQ6MX9M
... A162: FOXWELL NT630 Plus ABS SRS Airbag Bleed Scanner with FOXWELL BT100 Pro 12V Car Battery Tester | B162: B08HV27Q3M | C162: Handheld | D162: 159.99 | E162: 0 | F162: 0 | G162: 0 | H162: 0 | I162: 2 | J162: 3 | K162: https://amazon.com/dp/B08HV27Q3M | L162: =IF(K162="","",HYPERLINK(K162,K162)) -> https://amazon.com/dp/B08HV27Q3M
A163: Total | G163: =SUM(G108:G162) -> 189941 | H163: =SUM(H108:H162) -> 14797

Sheet iCarsoft
B7: Avg Price | C7: Avg Price MoM | D7: Avg Price YoY | E7: Quantity/Mo | F7: Qty by % | G7: Qty MoM | H7: Qty YoY | I7: Revenue/Mo | J7: Revenue by % | L7: Revenue MoM | M7: Revenue YoY
A8: Tablet $800+ | B8: 1549.6975 | C8: 0.058989363 | E8: 4 | F8: 0.0016025641 | G8: -0.2 | I8: 6198.79 | J8: 0.011843655 | L8: -0.15280851
A9: Tablet $400-$800 | B9: 486.31706 | C9: 0.082015016 | D9: -0.013548884 | E9: 51 | F9: 0.020432692 | G9: -0.055555556 | H9: -0.17741935 | I9: 24802.17 | J9: 0.047388013 | L9: 0.02190307 | M9: -0.1885644
A10: Tablet $400- | B10: 204.08907 | C10: 0.006354074 | D10: 0.0044221043 | E10: 1882 | F10: 0.75400641 | G10: -0.16578014 | H10: 0.093550261 | I10: 384095.63 | J10: 0.7338684 | L10: -0.16047945 | M10: 0.098386055
A11: Total Tablet | B11: 214.2987 | C11: 0.014304119 | D11: 0.00483326 | E11: 1937 | F11: 0.77604167 | G11: -0.16328294 | H11: 0.086371284 | I11: 415096.59 | J11: 0.79310006 | L11: -0.15131444 | M11: 0.091621999
A12: Handheld $75+ | B12: 209.8176 | C12: 0.091712351 | D12: 0.66137507 | E12: 501 | F12: 0.20072115 | G12: -0.2022293 | H12: 2.34 | I12: 105118.62 | J12: 0.20084382 | L12: -0.12906387 | M12: 4.5489927
A13: Handheld $75- | B13: 33.516667 | C13: -0.5165633 | D13: -0.45443694 | E13: 6 | F13: 0.0024038462 | G13: 5 | H13: 2 | I13: 201.1 | J13: 0.00038422966 | L13: 1.9006202 | M13: 0.63668918
A14: Total Handheld | B14: 207.7312 | C14: 0.081956106 | D14: 0.65604475 | E14: 507 | F14: 0.203125 | G14: -0.19395866 | H14: 2.3355263 | I14: 105319.72 | J14: 0.20122805 | L14: -0.12789866 | M14: 4.5237809
A15: Total Other Tools | B15: 57.088077 | C15: 0.035527883 | D15: -0.033015532 | E15: 52 | F15: 0.020833333 | G15: -0.037037037 | H15: 0.44444444 | I15: 2968.58 | J15: 0.0056718871 | L15: -0.0028250011 | M15: 0.39675534
A16: Total | B16: 209.68946 | C16: 0.025783352 | D16: 0.029516288 | E16: 2496 | F16: 1 | G16: -0.16744496 | H16: 0.26636225 | I16: 523384.89 | J16: 1 | L16: -0.1459789 | M16: 0.30374057
A51: Rank by Revenue
A52: Product Name | B52: ASIN | C52: Type | D52: Avg Price | E52: Estimated 12mo Revenue | F52: Monthly Rev | G52: Estimated 12mo Units | H52: Monthly Units | I52: # of Reviews | J52: Tool Rating | K52: Column1 | L52: Link
A53: iCarsoft Bidirectional Diagnostic Tool for Most Mercedes-Benz/Sprinter/Smart from 1996-2025 MB V3.0 2026 Version Up to 39 Service Full System OBD2 Scanner All Test AutoVIN Battery Test Free Update | B53: B0D3DQQK1S | C53: Tablet | D53: 220.08843 | E53: 807245.11 | F53: 109604.04 | G53: 3706 | H53: 498 | I53: 189 | J53: 3.8 | K53: https://amazon.com/dp/B0D3DQQK1S | L53: =IF(K53="","",HYPERLINK(K53,K53)) -> https://amazon.com/dp/B0D3DQQK1S
A54: iCarsoft MB V4.0 Full System Bidirectional Diagnostic Scan Tool for Most Benz/Sprinter/Smart/Maybach Free 2 Further Vehicle Groups Lifetime Free Update Up to 41 Resets Automotive Active Test Scanner | B54: B0G4MR79SY | C54: Handheld | D54: 268.96678 | E54: 431231.24 | F54: 47607.12 | G54: 459 | H54: 177 | I54: 35 | J54: 4 | K54: https://amazon.com/dp/B0G4MR79SY | L54: =IF(K54="","",HYPERLINK(K54,K54)) -> https://amazon.com/dp/B0G4MR79SY
A55: iCarsoft POR V4.0 Bidirectional Diagnostic Tool for Porsche + 2 Car Make Groups, OBD2 Scanner with Actuation Test, 28 Services Battery Registration,Support CAN-FD-Free Update | B55: B0G4M5G2CR | C55: Tablet | D55: 269.59867 | E55: 341463.6 | F55: 28307.86 | G55: 684 | H55: 105 | I55: 12 | J55: 4.9 | K55: https://amazon.com/dp/B0G4M5G2CR | L55: =IF(K55="","",HYPERLINK(K55,K55)) -> https://amazon.com/dp/B0G4M5G2CR
A56: Bidirectional Diagnostic Tool for Porsche/Cayenne, iCarsoft POR V3.0 All System OBD2 Scanner, 26 Resets +12 Extra Services Battery Registration Code Reader for Porsche,Support CAN-FD, Free Update | B56: B0D3DPDV86 | C56: Tablet | D56: 190.31504 | E56: 399096.99 | F56: 25692.53 | G56: 1970 | H56: 135 | I56: 796 | J56: 4.1 | K56: https://amazon.com/dp/B0D3DPDV86 | L56: =IF(K56="","",HYPERLINK(K56,K56)) -> https://amazon.com/dp/B0D3DPDV86
A57: iCarsoft M900 V2.0 Full Systems Diagnostic Scan Tool for Mercedes Benz/Sprinter/Smart/Maybach from 1996–Present OBD2 Scanner Code Reader 9 Resets Battery Test CAN-FD AUTOVIN Lifetime Free Update | B57: B07BFPKLMY | C57: Tablet | D57: 149.55975 | E57: 128618.09 | F57: 23780 | G57: 857 | H57: 159 | I57: 125 | J57: 4.2 | K57: https://amazon.com/dp/B07BFPKLMY | L57: =IF(K57="","",HYPERLINK(K57,K57)) -> https://amazon.com/dp/B07BFPKLMY
A58: iCarsoft LR V3.0 2026 Version Bidirectional OBD2 Scanner for Most Land Rover/Jaguar from 1996-2025 Full Systems 36 Services Diagnostic Scan Tool Graphic Data Car Code Reader with Lifetime Free Update | B58: B0FZ8JJY1T | C58: Tablet | D58: 189.3971 | E58: 148181.85 | F58: 17613.93 | G58: 319 | H58: 93 | I58: 7 | J58: 3.4 | K58: https://amazon.com/dp/B0FZ8JJY1T | L58: =IF(K58="","",HYPERLINK(K58,K58)) -> https://amazon.com/dp/B0FZ8JJY1T
A59: iCarsoft Bidirectional Scan Tool CR Max OBD2 Diagnostic Scanner for Most Vehicles Full System 50 Resets All Active Tests ECU Coding Battery Registration Lifetime Free Updates CAN FD Supported | B59: B0D1BJTGLL | C59: Tablet | D59: 369.9425 | E59: 146214.69 | F59: 11838.16 | G59: 394 | H59: 32 | I59: 239 | J59: 4.2 | K59: https://amazon.com/dp/B0D1BJTGLL | L59: =IF(K59="","",HYPERLINK(K59,K59)) -> https://amazon.com/dp/B0D1BJTGLL
A60: iCarsoft P700 V2.0 Diagnostic Scanner for Porsche from 1996 to 2025 9 Essential Services Full System Diagnosis Scan OBD2 Code Reader Battery/O2 Sensor/EVAP Test AutoVIN Lifetime Free Software Update | B60: B07FP9QJLN | C60: Tablet | D60: 148.57949 | E60: 149601.63 | F60: 11737.78 | G60: 1004 | H60: 79 | I60: 208 | J60: 4.2 | K60: https://amazon.com/dp/B07FP9QJLN | L60: =IF(K60="","",HYPERLINK(K60,K60)) -> https://amazon.com/dp/B07FP9QJLN
A61: iCarsoft POR V4.0 Bidirectional Diagnostic Tool for Porsche, All System Full Active Tests 27 Services OBD2 Scanner for Porsche, Code Reader, Auto VIN | B61: B0FKN6LJRN | C61: Tablet | D61: 248.93109 | E61: 118577.5 | F61: 11450.83 | G61: 330 | H61: 46 | I61: 17 | J61: 3.6 | K61: https://amazon.com/dp/B0FKN6LJRN | L61: =IF(K61="","",HYPERLINK(K61,K61)) -> https://amazon.com/dp/B0FKN6LJRN
A62: iCarsoft LR V4.0 Full System Bidirectional Diagnostic Scan Tool for Most Land Rover and Jaguar Free 2 Further Vehicle Groups Lifetime Free Update Up to 38 Resets Automotive Active Test Scanner CAN FD | B62: B0GC526PYX | C62: Handheld | D62: 271.40154 | E62: 102672.24 | F62: 10584.66 | G62: 91 | H62: 39 | I62: 4 | J62: 3 | K62: https://amazon.com/dp/B0GC526PYX | L62: =IF(K62="","",HYPERLINK(K62,K62)) -> https://amazon.com/dp/B0GC526PYX
A63: iCarsoft MT V6 Motorcycle Diagnostic Scan Tool for Harley, 57 Reset Services, 43 Actuation Test, Battery Test, All Motorbike System Diagnose, Read/Clear Codes, Live Data,Also Car OBD2 Diagnose | B63: B0FRFFNCZ9 | C63: Tablet | D63: 217.83766 | E63: 100654.49 | F63: 10238.37 | G63: 157 | H63: 47 | I63: 5 | J63: 5 | K63: https://amazon.com/dp/B0FRFFNCZ9 | L63: =IF(K63="","",HYPERLINK(K63,K63)) -> https://amazon.com/dp/B0FRFFNCZ9
A64: iCarsoft CR MAX P Bidirectional Scan Tools 10-inch Full Systems Diagnostic Tool Up to 50 Services All Active Test OBD2 Scanner ECU Coding AutoVIN CAN FD/DoIP Lifetime Free Update for 10000+ Cars | B64: B0GLFPC298 | C64: Tablet | D64: 574.91562 | E64: 90299.852 | F64: 9198.65 | G64: 37 | H64: 16 | I64: 1 | J64: 4 | K64: https://amazon.com/dp/B0GLFPC298 | L64: =IF(K64="","",HYPERLINK(K64,K64)) -> https://amazon.com/dp/B0GLFPC298
... A234: iCarsoft i900 OBD2 Scanner for US Brand Vehicles, All System in-Depth Diagnostic Scan Tool for Ford/Jeep/Chevrolet/Cadillac, Oil Reset/Steering Angle Reset, Live Data OBDII Engine Code Reader | B234: B0F62YNX9J | C234: Tablet | D234: 109 | E234: 633.93 | F234: 0 | G234: 5 | H234: 0 | I234: 0 | J234: 0 | K234: https://amazon.com/dp/B0F62YNX9J | L234: =IF(K234="","",HYPERLINK(K234,K234)) -> https://amazon.com/dp/B0F62YNX9J
A235: Total | E235: =SUM(E53:E234) -> 6757337 | F235: =SUM(F53:F234) -> 523384.89
A237: Rank by Units
A238: Product Name | B238: ASIN | C238: Type | D238: Avg Price | E238: Estimated 12mo Revenue | F238: Monthly Rev | G238: Estimated 12mo Units | H238: Monthly Units | I238: # of Reviews | J238: Tool Rating | K238: Column1 | L238: Link
A239: iCarsoft Bidirectional Diagnostic Tool for Most Mercedes-Benz/Sprinter/Smart from 1996-2025 MB V3.0 2026 Version Up to 39 Service Full System OBD2 Scanner All Test AutoVIN Battery Test Free Update | B239: B0D3DQQK1S | C239: Tablet | D239: 220.08843 | E239: 807245.11 | F239: 109604.04 | G239: 3706 | H239: 498 | I239: 189 | J239: 3.8 | K239: https://amazon.com/dp/B0D3DQQK1S | L239: =IF(K239="","",HYPERLINK(K239,K239)) -> https://amazon.com/dp/B0D3DQQK1S
A240: iCarsoft MB V4.0 Full System Bidirectional Diagnostic Scan Tool for Most Benz/Sprinter/Smart/Maybach Free 2 Further Vehicle Groups Lifetime Free Update Up to 41 Resets Automotive Active Test Scanner | B240: B0G4MR79SY | C240: Handheld | D240: 268.96678 | E240: 431231.24 | F240: 47607.12 | G240: 459 | H240: 177 | I240: 35 | J240: 4 | K240: https://amazon.com/dp/B0G4MR79SY | L240: =IF(K240="","",HYPERLINK(K240,K240)) -> https://amazon.com/dp/B0G4MR79SY
A241: iCarsoft M900 V2.0 Full Systems Diagnostic Scan Tool for Mercedes Benz/Sprinter/Smart/Maybach from 1996–Present OBD2 Scanner Code Reader 9 Resets Battery Test CAN-FD AUTOVIN Lifetime Free Update | B241: B07BFPKLMY | C241: Tablet | D241: 149.55975 | E241: 128618.09 | F241: 23780 | G241: 857 | H241: 159 | I241: 125 | J241: 4.2 | K241: https://amazon.com/dp/B07BFPKLMY | L241: =IF(K241="","",HYPERLINK(K241,K241)) -> https://amazon.com/dp/B07BFPKLMY
A242: Bidirectional Diagnostic Tool for Porsche/Cayenne, iCarsoft POR V3.0 All System OBD2 Scanner, 26 Resets +12 Extra Services Battery Registration Code Reader for Porsche,Support CAN-FD, Free Update | B242: B0D3DPDV86 | C242: Tablet | D242: 190.31504 | E242: 399096.99 | F242: 25692.53 | G242: 1970 | H242: 135 | I242: 796 | J242: 4.1 | K242: https://amazon.com/dp/B0D3DPDV86 | L242: =IF(K242="","",HYPERLINK(K242,K242)) -> https://amazon.com/dp/B0D3DPDV86
A243: iCarsoft POR V4.0 Bidirectional Diagnostic Tool for Porsche + 2 Car Make Groups, OBD2 Scanner with Actuation Test, 28 Services Battery Registration,Support CAN-FD-Free Update | B243: B0G4M5G2CR | C243: Tablet | D243: 269.59867 | E243: 341463.6 | F243: 28307.86 | G243: 684 | H243: 105 | I243: 12 | J243: 4.9 | K243: https://amazon.com/dp/B0G4M5G2CR | L243: =IF(K243="","",HYPERLINK(K243,K243)) -> https://amazon.com/dp/B0G4M5G2CR
A244: iCarsoft LR V3.0 2026 Version Bidirectional OBD2 Scanner for Most Land Rover/Jaguar from 1996-2025 Full Systems 36 Services Diagnostic Scan Tool Graphic Data Car Code Reader with Lifetime Free Update | B244: B0FZ8JJY1T | C244: Tablet | D244: 189.3971 | E244: 148181.85 | F244: 17613.93 | G244: 319 | H244: 93 | I244: 7 | J244: 3.4 | K244: https://amazon.com/dp/B0FZ8JJY1T | L244: =IF(K244="","",HYPERLINK(K244,K244)) -> https://amazon.com/dp/B0FZ8JJY1T
A245: iCarsoft P700 V2.0 Diagnostic Scanner for Porsche from 1996 to 2025 9 Essential Services Full System Diagnosis Scan OBD2 Code Reader Battery/O2 Sensor/EVAP Test AutoVIN Lifetime Free Software Update | B245: B07FP9QJLN | C245: Tablet | D245: 148.57949 | E245: 149601.63 | F245: 11737.78 | G245: 1004 | H245: 79 | I245: 208 | J245: 4.2 | K245: https://amazon.com/dp/B07FP9QJLN | L245: =IF(K245="","",HYPERLINK(K245,K245)) -> https://amazon.com/dp/B07FP9QJLN
A246: iCarsoft Auto Diagnostic Scanner POR V2.0 | B246: B07F2WF96Y | C246: Tablet | D246: 114.6505 | E246: 192680.74 | F246: 6879.03 | G246: 1496 | H246: 60 | I246: 797 | J246: 4.1 | K246: https://amazon.com/dp/B07F2WF96Y | L246: =IF(K246="","",HYPERLINK(K246,K246)) -> https://amazon.com/dp/B07F2WF96Y
A247: iCarsoft E660 2026 Version 4 Systems OBD2 Scanner, ABS SRS Engine Transmission Car Code Reader with 6 Reset Service Clear Fault Codes Battery Test Diagnostic Scan Tools Lifetime Free Upgrade | B247: B0F9FP9KPH | C247: Handheld | D247: 139.51434 | E247: 128013.09 | F247: 7394.26 | G247: 933 | H247: 53 | I247: 484 | J247: 4.3 | K247: https://amazon.com/dp/B0F9FP9KPH | L247: =IF(K247="","",HYPERLINK(K247,K247)) -> https://amazon.com/dp/B0F9FP9KPH
A248: Bidirectional Diagnostic Tool for Porsche/BMW, iCarsoft POR V3.0 (Enhanced Ver) All System OBD2 Scanner Code Reader for Porsche, for BMW, Auto VIN | B248: B0DWFQ69VV | C248: Handheld | D248: 169.84 | E248: 48851.64 | F248: 8831.68 | G248: 278 | H248: 52 | I248: 10 | J248: 4.3 | K248: https://amazon.com/dp/B0DWFQ69VV | L248: =IF(K248="","",HYPERLINK(K248,K248)) -> https://amazon.com/dp/B0DWFQ69VV
A249: iCarsoft MB V2.0 Full System Diagnostic Scan Tool for Most Mercedes Benz from 1996-Present OBD2 Scanner 9 Reset AutoVIN Free Update Car Code Reader with Battery Test CAN FD 15 Languages Plug-and-Play | B249: B0DX2BSRYM | C249: Tablet | D249: 145.9498 | E249: 187549.42 | F249: 7443.44 | G249: 1212 | H249: 51 | I249: 39 | J249: 3.9 | K249: https://amazon.com/dp/B0DX2BSRYM | L249: =IF(K249="","",HYPERLINK(K249,K249)) -> https://amazon.com/dp/B0DX2BSRYM
A250: iCarsoft MB V3.0 Bidirectional Diagnostic Tool for Mercedes-Benz/Sprinter/Smart/Maybach 39 Service All Systems OBD2 Scanner Quick Scan Battery Test Full Actuation Test Auto VIN Free Lifetime Update | B250: B0FBWTJ9S4 | C250: Tablet | D250: 190.59702 | E250: 90604.33 | F250: 8958.06 | G250: 456 | H250: 47 | I250: 24 | J250: 4.1 | K250: https://amazon.com/dp/B0FBWTJ9S4 | L250: =IF(K250="","",HYPERLINK(K250,K250)) -> https://amazon.com/dp/B0FBWTJ9S4
... A420: iCarsoft i900 OBD2 Scanner for US Brand Vehicles, All System in-Depth Diagnostic Scan Tool for Ford/Jeep/Chevrolet/Cadillac, Oil Reset/Steering Angle Reset, Live Data OBDII Engine Code Reader | B420: B0F62YNX9J | C420: Tablet | D420: 109 | E420: 633.93 | F420: 0 | G420: 5 | H420: 0 | I420: 0 | J420: 0 | K420: https://amazon.com/dp/B0F62YNX9J | L420: =IF(K420="","",HYPERLINK(K420,K420)) -> https://amazon.com/dp/B0F62YNX9J
A421: Total | G421: =SUM(G239:G420) -> 27617 | H421: =SUM(H239:H420) -> 2496

Sheet LAUNCH
B7: Avg Price | C7: Avg Price MoM | D7: Avg Price YoY | E7: Quantity/Mo | F7: Qty by % | G7: Qty MoM | H7: Qty YoY | I7: Revenue/Mo | J7: Revenue by % | L7: Revenue MoM | M7: Revenue YoY
A8: Tablet $800+ | B8: 1289.4599 | C8: 0.033920138 | D8: -0.013875621 | E8: 703 | F8: 0.12451293 | G8: -0.30943026 | H8: -0.14580802 | I8: 906490.33 | J8: 0.42851921 | L8: -0.28600603 | M8: -0.15766046
A9: Tablet $400-$800 | B9: 554.10393 | C9: -0.038343847 | D9: 0.0027720742 | E9: 1307 | F9: 0.23149132 | G9: -0.34747878 | H9: -0.16164208 | I9: 724213.84 | J9: 0.34235285 | L9: -0.37249896 | M9: -0.15931809
A10: Tablet $400- | B10: 186.20196 | C10: -0.036622572 | D10: 0.057537918 | E10: 2290 | F10: 0.40559688 | G10: -0.080321285 | H10: -0.47621226 | I10: 426402.49 | J10: 0.20157044 | L10: -0.11400229 | M10: -0.4460746
A11: Total Tablet | B11: 478.3969 | C11: -0.092444713 | D11: 0.1934296 | E11: 4300 | F11: 0.76160113 | G11: -0.21974233 | H11: -0.36334024 | I11: 2057106.7 | J11: 0.9724425 | L11: -0.29187303 | M11: -0.2401914
A12: Handheld $75+ | B12: 118.14784 | C12: -0.2158145 | D12: -0.18161023 | E12: 51 | F12: 0.0090329437 | G12: -0.89352818 | H12: -0.93772894 | I12: 6025.54 | J12: 0.0028484139 | L12: -0.91650635 | M12: -0.949038
A13: Handheld $75- | B13: 31.558841 | C13: 0.019747782 | D13: -0.018426323 | E13: 759 | F13: 0.13443146 | G13: -0.20021075 | H13: -0.31621622 | I13: 23953.16 | J13: 0.01132322 | L13: -0.18441668 | M13: -0.32881584
A14: Total Handheld | B14: 37.010741 | C14: -0.47948691 | D14: -0.53617507 | E14: 810 | F14: 0.1434644 | G14: -0.43277311 | H14: -0.58009331 | I14: 29978.7 | J14: 0.014171634 | L14: -0.70475098 | M14: -0.80523681
A15: Total Dongle | B15: 42.43 | C15: 0.063597339 | E15: 16 | F15: 0.0028338647 | G15: -0.33333333 | I15: 678.88 | J15: 0.00032092248 | L15: -0.29093511
A16: Total Other Tools | B16: 53.485146 | C16: 0.1717455 | D16: 0.27366145 | E16: 515 | F16: 0.091215019 | G16: -0.096491228 | H16: -0.078711986 | I16: 27544.85 | J16: 0.013021096 | L16: 0.058682338 | M16: 0.17340903
A17: Total | B17: 374.98832 | C17: -0.068805591 | D17: 0.20134602 | E17: 5641 | F17: 0.99911442 | G17: -0.25116156 | H17: -0.38963428 | I17: 2115309.1 | J17: 0.99995615 | L17: -0.30268583 | M17: -0.26673957
A50: Rank by Revenue
A51: Product Name | B51: ASIN | C51: Type | D51: Avg Price | E51: Estimated 12mo Revenue | F51: Monthly Rev | G51: Estimated 12mo Units | H51: Monthly Units | I51: # of Reviews | J51: Tool Rating | K51: Column1 | L51: Link
A52: Launch X431 PRO3 V+ Elite SmartlinkC Bidirectional Scan Tool J2534 Protocol | B52: B0DTTTJWYH | C52: Tablet | D52: 1327.7482 | E52: 1485349.6 | F52: 217750.71 | G52: 1125 | H52: 164 | I52: 113 | J52: 4.4 | K52: https://amazon.com/dp/B0DTTTJWYH | L52: =IF(K52="","",HYPERLINK(K52,K52)) -> https://amazon.com/dp/B0DTTTJWYH
A53: LAUNCH X431 CRP919XBT OBD2 Scanner, 2026 Wireless Bidirectional Scan Tool | B53: B0CJDTPDPB | C53: Tablet | D53: 536.91414 | E53: 1398413.9 | F53: 149262.13 | G53: 2707 | H53: 278 | I53: 428 | J53: 4.5 | K53: https://amazon.com/dp/B0CJDTPDPB | L53: =IF(K53="","",HYPERLINK(K53,K53)) -> https://amazon.com/dp/B0CJDTPDPB
A54: Launch X431 Scanner PROS Elite 2026 New Bidirectional Scan Tool, ECU Coding | B54: B092YL7M8P | C54: Tablet | D54: 694.41927 | E54: 1299987 | F54: 133328.5 | G54: 1990 | H54: 192 | I54: 437 | J54: 4.6 | K54: https://amazon.com/dp/B092YL7M8P | L54: =IF(K54="","",HYPERLINK(K54,K54)) -> https://amazon.com/dp/B092YL7M8P
A55: LAUNCH X431 PRO3S+ Smartlink HD Heavy Duty Truck Scanner,J2534 Protocols | B55: B08V59JNYP | C55: Tablet | D55: 1881.0209 | E55: 1797927 | F55: 129790.44 | G55: 972 | H55: 69 | I55: 186 | J55: 4.3 | K55: https://amazon.com/dp/B08V59JNYP | L55: =IF(K55="","",HYPERLINK(K55,K55)) -> https://amazon.com/dp/B08V59JNYP
A56: LAUNCH X431 PRO3S+ Elite, 2026 Bidirectional Scan Tool with J2534 Protocols | B56: B0D7VS8SHS | C56: Tablet | D56: 1218.3985 | E56: 2180164 | F56: 102345.47 | G56: 1736 | H56: 84 | I56: 172 | J56: 4.2 | K56: https://amazon.com/dp/B0D7VS8SHS | L56: =IF(K56="","",HYPERLINK(K56,K56)) -> https://amazon.com/dp/B0D7VS8SHS
A57: Launch OBD2 Scanner CRP123X V3.0 Elite,7 Resets Scan Tool,Lifetime Update | B57: B07RLF8FBC | C57: Tablet | D57: 191.23655 | E57: 1750445.4 | F57: 100207.95 | G57: 10306 | H57: 524 | I57: 3564 | J57: 4.5 | K57: https://amazon.com/dp/B07RLF8FBC | L57: =IF(K57="","",HYPERLINK(K57,K57)) -> https://amazon.com/dp/B07RLF8FBC
A58: LAUNCH X431 CRP919EBT 2026 Wireless Bidirectional Scan Tool, All-in-One Full System OBD2 Scanner, ECU Coding, 35+ Services, CANFD&DOIP, FCA AutoAuth, VAG Guide, 2Yrs Free Update, Upgraded of CRP919E | B58: B0C6TC2ZF3 | C58: Tablet | D58: 491.71407 | E58: 1139047.5 | F58: 66381.4 | G58: 2335 | H58: 135 | I58: 302 | J58: 4.3 | K58: https://amazon.com/dp/B0C6TC2ZF3 | L58: =IF(K58="","",HYPERLINK(K58,K58)) -> https://amazon.com/dp/B0C6TC2ZF3
A59: LAUNCH OBD2 Scanner CRP123I V3.0 Elite,7 Resets Car Scanner,Lifetime Update | B59: B07QW18S12 | C59: Tablet | D59: 189.63344 | E59: 847684.75 | F59: 60113.8 | G59: 4979 | H59: 317 | I59: 3420 | J59: 4.4 | K59: https://amazon.com/dp/B07QW18S12 | L59: =IF(K59="","",HYPERLINK(K59,K59)) -> https://amazon.com/dp/B07QW18S12
A60: LAUNCH X431 CRP919E Bidirectional Scan Tool,35+ Reset ECU Code OBD2 Scanner | B60: B0DKHKQBDW | C60: Tablet | D60: 460.43556 | E60: 706283.73 | F60: 57094.01 | G60: 1566 | H60: 124 | I60: 205 | J60: 4.4 | K60: https://amazon.com/dp/B0DKHKQBDW | L60: =IF(K60="","",HYPERLINK(K60,K60)) -> https://amazon.com/dp/B0DKHKQBDW
A61: LAUNCH X431 CRP919X OBD2 Scanner, ECU Coding Car Scanner, 2026 US Version | B61: B0DTPTB8MS | C61: Tablet | D61: 430.87264 | E61: 345178.44 | F61: 55582.57 | G61: 794 | H61: 129 | I61: 81 | J61: 4.5 | K61: https://amazon.com/dp/B0DTPTB8MS | L61: =IF(K61="","",HYPERLINK(K61,K61)) -> https://amazon.com/dp/B0DTPTB8MS
A62: Launch X431 PRO3S+ V5.0,2026 Upgrade All-in-One Bidirectional Scan Tool,HD Trucks Scan,Topology Map,ECU Code,55+ Service,Full System,CANFD&DOIP,DBSCar VII VCI 2-Year Update | B62: B092894STV | C62: Tablet | D62: 1046.2453 | E62: 1201771.3 | F62: 55451 | G62: 1147 | H62: 53 | I62: 699 | J62: 4.2 | K62: https://amazon.com/dp/B092894STV | L62: =IF(K62="","",HYPERLINK(K62,K62)) -> https://amazon.com/dp/B092894STV
A63: Launch X431 CRP919XBT Wireless Bidirectional Scan Tool with ECU Code, 2026 | B63: B0C5D1YM1F | C63: Tablet | D63: 528.1392 | E63: 396285.31 | F63: 46476.25 | G63: 792 | H63: 88 | I63: 631 | J63: 4.4 | K63: https://amazon.com/dp/B0C5D1YM1F | L63: =IF(K63="","",HYPERLINK(K63,K63)) -> https://amazon.com/dp/B0C5D1YM1F
... A177: Launch X431 Scanner 1MM0 Elite with X-PROG3(Valued $800),ECU C l0ne Tool | B177: B0DN5XKF1S | C177: Tablet | D177: 1081.64 | E177: 145141.7 | F177: 1081.64 | G177: 112 | H177: 1 | I177: 198 | J177: 4.1 | K177: https://amazon.com/dp/B0DN5XKF1S | L177: =IF(K177="","",HYPERLINK(K177,K177)) -> https://amazon.com/dp/B0DN5XKF1S
A178: LAUNCH Creader Elite X500 for GM OBD2 Scanner Diagnostic Tool Full System | B178: B0GX17T6Z2 | C178: Tablet | D178: 210 | E178: 12680.769 | F178: 1050 | G178: 5 | H178: 5 | K178: https://amazon.com/dp/B0GX17T6Z2 | L178: =IF(K178="","",HYPERLINK(K178,K178)) -> https://amazon.com/dp/B0GX17T6Z2
A179: LAUNCH CRP129E Plus OBD2 Scanner, All-in-ONE Full System Diagnostic Scan Tool, Lifetime Free Update, 12 Reset Oil/TPMS/EPB/SAS/BMS/Throttle Reset, Injector Coding, FCA AutoAuth, Battery Test,Auto VIN | B179: B0CL2BPJ47 | C179: Tablet | D179: 257.555 | E179: 9331.51 | F179: 1030.22 | G179: 37 | H179: 4 | I179: 37 | J179: 4.3 | K179: https://amazon.com/dp/B0CL2BPJ47 | L179: =IF(K179="","",HYPERLINK(K179,K179)) -> https://amazon.com/dp/B0CL2BPJ47
A180: LAUNCH Original Charger 5.0V 3.0A DC Power Supply Cord Replacement X-431 CRP123i, CRP123e, CRP123x, CRP129i, CRP129e, CRP129x, CRP909e, CRP909x Diagnostic Scanner | B180: B0G1LXYLLK | C180: Cable/Adapter | D180: 20.009608 | E180: 11136.818 | F180: 1020.49 | G180: 86 | H180: 51 | I180: 15 | J180: 4.6 | K180: https://amazon.com/dp/B0G1LXYLLK | L180: =IF(K180="","",HYPERLINK(K180,K180)) -> https://amazon.com/dp/B0G1LXYLLK
A181: LAUNCH X431 Remote Assisted Diagnostic Tool, Heavy Duty Truck Scanner, Bidirectional Diesel Scan Tool for 24V HD Trucks & Commercial Vehicle, Support CANFD&DOIP, Semi Trucks All System Diagnostic Tool | B181: B0D8FPG2LW | C181: VCI | D181: 973.15 | E181: 5905.74 | F181: 973.15 | G181: 6 | H181: 1 | I181: 1 | J181: 5 | K181: https://amazon.com/dp/B0D8FPG2LW | L181: =IF(K181="","",HYPERLINK(K181,K181)) -> https://amazon.com/dp/B0D8FPG2LW
A182: LAUNCH X431 PROS Elite Bidirectional Scan Tool, 2 Years Free Update | B182: B0CTCGBC8V | C182: Tablet | D182: 962.24 | E182: 56083.94 | F182: 962.24 | G182: 85 | H182: 1 | I182: 1186 | J182: 4.3 | K182: https://amazon.com/dp/B0CTCGBC8V | L182: =IF(K182="","",HYPERLINK(K182,K182)) -> https://amazon.com/dp/B0CTCGBC8V
A183: Launch CR529 Full OBD2 Function Professional Mechanic OBDII Diagnostic Tool | B183: B0811JXH3M | C183: Handheld | D183: 43.325714 | E183: 15500.29 | F183: 909.84 | G183: 348 | H183: 21 | I183: 2791 | J183: 4.3 | K183: https://amazon.com/dp/B0811JXH3M | L183: =IF(K183="","",HYPERLINK(K183,K183)) -> https://amazon.com/dp/B0811JXH3M
A184: LAUNCH CR HD V2 Heavy Duty Truck Scanner 2026 Diesel Full-System Scan Tool | B184: B0GYJZF7P6 | C184: Tablet | D184: 127.66286 | E184: 10792.422 | F184: 893.64 | G184: 7 | H184: 7 | I184: 10 | J184: 4.8 | K184: https://amazon.com/dp/B0GYJZF7P6 | L184: =IF(K184="","",HYPERLINK(K184,K184)) -> https://amazon.com/dp/B0GYJZF7P6
A185: Launch CRP129HD Heavy Duty Truck Scanner with DPF Regen, Speed Limit Reset | B185: B0DTDXZSHM | C185: Tablet | D185: 442.66 | E185: 58713.5 | F185: 885.32 | G185: 113 | H185: 2 | I185: 45 | J185: 4.1 | K185: https://amazon.com/dp/B0DTDXZSHM | L185: =IF(K185="","",HYPERLINK(K185,K185)) -> https://amazon.com/dp/B0DTDXZSHM
A186: OBD2 Scanner LAUNCH Millennium 90 Pro Car Scanner, Full OBD2 Code Reader, Diagnostic Scan Tool for ABS SRS AT Engine, with Oil EPB BMS ABS Bleeding SAS Reset Service Functions, Lifetime Free Update | B186: B074XD3TRS | C186: Handheld | D186: 95.175556 | E186: 12872.82 | F186: 856.58 | G186: 127 | H186: 9 | I186: 175 | J186: 4.3 | K186: https://amazon.com/dp/B074XD3TRS | L186: =IF(K186="","",HYPERLINK(K186,K186)) -> https://amazon.com/dp/B074XD3TRS
A187: LAUNCH X-431 DoIP Adapter Cable for X431 DBSCar VII Diagnostic Scanner | B187: B0GFM465BH | C187: Cable/Adapter | D187: 84.013 | E187: 9235.9623 | F187: 840.13 | G187: 43 | H187: 10 | I187: 2 | J187: 5 | K187: https://amazon.com/dp/B0GFM465BH | L187: =IF(K187="","",HYPERLINK(K187,K187)) -> https://amazon.com/dp/B0GFM465BH
A188: LAUNCH X-431 DoIP Connector Adapter Cable with USB and 16-Pin Male to Female for X-431 Series Diagnostic Scanner DBScar VII and SmartLink Connector | B188: B0CQ8GDK2L | C188: Cable/Adapter | D188: 85.7 | E188: 11013.06 | F188: 771.3 | G188: 118 | H188: 9 | I188: 6 | J188: 4.8 | K188: https://amazon.com/dp/B0CQ8GDK2L | L188: =IF(K188="","",HYPERLINK(K188,K188)) -> https://amazon.com/dp/B0CQ8GDK2L
A189: LAUNCH Original Adapter for DBSCar VII and SmartLink C VCI Connector, DR15 Male to OBD2 16 Pin Male Replacement Connector Work with X431 CRP919EBT, PRO3 ACE, PRO 3S+, PRO 5, PAD VII, PAD V | B189: B0D8PPVD5D | C189: Cable/Adapter | D189: 22.73125 | E189: 9132.31 | F189: 727.4 | G189: 397 | H189: 32 | I189: 35 | J189: 4.4 | K189: https://amazon.com/dp/B0D8PPVD5D | L189: =IF(K189="","",HYPERLINK(K189,K189)) -> https://amazon.com/dp/B0D8PPVD5D
A190: LAUNCH Professional OBD2 Scanner Diagnostic Tool CR3008 Plus,One-Click I/M | B190: B0CLDK3M3B | C190: Handheld | D190: 47.948667 | E190: 19495.5 | F190: 719.23 | G190: 435 | H190: 15 | I190: 164 | J190: 4.3 | K190: https://amazon.com/dp/B0CLDK3M3B | L190: =IF(K190="","",HYPERLINK(K190,K190)) -> https://amazon.com/dp/B0CLDK3M3B
... A333: Launch Millennium HD Pro Heavy Duty Code Scanner with DPF | B333: B07L5VQGY6 | C333: Handheld | D333: 448.77 | E333: 0 | F333: 0 | G333: 0 | H333: 0 | I333: 4 | J333: 3.8 | K333: https://amazon.com/dp/B07L5VQGY6 | L333: =IF(K333="","",HYPERLINK(K333,K333)) -> https://amazon.com/dp/B07L5VQGY6
A334: Total | E334: =SUM(E52:E333) -> 32859046 | F334: =SUM(F52:F333) -> 2115401.8
A336: Rank by Units
A337: Product Name | B337: ASIN | C337: Type | D337: Avg Price | E337: Estimated 12mo Revenue | F337: Monthly Rev | G337: Estimated 12mo Units | H337: Monthly Units | I337: # of Reviews | J337: Tool Rating | K337: Column1 | L337: Link
A338: Launch OBD2 Scanner CRP123X V3.0 Elite,7 Resets Scan Tool,Lifetime Update | B338: B07RLF8FBC | C338: Tablet | D338: 191.23655 | E338: 1750445.4 | F338: 100207.95 | G338: 10306 | H338: 524 | I338: 3564 | J338: 4.5 | K338: https://amazon.com/dp/B07RLF8FBC | L338: =IF(K338="","",HYPERLINK(K338,K338)) -> https://amazon.com/dp/B07RLF8FBC
A339: Launch CR529 OBD2 Diagnostic Scan Tool Code Reader for Car After 1996 | B339: B082MCG82X | C339: Handheld | D339: 38.353782 | E339: 189168.99 | F339: 16530.48 | G339: 4750 | H339: 431 | I339: 4304 | J339: 4.4 | K339: https://amazon.com/dp/B082MCG82X | L339: =IF(K339="","",HYPERLINK(K339,K339)) -> https://amazon.com/dp/B082MCG82X
A340: LAUNCH CRP123 V3.0 Elite OBD2 Scanner,Engine ABS SRS Transmission | B340: B073GW5MTS | C340: Tablet | D340: 133.66757 | E340: 671756.38 | F340: 45714.31 | G340: 5301 | H340: 342 | I340: 4094 | J340: 4.3 | K340: https://amazon.com/dp/B073GW5MTS | L340: =IF(K340="","",HYPERLINK(K340,K340)) -> https://amazon.com/dp/B073GW5MTS
A341: LAUNCH OBD2 Scanner CRP123I V3.0 Elite,7 Resets Car Scanner,Lifetime Update | B341: B07QW18S12 | C341: Tablet | D341: 189.63344 | E341: 847684.75 | F341: 60113.8 | G341: 4979 | H341: 317 | I341: 3420 | J341: 4.4 | K341: https://amazon.com/dp/B07QW18S12 | L341: =IF(K341="","",HYPERLINK(K341,K341)) -> https://amazon.com/dp/B07QW18S12
A342: LAUNCH X431 CRP919XBT OBD2 Scanner, 2026 Wireless Bidirectional Scan Tool | B342: B0CJDTPDPB | C342: Tablet | D342: 536.91414 | E342: 1398413.9 | F342: 149262.13 | G342: 2707 | H342: 278 | I342: 428 | J342: 4.5 | K342: https://amazon.com/dp/B0CJDTPDPB | L342: =IF(K342="","",HYPERLINK(K342,K342)) -> https://amazon.com/dp/B0CJDTPDPB
A343: Launch X431 Scanner PROS Elite 2026 New Bidirectional Scan Tool, ECU Coding | B343: B092YL7M8P | C343: Tablet | D343: 694.41927 | E343: 1299987 | F343: 133328.5 | G343: 1990 | H343: 192 | I343: 437 | J343: 4.6 | K343: https://amazon.com/dp/B092YL7M8P | L343: =IF(K343="","",HYPERLINK(K343,K343)) -> https://amazon.com/dp/B092YL7M8P
A344: Launch X431 PRO3 V+ Elite SmartlinkC Bidirectional Scan Tool J2534 Protocol | B344: B0DTTTJWYH | C344: Tablet | D344: 1327.7482 | E344: 1485349.6 | F344: 217750.71 | G344: 1125 | H344: 164 | I344: 113 | J344: 4.4 | K344: https://amazon.com/dp/B0DTTTJWYH | L344: =IF(K344="","",HYPERLINK(K344,K344)) -> https://amazon.com/dp/B0DTTTJWYH
A345: LAUNCH Creader 3001 OBD2 Scanner, Check Engine Code Reader, Lifetime Update | B345: B07D1KH9SC | C345: Handheld | D345: 17.360135 | E345: 54735.6 | F345: 2569.3 | G345: 2663 | H345: 148 | I345: 6040 | J345: 4.4 | K345: https://amazon.com/dp/B07D1KH9SC | L345: =IF(K345="","",HYPERLINK(K345,K345)) -> https://amazon.com/dp/B07D1KH9SC
A346: LAUNCH X431 CRP919EBT 2026 Wireless Bidirectional Scan Tool, All-in-One Full System OBD2 Scanner, ECU Coding, 35+ Services, CANFD&DOIP, FCA AutoAuth, VAG Guide, 2Yrs Free Update, Upgraded of CRP919E | B346: B0C6TC2ZF3 | C346: Tablet | D346: 491.71407 | E346: 1139047.5 | F346: 66381.4 | G346: 2335 | H346: 135 | I346: 302 | J346: 4.3 | K346: https://amazon.com/dp/B0C6TC2ZF3 | L346: =IF(K346="","",HYPERLINK(K346,K346)) -> https://amazon.com/dp/B0C6TC2ZF3
A347: LAUNCH X431 CRP919X OBD2 Scanner, ECU Coding Car Scanner, 2026 US Version | B347: B0DTPTB8MS | C347: Tablet | D347: 430.87264 | E347: 345178.44 | F347: 55582.57 | G347: 794 | H347: 129 | I347: 81 | J347: 4.5 | K347: https://amazon.com/dp/B0DTPTB8MS | L347: =IF(K347="","",HYPERLINK(K347,K347)) -> https://amazon.com/dp/B0DTPTB8MS
A348: LAUNCH X431 CRP919E Bidirectional Scan Tool,35+ Reset ECU Code OBD2 Scanner | B348: B0DKHKQBDW | C348: Tablet | D348: 460.43556 | E348: 706283.73 | F348: 57094.01 | G348: 1566 | H348: 124 | I348: 205 | J348: 4.4 | K348: https://amazon.com/dp/B0DKHKQBDW | L348: =IF(K348="","",HYPERLINK(K348,K348)) -> https://amazon.com/dp/B0DKHKQBDW
A349: LAUNCH Original USB Charging Cable Replacement X-431 CRP123i, CRP123e, CRP123x, CRP129i, CRP129e, CRP129x, CRP909E, CRP909X OBD2 Scanner 5V DC | B349: B0CSFNYXJJ | C349: Cable/Adapter | D349: 11.981944 | E349: 26211.08 | F349: 1294.05 | G349: 2231 | H349: 108 | I349: 170 | J349: 4.7 | K349: https://amazon.com/dp/B0CSFNYXJJ | L349: =IF(K349="","",HYPERLINK(K349,K349)) -> https://amazon.com/dp/B0CSFNYXJJ
... A466: LAUNCH X431 PRO3S+ Elite SmartlinkC 2.0 2026 Bidirectional Scan Tool J2534 | B466: B0D5MC58JP | C466: Tablet | D466: 1276.364 | E466: 180917.41 | F466: 6381.82 | G466: 141 | H466: 5 | I466: 39 | J466: 4.1 | K466: https://amazon.com/dp/B0D5MC58JP | L466: =IF(K466="","",HYPERLINK(K466,K466)) -> https://amazon.com/dp/B0D5MC58JP
A467: LAUNCH Creader Elite X500 for GM OBD2 Scanner Diagnostic Tool Full System | B467: B0GX17T6Z2 | C467: Tablet | D467: 210 | E467: 12680.769 | F467: 1050 | G467: 5 | H467: 5 | K467: https://amazon.com/dp/B0GX17T6Z2 | L467: =IF(K467="","",HYPERLINK(K467,K467)) -> https://amazon.com/dp/B0GX17T6Z2
A468: LAUNCH Original OBD1 External Power Supply via Battery Clipper Fit for DR15 Female to OBD2 16 Pin Famale Cable with External Power Port | B468: B0DXNYBDQP | C468: Other | D468: 18.206 | E468: 386.86 | F468: 91.03 | G468: 20 | H468: 5 | I468: 0 | J468: 0 | K468: https://amazon.com/dp/B0DXNYBDQP | L468: =IF(K468="","",HYPERLINK(K468,K468)) -> https://amazon.com/dp/B0DXNYBDQP
A469: Launch Scanner CRP129X Plus OBD2 Scanner Diagnostic Tool, All System Car Scanner, 12 Reset Injector Coding/Throttle/SAS/Oil/EPB/BMS/TPMS Reset Scan Tool, FCA SGW, CANFD&DoIP, Free Update | B469: B0CNSLR1VL | C469: Tablet | D469: 295.576 | E469: 64414.7 | F469: 1477.88 | G469: 240 | H469: 5 | I469: 122 | J469: 4.3 | K469: https://amazon.com/dp/B0CNSLR1VL | L469: =IF(K469="","",HYPERLINK(K469,K469)) -> https://amazon.com/dp/B0CNSLR1VL
A470: LAUNCH X431 IM Elite with PRG3 Scan Tool,5000 ECU/MCU/EEPR0M Read,Write | B470: B0DLGSXQ95 | C470: Tablet | D470: 1261.9 | E470: 104457.71 | F470: 6309.5 | G470: 84 | H470: 5 | I470: 2793 | J470: 4.3 | K470: https://amazon.com/dp/B0DLGSXQ95 | L470: =IF(K470="","",HYPERLINK(K470,K470)) -> https://amazon.com/dp/B0DLGSXQ95
A471: LAUNCH X431 CRP919EBT 2026 Wireless Bidirectional OBD2 Scan Tool | B471: B0C68BKGN3 | C471: Tablet | D471: 510.66 | E471: 116580.87 | F471: 2553.3 | G471: 225 | H471: 5 | I471: 43 | J471: 4.2 | K471: https://amazon.com/dp/B0C68BKGN3 | L471: =IF(K471="","",HYPERLINK(K471,K471)) -> https://amazon.com/dp/B0C68BKGN3
A472: LAUNCH X431 Creader VII+ V2.0 Car Code Reader 2026, Lifetime Free Update | B472: B00EN7JOQC | C472: Tablet | D472: 148.375 | E472: 23579.606 | F472: 593.5 | G472: 174 | H472: 4 | I472: 720 | J472: 4 | K472: https://amazon.com/dp/B00EN7JOQC | L472: =IF(K472="","",HYPERLINK(K472,K472)) -> https://amazon.com/dp/B00EN7JOQC
A473: LAUNCH X431 CAN FD Adapter Code Reader Cable | B473: B0B8D789HP | C473: Cable/Adapter | D473: 75.1925 | E473: 1299.7738 | F473: 300.77 | G473: 13 | H473: 4 | I473: 2 | J473: 5 | K473: https://amazon.com/dp/B0B8D789HP | L473: =IF(K473="","",HYPERLINK(K473,K473)) -> https://amazon.com/dp/B0B8D789HP
A474: LAUNCH OBD-II OBD2 Extension Cable, Ultra-Long 4ft 120cm 1.2M, Auto Car 16 Pin Male to Female OBD2 Diagnostic Extender Cord Adapter for All OBD2 Scanners(4ft 120cm 1.2M) | B474: B0DWXHXJG1 | C474: Cable/Adapter | D474: 17.76 | E474: 1341.17 | F474: 71.04 | G474: 76 | H474: 4 | I474: 7 | J474: 4.8 | K474: https://amazon.com/dp/B0DWXHXJG1 | L474: =IF(K474="","",HYPERLINK(K474,K474)) -> https://amazon.com/dp/B0DWXHXJG1
A475: LAUNCH X431 PRO5 Car Scanner, 2026 J2534 Programming Tool, Topology Mapping | B475: B07L6WWL62 | C475: Tablet | D475: 1637.2925 | E475: 214498.34 | F475: 6549.17 | G475: 142 | H475: 4 | I475: 103 | J475: 4 | K475: https://amazon.com/dp/B07L6WWL62 | L475: =IF(K475="","",HYPERLINK(K475,K475)) -> https://amazon.com/dp/B07L6WWL62
A476: LAUNCH X-431 VSP-100 Endoscope Work with X-431 Tablet 5.5mm Ultra-Thin Digital HD USB Video Inspection Camera Multi-Angle Imaging One-Click Snapshot IP67 Waterproof Borescope Videoscope | B476: B0FDK1BNPW | C476: Other | D476: 47.86 | E476: 2303.4338 | F476: 191.44 | G476: 43 | H476: 4 | I476: 3 | J476: 5 | K476: https://amazon.com/dp/B0FDK1BNPW | L476: =IF(K476="","",HYPERLINK(K476,K476)) -> https://amazon.com/dp/B0FDK1BNPW
A477: Launch X-431 Elite PRO Diagnostic Tablet – 10.1" Android 10 Bidirectional Scan Tool, CANFD & DOIP, VW/Audi Guided Functions, SmartLinkC J2534 PassThru, USA Version | B477: B0H2JM4CMY | C477: Tablet | D477: 949.99 | E477: 45891.825 | F477: 3799.96 | G477: 4 | H477: 4 | I477: 0 | J477: 0 | K477: https://amazon.com/dp/B0H2JM4CMY | L477: =IF(K477="","",HYPERLINK(K477,K477)) -> https://amazon.com/dp/B0H2JM4CMY
A478: LAUNCH Creader 3001 OBD2 Engine Fault Code Reader Scanner | B478: B09B2C4TBV | C478: Handheld | D478: 18.0775 | E478: 2856.2285 | F478: 72.31 | G478: 144 | H478: 4 | I478: 11 | J478: 4.3 | K478: https://amazon.com/dp/B09B2C4TBV | L478: =IF(K478="","",HYPERLINK(K478,K478)) -> https://amazon.com/dp/B09B2C4TBV
A479: LAUNCH Creader VII+ V2.0 OBD2 Scanner Diagnostic Scan Tool, 2026 New Automotive Check ABS SRS Transmission and Engine Code Reader, 3 Reset Oil Service/Throttle Relearn/SAS Reset, Free Update | B479: B00DZFHQN6 | C479: Tablet | D479: 121.625 | E479: 13348.31 | F479: 486.5 | G479: 104 | H479: 4 | I479: 202 | J479: 4.2 | K479: https://amazon.com/dp/B00DZFHQN6 | L479: =IF(K479="","",HYPERLINK(K479,K479)) -> https://amazon.com/dp/B00DZFHQN6
... A619: Launch Millennium HD Pro Heavy Duty Code Scanner with DPF | B619: B07L5VQGY6 | C619: Handheld | D619: 448.77 | E619: 0 | F619: 0 | G619: 0 | H619: 0 | I619: 4 | J619: 3.8 | K619: https://amazon.com/dp/B07L5VQGY6 | L619: =IF(K619="","",HYPERLINK(K619,K619)) -> https://amazon.com/dp/B07L5VQGY6
A620: Total | G620: =SUM(G338:G619) -> 91983 | H620: =SUM(H338:H619) -> 5646

Sheet TOPDON
B7: Avg Price | C7: Avg Price MoM | D7: Avg Price YoY | E7: Quantity/Mo | F7: Qty by % | G7: Qty MoM | H7: Qty YoY | I7: Revenue/Mo | J7: Revenue by % | L7: Revenue MoM | M7: Revenue YoY
A8: Tablet $800+ | B8: 1200.1367 | C8: -0.033244164 | D8: -0.014638563 | E8: 324 | F8: 0.02804952 | G8: -0.21927711 | H8: -0.3106383 | I8: 388844.3 | J8: 0.14350686 | L8: -0.24523159 | M8: -0.32072956
A9: Tablet $400-$800 | B9: 615.18187 | C9: -0.020308442 | D9: 0.29935597 | E9: 1053 | F9: 0.091160938 | G9: -0.28269755 | H9: -0.3965616 | I9: 647786.51 | J9: 0.23907206 | L9: -0.29726484 | M9: -0.21591872
A10: Tablet $400- | B10: 236.55165 | C10: -0.04279377 | D10: 0.18014981 | E10: 4961 | F10: 0.42948662 | G10: -0.066603951 | H10: 0.18203479 | I10: 1173532.7 | J10: 0.43310394 | L10: -0.10654749 | M10: 0.39497812
A11: Total Tablet | B11: 348.71624 | C11: -0.087407675 | D11: -0.0017426969 | E11: 6338 | F11: 0.54869708 | G11: -0.11947763 | H11: -0.011540861 | I11: 2210163.5 | J11: 0.81568286 | L11: -0.19644205 | M11: -0.013263446
A12: Handheld $75- | B12: 40.427208 | C12: 0.34813218 | D12: 0.0058463086 | E12: 240 | F12: 0.020777422 | G12: 1.2429907 | H12: 1.1428571 | I12: 9702.53 | J12: 0.0035808153 | L12: 2.0238479 | M12: 1.1553849
A13: Total Handheld | B13: 40.427208 | C13: -0.13852383 | D13: -0.26379823 | E13: 240 | F13: 0.020777422 | G13: 0.44578313 | H13: 0.37931034 | I13: 9702.53 | J13: 0.0035808153 | L13: 0.24550771 | M13: 0.015450711
A14: Total Dongle | B14: 61.476602 | C14: -0.048328212 | D14: -0.27331729 | E14: 3640 | F14: 0.31512423 | G14: -0.016747704 | H14: 0.24444444 | I14: 223774.83 | J14: 0.082586328 | L14: -0.064266529 | M14: -0.095683744
A15: Total Other Tools | B15: 199.50934 | C15: -0.034697593 | D15: -0.27298701 | E15: 1333 | F15: 0.11540126 | G15: -0.2200117 | H15: 1.9754464 | I15: 265945.95 | J15: 0.09815 | L15: -0.24707542 | M15: 1.1631882
A16: Total | B16: 234.57596 | C16: -0.10562665 | D16: -0.10828168 | E16: 11551 | F16: 1 | G16: -0.095812133 | H16: 0.15985541 | I16: 2709586.9 | J16: 1 | L16: -0.19131847 | M16: 0.034264321
A49: Rank by Revenue
A50: Product Name | B50: ASIN | C50: Type | D50: Avg Price | E50: Estimated 12mo Revenue | F50: Monthly Rev | G50: Estimated 12mo Units | H50: Monthly Units | I50: # of Reviews | J50: Tool Rating | K50: Column1 | L50: Link
A51: TOPDON ONE Bidirectional Scan Tool, 10.1" Professional Diagnostic Tool | B51: B0GK9G6YDL | C51: Tablet | D51: 734.64028 | E51: 4421314.4 | F51: 418010.32 | G51: 2304 | H51: 569 | I51: 206 | J51: 4.5 | K51: https://amazon.com/dp/B0GK9G6YDL | L51: =IF(K51="","",HYPERLINK(K51,K51)) -> https://amazon.com/dp/B0GK9G6YDL
A52: TOPDON AD900 Lite OBD2 Scanner, Bidirectional Scan Tool, 8" Large Screen | B52: B0C33Y285Y | C52: Tablet | D52: 313.50156 | E52: 5256182.9 | F52: 323847.11 | G52: 15508 | H52: 1033 | I52: 3990 | J52: 4.3 | K52: https://amazon.com/dp/B0C33Y285Y | L52: =IF(K52="","",HYPERLINK(K52,K52)) -> https://amazon.com/dp/B0C33Y285Y
