Workbook

Sheet Summary
A1: November '25 Monthly Summary
B3: Avg Price | C3: Avg Price MoM | D3: Avg Price YoY | E3: Quantity/Mo | F3: Qty by % | G3: Qty MoM | H3: Qty YoY | I3: Revenue/Mo | J3: Revenue by % | K3: Revenue MoM | L3: Revenue YoY
A4: Tablet $800+ | B4: 1456.7424 | C4: -0.029265699 | D4: -0.08928515 | E4: 2861 | F4: 0.0093000728 | G4: -0.026870748 | H4: 0.14899598 | I4: 4167739.9 | J4: 0.12714231 | K4: -0.055350056 | L4: 0.046407706
A5: Tablet $400-$800 | B5: 527.27126 | C5: 0.0062141033 | D5: 0.003051364 | E5: 10794 | F5: 0.035087377 | G5: -0.025548434 | H5: 0.37503185 | I5: 5691366 | J5: 0.1736225 | K5: -0.019493091 | L5: 0.37922757
A6: Tablet $400- | B6: 220.0284 | C6: 0.017310952 | D6: 0.056287993 | E6: 25919 | F6: 0.084253264 | G6: 0.20078758 | H6: 0.81049176 | I6: 5702916.1 | J6: 0.17397485 | K6: 0.22157436 | L6: 0.91240071
A7: Total Tablet | B7: 393.23854 | C7: -0.059447514 | D7: -0.12584209 | E7: 39574 | F7: 0.12864071 | G7: 0.11156677 | H7: 0.60504543 | I7: 15562022 | J7: 0.47473967 | K7: 0.045486885 | L7: 0.40306315
A8: Handheld $75+ | B8: 164.58942 | C8: -0.050551412 | D8: -0.074970791 | E8: 19418 | F8: 0.063120872 | G8: 0.12210344 | H8: 0.41882215 | I8: 3195997.3 | J8: 0.097498044 | K8: 0.065379525 | L8: 0.31245193
A9: Handheld $75- | B9: 32.09868 | C9: 0.016644668 | D9: -0.051736376 | E9: 114697 | F9: 0.37283833 | G9: 0.09855661 | H9: 0.41588998 | I9: 3681622.3 | J9: 0.11231266 | K9: 0.11684172 | L9: 0.34263697
A10: Total Handheld | B10: 51.281509 | C10: -0.0086956713 | D10: -0.062044522 | E10: 134115 | F10: 0.4359592 | G10: 0.1019045 | H10: 0.41631377 | I10: 6877619.6 | J10: 0.20981071 | K10: 0.092322697 | L10: 0.32843926
A11: Total Dongle | B11: 71.773221 | C11: -0.055297537 | D11: 0.0040103229 | E11: 67553 | F11: 0.21959029 | G11: 0.087354731 | H11: 0.084317817 | I11: 4848496.4 | J11: 0.14790967 | K11: 0.027226693 | L11: 0.088666282
A12: Total Other Tools | B12: 65.215505 | C12: -0.09560381 | D12: -0.18747043 | E12: 44726 | F12: 0.145388 | G12: -0.029067622 | H12: 0.81010968 | I12: 2916828.7 | J12: 0.088981642 | K12: -0.12189246 | L12: 0.47076764
A13: Total | B13: 105.62359 | C13: -0.040358463 | D13: -0.040044069 | E13: 285968 | F13: 0.9295782 | G13: 0.077071995 | H13: 0.38578587 | I13: 30204967 | J13: 0.92144169 | K13: 0.033603025 | L13: 0.33029336
A45: November '25 Monthly Summary- Revenue
A46: Brand | B46: # of Listings | C46: Monthly Rev | D46: Estimated 12mo Revenue | E46: Monthly Units | F46: Monthly Rev Market Share % | G46: Price Per Unit | H46: Total Reviews | I46: Avg Rating
A47: autel | B47: 560 | C47: 5474504.9 | D47: 58623848 | E47: 19081 | F47: 0.167 | G47: 286.91 | H47: 132237 | I47: 4.5
A48: topdon | B48: 53 | C48: 3543161 | D48: 27983534 | E48: 13907 | F48: 0.1081 | G48: 254.78 | H48: 21711 | I48: 4.4
A49: ancel | B49: 75 | C49: 3020274.3 | D49: 26010885 | E49: 57813 | F49: 0.0921 | G49: 52.24 | H49: 119616 | I49: 4.2
A50: launch | B50: 256 | C50: 2827315.9 | D50: 29800141 | E50: 9093 | F50: 0.0863 | G50: 310.93 | H50: 80730 | I50: 4.2
A51: innova | B51: 20 | C51: 1786011.3 | D51: 11806561 | E51: 10062 | F51: 0.0545 | G51: 177.5 | H51: 14416 | I51: 4.2
A52: foxwell | B52: 48 | C52: 1771619.6 | D52: 18380377 | E52: 14649 | F52: 0.054 | G52: 120.94 | H52: 68025 | I52: 4.2
A53: xtool | B53: 58 | C53: 1671808.4 | D53: 13195976 | E53: 6085 | F53: 0.051 | G53: 274.74 | H53: 10712 | I53: 4.4
A54: bluedriver | B54: 1 | C54: 1319399.8 | D54: 12294051 | E54: 17744 | F54: 0.0403 | G54: 74.36 | H54: 60886 | I54: 4.4
A55: obdlink | B55: 4 | C55: 1186053.6 | D55: 12199618 | E55: 11756 | F55: 0.0362 | G55: 100.89 | H55: 35402 | I55: 4.6
A56: thinkcar | B56: 21 | C56: 997358.64 | D56: 6409132 | E56: 3436 | F56: 0.0304 | G56: 290.27 | H56: 11082 | I56: 4.3
A57: diesel laptops | B57: 18 | C57: 578085.79 | D57: 6188170.1 | E57: 880 | F57: 0.0176 | G57: 656.92 | H57: 532 | I57: 4.1
A58: blcktec | B58: 6 | C58: 561934.45 | D58: 3585625.9 | E58: 4957 | F58: 0.0171 | G58: 113.36 | H58: 4898 | I58: 4.4
... A71: kingbolen | B71: 15 | C71: 208303.91 | D71: 2654784 | E71: 1759 | F71: 0.0064 | G71: 118.42 | H71: 3186 | I71: 4.2
A73: Total | B73: =SUM(B46:B71) -> 1595 | C73: =SUM(C47:C71) -> 28507387 | D73: =SUM(D47:D71) -> 2.6106088e+08 | E73: =SUM(E47:E71) -> 217681 | F73: =SUM(F47:F71) -> 0.8697 | G73: =AVERAGE(G47:G71) -> 217.27 | H73: =SUM(H47:H71) -> 794810 | I73: =AVERAGE(I47:I71) -> 4.28
A76: Monthly Summary - Units
A77: Brand | B77: # of Listings | C77: Monthly Rev | D77: Estimated 12mo Units | E77: Monthly Units | F77: Monthly Unit Market Share % | G77: Price Per Unit | H77: Reviews | I77: Avg Rating
A78: ancel | B78: 75 | C78: 3020274.3 | D78: 508372.62 | E78: 57813 | F78: 0.1879 | G78: 52.24 | H78: 119616 | I78: 4.2
A79: autel | B79: 560 | C79: 5474504.9 | D79: 192381.23 | E79: 19081 | F79: 0.062 | G79: 286.91 | H79: 132237 | I79: 4.5
A80: bluedriver | B80: 1 | C80: 1319399.8 | D80: 142107.69 | E80: 17744 | F80: 0.0577 | G80: 74.36 | H80: 60886 | I80: 4.4
A81: foxwell | B81: 48 | C81: 1771619.6 | D81: 144397.85 | E81: 14649 | F81: 0.0476 | G81: 120.94 | H81: 68025 | I81: 4.2
A82: topdon | B82: 53 | C82: 3543161 | D82: 128028.92 | E82: 13907 | F82: 0.0452 | G82: 254.78 | H82: 21711 | I82: 4.4
A83: motopower | B83: 6 | C83: 318008.37 | D83: 108366.46 | E83: 12166 | F83: 0.0395 | G83: 26.14 | H83: 55132 | I83: 4.4
A84: obdlink | B84: 4 | C84: 1186053.6 | D84: 128833.85 | E84: 11756 | F84: 0.0382 | G84: 100.89 | H84: 35402 | I84: 4.6
A85: innova | B85: 20 | C85: 1786011.3 | D85: 63731.077 | E85: 10062 | F85: 0.0327 | G85: 177.5 | H85: 14416 | I85: 4.2
A86: launch | B86: 256 | C86: 2827315.9 | D86: 97113.231 | E86: 9093 | F86: 0.0296 | G86: 310.93 | H86: 80730 | I86: 4.2
A87: fixd | B87: 3 | C87: 312500.11 | D87: 124167.69 | E87: 7721 | F87: 0.0251 | G87: 40.47 | H87: 34866 | I87: 4.2
A88: veepeak | B88: 5 | C88: 211949.5 | D88: 61216.615 | E88: 7125 | F88: 0.0232 | G88: 29.75 | H88: 51206 | I88: 4.5
A89: vgate | B89: 33 | C89: 252683.65 | D89: 56645.538 | E89: 6442 | F89: 0.0209 | G89: 39.22 | H89: 36766 | I89: 4.4
... A102: kingbolen | B102: 15 | C102: 208303.91 | D102: 18709.846 | E102: 1759 | F102: 0.0057 | G102: 118.42 | H102: 3186 | I102: 4.2
A104: Total | B104: =SUM(B78:B102) -> 1432 | C104: =SUM(C78:C102) -> 26627658 | D104: =SUM(D78:D102) -> 2103156.9 | E104: =SUM(E78:E102) -> 230439 | F104: =SUM(F78:F102) -> 0.7491 | G104: =AVERAGE(G78:G102) -> 109.6856 | H104: =SUM(H78:H102) -> 808373 | I104: =AVERAGE(I78:I102) -> 4.336

Sheet Top 50
A1: Top 50 Products - November '25 ONLY
B3: Avg Price | C3: Avg Price MoM | D3: Avg Price YoY | E3: Quantity/Mo | F3: Qty by % | G3: Qty MoM | H3: Qty YoY | I3: Revenue/Mo | J3: Revenue by % | L3: Revenue MoM | M3: Revenue YoY
A4: Tablets | B4: 344.22355 | C4: -0.11859123 | D4: -0.1353626 | E4: 21723 | F4: 0.15237474 | G4: 0.32070768 | H4: 1.2259453 | I4: 7477568.1 | J4: 0.47963781 | K4: 0.16408334 | L4: 0.16408334 | M4: 0.92463555
A5: Handheld | B5: 51.801609 | C5: 0.026728513 | D5: 0.065916428 | E5: 74974 | F5: 0.52590083 | G5: 0.29336876 | H5: 0.66909326 | I5: 3883773.8 | J5: 0.24911906 | K5: 0.32793858 | L5: 0.32793858 | M5: 0.77911392
A6: Dongle | B6: 81.218528 | C6: -0.065713874 | D6: -0.057140899 | E6: 40076 | F6: 0.28111081 | G6: 0.14290603 | H6: 0.06729873 | I6: 3254913.7 | J6: 0.20878174 | K6: 0.067801249 | L6: 0.067801249 | M6: 0.0063123209
A7: Other Tools | B7: 168.18222 | C7: -0.11163752 | D7: 0.33730085 | E7: 5790 | F7: 0.040613623 | G7: 0.04230423 | H7: 0.3639576 | I7: 973775.03 | J7: 0.062461393 | K7: -0.074056032 | L7: -0.074056032 | M7: 0.82402166
A8: Total | B8: 109.35538 | C8: -0.064568251 | D8: 0.072505803 | E8: 142563 | F8: 1 | G8: 0.23929031 | H8: 0.47776557 | I8: 15590031 | J8: 1 | K8: 0.1592715 | L8: 0.1592715 | M8: 0.58491215
A40: Rank By Monthly Revenue - Nov '25 ONLY
A41: Ranking | B41: ASIN | C41: Product Name | D41: Brand | E41: Type | F41: Price | G41: Est. Monthly Retail Rev | H41: Est. Monthly Units Sold | I41: # of Reviews | J41: Avg. Rating | K41: Column2 | L41: Link
A42: 1 | B42: B00652G4TS | C42: BlueDriver Bluetooth Pro OBDII Scan Tool for iPhone & Android - No Subscription Fee - OBD2 Car Scanner and Code Reader - Diagnose Check Engine, ABS, SRS, Airbag & 7000+ Issues on Vehicles 1996+ | D42: bluedriver | E42: Dongle | F42: 74.357517 | G42: 1319399.8 | H42: 17744 | I42: 60886 | J42: 4.4 | K42: https://amazon.com/dp/B00652G4TS | L42: =HYPERLINK(K42) -> https://amazon.com/dp/B00652G4TS
A43: 2 | B43: B01G5EA74I | C43: ANCEL AD310 Classic Enhanced Universal OBD II Scanner Car Engine Fault Code Reader CAN Diagnostic Scan Tool, Read and Clear Error Codes for 1996 or Newer OBD2 Protocol Vehicle (Black) | D43: ancel | E43: Handheld | F43: 28.282506 | G43: 1131017.4 | H43: 39990 | I43: 59738 | J43: 4.6 | K43: https://amazon.com/dp/B01G5EA74I | L43: =HYPERLINK(K43) -> https://amazon.com/dp/B01G5EA74I
A44: 3 | B44: B07Z481NJM | C44: Innova 5610 OBD2 Bidirectional Scan Tool - Understand Your Vehicle, Pinpoint What's Wrong, and Complete Your Repairs with Less Headache, Updates Included, US-Based Technical Support | D44: innova | E44: Handheld | F44: 287.32292 | G44: 1127455.1 | H44: 3924 | I44: 2889 | J44: 4.4 | K44: https://amazon.com/dp/B07Z481NJM | L44: =HYPERLINK(K44) -> https://amazon.com/dp/B07Z481NJM
A45: 4 | B45: B0744B55QV | C45: Autel Scanner MaxiCOM MK808S: 2025 Bidirectional Tool as MK808BT Pro MX808S M808Z, Work as MaxiCheck MX900 MK900BT, 28+ Service, Active Test, All System Diagnose, Injector C0ding, FCA Autoauth OS 11 | D45: autel | E45: Tablet | F45: 451.83728 | G45: 684985.31 | H45: 1516 | I45: 3604 | J45: 4.5 | K45: https://amazon.com/dp/B0744B55QV | L45: =HYPERLINK(K45) -> https://amazon.com/dp/B0744B55QV
A46: 5 | B46: B07JFRFJG6 | C46: OBDLink MX+ OBD2 Bluetooth Scanner for iPhone, Android, and Windows | D46: obdlink | E46: Dongle | F46: 139.94207 | G46: 666544.1 | H46: 4763 | I46: 14685 | J46: 4.6 | K46: https://amazon.com/dp/B07JFRFJG6 | L46: =HYPERLINK(K46) -> https://amazon.com/dp/B07JFRFJG6
A47: 6 | B47: B0C33Y285Y | C47: TOPDON Bidirectional Scan Tool, 2025 New ArtiDiag900 Lite Automotive Diagnostic Tool for Full System, Scanner for Car with Active Test, 8 Reset, Wireless OBD2 Scanner Diagnostic Tool for All Vehicles | D47: topdon | E47: Tablet | F47: 313.53909 | G47: 520788.43 | H47: 1661 | I47: 999 | J47: 4.3 | K47: https://amazon.com/dp/B0C33Y285Y | L47: =HYPERLINK(K47) -> https://amazon.com/dp/B0C33Y285Y
A48: 7 | B48: B098PYB8XG | C48: Autel Scanner MaxiCOM MK900BT, 2025 MK900-BT V2.0 Bidirectional Diagnostic Tool, 8in Up of MK900 MX900 MK808S MK808BT MX808S MK808Z, 3000+ Active Tests, 40+ Service, CAN-FD&DOIP, All System, FCA 11 OS | D48: autel | E48: Tablet | F48: 659.22073 | G48: 479912.69 | H48: 728 | I48: 580 | J48: 4.6 | K48: https://amazon.com/dp/B098PYB8XG | L48: =HYPERLINK(K48) -> https://amazon.com/dp/B098PYB8XG
A49: 8 | B49: B00UJV3E12 | C49: FOXWELL NT301 OBD2 Scanner Live Data Professional Mechanic OBDII Diagnostic Code Reader Tool for Check Engine Light | D49: foxwell | E49: Handheld | F49: 64.359672 | G49: 410035.47 | H49: 6371 | I49: 29066 | J49: 4.5 | K49: https://amazon.com/dp/B00UJV3E12 | L49: =HYPERLINK(K49) -> https://amazon.com/dp/B00UJV3E12
A50: 9 | B50: B0DV2N2FND | C50: BLCKTEC 460T OBD2 Scanner Car Code Reader Engine ABS SRS Transmission Diagnostic Tool, 12 Reset Services, Oil/TPMS/EPB/BMS/SAS/DPF/Throttle Reset, ABS Bleeding, Battery Test, Auto VIN, Free Update | D50: blcktec | E50: Tablet | F50: 198.0568 | G50: 402451.42 | H50: 2032 | I50: 312 | J50: 4.4 | K50: https://amazon.com/dp/B0DV2N2FND | L50: =HYPERLINK(K50) -> https://amazon.com/dp/B0DV2N2FND
A51: 10 | B51: B0DCFRF2TF | C51: THINKCAR Bidirectional Scan Tool, THINKSCAN 689BT All System Automotive Diagnostic Tool, Bi Directional OBD2 Scanner with ECU Coding, 34 Services, FCA Autoauth, CANFD and DoIP, Wireless Update | D51: thinkcar | E51: Tablet | F51: 501.58996 | G51: 393748.12 | H51: 785 | I51: 401 | J51: 4.4 | K51: https://amazon.com/dp/B0DCFRF2TF | L51: =HYPERLINK(K51) -> https://amazon.com/dp/B0DCFRF2TF
A52: 11 | B52: B0DTK24XKB | C52: MUCAR 892BT AI-Assisted Bidirectional Scan Tool, Full System OBD2 Scanner, Bi-Directional OBD2 Scanner Diagnostic Tool,ECU Coding, 35 Services, FCA Autoauth, CANFD and DOIP, Free Lifetime Upgrade | D52: mucar | E52: Tablet | F52: 612.13041 | G52: 385030.03 | H52: 629 | I52: 249 | J52: 4.3 | K52: https://amazon.com/dp/B0DTK24XKB | L52: =HYPERLINK(K52) -> https://amazon.com/dp/B0DTK24XKB
A53: 12 | B53: B091BQNR3S | C53: TOPDON Phoenix Plus 2, ECU Code TOPDON Scanner V2.0, Bidirectional Scan Tool, Topology Map, CANFD, High-End OEM Full System, 42+ Service, FCA SGW AutoAuth, V.A.G Guided, 2 Years Free Update | D53: topdon | E53: Tablet | F53: 1096.3385 | G53: 368369.72 | H53: 336 | I53: 447 | J53: 4.5 | K53: https://amazon.com/dp/B091BQNR3S | L53: =HYPERLINK(K53) -> https://amazon.com/dp/B091BQNR3S
... A91: 50 | B91: B09712X5CW | C91: Autel Scanner MaxiCOM MK900BT, 2025 MK900-BT Bidirectional Diagnostic Scan Tool, 2.0 BT Ver. of MK900 MX900, 8in Up of MK808S MK808BT PRO MX808S MK808Z, 40+ Reset, 3K+ Active Tests, CAN FD & DoIP, FCA | D91: autel | E91: Tablet | F91: 659.10106 | G91: 112047.18 | H91: 170 | I91: 165 | J91: 4.6 | K91: https://amazon.com/dp/B09712X5CW | L91: =HYPERLINK(K91) -> https://amazon.com/dp/B09712X5CW
A94: Rank By Monthly Units - Nov '25 ONLY
A95: Ranking | B95: ASIN | C95: Product Name | D95: Brand | E95: Type | F95: Price | G95: Est. Monthly Retail Rev | H95: Est. Monthly Units Sold | I95: # of Reviews | J95: Avg. Rating | K95: Column2 | L95: Link
A96: 1 | B96: B01G5EA74I | C96: ANCEL AD310 Classic Enhanced Universal OBD II Scanner Car Engine Fault Code Reader CAN Diagnostic Scan Tool, Read and Clear Error Codes for 1996 or Newer OBD2 Protocol Vehicle (Black) | D96: ancel | E96: Handheld | F96: 28.282506 | G96: 1131017.4 | H96: 39990 | I96: 59738 | J96: 4.6 | K96: https://amazon.com/dp/B01G5EA74I | L96: =HYPERLINK(K96) -> https://amazon.com/dp/B01G5EA74I
A97: 2 | B97: B00652G4TS | C97: BlueDriver Bluetooth Pro OBDII Scan Tool for iPhone & Android - No Subscription Fee - OBD2 Car Scanner and Code Reader - Diagnose Check Engine, ABS, SRS, Airbag & 7000+ Issues on Vehicles 1996+ | D97: bluedriver | E97: Dongle | F97: 74.357517 | G97: 1319399.8 | H97: 17744 | I97: 60886 | J97: 4.4 | K97: https://amazon.com/dp/B00652G4TS | L97: =HYPERLINK(K97) -> https://amazon.com/dp/B00652G4TS
A98: 3 | B98: B07Z3HB7DR | C98: MOTOPOWER MP69033 Car OBD2 Scanner Code Reader Engine Fault Scanner CAN Diagnostic Scan Tool for All OBD II Protocol Cars Since 1996, Yellow | D98: motopower | E98: Handheld | F98: 25.196317 | G98: 261109.43 | H98: 10363 | I98: 48232 | J98: 4.6 | K98: https://amazon.com/dp/B07Z3HB7DR | L98: =HYPERLINK(K98) -> https://amazon.com/dp/B07Z3HB7DR
A99: 4 | B99: B013RIQMEO | C99: FIXD Bluetooth OBD2 Scanner for Car - Car Code Readers & Scan Tools for iPhone/Android - Wireless OBD2 Auto Diagnostic Tool - Check Engine & Fix All Vehicles 1996+ (1 Pack w/Free FIXD Premium Trial) | D99: fixd | E99: Dongle | F99: 39.990511 | G99: 306207.34 | H99: 7657 | I99: 33653 | J99: 4.1 | K99: https://amazon.com/dp/B013RIQMEO | L99: =HYPERLINK(K99) -> https://amazon.com/dp/B013RIQMEO
A100: 5 | B100: B071FSNL73 | C100: ANCEL AD410 Enhanced OBD2 Scanner, Vehicle Code Reader for Check Engine Light, Automotive OBD II Scanner Fault Diagnosis, OBDII Scan Tool for All OBDII Cars 1996+, Black/Yellow | D100: ancel | E100: Handheld | F100: 49.987904 | G100: 347165.99 | H100: 6945 | I100: 14142 | J100: 4.5 | K100: https://amazon.com/dp/B071FSNL73 | L100: =HYPERLINK(K100) -> https://amazon.com/dp/B071FSNL73
A101: 6 | B101: B00UJV3E12 | C101: FOXWELL NT301 OBD2 Scanner Live Data Professional Mechanic OBDII Diagnostic Code Reader Tool for Check Engine Light | D101: foxwell | E101: Handheld | F101: 64.359672 | G101: 410035.47 | H101: 6371 | I101: 29066 | J101: 4.5 | K101: https://amazon.com/dp/B00UJV3E12 | L101: =HYPERLINK(K101) -> https://amazon.com/dp/B00UJV3E12
A102: 7 | B102: B07JFRFJG6 | C102: OBDLink MX+ OBD2 Bluetooth Scanner for iPhone, Android, and Windows | D102: obdlink | E102: Dongle | F102: 139.94207 | G102: 666544.1 | H102: 4763 | I102: 14685 | J102: 4.6 | K102: https://amazon.com/dp/B07JFRFJG6 | L102: =HYPERLINK(K102) -> https://amazon.com/dp/B07JFRFJG6
A103: 8 | B103: B073XKQQQW | C103: Veepeak OBDCheck BLE Bluetooth OBD II Scanner for iOS & Android, Car Wireless Check Engine Light Code Reader Diagnostic Tool | D103: veepeak | E103: Dongle | F103: 30.040911 | G103: 135214.14 | H103: 4501 | I103: 22552 | J103: 4.5 | K103: https://amazon.com/dp/B073XKQQQW | L103: =HYPERLINK(K103) -> https://amazon.com/dp/B073XKQQQW
A104: 9 | B104: B081VQVD3F | C104: OBDLink EX FORScan OBD Adapter | D104: obdlink | E104: Cable/Adapter | F104: 69.934779 | G104: 306454.2 | H104: 4382 | I104: 9449 | J104: 4.8 | K104: https://amazon.com/dp/B081VQVD3F | L104: =HYPERLINK(K104) -> https://amazon.com/dp/B081VQVD3F
A105: 10 | B105: B0BY1TS725 | C105: VDIAGTOOL VD10 OBD2 Scanner Code Reader Car Diagnostic Tool Engine Fault Code Reader for Turn Off CEL with Freeze Frame/I/M Readiness for All OBDII Protocol Cars, OBD2 Scanner Diagnostic Tool | D105: vdiagtool | E105: Handheld | F105: 19.98077 | G105: 80142.87 | H105: 4011 | I105: 1843 | J105: 4.6 | K105: https://amazon.com/dp/B0BY1TS725 | L105: =HYPERLINK(K105) -> https://amazon.com/dp/B0BY1TS725
A106: 11 | B106: B07Z481NJM | C106: Innova 5610 OBD2 Bidirectional Scan Tool - Understand Your Vehicle, Pinpoint What's Wrong, and Complete Your Repairs with Less Headache, Updates Included, US-Based Technical Support | D106: innova | E106: Handheld | F106: 287.32292 | G106: 1127455.1 | H106: 3924 | I106: 2889 | J106: 4.4 | K106: https://amazon.com/dp/B07Z481NJM | L106: =HYPERLINK(K106) -> https://amazon.com/dp/B07Z481NJM
A107: 12 | B107: B07Z46L5FG | C107: Innova 5210 OBD2 Scanner & Engine Code Reader, Battery Tester, Live Data, Oil Reset, Car Diagnostic Tool for Most Vehicles, Bluetooth Compatible with America's Top Car Repair App | D107: innova | E107: Handheld | F107: 84.710609 | G107: 265821.89 | H107: 3138 | I107: 3668 | J107: 4.5 | K107: https://amazon.com/dp/B07Z46L5FG | L107: =HYPERLINK(K107) -> https://amazon.com/dp/B07Z46L5FG
... A145: 50 | B145: B0BLRV8QQP | C145: Zmoon OBD2 Scanner Diagnostic Tool, Vehicle Check Engine Code Readers with Reset & I/M Readiness & More, Car OBDII/EOBD Diagnostic Scan Tool for All Vehicles After 1996 | D145: zmoon | E145: Handheld | F145: 19.869085 | G145: 16928.46 | H145: 852 | I145: 1624 | J145: 4.5 | K145: https://amazon.com/dp/B0BLRV8QQP | L145: =HYPERLINK(K145) -> https://amazon.com/dp/B0BLRV8QQP

Sheet Tablet Total
A1: Tablet Monthly Summary
A3: Tablet Overall
B4: Avg Price | C4: Avg Price MoM | D4: Avg Price YoY | E4: Quantity/Mo | F4: Qty by % | G4: Qty MoM | H4: Qty YoY | I4: Revenue/Mo | J4: Revenue by % | L4: Revenue MoM | M4: Revenue YoY
A5: autel | B5: 778.9176 | C5: -0.058217228 | D5: -0.1138579 | E5: 5661 | F5: 0.14304847 | G5: 0.033783784 | H5: 0.20421187 | I5: 4409452.5 | J5: 0.28334702 | K5: -0.026400242 | L5: -0.026400242 | M5: 0.06710284
A6: topdon | B6: 318.11918 | C6: -0.023844596 | D6: -0.032768095 | E6: 9829 | F6: 0.24837014 | G6: 0.20675261 | H6: 1.2826289 | I6: 3126793.5 | J6: 0.20092463 | K6: 0.17797808 | L6: 0.17797808 | M6: 1.2078315
A7: launch | B7: 386.26828 | C7: -0.048693863 | D7: -0.13372217 | E7: 6596 | F7: 0.16667509 | G7: 0.032722718 | H7: 0.2278481 | I7: 2547825.6 | J7: 0.16372073 | K7: -0.017564541 | L7: -0.017564541 | M7: 0.063657585
A8: xtool | B8: 394.61118 | C8: -0.0088289936 | D8: -0.22188385 | E8: 3265 | F8: 0.082503664 | G8: 0.04313099 | H8: 0.9239835 | I8: 1288405.5 | J8: 0.08279165 | K8: 0.033921194 | L8: 0.033921194 | M8: 0.49708264
A9: foxwell | B9: 228.69419 | C9: -0.056322602 | D9: -0.057541937 | E9: 3287 | F9: 0.083059585 | G9: 0.038546603 | H9: -0.07486631 | I9: 751717.8 | J9: 0.048304635 | K9: -0.019947043 | L9: -0.019947043 | M9: -0.12810029
A10: blcktec | B10: 198.0568 | C10: 0.018644659 | E10: 2032 | F10: 0.051346844 | G10: 0.41209173 | I10: 402451.42 | J10: 0.025861126 | K10: 0.4384197 | L10: 0.4384197
A11: innova | B11: 137.95047 | C11: -0.034313523 | E11: 1336 | F11: 0.033759539 | G11: 0.91404011 | I11: 184301.83 | J11: 0.011843052 | K11: 0.84836266 | L11: 0.84836266
A12: Other | B12: 376.72754 | C12: -0.0064107823 | D12: 0.32903884 | E12: 7568 | F12: 0.19123667 | G12: 0.056688076 | H12: 0.50547046 | I12: 2851074 | J12: 0.18320717 | K12: 0.049913879 | L12: 0.049913879 | M12: 1.0008287
A13: Total | B13: =Summary!B7 -> 393.23854 | C13: =Summary!C7 -> -0.059447514 | D13: =Summary!D7 -> -0.12584209 | E13: =Summary!E7 -> 39574 | F13: =SUM(F5:F12) -> 1 | G13: =Summary!G7 -> 0.11156677 | H13: =Summary!H7 -> 0.60504543 | I13: =Summary!I7 -> 15562022 | J13: =SUM(J5:J12) -> 1 | L13: =Summary!K7 -> 0.045486885 | M13: =Summary!L7 -> 0.40306315
A45: Rank By Monthly Revenue - Nov '25 ONLY
A46: Ranking | B46: ASIN | C46: Product Name | D46: Brand | E46: Type | F46: Price | G46: Est. Monthly Retail Rev | H46: Est. Monthly Units Sold | I46: # of Reviews | J46: Avg. Rating | K46: Column2 | L46: Link
A47: 1 | B47: B0744B55QV | C47: Autel Scanner MaxiCOM MK808S: 2025 Bidirectional Tool as MK808BT Pro MX808S M808Z, Work as MaxiCheck MX900 MK900BT, 28+ Service, Active Test, All System Diagnose, Injector C0ding, FCA Autoauth OS 11 | D47: autel | E47: Tablet | F47: 451.83728 | G47: 684985.31 | H47: 1516 | I47: 3604 | J47: 4.5 | K47: https://amazon.com/dp/B0744B55QV | L47: =HYPERLINK(K47) -> https://amazon.com/dp/B0744B55QV
A48: 2 | B48: B0C33Y285Y | C48: TOPDON Bidirectional Scan Tool, 2025 New ArtiDiag900 Lite Automotive Diagnostic Tool for Full System, Scanner for Car with Active Test, 8 Reset, Wireless OBD2 Scanner Diagnostic Tool for All Vehicles | D48: topdon | E48: Tablet | F48: 313.53909 | G48: 520788.43 | H48: 1661 | I48: 999 | J48: 4.3 | K48: https://amazon.com/dp/B0C33Y285Y | L48: =HYPERLINK(K48) -> https://amazon.com/dp/B0C33Y285Y
A49: 3 | B49: B098PYB8XG | C49: Autel Scanner MaxiCOM MK900BT, 2025 MK900-BT V2.0 Bidirectional Diagnostic Tool, 8in Up of MK900 MX900 MK808S MK808BT MX808S MK808Z, 3000+ Active Tests, 40+ Service, CAN-FD&DOIP, All System, FCA 11 OS | D49: autel | E49: Tablet | F49: 659.22073 | G49: 479912.69 | H49: 728 | I49: 580 | J49: 4.6 | K49: https://amazon.com/dp/B098PYB8XG | L49: =HYPERLINK(K49) -> https://amazon.com/dp/B098PYB8XG
A50: 4 | B50: B0DV2N2FND | C50: BLCKTEC 460T OBD2 Scanner Car Code Reader Engine ABS SRS Transmission Diagnostic Tool, 12 Reset Services, Oil/TPMS/EPB/BMS/SAS/DPF/Throttle Reset, ABS Bleeding, Battery Test, Auto VIN, Free Update | D50: blcktec | E50: Tablet | F50: 198.0568 | G50: 402451.42 | H50: 2032 | I50: 312 | J50: 4.4 | K50: https://amazon.com/dp/B0DV2N2FND | L50: =HYPERLINK(K50) -> https://amazon.com/dp/B0DV2N2FND
A51: 5 | B51: B0DCFRF2TF | C51: THINKCAR Bidirectional Scan Tool, THINKSCAN 689BT All System Automotive Diagnostic Tool, Bi Directional OBD2 Scanner with ECU Coding, 34 Services, FCA Autoauth, CANFD and DoIP, Wireless Update | D51: thinkcar | E51: Tablet | F51: 501.58996 | G51: 393748.12 | H51: 785 | I51: 401 | J51: 4.4 | K51: https://amazon.com/dp/B0DCFRF2TF | L51: =HYPERLINK(K51) -> https://amazon.com/dp/B0DCFRF2TF
A52: 6 | B52: B0DTK24XKB | C52: MUCAR 892BT AI-Assisted Bidirectional Scan Tool, Full System OBD2 Scanner, Bi-Directional OBD2 Scanner Diagnostic Tool,ECU Coding, 35 Services, FCA Autoauth, CANFD and DOIP, Free Lifetime Upgrade | D52: mucar | E52: Tablet | F52: 612.13041 | G52: 385030.03 | H52: 629 | I52: 249 | J52: 4.3 | K52: https://amazon.com/dp/B0DTK24XKB | L52: =HYPERLINK(K52) -> https://amazon.com/dp/B0DTK24XKB
A53: 7 | B53: B091BQNR3S | C53: TOPDON Phoenix Plus 2, ECU Code TOPDON Scanner V2.0, Bidirectional Scan Tool, Topology Map, CANFD, High-End OEM Full System, 42+ Service, FCA SGW AutoAuth, V.A.G Guided, 2 Years Free Update | D53: topdon | E53: Tablet | F53: 1096.3385 | G53: 368369.72 | H53: 336 | I53: 447 | J53: 4.5 | K53: https://amazon.com/dp/B091BQNR3S | L53: =HYPERLINK(K53) -> https://amazon.com/dp/B091BQNR3S
A54: 8 | B54: B0BNKHCXVC | C54: TOPDON ArtiDiag Pro OBD2 Scanner Diagnostic Tool, Bidirectional Scan Tool with ECU Coding, 35+ Services, V.A.G Guided, FCA SGW, Can FD DoIP/All System Diagnosis | D54: topdon | E54: Tablet | F54: 478.70164 | G54: 321687.5 | H54: 672 | I54: 677 | J54: 4.4 | K54: https://amazon.com/dp/B0BNKHCXVC | L54: =HYPERLINK(K54) -> https://amazon.com/dp/B0BNKHCXVC
A55: 9 | B55: B08XK3DJ42 | C55: OBD2 Scanner TOPDON AD500, Oil SAS Throttle TPMS BMS EPB Reset, Engine ABS SRS Transmission, Diagnostic Scan Tool, AutoVIN, Car Check Engine Code Reader with Battery Test, Lifetime Wi-Fi Free Update | D55: topdon | E55: Tablet | F55: 149.94128 | G55: 315626.4 | H55: 2105 | I55: 1431 | J55: 4.4 | K55: https://amazon.com/dp/B08XK3DJ42 | L55: =HYPERLINK(K55) -> https://amazon.com/dp/B08XK3DJ42
A56: 10 | B56: B08TR5PS5V | C56: TOPDON AD800BT 2 OBD2 Scanner, 2025 Bidirectional Scan Tool, Function as AD900 Lite AD Pro, All System Automotive Diagnostic Scanner, Active Test, 28+ Reset Service, FCA Autoauth, 2 Years Free Update | D56: topdon | E56: Tablet | F56: 390.68245 | G56: 300044.12 | H56: 768 | I56: 728 | J56: 4.3 | K56: https://amazon.com/dp/B08TR5PS5V | L56: =HYPERLINK(K56) -> https://amazon.com/dp/B08TR5PS5V
A58: Rank By Monthly Units - Nov '25 ONLY
A59: Ranking | B59: ASIN | C59: Product Name | D59: Brand | E59: Type | F59: Price | G59: Est. Monthly Retail Rev | H59: Est. Monthly Units Sold | I59: # of Reviews | J59: Avg. Rating | K59: Column2 | L59: Link
A60: 1 | B60: B08XK3DJ42 | C60: OBD2 Scanner TOPDON AD500, Oil SAS Throttle TPMS BMS EPB Reset, Engine ABS SRS Transmission, Diagnostic Scan Tool, AutoVIN, Car Check Engine Code Reader with Battery Test, Lifetime Wi-Fi Free Update | D60: topdon | E60: Tablet | F60: 149.94128 | G60: 315626.4 | H60: 2105 | I60: 1431 | J60: 4.4 | K60: https://amazon.com/dp/B08XK3DJ42 | L60: =HYPERLINK(K60) -> https://amazon.com/dp/B08XK3DJ42
A61: 2 | B61: B0DV2N2FND | C61: BLCKTEC 460T OBD2 Scanner Car Code Reader Engine ABS SRS Transmission Diagnostic Tool, 12 Reset Services, Oil/TPMS/EPB/BMS/SAS/DPF/Throttle Reset, ABS Bleeding, Battery Test, Auto VIN, Free Update | D61: blcktec | E61: Tablet | F61: 198.0568 | G61: 402451.42 | H61: 2032 | I61: 312 | J61: 4.4 | K61: https://amazon.com/dp/B0DV2N2FND | L61: =HYPERLINK(K61) -> https://amazon.com/dp/B0DV2N2FND
A62: 3 | B62: B0C33Y285Y | C62: TOPDON Bidirectional Scan Tool, 2025 New ArtiDiag900 Lite Automotive Diagnostic Tool for Full System, Scanner for Car with Active Test, 8 Reset, Wireless OBD2 Scanner Diagnostic Tool for All Vehicles | D62: topdon | E62: Tablet | F62: 313.53909 | G62: 520788.43 | H62: 1661 | I62: 999 | J62: 4.3 | K62: https://amazon.com/dp/B0C33Y285Y | L62: =HYPERLINK(K62) -> https://amazon.com/dp/B0C33Y285Y
A63: 4 | B63: B0744B55QV | C63: Autel Scanner MaxiCOM MK808S: 2025 Bidirectional Tool as MK808BT Pro MX808S M808Z, Work as MaxiCheck MX900 MK900BT, 28+ Service, Active Test, All System Diagnose, Injector C0ding, FCA Autoauth OS 11 | D63: autel | E63: Tablet | F63: 451.83728 | G63: 684985.31 | H63: 1516 | I63: 3604 | J63: 4.5 | K63: https://amazon.com/dp/B0744B55QV | L63: =HYPERLINK(K63) -> https://amazon.com/dp/B0744B55QV
A64: 5 | B64: B09KZTYD18 | C64: OBD2 Scanner TOPDON AD600S Scan Tool, Code Reader, Diagnostics Scanner for ABS/SRS/AT/Engine, 9 Reset Services, Oil/Brake/BMS/SAS/DPF/TPMS/ETS Reset/ABS Bleeding/Injector Coding, Free Lifetime Upgrade | D64: topdon | E64: Tablet | F64: 210.06127 | G64: 288414.13 | H64: 1373 | I64: 1535 | J64: 4.4 | K64: https://amazon.com/dp/B09KZTYD18 | L64: =HYPERLINK(K64) -> https://amazon.com/dp/B09KZTYD18
A65: 6 | B65: B08PFJMTY3 | C65: FOXWELL Car Scanner NT604 Elite OBD2 Scanner ABS SRS Transmission, Check Engine Code Reader for Cars and Trucks, Diagnostic Scan Tool with SRS Airbag, Automotive Diagnostic Tool with Live Data | D65: foxwell | E65: Tablet | F65: 158.82678 | G65: 214416.15 | H65: 1350 | I65: 4495 | J65: 4.3 | K65: https://amazon.com/dp/B08PFJMTY3 | L65: =HYPERLINK(K65) -> https://amazon.com/dp/B08PFJMTY3
A66: 7 | B66: B0F254MVB5 | C66: Innova SD35 OBD2 Scanner – ABS, SRS, TPMS & Check Engine Code Reader, Live Data, All System Diagnostics, Compatible with Most Vehicles | D66: innova | E66: Tablet | F66: 129.97499 | G66: 161428.94 | H66: 1242 | I66: 101 | J66: 4.5 | K66: https://amazon.com/dp/B0F254MVB5 | L66: =HYPERLINK(K66) -> https://amazon.com/dp/B0F254MVB5
A67: 8 | B67: B07RLF8FBC | C67: LAUNCH OBD2 Scanner CRP123X Elite, 2025 Lifetime Free WiFi Update scan Tool, FCA SGW, SAS Calibration/Throttle/Brake/BMS/D-P-F/Oil Reset/ABS bleeding, Multi Systems Car Scanner, Battery Test, Auto VIN | D67: launch | E67: Tablet | F67: 160.31228 | G67: 173297.57 | H67: 1081 | I67: 3227 | J67: 4.4 | K67: https://amazon.com/dp/B07RLF8FBC | L67: =HYPERLINK(K67) -> https://amazon.com/dp/B07RLF8FBC
A68: 9 | B68: B0CTHJW813 | C68: TOPDON Upgraded AD600S OBD2 Scanner, Diagnostic Tool, ABS SRS Transmission Engine Code Reader, 9 Reset Services Scan Tool, Oil/Brake/BMS/SAS/DPF/TPMS/ETS Reset, Injector Coding, Lifetime Free Update | D68: topdon | E68: Tablet | F68: 216.01884 | G68: 204785.86 | H68: 948 | I68: 665 | J68: 4.5 | K68: https://amazon.com/dp/B0CTHJW813 | L68: =HYPERLINK(K68) -> https://amazon.com/dp/B0CTHJW813
A69: 10 | B69: B0DCFRF2TF | C69: THINKCAR Bidirectional Scan Tool, THINKSCAN 689BT All System Automotive Diagnostic Tool, Bi Directional OBD2 Scanner with ECU Coding, 34 Services, FCA Autoauth, CANFD and DoIP, Wireless Update | D69: thinkcar | E69: Tablet | F69: 501.58996 | G69: 393748.12 | H69: 785 | I69: 401 | J69: 4.4 | K69: https://amazon.com/dp/B0DCFRF2TF | L69: =HYPERLINK(K69) -> https://amazon.com/dp/B0DCFRF2TF
A71: Tablet $800+
B72: Avg Price | C72: Avg Price MoM | D72: Avg Price YoY | E72: Quantity/Mo | F72: Qty by % | G72: Qty MoM | H72: Qty YoY | I72: Revenue/Mo | J72: Revenue by % | L72: Revenue MoM | M72: Revenue YoY
A73: autel | B73: 1911.1723 | C73: 0.03079727 | D73: -0.051980902 | E73: 1031 | F73: 0.36036351 | G73: -0.16720517 | H73: -0.070333634 | I73: 1970418.6 | J73: 0.4727787 | K73: -0.14155736 | L73: -0.14155736 | M73: -0.11865853
A74: launch | B74: 1279.214 | C74: -0.04524597 | D74: -0.020425317 | E74: 868 | F74: 0.30339042 | G74: 0.1043257 | H74: 0.028436019 | I74: 1110357.8 | J74: 0.26641724 | K74: 0.054359412 | L74: 0.054359412 | M74: 0.0074298873
A75: topdon | B75: 1194.9252 | C75: -0.08924766 | D75: -0.068075016 | E75: 489 | F75: 0.17091926 | G75: 0.4092219 | H75: 1.0720339 | I75: 584318.4 | J75: 0.1402003 | K75: 0.28345214 | L75: 0.28345214 | M75: 0.93098016
A76: xtool | B76: 1457.9837 | C76: 0.051819597 | D76: 0.28148187 | E76: 139 | F76: 0.048584411 | G76: -0.17261905 | H76: -0.060810811 | I76: 202659.74 | J76: 0.048625812 | K76: -0.1297445 | L76: -0.1297445 | M76: 0.20355392
A77: ancel | B77: 829.74557 | C77: -0.048725546 | D77: -0.20974596 | E77: 221 | F77: 0.077245718 | G77: -0.14341085 | H77: 3.1698113 | I77: 183373.77 | J77: 0.043998371 | K77: -0.18514863 | L77: -0.18514863 | M77: 2.2952102
A78: Other | B78: 1031.961 | C78: -0.018190344 | D78: -0.12837299 | E78: 113 | F78: 0.039496679 | G78: -0.20979021 | H78: 0.13 | I78: 116611.59 | J78: 0.027979574 | K78: -0.2241644 | L78: -0.2241644 | M78: -0.015061474
A79: Total | B79: =Summary!B4 -> 1456.7424 | C79: =Summary!C4 -> -0.029265699 | D79: =Summary!D4 -> -0.08928515 | E79: =Summary!E4 -> 2861 | F79: =SUM(F73:F78) -> 1 | G79: =Summary!G4 -> -0.026870748 | H79: =Summary!H4 -> 0.14899598 | I79: =Summary!I4 -> 4167739.9 | J79: =SUM(J73:J78) -> 1 | L79: =Summary!K4 -> -0.055350056 | M79: =Summary!L4 -> 0.046407706
A81: Tablet $400-$800
B82: Avg Price | C82: Avg Price MoM | D82: Avg Price YoY | E82: Quantity/Mo | F82: Qty by % | G82: Qty MoM | H82: Qty YoY | I82: Revenue/Mo | J82: Revenue by % | L82: Revenue MoM | M82: Revenue YoY
A83: autel | B83: 528.17359 | C83: 0.0017846352 | D83: 0.00038571678 | E83: 4587 | F83: 0.42495831 | G83: 0.083372697 | H83: 0.27700445 | I83: 2422732.2 | J83: 0.42568554 | K83: 0.085306122 | L83: 0.085306122 | M83: 0.27749702
A84: thinkcar | B84: 491.03136 | C84: -0.10993403 | D84: 0.088471286 | E84: 1289 | F84: 0.1194182 | G84: 0.13969938 | H84: 21.614035 | I84: 632939.42 | J84: 0.11121046 | K84: 0.014407634 | L84: 0.014407634 | M84: 23.614728
A85: launch | B85: 519.47139 | C85: -0.056736789 | D85: -0.12619994 | E85: 1163 | F85: 0.10774504 | G85: -0.18784916 | H85: 0.17831814 | I85: 604145.23 | J85: 0.10615118 | K85: -0.23392799 | L85: -0.23392799 | M85: 0.029614461
A86: xtool | B86: 534.86478 | C86: 0.010377328 | D86: -0.0088714545 | E86: 1093 | F86: 0.10125996 | G86: 0.13146998 | H86: 0.35776398 | I86: 584607.21 | J86: 0.10271826 | K86: 0.14321161 | L86: 0.14321161 | M86: 0.34571863
A87: topdon | B87: 530.79979 | C87: 0.17806903 | D87: 0.15606933 | E87: 913 | F87: 0.084584028 | G87: -0.52718799 | H87: -0.29661017 | I87: 484620.21 | J87: 0.085150069 | K87: -0.44299481 | L87: -0.44299481 | M87: -0.18683259
A88: Other | B88: 550.21253 | C88: -0.022193195 | D88: 0.041104512 | E88: 1749 | F88: 0.16203446 | G88: 0.26464208 | H88: 0.57425743 | I88: 962321.71 | J88: 0.16908449 | K88: 0.23657563 | L88: 0.23657563 | M88: 0.63896651
A89: Total | B89: =Summary!B5 -> 527.27126 | C89: =Summary!C5 -> 0.0062141033 | D89: =Summary!D5 -> 0.003051364 | E89: =Summary!E5 -> 10794 | F89: =SUM(F83:F88) -> 1 | G89: =Summary!G5 -> -0.025548434 | H89: =Summary!H5 -> 0.37503185 | I89: =Summary!I5 -> 5691366 | J89: =SUM(J83:J88) -> 1 | L89: =Summary!K5 -> -0.019493091 | M89: =Summary!L5 -> 0.37922757
A91: Tablet $400-
B92: Avg Price | C92: Avg Price MoM | D92: Avg Price YoY | E92: Quantity/Mo | F92: Qty by % | G92: Qty MoM | H92: Qty YoY | I92: Revenue/Mo | J92: Revenue by % | L92: Revenue MoM | M92: Revenue YoY
A93: topdon | B93: 244.1978 | C93: 0.0779894 | D93: 0.30764591 | E93: 8427 | F93: 0.32512828 | G93: 0.43633884 | H93: 2.0400433 | I93: 2057854.9 | J93: 0.36084256 | K93: 0.54835805 | L93: 0.54835805 | M93: 2.9753002
A94: launch | B94: 182.54601 | C94: 0.012500387 | D94: -0.084952687 | E94: 4565 | F94: 0.17612562 | G94: 0.094986807 | H94: 0.28918385 | I94: 833322.54 | J94: 0.14612218 | K94: 0.10867457 | L94: 0.10867457 | M94: 0.17966421
A95: foxwell | B95: 191.86211 | C95: -0.057409781 | D95: -0.069300025 | E95: 2973 | F95: 0.1147035 | G95: 0.049788136 | H95: -0.063916877 | I95: 570406.05 | J95: 0.10002007 | K95: -0.010479971 | L95: -0.010479971 | M95: -0.12878746
A96: xtool | B96: 246.50199 | C96: -0.019666903 | D96: -0.28862292 | E96: 2033 | F96: 0.078436668 | G96: 0.018537074 | H96: 1.7325269 | I96: 501138.54 | J96: 0.087874086 | K96: -0.0014943955 | L96: -0.0014943955 | M96: 0.94385699
A97: blcktec | B97: 198.0568 | C97: 0.018644659 | E97: 2032 | F97: 0.078398086 | G97: 0.41209173 | I97: 402451.42 | J97: 0.070569409 | K97: 0.4384197 | L97: 0.4384197
A98: innova | B98: 137.95047 | C98: -0.034313523 | E98: 1336 | F98: 0.051545199 | G98: 0.91404011 | I98: 184301.83 | J98: 0.032317121 | K98: 0.84836266 | L98: 0.84836266
A99: Other | B99: 253.33645 | C99: 0.027722874 | D99: 0.22342632 | E99: 4553 | F99: 0.17566264 | G99: -0.0067626527 | H99: 0.11511144 | I99: 1153440.9 | J99: 0.20225457 | K99: 0.020772741 | L99: 0.020772741 | M99: 0.36425669
A100: Total | B100: =Summary!B6 -> 220.0284 | C100: =Summary!C6 -> 0.017310952 | D100: =Summary!C6 -> 0.017310952 | E100: =Summary!E6 -> 25919 | F100: =SUM(F93:F99) -> 1 | G100: =Summary!G6 -> 0.20078758 | H100: =Summary!H6 -> 0.81049176 | I100: =Summary!I6 -> 5702916.1 | J100: =SUM(J93:J99) -> 1 | L100: =Summary!K6 -> 0.22157436 | M100: =Summary!L6 -> 0.91240071

Sheet Tablet $800+
A1: Tablet $800+ Monthly Summary
A3: ='Tablet Total'!A71 -> Tablet $800+
B4: Avg Price | C4: Avg Price MoM | D4: Avg Price YoY | E4: Quantity/Mo | F4: Qty by % | G4: Qty MoM | H4: Qty YoY | I4: Revenue/Mo | J4: Revenue by % | L4: Revenue MoM | M4: Revenue YoY
A5: ='Tablet Total'!A73 -> autel | B5: ='Tablet Total'!B73 -> 1911.1723 | C5: ='Tablet Total'!C73 -> 0.03079727 | D5: ='Tablet Total'!D73 -> -0.051980902 | E5: ='Tablet Total'!E73 -> 1031 | F5: ='Tablet Total'!F73 -> 0.36036351 | G5: ='Tablet Total'!G73 -> -0.16720517 | H5: ='Tablet Total'!H73 -> -0.070333634 | ... J5: ='Tablet Total'!J73 -> 0.4727787 | L5: ='Tablet Total'!L73 -> -0.14155736 | M5: ='Tablet Total'!M73 -> -0.11865853
A6: ='Tablet Total'!A74 -> launch | B6: ='Tablet Total'!B74 -> 1279.214 | C6: ='Tablet Total'!C74 -> -0.04524597 | D6: ='Tablet Total'!D74 -> -0.020425317 | E6: ='Tablet Total'!E74 -> 868 | F6: ='Tablet Total'!F74 -> 0.30339042 | G6: ='Tablet Total'!G74 -> 0.1043257 | H6: ='Tablet Total'!H74 -> 0.028436019 | ... J6: ='Tablet Total'!J74 -> 0.26641724 | L6: ='Tablet Total'!L74 -> 0.054359412 | M6: ='Tablet Total'!M74 -> 0.0074298873
A7: ='Tablet Total'!A75 -> topdon | B7: ='Tablet Total'!B75 -> 1194.9252 | C7: ='Tablet Total'!C75 -> -0.08924766 | D7: ='Tablet Total'!D75 -> -0.068075016 | E7: ='Tablet Total'!E75 -> 489 | F7: ='Tablet Total'!F75 -> 0.17091926 | G7: ='Tablet Total'!G75 -> 0.4092219 | H7: ='Tablet Total'!H75 -> 1.0720339 | ... J7: ='Tablet Total'!J75 -> 0.1402003 | L7: ='Tablet Total'!L75 -> 0.28345214 | M7: ='Tablet Total'!M75 -> 0.93098016
A8: ='Tablet Total'!A76 -> xtool | B8: ='Tablet Total'!B76 -> 1457.9837 | C8: ='Tablet Total'!C76 -> 0.051819597 | D8: ='Tablet Total'!D76 -> 0.28148187 | E8: ='Tablet Total'!E76 -> 139 | F8: ='Tablet Total'!F76 -> 0.048584411 | G8: ='Tablet Total'!G76 -> -0.17261905 | H8: ='Tablet Total'!H76 -> -0.060810811 | ... J8: ='Tablet Total'!J76 -> 0.048625812 | L8: ='Tablet Total'!L76 -> -0.1297445 | M8: ='Tablet Total'!M76 -> 0.20355392
A9: ='Tablet Total'!A77 -> ancel | B9: ='Tablet Total'!B77 -> 829.74557 | C9: ='Tablet Total'!C77 -> -0.048725546 | D9: ='Tablet Total'!D77 -> -0.20974596 | E9: ='Tablet Total'!E77 -> 221 | F9: ='Tablet Total'!F77 -> 0.077245718 | G9: ='Tablet Total'!G77 -> -0.14341085 | H9: ='Tablet Total'!H77 -> 3.1698113 | ... J9: ='Tablet Total'!J77 -> 0.043998371 | L9: ='Tablet Total'!L77 -> -0.18514863 | M9: ='Tablet Total'!M77 -> 2.2952102
A10: ='Tablet Total'!A78 -> Other | B10: ='Tablet Total'!B78 -> 1031.961 | C10: ='Tablet Total'!C78 -> -0.018190344 | D10: ='Tablet Total'!D78 -> -0.12837299 | E10: ='Tablet Total'!E78 -> 113 | F10: ='Tablet Total'!F78 -> 0.039496679 | G10: ='Tablet Total'!G78 -> -0.20979021 | H10: ='Tablet Total'!H78 -> 0.13 | ... J10: ='Tablet Total'!J78 -> 0.027979574 | L10: ='Tablet Total'!L78 -> -0.2241644 | M10: ='Tablet Total'!M78 -> -0.015061474
A11: ='Tablet Total'!A79 -> Total | B11: ='Tablet Total'!B79 -> 1456.7424 | C11: ='Tablet Total'!C79 -> -0.029265699 | D11: ='Tablet Total'!D79 -> -0.08928515 | E11: ='Tablet Total'!E79 -> 2861 | F11: ='Tablet Total'!F79 -> 1 | G11: ='Tablet Total'!G79 -> -0.026870748 | H11: ='Tablet Total'!H79 -> 0.14899598 | ... J11: ='Tablet Total'!J79 -> 1 | L11: ='Tablet Total'!L79 -> -0.055350056 | M11: ='Tablet Total'!M79 -> 0.046407706
A43: Rank By Monthly Revenue - Nov '25 ONLY
A44: Ranking | B44: ASIN | C44: Product Name | D44: Brand | E44: Type | F44: Price | G44: Est. Monthly Retail Rev | H44: Est. Monthly Units Sold | I44: # of Reviews | J44: Avg. Rating | K44: Column2 | L44: Link
A45: 1 | B45: B091BQNR3S | C45: TOPDON Phoenix Plus 2, ECU Code TOPDON Scanner V2.0, Bidirectional Scan Tool, Topology Map, CANFD, High-End OEM Full System, 42+ Service, FCA SGW AutoAuth, V.A.G Guided, 2 Years Free Update | D45: topdon | E45: Tablet | F45: 1096.3385 | G45: 368369.72 | H45: 336 | I45: 447 | J45: 4.5 | K45: https://amazon.com/dp/B091BQNR3S | L45: =HYPERLINK(K45) -> https://amazon.com/dp/B091BQNR3S
A46: 2 | B46: B0BZ82WQ4Q | C46: ANCEL X7HD 10'' Heavy Duty Truck Scanner, Semi Trucks Full System Diagnostic Tool, Bidirectional Diesel Scan Tool with DPF, ECU Coding, 40+ Reset for Cummins, Detroit, Caterpillar, Volvo, Paccar etc | D46: ancel | E46: Tablet | F46: 815.06799 | G46: 170349.21 | H46: 209 | I46: 764 | J46: 3.9 | K46: https://amazon.com/dp/B0BZ82WQ4Q | L46: =HYPERLINK(K46) -> https://amazon.com/dp/B0BZ82WQ4Q
A47: 3 | B47: B0DZC1M7MZ | C47: Autel MaxiSys Ultra S2 Scanner, 2025 Top Intelligen Scan Diagnostic with AI, 6-in-1 VCMI2, Up of MSUltra/ MS919, Topology 3.0, Multi-Point DVI, Programming, Motor Truspeed Repair, EV Test, 48+ Service | D47: autel | E47: Tablet | F47: 5586.271 | G47: 162001.86 | H47: 29 | I47: 16 | J47: 4.6 | K47: https://amazon.com/dp/B0DZC1M7MZ | L47: =HYPERLINK(K47) -> https://amazon.com/dp/B0DZC1M7MZ
A48: 4 | B48: B08V59JNYP | C48: LAUNCH X431 PRO3S+ Smartlink HD Heavy Duty Truck Scanner,2025 Diesel&Gasoline Bidirectional Diagnostic Scan Tool with J2534 Protocols,Topology Map,60+Service,ECU Code,CANFD &DOIP,2 Yrs Free Update | D48: launch | E48: Tablet | F48: 1898.2964 | G48: 146168.82 | H48: 77 | I48: 169 | J48: 4.3 | K48: https://amazon.com/dp/B08V59JNYP | L48: =HYPERLINK(K48) -> https://amazon.com/dp/B08V59JNYP
A49: 5 | B49: B0D7VS8SHS | C49: LAUNCH X431 PRO3S+ Elite, 2025 All-in-One Bidirectional Scan Tool with J2534 Protocols, HD Trucks Scanner, Topology Map, 60+Service, ECU Code Full Function Scanner, CANFD/DoIP/D-PDU/FCA, 2 Yrs Update | D49: launch | E49: Tablet | F49: 1268.8326 | G49: 131958.59 | H49: 104 | I49: 110 | J49: 4.3 | K49: https://amazon.com/dp/B0D7VS8SHS | L49: =HYPERLINK(K49) -> https://amazon.com/dp/B0D7VS8SHS
A50: 6 | B50: B092894STV | C50: Launch X431 PRO3S+ V5.0,2025 Upgrade All-in-One Bidirectional Scan Tool,HD Trucks Scan,Topology Map,ECU Code,55+ Service,Full System,CANFD&DOIP,DBSCar VII VCI 2-Year Update | D50: launch | E50: Tablet | F50: 1036.781 | G50: 81905.7 | H50: 79 | I50: 635 | J50: 4.2 | K50: https://amazon.com/dp/B092894STV | L50: =HYPERLINK(K50) -> https://amazon.com/dp/B092894STV
A51: 7 | B51: B0DBLQXQ6W | C51: XTOOL IP919 PRO Scan Tool, ECU Pr0 gramming Car OBD2 Scanner with Topology Mapping, Upgrade of D9S PRO, 51+ Resets, ECU C 0ding, FCA/CAN FD/DoIP, Automotive Bidirectional Scan Tool with 3-Year Updates | D51: xtool | E51: Tablet | F51: 1601.6151 | G51: 81682.37 | H51: 51 | I51: 61 | J51: 4.5 | K51: https://amazon.com/dp/B0DBLQXQ6W | L51: =HYPERLINK(K51) -> https://amazon.com/dp/B0DBLQXQ6W
A52: 8 | B52: B0CLS8B1BK | C52: LAUNCH X431 PROS V 5.0, Bidirectional Scan Tool PROS V+ 5.0 Elite with 2025 Newly Released DBSCar VII Connector,38+ Reset for All Cars,ECU Online Coding,CANFD,FCA AutoAuth,VAG Guide,2 Yrs F-Ree Update | D52: launch | E52: Tablet | F52: 826.64878 | G52: 74398.39 | H52: 90 | I52: 214 | J52: 4.4 | K52: https://amazon.com/dp/B0CLS8B1BK | L52: =HYPERLINK(K52) -> https://amazon.com/dp/B0CLS8B1BK
A53: 9 | B53: B01GRN4BRQ | C53: LAUNCH X431 PRO V 5.0,2025 New Gen. OEM Bluetooth Bidirectional Scan Tool w/Canfd Doip,Same as Pro3s+ 5.0,Online Code & 38+ Reset for All Cars,2 Yrs Free Update | D53: launch | E53: Tablet | F53: 815.80747 | G53: 70975.25 | H53: 87 | I53: 1035 | J53: 4.3 | K53: https://amazon.com/dp/B01GRN4BRQ | L53: =HYPERLINK(K53) -> https://amazon.com/dp/B01GRN4BRQ
A54: 10 | B54: B0F2HNM2VH | C54: LAUNCH Scanner X431 1MM* Plus Car Tool with X-PROG3 (Valued $800), Engine/Gearbox ECU Cl**é, All-in-One Diagnostic Tool, ECU Coding as X431 PAD, 39+ Services, All-System Scan, 2-Year Update | D54: launch | E54: Tablet | F54: 1467.1006 | G54: 68953.73 | H54: 47 | I54: 36 | J54: 4 | K54: https://amazon.com/dp/B0F2HNM2VH | L54: =HYPERLINK(K54) -> https://amazon.com/dp/B0F2HNM2VH
A56: Rank By Monthly Units - Nov '25 ONLY
A57: Ranking | B57: ASIN | C57: Product Name | D57: Brand | E57: Type | F57: Price | G57: Est. Monthly Retail Rev | H57: Est. Monthly Units Sold | I57: # of Reviews | J57: Avg. Rating | K57: Column2 | L57: Link
A58: 1 | B58: B091BQNR3S | C58: TOPDON Phoenix Plus 2, ECU Code TOPDON Scanner V2.0, Bidirectional Scan Tool, Topology Map, CANFD, High-End OEM Full System, 42+ Service, FCA SGW AutoAuth, V.A.G Guided, 2 Years Free Update | D58: topdon | E58: Tablet | F58: 1096.3385 | G58: 368369.72 | H58: 336 | I58: 447 | J58: 4.5 | K58: https://amazon.com/dp/B091BQNR3S | L58: =HYPERLINK(K58) -> https://amazon.com/dp/B091BQNR3S
A59: 2 | B59: B0BZ82WQ4Q | C59: ANCEL X7HD 10'' Heavy Duty Truck Scanner, Semi Trucks Full System Diagnostic Tool, Bidirectional Diesel Scan Tool with DPF, ECU Coding, 40+ Reset for Cummins, Detroit, Caterpillar, Volvo, Paccar etc | D59: ancel | E59: Tablet | F59: 815.06799 | G59: 170349.21 | H59: 209 | I59: 764 | J59: 3.9 | K59: https://amazon.com/dp/B0BZ82WQ4Q | L59: =HYPERLINK(K59) -> https://amazon.com/dp/B0BZ82WQ4Q
A60: 3 | B60: B0D7VS8SHS | C60: LAUNCH X431 PRO3S+ Elite, 2025 All-in-One Bidirectional Scan Tool with J2534 Protocols, HD Trucks Scanner, Topology Map, 60+Service, ECU Code Full Function Scanner, CANFD/DoIP/D-PDU/FCA, 2 Yrs Update | D60: launch | E60: Tablet | F60: 1268.8326 | G60: 131958.59 | H60: 104 | I60: 110 | J60: 4.3 | K60: https://amazon.com/dp/B0D7VS8SHS | L60: =HYPERLINK(K60) -> https://amazon.com/dp/B0D7VS8SHS
A61: 4 | B61: B0CLS8B1BK | C61: LAUNCH X431 PROS V 5.0, Bidirectional Scan Tool PROS V+ 5.0 Elite with 2025 Newly Released DBSCar VII Connector,38+ Reset for All Cars,ECU Online Coding,CANFD,FCA AutoAuth,VAG Guide,2 Yrs F-Ree Update | D61: launch | E61: Tablet | F61: 826.64878 | G61: 74398.39 | H61: 90 | I61: 214 | J61: 4.4 | K61: https://amazon.com/dp/B0CLS8B1BK | L61: =HYPERLINK(K61) -> https://amazon.com/dp/B0CLS8B1BK
A62: 5 | B62: B01GRN4BRQ | C62: LAUNCH X431 PRO V 5.0,2025 New Gen. OEM Bluetooth Bidirectional Scan Tool w/Canfd Doip,Same as Pro3s+ 5.0,Online Code & 38+ Reset for All Cars,2 Yrs Free Update | D62: launch | E62: Tablet | F62: 815.80747 | G62: 70975.25 | H62: 87 | I62: 1035 | J62: 4.3 | K62: https://amazon.com/dp/B01GRN4BRQ | L62: =HYPERLINK(K62) -> https://amazon.com/dp/B01GRN4BRQ
A63: 6 | B63: B092894STV | C63: Launch X431 PRO3S+ V5.0,2025 Upgrade All-in-One Bidirectional Scan Tool,HD Trucks Scan,Topology Map,ECU Code,55+ Service,Full System,CANFD&DOIP,DBSCar VII VCI 2-Year Update | D63: launch | E63: Tablet | F63: 1036.781 | G63: 81905.7 | H63: 79 | I63: 635 | J63: 4.2 | K63: https://amazon.com/dp/B092894STV | L63: =HYPERLINK(K63) -> https://amazon.com/dp/B092894STV
A64: 7 | B64: B08V59JNYP | C64: LAUNCH X431 PRO3S+ Smartlink HD Heavy Duty Truck Scanner,2025 Diesel&Gasoline Bidirectional Diagnostic Scan Tool with J2534 Protocols,Topology Map,60+Service,ECU Code,CANFD &DOIP,2 Yrs Free Update | D64: launch | E64: Tablet | F64: 1898.2964 | G64: 146168.82 | H64: 77 | I64: 169 | J64: 4.3 | K64: https://amazon.com/dp/B08V59JNYP | L64: =HYPERLINK(K64) -> https://amazon.com/dp/B08V59JNYP
A65: 8 | B65: B0DFLWDPK2 | C65: TOPDON Phoenix Lite 3, 2025 Upgraded Scanner of Lite 2, Bidirectional Scan Tool with CAN-FD, Car Scanner Diagnostic Tool, 35+ Maintenance Resets, Topology Mapping, ECU Coding, FCA Autoauth | D65: topdon | E65: Tablet | F65: 863.2663 | G65: 46616.38 | H65: 54 | I65: 13 | J65: 4.6 | K65: https://amazon.com/dp/B0DFLWDPK2 | L65: =HYPERLINK(K65) -> https://amazon.com/dp/B0DFLWDPK2
A66: 9 | B66: B0DBLQXQ6W | C66: XTOOL IP919 PRO Scan Tool, ECU Pr0 gramming Car OBD2 Scanner with Topology Mapping, Upgrade of D9S PRO, 51+ Resets, ECU C 0ding, FCA/CAN FD/DoIP, Automotive Bidirectional Scan Tool with 3-Year Updates | D66: xtool | E66: Tablet | F66: 1601.6151 | G66: 81682.37 | H66: 51 | I66: 61 | J66: 4.5 | K66: https://amazon.com/dp/B0DBLQXQ6W | L66: =HYPERLINK(K66) -> https://amazon.com/dp/B0DBLQXQ6W
A67: 10 | B67: B0F2HNM2VH | C67: LAUNCH Scanner X431 1MM* Plus Car Tool with X-PROG3 (Valued $800), Engine/Gearbox ECU Cl**é, All-in-One Diagnostic Tool, ECU Coding as X431 PAD, 39+ Services, All-System Scan, 2-Year Update | D67: launch | E67: Tablet | F67: 1467.1006 | G67: 68953.73 | H67: 47 | I67: 36 | J67: 4 | K67: https://amazon.com/dp/B0F2HNM2VH | L67: =HYPERLINK(K67) -> https://amazon.com/dp/B0F2HNM2VH

Sheet Tablet $400-$800
A1: Tablet $400-$800 Monthly Summary
A3: ='Tablet Total'!A81 -> Tablet $400-$800
B4: Avg Price | C4: Avg Price MoM | D4: Avg Price YoY | E4: Quantity/Mo | F4: Qty by % | G4: Qty MoM | H4: Qty YoY | I4: Revenue/Mo | J4: Revenue by % | L4: Revenue MoM | M4: Revenue YoY
A5: ='Tablet Total'!A83 -> autel | B5: ='Tablet Total'!B83 -> 528.17359 | C5: ='Tablet Total'!C83 -> 0.0017846352 | D5: ='Tablet Total'!D83 -> 0.00038571678 | E5: ='Tablet Total'!E83 -> 4587 | F5: ='Tablet Total'!F83 -> 0.42495831 | G5: ='Tablet Total'!G83 -> 0.083372697 | H5: ='Tablet Total'!H83 -> 0.27700445 | ... J5: ='Tablet Total'!J83 -> 0.42568554 | L5: ='Tablet Total'!L83 -> 0.085306122 | M5: ='Tablet Total'!M83 -> 0.27749702
A6: ='Tablet Total'!A84 -> thinkcar | B6: ='Tablet Total'!B84 -> 491.03136 | C6: ='Tablet Total'!C84 -> -0.10993403 | D6: ='Tablet Total'!D84 -> 0.088471286 | E6: ='Tablet Total'!E84 -> 1289 | F6: ='Tablet Total'!F84 -> 0.1194182 | G6: ='Tablet Total'!G84 -> 0.13969938 | H6: ='Tablet Total'!H84 -> 21.614035 | ... J6: ='Tablet Total'!J84 -> 0.11121046 | L6: ='Tablet Total'!L84 -> 0.014407634 | M6: ='Tablet Total'!M84 -> 23.614728
A7: ='Tablet Total'!A85 -> launch | B7: ='Tablet Total'!B85 -> 519.47139 | C7: ='Tablet Total'!C85 -> -0.056736789 | D7: ='Tablet Total'!D85 -> -0.12619994 | E7: ='Tablet Total'!E85 -> 1163 | F7: ='Tablet Total'!F85 -> 0.10774504 | G7: ='Tablet Total'!G85 -> -0.18784916 | H7: ='Tablet Total'!H85 -> 0.17831814 | ... J7: ='Tablet Total'!J85 -> 0.10615118 | L7: ='Tablet Total'!L85 -> -0.23392799 | M7: ='Tablet Total'!M85 -> 0.029614461
A8: ='Tablet Total'!A86 -> xtool | B8: ='Tablet Total'!B86 -> 534.86478 | C8: ='Tablet Total'!C86 -> 0.010377328 | D8: ='Tablet Total'!D86 -> -0.0088714545 | E8: ='Tablet Total'!E86 -> 1093 | F8: ='Tablet Total'!F86 -> 0.10125996 | G8: ='Tablet Total'!G86 -> 0.13146998 | H8: ='Tablet Total'!H86 -> 0.35776398 | ... J8: ='Tablet Total'!J86 -> 0.10271826 | L8: ='Tablet Total'!L86 -> 0.14321161 | M8: ='Tablet Total'!M86 -> 0.34571863
A9: ='Tablet Total'!A87 -> topdon | B9: ='Tablet Total'!B87 -> 530.79979 | C9: ='Tablet Total'!C87 -> 0.17806903 | D9: ='Tablet Total'!D87 -> 0.15606933 | E9: ='Tablet Total'!E87 -> 913 | F9: ='Tablet Total'!F87 -> 0.084584028 | G9: ='Tablet Total'!G87 -> -0.52718799 | H9: ='Tablet Total'!H87 -> -0.29661017 | ... J9: ='Tablet Total'!J87 -> 0.085150069 | L9: ='Tablet Total'!L87 -> -0.44299481 | M9: ='Tablet Total'!M87 -> -0.18683259
A10: ='Tablet Total'!A88 -> Other | B10: ='Tablet Total'!B88 -> 550.21253 | C10: ='Tablet Total'!C88 -> -0.022193195 | D10: ='Tablet Total'!D88 -> 0.041104512 | E10: ='Tablet Total'!E88 -> 1749 | F10: ='Tablet Total'!F88 -> 0.16203446 | G10: ='Tablet Total'!G88 -> 0.26464208 | H10: ='Tablet Total'!H88 -> 0.57425743 | ... J10: ='Tablet Total'!J88 -> 0.16908449 | L10: ='Tablet Total'!L88 -> 0.23657563 | M10: ='Tablet Total'!M88 -> 0.63896651
A11: ='Tablet Total'!A89 -> Total | B11: ='Tablet Total'!B89 -> 527.27126 | C11: ='Tablet Total'!C89 -> 0.0062141033 | D11: ='Tablet Total'!D89 -> 0.003051364 | E11: ='Tablet Total'!E89 -> 10794 | F11: ='Tablet Total'!F89 -> 1 | G11: ='Tablet Total'!G89 -> -0.025548434 | H11: ='Tablet Total'!H89 -> 0.37503185 | ... J11: ='Tablet Total'!J89 -> 1 | L11: ='Tablet Total'!L89 -> -0.019493091 | M11: ='Tablet Total'!M89 -> 0.37922757
A43: Rank By Monthly Revenue - Nov '25 ONLY
A44: Ranking | B44: ASIN | C44: Product Name | D44: Brand | E44: Type | F44: Price | G44: Est. Monthly Retail Rev | H44: Est. Monthly Units Sold | I44: # of Reviews | J44: Avg. Rating | K44: Column2 | L44: Link
A45: 1 | B45: B0744B55QV | C45: Autel Scanner MaxiCOM MK808S: 2025 Bidirectional Tool as MK808BT Pro MX808S M808Z, Work as MaxiCheck MX900 MK900BT, 28+ Service, Active Test, All System Diagnose, Injector C0ding, FCA Autoauth OS 11 | D45: autel | E45: Tablet | F45: 451.83728 | G45: 684985.31 | H45: 1516 | I45: 3604 | J45: 4.5 | K45: https://amazon.com/dp/B0744B55QV | L45: =HYPERLINK(K45) -> https://amazon.com/dp/B0744B55QV
A46: 2 | B46: B098PYB8XG | C46: Autel Scanner MaxiCOM MK900BT, 2025 MK900-BT V2.0 Bidirectional Diagnostic Tool, 8in Up of MK900 MX900 MK808S MK808BT MX808S MK808Z, 3000+ Active Tests, 40+ Service, CAN-FD&DOIP, All System, FCA 11 OS | D46: autel | E46: Tablet | F46: 659.22073 | G46: 479912.69 | H46: 728 | I46: 580 | J46: 4.6 | K46: https://amazon.com/dp/B098PYB8XG | L46: =HYPERLINK(K46) -> https://amazon.com/dp/B098PYB8XG
A47: 3 | B47: B0DCFRF2TF | C47: THINKCAR Bidirectional Scan Tool, THINKSCAN 689BT All System Automotive Diagnostic Tool, Bi Directional OBD2 Scanner with ECU Coding, 34 Services, FCA Autoauth, CANFD and DoIP, Wireless Update | D47: thinkcar | E47: Tablet | F47: 501.58996 | G47: 393748.12 | H47: 785 | I47: 401 | J47: 4.4 | K47: https://amazon.com/dp/B0DCFRF2TF | L47: =HYPERLINK(K47) -> https://amazon.com/dp/B0DCFRF2TF
A48: 4 | B48: B0DTK24XKB | C48: MUCAR 892BT AI-Assisted Bidirectional Scan Tool, Full System OBD2 Scanner, Bi-Directional OBD2 Scanner Diagnostic Tool,ECU Coding, 35 Services, FCA Autoauth, CANFD and DOIP, Free Lifetime Upgrade | D48: mucar | E48: Tablet | F48: 612.13041 | G48: 385030.03 | H48: 629 | I48: 249 | J48: 4.3 | K48: https://amazon.com/dp/B0DTK24XKB | L48: =HYPERLINK(K48) -> https://amazon.com/dp/B0DTK24XKB
A49: 5 | B49: B0BNKHCXVC | C49: TOPDON ArtiDiag Pro OBD2 Scanner Diagnostic Tool, Bidirectional Scan Tool with ECU Coding, 35+ Services, V.A.G Guided, FCA SGW, Can FD DoIP/All System Diagnosis | D49: topdon | E49: Tablet | F49: 478.70164 | G49: 321687.5 | H49: 672 | I49: 677 | J49: 4.4 | K49: https://amazon.com/dp/B0BNKHCXVC | L49: =HYPERLINK(K49) -> https://amazon.com/dp/B0BNKHCXVC
A50: 6 | B50: B08ML7T7KZ | C50: Autel Scanner MaxiCheck MX808S, 2025 US Ver. of MaxiCOM MK808S/ MK808Z, Bidirectional 11OS as MX900 MK900 MK900BT, 3000+ Active Test, 28+ Service, OE All System OBDII Diagnostic Tool, FCA Autoauth | D50: autel | E50: Tablet | F50: 443.71323 | G50: 287526.17 | H50: 648 | I50: 643 | J50: 4.7 | K50: https://amazon.com/dp/B08ML7T7KZ | L50: =HYPERLINK(K50) -> https://amazon.com/dp/B08ML7T7KZ
A51: 7 | B51: B0DCFF7VGF | C51: THINKCAR THINKSCAN 689 OBD2 Scanner, Bidirectional Scan Tool with Lifetime Free Update, 34+ Reset, 3000+ Active Test, ECU Coding, PMI, All System Diagnostic Scanner for Cars, CANFD & DOIP, FCA SGW | D51: thinkcar | E51: Tablet | F51: 475.76669 | G51: 234077.21 | H51: 492 | I51: 181 | J51: 4.4 | K51: https://amazon.com/dp/B0DCFF7VGF | L51: =HYPERLINK(K51) -> https://amazon.com/dp/B0DCFF7VGF
A52: 8 | B52: B073CQMF25 | C52: Autel Scanner MaxiCOM MK900: 2025 Same as MK900BT MK900-BT MX900 Bidirectional Diagnostic Tool, 8in Up of MK808S MK808BT Pro MX808S MK808Z, 3K+ Active Tests, 40+ Service, CAN-FD&DOIP, All System, FCA | D52: autel | E52: Tablet | F52: 546.5021 | G52: 159032.11 | H52: 291 | I52: 265 | J52: 4.4 | K52: https://amazon.com/dp/B073CQMF25 | L52: =HYPERLINK(K52) -> https://amazon.com/dp/B073CQMF25
A53: 9 | B53: B07MBSZH48 | C53: Autel Scanner MaxiCOM MK808BT PRO, 2025 2.0 Full Bidirectional Diagnostic Tool as MK900 MX900 MK900BT, Pro Ver. of MK808S MX808S, 3000+ Test, 28+ Service, All System, Brake Bleed, Injector Coding, FCA | D53: autel | E53: Tablet | F53: 512.48232 | G53: 154769.66 | H53: 302 | I53: 1750 | J53: 4.6 | K53: https://amazon.com/dp/B07MBSZH48 | L53: =HYPERLINK(K53) -> https://amazon.com/dp/B07MBSZH48
A54: 10 | B54: B09712X5CW | C54: Autel Scanner MaxiCOM MK900BT, 2025 MK900-BT Bidirectional Diagnostic Scan Tool, 2.0 BT Ver. of MK900 MX900, 8in Up of MK808S MK808BT PRO MX808S MK808Z, 40+ Reset, 3K+ Active Tests, CAN FD & DoIP, FCA | D54: autel | E54: Tablet | F54: 659.10106 | G54: 112047.18 | H54: 170 | I54: 165 | J54: 4.6 | K54: https://amazon.com/dp/B09712X5CW | L54: =HYPERLINK(K54) -> https://amazon.com/dp/B09712X5CW
A56: Rank By Monthly Units - Nov '25 ONLY
A57: Ranking | B57: ASIN | C57: Product Name | D57: Brand | E57: Type | F57: Price | G57: Est. Monthly Retail Rev | H57: Est. Monthly Units Sold | I57: # of Reviews | J57: Avg. Rating | K57: Column2 | L57: Link
A58: 1 | B58: B0744B55QV | C58: Autel Scanner MaxiCOM MK808S: 2025 Bidirectional Tool as MK808BT Pro MX808S M808Z, Work as MaxiCheck MX900 MK900BT, 28+ Service, Active Test, All System Diagnose, Injector C0ding, FCA Autoauth OS 11 | D58: autel | E58: Tablet | F58: 451.83728 | G58: 684985.31 | H58: 1516 | I58: 3604 | J58: 4.5 | K58: https://amazon.com/dp/B0744B55QV | L58: =HYPERLINK(K58) -> https://amazon.com/dp/B0744B55QV
A59: 2 | B59: B0DCFRF2TF | C59: THINKCAR Bidirectional Scan Tool, THINKSCAN 689BT All System Automotive Diagnostic Tool, Bi Directional OBD2 Scanner with ECU Coding, 34 Services, FCA Autoauth, CANFD and DoIP, Wireless Update | D59: thinkcar | E59: Tablet | F59: 501.58996 | G59: 393748.12 | H59: 785 | I59: 401 | J59: 4.4 | K59: https://amazon.com/dp/B0DCFRF2TF | L59: =HYPERLINK(K59) -> https://amazon.com/dp/B0DCFRF2TF
A60: 3 | B60: B098PYB8XG | C60: Autel Scanner MaxiCOM MK900BT, 2025 MK900-BT V2.0 Bidirectional Diagnostic Tool, 8in Up of MK900 MX900 MK808S MK808BT MX808S MK808Z, 3000+ Active Tests, 40+ Service, CAN-FD&DOIP, All System, FCA 11 OS | D60: autel | E60: Tablet | F60: 659.22073 | G60: 479912.69 | H60: 728 | I60: 580 | J60: 4.6 | K60: https://amazon.com/dp/B098PYB8XG | L60: =HYPERLINK(K60) -> https://amazon.com/dp/B098PYB8XG
A61: 4 | B61: B0BNKHCXVC | C61: TOPDON ArtiDiag Pro OBD2 Scanner Diagnostic Tool, Bidirectional Scan Tool with ECU Coding, 35+ Services, V.A.G Guided, FCA SGW, Can FD DoIP/All System Diagnosis | D61: topdon | E61: Tablet | F61: 478.70164 | G61: 321687.5 | H61: 672 | I61: 677 | J61: 4.4 | K61: https://amazon.com/dp/B0BNKHCXVC | L61: =HYPERLINK(K61) -> https://amazon.com/dp/B0BNKHCXVC
A62: 5 | B62: B08ML7T7KZ | C62: Autel Scanner MaxiCheck MX808S, 2025 US Ver. of MaxiCOM MK808S/ MK808Z, Bidirectional 11OS as MX900 MK900 MK900BT, 3000+ Active Test, 28+ Service, OE All System OBDII Diagnostic Tool, FCA Autoauth | D62: autel | E62: Tablet | F62: 443.71323 | G62: 287526.17 | H62: 648 | I62: 643 | J62: 4.7 | K62: https://amazon.com/dp/B08ML7T7KZ | L62: =HYPERLINK(K62) -> https://amazon.com/dp/B08ML7T7KZ
A63: 6 | B63: B0DTK24XKB | C63: MUCAR 892BT AI-Assisted Bidirectional Scan Tool, Full System OBD2 Scanner, Bi-Directional OBD2 Scanner Diagnostic Tool,ECU Coding, 35 Services, FCA Autoauth, CANFD and DOIP, Free Lifetime Upgrade | D63: mucar | E63: Tablet | F63: 612.13041 | G63: 385030.03 | H63: 629 | I63: 249 | J63: 4.3 | K63: https://amazon.com/dp/B0DTK24XKB | L63: =HYPERLINK(K63) -> https://amazon.com/dp/B0DTK24XKB
A64: 7 | B64: B0DCFF7VGF | C64: THINKCAR THINKSCAN 689 OBD2 Scanner, Bidirectional Scan Tool with Lifetime Free Update, 34+ Reset, 3000+ Active Test, ECU Coding, PMI, All System Diagnostic Scanner for Cars, CANFD & DOIP, FCA SGW | D64: thinkcar | E64: Tablet | F64: 475.76669 | G64: 234077.21 | H64: 492 | I64: 181 | J64: 4.4 | K64: https://amazon.com/dp/B0DCFF7VGF | L64: =HYPERLINK(K64) -> https://amazon.com/dp/B0DCFF7VGF
A65: 8 | B65: B07MBSZH48 | C65: Autel Scanner MaxiCOM MK808BT PRO, 2025 2.0 Full Bidirectional Diagnostic Tool as MK900 MX900 MK900BT, Pro Ver. of MK808S MX808S, 3000+ Test, 28+ Service, All System, Brake Bleed, Injector Coding, FCA | D65: autel | E65: Tablet | F65: 512.48232 | G65: 154769.66 | H65: 302 | I65: 1750 | J65: 4.6 | K65: https://amazon.com/dp/B07MBSZH48 | L65: =HYPERLINK(K65) -> https://amazon.com/dp/B07MBSZH48
A66: 9 | B66: B073CQMF25 | C66: Autel Scanner MaxiCOM MK900: 2025 Same as MK900BT MK900-BT MX900 Bidirectional Diagnostic Tool, 8in Up of MK808S MK808BT Pro MX808S MK808Z, 3K+ Active Tests, 40+ Service, CAN-FD&DOIP, All System, FCA | D66: autel | E66: Tablet | F66: 546.5021 | G66: 159032.11 | H66: 291 | I66: 265 | J66: 4.4 | K66: https://amazon.com/dp/B073CQMF25 | L66: =HYPERLINK(K66) -> https://amazon.com/dp/B073CQMF25
A67: 10 | B67: B0CJDTPDPB | C67: LAUNCH X431 CRP919XBT OBD2 Scanner, 2025 Wireless Bidirectional Scan Tool with DBSCar VII Connector, ECU Coding, FCA AutoAuth, 2-Year Free Update, V.A.G Guide, 35+ Services, All Systems, CANFD | D67: launch | E67: Tablet | F67: 483.21842 | G67: 88428.97 | H67: 183 | I67: 283 | J67: 4.5 | K67: https://amazon.com/dp/B0CJDTPDPB | L67: =HYPERLINK(K67) -> https://amazon.com/dp/B0CJDTPDPB

Sheet Tablet $400-
A1: Tablet $400- Monthly Summary
A3: ='Tablet Total'!A91 -> Tablet $400-
B4: Avg Price | C4: Avg Price MoM | D4: Avg Price YoY | E4: Quantity/Mo | F4: Qty by % | G4: Qty MoM | H4: Qty YoY | I4: Revenue/Mo | J4: Revenue by % | L4: Revenue MoM | M4: Revenue YoY
A5: ='Tablet Total'!A93 -> topdon | B5: ='Tablet Total'!B93 -> 244.1978 | C5: ='Tablet Total'!C93 -> 0.0779894 | D5: ='Tablet Total'!D93 -> 0.30764591 | E5: ='Tablet Total'!E93 -> 8427 | F5: ='Tablet Total'!F93 -> 0.32512828 | G5: ='Tablet Total'!G93 -> 0.43633884 | H5: ='Tablet Total'!H93 -> 2.0400433 | ... J5: ='Tablet Total'!J93 -> 0.36084256 | L5: ='Tablet Total'!L93 -> 0.54835805 | M5: ='Tablet Total'!M93 -> 2.9753002
A6: ='Tablet Total'!A94 -> launch | B6: ='Tablet Total'!B94 -> 182.54601 | C6: ='Tablet Total'!C94 -> 0.012500387 | D6: ='Tablet Total'!D94 -> -0.084952687 | E6: ='Tablet Total'!E94 -> 4565 | F6: ='Tablet Total'!F94 -> 0.17612562 | G6: ='Tablet Total'!G94 -> 0.094986807 | H6: ='Tablet Total'!H94 -> 0.28918385 | ... J6: ='Tablet Total'!J94 -> 0.14612218 | L6: ='Tablet Total'!L94 -> 0.10867457 | M6: ='Tablet Total'!M94 -> 0.17966421
A7: ='Tablet Total'!A95 -> foxwell | B7: ='Tablet Total'!B95 -> 191.86211 | C7: ='Tablet Total'!C95 -> -0.057409781 | D7: ='Tablet Total'!D95 -> -0.069300025 | E7: ='Tablet Total'!E95 -> 2973 | F7: ='Tablet Total'!F95 -> 0.1147035 | G7: ='Tablet Total'!G95 -> 0.049788136 | H7: ='Tablet Total'!H95 -> -0.063916877 | ... J7: ='Tablet Total'!J95 -> 0.10002007 | L7: ='Tablet Total'!L95 -> -0.010479971 | M7: ='Tablet Total'!M95 -> -0.12878746
A8: ='Tablet Total'!A96 -> xtool | B8: ='Tablet Total'!B96 -> 246.50199 | C8: ='Tablet Total'!C96 -> -0.019666903 | D8: ='Tablet Total'!D96 -> -0.28862292 | E8: ='Tablet Total'!E96 -> 2033 | F8: ='Tablet Total'!F96 -> 0.078436668 | G8: ='Tablet Total'!G96 -> 0.018537074 | H8: ='Tablet Total'!H96 -> 1.7325269 | ... J8: ='Tablet Total'!J96 -> 0.087874086 | L8: ='Tablet Total'!L96 -> -0.0014943955 | M8: ='Tablet Total'!M96 -> 0.94385699
A9: ='Tablet Total'!A97 -> blcktec | B9: ='Tablet Total'!B97 -> 198.0568 | C9: ='Tablet Total'!C97 -> 0.018644659 | D9: ='Tablet Total'!D97 -> 0 | E9: ='Tablet Total'!E97 -> 2032 | F9: ='Tablet Total'!F97 -> 0.078398086 | G9: ='Tablet Total'!G97 -> 0.41209173 | H9: ='Tablet Total'!H97 -> 0 | ... J9: ='Tablet Total'!J97 -> 0.070569409 | L9: ='Tablet Total'!L97 -> 0.4384197 | M9: ='Tablet Total'!M97 -> 0
A10: ='Tablet Total'!A98 -> innova | B10: ='Tablet Total'!B98 -> 137.95047 | C10: ='Tablet Total'!C98 -> -0.034313523 | D10: ='Tablet Total'!D98 -> 0 | E10: ='Tablet Total'!E98 -> 1336 | F10: ='Tablet Total'!F98 -> 0.051545199 | G10: ='Tablet Total'!G98 -> 0.91404011 | H10: ='Tablet Total'!H98 -> 0 | ... J10: ='Tablet Total'!J98 -> 0.032317121 | L10: ='Tablet Total'!L98 -> 0.84836266 | M10: ='Tablet Total'!M98 -> 0
A11: ='Tablet Total'!A99 -> Other | B11: ='Tablet Total'!B99 -> 253.33645 | C11: ='Tablet Total'!C99 -> 0.027722874 | D11: ='Tablet Total'!D99 -> 0.22342632 | E11: ='Tablet Total'!E99 -> 4553 | F11: ='Tablet Total'!F99 -> 0.17566264 | G11: ='Tablet Total'!G99 -> -0.0067626527 | H11: ='Tablet Total'!H99 -> 0.11511144 | ... J11: ='Tablet Total'!J99 -> 0.20225457 | L11: ='Tablet Total'!L99 -> 0.020772741 | M11: ='Tablet Total'!M99 -> 0.36425669
A13: ='Tablet Total'!A100 -> Total | B13: ='Tablet Total'!B100 -> 220.0284 | C13: ='Tablet Total'!C100 -> 0.017310952 | D13: ='Tablet Total'!D100 -> 0.017310952 | E13: ='Tablet Total'!E100 -> 25919 | F13: ='Tablet Total'!F100 -> 1 | G13: ='Tablet Total'!G100 -> 0.20078758 | H13: ='Tablet Total'!H100 -> 0.81049176 | ... J13: ='Tablet Total'!J100 -> 1 | L13: ='Tablet Total'!L100 -> 0.22157436 | M13: ='Tablet Total'!M100 -> 0.91240071
A45: Rank By Monthly Revenue - Nov '25 ONLY
A46: Ranking | B46: ASIN | C46: Product Name | D46: Brand | E46: Type | F46: Price | G46: Est. Monthly Retail Rev | H46: Est. Monthly Units Sold | I46: # of Reviews | J46: Avg. Rating | K46: Column2 | L46: Link
A47: 1 | B47: B0C33Y285Y | C47: TOPDON Bidirectional Scan Tool, 2025 New ArtiDiag900 Lite Automotive Diagnostic Tool for Full System, Scanner for Car with Active Test, 8 Reset, Wireless OBD2 Scanner Diagnostic Tool for All Vehicles | D47: topdon | E47: Tablet | F47: 313.53909 | G47: 520788.43 | H47: 1661 | I47: 999 | J47: 4.3 | K47: https://amazon.com/dp/B0C33Y285Y | L47: =HYPERLINK(K47) -> https://amazon.com/dp/B0C33Y285Y
A48: 2 | B48: B0DV2N2FND | C48: BLCKTEC 460T OBD2 Scanner Car Code Reader Engine ABS SRS Transmission Diagnostic Tool, 12 Reset Services, Oil/TPMS/EPB/BMS/SAS/DPF/Throttle Reset, ABS Bleeding, Battery Test, Auto VIN, Free Update | D48: blcktec | E48: Tablet | F48: 198.0568 | G48: 402451.42 | H48: 2032 | I48: 312 | J48: 4.4 | K48: https://amazon.com/dp/B0DV2N2FND | L48: =HYPERLINK(K48) -> https://amazon.com/dp/B0DV2N2FND
A49: 3 | B49: B08XK3DJ42 | C49: OBD2 Scanner TOPDON AD500, Oil SAS Throttle TPMS BMS EPB Reset, Engine ABS SRS Transmission, Diagnostic Scan Tool, AutoVIN, Car Check Engine Code Reader with Battery Test, Lifetime Wi-Fi Free Update | D49: topdon | E49: Tablet | F49: 149.94128 | G49: 315626.4 | H49: 2105 | I49: 1431 | J49: 4.4 | K49: https://amazon.com/dp/B08XK3DJ42 | L49: =HYPERLINK(K49) -> https://amazon.com/dp/B08XK3DJ42
A50: 4 | B50: B08TR5PS5V | C50: TOPDON AD800BT 2 OBD2 Scanner, 2025 Bidirectional Scan Tool, Function as AD900 Lite AD Pro, All System Automotive Diagnostic Scanner, Active Test, 28+ Reset Service, FCA Autoauth, 2 Years Free Update | D50: topdon | E50: Tablet | F50: 390.68245 | G50: 300044.12 | H50: 768 | I50: 728 | J50: 4.3 | K50: https://amazon.com/dp/B08TR5PS5V | L50: =HYPERLINK(K50) -> https://amazon.com/dp/B08TR5PS5V
A51: 5 | B51: B09KZTYD18 | C51: OBD2 Scanner TOPDON AD600S Scan Tool, Code Reader, Diagnostics Scanner for ABS/SRS/AT/Engine, 9 Reset Services, Oil/Brake/BMS/SAS/DPF/TPMS/ETS Reset/ABS Bleeding/Injector Coding, Free Lifetime Upgrade | D51: topdon | E51: Tablet | F51: 210.06127 | G51: 288414.13 | H51: 1373 | I51: 1535 | J51: 4.4 | K51: https://amazon.com/dp/B09KZTYD18 | L51: =HYPERLINK(K51) -> https://amazon.com/dp/B09KZTYD18
A52: 6 | B52: B098LF38DS | C52: XTOOL D7 Bidirectional OBD2 Scanner: 2025 Scan Tool with 36+ Resets, Full System Car Scanner Diagnostic Tool, Injector Calibration, Throttle Relearn, Crank Sensor Relearn, FCA, CANFD & DoIP | D52: xtool | E52: Tablet | F52: 395.2915 | G52: 234407.86 | H52: 593 | I52: 1545 | J52: 4.4 | K52: https://amazon.com/dp/B098LF38DS | L52: =HYPERLINK(K52) -> https://amazon.com/dp/B098LF38DS
A53: 7 | B53: B08TBRDH7W | C53: TOPDON Scanner AD800BT V2.0, Bidirectional Scan Tool, Full Systems Diagnostic Tool for All Vehicles, Automotive Diagnostic Scanner for Car, 28+ Services, FCA AutoAuth, CANFD, 2 Years Free Update | D53: topdon | E53: Tablet | F53: 364.28847 | G53: 231323.18 | H53: 635 | I53: 558 | J53: 4.4 | K53: https://amazon.com/dp/B08TBRDH7W | L53: =HYPERLINK(K53) -> https://amazon.com/dp/B08TBRDH7W
A54: 8 | B54: B08PFJMTY3 | C54: FOXWELL Car Scanner NT604 Elite OBD2 Scanner ABS SRS Transmission, Check Engine Code Reader for Cars and Trucks, Diagnostic Scan Tool with SRS Airbag, Automotive Diagnostic Tool with Live Data | D54: foxwell | E54: Tablet | F54: 158.82678 | G54: 214416.15 | H54: 1350 | I54: 4495 | J54: 4.3 | K54: https://amazon.com/dp/B08PFJMTY3 | L54: =HYPERLINK(K54) -> https://amazon.com/dp/B08PFJMTY3
A55: 9 | B55: B0CTHJW813 | C55: TOPDON Upgraded AD600S OBD2 Scanner, Diagnostic Tool, ABS SRS Transmission Engine Code Reader, 9 Reset Services Scan Tool, Oil/Brake/BMS/SAS/DPF/TPMS/ETS Reset, Injector Coding, Lifetime Free Update | D55: topdon | E55: Tablet | F55: 216.01884 | G55: 204785.86 | H55: 948 | I55: 665 | J55: 4.5 | K55: https://amazon.com/dp/B0CTHJW813 | L55: =HYPERLINK(K55) -> https://amazon.com/dp/B0CTHJW813
A56: 10 | B56: B07RLF8FBC | C56: LAUNCH OBD2 Scanner CRP123X Elite, 2025 Lifetime Free WiFi Update scan Tool, FCA SGW, SAS Calibration/Throttle/Brake/BMS/D-P-F/Oil Reset/ABS bleeding, Multi Systems Car Scanner, Battery Test, Auto VIN | D56: launch | E56: Tablet | F56: 160.31228 | G56: 173297.57 | H56: 1081 | I56: 3227 | J56: 4.4 | K56: https://amazon.com/dp/B07RLF8FBC | L56: =HYPERLINK(K56) -> https://amazon.com/dp/B07RLF8FBC
A58: Rank By Monthly Units - Nov '25 ONLY
A59: Ranking | B59: ASIN | C59: Product Name | D59: Brand | E59: Type | F59: Price | G59: Est. Monthly Retail Rev | H59: Est. Monthly Units Sold | I59: # of Reviews | J59: Avg. Rating | K59: Column2 | L59: Link
A60: 1 | B60: B08XK3DJ42 | C60: OBD2 Scanner TOPDON AD500, Oil SAS Throttle TPMS BMS EPB Reset, Engine ABS SRS Transmission, Diagnostic Scan Tool, AutoVIN, Car Check Engine Code Reader with Battery Test, Lifetime Wi-Fi Free Update | D60: topdon | E60: Tablet | F60: 149.94128 | G60: 315626.4 | H60: 2105 | I60: 1431 | J60: 4.4 | K60: https://amazon.com/dp/B08XK3DJ42 | L60: =HYPERLINK(K60) -> https://amazon.com/dp/B08XK3DJ42
A61: 2 | B61: B0DV2N2FND | C61: BLCKTEC 460T OBD2 Scanner Car Code Reader Engine ABS SRS Transmission Diagnostic Tool, 12 Reset Services, Oil/TPMS/EPB/BMS/SAS/DPF/Throttle Reset, ABS Bleeding, Battery Test, Auto VIN, Free Update | D61: blcktec | E61: Tablet | F61: 198.0568 | G61: 402451.42 | H61: 2032 | I61: 312 | J61: 4.4 | K61: https://amazon.com/dp/B0DV2N2FND | L61: =HYPERLINK(K61) -> https://amazon.com/dp/B0DV2N2FND
A62: 3 | B62: B0C33Y285Y | C62: TOPDON Bidirectional Scan Tool, 2025 New ArtiDiag900 Lite Automotive Diagnostic Tool for Full System, Scanner for Car with Active Test, 8 Reset, Wireless OBD2 Scanner Diagnostic Tool for All Vehicles | D62: topdon | E62: Tablet | F62: 313.53909 | G62: 520788.43 | H62: 1661 | I62: 999 | J62: 4.3 | K62: https://amazon.com/dp/B0C33Y285Y | L62: =HYPERLINK(K62) -> https://amazon.com/dp/B0C33Y285Y
A63: 4 | B63: B09KZTYD18 | C63: OBD2 Scanner TOPDON AD600S Scan Tool, Code Reader, Diagnostics Scanner for ABS/SRS/AT/Engine, 9 Reset Services, Oil/Brake/BMS/SAS/DPF/TPMS/ETS Reset/ABS Bleeding/Injector Coding, Free Lifetime Upgrade | D63: topdon | E63: Tablet | F63: 210.06127 | G63: 288414.13 | H63: 1373 | I63: 1535 | J63: 4.4 | K63: https://amazon.com/dp/B09KZTYD18 | L63: =HYPERLINK(K63) -> https://amazon.com/dp/B09KZTYD18
A64: 5 | B64: B08PFJMTY3 | C64: FOXWELL Car Scanner NT604 Elite OBD2 Scanner ABS SRS Transmission, Check Engine Code Reader for Cars and Trucks, Diagnostic Scan Tool with SRS Airbag, Automotive Diagnostic Tool with Live Data | D64: foxwell | E64: Tablet | F64: 158.82678 | G64: 214416.15 | H64: 1350 | I64: 4495 | J64: 4.3 | K64: https://amazon.com/dp/B08PFJMTY3 | L64: =HYPERLINK(K64) -> https://amazon.com/dp/B08PFJMTY3
A65: 6 | B65: B0F254MVB5 | C65: Innova SD35 OBD2 Scanner – ABS, SRS, TPMS & Check Engine Code Reader, Live Data, All System Diagnostics, Compatible with Most Vehicles | D65: innova | E65: Tablet | F65: 129.97499 | G65: 161428.94 | H65: 1242 | I65: 101 | J65: 4.5 | K65: https://amazon.com/dp/B0F254MVB5 | L65: =HYPERLINK(K65) -> https://amazon.com/dp/B0F254MVB5
A66: 7 | B66: B07RLF8FBC | C66: LAUNCH OBD2 Scanner CRP123X Elite, 2025 Lifetime Free WiFi Update scan Tool, FCA SGW, SAS Calibration/Throttle/Brake/BMS/D-P-F/Oil Reset/ABS bleeding, Multi Systems Car Scanner, Battery Test, Auto VIN | D66: launch | E66: Tablet | F66: 160.31228 | G66: 173297.57 | H66: 1081 | I66: 3227 | J66: 4.4 | K66: https://amazon.com/dp/B07RLF8FBC | L66: =HYPERLINK(K66) -> https://amazon.com/dp/B07RLF8FBC
A67: 8 | B67: B0CTHJW813 | C67: TOPDON Upgraded AD600S OBD2 Scanner, Diagnostic Tool, ABS SRS Transmission Engine Code Reader, 9 Reset Services Scan Tool, Oil/Brake/BMS/SAS/DPF/TPMS/ETS Reset, Injector Coding, Lifetime Free Update | D67: topdon | E67: Tablet | F67: 216.01884 | G67: 204785.86 | H67: 948 | I67: 665 | J67: 4.5 | K67: https://amazon.com/dp/B0CTHJW813 | L67: =HYPERLINK(K67) -> https://amazon.com/dp/B0CTHJW813
A68: 9 | B68: B08TR5PS5V | C68: TOPDON AD800BT 2 OBD2 Scanner, 2025 Bidirectional Scan Tool, Function as AD900 Lite AD Pro, All System Automotive Diagnostic Scanner, Active Test, 28+ Reset Service, FCA Autoauth, 2 Years Free Update | D68: topdon | E68: Tablet | F68: 390.68245 | G68: 300044.12 | H68: 768 | I68: 728 | J68: 4.3 | K68: https://amazon.com/dp/B08TR5PS5V | L68: =HYPERLINK(K68) -> https://amazon.com/dp/B08TR5PS5V
A69: 10 | B69: B08DCNDFVK | C69: Upgrade of NT604 OBD2 Scanner, FOXWELL NT614 Elite 4 Systems Diagnostic Scanner, 5 Resets ABS Bleeding, Oil, EPB, SAS, Throttle Relearn Code Reader, WiFi Update, AutoVIN, Live Data Automotive Tool | D69: foxwell | E69: Tablet | F69: 169.66096 | G69: 109600.98 | H69: 646 | I69: 545 | J69: 4.3 | K69: https://amazon.com/dp/B08DCNDFVK | L69: =HYPERLINK(K69) -> https://amazon.com/dp/B08DCNDFVK

Sheet Handheld Total
A1: Handheld Monthly Summary
A3: Handheld Overall
B4: Avg Price | C4: Avg Price MoM | D4: Avg Price YoY | E4: Quantity/Mo | F4: Qty by % | G4: Qty MoM | H4: Qty YoY | I4: Revenue/Mo | J4: Revenue by % | L4: Revenue MoM | M4: Revenue YoY
A5: ancel | B5: 38.755293 | C5: -0.045006507 | D5: -0.056266323 | E5: 53427 | F5: 0.39836707 | G5: 0.2026878 | H5: 0.89376861 | I5: 2070579.1 | J5: 0.30106042 | K5: 0.14855902 | L5: 0.14855902 | M5: 0.78721321
A6: innova | B6: 188.74263 | C6: -0.059977202 | D6: -0.037815195 | E6: 8269 | F6: 0.061656041 | G6: 0.5534473 | H6: 1.3720597 | I6: 1560712.8 | J6: 0.2269263 | K6: 0.46027588 | L6: 0.46027588 | M6: 1.2823598
A7: foxwell | B7: 81.565055 | C7: -0.092822362 | D7: -0.034171852 | E7: 10624 | F7: 0.079215599 | G7: 0.21569974 | H7: 0.11083229 | I7: 866547.14 | J7: 0.12599521 | K7: 0.10285562 | L7: 0.10285562 | M7: 0.072873092
A8: autel | B8: 55.863257 | C8: -0.31528131 | D8: -0.33907009 | E8: 7203 | F8: 0.053707639 | G8: -0.057938792 | H8: -0.1089807 | I8: 402383.04 | J8: 0.058506149 | K8: -0.35495309 | L8: -0.35495309 | M8: -0.4110987
A9: motopower | B9: 26.139107 | C9: 0.11856589 | D9: 0.10657814 | E9: 12166 | F9: 0.090713194 | G9: 0.070856439 | H9: 0.41580356 | I9: 318008.37 | J9: 0.046238145 | K9: 0.19782349 | L9: 0.19782349 | M9: 0.56669728
A10: blcktec | B10: 53.433743 | C10: 0.017079775 | D10: 0.14648215 | E10: 1774 | F10: 0.013227454 | G10: 0.093037585 | H10: -0.38785369 | I10: 94791.46 | J10: 0.013782597 | K10: 0.11170642 | L10: 0.11170642 | M10: -0.29818519
A11: Other | B11: 38.487596 | C11: -0.01505848 | D11: -0.13374684 | E11: 40652 | F11: 0.303113 | G11: -0.045638088 | H11: 0.20122924 | I11: 1564597.8 | J11: 0.22749117 | K11: -0.060009328 | L11: -0.060009328 | M11: 0.040568627
A12: Total | B12: =Summary!B10 -> 51.281509 | C12: =Summary!C10 -> -0.0086956713 | D12: =Summary!D10 -> -0.062044522 | E12: =Summary!E10 -> 134115 | F12: =SUM(F5:F11) -> 1 | G12: =Summary!G10 -> 0.1019045 | H12: =Summary!H10 -> 0.41631377 | I12: =Summary!I10 -> 6877619.6 | J12: =SUM(J5:J11) -> 1 | L12: =Summary!K10 -> 0.092322697 | M12: =Summary!L10 -> 0.32843926
A44: Rank By Monthly Revenue - Nov '25 ONLY
A45: Ranking | B45: ASIN | C45: Product Name | D45: Brand | E45: Type | F45: Price | G45: Est. Monthly Retail Rev | H45: Est. Monthly Units Sold | I45: # of Reviews | J45: Avg. Rating | K45: Column2 | L45: Link
A46: 1 | B46: B01G5EA74I | C46: ANCEL AD310 Classic Enhanced Universal OBD II Scanner Car Engine Fault Code Reader CAN Diagnostic Scan Tool, Read and Clear Error Codes for 1996 or Newer OBD2 Protocol Vehicle (Black) | D46: ancel | E46: Handheld | F46: 28.282506 | G46: 1131017.4 | H46: 39990 | I46: 59738 | J46: 4.6 | K46: https://amazon.com/dp/B01G5EA74I | L46: =HYPERLINK(K46) -> https://amazon.com/dp/B01G5EA74I
A47: 2 | B47: B07Z481NJM | C47: Innova 5610 OBD2 Bidirectional Scan Tool - Understand Your Vehicle, Pinpoint What's Wrong, and Complete Your Repairs with Less Headache, Updates Included, US-Based Technical Support | D47: innova | E47: Handheld | F47: 287.32292 | G47: 1127455.1 | H47: 3924 | I47: 2889 | J47: 4.4 | K47: https://amazon.com/dp/B07Z481NJM | L47: =HYPERLINK(K47) -> https://amazon.com/dp/B07Z481NJM
A48: 3 | B48: B00UJV3E12 | C48: FOXWELL NT301 OBD2 Scanner Live Data Professional Mechanic OBDII Diagnostic Code Reader Tool for Check Engine Light | D48: foxwell | E48: Handheld | F48: 64.359672 | G48: 410035.47 | H48: 6371 | I48: 29066 | J48: 4.5 | K48: https://amazon.com/dp/B00UJV3E12 | L48: =HYPERLINK(K48) -> https://amazon.com/dp/B00UJV3E12
A49: 4 | B49: B071FSNL73 | C49: ANCEL AD410 Enhanced OBD2 Scanner, Vehicle Code Reader for Check Engine Light, Automotive OBD II Scanner Fault Diagnosis, OBDII Scan Tool for All OBDII Cars 1996+, Black/Yellow | D49: ancel | E49: Handheld | F49: 49.987904 | G49: 347165.99 | H49: 6945 | I49: 14142 | J49: 4.5 | K49: https://amazon.com/dp/B071FSNL73 | L49: =HYPERLINK(K49) -> https://amazon.com/dp/B071FSNL73
A50: 5 | B50: B07Z46L5FG | C50: Innova 5210 OBD2 Scanner & Engine Code Reader, Battery Tester, Live Data, Oil Reset, Car Diagnostic Tool for Most Vehicles, Bluetooth Compatible with America's Top Car Repair App | D50: innova | E50: Handheld | F50: 84.710609 | G50: 265821.89 | H50: 3138 | I50: 3668 | J50: 4.5 | K50: https://amazon.com/dp/B07Z46L5FG | L50: =HYPERLINK(K50) -> https://amazon.com/dp/B07Z46L5FG
A51: 6 | B51: B07Z3HB7DR | C51: MOTOPOWER MP69033 Car OBD2 Scanner Code Reader Engine Fault Scanner CAN Diagnostic Scan Tool for All OBD II Protocol Cars Since 1996, Yellow | D51: motopower | E51: Handheld | F51: 25.196317 | G51: 261109.43 | H51: 10363 | I51: 48232 | J51: 4.6 | K51: https://amazon.com/dp/B07Z3HB7DR | L51: =HYPERLINK(K51) -> https://amazon.com/dp/B07Z3HB7DR
A52: 7 | B52: B0CGJ9LZQ4 | C52: OBD2 Scanner Diagnostic Tool, Check Engine Code Reader OBD2 Scanner with Reset, Mode 6, Mode 8 & I/M Readiness, Auto Check Engine Light Car Diagnostic Scan Tool for All OBDII Car Since 1996 | D52: wejowe | E52: Handheld | F52: 39.645838 | G52: 116796.64 | H52: 2946 | I52: 1353 | J52: 4.5 | K52: https://amazon.com/dp/B0CGJ9LZQ4 | L52: =HYPERLINK(K52) -> https://amazon.com/dp/B0CGJ9LZQ4
A53: 8 | B53: B0B452YDWT | C53: ANCEL Heavy Duty Truck Scanner HD601 All System Diesel Diagnostic Scan Tool fits for Cummins, Detroit, Freightliner, International, Paccar, Check Engine for Truck & Car 2 in 1 Code Reader | D53: ancel | E53: Handheld | F53: 158.68479 | G53: 112190.15 | H53: 707 | I53: 1122 | J53: 4 | K53: https://amazon.com/dp/B0B452YDWT | L53: =HYPERLINK(K53) -> https://amazon.com/dp/B0B452YDWT
A54: 9 | B54: B019QCG5RE | C54: FOXWELL NT510 Elite Scan Tool fit for BMW Scanner Full Diagnostic Tool OBD2 Scanner, All System Bi-Directional Control Code Reader with All Reset Services, Battery Registration Tool fit for BMW Mini | D54: foxwell | E54: Handheld | F54: 190.13846 | G54: 112181.69 | H54: 590 | I54: 3066 | J54: 4.3 | K54: https://amazon.com/dp/B019QCG5RE | L54: =HYPERLINK(K54) -> https://amazon.com/dp/B019QCG5RE
A55: 10 | B55: B0C2V3RYLY | C55: ZMOON ZM201 Professional OBD2 Scanner Diagnostic Tool, Enhanced Check Engine Code Reader with Reset OBDII/EOBD Car Diagnostic Scan Tools for All Vehicles After 1996, 2025 Upgraded | D55: zmoon | E55: Handheld | F55: 36.641688 | G55: 108752.53 | H55: 2968 | I55: 2214 | J55: 4.5 | K55: https://amazon.com/dp/B0C2V3RYLY | L55: =HYPERLINK(K55) -> https://amazon.com/dp/B0C2V3RYLY
A57: Rank By Monthly Units - Nov '25 ONLY
A58: Ranking | B58: ASIN | C58: Product Name | D58: Brand | E58: Type | F58: Price | G58: Est. Monthly Retail Rev | H58: Est. Monthly Units Sold | I58: # of Reviews | J58: Avg. Rating | K58: Column2 | L58: Link
A59: 1 | B59: B01G5EA74I | C59: ANCEL AD310 Classic Enhanced Universal OBD II Scanner Car Engine Fault Code Reader CAN Diagnostic Scan Tool, Read and Clear Error Codes for 1996 or Newer OBD2 Protocol Vehicle (Black) | D59: ancel | E59: Handheld | F59: 28.282506 | G59: 1131017.4 | H59: 39990 | I59: 59738 | J59: 4.6 | K59: https://amazon.com/dp/B01G5EA74I | L59: =HYPERLINK(K59) -> https://amazon.com/dp/B01G5EA74I
A60: 2 | B60: B07Z3HB7DR | C60: MOTOPOWER MP69033 Car OBD2 Scanner Code Reader Engine Fault Scanner CAN Diagnostic Scan Tool for All OBD II Protocol Cars Since 1996, Yellow | D60: motopower | E60: Handheld | F60: 25.196317 | G60: 261109.43 | H60: 10363 | I60: 48232 | J60: 4.6 | K60: https://amazon.com/dp/B07Z3HB7DR | L60: =HYPERLINK(K60) -> https://amazon.com/dp/B07Z3HB7DR
A61: 3 | B61: B071FSNL73 | C61: ANCEL AD410 Enhanced OBD2 Scanner, Vehicle Code Reader for Check Engine Light, Automotive OBD II Scanner Fault Diagnosis, OBDII Scan Tool for All OBDII Cars 1996+, Black/Yellow | D61: ancel | E61: Handheld | F61: 49.987904 | G61: 347165.99 | H61: 6945 | I61: 14142 | J61: 4.5 | K61: https://amazon.com/dp/B071FSNL73 | L61: =HYPERLINK(K61) -> https://amazon.com/dp/B071FSNL73
A62: 4 | B62: B00UJV3E12 | C62: FOXWELL NT301 OBD2 Scanner Live Data Professional Mechanic OBDII Diagnostic Code Reader Tool for Check Engine Light | D62: foxwell | E62: Handheld | F62: 64.359672 | G62: 410035.47 | H62: 6371 | I62: 29066 | J62: 4.5 | K62: https://amazon.com/dp/B00UJV3E12 | L62: =HYPERLINK(K62) -> https://amazon.com/dp/B00UJV3E12
A63: 5 | B63: B0BY1TS725 | C63: VDIAGTOOL VD10 OBD2 Scanner Code Reader Car Diagnostic Tool Engine Fault Code Reader for Turn Off CEL with Freeze Frame/I/M Readiness for All OBDII Protocol Cars, OBD2 Scanner Diagnostic Tool | D63: vdiagtool | E63: Handheld | F63: 19.98077 | G63: 80142.87 | H63: 4011 | I63: 1843 | J63: 4.6 | K63: https://amazon.com/dp/B0BY1TS725 | L63: =HYPERLINK(K63) -> https://amazon.com/dp/B0BY1TS725
A64: 6 | B64: B07Z481NJM | C64: Innova 5610 OBD2 Bidirectional Scan Tool - Understand Your Vehicle, Pinpoint What's Wrong, and Complete Your Repairs with Less Headache, Updates Included, US-Based Technical Support | D64: innova | E64: Handheld | F64: 287.32292 | G64: 1127455.1 | H64: 3924 | I64: 2889 | J64: 4.4 | K64: https://amazon.com/dp/B07Z481NJM | L64: =HYPERLINK(K64) -> https://amazon.com/dp/B07Z481NJM
A65: 7 | B65: B07Z46L5FG | C65: Innova 5210 OBD2 Scanner & Engine Code Reader, Battery Tester, Live Data, Oil Reset, Car Diagnostic Tool for Most Vehicles, Bluetooth Compatible with America's Top Car Repair App | D65: innova | E65: Handheld | F65: 84.710609 | G65: 265821.89 | H65: 3138 | I65: 3668 | J65: 4.5 | K65: https://amazon.com/dp/B07Z46L5FG | L65: =HYPERLINK(K65) -> https://amazon.com/dp/B07Z46L5FG
A66: 8 | B66: B0C2V3RYLY | C66: ZMOON ZM201 Professional OBD2 Scanner Diagnostic Tool, Enhanced Check Engine Code Reader with Reset OBDII/EOBD Car Diagnostic Scan Tools for All Vehicles After 1996, 2025 Upgraded | D66: zmoon | E66: Handheld | F66: 36.641688 | G66: 108752.53 | H66: 2968 | I66: 2214 | J66: 4.5 | K66: https://amazon.com/dp/B0C2V3RYLY | L66: =HYPERLINK(K66) -> https://amazon.com/dp/B0C2V3RYLY
A67: 9 | B67: B0CGJ9LZQ4 | C67: OBD2 Scanner Diagnostic Tool, Check Engine Code Reader OBD2 Scanner with Reset, Mode 6, Mode 8 & I/M Readiness, Auto Check Engine Light Car Diagnostic Scan Tool for All OBDII Car Since 1996 | D67: wejowe | E67: Handheld | F67: 39.645838 | G67: 116796.64 | H67: 2946 | I67: 1353 | J67: 4.5 | K67: https://amazon.com/dp/B0CGJ9LZQ4 | L67: =HYPERLINK(K67) -> https://amazon.com/dp/B0CGJ9LZQ4
A68: 10 | B68: B007XE8C74 | C68: Autel Professional OBD2 Scanner AL319 Code Reader, Enhanced Check and Reset Engine Fault Code, Live Data, Freeze Frame, CAN Car Diagnostic Scan Tools for All OBDII Vehicles After 1996, 2025 Upgraded | D68: autel | E68: Handheld | F68: 31.314212 | G68: 87648.48 | H68: 2799 | I68: 25566 | J68: 4.6 | K68: https://amazon.com/dp/B007XE8C74 | L68: =HYPERLINK(K68) -> https://amazon.com/dp/B007XE8C74
A70: Handheld $75+
B71: Avg Price | C71: Avg Price MoM | D71: Avg Price YoY | E71: Quantity/Mo | F71: Qty by % | G71: Qty MoM | H71: Qty YoY | I71: Revenue/Mo | J71: Revenue by % | L71: Revenue MoM | M71: Revenue YoY
A72: innova | B72: 191.15893 | C72: -0.068222293 | D72: -0.059410431 | E72: 8109 | F72: 0.41760222 | G72: 0.5727308 | H72: 1.4528131 | I72: 1550107.7 | J72: 0.48501534 | K72: 0.4654355 | L72: 0.4654355 | M72: 1.3070904
A73: ancel | B73: 115.16903 | C73: -0.016479799 | D73: -0.075911023 | E73: 3518 | F73: 0.18117211 | G73: 0.11258697 | H73: 0.36462374 | I73: 405164.66 | J73: 0.12677253 | K73: 0.09425176 | L73: 0.09425176 | M73: 0.26103376
A74: foxwell | B74: 147.28282 | C74: -0.042181138 | D74: 0.0131249 | E74: 2703 | F74: 0.13920074 | G74: 0.028147585 | H74: 0.0074543422 | I74: 398105.47 | J74: 0.12456377 | K74: -0.01522085 | L74: -0.01522085 | M74: 0.02067708
A75: autel | B75: 190.88699 | C75: -0.31136553 | D75: -0.35221112 | E75: 1001 | F75: 0.051550108 | G75: -0.31344307 | H75: -0.35502577 | I75: 191077.88 | J75: 0.05978662 | K75: -0.52721323 | L75: -0.52721323 | M75: -0.58219287
A76: launch | B76: 151.40622 | C76: 0.052273339 | D76: -0.067845938 | E76: 864 | F76: 0.044494799 | G76: -0.11926606 | H76: 0.39579968 | I76: 130814.97 | J76: 0.040930876 | K76: -0.073227151 | L76: -0.073227151 | M76: 0.30110034
A77: Other | B77: 161.56582 | C77: 0.017544148 | D77: -0.034913755 | E77: 3223 | F77: 0.16598002 | G77: -0.17759633 | H77: 0.097004765 | I77: 520726.63 | J77: 0.16293087 | K77: -0.16316795 | L77: -0.16316795 | M77: 0.05870421
A78: Total | B78: =Summary!B8 -> 164.58942 | C78: =Summary!C8 -> -0.050551412 | D78: =Summary!D8 -> -0.074970791 | E78: =Summary!E8 -> 19418 | F78: =SUM(F72:F76) -> 0.83401998 | G78: =Summary!G8 -> 0.12210344 | H78: =Summary!H8 -> 0.41882215 | I78: =Summary!I8 -> 3195997.3 | J78: =SUM(J72:J76) -> 0.83706913 | L78: =Summary!K8 -> 0.065379525 | M78: =Summary!L8 -> 0.31245193
A80: Handheld $75-
B81: Avg Price | C81: Avg Price MoM | D81: Avg Price YoY | E81: Quantity/Mo | F81: Qty by % | G81: Qty MoM | H81: Qty YoY | I81: Revenue/Mo | J81: Revenue by % | L81: Revenue MoM | M81: Revenue YoY
A82: ancel | B82: 33.369019 | C82: -0.038853106 | D82: 0.021648469 | E82: 49909 | F82: 0.4351378 | G82: 0.20959259 | H82: 0.94698447 | I82: 1665414.4 | J82: 0.45235884 | K82: 0.16259616 | L82: 0.16259616 | M82: 0.98913371
A83: foxwell | B83: 59.139208 | C83: -0.052772368 | D83: -0.025645834 | E83: 7921 | F83: 0.06906022 | G83: 0.29639935 | H83: 0.15114082 | I83: 468441.67 | J83: 0.12723784 | K83: 0.22798528 | L83: 0.22798528 | M83: 0.12161886
A84: motopower | B84: 26.139107 | C84: 0.16063976 | D84: 0.10657814 | E84: 12166 | F84: 0.10607078 | G84: 0.087415088 | H84: 0.41580356 | I84: 318008.37 | J84: 0.08637724 | K84: 0.26209719 | L84: 0.26209719 | M84: 0.56669728
A85: autel | B85: 34.070487 | C85: -0.040171673 | D85: -0.015021523 | E85: 6202 | F85: 0.054072905 | G85: 0.0022624434 | H85: -0.050520514 | I85: 211305.16 | J85: 0.057394579 | K85: -0.038000116 | L85: -0.038000116 | M85: -0.064783143
A86: zmoon | B86: 33.198202 | C86: 0.051667078 | D86: -0.22700309 | E86: 3988 | F86: 0.034769872 | G86: 0.15160266 | H86: 0.055584966 | I86: 132394.43 | J86: 0.035960895 | K86: 0.2111026 | L86: 0.2111026 | M86: -0.18403608
A87: blcktec | B87: 53.433743 | C87: 0.017079775 | D87: 0.14648215 | E87: 1774 | F87: 0.015466839 | G87: 0.093037585 | H87: -0.38785369 | I87: 94791.46 | J87: 0.025747199 | K87: 0.11170642 | L87: 0.11170642 | M87: -0.29818519
A88: innova | B88: 66.281562 | C88: 0.0062901824 | D88: 0.00032458386 | E88: 160 | F88: 0.0013949798 | G88: -0.041916168 | H88: -0.11111111 | I88: 10605.05 | J88: 0.0028805372 | K88: -0.035889646 | L88: -0.035889646 | M88: -0.11082259
A89: Other | B89: 23.963586 | C89: 0.02386312 | D89: -0.15187444 | E89: 32577 | F89: 0.28402661 | G89: -0.053159333 | H89: 0.22899611 | I89: 780661.73 | J89: 0.21204286 | K89: -0.03056476 | L89: -0.03056476 | M89: 0.042343018
A90: Total | B90: =Summary!B9 -> 32.09868 | C90: =Summary!C9 -> 0.016644668 | D90: =Summary!D20 -> 0 | E90: =Summary!E9 -> 114697 | F90: =SUM(F82:F89) -> 1 | G90: =Summary!G9 -> 0.09855661 | H90: =Summary!H20 -> 0 | I90: =Summary!I9 -> 3681622.3 | J90: =SUM(J82:J89) -> 1 | L90: =Summary!K9 -> 0.11684172 | M90: =Summary!L20 -> 0

Sheet Handheld $75+
A1: Handheld $75+ Monthly Summary
A3: ='Handheld Total'!A70 -> Handheld $75+
B4: Avg Price | C4: Avg Price MoM | D4: Avg Price YoY | E4: Quantity/Mo | F4: Qty by % | G4: Qty MoM | H4: Qty YoY | I4: Revenue/Mo | J4: Revenue by % | L4: Revenue MoM | M4: Revenue YoY
A5: innova | B5: ='Handheld Total'!B72 -> 191.15893 | C5: ='Handheld Total'!C72 -> -0.068222293 | D5: ='Handheld Total'!D72 -> -0.059410431 | E5: ='Handheld Total'!E72 -> 8109 | F5: ='Handheld Total'!F72 -> 0.41760222 | G5: ='Handheld Total'!G72 -> 0.5727308 | H5: ='Handheld Total'!H72 -> 1.4528131 | I5: ='Handheld Total'!I72 -> 1550107.7 | J5: ='Handheld Total'!J72 -> 0.48501534 | K5: -0.012705045 | L5: ='Handheld Total'!L72 -> 0.4654355 | M5: ='Handheld Total'!M72 -> 1.3070904
A6: foxwell | B6: ='Handheld Total'!B73 -> 115.16903 | C6: ='Handheld Total'!C73 -> -0.016479799 | D6: ='Handheld Total'!D73 -> -0.075911023 | E6: ='Handheld Total'!E73 -> 3518 | F6: ='Handheld Total'!F73 -> 0.18117211 | G6: ='Handheld Total'!G73 -> 0.11258697 | H6: ='Handheld Total'!H73 -> 0.36462374 | I6: ='Handheld Total'!I73 -> 405164.66 | J6: ='Handheld Total'!J73 -> 0.12677253 | K6: -0.039622682 | L6: ='Handheld Total'!L73 -> 0.09425176 | M6: ='Handheld Total'!M73 -> 0.26103376
A7: autel | B7: ='Handheld Total'!B74 -> 147.28282 | C7: ='Handheld Total'!C74 -> -0.042181138 | D7: ='Handheld Total'!D74 -> 0.0131249 | E7: ='Handheld Total'!E74 -> 2703 | F7: ='Handheld Total'!F74 -> 0.13920074 | G7: ='Handheld Total'!G74 -> 0.028147585 | H7: ='Handheld Total'!H74 -> 0.0074543422 | I7: ='Handheld Total'!I74 -> 398105.47 | J7: ='Handheld Total'!J74 -> 0.12456377 | K7: -0.015121182 | L7: ='Handheld Total'!L74 -> -0.01522085 | M7: ='Handheld Total'!M74 -> 0.02067708
A8: ancel | B8: ='Handheld Total'!B75 -> 190.88699 | C8: ='Handheld Total'!C75 -> -0.31136553 | D8: ='Handheld Total'!D75 -> -0.35221112 | E8: ='Handheld Total'!E75 -> 1001 | F8: ='Handheld Total'!F75 -> 0.051550108 | G8: ='Handheld Total'!G75 -> -0.31344307 | H8: ='Handheld Total'!H75 -> -0.35502577 | I8: ='Handheld Total'!I75 -> 191077.88 | J8: ='Handheld Total'!J75 -> 0.05978662 | K8: 0.049576305 | L8: ='Handheld Total'!L75 -> -0.52721323 | M8: ='Handheld Total'!M75 -> -0.58219287
A9: launch | B9: ='Handheld Total'!B76 -> 151.40622 | C9: ='Handheld Total'!C76 -> 0.052273339 | D9: ='Handheld Total'!D76 -> -0.067845938 | E9: ='Handheld Total'!E76 -> 864 | F9: ='Handheld Total'!F76 -> 0.044494799 | G9: ='Handheld Total'!G76 -> -0.11926606 | H9: ='Handheld Total'!H76 -> 0.39579968 | I9: ='Handheld Total'!I76 -> 130814.97 | J9: ='Handheld Total'!J76 -> 0.040930876 | K9: -0.071402476 | L9: ='Handheld Total'!L76 -> -0.073227151 | M9: ='Handheld Total'!M76 -> 0.30110034
A10: Other | B10: ='Handheld Total'!B77 -> 161.56582 | C10: ='Handheld Total'!C77 -> 0.017544148 | D10: ='Handheld Total'!D77 -> -0.034913755 | E10: ='Handheld Total'!E77 -> 3223 | F10: ='Handheld Total'!F77 -> 0.16598002 | G10: ='Handheld Total'!G77 -> -0.17759633 | H10: ='Handheld Total'!H77 -> 0.097004765 | I10: ='Handheld Total'!I77 -> 520726.63 | J10: ='Handheld Total'!J77 -> 0.16293087 | K10: -0.013437713 | L10: ='Handheld Total'!L77 -> -0.16316795 | M10: ='Handheld Total'!M77 -> 0.05870421
A11: ='Handheld Total'!A78 -> Total | B11: ='Handheld Total'!B78 -> 164.58942 | C11: ='Handheld Total'!C78 -> -0.050551412 | D11: ='Handheld Total'!D78 -> -0.074970791 | E11: ='Handheld Total'!E78 -> 19418 | F11: ='Handheld Total'!F78 -> 0.83401998 | G11: ='Handheld Total'!G78 -> 0.12210344 | H11: ='Handheld Total'!H78 -> 0.41882215 | ... J11: ='Handheld Total'!J78 -> 0.83706913 | L11: ='Handheld Total'!L78 -> 0.065379525 | M11: ='Handheld Total'!M78 -> 0.31245193
A43: Rank By Monthly Revenue - Nov '25 ONLY
A44: Ranking | B44: ASIN | C44: Product Name | D44: Brand | E44: Type | F44: Price | G44: Est. Monthly Retail Rev | H44: Est. Monthly Units Sold | I44: # of Reviews | J44: Avg. Rating | K44: Column2 | L44: Link
A45: 1 | B45: B07Z481NJM | C45: Innova 5610 OBD2 Bidirectional Scan Tool - Understand Your Vehicle, Pinpoint What's Wrong, and Complete Your Repairs with Less Headache, Updates Included, US-Based Technical Support | D45: innova | E45: Handheld | F45: 287.32292 | G45: 1127455.1 | H45: 3924 | I45: 2889 | J45: 4.4 | K45: https://amazon.com/dp/B07Z481NJM | L45: =HYPERLINK(K45) -> https://amazon.com/dp/B07Z481NJM
A46: 2 | B46: B07Z46L5FG | C46: Innova 5210 OBD2 Scanner & Engine Code Reader, Battery Tester, Live Data, Oil Reset, Car Diagnostic Tool for Most Vehicles, Bluetooth Compatible with America's Top Car Repair App | D46: innova | E46: Handheld | F46: 84.710609 | G46: 265821.89 | H46: 3138 | I46: 3668 | J46: 4.5 | K46: https://amazon.com/dp/B07Z46L5FG | L46: =HYPERLINK(K46) -> https://amazon.com/dp/B07Z46L5FG
A47: 3 | B47: B0B452YDWT | C47: ANCEL Heavy Duty Truck Scanner HD601 All System Diesel Diagnostic Scan Tool fits for Cummins, Detroit, Freightliner, International, Paccar, Check Engine for Truck & Car 2 in 1 Code Reader | D47: ancel | E47: Handheld | F47: 158.68479 | G47: 112190.15 | H47: 707 | I47: 1122 | J47: 4 | K47: https://amazon.com/dp/B0B452YDWT | L47: =HYPERLINK(K47) -> https://amazon.com/dp/B0B452YDWT
A48: 4 | B48: B019QCG5RE | C48: FOXWELL NT510 Elite Scan Tool fit for BMW Scanner Full Diagnostic Tool OBD2 Scanner, All System Bi-Directional Control Code Reader with All Reset Services, Battery Registration Tool fit for BMW Mini | D48: foxwell | E48: Handheld | F48: 190.13846 | G48: 112181.69 | H48: 590 | I48: 3066 | J48: 4.3 | K48: https://amazon.com/dp/B019QCG5RE | L48: =HYPERLINK(K48) -> https://amazon.com/dp/B019QCG5RE
A49: 5 | B49: B09YRDGY3Z | C49: Thinkdiag2 All System Bidirectional OBD2 Diagnostic Scanner for iOS & Android, Bluetooth Scan Tool with CAN-FD Protocol, 15+ Reset Functions, ECU Code, Active Test, AutoVIN, 1 Year Update | D49: thinkcar | E49: Handheld | F49: 159.9975 | G49: 92158.56 | H49: 576 | I49: 1233 | J49: 4.2 | K49: https://amazon.com/dp/B09YRDGY3Z | L49: =HYPERLINK(K49) -> https://amazon.com/dp/B09YRDGY3Z
A50: 6 | B50: B0BX3K8VGJ | C50: ANCEL AD410 PRO OBD2 Scanner and Battery Tester, 2-in-1 Car Diagnostic Tool, Check Engine Light, EVAP Test, Live Data, 12V Battery Analyzer with Cranking & Charging System Test for Car Motorcycle | D50: ancel | E50: Handheld | F50: 77.696897 | G50: 90905.37 | H50: 1170 | I50: 3830 | J50: 4.6 | K50: https://amazon.com/dp/B0BX3K8VGJ | L50: =HYPERLINK(K50) -> https://amazon.com/dp/B0BX3K8VGJ
A51: 7 | B51: B07ZL7CLYR | C51: Innova 5410 All-System OBD2 Scanner Diagnostic Tool for Cars & Trucks – Automotive Scan Tools for Engine, ABS, SRS & Transmission, Bluetooth Compatible with America's Top Car Repair App | D51: innova | E51: Handheld | F51: 152.89123 | G51: 88371.13 | H51: 578 | I51: 621 | J51: 4.4 | K51: https://amazon.com/dp/B07ZL7CLYR | L51: =HYPERLINK(K51) -> https://amazon.com/dp/B07ZL7CLYR
A52: 8 | B52: B07WD9B7GR | C52: ANCEL VD700 OBD2 Diagnostic Code Reader Scan Tool Fit for Volkswagen Audi VW Skoda Seat, All Functions OBD11 Scanner for VAG Vehicles with Battery Registration EPB Reset (Upgraded VD500) | D52: ancel | E52: Handheld | F52: 147.65206 | G52: 87557.67 | H52: 593 | I52: 1577 | J52: 4.4 | K52: https://amazon.com/dp/B07WD9B7GR | L52: =HYPERLINK(K52) -> https://amazon.com/dp/B07WD9B7GR
A53: 9 | B53: B08JGK8PPM | C53: Upgraded of NT301, FOXWELL NT301 Plus 2-in-1 OBD2 Scanner Battery Tester, Professional Check Engine Code Reader Car Diagnostic Tool, 12V Cranking Charging Analyzer for 1996+ Newer Vehicle | D53: foxwell | E53: Handheld | F53: 93.082631 | G53: 87032.26 | H53: 935 | I53: 2485 | J53: 4.5 | K53: https://amazon.com/dp/B08JGK8PPM | L53: =HYPERLINK(K53) -> https://amazon.com/dp/B08JGK8PPM
A54: 10 | B54: B07CSMJJK9 | C54: FOXWELL NT630 Plus OBD2 Scanner with ABS and SRS, 2025 ABS Auto Bleed Scan Tool Brake SRS Scanner Live Data, Car Code Reader Diagnostic Tool Bidirectional Scanner with SAS Oil Light | D54: foxwell | E54: Handheld | F54: 136.86216 | G54: 56934.66 | H54: 416 | I54: 3924 | J54: 4.2 | K54: https://amazon.com/dp/B07CSMJJK9 | L54: =HYPERLINK(K54) -> https://amazon.com/dp/B07CSMJJK9
A56: Rank By Monthly Units - Nov '25 ONLY
A57: Ranking | B57: ASIN | C57: Product Name | D57: Brand | E57: Type | F57: Price | G57: Est. Monthly Retail Rev | H57: Est. Monthly Units Sold | I57: # of Reviews | J57: Avg. Rating | K57: Column2 | L57: Link
A58: 1 | B58: B07Z481NJM | C58: Innova 5610 OBD2 Bidirectional Scan Tool - Understand Your Vehicle, Pinpoint What's Wrong, and Complete Your Repairs with Less Headache, Updates Included, US-Based Technical Support | D58: innova | E58: Handheld | F58: 287.32292 | G58: 1127455.1 | H58: 3924 | I58: 2889 | J58: 4.4 | K58: https://amazon.com/dp/B07Z481NJM | L58: =HYPERLINK(K58) -> https://amazon.com/dp/B07Z481NJM
A59: 2 | B59: B07Z46L5FG | C59: Innova 5210 OBD2 Scanner & Engine Code Reader, Battery Tester, Live Data, Oil Reset, Car Diagnostic Tool for Most Vehicles, Bluetooth Compatible with America's Top Car Repair App | D59: innova | E59: Handheld | F59: 84.710609 | G59: 265821.89 | H59: 3138 | I59: 3668 | J59: 4.5 | K59: https://amazon.com/dp/B07Z46L5FG | L59: =HYPERLINK(K59) -> https://amazon.com/dp/B07Z46L5FG
A60: 3 | B60: B0BX3K8VGJ | C60: ANCEL AD410 PRO OBD2 Scanner and Battery Tester, 2-in-1 Car Diagnostic Tool, Check Engine Light, EVAP Test, Live Data, 12V Battery Analyzer with Cranking & Charging System Test for Car Motorcycle | D60: ancel | E60: Handheld | F60: 77.696897 | G60: 90905.37 | H60: 1170 | I60: 3830 | J60: 4.6 | K60: https://amazon.com/dp/B0BX3K8VGJ | L60: =HYPERLINK(K60) -> https://amazon.com/dp/B0BX3K8VGJ
A61: 4 | B61: B08JGK8PPM | C61: Upgraded of NT301, FOXWELL NT301 Plus 2-in-1 OBD2 Scanner Battery Tester, Professional Check Engine Code Reader Car Diagnostic Tool, 12V Cranking Charging Analyzer for 1996+ Newer Vehicle | D61: foxwell | E61: Handheld | F61: 93.082631 | G61: 87032.26 | H61: 935 | I61: 2485 | J61: 4.5 | K61: https://amazon.com/dp/B08JGK8PPM | L61: =HYPERLINK(K61) -> https://amazon.com/dp/B08JGK8PPM
A62: 5 | B62: B0B452YDWT | C62: ANCEL Heavy Duty Truck Scanner HD601 All System Diesel Diagnostic Scan Tool fits for Cummins, Detroit, Freightliner, International, Paccar, Check Engine for Truck & Car 2 in 1 Code Reader | D62: ancel | E62: Handheld | F62: 158.68479 | G62: 112190.15 | H62: 707 | I62: 1122 | J62: 4 | K62: https://amazon.com/dp/B0B452YDWT | L62: =HYPERLINK(K62) -> https://amazon.com/dp/B0B452YDWT
A63: 6 | B63: B07WD9B7GR | C63: ANCEL VD700 OBD2 Diagnostic Code Reader Scan Tool Fit for Volkswagen Audi VW Skoda Seat, All Functions OBD11 Scanner for VAG Vehicles with Battery Registration EPB Reset (Upgraded VD500) | D63: ancel | E63: Handheld | F63: 147.65206 | G63: 87557.67 | H63: 593 | I63: 1577 | J63: 4.4 | K63: https://amazon.com/dp/B07WD9B7GR | L63: =HYPERLINK(K63) -> https://amazon.com/dp/B07WD9B7GR
A64: 7 | B64: B019QCG5RE | C64: FOXWELL NT510 Elite Scan Tool fit for BMW Scanner Full Diagnostic Tool OBD2 Scanner, All System Bi-Directional Control Code Reader with All Reset Services, Battery Registration Tool fit for BMW Mini | D64: foxwell | E64: Handheld | F64: 190.13846 | G64: 112181.69 | H64: 590 | I64: 3066 | J64: 4.3 | K64: https://amazon.com/dp/B019QCG5RE | L64: =HYPERLINK(K64) -> https://amazon.com/dp/B019QCG5RE
A65: 8 | B65: B07ZL7CLYR | C65: Innova 5410 All-System OBD2 Scanner Diagnostic Tool for Cars & Trucks – Automotive Scan Tools for Engine, ABS, SRS & Transmission, Bluetooth Compatible with America's Top Car Repair App | D65: innova | E65: Handheld | F65: 152.89123 | G65: 88371.13 | H65: 578 | I65: 621 | J65: 4.4 | K65: https://amazon.com/dp/B07ZL7CLYR | L65: =HYPERLINK(K65) -> https://amazon.com/dp/B07ZL7CLYR
A66: 9 | B66: B09YRDGY3Z | C66: Thinkdiag2 All System Bidirectional OBD2 Diagnostic Scanner for iOS & Android, Bluetooth Scan Tool with CAN-FD Protocol, 15+ Reset Functions, ECU Code, Active Test, AutoVIN, 1 Year Update | D66: thinkcar | E66: Handheld | F66: 159.9975 | G66: 92158.56 | H66: 576 | I66: 1233 | J66: 4.2 | K66: https://amazon.com/dp/B09YRDGY3Z | L66: =HYPERLINK(K66) -> https://amazon.com/dp/B09YRDGY3Z
A67: 10 | B67: B08925H3H1 | C67: ANCEL BM500 Battery Registration Tool Fits for BMW Mini - All Systems OBD2 Scanner with Engine, ABS, SRS, ESP, SAS System Diagnosis, Car Code Reader for CBS, EPB, ETC, BMS, PCM, Oil Reset | D67: ancel | E67: Handheld | F67: 99.890412 | G67: 48546.74 | H67: 486 | I67: 794 | J67: 4.5 | K67: https://amazon.com/dp/B08925H3H1 | L67: =HYPERLINK(K67) -> https://amazon.com/dp/B08925H3H1

Sheet Handheld $75-
A1: Handheld $75- Monthly Summary
A3: ='Handheld Total'!A80 -> Handheld $75-
B4: Avg Price | C4: Avg Price MoM | D4: Avg Price YoY | E4: Quantity/Mo | F4: Qty by % | G4: Qty MoM | H4: Qty YoY | I4: Revenue/Mo | J4: Revenue by % | L4: Revenue MoM | M4: Revenue YoY
A5: ancel | B5: ='Handheld Total'!B82 -> 33.369019 | C5: ='Handheld Total'!C82 -> -0.038853106 | D5: ='Handheld Total'!D82 -> 0.021648469 | E5: ='Handheld Total'!E82 -> 49909 | F5: ='Handheld Total'!F82 -> 0.4351378 | G5: ='Handheld Total'!G82 -> 0.20959259 | H5: ='Handheld Total'!H82 -> 0.94698447 | I5: ='Handheld Total'!I82 -> 1665414.4 | J5: ='Handheld Total'!J82 -> 0.45235884 | L5: ='Handheld Total'!L82 -> 0.16259616 | M5: ='Handheld Total'!M82 -> 0.98913371
A6: foxwell | B6: ='Handheld Total'!B83 -> 59.139208 | C6: ='Handheld Total'!C83 -> -0.052772368 | D6: ='Handheld Total'!D83 -> -0.025645834 | E6: ='Handheld Total'!E83 -> 7921 | F6: ='Handheld Total'!F83 -> 0.06906022 | G6: ='Handheld Total'!G83 -> 0.29639935 | H6: ='Handheld Total'!H83 -> 0.15114082 | I6: ='Handheld Total'!I83 -> 468441.67 | J6: ='Handheld Total'!J83 -> 0.12723784 | L6: ='Handheld Total'!L83 -> 0.22798528 | M6: ='Handheld Total'!M83 -> 0.12161886
A7: motopower | B7: ='Handheld Total'!B84 -> 26.139107 | C7: ='Handheld Total'!C84 -> 0.16063976 | D7: ='Handheld Total'!D84 -> 0.10657814 | E7: ='Handheld Total'!E84 -> 12166 | F7: ='Handheld Total'!F84 -> 0.10607078 | G7: ='Handheld Total'!G84 -> 0.087415088 | H7: ='Handheld Total'!H84 -> 0.41580356 | I7: ='Handheld Total'!I84 -> 318008.37 | J7: ='Handheld Total'!J84 -> 0.08637724 | L7: ='Handheld Total'!L84 -> 0.26209719 | M7: ='Handheld Total'!M84 -> 0.56669728
A8: autel | B8: ='Handheld Total'!B85 -> 34.070487 | C8: ='Handheld Total'!C85 -> -0.040171673 | D8: ='Handheld Total'!D85 -> -0.015021523 | E8: ='Handheld Total'!E85 -> 6202 | F8: ='Handheld Total'!F85 -> 0.054072905 | G8: ='Handheld Total'!G85 -> 0.0022624434 | H8: ='Handheld Total'!H85 -> -0.050520514 | I8: ='Handheld Total'!I85 -> 211305.16 | J8: ='Handheld Total'!J85 -> 0.057394579 | L8: ='Handheld Total'!L85 -> -0.038000116 | M8: ='Handheld Total'!M85 -> -0.064783143
A9: zmoon | B9: ='Handheld Total'!B86 -> 33.198202 | C9: ='Handheld Total'!C86 -> 0.051667078 | D9: ='Handheld Total'!D86 -> -0.22700309 | E9: ='Handheld Total'!E86 -> 3988 | F9: ='Handheld Total'!F86 -> 0.034769872 | G9: ='Handheld Total'!G86 -> 0.15160266 | H9: ='Handheld Total'!H86 -> 0.055584966 | I9: ='Handheld Total'!I86 -> 132394.43 | J9: ='Handheld Total'!J86 -> 0.035960895 | L9: ='Handheld Total'!L86 -> 0.2111026 | M9: ='Handheld Total'!M86 -> -0.18403608
A10: blcktec | B10: ='Handheld Total'!B87 -> 53.433743 | C10: ='Handheld Total'!C87 -> 0.017079775 | D10: ='Handheld Total'!D87 -> 0.14648215 | E10: ='Handheld Total'!E87 -> 1774 | F10: ='Handheld Total'!F87 -> 0.015466839 | G10: ='Handheld Total'!G87 -> 0.093037585 | H10: ='Handheld Total'!H87 -> -0.38785369 | I10: ='Handheld Total'!I87 -> 94791.46 | J10: ='Handheld Total'!J87 -> 0.025747199 | L10: ='Handheld Total'!L87 -> 0.11170642 | M10: ='Handheld Total'!M87 -> -0.29818519
A11: innova | B11: ='Handheld Total'!B88 -> 66.281562 | C11: ='Handheld Total'!C88 -> 0.0062901824 | D11: ='Handheld Total'!D88 -> 0.00032458386 | E11: ='Handheld Total'!E88 -> 160 | F11: ='Handheld Total'!F88 -> 0.0013949798 | G11: ='Handheld Total'!G88 -> -0.041916168 | H11: ='Handheld Total'!H88 -> -0.11111111 | I11: ='Handheld Total'!I88 -> 10605.05 | J11: ='Handheld Total'!J88 -> 0.0028805372 | L11: ='Handheld Total'!L88 -> -0.035889646 | M11: ='Handheld Total'!M88 -> -0.11082259
A12: Other | B12: ='Handheld Total'!B89 -> 23.963586 | C12: ='Handheld Total'!C89 -> 0.02386312 | D12: ='Handheld Total'!D89 -> -0.15187444 | E12: ='Handheld Total'!E89 -> 32577 | F12: ='Handheld Total'!F89 -> 0.28402661 | G12: ='Handheld Total'!G89 -> -0.053159333 | H12: ='Handheld Total'!H89 -> 0.22899611 | I12: ='Handheld Total'!I89 -> 780661.73 | J12: ='Handheld Total'!J89 -> 0.21204286 | L12: ='Handheld Total'!L89 -> -0.03056476 | M12: ='Handheld Total'!M89 -> 0.042343018
A13: ='Handheld Total'!A90 -> Total | B13: ='Handheld Total'!B90 -> 32.09868 | C13: ='Handheld Total'!C90 -> 0.016644668 | D13: ='Handheld Total'!D90 -> 0 | E13: ='Handheld Total'!E90 -> 114697 | F13: ='Handheld Total'!F90 -> 1 | G13: ='Handheld Total'!G90 -> 0.09855661 | H13: ='Handheld Total'!H90 -> 0 | ... J13: ='Handheld Total'!J90 -> 1 | L13: ='Handheld Total'!L90 -> 0.11684172 | M13: ='Handheld Total'!M90 -> 0
A45: Rank By Monthly Revenue - Nov '25 ONLY
A46: Ranking | B46: ASIN | C46: Product Name | D46: Brand | E46: Type | F46: Price | G46: Est. Monthly Retail Rev | H46: Est. Monthly Units Sold | I46: # of Reviews | J46: Avg. Rating | K46: Column2 | L46: Link
A47: 1 | B47: B01G5EA74I | C47: ANCEL AD310 Classic Enhanced Universal OBD II Scanner Car Engine Fault Code Reader CAN Diagnostic Scan Tool, Read and Clear Error Codes for 1996 or Newer OBD2 Protocol Vehicle (Black) | D47: ancel | E47: Handheld | F47: 28.282506 | G47: 1131017.4 | H47: 39990 | I47: 59738 | J47: 4.6 | K47: https://amazon.com/dp/B01G5EA74I | L47: =HYPERLINK(K47) -> https://amazon.com/dp/B01G5EA74I
A48: 2 | B48: B00UJV3E12 | C48: FOXWELL NT301 OBD2 Scanner Live Data Professional Mechanic OBDII Diagnostic Code Reader Tool for Check Engine Light | D48: foxwell | E48: Handheld | F48: 64.359672 | G48: 410035.47 | H48: 6371 | I48: 29066 | J48: 4.5 | K48: https://amazon.com/dp/B00UJV3E12 | L48: =HYPERLINK(K48) -> https://amazon.com/dp/B00UJV3E12
A49: 3 | B49: B071FSNL73 | C49: ANCEL AD410 Enhanced OBD2 Scanner, Vehicle Code Reader for Check Engine Light, Automotive OBD II Scanner Fault Diagnosis, OBDII Scan Tool for All OBDII Cars 1996+, Black/Yellow | D49: ancel | E49: Handheld | F49: 49.987904 | G49: 347165.99 | H49: 6945 | I49: 14142 | J49: 4.5 | K49: https://amazon.com/dp/B071FSNL73 | L49: =HYPERLINK(K49) -> https://amazon.com/dp/B071FSNL73
A50: 4 | B50: B07Z3HB7DR | C50: MOTOPOWER MP69033 Car OBD2 Scanner Code Reader Engine Fault Scanner CAN Diagnostic Scan Tool for All OBD II Protocol Cars Since 1996, Yellow | D50: motopower | E50: Handheld | F50: 25.196317 | G50: 261109.43 | H50: 10363 | I50: 48232 | J50: 4.6 | K50: https://amazon.com/dp/B07Z3HB7DR | L50: =HYPERLINK(K50) -> https://amazon.com/dp/B07Z3HB7DR
A51: 5 | B51: B0CGJ9LZQ4 | C51: OBD2 Scanner Diagnostic Tool, Check Engine Code Reader OBD2 Scanner with Reset, Mode 6, Mode 8 & I/M Readiness, Auto Check Engine Light Car Diagnostic Scan Tool for All OBDII Car Since 1996 | D51: wejowe | E51: Handheld | F51: 39.645838 | G51: 116796.64 | H51: 2946 | I51: 1353 | J51: 4.5 | K51: https://amazon.com/dp/B0CGJ9LZQ4 | L51: =HYPERLINK(K51) -> https://amazon.com/dp/B0CGJ9LZQ4
A52: 6 | B52: B0C2V3RYLY | C52: ZMOON ZM201 Professional OBD2 Scanner Diagnostic Tool, Enhanced Check Engine Code Reader with Reset OBDII/EOBD Car Diagnostic Scan Tools for All Vehicles After 1996, 2025 Upgraded | D52: zmoon | E52: Handheld | F52: 36.641688 | G52: 108752.53 | H52: 2968 | I52: 2214 | J52: 4.5 | K52: https://amazon.com/dp/B0C2V3RYLY | L52: =HYPERLINK(K52) -> https://amazon.com/dp/B0C2V3RYLY
A53: 7 | B53: B007XE8C74 | C53: Autel Professional OBD2 Scanner AL319 Code Reader, Enhanced Check and Reset Engine Fault Code, Live Data, Freeze Frame, CAN Car Diagnostic Scan Tools for All OBDII Vehicles After 1996, 2025 Upgraded | D53: autel | E53: Handheld | F53: 31.314212 | G53: 87648.48 | H53: 2799 | I53: 25566 | J53: 4.6 | K53: https://amazon.com/dp/B007XE8C74 | L53: =HYPERLINK(K53) -> https://amazon.com/dp/B007XE8C74
A54: 8 | B54: B0BY1TS725 | C54: VDIAGTOOL VD10 OBD2 Scanner Code Reader Car Diagnostic Tool Engine Fault Code Reader for Turn Off CEL with Freeze Frame/I/M Readiness for All OBDII Protocol Cars, OBD2 Scanner Diagnostic Tool | D54: vdiagtool | E54: Handheld | F54: 19.98077 | G54: 80142.87 | H54: 4011 | I54: 1843 | J54: 4.6 | K54: https://amazon.com/dp/B0BY1TS725 | L54: =HYPERLINK(K54) -> https://amazon.com/dp/B0BY1TS725
A55: 9 | B55: B07BS7PDC2 | C55: ANCEL VD500 OBD2 Scanner Diagnostic Tool for Volkswagen VW Audi Skoda Seat Diagnosis Check Engine Light EPB ABS SRS Code Reader Oil Throttle Position Adaption Brake Pad Reset | D55: ancel | E55: Handheld | F55: 67.114046 | G55: 64026.8 | H55: 954 | I55: 6150 | J55: 4.5 | K55: https://amazon.com/dp/B07BS7PDC2 | L55: =HYPERLINK(K55) -> https://amazon.com/dp/B07BS7PDC2
A56: 10 | B56: B07J51W9NS | C56: ANCEL BD310 OBD2 Scanner & Engine Code Reader - Advanced Battery Test, Trip Analysis, Performance Test, Bluetooth Diagnostic Tool for Android & iPhone - Works for All 1996+ Vehicles | D56: ancel | E56: Handheld | F56: 60.184365 | G56: 59702.89 | H56: 992 | I56: 1337 | J56: 4.3 | K56: https://amazon.com/dp/B07J51W9NS | L56: =HYPERLINK(K56) -> https://amazon.com/dp/B07J51W9NS
A58: Rank By Monthly Units - Nov '25 ONLY
A59: Ranking | B59: ASIN | C59: Product Name | D59: Brand | E59: Type | F59: Price | G59: Est. Monthly Retail Rev | H59: Est. Monthly Units Sold | I59: # of Reviews | J59: Avg. Rating | K59: Column2 | L59: Link
A60: 1 | B60: B01G5EA74I | C60: ANCEL AD310 Classic Enhanced Universal OBD II Scanner Car Engine Fault Code Reader CAN Diagnostic Scan Tool, Read and Clear Error Codes for 1996 or Newer OBD2 Protocol Vehicle (Black) | D60: ancel | E60: Handheld | F60: 28.282506 | G60: 1131017.4 | H60: 39990 | I60: 59738 | J60: 4.6 | K60: https://amazon.com/dp/B01G5EA74I | L60: =HYPERLINK(K60) -> https://amazon.com/dp/B01G5EA74I
A61: 2 | B61: B07Z3HB7DR | C61: MOTOPOWER MP69033 Car OBD2 Scanner Code Reader Engine Fault Scanner CAN Diagnostic Scan Tool for All OBD II Protocol Cars Since 1996, Yellow | D61: motopower | E61: Handheld | F61: 25.196317 | G61: 261109.43 | H61: 10363 | I61: 48232 | J61: 4.6 | K61: https://amazon.com/dp/B07Z3HB7DR | L61: =HYPERLINK(K61) -> https://amazon.com/dp/B07Z3HB7DR
A62: 3 | B62: B071FSNL73 | C62: ANCEL AD410 Enhanced OBD2 Scanner, Vehicle Code Reader for Check Engine Light, Automotive OBD II Scanner Fault Diagnosis, OBDII Scan Tool for All OBDII Cars 1996+, Black/Yellow | D62: ancel | E62: Handheld | F62: 49.987904 | G62: 347165.99 | H62: 6945 | I62: 14142 | J62: 4.5 | K62: https://amazon.com/dp/B071FSNL73 | L62: =HYPERLINK(K62) -> https://amazon.com/dp/B071FSNL73
A63: 4 | B63: B00UJV3E12 | C63: FOXWELL NT301 OBD2 Scanner Live Data Professional Mechanic OBDII Diagnostic Code Reader Tool for Check Engine Light | D63: foxwell | E63: Handheld | F63: 64.359672 | G63: 410035.47 | H63: 6371 | I63: 29066 | J63: 4.5 | K63: https://amazon.com/dp/B00UJV3E12 | L63: =HYPERLINK(K63) -> https://amazon.com/dp/B00UJV3E12
A64: 5 | B64: B0BY1TS725 | C64: VDIAGTOOL VD10 OBD2 Scanner Code Reader Car Diagnostic Tool Engine Fault Code Reader for Turn Off CEL with Freeze Frame/I/M Readiness for All OBDII Protocol Cars, OBD2 Scanner Diagnostic Tool | D64: vdiagtool | E64: Handheld | F64: 19.98077 | G64: 80142.87 | H64: 4011 | I64: 1843 | J64: 4.6 | K64: https://amazon.com/dp/B0BY1TS725 | L64: =HYPERLINK(K64) -> https://amazon.com/dp/B0BY1TS725
A65: 6 | B65: B0C2V3RYLY | C65: ZMOON ZM201 Professional OBD2 Scanner Diagnostic Tool, Enhanced Check Engine Code Reader with Reset OBDII/EOBD Car Diagnostic Scan Tools for All Vehicles After 1996, 2025 Upgraded | D65: zmoon | E65: Handheld | F65: 36.641688 | G65: 108752.53 | H65: 2968 | I65: 2214 | J65: 4.5 | K65: https://amazon.com/dp/B0C2V3RYLY | L65: =HYPERLINK(K65) -> https://amazon.com/dp/B0C2V3RYLY
A66: 7 | B66: B0CGJ9LZQ4 | C66: OBD2 Scanner Diagnostic Tool, Check Engine Code Reader OBD2 Scanner with Reset, Mode 6, Mode 8 & I/M Readiness, Auto Check Engine Light Car Diagnostic Scan Tool for All OBDII Car Since 1996 | D66: wejowe | E66: Handheld | F66: 39.645838 | G66: 116796.64 | H66: 2946 | I66: 1353 | J66: 4.5 | K66: https://amazon.com/dp/B0CGJ9LZQ4 | L66: =HYPERLINK(K66) -> https://amazon.com/dp/B0CGJ9LZQ4
A67: 8 | B67: B007XE8C74 | C67: Autel Professional OBD2 Scanner AL319 Code Reader, Enhanced Check and Reset Engine Fault Code, Live Data, Freeze Frame, CAN Car Diagnostic Scan Tools for All OBDII Vehicles After 1996, 2025 Upgraded | D67: autel | E67: Handheld | F67: 31.314212 | G67: 87648.48 | H67: 2799 | I67: 25566 | J67: 4.6 | K67: https://amazon.com/dp/B007XE8C74 | L67: =HYPERLINK(K67) -> https://amazon.com/dp/B007XE8C74
A68: 9 | B68: B01N6RKE29 | C68: FOXWELL NT201 OBD2 Scanner Code Reader for Cars and Trucks - Reset Check Engine Light, Read and Clear Fault Codes, Live Data Diagnostic Tool for All Cars Since 1996 | D68: foxwell | E68: Handheld | F68: 37.681419 | G68: 58406.2 | H68: 1550 | I68: 9808 | J68: 4.5 | K68: https://amazon.com/dp/B01N6RKE29 | L68: =HYPERLINK(K68) -> https://amazon.com/dp/B01N6RKE29
A69: 10 | B69: B07Q5H7M5S | C69: Autel OBD2 Scanner MS309 Universal Car Engine Fault Code Reader, Check Engine Light and Emission Monitor Status, OBDII CAN Diagnostic Scan Tool | D69: autel | E69: Handheld | F69: 22.689867 | G69: 30654.01 | H69: 1351 | I69: 16893 | J69: 4.6 | K69: https://amazon.com/dp/B07Q5H7M5S | L69: =HYPERLINK(K69) -> https://amazon.com/dp/B07Q5H7M5S

Sheet Dongle
A1: Dongle Monthly Summary
A3: Dongle Overall
B4: Avg Price | C4: Avg Price MoM | D4: Avg Price YoY | E4: Quantity/Mo | F4: Qty by % | G4: Qty MoM | H4: Qty YoY | I4: Revenue/Mo | J4: Revenue by % | L4: Revenue MoM | M4: Revenue YoY
A5: bluedriver | B5: 74.357517 | C5: -0.09378144 | D5: -0.16237534 | E5: 17744 | F5: 0.26266783 | G5: 0.38064115 | H5: 0.73824451 | I5: 1319399.8 | J5: 0.27212556 | K5: 0.25116263 | L5: 0.25116263 | M5: 0.45599647
A6: obdlink | B6: 119.28388 | C6: 0.0045536792 | D6: -0.0091418087 | E6: 7374 | F6: 0.10915873 | G6: 0.16144275 | H6: 0.15417123 | I6: 879599.35 | J6: 0.18141693 | K6: 0.16673158 | L6: 0.16673158 | M6: 0.14362002
A7: fixd | B7: 40.474046 | C7: 0.0020463989 | D7: -0.17578265 | E7: 7721 | F7: 0.11429544 | G7: -0.0012934937 | H7: -0.40396789 | I7: 312500.11 | J7: 0.064452994 | K7: 0.0007502582 | L7: 0.0007502582 | M7: -0.50873999
A8: xtool | B8: 116.27821 | C8: -0.058323433 | D8: 0.22533176 | E8: 2188 | F8: 0.032389383 | G8: 0.089099054 | H8: 2.2951807 | I8: 254416.72 | J8: 0.052473323 | K8: 0.025579058 | L8: 0.025579058 | M8: 3.0376896
A9: topdon | B9: 68.744628 | C9: -0.15165695 | D9: 0.031116823 | E9: 3088 | F9: 0.045712256 | G9: -0.047795251 | H9: -0.40944731 | I9: 212283.41 | J9: 0.043783349 | K9: -0.19220372 | L9: -0.19220372 | M9: -0.39107119
A10: blcktec | B10: 58.359595 | C10: -0.024803395 | D10: 0.068795347 | E10: 988 | F10: 0.014625553 | G10: 0.15151515 | H10: -0.50326797 | I10: 57659.28 | J10: 0.011892198 | K10: 0.12295367 | L10: 0.12295367 | M10: -0.46909512
A11: innova | B11: 89.708249 | C11: -0.0030875821 | D11: -0.10022665 | E11: 457 | F11: 0.0067650585 | G11: 0.015555556 | H11: -0.49446903 | I11: 40996.67 | J11: 0.008455543 | K11: 0.012419944 | L11: 0.012419944 | M11: -0.5451367
A12: Other | B12: 63.288718 | C12: 0.020540736 | D12: 0.075775914 | E12: 27993 | F12: 0.41438574 | G12: 0.00092966711 | H12: 0.18599331 | I12: 1771641.1 | J12: 0.3654001 | K12: 0.021489499 | L12: 0.021489499 | M12: 0.27586303
A13: Total | B13: =Summary!B11 -> 71.773221 | C13: =Summary!C11 -> -0.055297537 | D13: =Summary!D11 -> 0.0040103229 | E13: =Summary!E11 -> 67553 | F13: =SUM(F5:F12) -> 1 | G13: =Summary!G11 -> 0.087354731 | H13: =Summary!H11 -> 0.084317817 | I13: =Summary!I11 -> 4848496.4 | J13: =SUM(J5:J12) -> 1 | L13: =Summary!K11 -> 0.027226693 | M13: =Summary!L11 -> 0.088666282
A45: Rank By Monthly Revenue - Nov '25 ONLY
A46: Ranking | B46: ASIN | C46: Product Name | D46: Brand | E46: Type | F46: Price | G46: Est. Monthly Retail Rev | H46: Est. Monthly Units Sold | I46: # of Reviews | J46: Avg. Rating | K46: Column2 | L46: Link
A47: 1 | B47: B00652G4TS | C47: BlueDriver Bluetooth Pro OBDII Scan Tool for iPhone & Android - No Subscription Fee - OBD2 Car Scanner and Code Reader - Diagnose Check Engine, ABS, SRS, Airbag & 7000+ Issues on Vehicles 1996+ | D47: bluedriver | E47: Dongle | F47: 74.357517 | G47: 1319399.8 | H47: 17744 | I47: 60886 | J47: 4.4 | K47: https://amazon.com/dp/B00652G4TS | L47: =HYPERLINK(K47) -> https://amazon.com/dp/B00652G4TS
A48: 2 | B48: B07JFRFJG6 | C48: OBDLink MX+ OBD2 Bluetooth Scanner for iPhone, Android, and Windows | D48: obdlink | E48: Dongle | F48: 139.94207 | G48: 666544.1 | H48: 4763 | I48: 14685 | J48: 4.6 | K48: https://amazon.com/dp/B07JFRFJG6 | L48: =HYPERLINK(K48) -> https://amazon.com/dp/B07JFRFJG6
A49: 3 | B49: B013RIQMEO | C49: FIXD Bluetooth OBD2 Scanner for Car - Car Code Readers & Scan Tools for iPhone/Android - Wireless OBD2 Auto Diagnostic Tool - Check Engine & Fix All Vehicles 1996+ (1 Pack w/Free FIXD Premium Trial) | D49: fixd | E49: Dongle | F49: 39.990511 | G49: 306207.34 | H49: 7657 | I49: 33653 | J49: 4.1 | K49: https://amazon.com/dp/B013RIQMEO | L49: =HYPERLINK(K49) -> https://amazon.com/dp/B013RIQMEO
A50: 4 | B50: B0BSFTHFC1 | C50: Diesel Laptops Nexiq USB Link 3 Wireless Edition with Repair Information & Diagnostic Software Bluetooth WiFi | D50: diesel laptops | E50: Dongle | F50: 793.11914 | G50: 202245.38 | H50: 255 | I50: 106 | J50: 4.5 | K50: https://amazon.com/dp/B0BSFTHFC1 | L50: =HYPERLINK(K50) -> https://amazon.com/dp/B0BSFTHFC1
A51: 5 | B51: B09KT9XNML | C51: OBD2 Scanner Diagnostic Tool XTOOL Anyscan A30M V2.0, 2025 Wireless Bidirectional Scan Tool with Free Updates, 26 Resets, All System for Android & iPhone, Crank Sensor Relearn, EPB, Throttle Relearn | D51: xtool | E51: Dongle | F51: 141.81527 | G51: 201661.31 | H51: 1422 | I51: 1113 | J51: 4.4 | K51: https://amazon.com/dp/B09KT9XNML | L51: =HYPERLINK(K51) -> https://amazon.com/dp/B09KT9XNML
A52: 6 | B52: B08NFLL3NT | C52: OBDLink CX Bimmercode Bluetooth 5.1 OBD2 Adapter for BMW/Mini, Works with iPhone/iOS & Android, Car Coding, OBD II Diagnostic Scanner | D52: obdlink | E52: Dongle | F52: 79.9424 | G52: 173874.72 | H52: 2175 | I52: 3869 | J52: 4.6 | K52: https://amazon.com/dp/B08NFLL3NT | L52: =HYPERLINK(K52) -> https://amazon.com/dp/B08NFLL3NT
A53: 7 | B53: B073XKQQQW | C53: Veepeak OBDCheck BLE Bluetooth OBD II Scanner for iOS & Android, Car Wireless Check Engine Light Code Reader Diagnostic Tool | D53: veepeak | E53: Dongle | F53: 30.040911 | G53: 135214.14 | H53: 4501 | I53: 22552 | J53: 4.5 | K53: https://amazon.com/dp/B073XKQQQW | L53: =HYPERLINK(K53) -> https://amazon.com/dp/B073XKQQQW
A54: 8 | B54: B09N9RMVFP | C54: Z Automotive Tazer Mini Programmer | Fits 2018-2026 Jeep Wrangler JL and Gladiator JT | Customize Over 70 Settings | Activates Anti-Theft Pin Lock, Rock Crawl, Winch Mode and More! | D54: z automotive | E54: Dongle | F54: 324.35142 | G54: 132659.73 | H54: 409 | I54: 911 | J54: 4.6 | K54: https://amazon.com/dp/B09N9RMVFP | L54: =HYPERLINK(K54) -> https://amazon.com/dp/B09N9RMVFP
A55: 9 | B55: B0DP8PH63Q | C55: KINGBOLEN Ediag Elite OBD2 Scanner Bluetooth, Bidirectional Control Scanner All System Diagnostic Tool for iOS & Android, 15+ Hot Reset, CANFD Protocol, FCA AutoAuth, No Subscriptions Lifetime Update | D55: kingbolen | E55: Dongle | F55: 101.83235 | G55: 117107.2 | H55: 1150 | I55: 539 | J55: 4.2 | K55: https://amazon.com/dp/B0DP8PH63Q | L55: =HYPERLINK(K55) -> https://amazon.com/dp/B0DP8PH63Q
A56: 10 | B56: B0C3QQYQ1B | C56: TOPDON TopScan Lite OBD2 Scanner Bluetooth, Bi-Directional Scanner Wireless All System Diagnostic Tool for iOS & Android, 8+ Hot Reset, Repair Guides, Check Engine Car Code Reader, Performance Test | D56: topdon | E56: Dongle | F56: 65.301262 | G56: 100890.45 | H56: 1545 | I56: 6516 | J56: 4.1 | K56: https://amazon.com/dp/B0C3QQYQ1B | L56: =HYPERLINK(K56) -> https://amazon.com/dp/B0C3QQYQ1B
A58: Rank By Monthly Units - Nov '25 ONLY
A59: Ranking | B59: ASIN | C59: Product Name | D59: Brand | E59: Type | F59: Price | G59: Est. Monthly Retail Rev | H59: Est. Monthly Units Sold | I59: # of Reviews | J59: Avg. Rating | K59: Column2 | L59: Link
A60: 1 | B60: B00652G4TS | C60: BlueDriver Bluetooth Pro OBDII Scan Tool for iPhone & Android - No Subscription Fee - OBD2 Car Scanner and Code Reader - Diagnose Check Engine, ABS, SRS, Airbag & 7000+ Issues on Vehicles 1996+ | D60: bluedriver | E60: Dongle | F60: 74.357517 | G60: 1319399.8 | H60: 17744 | I60: 60886 | J60: 4.4 | K60: https://amazon.com/dp/B00652G4TS | L60: =HYPERLINK(K60) -> https://amazon.com/dp/B00652G4TS
A61: 2 | B61: B013RIQMEO | C61: FIXD Bluetooth OBD2 Scanner for Car - Car Code Readers & Scan Tools for iPhone/Android - Wireless OBD2 Auto Diagnostic Tool - Check Engine & Fix All Vehicles 1996+ (1 Pack w/Free FIXD Premium Trial) | D61: fixd | E61: Dongle | F61: 39.990511 | G61: 306207.34 | H61: 7657 | I61: 33653 | J61: 4.1 | K61: https://amazon.com/dp/B013RIQMEO | L61: =HYPERLINK(K61) -> https://amazon.com/dp/B013RIQMEO
A62: 3 | B62: B07JFRFJG6 | C62: OBDLink MX+ OBD2 Bluetooth Scanner for iPhone, Android, and Windows | D62: obdlink | E62: Dongle | F62: 139.94207 | G62: 666544.1 | H62: 4763 | I62: 14685 | J62: 4.6 | K62: https://amazon.com/dp/B07JFRFJG6 | L62: =HYPERLINK(K62) -> https://amazon.com/dp/B07JFRFJG6
A63: 4 | B63: B073XKQQQW | C63: Veepeak OBDCheck BLE Bluetooth OBD II Scanner for iOS & Android, Car Wireless Check Engine Light Code Reader Diagnostic Tool | D63: veepeak | E63: Dongle | F63: 30.040911 | G63: 135214.14 | H63: 4501 | I63: 22552 | J63: 4.5 | K63: https://amazon.com/dp/B073XKQQQW | L63: =HYPERLINK(K63) -> https://amazon.com/dp/B073XKQQQW
A64: 5 | B64: B08NFLL3NT | C64: OBDLink CX Bimmercode Bluetooth 5.1 OBD2 Adapter for BMW/Mini, Works with iPhone/iOS & Android, Car Coding, OBD II Diagnostic Scanner | D64: obdlink | E64: Dongle | F64: 79.9424 | G64: 173874.72 | H64: 2175 | I64: 3869 | J64: 4.6 | K64: https://amazon.com/dp/B08NFLL3NT | L64: =HYPERLINK(K64) -> https://amazon.com/dp/B08NFLL3NT
A65: 6 | B65: B0C3QQYQ1B | C65: TOPDON TopScan Lite OBD2 Scanner Bluetooth, Bi-Directional Scanner Wireless All System Diagnostic Tool for iOS & Android, 8+ Hot Reset, Repair Guides, Check Engine Car Code Reader, Performance Test | D65: topdon | E65: Dongle | F65: 65.301262 | G65: 100890.45 | H65: 1545 | I65: 6516 | J65: 4.1 | K65: https://amazon.com/dp/B0C3QQYQ1B | L65: =HYPERLINK(K65) -> https://amazon.com/dp/B0C3QQYQ1B
A66: 7 | B66: B09KT9XNML | C66: OBD2 Scanner Diagnostic Tool XTOOL Anyscan A30M V2.0, 2025 Wireless Bidirectional Scan Tool with Free Updates, 26 Resets, All System for Android & iPhone, Crank Sensor Relearn, EPB, Throttle Relearn | D66: xtool | E66: Dongle | F66: 141.81527 | G66: 201661.31 | H66: 1422 | I66: 1113 | J66: 4.4 | K66: https://amazon.com/dp/B09KT9XNML | L66: =HYPERLINK(K66) -> https://amazon.com/dp/B09KT9XNML
A67: 8 | B67: B06XGB4873 | C67: Vgate iCar Pro Bluetooth 4.0 (BLE) OBD2 Fault Code Reader OBDII Code Scanner Car Check Engine Light for iOS/Android | D67: vgate | E67: Dongle | F67: 31.989096 | G67: 44592.8 | H67: 1394 | I67: 8071 | J67: 4.5 | K67: https://amazon.com/dp/B06XGB4873 | L67: =HYPERLINK(K67) -> https://amazon.com/dp/B06XGB4873
A68: 9 | B68: B076XVQMVS | C68: Veepeak OBDCheck BLE+ Bluetooth OBD II Scanner for iOS & Android, Car Check Engine Code Reader Wireless OBD Diagnostic Scan Tool | D68: veepeak | E68: Dongle | F68: 41.957507 | G68: 57733.53 | H68: 1376 | I68: 10201 | J68: 4.6 | K68: https://amazon.com/dp/B076XVQMVS | L68: =HYPERLINK(K68) -> https://amazon.com/dp/B076XVQMVS
A69: 10 | B69: B011NSX27A | C69: Veepeak Mini Bluetooth OBD2 Scanner for Android – Not Compatible with iOS – Wireless Check Engine Light Code Reader & Diagnostic Tool | D69: veepeak | E69: Dongle | F69: 14.962462 | G69: 17805.33 | H69: 1190 | I69: 18275 | J69: 4.3 | K69: https://amazon.com/dp/B011NSX27A | L69: =HYPERLINK(K69) -> https://amazon.com/dp/B011NSX27A

Sheet Other Tools
A1: Other Tools Monthly Summary
A3: Other Tools Overall
B4: Avg Price | C4: Avg Price MoM | D4: Avg Price YoY | E4: Quantity/Mo | F4: Qty by % | G4: Qty MoM | H4: Qty YoY | I4: Revenue/Mo | J4: Revenue by % | L4: Revenue MoM | M4: Revenue YoY
A5: diesel laptops | B5: 609.38684 | C5: -0.0028583688 | D5: -0.0052021383 | E5: 602 | F5: 0.013471178 | G5: -0.16504854 | H5: 0.14448669 | I5: 366850.88 | J5: 0.12607278 | K5: -0.16743514 | L5: -0.16743514 | M5: 0.13853291
A6: obdlink | B6: 69.934779 | C6: 0.025962709 | D6: 0.1820146 | E6: 4382 | F6: 0.098057644 | G6: 0.0045850527 | H6: 0.04134981 | I6: 306454.2 | J6: 0.10531672 | K6: 0.030666802 | L6: 0.030666802 | M6: 0.23089068
A7: autel | B7: 62.023481 | C7: -0.27107231 | D7: -0.18719677 | E7: 4231 | F7: 0.094678661 | G7: -0.029587156 | H7: 0.41979866 | I7: 262421.35 | J7: 0.090184299 | K7: -0.29263921 | L7: -0.29263921 | M7: 0.15401693
A8: opus | ivs | B8: 697.34109 | C8: -0.0056726035 | D8: -0.058006336 | E8: 350 | F8: 0.0078320802 | G8: -0.18224299 | H8: 0.17056856 | I8: 244069.38 | J8: 0.08387742 | K8: -0.1868818 | L8: -0.1868818 | M8: 0.10266817
A9: krazy on highways | B9: 429.4035 | C9: 0.00046201259 | E9: 440 | F9: 0.0098460437 | G9: -0.013452915 | I9: 188937.54 | J9: 0.064930691 | K9: -0.012997118 | L9: -0.012997118
A10: Other | B10: 44.433895 | C10: -0.07484058 | D10: -0.2296803 | E10: 34683 | F10: 0.77611439 | G10: -0.028895422 | H10: 1.0774483 | I10: 1541100.8 | J10: 0.52961809 | K10: -0.10157345 | L10: -0.10157345 | M10: 0.60029937
A11: Total | B11: =Summary!B12 -> 65.215505 | C11: =Summary!C12 -> -0.09560381 | D11: =Summary!D12 -> -0.18747043 | E11: =Summary!E12 -> 44726 | F11: =SUM(F5:F10) -> 1 | G11: =Summary!G12 -> -0.029067622 | H11: =Summary!H12 -> 0.81010968 | I11: =Summary!I12 -> 2916828.7 | J11: =SUM(J5:J10) -> 1 | L11: =Summary!K12 -> -0.12189246 | M11: =Summary!L12 -> 0.47076764
A43: Rank By Monthly Revenue - Nov '25 ONLY
A44: Ranking | B44: ASIN | C44: Product Name | D44: Brand | E44: Type | F44: Price | G44: Est. Monthly Retail Rev | H44: Est. Monthly Units Sold | I44: # of Reviews | J44: Avg. Rating | K44: Column2 | L44: Link
A45: 1 | B45: B0BPYPNDVP | C45: Diesel Laptops Nexiq USB Link 3 Wired Edition with Repair Information & Diagnostic Software | D45: diesel laptops | E45: VCI | F45: 744.77953 | G45: 347812.04 | H45: 467 | I45: 211 | J45: 4.6 | K45: https://amazon.com/dp/B0BPYPNDVP | L45: =HYPERLINK(K45) -> https://amazon.com/dp/B0BPYPNDVP
A46: 2 | B46: B081VQVD3F | C46: OBDLink EX FORScan OBD Adapter | D46: obdlink | E46: Cable/Adapter | F46: 69.934779 | G46: 306454.2 | H46: 4382 | I46: 9449 | J46: 4.8 | K46: https://amazon.com/dp/B081VQVD3F | L46: =HYPERLINK(K46) -> https://amazon.com/dp/B081VQVD3F
A47: 3 | B47: B087WMGLF1 | C47: Edge Insight CTS3 Digital Gauge, Compatible with 1996 & Up OBD-II Vehicles. 84130-3 | D47: krazy on highways | E47: Other | F47: 429.4035 | G47: 188937.54 | H47: 440 | I47: 995 | J47: 4.4 | K47: https://amazon.com/dp/B087WMGLF1 | L47: =HYPERLINK(K47) -> https://amazon.com/dp/B087WMGLF1
A48: 4 | B48: B0DFM25BZB | C48: TOPDON RLink J2534 Pass-Thru Programmer, OEM Reprogramming and Diagnostic Tool, Enhanced J2534 VCI, Supports J2534/D-PDU/CAN-FD/DoIP, Compatible with 17+ Vehicle Brands, No OE Software Provided | D48: topdon | E48: VCI | F48: 260.62126 | G48: 130571.25 | H48: 501 | I48: 178 | J48: 4.5 | K48: https://amazon.com/dp/B0DFM25BZB | L48: =HYPERLINK(K48) -> https://amazon.com/dp/B0DFM25BZB
A49: 5 | B49: B07HX5QHKV | C49: Bosch EL-52100-AM GM Global Multiple Diagnostic Interface (MDI 2) Kit | D49: bosch | E49: VCI | F49: 1045.2392 | G49: 94071.53 | H49: 90 | I49: 121 | J49: 4.4 | K49: https://amazon.com/dp/B07HX5QHKV | L49: =HYPERLINK(K49) -> https://amazon.com/dp/B07HX5QHKV
A50: 6 | B50: B097NFNZBG | C50: Opus IVS Mongoose-Plus J2534 OEM Vehicle Interface Cable - Toyota/Lexus/Scion OEM Reprogramming and Diagnostics | D50: opus | ivs | E50: Cable/Adapter | F50: 575.77486 | G50: 84063.13 | H50: 146 | I50: 315 | J50: 4.5 | K50: https://amazon.com/dp/B097NFNZBG | L50: =HYPERLINK(K50) -> https://amazon.com/dp/B097NFNZBG
A51: 7 | B51: B09HVVFN9W | C51: STEELMAN PRO Wireless ChassisEAR 2 Auto Diagnostic Kit | D51: steelman pro | E51: Other | F51: 385.89673 | G51: 64830.65 | H51: 168 | I51: 89 | J51: 4.3 | K51: https://amazon.com/dp/B09HVVFN9W | L51: =HYPERLINK(K51) -> https://amazon.com/dp/B09HVVFN9W
A52: 8 | B52: B09SP8F2X6 | C52: Opus IVS CarDAQ-Plus 3 All Makes J2534 Reprogramming Tool | D52: opus | ivs | E52: Other | F52: 1926.3142 | G52: 59715.74 | H52: 31 | I52: 66 | J52: 4.4 | K52: https://amazon.com/dp/B09SP8F2X6 | L52: =HYPERLINK(K52) -> https://amazon.com/dp/B09SP8F2X6
A53: 9 | B53: B094Z7PBLS | C53: Vgate vLinker FS OBD2 USB Adapter for FORScan HS/MS-CAN Auto Switch | D53: vgate | E53: Cable/Adapter | F53: 34.980388 | G53: 54989.17 | H53: 1572 | I53: 2310 | J53: 4.7 | K53: https://amazon.com/dp/B094Z7PBLS | L53: =HYPERLINK(K53) -> https://amazon.com/dp/B094Z7PBLS
A54: 10 | B54: B000AAMY86 | C54: ScanGauge - SG2 Ultra Compact 3-in-1 Automotive Computer with Customizable Real-Time Fuel Economy Digital Gauges for OBD2 Vehicles | D54: scangauge | E54: Other | F54: 159.83081 | G54: 53223.66 | H54: 333 | I54: 2717 | J54: 4.6 | K54: https://amazon.com/dp/B000AAMY86 | L54: =HYPERLINK(K54) -> https://amazon.com/dp/B000AAMY86
A56: Rank By Monthly Units - Nov '25 ONLY
A57: Ranking | B57: ASIN | C57: Product Name | D57: Brand | E57: Type | F57: Price | G57: Est. Monthly Retail Rev | H57: Est. Monthly Units Sold | I57: # of Reviews | J57: Avg. Rating | K57: Column2 | L57: Link
A58: 1 | B58: B081VQVD3F | C58: OBDLink EX FORScan OBD Adapter | D58: obdlink | E58: Cable/Adapter | F58: 69.934779 | G58: 306454.2 | H58: 4382 | I58: 9449 | J58: 4.8 | K58: https://amazon.com/dp/B081VQVD3F | L58: =HYPERLINK(K58) -> https://amazon.com/dp/B081VQVD3F
A59: 2 | B59: B094Z7PBLS | C59: Vgate vLinker FS OBD2 USB Adapter for FORScan HS/MS-CAN Auto Switch | D59: vgate | E59: Cable/Adapter | F59: 34.980388 | G59: 54989.17 | H59: 1572 | I59: 2310 | J59: 4.7 | K59: https://amazon.com/dp/B094Z7PBLS | L59: =HYPERLINK(K59) -> https://amazon.com/dp/B094Z7PBLS
A60: 3 | B60: B01F0GVBWY | C60: OHP FORScan ELM327-based OBD2 to USB Diagnostic Scan Tool with MS-Can/HS-Can Switch for Ford Lincoln Mazda Mercury Vehicles | D60: ohp | E60: Cable/Adapter | F60: 34.00288 | G60: 42741.62 | H60: 1257 | I60: 4806 | J60: 4.4 | K60: https://amazon.com/dp/B01F0GVBWY | L60: =HYPERLINK(K60) -> https://amazon.com/dp/B01F0GVBWY
A61: 4 | B61: B07MQ8GHG3 | C61: ELM327 USB Adapter OBD2 Scanner for Windows, ELMconfig FoCCCus Diagnostic Scan Tool with MS-Can/HS-Can Switch for Ford Lincoln Mazda Mercury Series Vehicles | D61: obdresource | E61: Cable/Adapter | F61: 18.44333 | G61: 21431.15 | H61: 1162 | I61: 6755 | J61: 4.4 | K61: https://amazon.com/dp/B07MQ8GHG3 | L61: =HYPERLINK(K61) -> https://amazon.com/dp/B07MQ8GHG3
A62: 5 | B62: B071L8W7Q7 | C62: bbfly-B6 OBD2 Splitter 16 Pin OBD II Splitter Extension 1x Male and 2X Female Extension Cable Adapter (1FT/30CM) (1Pack) | D62: bbfly | E62: Cable/Adapter | F62: 10.88905 | G62: 8939.91 | H62: 821 | I62: 2017 | J62: 4.6 | K62: https://amazon.com/dp/B071L8W7Q7 | L62: =HYPERLINK(K62) -> https://amazon.com/dp/B071L8W7Q7
A63: 6 | B63: B0711LGRGQ | C63: bbfly-A9 OBD II OBD2 16 Pin Splitter Extension 1x Male and 2X Female Extension Cable Adapter (2FT/60CM) | D63: bbfly | E63: Cable/Adapter | F63: 9.8879156 | G63: 7969.66 | H63: 806 | I63: 2963 | J63: 4.6 | K63: https://amazon.com/dp/B0711LGRGQ | L63: =HYPERLINK(K63) -> https://amazon.com/dp/B0711LGRGQ
A64: 7 | B64: B0BJQKK2TJ | C64: Autel Original OBD2 12+8 Adapter for Chrysler, OBD II Bypass Cable Gateway Protocol, Universal Security Bypass 12 8 Connector for FCA SGW Car, Work for All Scanner MK808 MX808 MX900 MS906 MS908 | D64: autel | E64: Cable/Adapter | F64: 25.988545 | G64: 19647.34 | H64: 756 | I64: 413 | J64: 4.7 | K64: https://amazon.com/dp/B0BJQKK2TJ | L64: =HYPERLINK(K64) -> https://amazon.com/dp/B0BJQKK2TJ
A65: 8 | B65: B0D1MHF19J | C65: Hirificing OBD1 Scanner, OBD1 to OBD2 GM Adapter, OBD 1 Scanner Cable Code Reader OBD1 12 Pins to OBD2 OBD II 16 Pins Socket Scan Diagnostic Extension Tool Cable Connector Replacement for GM Popular | D65: hirificing | E65: Cable/Adapter | F65: 8.9794694 | G65: 6599.91 | H65: 735 | I65: 345 | J65: 3.6 | K65: https://amazon.com/dp/B0D1MHF19J | L65: =HYPERLINK(K65) -> https://amazon.com/dp/B0D1MHF19J
A66: 9 | B66: B08ZL4LRVK | C66: TTXSPP Cable Adaptor for Chrysler 12+8 Programming Cable Connector for Autel DS808 Maxisys Main Test Cable for Autel DS808 Maxisys MS905 MS906 MS906BT MS906S MS908 MS908S Pro | D66: ttxspp | E66: Cable/Adapter | F66: 15.780606 | G66: 11456.72 | H66: 726 | I66: 900 | J66: 4.8 | K66: https://amazon.com/dp/B08ZL4LRVK | L66: =HYPERLINK(K66) -> https://amazon.com/dp/B08ZL4LRVK
A67: 10 | B67: B07V3C47YD | C67: OHP ENET Bimmercode OBD2 Cable for BMW F- Series Coding | E SYS ISTA+ ICOM Bootmod3 Bimmerlink OBD | Heavy Duty Cable | D67: ohp | E67: Cable/Adapter | F67: 22.978496 | G67: 12982.85 | H67: 565 | I67: 1453 | J67: 4.7 | K67: https://amazon.com/dp/B07V3C47YD | L67: =HYPERLINK(K67) -> https://amazon.com/dp/B07V3C47YD

Sheet Ancel
A1: #VALUE!
B7: Avg Price | C7: Avg Price MoM | D7: Avg Price YoY | E7: Quantity/Mo | F7: Qty by % | G7: Qty MoM | H7: Qty YoY | I7: Revenue/Mo | J7: Revenue by % | L7: Revenue MoM | M7: Revenue YoY
A8: Tablet $800+ | B8: 829.74557 | C8: -0.048725546 | D8: -0.20974596 | E8: 221 | F8: 0.0038226696 | G8: -0.14341085 | H8: 3.1698113 | I8: 183373.77 | J8: 0.060714276 | K8: -0.18514863 | L8: -0.18514863 | M8: 2.2952102
A9: Tablet $400-$800 | B9: 489.13162 | C9: -0.060089466 | D9: -0.12070906 | E9: 377 | F9: 0.0065210247 | G9: 0.21221865 | H9: 0.24422442 | I9: 184402.62 | J9: 0.061054924 | K9: 0.13937708 | L9: 0.13937708 | M9: 0.094035267
A10: Tablet $400- | B10: 241.03601 | C10: 0.044968328 | D10: 0.18011935 | E10: 1235 | F10: 0.021361977 | G10: 0.026600166 | H10: 0.46327014 | I10: 297679.47 | J10: 0.098560408 | K10: 0.072764659 | L10: 0.072764659 | M10: 0.72683341
A11: Total Tablet | B11: 363.04193 | C11: -0.031702815 | D11: 0.098501809 | E11: 1833 | F11: 0.031705672 | G11: 0.034424379 | H11: 0.5275 | I11: 665455.86 | J11: 0.22032961 | K11: 0.0016302143 | L11: 0.0016302143 | M11: 0.67796151
A12: Handheld $75+ | B12: 115.16903 | C12: -0.016479799 | D12: -0.075911023 | E12: 3518 | F12: 0.060851366 | G12: 0.11258697 | H12: 0.36462374 | I12: 405164.66 | J12: 0.1341483 | K12: 0.09425176 | L12: 0.09425176 | M12: 0.26103376
A13: Handheld $75- | B13: 33.369019 | C13: -0.038853106 | D13: 0.021648469 | E13: 49909 | F13: 0.86328334 | G13: 0.20959259 | H13: 0.94698447 | I13: 1665414.4 | J13: 0.55141163 | K13: 0.16259616 | L13: 0.16259616 | M13: 0.98913371
A14: Total Handheld | B14: 38.755293 | C14: -0.045006507 | D14: -0.056266323 | E14: 53427 | F14: 0.92413471 | G14: 0.2026878 | H14: 0.89376861 | I14: 2070579.1 | J14: 0.68555993 | K14: 0.14855902 | L14: 0.14855902 | M14: 0.78721321
A15: Total Dongle | B15: 102.26206 | C15: 0.046709654 | D15: 0.042920265 | E15: 471 | F15: 0.0081469566 | G15: -0.14981949 | H15: -0.42350061 | I15: 48165.43 | J15: 0.015947369 | K15: -0.11010786 | L15: -0.11010786 | M15: -0.39875711
A16: Total Other Tools | B16: 62.653349 | C16: -0.13114189 | D16: 0.20260015 | E16: 1266 | F16: 0.021898189 | G16: 0.29846154 | H16: 0.50714286 | I16: 79319.14 | J16: 0.02626223 | K16: 0.12817883 | L16: 0.12817883 | M16: 0.81249023
A17: Total | B17: 50.239828 | C17: -0.074828044 | D17: -0.070344277 | E17: 56997 | F17: 0.98588553 | G17: 0.19430475 | H17: 0.8345296 | I17: 2863519.5 | J17: 0.94809914 | K17: 0.10493726 | L17: 0.10493726 | M17: 0.70548094
A49: Rank by Revenue
A50: Product Name | B50: ASIN | C50: Type | D50: Avg Price | E50: Estimated 12mo Revenue | F50: Monthly Rev | G50: Estimated 12mo Units | H50: Monthly Units | I50: # of Reviews | J50: Tool Rating | K50: Column1 | L50: Link
A51: ANCEL AD310 Classic Enhanced Universal OBD II Scanner Car Engine Fault Code Reader CAN Diagnostic Scan Tool, Read and Clear Error Codes for 1996 or Newer OBD2 Protocol Vehicle (Black) | B51: B01G5EA74I | C51: Handheld | D51: 28.282506 | E51: 11078267 | F51: 1131017.4 | G51: 379037 | H51: 39990 | I51: 59738 | J51: 4.6 | K51: https://amazon.com/dp/B01G5EA74I | L51: =HYPERLINK(K51) -> https://amazon.com/dp/B01G5EA74I
A52: ANCEL AD410 Enhanced OBD2 Scanner, Vehicle Code Reader for Check Engine Light, Automotive OBD II Scanner Fault Diagnosis, OBDII Scan Tool for All OBDII Cars 1996+, Black/Yellow | B52: B071FSNL73 | C52: Handheld | D52: 49.987904 | E52: 3614384.5 | F52: 347165.99 | G52: 62211 | H52: 6945 | I52: 14142 | J52: 4.5 | K52: https://amazon.com/dp/B071FSNL73 | L52: =HYPERLINK(K52) -> https://amazon.com/dp/B071FSNL73
A53: ANCEL X7HD 10'' Heavy Duty Truck Scanner, Semi Trucks Full System Diagnostic Tool, Bidirectional Diesel Scan Tool with DPF, ECU Coding, 40+ Reset for Cummins, Detroit, Caterpillar, Volvo, Paccar etc | B53: B0BZ82WQ4Q | C53: Tablet | D53: 815.06799 | E53: 1440167.7 | F53: 170349.21 | G53: 1492 | H53: 209 | I53: 764 | J53: 3.9 | K53: https://amazon.com/dp/B0BZ82WQ4Q | L53: =HYPERLINK(K53) -> https://amazon.com/dp/B0BZ82WQ4Q
A54: ANCEL Heavy Duty Truck Scanner HD601 All System Diesel Diagnostic Scan Tool fits for Cummins, Detroit, Freightliner, International, Paccar, Check Engine for Truck & Car 2 in 1 Code Reader | B54: B0B452YDWT | C54: Handheld | D54: 158.68479 | E54: 1317292.2 | F54: 112190.15 | G54: 6923 | H54: 707 | I54: 1122 | J54: 4 | K54: https://amazon.com/dp/B0B452YDWT | L54: =HYPERLINK(K54) -> https://amazon.com/dp/B0B452YDWT
A55: ANCEL AD410 PRO OBD2 Scanner and Battery Tester, 2-in-1 Car Diagnostic Tool, Check Engine Light, EVAP Test, Live Data, 12V Battery Analyzer with Cranking & Charging System Test for Car Motorcycle | B55: B0BX3K8VGJ | C55: Handheld | D55: 77.696897 | E55: 860328.69 | F55: 90905.37 | G55: 8968 | H55: 1170 | I55: 3830 | J55: 4.6 | K55: https://amazon.com/dp/B0BX3K8VGJ | L55: =HYPERLINK(K55) -> https://amazon.com/dp/B0BX3K8VGJ
A56: ANCEL VD700 OBD2 Diagnostic Code Reader Scan Tool Fit for Volkswagen Audi VW Skoda Seat, All Functions OBD11 Scanner for VAG Vehicles with Battery Registration EPB Reset (Upgraded VD500) | B56: B07WD9B7GR | C56: Handheld | D56: 147.65206 | E56: 748857.56 | F56: 87557.67 | G56: 4951 | H56: 593 | I56: 1577 | J56: 4.4 | K56: https://amazon.com/dp/B07WD9B7GR | L56: =HYPERLINK(K56) -> https://amazon.com/dp/B07WD9B7GR
A57: ANCEL HD3400 Pro Heavy Duty Truck Scanner | DPF Regeneration, Lifetime Free Update, Compatible with Commercial Vehicles with Cummins, Paccar, Caterpillar, Detroit, Volvo, Mack, International Engines | B57: B09R3L5BP2 | C57: Tablet | D57: 498.69187 | E57: 763473.32 | F57: 85276.31 | G57: 1252 | H57: 171 | I57: 504 | J57: 4.1 | K57: https://amazon.com/dp/B09R3L5BP2 | L57: =HYPERLINK(K57) -> https://amazon.com/dp/B09R3L5BP2
A58: OBD2 Scanner ANCEL FX6100 Bidirectional Scan Tool, All Systems Car Diagnostic Scanner, Code Reader with Active Test,15+ Reset, Oil/EPB/BMS/ABS Bleeding/SAS/D-PF Reset, FCA&CANFD, AutoVin, Free Upgrade | B58: B0F38JZ2PR | C58: Tablet | D58: 311.81066 | E58: 833923.47 | F58: 71404.64 | G58: 1194 | H58: 229 | I58: 159 | J58: 4.4 | K58: https://amazon.com/dp/B0F38JZ2PR | L58: =HYPERLINK(K58) -> https://amazon.com/dp/B0F38JZ2PR
A59: ANCEL VD500 OBD2 Scanner Diagnostic Tool for Volkswagen VW Audi Skoda Seat Diagnosis Check Engine Light EPB ABS SRS Code Reader Oil Throttle Position Adaption Brake Pad Reset | B59: B07BS7PDC2 | C59: Handheld | D59: 67.114046 | E59: 700876.5 | F59: 64026.8 | G59: 8770 | H59: 954 | I59: 6150 | J59: 4.5 | K59: https://amazon.com/dp/B07BS7PDC2 | L59: =HYPERLINK(K59) -> https://amazon.com/dp/B07BS7PDC2
A60: ANCEL BD310 OBD2 Scanner & Engine Code Reader - Advanced Battery Test, Trip Analysis, Performance Test, Bluetooth Diagnostic Tool for Android & iPhone - Works for All 1996+ Vehicles | B60: B07J51W9NS | C60: Handheld | D60: 60.184365 | E60: 928856.8 | F60: 59702.89 | G60: 12831 | H60: 992 | I60: 1337 | J60: 4.3 | K60: https://amazon.com/dp/B07J51W9NS | L60: =HYPERLINK(K60) -> https://amazon.com/dp/B07J51W9NS
A61: ANCEL DS100 OBD2 Scanner - ABS, SRS, Transmission & Check Engine Code Reader with 7 Reset, Oil/Brake/BMS/SAS/ETS Reset, ABS Bleeding, Gear Learning, Lifetime Free Update, Online Customer Service | B61: B0DHX8FFVR | C61: Tablet | D61: 199.98468 | E61: 705797.52 | F61: 58995.48 | G61: 3525 | H61: 295 | I61: 283 | J61: 4.4 | K61: https://amazon.com/dp/B0DHX8FFVR | L61: =HYPERLINK(K61) -> https://amazon.com/dp/B0DHX8FFVR
A62: ANCEL DS200 Full System OBD2 Scanner with 15+ Reset Services - Oil/BMS/Brake Reset, DPF Regen, Injector Coding, ABS Bleeding, Free Lifetime Updates, Online Customer Service | B62: B0DHX29NMC | C62: Tablet | D62: 278.43624 | E62: 514665.91 | F62: 58471.61 | G62: 1641 | H62: 210 | I62: 171 | J62: 4.4 | K62: https://amazon.com/dp/B0DHX29NMC | L62: =HYPERLINK(K62) -> https://amazon.com/dp/B0DHX29NMC
... A125: ANCEL MT700 Motorcycle Diagnostic Tool for Harley BMW Kawasaki Suzuki Piaggio Ducati Obd2 Scanner, ABS Bleeding Check Engine Code Reader with Oil Light Reset, 31+ Function, 16 Brand-Specific Adapters | B125: B0CGXFXRJY | C125: Tablet | D125: 899.99 | E125: 30955.93 | F125: 0 | G125: 33 | H125: 0 | I125: 2 | J125: 2 | K125: https://amazon.com/dp/B0CGXFXRJY | L125: =HYPERLINK(K125) -> https://amazon.com/dp/B0CGXFXRJY
A126: Total | E126: =SUM(E51:E125) -> 32390812 | F126: =SUM(F51:F125) -> 3020274.3
A129: Rank by Units
A130: Product Name | B130: ASIN | C130: Type | D130: Avg Price | E130: Estimated 12mo Revenue | F130: Monthly Rev | G130: Estimated 12mo Units | H130: Monthly Units | I130: # of Reviews | J130: Tool Rating | K130: Column1 | L130: Link
A131: ANCEL AD310 Classic Enhanced Universal OBD II Scanner Car Engine Fault Code Reader CAN Diagnostic Scan Tool, Read and Clear Error Codes for 1996 or Newer OBD2 Protocol Vehicle (Black) | B131: B01G5EA74I | C131: Handheld | D131: 28.282506 | E131: 11078267 | F131: 1131017.4 | G131: 379037 | H131: 39990 | I131: 59738 | J131: 4.6 | K131: https://amazon.com/dp/B01G5EA74I | L131: =HYPERLINK(K131) -> https://amazon.com/dp/B01G5EA74I
A132: ANCEL AD410 Enhanced OBD2 Scanner, Vehicle Code Reader for Check Engine Light, Automotive OBD II Scanner Fault Diagnosis, OBDII Scan Tool for All OBDII Cars 1996+, Black/Yellow | B132: B071FSNL73 | C132: Handheld | D132: 49.987904 | E132: 3614384.5 | F132: 347165.99 | G132: 62211 | H132: 6945 | I132: 14142 | J132: 4.5 | K132: https://amazon.com/dp/B071FSNL73 | L132: =HYPERLINK(K132) -> https://amazon.com/dp/B071FSNL73
A133: ANCEL AD410 PRO OBD2 Scanner and Battery Tester, 2-in-1 Car Diagnostic Tool, Check Engine Light, EVAP Test, Live Data, 12V Battery Analyzer with Cranking & Charging System Test for Car Motorcycle | B133: B0BX3K8VGJ | C133: Handheld | D133: 77.696897 | E133: 860328.69 | F133: 90905.37 | G133: 8968 | H133: 1170 | I133: 3830 | J133: 4.6 | K133: https://amazon.com/dp/B0BX3K8VGJ | L133: =HYPERLINK(K133) -> https://amazon.com/dp/B0BX3K8VGJ
A134: ANCEL BD310 OBD2 Scanner & Engine Code Reader - Advanced Battery Test, Trip Analysis, Performance Test, Bluetooth Diagnostic Tool for Android & iPhone - Works for All 1996+ Vehicles | B134: B07J51W9NS | C134: Handheld | D134: 60.184365 | E134: 928856.8 | F134: 59702.89 | G134: 12831 | H134: 992 | I134: 1337 | J134: 4.3 | K134: https://amazon.com/dp/B07J51W9NS | L134: =HYPERLINK(K134) -> https://amazon.com/dp/B07J51W9NS
A135: ANCEL VD500 OBD2 Scanner Diagnostic Tool for Volkswagen VW Audi Skoda Seat Diagnosis Check Engine Light EPB ABS SRS Code Reader Oil Throttle Position Adaption Brake Pad Reset | B135: B07BS7PDC2 | C135: Handheld | D135: 67.114046 | E135: 700876.5 | F135: 64026.8 | G135: 8770 | H135: 954 | I135: 6150 | J135: 4.5 | K135: https://amazon.com/dp/B07BS7PDC2 | L135: =HYPERLINK(K135) -> https://amazon.com/dp/B07BS7PDC2
A136: ANCEL AD530 OBD2 Scanner Diagnostic Tool, Universal Check Engine Code Reader with Live Data, Car Diagnostic Tool with Upgraded Battery Tester & All OBD2 Functions for 1996+ Cars, Upgraded AD310 | B136: B07N66TTQG | C136: Handheld | D136: 64.7525 | E136: 618039.7 | F136: 53097.05 | G136: 8686 | H136: 820 | I136: 3922 | J136: 4.5 | K136: https://amazon.com/dp/B07N66TTQG | L136: =HYPERLINK(K136) -> https://amazon.com/dp/B07N66TTQG
A137: ANCEL Heavy Duty Truck Scanner HD601 All System Diesel Diagnostic Scan Tool fits for Cummins, Detroit, Freightliner, International, Paccar, Check Engine for Truck & Car 2 in 1 Code Reader | B137: B0B452YDWT | C137: Handheld | D137: 158.68479 | E137: 1317292.2 | F137: 112190.15 | G137: 6923 | H137: 707 | I137: 1122 | J137: 4 | K137: https://amazon.com/dp/B0B452YDWT | L137: =HYPERLINK(K137) -> https://amazon.com/dp/B0B452YDWT
A138: ANCEL VD700 OBD2 Diagnostic Code Reader Scan Tool Fit for Volkswagen Audi VW Skoda Seat, All Functions OBD11 Scanner for VAG Vehicles with Battery Registration EPB Reset (Upgraded VD500) | B138: B07WD9B7GR | C138: Handheld | D138: 147.65206 | E138: 748857.56 | F138: 87557.67 | G138: 4951 | H138: 593 | I138: 1577 | J138: 4.4 | K138: https://amazon.com/dp/B07WD9B7GR | L138: =HYPERLINK(K138) -> https://amazon.com/dp/B07WD9B7GR
A139: ANCEL BM500 Battery Registration Tool Fits for BMW Mini - All Systems OBD2 Scanner with Engine, ABS, SRS, ESP, SAS System Diagnosis, Car Code Reader for CBS, EPB, ETC, BMS, PCM, Oil Reset | B139: B08925H3H1 | C139: Handheld | D139: 99.890412 | E139: 457942.06 | F139: 48546.74 | G139: 2858 | H139: 486 | I139: 794 | J139: 4.5 | K139: https://amazon.com/dp/B08925H3H1 | L139: =HYPERLINK(K139) -> https://amazon.com/dp/B08925H3H1
A140: ANCEL BM700 PRO Fit for BMW Scanner - Battery Registration Tool, Code Reader for BMW/Mini/RR, Advanced OBD2 Scanner Auto V-I-N, Full System Diagnostic for BMW Scan Tool with All Reset Services (Blue) | B140: B0F7R3JGYM | C140: Handheld | D140: 140.37934 | E140: 622234.01 | F140: 52923.01 | G140: 1590 | H140: 377 | I140: 2066 | J140: 4.5 | K140: https://amazon.com/dp/B0F7R3JGYM | L140: =HYPERLINK(K140) -> https://amazon.com/dp/B0F7R3JGYM
A141: ANCEL Protective Case Storage Bag for OBD2 Scanner Code Reader Diagnostic Scan Tool Battery Tester | B141: B07B49PHXD | C141: Other | D141: 22.965702 | E141: 128493.19 | F141: 8175.79 | G141: 4349 | H141: 356 | I141: 3832 | J141: 4.6 | K141: https://amazon.com/dp/B07B49PHXD | L141: =HYPERLINK(K141) -> https://amazon.com/dp/B07B49PHXD
A142: ANCEL DS100 OBD2 Scanner - ABS, SRS, Transmission & Check Engine Code Reader with 7 Reset, Oil/Brake/BMS/SAS/ETS Reset, ABS Bleeding, Gear Learning, Lifetime Free Update, Online Customer Service | B142: B0DHX8FFVR | C142: Tablet | D142: 199.98468 | E142: 705797.52 | F142: 58995.48 | G142: 3525 | H142: 295 | I142: 283 | J142: 4.4 | K142: https://amazon.com/dp/B0DHX8FFVR | L142: =HYPERLINK(K142) -> https://amazon.com/dp/B0DHX8FFVR
... A205: ANCEL MT700 Motorcycle Diagnostic Tool for Harley BMW Kawasaki Suzuki Piaggio Ducati Obd2 Scanner, ABS Bleeding Check Engine Code Reader with Oil Light Reset, 31+ Function, 16 Brand-Specific Adapters | B205: B0CGXFXRJY | C205: Tablet | D205: 899.99 | E205: 30955.93 | F205: 0 | G205: 33 | H205: 0 | I205: 2 | J205: 2 | K205: https://amazon.com/dp/B0CGXFXRJY | L205: =HYPERLINK(K205) -> https://amazon.com/dp/B0CGXFXRJY
A206: Total | G206: =SUM(G131:G205) -> 544472 | H206: =SUM(H131:H205) -> 57813

Sheet AUTEL
A1: #VALUE!
B7: Avg Price | C7: Avg Price MoM | D7: Avg Price YoY | E7: Quantity/Mo | F7: Qty by % | G7: Qty MoM | H7: Qty YoY | I7: Revenue/Mo | J7: Revenue by % | L7: Revenue MoM | M7: Revenue YoY
A8: Tablet $800+ | B8: 1911.1723 | C8: 0.03079727 | D8: -0.051980902 | E8: 1031 | F8: 0.054032808 | G8: -0.16720517 | H8: -0.070333634 | I8: 1970418.6 | J8: 0.35992637 | K8: -0.14155736 | L8: -0.14155736 | M8: -0.11865853
A9: Tablet $400-$800 | B9: 528.17359 | C9: 0.0017846352 | D9: 0.00038571678 | E9: 4587 | F9: 0.24039621 | G9: 0.083372697 | H9: 0.27700445 | I9: 2422732.2 | J9: 0.44254819 | K9: 0.085306122 | L9: 0.085306122 | M9: 0.27749702
A10: Tablet $400- | B10: 379.10721 | C10: 0.10244041 | E10: 43 | F10: 0.0022535507 | G10: 9.75 | H10: N/A | I10: 16301.61 | J10: 0.0029777323 | K10: 10.851234 | L10: 10.851234 | M10: N/A
A11: Total Tablet | B11: 778.9176 | C11: -0.058217228 | D11: -0.1138579 | E11: 5661 | F11: 0.29668256 | G11: 0.033783784 | H11: 0.20421187 | I11: 4409452.5 | J11: 0.80545229 | K11: -0.026400242 | L11: -0.026400242 | M11: 0.06710284
A12: Handheld $75+ | B12: 190.88699 | C12: -0.31136553 | D12: -0.35221112 | E12: 1001 | F12: 0.052460563 | G12: -0.31344307 | H12: -0.35502577 | I12: 191077.88 | J12: 0.034903226 | K12: -0.52721323 | L12: -0.52721323 | M12: -0.58219287
A13: Handheld $75- | B13: 34.070487 | C13: -0.040171673 | D13: -0.015021523 | E13: 6202 | F13: 0.32503538 | G13: 0.0022624434 | H13: -0.050520514 | I13: 211305.16 | J13: 0.03859804 | K13: -0.038000116 | L13: -0.038000116 | M13: -0.064783143
A14: Total Handheld | B14: 55.863257 | C14: -0.31528131 | D14: -0.33907009 | E14: 7203 | F14: 0.37749594 | G14: -0.057938792 | H14: -0.1089807 | I14: 402383.04 | J14: 0.073501266 | K14: -0.35495309 | L14: -0.35495309 | M14: -0.4110987
A15: Total Dongle | B15: 98.034724 | C15: 0.015832269 | D15: -0.086368086 | E15: 1179 | F15: 0.061789214 | G15: 0.0025510204 | H15: 0.33673469 | I15: 115582.94 | J15: 0.021112949 | K15: 0.018423677 | L15: 0.018423677 | M15: 0.22128348
A16: Total Other Tools | B16: 62.023481 | C16: -0.27107231 | D16: -0.18719677 | E16: 4231 | F16: 0.2217389 | G16: -0.029587156 | H16: 0.41979866 | I16: 262421.35 | J16: 0.047935175 | K16: -0.29263921 | L16: -0.29263921 | M16: 0.15401693
A17: Total | B17: 284.0013 | C17: -0.060029819 | D17: -0.079750759 | E17: 18274 | F17: 0.95770662 | G17: -0.020580984 | H17: 0.097735328 | I17: 5189839.8 | J17: 0.94800168 | K17: -0.07937533 | L17: -0.07937533 | M17: 0.010190102
A49: Rank by Revenue
A50: Product Name | B50: ASIN | C50: Type | D50: Avg Price | E50: Estimated 12mo Revenue | F50: Monthly Rev | G50: Estimated 12mo Units | H50: Monthly Units | I50: # of Reviews | J50: Tool Rating | K50: Column1 | L50: Link
A51: Autel Scanner MaxiCOM MK808S: 2025 Bidirectional Tool as MK808BT Pro MX808S M808Z, Work as MaxiCheck MX900 MK900BT, 28+ Service, Active Test, All System Diagnose, Injector C0ding, FCA Autoauth OS 11 | B51: B0744B55QV | C51: Tablet | D51: 451.83728 | E51: 8931538.6 | F51: 684985.31 | G51: 18301 | H51: 1516 | I51: 3604 | J51: 4.5 | K51: https://amazon.com/dp/B0744B55QV | L51: =HYPERLINK(K51) -> https://amazon.com/dp/B0744B55QV
A52: Autel Scanner MaxiCOM MK900BT, 2025 MK900-BT V2.0 Bidirectional Diagnostic Tool, 8in Up of MK900 MX900 MK808S MK808BT MX808S MK808Z, 3000+ Active Tests, 40+ Service, CAN-FD&DOIP, All System, FCA 11 OS | B52: B098PYB8XG | C52: Tablet | D52: 659.22073 | E52: 4661285.6 | F52: 479912.69 | G52: 5728 | H52: 728 | I52: 580 | J52: 4.6 | K52: https://amazon.com/dp/B098PYB8XG | L52: =HYPERLINK(K52) -> https://amazon.com/dp/B098PYB8XG
A53: Autel Scanner MaxiCheck MX808S, 2025 US Ver. of MaxiCOM MK808S/ MK808Z, Bidirectional 11OS as MX900 MK900 MK900BT, 3000+ Active Test, 28+ Service, OE All System OBDII Diagnostic Tool, FCA Autoauth | B53: B08ML7T7KZ | C53: Tablet | D53: 443.71323 | E53: 2906357.2 | F53: 287526.17 | G53: 5442 | H53: 648 | I53: 643 | J53: 4.7 | K53: https://amazon.com/dp/B08ML7T7KZ | L53: =HYPERLINK(K53) -> https://amazon.com/dp/B08ML7T7KZ
A54: Autel MaxiSys Ultra S2 Scanner, 2025 Top Intelligen Scan Diagnostic with AI, 6-in-1 VCMI2, Up of MSUltra/ MS919, Topology 3.0, Multi-Point DVI, Programming, Motor Truspeed Repair, EV Test, 48+ Service | B54: B0DZC1M7MZ | C54: Tablet | D54: 5586.271 | E54: 1853332.9 | F54: 162001.86 | G54: 166 | H54: 29 | I54: 16 | J54: 4.6 | K54: https://amazon.com/dp/B0DZC1M7MZ | L54: =HYPERLINK(K54) -> https://amazon.com/dp/B0DZC1M7MZ
A55: Autel Scanner MaxiCOM MK900: 2025 Same as MK900BT MK900-BT MX900 Bidirectional Diagnostic Tool, 8in Up of MK808S MK808BT Pro MX808S MK808Z, 3K+ Active Tests, 40+ Service, CAN-FD&DOIP, All System, FCA | B55: B073CQMF25 | C55: Tablet | D55: 546.5021 | E55: 2014309.1 | F55: 159032.11 | G55: 2973 | H55: 291 | I55: 265 | J55: 4.4 | K55: https://amazon.com/dp/B073CQMF25 | L55: =HYPERLINK(K55) -> https://amazon.com/dp/B073CQMF25
A56: Autel Scanner MaxiCOM MK808BT PRO, 2025 2.0 Full Bidirectional Diagnostic Tool as MK900 MX900 MK900BT, Pro Ver. of MK808S MX808S, 3000+ Test, 28+ Service, All System, Brake Bleed, Injector Coding, FCA | B56: B07MBSZH48 | C56: Tablet | D56: 512.48232 | E56: 2135390.3 | F56: 154769.66 | G56: 3805 | H56: 302 | I56: 1750 | J56: 4.6 | K56: https://amazon.com/dp/B07MBSZH48 | L56: =HYPERLINK(K56) -> https://amazon.com/dp/B07MBSZH48
A57: Autel Scanner MaxiCOM MK900BT, 2025 MK900-BT Bidirectional Diagnostic Scan Tool, 2.0 BT Ver. of MK900 MX900, 8in Up of MK808S MK808BT PRO MX808S MK808Z, 40+ Reset, 3K+ Active Tests, CAN FD & DoIP, FCA | B57: B09712X5CW | C57: Tablet | D57: 659.10106 | E57: 1315101.2 | F57: 112047.18 | G57: 1839 | H57: 170 | I57: 165 | J57: 4.6 | K57: https://amazon.com/dp/B09712X5CW | L57: =HYPERLINK(K57) -> https://amazon.com/dp/B09712X5CW
A58: Autel Scanner MaxiCOM MK900BT: 2025 8in MK900-BT V2.0 Bidirectional Scan Tool, 33ft BT Ver. of MK900 MX900 MK808S MK808BT PRO MX808S MK808Z, 40+ Service, 3K+ Active Tests, DOIP CANFD, All System, FCA | B58: B07PGYY8SS | C58: Tablet | D58: 657.04445 | E58: 998982.31 | F58: 107755.29 | G58: 1214 | H58: 164 | I58: 146 | J58: 4.7 | K58: https://amazon.com/dp/B07PGYY8SS | L58: =HYPERLINK(K58) -> https://amazon.com/dp/B07PGYY8SS
A59: Autel Professional OBD2 Scanner AL319 Code Reader, Enhanced Check and Reset Engine Fault Code, Live Data, Freeze Frame, CAN Car Diagnostic Scan Tools for All OBDII Vehicles After 1996, 2025 Upgraded | B59: B007XE8C74 | C59: Handheld | D59: 31.314212 | E59: 1101727.8 | F59: 87648.48 | G59: 25635 | H59: 2799 | I59: 25566 | J59: 4.6 | K59: https://amazon.com/dp/B007XE8C74 | L59: =HYPERLINK(K59) -> https://amazon.com/dp/B007XE8C74
A60: Autel Scanner MaxiSYS MS906 PRO-TS, 2025 MS906 Pro TS Up of MS906MAX MS906PRO MP900TS MP900BT, Top TPMS Function, CAN FD&DoIP, Bidirectional Scan Tool, 3000+ Active Test, 36+ Service, FCA, OS 10 | B60: B09JG9L1QC | C60: Tablet | D60: 1609.7222 | E60: 963853.21 | F60: 57950 | G60: 577 | H60: 36 | I60: 193 | J60: 4.6 | K60: https://amazon.com/dp/B09JG9L1QC | L60: =HYPERLINK(K60) -> https://amazon.com/dp/B09JG9L1QC
A61: Autel Scanner MaxiSys MS909 Intelligent Scan Tool, 2025 Motor TruSpeed Same as MSUltra Ultra S2 MS919, TSB, Topology 2.0, Up of Elite 2 PRO MS908S PRO II, DOIP & CAN FD, 40+ Service, 3K+ Bidirectional | B61: B08P3CX6MY | C61: Tablet | D61: 2945.6433 | E61: 396649.57 | F61: 53021.58 | G61: 96 | H61: 18 | I61: 23 | J61: 4.7 | K61: https://amazon.com/dp/B08P3CX6MY | L61: =HYPERLINK(K61) -> https://amazon.com/dp/B08P3CX6MY
A62: Autel Scanner MaxiCOM MK808BT PRO, 2025 Bidirectional Diagnostic Scan Tool as MK900BT, 2.0 BT Ver. of MK808S MX808S MX900 MK900, 3000+ Active Tests, 28+ Reset, Injector Coding, All Systems, FCA, OS 11 | B62: B07FFT8SCC | C62: Tablet | D62: 546.73189 | E62: 433891.51 | F62: 49205.87 | G62: 706 | H62: 90 | I62: 641 | J62: 4.5 | K62: https://amazon.com/dp/B07FFT8SCC | L62: =HYPERLINK(K62) -> https://amazon.com/dp/B07FFT8SCC
... A73: Autel OBD2 Scanner, 2025 Automotive Diagnostic Tool with $1316 Accessory Tools, Up of MaxiSYS Elite 2 PRO MS908S PRO II, 3000+ Active Tests Bidirectional, 40+ Services, OS10 4/128GB CAN FD DoIP | B73: B08PNTTMQ8 | C73: Tablet | D73: 3295.26 | E73: 1101048.8 | F73: 36247.86 | G73: 325 | H73: 11 | I73: 76 | J73: 4.8 | K73: https://amazon.com/dp/B08PNTTMQ8 | L73: =HYPERLINK(K73) -> https://amazon.com/dp/B08PNTTMQ8
A74: Autel MaxiSys Elite II Pro Diagnostic Scanner - J2534 Reprogramming Tool as Ultra MS908S PRO II, OE-Level ECU Programming Tool with 150+ Car Brands Coverage, 40+ Services, 2-Year Free Updates | B74: B0FJLSKLBP | D74: 2193.2294 | E74: 391407.09 | F74: 35091.67 | G74: 16 | H74: 16 | I74: 2 | J74: 5 | K74: https://amazon.com/dp/B0FJLSKLBP | L74: =HYPERLINK(K74) -> https://amazon.com/dp/B0FJLSKLBP
A75: Autel MaxiPRO MP900-BT KIT Scanner: 2025 Level-up of MP900Z-BT, MP808BT Pro, MP808BT KIT w/DoIP CAN-FD, 40+ Services, OE ECU C0ding, 11 PCS OBD1 Cables, Bi-Directional, 150+ Makes, FCA Re.Nault SGW | B75: B0751G1W5C | C75: Tablet | D75: 971.14472 | E75: 344341.53 | F75: 34961.21 | G75: 321 | H75: 36 | I75: 129 | J75: 4.6 | K75: https://amazon.com/dp/B0751G1W5C | L75: =HYPERLINK(K75) -> https://amazon.com/dp/B0751G1W5C
A76: Autel MaxiCheck MX808S-TS Scanner: 2025 Same as MX900-TS TS900, US Ver. of MaxiCOM MK808S-TS MK808Z-TS Upgrade of MK808S MK808Z, Top TPMS Programming Tool, 3000+ Active Test, 28+ Service, 11 OS, FCA | B76: B09QX69JQW | C76: Tablet | D76: 658.25057 | E76: 275866.3 | F76: 34887.28 | G76: 318 | H76: 53 | I76: 87 | J76: 4.7 | K76: https://amazon.com/dp/B09QX69JQW | L76: =HYPERLINK(K76) -> https://amazon.com/dp/B09QX69JQW
A77: Autel Scanner MaxiSYS MS919, 2025 Top Intelligent Same as MSUltra, $2000 5in1 VCMI, Motor TruSpeed Topology 2.0, Up of MS909/ Elite II Pro/Ultra Lite, J2534 Tool, 40+ Services, 3000+ Active Tests | B77: B08PPBL1GS | C77: Tablet | D77: 3853.14 | E77: 223723.58 | F77: 34678.26 | G77: 16 | H77: 9 | I77: 21 | J77: 4.3 | K77: https://amazon.com/dp/B08PPBL1GS | L77: =HYPERLINK(K77) -> https://amazon.com/dp/B08PPBL1GS
A78: 2025 Autel Scanner Bidirectional Diagnostic Scan Tool, Full Bundle Pro Version, Enhanced All System Diagnose w/ 3000+ Active Test, 40+ Service, OS11.0, FCA SGW | B78: B07W6YYLY8 | C78: Tablet | D78: 1684.9965 | E78: 557773.96 | F78: 33699.93 | G78: 292 | H78: 20 | I78: 77 | J78: 4.4 | K78: https://amazon.com/dp/B07W6YYLY8 | L78: =HYPERLINK(K78) -> https://amazon.com/dp/B07W6YYLY8
A79: Autel MaxiSYS Ultra S2 OBD2 Scanner, 2025 New Diagnostic with AI, Upgraded MS Ultra, 6-in-1 VCMI2, Topology 3.0, EV Tests, WiFi 6, 48+ Services, Motor Truspeed Repair, Multi-Point DVI, ECU Programming | B79: B0F2M4JM9H | C79: Tablet | D79: 5616.0567 | E79: 318059.63 | F79: 33696.34 | G79: 22 | H79: 6 | I79: 2 | J79: 5 | K79: https://amazon.com/dp/B0F2M4JM9H | L79: =HYPERLINK(K79) -> https://amazon.com/dp/B0F2M4JM9H
A80: Autel MaxiSys MS906 PRO Scanner, 2025 MS906Pro Same as MS906MAX, Top ECU Elite 2.0 of MS906BT MP900BT MP900 MS908S, Bidirectional 3K+ Test, OE All Sys, CAN FD DoIP, 36+ Service, AutoScan 2.0 | B80: B00UEHHI3G | C80: Tablet | D80: 1423.2613 | E80: 319728.06 | F80: 32735.01 | G80: 190 | H80: 23 | I80: 25 | J80: 4.6 | K80: https://amazon.com/dp/B00UEHHI3G | L80: =HYPERLINK(K80) -> https://amazon.com/dp/B00UEHHI3G
A81: Autel MaxiSYS MS906 PRO Scanner: 2025 MS906PRO V2.0 Same as MS906MAX Up of MS906BT MP900BT MS908S, CAN FD DoIP, 36+ Resets, Bidirectional 3K+ Tests, Full Diagnostic, Auto Scan 2.0, FCA | B81: B086DRGM15 | C81: Tablet | D81: 1473.5327 | E81: 501409.03 | F81: 32417.72 | G81: 322 | H81: 22 | I81: 76 | J81: 4.4 | K81: https://amazon.com/dp/B086DRGM15 | L81: =HYPERLINK(K81) -> https://amazon.com/dp/B086DRGM15
A82: Autel MaxiSys Elite II Pro Scanner: 2025 2-Years Free Update Elite 2 Pro Updated of Ultra MS908S Pro II, Motor TruSpeed Repair, 40 Reset Service w/CAN FD & Do IP, 3000+ Active Test | B82: B00RD6B6MU | C82: Tablet | D82: 2483.5038 | E82: 461182.85 | F82: 32285.55 | G82: 165 | H82: 13 | I82: 73 | J82: 4.4 | K82: https://amazon.com/dp/B00RD6B6MU | L82: =HYPERLINK(K82) -> https://amazon.com/dp/B00RD6B6MU
A83: Autel Scanner MaxiSYS MS908S PRO II: 2025 Automotive Diagnostic Scan Tool As MSUltra MS919 Elite II PRO, US Ver. of MaxiCOM MK908 PRO II, AutoScan 2.0, Active Test 38+ Resets, 8-Core, 4/128G | B83: B088FRCPTB | C83: Tablet | D83: 2013.5194 | E83: 460090.75 | F83: 32216.31 | G83: 212 | H83: 16 | I83: 100 | J83: 4.5 | K83: https://amazon.com/dp/B088FRCPTB | L83: =HYPERLINK(K83) -> https://amazon.com/dp/B088FRCPTB
A84: Autel Scanner MaxiCOM MK808BT PRO w/ MV108S, 2025 2.0 Bidirectional Scan Tool as MX900 MK900 MK900BT, Upgrade of MK808S MX808S MK808Z, 3000+ Active Test, 28+ Service, OE All-Sys Diagnostic, FCA, 11 OS | B84: B07H3M98FL | C84: Tablet | D84: 575.18857 | E84: 434328.32 | F84: 32210.56 | G84: 700 | H84: 56 | I84: 644 | J84: 4.6 | K84: https://amazon.com/dp/B07H3M98FL | L84: =HYPERLINK(K84) -> https://amazon.com/dp/B07H3M98FL
A85: 2025 Autel MaxiSYS Elite II PRO Scanner, 2-Year Free Update ($2590) Elite 2 Pro J2534 Tool as Ultra MS919 MS909, with MV108S, Motor TruSpeed, 40+ Services 3000+ Tests CAN FD/Do IP | B85: B09TT2GQ6P | C85: Tablet | D85: 2474.5738 | E85: 291740.14 | F85: 32169.46 | G85: 109 | H85: 13 | I85: 16 | J85: 4.8 | K85: https://amazon.com/dp/B09TT2GQ6P | L85: =HYPERLINK(K85) -> https://amazon.com/dp/B09TT2GQ6P
A86: Autel Ultra S2, Dianostic Scanner with AI, 2025 New 6-in-1 VCMI2, Upgraded MaxiSYS Ultra, Topology 3.0, EV Tests, WiFi 6, 48+ Services, Motor Truspeed Repair, Multi-Point DVI, ECU Programming | B86: B0F3X8ZWBN | C86: Tablet | D86: 5262.8317 | E86: 337888.32 | F86: 31576.99 | G86: 29 | H86: 6 | I86: 3 | J86: 5 | K86: https://amazon.com/dp/B0F3X8ZWBN | L86: =HYPERLINK(K86) -> https://amazon.com/dp/B0F3X8ZWBN
... A102: Autel MaxiSYS MS908CV II Heavy Duty Truck Scanner, Better MS908CV, Same as MS909CV Diagnostic Scan Tool for Commercial Vehicles, J2534 ECU Programming/Coding, 64 Services, 3000+ Active Tests | B102: B0D6F6JVQ1 | C102: Tablet | D102: 3038.3938 | E102: 192588.45 | F102: 24307.15 | G102: 50 | H102: 8 | I102: 7 | J102: 4.6 | K102: https://amazon.com/dp/B0D6F6JVQ1 | L102: =HYPERLINK(K102) -> https://amazon.com/dp/B0D6F6JVQ1
A103: Autel MaxiSYS MS906 PRO2-TS Scanner: 2025 MS906Pro2-TS Up of MS906Pro-TS MK900TS MP900BT Kit MS908S MS906 PRO,Top TPMS Function& ЁCU Coding, Bidirectional Tool, 36+ Service, Auto Scan2.0, CAN FD&DoIP | B103: B0FN72T1LS | D103: 1734.865 | E103: 277381.41 | F103: 24288.11 | G103: 18 | H103: 14 | K103: https://amazon.com/dp/B0FN72T1LS | L103: =HYPERLINK(K103) -> https://amazon.com/dp/B0FN72T1LS
A104: Autel MaxiSys MS909CV 2025 Top Heavy Duty Truck Scanner for Semi Commercial Cars, Upgrade of MS908CV with Intelligent Scan, 60+ Services, J2534 P.roğrammer Coding, 3000+ Test,Topology 2.0 | B104: B094XRTNPK | C104: Tablet | D104: 4810.134 | E104: 155791.29 | F104: 24050.67 | G104: 30 | H104: 5 | I104: 6 | J104: 4.1 | K104: https://amazon.com/dp/B094XRTNPK | L104: =HYPERLINK(K104) -> https://amazon.com/dp/B094XRTNPK
A105: Autel MaxiSYS MS906 PRO Scanner, 2025 MS906PRO V2.0 Same as MS906 MAX, 3000+ Bidirectional Diagnostic Scan Tool Up of MP900BT MS906BT MS908 MK908, CAN FD DoIP, 36+ Service, Auto Scan 2.0, Active Tests | B105: B09JGL9BXC | C105: Tablet | D105: 1466.7219 | E105: 382548.43 | F105: 23467.55 | G105: 256 | H105: 16 | I105: 58 | J105: 4.7 | K105: https://amazon.com/dp/B09JGL9BXC | L105: =HYPERLINK(K105) -> https://amazon.com/dp/B09JGL9BXC
A106: Autel Scanner MaxiCOM MK900TS, 2025 8IN MK900-TS with DoIP/CAN FD 40+ Service, Up of MK900BT MK900 MK808S-TS TS900, Top TPMS Programming, Bidirectional OBD2 Diagnostic Tool, 3000+ Active Tests, FCA | B106: B09YM97Q9N | C106: Tablet | D106: 863.53462 | E106: 157670.86 | F106: 22451.9 | G106: 132 | H106: 26 | I106: 27 | J106: 4.5 | K106: https://amazon.com/dp/B09YM97Q9N | L106: =HYPERLINK(K106) -> https://amazon.com/dp/B09YM97Q9N
A107: Autel Scanner MaxiPRO MP900 KIT, 11PCS OBD Adapters $200, 2025 DoIP CAN FD Newer of MS906 MP808S MX900 MK900 MK808S, Full Bidirectional as MS906 PRO MP900-BT, 40+ Reset, 3000+ Active Test, FCA | B107: B08PDJ21WS | C107: Tablet | D107: 877.6152 | E107: 113546.57 | F107: 21940.38 | G107: 105 | H107: 25 | I107: 53 | J107: 4.5 | K107: https://amazon.com/dp/B08PDJ21WS | L107: =HYPERLINK(K107) -> https://amazon.com/dp/B08PDJ21WS
A108: Autel Maxisys MS906 Pro-TS 2025, Top Scanner with TPMS Programming Tool, Upgrade of MP900TS, MP900BT, MS906Pro, MS906TS, MS906BT, OBD2 Diagnostic Tool, Auto Scan 2.0, CAN FD/DoIP | B108: B0D1QRKDYD | C108: Tablet | D108: 1548.0079 | E108: 217672.97 | F108: 21672.11 | G108: 126 | H108: 14 | I108: 9 | J108: 5 | K108: https://amazon.com/dp/B0D1QRKDYD | L108: =HYPERLINK(K108) -> https://amazon.com/dp/B0D1QRKDYD
A109: Autel Scanner Maxicom MK908 Pro II 2025, Car Diagnostic Tool As MS908S PRO II Elite 2 Pro MSUltra w/AutoScan 2.0, Up of MS906MAX/MS906 PRO, 3000+ Active Test 38+ Services OS10.0 4/128G | B109: B07MV26KVM | C109: Tablet | D109: 2086.231 | E109: 239742.84 | F109: 20862.31 | G109: 110 | H109: 10 | I109: 67 | J109: 4.4 | K109: https://amazon.com/dp/B07MV26KVM | L109: =HYPERLINK(K109) -> https://amazon.com/dp/B07MV26KVM
A110: 2025 Autel MaxiSYS CV MS908CV II Heavy Duty Truck Scanner, Same as MS909CV Up of MS908CV, J2534 Tool, Semi Truck Full System Diagnostic Tool, Bidirectional Diesel Scan Tool, 3000+ Tests, 64+ Resets | B110: B0CWTM3KVX | C110: Tablet | D110: 2812.1029 | E110: 154627.91 | F110: 19684.72 | G110: 34 | H110: 7 | I110: 15 | J110: 4.8 | K110: https://amazon.com/dp/B0CWTM3KVX | L110: =HYPERLINK(K110) -> https://amazon.com/dp/B0CWTM3KVX
A111: Autel Original OBD2 12+8 Adapter for Chrysler, OBD II Bypass Cable Gateway Protocol, Universal Security Bypass 12 8 Connector for FCA SGW Car, Work for All Scanner MK808 MX808 MX900 MS906 MS908 | B111: B0BJQKK2TJ | C111: Cable/Adapter | D111: 25.988545 | E111: 227494.42 | F111: 19647.34 | G111: 8209 | H111: 756 | I111: 413 | J111: 4.7 | K111: https://amazon.com/dp/B0BJQKK2TJ | L111: =HYPERLINK(K111) -> https://amazon.com/dp/B0BJQKK2TJ
A112: Autel Scanner MaxiCOM MK808BT PRO: 2025 Bidirectional Scan Tool Work as MK900BT, 33FT BT 2.0 Ver. of MK900 MX900 MK808S MaxiCheck MX808S MK808Z, 3K+ Active Tests, 28+ Services, OE Full Sys, OS 11, FCA | B112: B07KXDKWRS | C112: Tablet | D112: 545.61583 | E112: 443544.9 | F112: 19642.17 | G112: 774 | H112: 36 | I112: 595 | J112: 4.6 | K112: https://amazon.com/dp/B07KXDKWRS | L112: =HYPERLINK(K112) -> https://amazon.com/dp/B07KXDKWRS
A113: Autel Scanner MaxiCOM MK908 Pro MS908S PRO II: 2025 J2534 Reprogramming Tool as MaxiSYS MS909 MS919 Elite II PRO Ultra Lite S2, OE Coding, 38+ Resets, All System Scan, 3K+ Active Tests, CANFD & DoIP | B113: B00RFUY6XU | C113: Tablet | D113: 1909.516 | E113: 212309.65 | F113: 19095.16 | G113: 98 | H113: 10 | I113: 172 | J113: 4.2 | K113: https://amazon.com/dp/B00RFUY6XU | L113: =HYPERLINK(K113) -> https://amazon.com/dp/B00RFUY6XU
A114: Autel MaxiSys Elite II Pro Scanner J2534 Reprogramming Tool as Ultra MS908S PRO II Up of MS908S Pro II MK908P 2-Years Free Update Motor TruSpeed Repair CANFD &DoIP 40+ Hot Services 3K+ Active Test | B114: B0FHVC9TMC | D114: 2384.4875 | E114: 218177.3 | F114: 19075.9 | G114: 25 | H114: 8 | I114: 2 | J114: 5 | K114: https://amazon.com/dp/B0FHVC9TMC | L114: =HYPERLINK(K114) -> https://amazon.com/dp/B0FHVC9TMC
A115: Autel MaxiCheck MX900 Scanner, 2025 Bidirectional Diagnostic Scan Tool Same as MK900 MK900BT, 8in Up of MaxiCOM MK808S MX808S MK808BT PRO, CAN FD DoIP, 3K+ Active Tests, 40+ Services, All Systems, FCA | B115: B0BZS52VQD | C115: Tablet | D115: 563.81727 | E115: 207328.27 | F115: 18605.97 | G115: 353 | H115: 33 | I115: 54 | J115: 4.5 | K115: https://amazon.com/dp/B0BZS52VQD | L115: =HYPERLINK(K115) -> https://amazon.com/dp/B0BZS52VQD
A116: Autel MaxiPRO MP900TS Scanner, 2025 8IN MP900-TS Up of MP900-BT MS906 Pro MP900 MS906TS MK900TS, V2.0 DoIP CANFD, Full TPMS as MS906 Pro-TS, 40+ Services, 3000+ Bidirectional Scan Tool, Auto Scan 2.0 | B116: B08K72QDGQ | C116: Tablet | D116: 1143.1894 | E116: 262640.71 | F116: 18291.03 | G116: 217 | H116: 16 | I116: 73 | J116: 4.5 | K116: https://amazon.com/dp/B08K72QDGQ | L116: =HYPERLINK(K116) -> https://amazon.com/dp/B08K72QDGQ
A117: 2025 Autel MaxiSYS Ultra Scanner: Top Auto Tool with 40+ Service, 5-in-1 VCMI, Intelligent Scan, Topology Map, ECU Programming & Coding, Upgraded of MaxiCOM Ultra Lite Elite II Pro MS919 Ultra EV | B117: B08SVXHWK9 | C117: Tablet | D117: 3565.066 | E117: 367289.3 | F117: 17825.33 | G117: 94 | H117: 5 | I117: 31 | J117: 4.3 | K117: https://amazon.com/dp/B08SVXHWK9 | L117: =HYPERLINK(K117) -> https://amazon.com/dp/B08SVXHWK9
A118: Autel MaxiSys MS906 Pro2-TS Scanner Full TPMS Functionality 2.0 Up of MS906 PRO TS MK906 PRO-TS MP900TS MS906PRO MS906MAX OE-Level All Systems Diagnostics & Services Same as MK906S PRO2-TS | B118: B0FPKHZ6ML | D118: 1736.676 | E118: 193706.17 | F118: 17366.76 | G118: 10 | H118: 10 | K118: https://amazon.com/dp/B0FPKHZ6ML | L118: =HYPERLINK(K118) -> https://amazon.com/dp/B0FPKHZ6ML
A119: Autel Scanner MaxiSYS MS908S PRO II 2025, Plus $219 TS501 PRO TPMS Relearn Tool, Bidirectional Diagnostic Scan as Ultra MS919 MS909 Elite 2 Pro, Up of MK908P MS906MAX, 3K+ Active Tests, 38+ Reset | B119: B07NN6J4BH | C119: Tablet | D119: 2151.2712 | E119: 131468.29 | F119: 17210.17 | G119: 52 | H119: 8 | I119: 30 | J119: 4.1 | K119: https://amazon.com/dp/B07NN6J4BH | L119: =HYPERLINK(K119) -> https://amazon.com/dp/B07NN6J4BH
A120: Autel OBD2 Scanner AutoLink AL549(Upgraded Ver. of AL519)Code Reader with AutoVin, Read/Erase DTCs for ABS, Universal Car Battery Test,OBDII Scan with Live Data,Check Engine Fault OBD2 Diagnostic Tool | B120: B0CZ8TZCQS | C120: Handheld | D120: 69.01121 | E120: 189211.59 | F120: 17114.78 | G120: 2197 | H120: 248 | I120: 498 | J120: 4.5 | K120: https://amazon.com/dp/B0CZ8TZCQS | L120: =HYPERLINK(K120) -> https://amazon.com/dp/B0CZ8TZCQS
A121: Autel MaxiPRO MP900-BT Kit Scanner w/ 200 Bucks OBD1 Kit: 2025 DoIP/CAN FD MP900BT Kit, New Model of MK900BT MP900-BT MS906BT, Pro ECU C0ding as MS906 Pro, 3000+ Tests, 40+ Service, OS 11, FCA SGW | B121: B01CQNNBA4 | C121: Tablet | D121: 990.78529 | E121: 157113.28 | F121: 16843.35 | G121: 145 | H121: 17 | I121: 237 | J121: 4.5 | K121: https://amazon.com/dp/B01CQNNBA4 | L121: =HYPERLINK(K121) -> https://amazon.com/dp/B01CQNNBA4
A122: Autel MaxiCOM MK908 II Scanner: 2025 Up of MS906 PRO MS906MAX MP900BT MS906BT MK908, 38+ Services as Elite 2 PRO MK908P II MS908S Pro II, 3K+ Bidirectional Scan Tool, OE All Sys, Auto Scan 2.0, OS 10 | B122: B07PDG5YR9 | C122: Tablet | D122: 1505.1627 | E122: 104754.08 | F122: 16556.79 | G122: 56 | H122: 11 | I122: 35 | J122: 4.8 | K122: https://amazon.com/dp/B07PDG5YR9 | L122: =HYPERLINK(K122) -> https://amazon.com/dp/B07PDG5YR9
A123: Autel MaxiDiag MD906PRO MD906 Pro OBD2 Scanner: 2025 2.0 of MD802Pro MD806 MD808 Pro, BT Wireless Full Systems Diagnostics, 11 Service Oil Reset Bleeding Injector SAS etc, FCA SGW CAN FD, Free Update | B123: B0FHPX5VNF | D123: 277.59203 | E123: 169792.55 | F123: 16377.93 | G123: 120 | H123: 59 | I123: 20 | J123: 4.6 | K123: https://amazon.com/dp/B0FHPX5VNF | L123: =HYPERLINK(K123) -> https://amazon.com/dp/B0FHPX5VNF
A124: Autel MaxiPRO MP900TS Scanner 2025: MP900-TS up of MaxiSYS MS906TS MP900-BT MK900-TS, Top TPMS as MS906 Pro-TS, OE ECU C0.ding, Bidirectional Tests, 40+ Service, 8'' All System OBD2 Tool, CAN FD&DOIP | B124: B073CS2RLP | C124: Tablet | D124: 1089.7967 | E124: 197152.13 | F124: 16346.95 | G124: 148 | H124: 15 | I124: 70 | J124: 4.6 | K124: https://amazon.com/dp/B073CS2RLP | L124: =HYPERLINK(K124) -> https://amazon.com/dp/B073CS2RLP
A125: Autel AutoLink AL519 OBD2 Scanner Enhanced Mode 6 Car Diagnostic Tool Check Engine Code Reader CAN Scan Tool, Advanced Ver. of AL319 | B125: B07PQH6HSQ | C125: Handheld | D125: 60.025097 | E125: 220156.8 | F125: 15546.5 | G125: 3263 | H125: 259 | I125: 2564 | J125: 4.5 | K125: https://amazon.com/dp/B07PQH6HSQ | L125: =HYPERLINK(K125) -> https://amazon.com/dp/B07PQH6HSQ
A126: Autel MaxiVCI V200 VCI200 Wireless Diagnostic Dongle, 2025 VCI 200 OBD2 Connector Adapter, Work with Scanner MaxiSys MS906 PRO MS906MAX MS906 PRO-TS MK906 PRO-TS KM100 BT608 BT609 ITS600 | B126: B0BBFY2848 | C126: Dongle | D126: 220.02686 | E126: 197188.21 | F126: 15401.88 | G126: 872 | H126: 70 | I126: 61 | J126: 4.5 | K126: https://amazon.com/dp/B0BBFY2848 | L126: =HYPERLINK(K126) -> https://amazon.com/dp/B0BBFY2848
A127: Autel MaxiSYS MS906 MAX Scanner, 2025 MS906MAX 2.0 Ver. of MS906 PRO/ MS908S/ MK908 II, Lite of Elite 2 PRO, Top Scan Tool Bidirectional, 3000+ Active Tests, 40+ Resets, CAN FD DoIP Auto Scan2.0 FCA | B127: B09PG3L6K1 | C127: Tablet | D127: 1533.22 | E127: 176923.23 | F127: 15332.2 | G127: 50 | H127: 10 | I127: 10 | J127: 5 | K127: https://amazon.com/dp/B09PG3L6K1 | L127: =HYPERLINK(K127) -> https://amazon.com/dp/B09PG3L6K1
A128: Autel AutoLink AL619 Scanner, 2025 ABS SRS Airbag Warning Light Diagnostic Scan Tool, Up of AL519 ML519 ML619, 10 OBDII Test Modes, DTCs Lookup, Live Data, Turn Off Check Engine Light OBD2 Code Reader | B128: B0925G7QY1 | C128: Handheld | D128: 99.863464 | E128: 194917.32 | F128: 15279.11 | G128: 1833 | H128: 153 | I128: 536 | J128: 4.3 | K128: https://amazon.com/dp/B0925G7QY1 | L128: =HYPERLINK(K128) -> https://amazon.com/dp/B0925G7QY1
A129: Autel MaxiPRO MP900 Scanner, 2025 Newer of MP808BT PRO MP808S MK900 MX900, Function as MP900BT MS906 PRO MS906 MAX, Bidirectional Diagnostic Scan Tool, 3000+ Active Test, 40+ Service, CAN FD &DOIP | B129: B09YM7YPDJ | C129: Tablet | D129: 799.26368 | E129: 180359.26 | F129: 15186.01 | G129: 205 | H129: 19 | I129: 35 | J129: 4.4 | K129: https://amazon.com/dp/B09YM7YPDJ | L129: =HYPERLINK(K129) -> https://amazon.com/dp/B09YM7YPDJ
A130: Autel J2534 MaxiFlash VCI, 2025 J2534 Reprogramming Tool, Pass-Thru ECU Programming Tool, DoIP/CAN FD/D-PDU 4 Channels, Work w/MaxiCOM Ultra Lite MaxiSYS Elite II Pro MS909 MS909EV MS909CV | B130: B0D5MDKFCF | C130: VCI | D130: 1004.2447 | E130: 145985.35 | F130: 15063.67 | G130: 132 | H130: 15 | I130: 66 | J130: 4.5 | K130: https://amazon.com/dp/B0D5MDKFCF | L130: =HYPERLINK(K130) -> https://amazon.com/dp/B0D5MDKFCF
A131: Autel Scanner MaxiSYS Elite II, 2 Years Update (Value $2590), Alternative to Autel Ultra, J2534 ECU Programming & Coding, 38+ Services Bi-Directional Scan Tool | B131: B0C5XB41JF | C131: Tablet | D131: 2146.0157 | E131: 128869.11 | F131: 15022.11 | G131: 49 | H131: 7 | I131: 1 | J131: 5 | K131: https://amazon.com/dp/B0C5XB41JF | L131: =HYPERLINK(K131) -> https://amazon.com/dp/B0C5XB41JF
A132: Autel MaxiSys Ultra S2 AI Scanner, 2025 UltraS2 Top Intelligent Scan Tool, Up of Ultra EV MSUltra, 6-in-1 VCMI2, Multi-Point DVI, Topology 3.0, Motor Truspeed, 48+ Services, EV Tests, 3K+ Active Tests | B132: B0936PQ6Y8 | C132: Tablet | D132: 4963.1767 | E132: 106243.22 | F132: 14889.53 | G132: 5 | H132: 3 | I132: 8 | J132: 5 | K132: https://amazon.com/dp/B0936PQ6Y8 | L132: =HYPERLINK(K132) -> https://amazon.com/dp/B0936PQ6Y8
A133: Autel OBD2 Scanner bidirectional scan Tool: MK808Z 2025 Diagnostic Tool for All Vehicles Upgraded from maxicom MK808S MX808S,All System Diagnose, Active Test,Escaner Automotriz,Work as MX900 MK900BT | B133: B098TDC7FM | C133: Tablet | D133: 389.62105 | E133: 416064.15 | F133: 14805.6 | G133: 890 | H133: 38 | I133: 358 | J133: 4.4 | K133: https://amazon.com/dp/B098TDC7FM | L133: =HYPERLINK(K133) -> https://amazon.com/dp/B098TDC7FM
A134: Autel MaxiCOM MK808S-TS OBD2 Scanner: 2025 Updated of MK808BT PRO, MK808TS MX808TS TS601 with Bidirectional Test, 32 Service 150 Makes, TPMS Pr0gramming Relearn Retrofit, All-System Scan, OS 11 4+64G | B134: B07GZBCH7K | C134: Tablet | D134: 702.81238 | E134: 295084.46 | F134: 14759.06 | G134: 410 | H134: 21 | I134: 622 | J134: 4.5 | K134: https://amazon.com/dp/B07GZBCH7K | L134: =HYPERLINK(K134) -> https://amazon.com/dp/B07GZBCH7K
A135: Autel MaxiSys Elite II Pro Scanner, 2025 2 Years Free Update Elite 2 Pro, J2534 Reprogramming Tool as Ultra MS909 MS919 Up of MS908SP II MK908P II, Motor TruSpeed, 45+ Resets, CAN FD DoIP, 3K+ Test | B135: B01EHL39ZU | C135: Tablet | D135: 2398.975 | E135: 262343.98 | F135: 14393.85 | G135: 105 | H135: 6 | I135: 157 | J135: 4.2 | K135: https://amazon.com/dp/B01EHL39ZU | L135: =HYPERLINK(K135) -> https://amazon.com/dp/B01EHL39ZU
A136: Autel MS906 MAX Bi-Directional Scanner: 2025 MS906MAX Updated of MS906 Pro MP900BT with ECU C0ding, DoIP, CANFD, FCA SGW AutAuth, All System Scan, 40+ Service 3000+ Active Tests as MS908S PRO II | B136: B0DXKBMLVB | C136: Tablet | D136: 1565.4389 | E136: 135407.66 | F136: 14088.95 | G136: 38 | H136: 9 | I136: 9 | J136: 4.7 | K136: https://amazon.com/dp/B0DXKBMLVB | L136: =HYPERLINK(K136) -> https://amazon.com/dp/B0DXKBMLVB
A137: 2025 Autel MaxiSYS Ultra S2 AI Scanner, Top Intelligent Up of MSUltra UltraEV MS919 S2, 6IN1 VCMI2 [Valued 3000$] Topology 3.0 PID Analysis Multi-Point DVI, Motor TruSpeed EV Test 48 Reset | B137: B0F37T6R92 | D137: 6937.9 | E137: 210092.69 | F137: 13875.8 | G137: 20 | H137: 2 | I137: 1 | J137: 5 | K137: https://amazon.com/dp/B0F37T6R92 | L137: =HYPERLINK(K137) -> https://amazon.com/dp/B0F37T6R92
A138: Autel Scanner Bidirectional Diagnostic Scan Tool, 2025 V2.0 All System Diagnose w/ 40+ Service, 3000+ Active Test, OS 10.0, 4G&128G 10.1'' 1920x1200 | B138: B08PDMD8ZT | C138: Tablet | D138: 2733.158 | E138: 167370.76 | F138: 13665.79 | G138: 50 | H138: 5 | I138: 7 | J138: 4.8 | K138: https://amazon.com/dp/B08PDMD8ZT | L138: =HYPERLINK(K138) -> https://amazon.com/dp/B08PDMD8ZT
A139: Autel MaxiSys MS909 S2 Scanner, 2025 Same as Ultra S2 Up of MS Ultra MS909, Top Intelligen Scan Diagnostic with AI, Topology 3.0, Enhanced PID Analysis, Motor Truspeed, 48+ Service, ECU Program | B139: B0FKMK8YNR | D139: 3401.695 | E139: 146914.25 | F139: 13606.78 | G139: 6 | H139: 4 | I139: 1 | J139: 5 | K139: https://amazon.com/dp/B0FKMK8YNR | L139: =HYPERLINK(K139) -> https://amazon.com/dp/B0FKMK8YNR
A140: Autel MaxiTPMS ITS600 (E) TPMS Programming Tool, 2025 Complete TPMS Functions as ITS600 Pro Up of TS508WF/ MK808S-TS/ TS900, Relearn/Activate Sensors, Oil Reset EPB BMS SAS, Lifetime Free Updates | B140: B09QX9B31K | C140: Handheld | D140: 495.56741 | E140: 77083.349 | F140: 13380.32 | G140: 105 | H140: 27 | I140: 11 | J140: 4.8 | K140: https://amazon.com/dp/B09QX9B31K | L140: =HYPERLINK(K140) -> https://amazon.com/dp/B09QX9B31K
A141: Autel Maxi.I-M Diagnostic Tool, 2025 Car Scan Tool Advanced as Elite II Pro, 40+ Service, 3000+ Active Test, OE Full Diagnostic, Upgraded Hardware Up of I-M6O8 PRO/I-M5O8S | B141: B0DJ1DKRZQ | C141: Tablet | D141: 3283.035 | E141: 129179.53 | F141: 13132.14 | G141: 38 | H141: 4 | I141: 4 | J141: 5 | K141: https://amazon.com/dp/B0DJ1DKRZQ | L141: =HYPERLINK(K141) -> https://amazon.com/dp/B0DJ1DKRZQ
A142: Autel MaxiSYS MS906pro TS Autel Scanner Upgrade of MS906 Pro/ MS906TS/ MK908 Top Car Scanner CAN FD/Do IP 36+ Services All System Diagnostic ECU Coding 3000+ Test FCA OS 10 | B142: B0BG2M2ZFD | C142: Tablet | D142: 1456.8856 | E142: 189005.22 | F142: 13111.97 | G142: 107 | H142: 9 | I142: 15 | J142: 4.9 | K142: https://amazon.com/dp/B0BG2M2ZFD | L142: =HYPERLINK(K142) -> https://amazon.com/dp/B0BG2M2ZFD
A143: Autel AL519 OBD2 Scanner, 2025 Newer Professional Mechanic OBDII & CAN Car Diagnostic Code Reader Tool for Check Engine Light, One-Click Smog Check, DTCs Lookup, Upgraded Ver. of AL319/ MS309 | B143: B07CJHWHNX | C143: Handheld | D143: 60.124128 | E143: 166449.6 | F143: 13107.06 | G143: 2412 | H143: 218 | I143: 1050 | J143: 4.5 | K143: https://amazon.com/dp/B07CJHWHNX | L143: =HYPERLINK(K143) -> https://amazon.com/dp/B07CJHWHNX
A144: Autel MaxiSys Ultra Autel Scanner: 2025 Top Automotive Intelligent Diagnostic Scan Tool with 5-in-1 VCMI, J2534 ECU Programming, 40+ Services, Topology Map, Upgraded of MS908S Pro Elite/MS909/MS919 | B144: B09PNBLDM9 | C144: Tablet | D144: 4309.43 | E144: 86524.982 | F144: 12928.29 | G144: 15 | H144: 3 | I144: 3 | J144: 5 | K144: https://amazon.com/dp/B09PNBLDM9 | L144: =HYPERLINK(K144) -> https://amazon.com/dp/B09PNBLDM9
A145: Autel MaxiCom Ultra Lite Scanner, 2 Years Free Updates, Same as MaxiSys Ultra, 2025 Up of MS919 MS909 MS906 Elite II Pro, Topology 2.0, Motor TruSpeed Repair, 40+ Service, Repair Tips, FCA SGW, | B145: B0FJLZ19KF | D145: 2550.628 | E145: 156461.72 | F145: 12753.14 | G145: 14 | H145: 5 | I145: 7 | J145: 5 | K145: https://amazon.com/dp/B0FJLZ19KF | L145: =HYPERLINK(K145) -> https://amazon.com/dp/B0FJLZ19KF
A146: Autel MaxiSys MS906 Pro-TS Scanner, 2025 MS906PRO-TS Scan Tool Upgrade of MP900TS MS906MAX MS906 PRO MP900BT, Top TPMS Functions, 3000+ Active Tests, 36+ Services, CAN FD & DoIP, Auto Scan 2.0 | B146: B071RLXN2W | C146: Tablet | D146: 1584.6837 | E146: 85211.38 | F146: 12677.47 | G146: 47 | H146: 8 | I146: 22 | J146: 4.6 | K146: https://amazon.com/dp/B071RLXN2W | L146: =HYPERLINK(K146) -> https://amazon.com/dp/B071RLXN2W
A147: Autel MaxiCom Ultra Lite Scanner: 2025 2-Years Free Updates, Topology Mapping, Motor TruSpeed Repair, ECU Programming, 40 Service, Repair Tips, Updated of MS919/ Elite II Pro, Same as MaxiSys MSUltra | B147: B0172DD22U | C147: Tablet | D147: 2520.894 | E147: 129225.93 | F147: 12604.47 | G147: 32 | H147: 5 | I147: 7 | J147: 5 | K147: https://amazon.com/dp/B0172DD22U | L147: =HYPERLINK(K147) -> https://amazon.com/dp/B0172DD22U
A148: Autel MaxiPRO MP808BT PRO Scanner, 2025 Bidirectional Scan Tool with 2-Year Update, Pro as MS906 PRO MS906 MAX MP900BT, 30+ Service, 3000+ Test, Level-up of MK900BT MK900 MX900 MK808S, FCA SGW, OS 11 | B148: B09F3MZZ3F | C148: Tablet | D148: 699.51333 | E148: 151660.42 | F148: 12591.24 | G148: 189 | H148: 18 | I148: 85 | J148: 4.6 | K148: https://amazon.com/dp/B09F3MZZ3F | L148: =HYPERLINK(K148) -> https://amazon.com/dp/B09F3MZZ3F
A149: Autel MaxiSys MS908CV II Top CV Scanner, 2025 V2.0 of MS908CV Heavy Duty Truck Diagnostic Tool with J2534, Lite of MS909CV, Bidirectional 3000+ Test, 64 Services, Auto Scan 2.0 10 OS 4/128GB | B149: B09FLP47CD | C149: Tablet | D149: 3140.5375 | E149: 231994.99 | F149: 12562.15 | G149: 76 | H149: 4 | I149: 35 | J149: 4.8 | K149: https://amazon.com/dp/B09FLP47CD | L149: =HYPERLINK(K149) -> https://amazon.com/dp/B09FLP47CD
A150: Autel MaxiSYS MS906MAX Scanner, 2025 MS906 MAX 10.1" 2.0 Ver.of MS906 PRO MP900BT MS906BT MS908S MK908 MK900BT, Top 3K+ Bidirectional Diagnostic Tool, 40+ Resets, All Sys, CAN FD DoIP | B150: B0DXFPD42C | C150: Tablet | D150: 1522.9637 | E150: 147671.03 | F150: 12183.71 | G150: 44 | H150: 8 | I150: 25 | J150: 4.6 | K150: https://amazon.com/dp/B0DXFPD42C | L150: =HYPERLINK(K150) -> https://amazon.com/dp/B0DXFPD42C
A151: Autel MaxiSYS MS906 PRO TS Scanner, 2025 MS906 Pro-TS Up of MS906 MAX MS906Pro MP900TS MS906TS MP900BT, OE TPMS, Bidirectional Scan Tool, 3000+ Test, 36+ Service, DOIP&CAN FD, FCA, VAG | B151: B008PTN992 | C151: Handheld | D151: 1519.2025 | E151: 135630.36 | F151: 12153.62 | G151: 43 | H151: 8 | I151: 120 | J151: 4.5 | K151: https://amazon.com/dp/B008PTN992 | L151: =HYPERLINK(K151) -> https://amazon.com/dp/B008PTN992
A152: Autel MaxiCheck PRO Auto Bleed Scan Tool for ABS Brake Bleeding, OBD2 ABS SRS Diagnostic Scanner, Oil Reset, BMS, EPB, Airbag, SAS Services for Specific Vehicles Up to 2015, Lifetime Free Updates | B152: B075ZLVXHY | C152: Handheld | D152: 197.95217 | E152: 135648.25 | F152: 11877.13 | G152: 572 | H152: 60 | I152: 495 | J152: 4.4 | K152: https://amazon.com/dp/B075ZLVXHY | L152: =HYPERLINK(K152) -> https://amazon.com/dp/B075ZLVXHY
A153: Autel MaxiSys MS906MAX OBD2 Scanner, Way Better Than MS906 Pro, 2025 MS906 MAX Up of MS906S MS906BT MS908, E-C*U Coding, 3000+ Active Test, 40+ Service, All System Diagnosis, CAN FD/DoIP | B153: B0DRG4YXXJ | C153: Tablet | D153: 1439.505 | E153: 136327.32 | F153: 11516.04 | G153: 47 | H153: 8 | I153: 8 | J153: 4.7 | K153: https://amazon.com/dp/B0DRG4YXXJ | L153: =HYPERLINK(K153) -> https://amazon.com/dp/B0DRG4YXXJ
A154: Autel MaxiCOM MK808Z OBD2 Scanner, 2025 Bidirectional Scan Tool Same As MK808S MX808S, Work as MaxiCheck MX900 MK900BT, Active Test, 28+ Service, All System Diagnose, Injector Coding, FCA Autoauth | B154: B094VZN94S | C154: Tablet | D154: 418.92704 | E154: 170788.48 | F154: 11311.03 | G154: 178 | H154: 27 | I154: 53 | J154: 4.6 | K154: https://amazon.com/dp/B094VZN94S | L154: =HYPERLINK(K154) -> https://amazon.com/dp/B094VZN94S
A155: Autel MaxiSYS Ultra S2 Top AI Intelligent Scanner, 2025 UltraS2 Upgrade of MSUltra MS919 Scan Tool, 6in1 VCMI2, 3.0 Topology, Multi-Point DVI, Motor Truspeed, EV Test, 48 Service, OS 13.0 | B155: B0F37T2WCZ | C155: Tablet | D155: 5499.625 | E155: 158990.46 | F155: 10999.25 | G155: 13 | H155: 2 | I155: 8 | J155: 4.8 | K155: https://amazon.com/dp/B0F37T2WCZ | L155: =HYPERLINK(K155) -> https://amazon.com/dp/B0F37T2WCZ
A156: Autel AL539B OBD2 Scanner, 3-in-1 Code Reader Battery Tester Avometer for 12 Volts Batteries, Full OBDII Diagnosis and Circuit Starting & Charging Systems Test, All Enhanced Ver. of AL519 AL539 | B156: B079GXRV1M | C156: Handheld | D156: 89.916723 | E156: 157897.72 | F156: 10700.09 | G156: 1689 | H156: 119 | I156: 1420 | J156: 4.6 | K156: https://amazon.com/dp/B079GXRV1M | L156: =HYPERLINK(K156) -> https://amazon.com/dp/B079GXRV1M
A157: 2025 Autel MaxiCOM Ultra Lite Intelligent Scanner, 2 Years Free Update, Up of MS919 Elite II Pro Same as MaxiSys Ultra, Motor TruSpeed, Topology 2.0, 40+ Service, 3000+ Active Test, FCA SGW | B157: B09WYDCHGM | C157: Tablet | D157: 2667.315 | E157: 265204.19 | F157: 10669.26 | G157: 87 | H157: 4 | I157: 26 | J157: 5 | K157: https://amazon.com/dp/B09WYDCHGM | L157: =HYPERLINK(K157) -> https://amazon.com/dp/B09WYDCHGM
A158: Autel MaxiCheck MX900 OBD2 Scanner, Same as MaxiCOM MK900 MK900BT, Upgrade of MK808 MX808, All System Diagnostic Scan Tool for Cars, 40+ Services, 3000+ Active Tests, CAN FD/DoIP, FCA | B158: B0C65KF99Q | C158: Tablet | D158: 532.5935 | E158: 269008.74 | F158: 10651.87 | G158: 500 | H158: 20 | I158: 129 | J158: 4.5 | K158: https://amazon.com/dp/B0C65KF99Q | L158: =HYPERLINK(K158) -> https://amazon.com/dp/B0C65KF99Q
A159: Autel MaxiDiag MD909 PRO All-Systems Diagnostic Tool - Up of MD808PRO MD808 MD906 MD806 Scanner, 11 Services, CAN FD/DoIP Support, 1996+ US/Asian/European Vehicles, FCA AutoAuth, Lifetime Free Updates | B159: B0FFH14CPB | D159: 336.88194 | E159: 124144.72 | F159: 10443.34 | G159: 110 | H159: 31 | I159: 9 | J159: 4 | K159: https://amazon.com/dp/B0FFH14CPB | L159: =HYPERLINK(K159) -> https://amazon.com/dp/B0FFH14CPB
A160: Autel MaxiSYS Ultra Scanner, 2025 MSUltra Top Intelligent Scan Tool, Motor TruSpeed, Topology 2.0, [$2000] 5in1 VCMI J2534 Built-in, Up of MS919 MS909 Ultra Lite, 40+ Services 3000+ Tests 12/ 256GB | B160: B08P47HP15 | C160: Tablet | D160: 3450.35 | E160: 337561.39 | F160: 10351.05 | G160: 89 | H160: 3 | I160: 68 | J160: 4.6 | K160: https://amazon.com/dp/B08P47HP15 | L160: =HYPERLINK(K160) -> https://amazon.com/dp/B08P47HP15
A161: Autel Scanner MAXIDIAG MD600CV Heavy Duty Truck Scanner D-P-F Regen Full System Diesel Diagnostic Scan Tool Wireless Android Touchscreen Tablet for Truck Light Medium and Heavy Duty Truck Vehicle | B161: B0D97BL8PJ | C161: Handheld | D161: 978.995 | E161: 76972.117 | F161: 9789.95 | G161: 70 | H161: 10 | I161: 7 | J161: 4.8 | K161: https://amazon.com/dp/B0D97BL8PJ | L161: =HYPERLINK(K161) -> https://amazon.com/dp/B0D97BL8PJ
...

Sheet Foxwell
A1: #VALUE!
B7: Avg Price | C7: Avg Price MoM | D7: Avg Price YoY | E7: Quantity/Mo | F7: Qty by % | G7: Qty MoM | H7: Qty YoY | I7: Revenue/Mo | J7: Revenue by % | L7: Revenue MoM | M7: Revenue YoY
A8: Tablet $800+ | B8: 855.96158 | C8: -0.036415689 | D8: -0.079335738 | E8: 38 | F8: 0.0025940337 | G8: -0.095238095 | H8: 0.65217391 | I8: 32526.54 | J8: 0.018359776 | K8: -0.12818562 | L8: -0.12818562 | M8: 0.52109748
A9: Tablet $400-$800 | B9: 539.07685 | C9: 0.023554873 | D9: 0.025705767 | E9: 276 | F9: 0.018840877 | G9: -0.051546392 | H9: -0.22033898 | I9: 148785.21 | J9: 0.083982592 | K9: -0.029205688 | L9: -0.029205688 | M9: -0.2002972
A10: Tablet $400- | B10: 191.86211 | C10: -0.057409781 | D10: -0.069300025 | E10: 2973 | F10: 0.20294901 | G10: 0.049788136 | H10: -0.063916877 | I10: 570406.05 | J10: 0.32196869 | K10: -0.010479971 | L10: -0.010479971 | M10: -0.12878746
A11: Total Tablet | B11: 228.69419 | C11: -0.056322602 | D11: -0.057541937 | E11: 3287 | F11: 0.22438392 | G11: 0.038546603 | H11: -0.07486631 | I11: 751717.8 | J11: 0.42431106 | K11: -0.019947043 | L11: -0.019947043 | M11: -0.12810029
A12: Handheld $75+ | B12: 147.28282 | C12: -0.042181138 | D12: 0.0131249 | E12: 2703 | F12: 0.18451771 | G12: 0.028147585 | H12: 0.0074543422 | I12: 398105.47 | J12: 0.22471272 | K12: -0.01522085 | L12: -0.01522085 | M12: 0.02067708
A13: Handheld $75- | B13: 59.139208 | C13: -0.052772368 | D13: -0.025645834 | E13: 7921 | F13: 0.5407195 | G13: 0.29639935 | H13: 0.15114082 | I13: 468441.67 | J13: 0.26441436 | K13: 0.22798528 | L13: 0.22798528 | M13: 0.12161886
A14: Total Handheld | B14: 81.565055 | C14: -0.092822362 | D14: -0.034171852 | E14: 10624 | F14: 0.72523722 | G14: 0.21569974 | H14: 0.11083229 | I14: 866547.14 | J14: 0.48912708 | K14: 0.10285562 | L14: 0.10285562 | M14: 0.072873092
A15: Total Other Tools | B15: 15.154308 | C15: -0.015541252 | D15: -0.10191068 | E15: 318 | F15: 0.021707966 | G15: -0.086206897 | H15: -0.49842271 | I15: 4819.07 | J15: 0.0027201493 | K15: -0.10040839 | L15: -0.10040839 | M15: -0.5495388
A16: Total | B16: 114.06873 | C16: -0.10303204 | D16: -0.066637918 | E16: 14229 | F16: 0.9713291 | G16: 0.16136141 | H16: 0.034761108 | I16: 1623084 | J16: 0.91615828 | K16: 0.041703975 | L16: 0.041703975 | M16: -0.034193217
A48: Rank by Revenue
A49: Product Name | B49: ASIN | C49: Type | D49: Avg Price | E49: Estimated 12mo Revenue | F49: Monthly Rev | G49: Estimated 12mo Units | H49: Monthly Units | I49: # of Reviews | J49: Tool Rating | K49: Column1 | L49: Link
A50: FOXWELL NT301 OBD2 Scanner Live Data Professional Mechanic OBDII Diagnostic Code Reader Tool for Check Engine Light | B50: B00UJV3E12 | C50: Handheld | D50: 64.359672 | E50: 5058407.4 | F50: 410035.47 | G50: 59170 | H50: 6371 | I50: 29066 | J50: 4.5 | K50: https://amazon.com/dp/B00UJV3E12 | L50: =HYPERLINK(K50) -> https://amazon.com/dp/B00UJV3E12
A51: FOXWELL Car Scanner NT604 Elite OBD2 Scanner ABS SRS Transmission, Check Engine Code Reader for Cars and Trucks, Diagnostic Scan Tool with SRS Airbag, Automotive Diagnostic Tool with Live Data | B51: B08PFJMTY3 | C51: Tablet | D51: 158.82678 | E51: 3070023.3 | F51: 214416.15 | G51: 17761 | H51: 1350 | I51: 4495 | J51: 4.3 | K51: https://amazon.com/dp/B08PFJMTY3 | L51: =HYPERLINK(K51) -> https://amazon.com/dp/B08PFJMTY3
A52: FOXWELL NT510 Elite Scan Tool fit for BMW Scanner Full Diagnostic Tool OBD2 Scanner, All System Bi-Directional Control Code Reader with All Reset Services, Battery Registration Tool fit for BMW Mini | B52: B019QCG5RE | C52: Handheld | D52: 190.13846 | E52: 1228175 | F52: 112181.69 | G52: 5481 | H52: 590 | I52: 3066 | J52: 4.3 | K52: https://amazon.com/dp/B019QCG5RE | L52: =HYPERLINK(K52) -> https://amazon.com/dp/B019QCG5RE
A53: Upgrade of NT604 OBD2 Scanner, FOXWELL NT614 Elite 4 Systems Diagnostic Scanner, 5 Resets ABS Bleeding, Oil, EPB, SAS, Throttle Relearn Code Reader, WiFi Update, AutoVIN, Live Data Automotive Tool | B53: B08DCNDFVK | C53: Tablet | D53: 169.66096 | E53: 1168174.3 | F53: 109600.98 | G53: 5356 | H53: 646 | I53: 545 | J53: 4.3 | K53: https://amazon.com/dp/B08DCNDFVK | L53: =HYPERLINK(K53) -> https://amazon.com/dp/B08DCNDFVK
A54: FOXWELL HD500 Heavy Duty Truck Scanner with DPF Regen/Injector Cutoff/Limit Setting, Full System Diesel Diagnostic Scan Tool for Cummins, Detroit, Caterpillar, Paccar, Hino & More Pickup Semi Trucks | B54: B0D7M4Q46L | C54: Tablet | D54: 565.39727 | E54: 1189129.8 | F54: 99509.92 | G54: 1938 | H54: 176 | I54: 125 | J54: 4 | K54: https://amazon.com/dp/B0D7M4Q46L | L54: =HYPERLINK(K54) -> https://amazon.com/dp/B0D7M4Q46L
A55: Upgraded of NT301, FOXWELL NT301 Plus 2-in-1 OBD2 Scanner Battery Tester, Professional Check Engine Code Reader Car Diagnostic Tool, 12V Cranking Charging Analyzer for 1996+ Newer Vehicle | B55: B08JGK8PPM | C55: Handheld | D55: 93.082631 | E55: 1330612.8 | F55: 87032.26 | G55: 13083 | H55: 935 | I55: 2485 | J55: 4.5 | K55: https://amazon.com/dp/B08JGK8PPM | L55: =HYPERLINK(K55) -> https://amazon.com/dp/B08JGK8PPM
A56: FOXWELL NT201 OBD2 Scanner Code Reader for Cars and Trucks - Reset Check Engine Light, Read and Clear Fault Codes, Live Data Diagnostic Tool for All Cars Since 1996 | B56: B01N6RKE29 | C56: Handheld | D56: 37.681419 | E56: 691969.73 | F56: 58406.2 | G56: 14429 | H56: 1550 | I56: 9808 | J56: 4.5 | K56: https://amazon.com/dp/B01N6RKE29 | L56: =HYPERLINK(K56) -> https://amazon.com/dp/B01N6RKE29
A57: FOXWELL NT630 Plus OBD2 Scanner with ABS and SRS, 2025 ABS Auto Bleed Scan Tool Brake SRS Scanner Live Data, Car Code Reader Diagnostic Tool Bidirectional Scanner with SAS Oil Light | B57: B07CSMJJK9 | C57: Handheld | D57: 136.86216 | E57: 765072.59 | F57: 56934.66 | G57: 4664 | H57: 416 | I57: 3924 | J57: 4.2 | K57: https://amazon.com/dp/B07CSMJJK9 | L57: =HYPERLINK(K57) -> https://amazon.com/dp/B07CSMJJK9
A58: FOXWELL HD500 Heavy Duty Truck Scanner, Diesel Scaner Diagnostic Tool with DPF Regeneration/Injector Cutoff, fit for Cummins, Detroit, Caterpillar, Paccar, Hino, Lifetime Free Update, Orange | B58: B01FDKGEOC | D58: 552.49146 | E58: 531139.53 | F58: 56906.62 | G58: 286 | H58: 103 | I58: 125 | J58: 4 | K58: https://amazon.com/dp/B01FDKGEOC | L58: =HYPERLINK(K58) -> https://amazon.com/dp/B01FDKGEOC
A59: FOXWELL OBD2 Scanner Diagnostic Tool NT726, All System Bidirectional Scan Tool, Code Reader for Cars and Trucks with 12 Resets, ABS Bleeding/Oil/EPB/SAS/D-PF/TPMS/Injector Coding/Throttle/BMS..., FCA | B59: B0F3XRK4P9 | D59: 344.05717 | E59: 596407.34 | F59: 54705.09 | G59: 681 | H59: 159 | I59: 54 | J59: 4.4 | K59: https://amazon.com/dp/B0F3XRK4P9 | L59: =HYPERLINK(K59) -> https://amazon.com/dp/B0F3XRK4P9
A60: FOXWELL NT624 Elite OBD2 Scanner Upgraded from NT614Elite & NT604Elite Code Reader, All-System OBD2 Scan Tool, 8 Advanced Reset Functions, AutoVIN, Live Data, Lifetime WiFi Free Updates | B60: B07X9JQSGZ | C60: Tablet | D60: 255.19321 | E60: 868445.62 | F60: 46955.55 | G60: 3058 | H60: 184 | I60: 2269 | J60: 4.2 | K60: https://amazon.com/dp/B07X9JQSGZ | L60: =HYPERLINK(K60) -> https://amazon.com/dp/B07X9JQSGZ
A61: FOXWELL OBD2 Scanner NT716 Bidirectional Scan Tool, ABS SRS Transmission Engine, 9 Resets, Car Diagnostic Scanner with ABS Bleeding/SAS/Oil Light/EPB/BMS/DPF/Throttle Relearn/Injector, Black | B61: B015COS1EK | C61: Tablet | D61: 271.61913 | E61: 507004.69 | F61: 46718.49 | G61: 1340 | H61: 172 | I61: 116 | J61: 4.3 | K61: https://amazon.com/dp/B015COS1EK | L61: =HYPERLINK(K61) -> https://amazon.com/dp/B015COS1EK
A62: FOXWELL NT510 Elite fit for Honda Acura OBD2 Scanner, Bidirectional Full System Engine ABS TCM SRS Diagnostic Scan Tool, All Reset Crankshaft Relearn Oil EPB TPS ABS Bleeding, Code Reader, Free Update | B62: B08B5RMFBG | C62: Handheld | D62: 190.01835 | E62: 371884.87 | F62: 36863.56 | G62: 1775 | H62: 194 | I62: 440 | J62: 4.2 | K62: https://amazon.com/dp/B08B5RMFBG | L62: =HYPERLINK(K62) -> https://amazon.com/dp/B08B5RMFBG
A63: FOXWELL NT1009 All-System Bi-Directional Scan Tool with All Reset Services, Topology Mapping, V.A.G Guide & FCA SGW Support, CAN-FD DoIP Diagnostic Scanner for All Cars, 3-Year Free Updates | B63: B0D7Z2QF71 | C63: Tablet | D63: 855.96158 | E63: 265161.21 | F63: 32526.54 | G63: 235 | H63: 38 | I63: 265 | J63: 4.3 | K63: https://amazon.com/dp/B0D7Z2QF71 | L63: =HYPERLINK(K63) -> https://amazon.com/dp/B0D7Z2QF71
A64: FOXWELL NT710 Scan Tool fit for BMW, Full-System Diagnostic Tool with Bi-Directional Control, All Reset Services, Battery Registration & ECU Coding fit for BMW/Mini/RR, Lifetime Free Update | B64: B0BG6SRKWK | C64: Tablet | D64: 328.145 | E64: 358003.33 | F64: 32158.21 | G64: 1038 | H64: 98 | I64: 224 | J64: 4 | K64: https://amazon.com/dp/B0BG6SRKWK | L64: =HYPERLINK(K64) -> https://amazon.com/dp/B0BG6SRKWK
A65: 2025 FOXWELL Scanner NT809BT Bidirectional Scan Tool, All System OBD2 Scanner Diagnostic Tool, Car Code Reader with 30 Resets, Car Diagnostic Scanner for All cars, Wireless Automotive Diagnostic Tools | B65: B0DPZVGXS3 | C65: Tablet | D65: 459.71424 | E65: 316788.7 | F65: 30341.14 | G65: 432 | H65: 66 | I65: 197 | J65: 4.1 | K65: https://amazon.com/dp/B0DPZVGXS3 | L65: =HYPERLINK(K65) -> https://amazon.com/dp/B0DPZVGXS3
A66: Upgraded from NT630 Plus, 2025 FOXWELL NT630 Pro 2-in-1 ABS SRS OBD2 Scanner & Battery Tester, Car Scan Tool with 12V Battery Load Analyzer, ABS Bleed, BMS/Oil/SAS/EPB Reset, Live Data, Active Test | B66: B0DDQ6MX9M | C66: Handheld | D66: 200.00196 | E66: 260447.4 | F66: 29600.29 | G66: 1227 | H66: 148 | I66: 109 | J66: 4.4 | K66: https://amazon.com/dp/B0DDQ6MX9M | L66: =HYPERLINK(K66) -> https://amazon.com/dp/B0DDQ6MX9M
A67: FOXWELL OBD2 Scanner NT604E, 4 System Diagnostic Scanner for All Vehicles, ABS Scanner, Airbag Scanner, Check Engine Code Reader for Cars and Trucks, Transmission Car Scanner Diagnostic Tool, AutoVIN | B67: B096Y2B8LP | C67: Tablet | D67: 158.42728 | E67: 687069.85 | F67: 27407.92 | G67: 4144 | H67: 173 | I67: 464 | J67: 4.3 | K67: https://amazon.com/dp/B096Y2B8LP | L67: =HYPERLINK(K67) -> https://amazon.com/dp/B096Y2B8LP
A68: FOXWELL NT614 Elite OBD2 Scanner 4 System Code Reader Scan Engine ABS SRS Transmission, 5 Resets Oil/EPB/ABS Bleeding/SAS/Throttle Live Data, Auto VIN, WiFi Updates Car Diagnostic Tool for DIY & Pros | B68: B085TG89H4 | C68: Tablet | D68: 190.20606 | E68: 518926.19 | F68: 27009.26 | G68: 2574 | H68: 142 | I68: 1201 | J68: 4.3 | K68: https://amazon.com/dp/B085TG89H4 | L68: =HYPERLINK(K68) -> https://amazon.com/dp/B085TG89H4
A69: FOXWELL NT510 Pro fit for BMW OBD2 Scanner with 12V Battery Tester, Full System Diagnostic Bi-Directional Control Scanner, All Reset Services with Battery Registration Scan Tool fit for BMW/Mini/RR | B69: B0FRD79DJT | D69: 231.74154 | E69: 274144.21 | F69: 24101.12 | G69: 125 | H69: 104 | I69: 24 | J69: 4.9 | K69: https://amazon.com/dp/B0FRD79DJT | L69: =HYPERLINK(K69) -> https://amazon.com/dp/B0FRD79DJT
A70: FOXWELL NT510 Elite fit for GM OBD2 Scanner, Bi-Directional All System Engine ABS SRS Diagnostic Scan Tool Code Reader for Chevrolet Cadillac GMC, All Reset Oil EPB TPS ABS Bleeding Crankshaft Relearn | B70: B014CT4M3K | C70: Handheld | D70: 189.23533 | E70: 359652.37 | F70: 19869.71 | G70: 1818 | H70: 105 | I70: 548 | J70: 4 | K70: https://amazon.com/dp/B014CT4M3K | L70: =HYPERLINK(K70) -> https://amazon.com/dp/B014CT4M3K
A71: FOXWELL NT630 Plus OBD2 Scanner with ABS and SRS, ABS Auto Bleed Scan Tool, 2025 Brake Code Reader with Live Data, Bidirectional Control & SAS Oil Light EPB Reset Diagnostic Tool | B71: B08GXDMC7N | C71: Handheld | D71: 150.50305 | E71: 231637.87 | F71: 19264.39 | G71: 1333 | H71: 128 | I71: 481 | J71: 4.1 | K71: https://amazon.com/dp/B08GXDMC7N | L71: =HYPERLINK(K71) -> https://amazon.com/dp/B08GXDMC7N
A72: FOXWELL NT510 Elite for Porsche OBD2 Scanner, All System Bi-Directional Control Code Reader with All Reset Services Oil Reset ABS Bleeding Diagnostic Scan Tool for Porsche, Lifetime Free Update | B72: B07Z5JS7B9 | C72: Handheld | D72: 189.34908 | E72: 201602.82 | F72: 18556.21 | G72: 875 | H72: 98 | I72: 316 | J72: 3.8 | K72: https://amazon.com/dp/B07Z5JS7B9 | L72: =HYPERLINK(K72) -> https://amazon.com/dp/B07Z5JS7B9
A73: FOXWELL NT710 fit for Mercedes-Benz OBD2 Scanner, Full System Diagnostic Scan Tool, Bidirectional Control, All Free Resets Air Suspension/ABS Bleeding/Oil/SRS/EPB, Code Reader, Auto VIN, WiFi Update | B73: B0CHYGP6YB | C73: Tablet | D73: 331.68457 | E73: 228820.85 | F73: 15257.49 | G73: 667 | H73: 46 | I73: 99 | J73: 4.1 | K73: https://amazon.com/dp/B0CHYGP6YB | L73: =HYPERLINK(K73) -> https://amazon.com/dp/B0CHYGP6YB
A74: FOXWELL NT710 Fit for GM Diagnostic Scan Tool, Bi-Directional All System OBD2 Scanner for Chevrolet Buick GMC Cadillac, All Resets Code Reader Oil EPB SAS TPMS ABS Bleeding Throttle Crankshaft Relearn | B74: B0CDGH4WFH | C74: Tablet | D74: 330.73957 | E74: 172537.12 | F74: 15214.02 | G74: 484 | H74: 46 | I74: 67 | J74: 4.1 | K74: https://amazon.com/dp/B0CDGH4WFH | L74: =HYPERLINK(K74) -> https://amazon.com/dp/B0CDGH4WFH
